{"Stats": {"Full Time Result": "A", "Away Team Corners": 0, "Referee": "M Dean", "Home Team Fouls Committed": 5, "Home Team Corners": 5, "Away Team Shots": 7, "Away Team Red Cards": 0, "Home Team Red Cards": 0, "Half Time Away Team Goals": 2, "Full Time Home Team Goals": 0, "Away Team Yellow Cards": 2, "Away Team Shots on Target": 4, "Half Time Home Team Goals": 0, "Half Time Result": "A", "Home Team Yellow Cards": 2, "Home Team Shots": 13, "Div": "E0", "Away Team Fouls Committed": 14, "Home Team Shots on Target": 2, "Full Time Away Team Goals": 4}, "Description": "Goal!  Stoke City 0, Chelsea 1. Álvaro Morata (Chelsea) right footed shot from the left side of the box to the bottom right corner. Assisted by César Azpilicueta with a through ball. at minute 2. Bruno Martins Indi (Stoke City) wins a free kick in the defensive half. at minute 3. Foul by Álvaro Morata (Chelsea). at minute 3. Corner,  Stoke City. Conceded by Marcos Alonso. at minute 11. Foul by Mame Biram Diouf (Stoke City). at minute 13. Marcos Alonso (Chelsea) wins a free kick on the left wing. at minute 13. Erik Pieters (Stoke City) wins a free kick in the defensive half. at minute 14. Foul by Álvaro Morata (Chelsea). at minute 14. Attempt blocked. Xherdan Shaqiri (Stoke City) left footed shot from outside the box is blocked. Assisted by Joe Allen. at minute 17. Bruno Martins Indi (Stoke City) wins a free kick in the defensive half. at minute 23. Foul by Willian (Chelsea). at minute 23. Foul by Joe Allen (Stoke City). at minute 25. Tiemoué Bakayoko (Chelsea) wins a free kick in the defensive half. at minute 25. Foul by Álvaro Morata (Chelsea). at minute 26. Ramadan Sobhi (Stoke City) wins a free kick in the defensive half. at minute 26. Foul by Joe Allen (Stoke City). at minute 27. Álvaro Morata (Chelsea) wins a free kick in the defensive half. at minute 27. Goal!  Stoke City 0, Chelsea 2. Pedro (Chelsea) right footed shot from outside the box to the bottom left corner. at minute 30. Foul by Tiemoué Bakayoko (Chelsea). at minute 33. Joe Allen (Stoke City) wins a free kick in the attacking half. at minute 33. Attempt blocked. Xherdan Shaqiri (Stoke City) left footed shot from outside the box is blocked. at minute 34. Corner,  Stoke City. Conceded by Álvaro Morata. at minute 34. Corner,  Stoke City. Conceded by Andreas Christensen. at minute 38. Foul by Victor Moses (Chelsea). at minute 39. Ramadan Sobhi (Stoke City) wins a free kick on the left wing. at minute 39. Corner,  Stoke City. Conceded by Antonio Rüdiger. at minute 42. Attempt blocked. Darren Fletcher (Stoke City) left footed shot from outside the box is blocked. at minute 43. Attempt missed. Mame Biram Diouf (Stoke City) right footed shot from the centre of the box misses to the left. Assisted by Joe Allen with a cross. at minute 43. Attempt missed. Joe Allen (Stoke City) right footed shot from outside the box is high and wide to the right. at minute 45. First Half ends, Stoke City 0, Chelsea 2. at minute 47. Second Half begins Stoke City 0, Chelsea 2. at minute 45. Andreas Christensen (Chelsea) wins a free kick in the defensive half. at minute 48. Foul by Xherdan Shaqiri (Stoke City). at minute 48. Xherdan Shaqiri (Stoke City) is shown the yellow card. at minute 49. Foul by Marcos Alonso (Chelsea). at minute 51. Joe Allen (Stoke City) wins a free kick in the defensive half. at minute 51. Marcos Alonso (Chelsea) is shown the yellow card for a bad foul. at minute 51. Foul by Marcos Alonso (Chelsea). at minute 52. Mame Biram Diouf (Stoke City) wins a free kick on the right wing. at minute 52. Attempt missed. Joe Allen (Stoke City) right footed shot from the centre of the box is too high following a set piece situation. at minute 54. Attempt blocked. Joe Allen (Stoke City) right footed shot from outside the box is blocked. at minute 57. Foul by N'Golo Kanté (Chelsea). at minute 57. Ramadan Sobhi (Stoke City) wins a free kick in the defensive half. at minute 57. N'Golo Kanté (Chelsea) is shown the yellow card for a bad foul. at minute 57. Substitution, Chelsea. Gary Cahill replaces Marcos Alonso. at minute 59. Hand ball by N'Golo Kanté (Chelsea). at minute 59. Attempt saved. Xherdan Shaqiri (Stoke City) left footed shot from outside the box is saved in the centre of the goal. Assisted by Bruno Martins Indi. at minute 60. Substitution, Stoke City. Peter Crouch replaces Jesé. at minute 61. Attempt missed. Mame Biram Diouf (Stoke City) right footed shot from the right side of the six yard box is close, but misses the top right corner. Assisted by Peter Crouch with a headed pass. at minute 64. Attempt missed. Eric Maxim Choupo-Moting (Stoke City) left footed shot from the left side of the box misses to the right. at minute 65. Corner,  Stoke City. Conceded by Tiemoué Bakayoko. at minute 65. Delay in match Thibaut Courtois (Chelsea) because of an injury. at minute 66. Delay over. They are ready to continue. at minute 68. Substitution, Chelsea. Cesc Fàbregas replaces Pedro. at minute 68. Offside, Chelsea. Thibaut Courtois tries a through ball, but Álvaro Morata is caught offside. at minute 68. Foul by Cesc Fàbregas (Chelsea). at minute 71. Glen Johnson (Stoke City) wins a free kick on the right wing. at minute 71. Attempt missed. Mame Biram Diouf (Stoke City) right footed shot from the right side of the six yard box is close, but misses to the right. Assisted by Darren Fletcher following a set piece situation. at minute 72. Substitution, Chelsea. Eden Hazard replaces Willian. at minute 72. Eric Maxim Choupo-Moting (Stoke City) wins a free kick in the attacking half. at minute 73. Foul by Antonio Rüdiger (Chelsea). at minute 73. Attempt saved. Eric Maxim Choupo-Moting (Stoke City) header from the centre of the box is saved in the top right corner. Assisted by Xherdan Shaqiri with a cross. at minute 74. Foul by Tiemoué Bakayoko (Chelsea). at minute 74. Glen Johnson (Stoke City) wins a free kick on the right wing. at minute 74. Substitution, Stoke City. Ibrahim Afellay replaces Bruno Martins Indi. at minute 76. Goal!  Stoke City 0, Chelsea 3. Álvaro Morata (Chelsea) right footed shot from the left side of the six yard box to the centre of the goal. Assisted by Tiemoué Bakayoko. at minute 77. Attempt missed. Eden Hazard (Chelsea) right footed shot from a difficult angle on the right misses to the left. Assisted by Victor Moses. at minute 79. Foul by Victor Moses (Chelsea). at minute 80. Peter Crouch (Stoke City) wins a free kick on the left wing. at minute 80. Attempt missed. Eric Maxim Choupo-Moting (Stoke City) right footed shot from the left side of the box misses to the right. Assisted by Ramadan Sobhi. at minute 81. Goal!  Stoke City 0, Chelsea 4. Álvaro Morata (Chelsea) right footed shot from very close range to the bottom right corner. Assisted by César Azpilicueta. at minute 82. Attempt missed. Álvaro Morata (Chelsea) right footed shot from the centre of the box is close, but misses to the right. Assisted by Cesc Fàbregas. at minute 87. Attempt missed. Victor Moses (Chelsea) right footed shot from the right side of the box misses to the left. Assisted by N'Golo Kanté. at minute 88. Cesc Fàbregas (Chelsea) wins a free kick in the attacking half. at minute 89. Foul by Peter Crouch (Stoke City). at minute 89. Peter Crouch (Stoke City) is shown the yellow card for a bad foul. at minute 89. Second Half ends, Stoke City 0, Chelsea 4. at minute 94. Match ends, Stoke City 0, Chelsea 4. at minute 94. ", "Home Team": "Stoke City", "Away Team": "Chelsea", "Date": "23-09-2017", "Commentary": [["480847", "First Half begins.", "-", "Stoke City", "0", "0", "0", "1", "0", "0", "NA", "NA", "NA", "NA", "NA", "NA", "NA", "0", "NA", "NA", "0", "NA", "0", "0", "NA", "NA", "NA", "0", "NA", "NA", "NA", "0", "NA", "NA", "0", "NA", "0", "NA", "NA", "NA", "0", "NA", "NA", "0", "0", "NA", "NA", "NA", "0", "NA", "NA", "NA", "NA", "1", "1", "0", "NA", "NA", "NA"], ["480847", "Lineups are announced and players are warming up.", "-", "Stoke City", "0", "0", "0", "0", "0", "0", "NA", "NA", "NA", "NA", "NA", "NA", "NA", "0", "NA", "NA", "0", "NA", "0", "0", "NA", "NA", "NA", "0", "NA", "NA", "NA", "0", "NA", "NA", "0", "NA", "0", "NA", "NA", "NA", "0", "NA", "NA", "0", "0", "NA", "NA", "NA", "0", "NA", "NA", "NA", "NA", "1", "2", "0", "NA", "NA", "NA"], ["480847", "Goal!  Stoke City 0, Chelsea 1. Álvaro Morata (Chelsea) right footed shot from the left side of the box to the bottom right corner. Assisted by César Azpilicueta with a through ball.", "2'", "Stoke City", "0", "0", "0", "0", "1", "0", "goal", "Álvaro Morata", "Chelsea", "right", "the left side of the box", "bottom right corner", "César Azpilicueta", "0", "NA", "NA", "0", "through", "0", "0", "NA", "NA", "NA", "0", "NA", "NA", "NA", "0", "NA", "NA", "0", "NA", "0", "NA", "NA", "NA", "0", "NA", "NA", "0", "0", "NA", "NA", "NA", "0", "NA", "NA", "NA", "NA", "1", "3", "0", "NA", "NA", "2"], ["480847", "Bruno Martins Indi (Stoke City) wins a free kick in the defensive half.", "3'", "Stoke City", "0", "0", "0", "0", "0", "0", "NA", "NA", "NA", "NA", "NA", "NA", "NA", "0", "NA", "NA", "0", "NA", "0", "0", "NA", "NA", "NA", "0", "NA", "NA", "NA", "0", "NA", "NA", "0", "NA", "1", "Bruno Martins Indi", "Stoke City", "defensive half", "0", "NA", "NA", "0", "0", "NA", "NA", "NA", "0", "NA", "NA", "NA", "NA", "1", "4", "0", "NA", "NA", "3"], ["480847", "Foul by Álvaro Morata (Chelsea).", "3'", "Stoke City", "0", "0", "0", "0", "0", "0", "NA", "NA", "NA", "NA", "NA", "NA", "NA", "1", "Álvaro Morata", "Chelsea", "0", "NA", "0", "0", "NA", "NA", "NA", "0", "NA", "NA", "NA", "0", "NA", "NA", "0", "NA", "0", "NA", "NA", "NA", "0", "NA", "NA", "0", "0", "NA", "NA", "NA", "0", "NA", "NA", "NA", "NA", "1", "5", "0", "NA", "NA", "3"], ["480847", "Corner,  Stoke City. Conceded by Marcos Alonso.", "11'", "Stoke City", "0", "0", "0", "0", "0", "0", "NA", "NA", "NA", "NA", "NA", "NA", "NA", "0", "NA", "NA", "0", "NA", "0", "0", "NA", "NA", "NA", "0", "NA", "NA", "NA", "0", "NA", "NA", "0", "NA", "0", "NA", "NA", "NA", "1", "Stoke City", "Marcos Alonso", "0", "0", "NA", "NA", "NA", "0", "NA", "NA", "NA", "NA", "1", "6", "0", "NA", "NA", "11"], ["480847", "Foul by Mame Biram Diouf (Stoke City).", "13'", "Stoke City", "0", "0", "0", "0", "0", "0", "NA", "NA", "NA", "NA", "NA", "NA", "NA", "1", "Mame Biram Diouf", "Stoke City", "0", "NA", "0", "0", "NA", "NA", "NA", "0", "NA", "NA", "NA", "0", "NA", "NA", "0", "NA", "0", "NA", "NA", "NA", "0", "NA", "NA", "0", "0", "NA", "NA", "NA", "0", "NA", "NA", "NA", "NA", "1", "7", "0", "NA", "NA", "13"], ["480847", "Marcos Alonso (Chelsea) wins a free kick on the left wing.", "13'", "Stoke City", "0", "0", "0", "0", "0", "0", "NA", "NA", "NA", "NA", "NA", "NA", "NA", "0", "NA", "NA", "0", "NA", "0", "0", "NA", "NA", "NA", "0", "NA", "NA", "NA", "0", "NA", "NA", "0", "NA", "1", "Marcos Alonso", "Chelsea", "NA", "0", "NA", "NA", "0", "0", "NA", "NA", "NA", "0", "NA", "NA", "NA", "NA", "1", "8", "0", "NA", "NA", "13"], ["480847", "Erik Pieters (Stoke City) wins a free kick in the defensive half.", "14'", "Stoke City", "0", "0", "0", "0", "0", "0", "NA", "NA", "NA", "NA", "NA", "NA", "NA", "0", "NA", "NA", "0", "NA", "0", "0", "NA", "NA", "NA", "0", "NA", "NA", "NA", "0", "NA", "NA", "0", "NA", "1", "Erik Pieters", "Stoke City", "defensive half", "0", "NA", "NA", "0", "0", "NA", "NA", "NA", "0", "NA", "NA", "NA", "NA", "1", "9", "0", "NA", "NA", "14"], ["480847", "Foul by Álvaro Morata (Chelsea).", "14'", "Stoke City", "0", "0", "0", "0", "0", "0", "NA", "NA", "NA", "NA", "NA", "NA", "NA", "1", "Álvaro Morata", "Chelsea", "0", "NA", "0", "0", "NA", "NA", "NA", "0", "NA", "NA", "NA", "0", "NA", "NA", "0", "NA", "0", "NA", "NA", "NA", "0", "NA", "NA", "0", "0", "NA", "NA", "NA", "0", "NA", "NA", "NA", "NA", "1", "10", "0", "NA", "NA", "14"], ["480847", "Attempt blocked. Xherdan Shaqiri (Stoke City) left footed shot from outside the box is blocked. Assisted by Joe Allen.", "17'", "Stoke City", "0", "0", "0", "0", "1", "0", "blocked", "Xherdan Shaqiri", "Stoke City", "left", "outside the box", "NA", "Joe Allen", "0", "NA", "NA", "0", "NA", "0", "0", "NA", "NA", "NA", "0", "NA", "NA", "NA", "0", "NA", "NA", "0", "NA", "0", "NA", "NA", "NA", "0", "NA", "NA", "0", "0", "NA", "NA", "NA", "0", "NA", "NA", "NA", "NA", "1", "11", "0", "NA", "NA", "17"], ["480847", "Bruno Martins Indi (Stoke City) wins a free kick in the defensive half.", "23'", "Stoke City", "0", "0", "0", "0", "0", "0", "NA", "NA", "NA", "NA", "NA", "NA", "NA", "0", "NA", "NA", "0", "NA", "0", "0", "NA", "NA", "NA", "0", "NA", "NA", "NA", "0", "NA", "NA", "0", "NA", "1", "Bruno Martins Indi", "Stoke City", "defensive half", "0", "NA", "NA", "0", "0", "NA", "NA", "NA", "0", "NA", "NA", "NA", "NA", "1", "12", "0", "NA", "NA", "23"], ["480847", "Foul by Willian (Chelsea).", "23'", "Stoke City", "0", "0", "0", "0", "0", "0", "NA", "NA", "NA", "NA", "NA", "NA", "NA", "1", "Willian", "Chelsea", "0", "NA", "0", "0", "NA", "NA", "NA", "0", "NA", "NA", "NA", "0", "NA", "NA", "0", "NA", "0", "NA", "NA", "NA", "0", "NA", "NA", "0", "0", "NA", "NA", "NA", "0", "NA", "NA", "NA", "NA", "1", "13", "0", "NA", "NA", "23"], ["480847", "Foul by Joe Allen (Stoke City).", "25'", "Stoke City", "0", "0", "0", "0", "0", "0", "NA", "NA", "NA", "NA", "NA", "NA", "NA", "1", "Joe Allen", "Stoke City", "0", "NA", "0", "0", "NA", "NA", "NA", "0", "NA", "NA", "NA", "0", "NA", "NA", "0", "NA", "0", "NA", "NA", "NA", "0", "NA", "NA", "0", "0", "NA", "NA", "NA", "0", "NA", "NA", "NA", "NA", "1", "14", "0", "NA", "NA", "25"], ["480847", "Tiemoué Bakayoko (Chelsea) wins a free kick in the defensive half.", "25'", "Stoke City", "0", "0", "0", "0", "0", "0", "NA", "NA", "NA", "NA", "NA", "NA", "NA", "0", "NA", "NA", "0", "NA", "0", "0", "NA", "NA", "NA", "0", "NA", "NA", "NA", "0", "NA", "NA", "0", "NA", "1", "Tiemoué Bakayoko", "Chelsea", "defensive half", "0", "NA", "NA", "0", "0", "NA", "NA", "NA", "0", "NA", "NA", "NA", "NA", "1", "15", "0", "NA", "NA", "25"], ["480847", "Foul by Álvaro Morata (Chelsea).", "26'", "Stoke City", "0", "0", "0", "0", "0", "0", "NA", "NA", "NA", "NA", "NA", "NA", "NA", "1", "Álvaro Morata", "Chelsea", "0", "NA", "0", "0", "NA", "NA", "NA", "0", "NA", "NA", "NA", "0", "NA", "NA", "0", "NA", "0", "NA", "NA", "NA", "0", "NA", "NA", "0", "0", "NA", "NA", "NA", "0", "NA", "NA", "NA", "NA", "1", "16", "0", "NA", "NA", "26"], ["480847", "Ramadan Sobhi (Stoke City) wins a free kick in the defensive half.", "26'", "Stoke City", "0", "0", "0", "0", "0", "0", "NA", "NA", "NA", "NA", "NA", "NA", "NA", "0", "NA", "NA", "0", "NA", "0", "0", "NA", "NA", "NA", "0", "NA", "NA", "NA", "0", "NA", "NA", "0", "NA", "1", "Ramadan Sobhi", "Stoke City", "defensive half", "0", "NA", "NA", "0", "0", "NA", "NA", "NA", "0", "NA", "NA", "NA", "NA", "1", "17", "0", "NA", "NA", "26"], ["480847", "Foul by Joe Allen (Stoke City).", "27'", "Stoke City", "0", "0", "0", "0", "0", "0", "NA", "NA", "NA", "NA", "NA", "NA", "NA", "1", "Joe Allen", "Stoke City", "0", "NA", "0", "0", "NA", "NA", "NA", "0", "NA", "NA", "NA", "0", "NA", "NA", "0", "NA", "0", "NA", "NA", "NA", "0", "NA", "NA", "0", "0", "NA", "NA", "NA", "0", "NA", "NA", "NA", "NA", "1", "18", "0", "NA", "NA", "27"], ["480847", "Álvaro Morata (Chelsea) wins a free kick in the defensive half.", "27'", "Stoke City", "0", "0", "0", "0", "0", "0", "NA", "NA", "NA", "NA", "NA", "NA", "NA", "0", "NA", "NA", "0", "NA", "0", "0", "NA", "NA", "NA", "0", "NA", "NA", "NA", "0", "NA", "NA", "0", "NA", "1", "Álvaro Morata", "Chelsea", "defensive half", "0", "NA", "NA", "0", "0", "NA", "NA", "NA", "0", "NA", "NA", "NA", "NA", "1", "19", "0", "NA", "NA", "27"], ["480847", "Goal!  Stoke City 0, Chelsea 2. Pedro (Chelsea) right footed shot from outside the box to the bottom left corner.", "30'", "Stoke City", "0", "0", "0", "0", "1", "0", "goal", "Pedro", "Chelsea", "right", "outside the box", "bottom left corner", "NA", "0", "NA", "NA", "0", "NA", "0", "0", "NA", "NA", "NA", "0", "NA", "NA", "NA", "0", "NA", "NA", "0", "NA", "0", "NA", "NA", "NA", "0", "NA", "NA", "0", "0", "NA", "NA", "NA", "0", "NA", "NA", "NA", "NA", "1", "20", "0", "NA", "NA", "30"], ["480847", "Foul by Tiemoué Bakayoko (Chelsea).", "33'", "Stoke City", "0", "0", "0", "0", "0", "0", "NA", "NA", "NA", "NA", "NA", "NA", "NA", "1", "Tiemoué Bakayoko", "Chelsea", "0", "NA", "0", "0", "NA", "NA", "NA", "0", "NA", "NA", "NA", "0", "NA", "NA", "0", "NA", "0", "NA", "NA", "NA", "0", "NA", "NA", "0", "0", "NA", "NA", "NA", "0", "NA", "NA", "NA", "NA", "1", "21", "0", "NA", "NA", "33"], ["480847", "Joe Allen (Stoke City) wins a free kick in the attacking half.", "33'", "Stoke City", "0", "0", "0", "0", "0", "0", "NA", "NA", "NA", "NA", "NA", "NA", "NA", "0", "NA", "NA", "0", "NA", "0", "0", "NA", "NA", "NA", "0", "NA", "NA", "NA", "0", "NA", "NA", "0", "NA", "1", "Joe Allen", "Stoke City", "attacking half", "0", "NA", "NA", "0", "0", "NA", "NA", "NA", "0", "NA", "NA", "NA", "NA", "1", "22", "0", "NA", "NA", "33"], ["480847", "Attempt blocked. Xherdan Shaqiri (Stoke City) left footed shot from outside the box is blocked.", "34'", "Stoke City", "0", "0", "0", "0", "1", "0", "blocked", "Xherdan Shaqiri", "Stoke City", "left", "outside the box", "NA", "NA", "0", "NA", "NA", "0", "NA", "0", "0", "NA", "NA", "NA", "0", "NA", "NA", "NA", "0", "NA", "NA", "0", "NA", "0", "NA", "NA", "NA", "0", "NA", "NA", "0", "0", "NA", "NA", "NA", "0", "NA", "NA", "NA", "NA", "1", "23", "0", "NA", "NA", "34"], ["480847", "Corner,  Stoke City. Conceded by Álvaro Morata.", "34'", "Stoke City", "0", "0", "0", "0", "0", "0", "NA", "NA", "NA", "NA", "NA", "NA", "NA", "0", "NA", "NA", "0", "NA", "0", "0", "NA", "NA", "NA", "0", "NA", "NA", "NA", "0", "NA", "NA", "0", "NA", "0", "NA", "NA", "NA", "1", "Stoke City", "Álvaro Morata", "0", "0", "NA", "NA", "NA", "0", "NA", "NA", "NA", "NA", "1", "24", "0", "NA", "NA", "34"], ["480847", "Corner,  Stoke City. Conceded by Andreas Christensen.", "38'", "Stoke City", "0", "0", "0", "0", "0", "0", "NA", "NA", "NA", "NA", "NA", "NA", "NA", "0", "NA", "NA", "0", "NA", "0", "0", "NA", "NA", "NA", "0", "NA", "NA", "NA", "0", "NA", "NA", "0", "NA", "0", "NA", "NA", "NA", "1", "Stoke City", "Andreas Christensen", "0", "0", "NA", "NA", "NA", "0", "NA", "NA", "NA", "NA", "1", "25", "0", "NA", "NA", "38"], ["480847", "Foul by Victor Moses (Chelsea).", "39'", "Stoke City", "0", "0", "0", "0", "0", "0", "NA", "NA", "NA", "NA", "NA", "NA", "NA", "1", "Victor Moses", "Chelsea", "0", "NA", "0", "0", "NA", "NA", "NA", "0", "NA", "NA", "NA", "0", "NA", "NA", "0", "NA", "0", "NA", "NA", "NA", "0", "NA", "NA", "0", "0", "NA", "NA", "NA", "0", "NA", "NA", "NA", "NA", "1", "26", "0", "NA", "NA", "39"], ["480847", "Ramadan Sobhi (Stoke City) wins a free kick on the left wing.", "39'", "Stoke City", "0", "0", "0", "0", "0", "0", "NA", "NA", "NA", "NA", "NA", "NA", "NA", "0", "NA", "NA", "0", "NA", "0", "0", "NA", "NA", "NA", "0", "NA", "NA", "NA", "0", "NA", "NA", "0", "NA", "1", "Ramadan Sobhi", "Stoke City", "NA", "0", "NA", "NA", "0", "0", "NA", "NA", "NA", "0", "NA", "NA", "NA", "NA", "1", "27", "0", "NA", "NA", "39"], ["480847", "Corner,  Stoke City. Conceded by Antonio Rüdiger.", "42'", "Stoke City", "0", "0", "0", "0", "0", "0", "NA", "NA", "NA", "NA", "NA", "NA", "NA", "0", "NA", "NA", "0", "NA", "0", "0", "NA", "NA", "NA", "0", "NA", "NA", "NA", "0", "NA", "NA", "0", "NA", "0", "NA", "NA", "NA", "1", "Stoke City", "Antonio Rüdiger", "0", "0", "NA", "NA", "NA", "0", "NA", "NA", "NA", "NA", "1", "28", "0", "NA", "NA", "42"], ["480847", "Attempt blocked. Darren Fletcher (Stoke City) left footed shot from outside the box is blocked.", "43'", "Stoke City", "0", "0", "0", "0", "1", "0", "blocked", "Darren Fletcher", "Stoke City", "left", "outside the box", "NA", "NA", "0", "NA", "NA", "0", "NA", "0", "0", "NA", "NA", "NA", "0", "NA", "NA", "NA", "0", "NA", "NA", "0", "NA", "0", "NA", "NA", "NA", "0", "NA", "NA", "0", "0", "NA", "NA", "NA", "0", "NA", "NA", "NA", "NA", "1", "29", "0", "NA", "NA", "43"], ["480847", "Attempt missed. Mame Biram Diouf (Stoke City) right footed shot from the centre of the box misses to the left. Assisted by Joe Allen with a cross.", "43'", "Stoke City", "0", "0", "0", "0", "1", "0", "missed", "Mame Biram Diouf", "Stoke City", "right", "the centre of the box", "left", "Joe Allen", "0", "NA", "NA", "0", "cross", "0", "0", "NA", "NA", "NA", "0", "NA", "NA", "NA", "0", "NA", "NA", "0", "NA", "0", "NA", "NA", "NA", "0", "NA", "NA", "0", "0", "NA", "NA", "NA", "0", "NA", "NA", "NA", "NA", "1", "30", "0", "NA", "NA", "43"], ["480847", "Attempt missed. Joe Allen (Stoke City) right footed shot from outside the box is high and wide to the right.", "45'", "Stoke City", "0", "0", "0", "0", "1", "0", "missed", "Joe Allen", "Stoke City", "right", "outside the box", "high and wide to the right", "NA", "0", "NA", "NA", "0", "NA", "0", "0", "NA", "NA", "NA", "0", "NA", "NA", "NA", "0", "NA", "NA", "0", "NA", "0", "NA", "NA", "NA", "0", "NA", "NA", "0", "0", "NA", "NA", "NA", "0", "NA", "NA", "NA", "NA", "1", "31", "0", "NA", "NA", "45"], ["480847", "First Half ends, Stoke City 0, Chelsea 2.", "45'+2'", "Stoke City", "0", "1", "0", "0", "0", "0", "NA", "NA", "NA", "NA", "NA", "NA", "NA", "0", "NA", "NA", "0", "NA", "0", "0", "NA", "NA", "NA", "0", "NA", "NA", "NA", "0", "NA", "NA", "0", "NA", "0", "NA", "NA", "NA", "0", "NA", "NA", "0", "0", "NA", "NA", "NA", "0", "NA", "NA", "NA", "NA", "1", "32", "1", "NA", "NA", "47"], ["480847", "Second Half begins Stoke City 0, Chelsea 2.", "45'", "Stoke City", "0", "0", "0", "1", "0", "0", "NA", "NA", "NA", "NA", "NA", "NA", "NA", "0", "NA", "NA", "0", "NA", "0", "0", "NA", "NA", "NA", "0", "NA", "NA", "NA", "0", "NA", "NA", "0", "NA", "0", "NA", "NA", "NA", "0", "NA", "NA", "0", "0", "NA", "NA", "NA", "0", "NA", "NA", "NA", "NA", "2", "33", "0", "NA", "NA", "45"], ["480847", "Andreas Christensen (Chelsea) wins a free kick in the defensive half.", "48'", "Stoke City", "0", "0", "0", "0", "0", "0", "NA", "NA", "NA", "NA", "NA", "NA", "NA", "0", "NA", "NA", "0", "NA", "0", "0", "NA", "NA", "NA", "0", "NA", "NA", "NA", "0", "NA", "NA", "0", "NA", "1", "Andreas Christensen", "Chelsea", "defensive half", "0", "NA", "NA", "0", "0", "NA", "NA", "NA", "0", "NA", "NA", "NA", "NA", "2", "34", "0", "NA", "NA", "48"], ["480847", "Foul by Xherdan Shaqiri (Stoke City).", "48'", "Stoke City", "0", "0", "0", "0", "0", "0", "NA", "NA", "NA", "NA", "NA", "NA", "NA", "1", "Xherdan Shaqiri", "Stoke City", "0", "NA", "0", "0", "NA", "NA", "NA", "0", "NA", "NA", "NA", "0", "NA", "NA", "0", "NA", "0", "NA", "NA", "NA", "0", "NA", "NA", "0", "0", "NA", "NA", "NA", "0", "NA", "NA", "NA", "NA", "2", "35", "0", "NA", "NA", "48"], ["480847", "Xherdan Shaqiri (Stoke City) is shown the yellow card.", "49'", "Stoke City", "0", "0", "0", "0", "0", "0", "NA", "NA", "NA", "NA", "NA", "NA", "NA", "0", "NA", "NA", "0", "NA", "0", "0", "NA", "NA", "NA", "1", "yellow", "Xherdan Shaqiri", "Stoke City", "0", "NA", "NA", "0", "NA", "0", "NA", "NA", "NA", "0", "NA", "NA", "0", "0", "NA", "NA", "NA", "0", "NA", "NA", "NA", "NA", "2", "36", "0", "NA", "NA", "49"], ["480847", "Foul by Marcos Alonso (Chelsea).", "51'", "Stoke City", "0", "0", "0", "0", "0", "0", "NA", "NA", "NA", "NA", "NA", "NA", "NA", "1", "Marcos Alonso", "Chelsea", "0", "NA", "0", "0", "NA", "NA", "NA", "0", "NA", "NA", "NA", "0", "NA", "NA", "0", "NA", "0", "NA", "NA", "NA", "0", "NA", "NA", "0", "0", "NA", "NA", "NA", "0", "NA", "NA", "NA", "NA", "2", "37", "0", "NA", "NA", "51"], ["480847", "Joe Allen (Stoke City) wins a free kick in the defensive half.", "51'", "Stoke City", "0", "0", "0", "0", "0", "0", "NA", "NA", "NA", "NA", "NA", "NA", "NA", "0", "NA", "NA", "0", "NA", "0", "0", "NA", "NA", "NA", "0", "NA", "NA", "NA", "0", "NA", "NA", "0", "NA", "1", "Joe Allen", "Stoke City", "defensive half", "0", "NA", "NA", "0", "0", "NA", "NA", "NA", "0", "NA", "NA", "NA", "NA", "2", "38", "0", "NA", "NA", "51"], ["480847", "Marcos Alonso (Chelsea) is shown the yellow card for a bad foul.", "51'", "Stoke City", "0", "0", "0", "0", "0", "0", "NA", "NA", "NA", "NA", "NA", "NA", "NA", "0", "NA", "NA", "0", "NA", "0", "0", "NA", "NA", "NA", "1", "yellow", "Marcos Alonso", "Chelsea", "0", "NA", "NA", "0", "NA", "0", "NA", "NA", "NA", "0", "NA", "NA", "0", "0", "NA", "NA", "NA", "0", "NA", "NA", "NA", "NA", "2", "39", "0", "NA", "NA", "51"], ["480847", "Foul by Marcos Alonso (Chelsea).", "52'", "Stoke City", "0", "0", "0", "0", "0", "0", "NA", "NA", "NA", "NA", "NA", "NA", "NA", "1", "Marcos Alonso", "Chelsea", "0", "NA", "0", "0", "NA", "NA", "NA", "0", "NA", "NA", "NA", "0", "NA", "NA", "0", "NA", "0", "NA", "NA", "NA", "0", "NA", "NA", "0", "0", "NA", "NA", "NA", "0", "NA", "NA", "NA", "NA", "2", "40", "0", "NA", "NA", "52"], ["480847", "Mame Biram Diouf (Stoke City) wins a free kick on the right wing.", "52'", "Stoke City", "0", "0", "0", "0", "0", "0", "NA", "NA", "NA", "NA", "NA", "NA", "NA", "0", "NA", "NA", "0", "NA", "0", "0", "NA", "NA", "NA", "0", "NA", "NA", "NA", "0", "NA", "NA", "0", "NA", "1", "Mame Biram Diouf", "Stoke City", "NA", "0", "NA", "NA", "0", "0", "NA", "NA", "NA", "0", "NA", "NA", "NA", "NA", "2", "41", "0", "NA", "NA", "52"], ["480847", "Attempt missed. Joe Allen (Stoke City) right footed shot from the centre of the box is too high following a set piece situation.", "54'", "Stoke City", "0", "0", "0", "0", "1", "0", "missed", "Joe Allen", "Stoke City", "right", "the centre of the box", "too high", "NA", "0", "NA", "NA", "1", "NA", "0", "0", "NA", "NA", "NA", "0", "NA", "NA", "NA", "0", "NA", "NA", "0", "NA", "0", "NA", "NA", "NA", "0", "NA", "NA", "0", "0", "NA", "NA", "NA", "0", "NA", "NA", "NA", "NA", "2", "42", "0", "NA", "NA", "54"], ["480847", "Attempt blocked. Joe Allen (Stoke City) right footed shot from outside the box is blocked.", "57'", "Stoke City", "0", "0", "0", "0", "1", "0", "blocked", "Joe Allen", "Stoke City", "right", "outside the box", "NA", "NA", "0", "NA", "NA", "0", "NA", "0", "0", "NA", "NA", "NA", "0", "NA", "NA", "NA", "0", "NA", "NA", "0", "NA", "0", "NA", "NA", "NA", "0", "NA", "NA", "0", "0", "NA", "NA", "NA", "0", "NA", "NA", "NA", "NA", "2", "43", "0", "NA", "NA", "57"], ["480847", "Foul by N'Golo Kanté (Chelsea).", "57'", "Stoke City", "0", "0", "0", "0", "0", "0", "NA", "NA", "NA", "NA", "NA", "NA", "NA", "1", "N'Golo Kanté", "Chelsea", "0", "NA", "0", "0", "NA", "NA", "NA", "0", "NA", "NA", "NA", "0", "NA", "NA", "0", "NA", "0", "NA", "NA", "NA", "0", "NA", "NA", "0", "0", "NA", "NA", "NA", "0", "NA", "NA", "NA", "NA", "2", "44", "0", "NA", "NA", "57"], ["480847", "Ramadan Sobhi (Stoke City) wins a free kick in the defensive half.", "57'", "Stoke City", "0", "0", "0", "0", "0", "0", "NA", "NA", "NA", "NA", "NA", "NA", "NA", "0", "NA", "NA", "0", "NA", "0", "0", "NA", "NA", "NA", "0", "NA", "NA", "NA", "0", "NA", "NA", "0", "NA", "1", "Ramadan Sobhi", "Stoke City", "defensive half", "0", "NA", "NA", "0", "0", "NA", "NA", "NA", "0", "NA", "NA", "NA", "NA", "2", "45", "0", "NA", "NA", "57"], ["480847", "N'Golo Kanté (Chelsea) is shown the yellow card for a bad foul.", "57'", "Stoke City", "0", "0", "0", "0", "0", "0", "NA", "NA", "NA", "NA", "NA", "NA", "NA", "0", "NA", "NA", "0", "NA", "0", "0", "NA", "NA", "NA", "1", "yellow", "N'Golo Kanté", "Chelsea", "0", "NA", "NA", "0", "NA", "0", "NA", "NA", "NA", "0", "NA", "NA", "0", "0", "NA", "NA", "NA", "0", "NA", "NA", "NA", "NA", "2", "46", "0", "NA", "NA", "57"], ["480847", "Substitution, Chelsea. Gary Cahill replaces Marcos Alonso.", "59'", "Stoke City", "0", "0", "0", "0", "0", "0", "NA", "NA", "NA", "NA", "NA", "NA", "NA", "0", "NA", "NA", "0", "NA", "0", "0", "NA", "NA", "NA", "0", "NA", "NA", "NA", "0", "NA", "NA", "0", "NA", "0", "NA", "NA", "NA", "0", "NA", "NA", "1", "0", "Chelsea", "Gary Cahill", "Marcos Alonso", "0", "NA", "NA", "NA", "NA", "2", "47", "0", "NA", "NA", "59"], ["480847", "Hand ball by N'Golo Kanté (Chelsea).", "59'", "Stoke City", "0", "0", "0", "0", "0", "0", "NA", "NA", "NA", "NA", "NA", "NA", "NA", "0", "NA", "NA", "0", "NA", "0", "0", "NA", "NA", "NA", "0", "NA", "NA", "NA", "0", "NA", "NA", "0", "NA", "0", "NA", "NA", "NA", "0", "NA", "NA", "0", "0", "NA", "NA", "NA", "0", "NA", "NA", "NA", "NA", "2", "48", "0", "NA", "NA", "59"], ["480847", "Attempt saved. Xherdan Shaqiri (Stoke City) left footed shot from outside the box is saved in the centre of the goal. Assisted by Bruno Martins Indi.", "60'", "Stoke City", "0", "0", "0", "0", "1", "0", "saved", "Xherdan Shaqiri", "Stoke City", "left", "outside the box", "the centre of the goal", "Bruno Martins Indi", "0", "NA", "NA", "0", "NA", "0", "0", "NA", "NA", "NA", "0", "NA", "NA", "NA", "0", "NA", "NA", "0", "NA", "0", "NA", "NA", "NA", "0", "NA", "NA", "0", "0", "NA", "NA", "NA", "0", "NA", "NA", "NA", "NA", "2", "49", "0", "NA", "NA", "60"], ["480847", "Substitution, Stoke City. Peter Crouch replaces Jesé.", "61'", "Stoke City", "0", "0", "0", "0", "0", "0", "NA", "NA", "NA", "NA", "NA", "NA", "NA", "0", "NA", "NA", "0", "NA", "0", "0", "NA", "NA", "NA", "0", "NA", "NA", "NA", "0", "NA", "NA", "0", "NA", "0", "NA", "NA", "NA", "0", "NA", "NA", "1", "0", "Stoke City", "Peter Crouch", "Jesé", "0", "NA", "NA", "NA", "NA", "2", "50", "0", "NA", "NA", "61"], ["480847", "Attempt missed. Mame Biram Diouf (Stoke City) right footed shot from the right side of the six yard box is close, but misses the top right corner. Assisted by Peter Crouch with a headed pass.", "64'", "Stoke City", "0", "0", "0", "0", "1", "0", "missed", "Mame Biram Diouf", "Stoke City", "right", "the right side of the six yard box", "close, but misses the top right corner", "Peter Crouch", "0", "NA", "NA", "0", "NA", "0", "0", "NA", "NA", "NA", "0", "NA", "NA", "NA", "0", "NA", "NA", "0", "NA", "0", "NA", "NA", "NA", "0", "NA", "NA", "0", "0", "NA", "NA", "NA", "0", "NA", "NA", "NA", "NA", "2", "51", "0", "NA", "NA", "64"], ["480847", "Attempt missed. Eric Maxim Choupo-Moting (Stoke City) left footed shot from the left side of the box misses to the right.", "65'", "Stoke City", "0", "0", "0", "0", "1", "0", "missed", "NA", "Stoke City", "left", "the left side of the box", "right", "NA", "0", "NA", "NA", "0", "NA", "0", "0", "NA", "NA", "NA", "0", "NA", "NA", "NA", "0", "NA", "NA", "0", "NA", "0", "NA", "NA", "NA", "0", "NA", "NA", "0", "0", "NA", "NA", "NA", "0", "NA", "NA", "NA", "NA", "2", "52", "0", "NA", "NA", "65"], ["480847", "Corner,  Stoke City. Conceded by Tiemoué Bakayoko.", "65'", "Stoke City", "0", "0", "0", "0", "0", "0", "NA", "NA", "NA", "NA", "NA", "NA", "NA", "0", "NA", "NA", "0", "NA", "0", "0", "NA", "NA", "NA", "0", "NA", "NA", "NA", "0", "NA", "NA", "0", "NA", "0", "NA", "NA", "NA", "1", "Stoke City", "Tiemoué Bakayoko", "0", "0", "NA", "NA", "NA", "0", "NA", "NA", "NA", "NA", "2", "53", "0", "NA", "NA", "65"], ["480847", "Delay in match Thibaut Courtois (Chelsea) because of an injury.", "66'", "Stoke City", "0", "0", "0", "0", "0", "0", "NA", "NA", "NA", "NA", "NA", "NA", "NA", "0", "NA", "NA", "0", "NA", "0", "0", "NA", "NA", "NA", "0", "NA", "NA", "NA", "0", "NA", "NA", "1", "Chelsea", "0", "NA", "NA", "NA", "0", "NA", "NA", "0", "0", "NA", "NA", "NA", "0", "NA", "NA", "NA", "NA", "2", "54", "0", "NA", "NA", "66"], ["480847", "Delay over. They are ready to continue.", "68'", "Stoke City", "0", "0", "0", "0", "0", "0", "NA", "NA", "NA", "NA", "NA", "NA", "NA", "0", "NA", "NA", "0", "NA", "0", "0", "NA", "NA", "NA", "0", "NA", "NA", "NA", "0", "NA", "NA", "0", "NA", "0", "NA", "NA", "NA", "0", "NA", "NA", "0", "0", "NA", "NA", "NA", "0", "NA", "NA", "NA", "NA", "2", "55", "0", "NA", "NA", "68"], ["480847", "Substitution, Chelsea. Cesc Fàbregas replaces Pedro.", "68'", "Stoke City", "0", "0", "0", "0", "0", "0", "NA", "NA", "NA", "NA", "NA", "NA", "NA", "0", "NA", "NA", "0", "NA", "0", "0", "NA", "NA", "NA", "0", "NA", "NA", "NA", "0", "NA", "NA", "0", "NA", "0", "NA", "NA", "NA", "0", "NA", "NA", "1", "0", "Chelsea", "Cesc Fàbregas", "Pedro", "0", "NA", "NA", "NA", "NA", "2", "56", "0", "NA", "NA", "68"], ["480847", "Offside, Chelsea. Thibaut Courtois tries a through ball, but Álvaro Morata is caught offside.", "68'", "Stoke City", "0", "0", "0", "0", "0", "0", "NA", "NA", "NA", "NA", "NA", "NA", "NA", "0", "NA", "NA", "0", "NA", "0", "1", "Chelsea", "Álvaro Morata", "Thibaut Courtois", "0", "NA", "NA", "NA", "0", "NA", "NA", "0", "NA", "0", "NA", "NA", "NA", "0", "NA", "NA", "0", "0", "NA", "NA", "NA", "0", "NA", "NA", "NA", "NA", "2", "57", "0", "NA", "NA", "68"], ["480847", "Foul by Cesc Fàbregas (Chelsea).", "71'", "Stoke City", "0", "0", "0", "0", "0", "0", "NA", "NA", "NA", "NA", "NA", "NA", "NA", "1", "Cesc Fàbregas", "Chelsea", "0", "NA", "0", "0", "NA", "NA", "NA", "0", "NA", "NA", "NA", "0", "NA", "NA", "0", "NA", "0", "NA", "NA", "NA", "0", "NA", "NA", "0", "0", "NA", "NA", "NA", "0", "NA", "NA", "NA", "NA", "2", "58", "0", "NA", "NA", "71"], ["480847", "Glen Johnson (Stoke City) wins a free kick on the right wing.", "71'", "Stoke City", "0", "0", "0", "0", "0", "0", "NA", "NA", "NA", "NA", "NA", "NA", "NA", "0", "NA", "NA", "0", "NA", "0", "0", "NA", "NA", "NA", "0", "NA", "NA", "NA", "0", "NA", "NA", "0", "NA", "1", "Glen Johnson", "Stoke City", "NA", "0", "NA", "NA", "0", "0", "NA", "NA", "NA", "0", "NA", "NA", "NA", "NA", "2", "59", "0", "NA", "NA", "71"], ["480847", "Attempt missed. Mame Biram Diouf (Stoke City) right footed shot from the right side of the six yard box is close, but misses to the right. Assisted by Darren Fletcher following a set piece situation.", "72'", "Stoke City", "0", "0", "0", "0", "1", "0", "missed", "Mame Biram Diouf", "Stoke City", "right", "the right side of the six yard box", "close, but right", "Darren Fletcher", "0", "NA", "NA", "1", "NA", "0", "0", "NA", "NA", "NA", "0", "NA", "NA", "NA", "0", "NA", "NA", "0", "NA", "0", "NA", "NA", "NA", "0", "NA", "NA", "0", "0", "NA", "NA", "NA", "0", "NA", "NA", "NA", "NA", "2", "60", "0", "NA", "NA", "72"], ["480847", "Substitution, Chelsea. Eden Hazard replaces Willian.", "72'", "Stoke City", "0", "0", "0", "0", "0", "0", "NA", "NA", "NA", "NA", "NA", "NA", "NA", "0", "NA", "NA", "0", "NA", "0", "0", "NA", "NA", "NA", "0", "NA", "NA", "NA", "0", "NA", "NA", "0", "NA", "0", "NA", "NA", "NA", "0", "NA", "NA", "1", "0", "Chelsea", "Eden Hazard", "Willian", "0", "NA", "NA", "NA", "NA", "2", "61", "0", "NA", "NA", "72"], ["480847", "Eric Maxim Choupo-Moting (Stoke City) wins a free kick in the attacking half.", "73'", "Stoke City", "0", "0", "0", "0", "0", "0", "NA", "NA", "NA", "NA", "NA", "NA", "NA", "0", "NA", "NA", "0", "NA", "0", "0", "NA", "NA", "NA", "0", "NA", "NA", "NA", "0", "NA", "NA", "0", "NA", "1", "NA", "Stoke City", "attacking half", "0", "NA", "NA", "0", "0", "NA", "NA", "NA", "0", "NA", "NA", "NA", "NA", "2", "62", "0", "NA", "NA", "73"], ["480847", "Foul by Antonio Rüdiger (Chelsea).", "73'", "Stoke City", "0", "0", "0", "0", "0", "0", "NA", "NA", "NA", "NA", "NA", "NA", "NA", "1", "Antonio Rüdiger", "Chelsea", "0", "NA", "0", "0", "NA", "NA", "NA", "0", "NA", "NA", "NA", "0", "NA", "NA", "0", "NA", "0", "NA", "NA", "NA", "0", "NA", "NA", "0", "0", "NA", "NA", "NA", "0", "NA", "NA", "NA", "NA", "2", "63", "0", "NA", "NA", "73"], ["480847", "Attempt saved. Eric Maxim Choupo-Moting (Stoke City) header from the centre of the box is saved in the top right corner. Assisted by Xherdan Shaqiri with a cross.", "74'", "Stoke City", "0", "0", "0", "0", "1", "0", "saved", "NA", "Stoke City", "header", "the centre of the box", "the top right corner", "Xherdan Shaqiri", "0", "NA", "NA", "0", "cross", "0", "0", "NA", "NA", "NA", "0", "NA", "NA", "NA", "0", "NA", "NA", "0", "NA", "0", "NA", "NA", "NA", "0", "NA", "NA", "0", "0", "NA", "NA", "NA", "0", "NA", "NA", "NA", "NA", "2", "64", "0", "NA", "NA", "74"], ["480847", "Foul by Tiemoué Bakayoko (Chelsea).", "74'", "Stoke City", "0", "0", "0", "0", "0", "0", "NA", "NA", "NA", "NA", "NA", "NA", "NA", "1", "Tiemoué Bakayoko", "Chelsea", "0", "NA", "0", "0", "NA", "NA", "NA", "0", "NA", "NA", "NA", "0", "NA", "NA", "0", "NA", "0", "NA", "NA", "NA", "0", "NA", "NA", "0", "0", "NA", "NA", "NA", "0", "NA", "NA", "NA", "NA", "2", "65", "0", "NA", "NA", "74"], ["480847", "Glen Johnson (Stoke City) wins a free kick on the right wing.", "74'", "Stoke City", "0", "0", "0", "0", "0", "0", "NA", "NA", "NA", "NA", "NA", "NA", "NA", "0", "NA", "NA", "0", "NA", "0", "0", "NA", "NA", "NA", "0", "NA", "NA", "NA", "0", "NA", "NA", "0", "NA", "1", "Glen Johnson", "Stoke City", "NA", "0", "NA", "NA", "0", "0", "NA", "NA", "NA", "0", "NA", "NA", "NA", "NA", "2", "66", "0", "NA", "NA", "74"], ["480847", "Substitution, Stoke City. Ibrahim Afellay replaces Bruno Martins Indi.", "76'", "Stoke City", "0", "0", "0", "0", "0", "0", "NA", "NA", "NA", "NA", "NA", "NA", "NA", "0", "NA", "NA", "0", "NA", "0", "0", "NA", "NA", "NA", "0", "NA", "NA", "NA", "0", "NA", "NA", "0", "NA", "0", "NA", "NA", "NA", "0", "NA", "NA", "1", "0", "Stoke City", "Ibrahim Afellay", "Bruno Martins Indi", "0", "NA", "NA", "NA", "NA", "2", "67", "0", "NA", "NA", "76"], ["480847", "Goal!  Stoke City 0, Chelsea 3. Álvaro Morata (Chelsea) right footed shot from the left side of the six yard box to the centre of the goal. Assisted by Tiemoué Bakayoko.", "77'", "Stoke City", "0", "0", "0", "0", "1", "0", "goal", "Álvaro Morata", "Chelsea", "right", "the left side of the six yard box", "centre of the goal", "Tiemoué Bakayoko", "0", "NA", "NA", "0", "NA", "0", "0", "NA", "NA", "NA", "0", "NA", "NA", "NA", "0", "NA", "NA", "0", "NA", "0", "NA", "NA", "NA", "0", "NA", "NA", "0", "0", "NA", "NA", "NA", "0", "NA", "NA", "NA", "NA", "2", "68", "0", "NA", "NA", "77"], ["480847", "Attempt missed. Eden Hazard (Chelsea) right footed shot from a difficult angle on the right misses to the left. Assisted by Victor Moses.", "79'", "Stoke City", "0", "0", "0", "0", "1", "0", "missed", "Eden Hazard", "Chelsea", "right", "NA", "NA", "Victor Moses", "0", "NA", "NA", "0", "NA", "0", "0", "NA", "NA", "NA", "0", "NA", "NA", "NA", "0", "NA", "NA", "0", "NA", "0", "NA", "NA", "NA", "0", "NA", "NA", "0", "0", "NA", "NA", "NA", "0", "NA", "NA", "NA", "NA", "2", "69", "0", "NA", "NA", "79"], ["480847", "Foul by Victor Moses (Chelsea).", "80'", "Stoke City", "0", "0", "0", "0", "0", "0", "NA", "NA", "NA", "NA", "NA", "NA", "NA", "1", "Victor Moses", "Chelsea", "0", "NA", "0", "0", "NA", "NA", "NA", "0", "NA", "NA", "NA", "0", "NA", "NA", "0", "NA", "0", "NA", "NA", "NA", "0", "NA", "NA", "0", "0", "NA", "NA", "NA", "0", "NA", "NA", "NA", "NA", "2", "70", "0", "NA", "NA", "80"], ["480847", "Peter Crouch (Stoke City) wins a free kick on the left wing.", "80'", "Stoke City", "0", "0", "0", "0", "0", "0", "NA", "NA", "NA", "NA", "NA", "NA", "NA", "0", "NA", "NA", "0", "NA", "0", "0", "NA", "NA", "NA", "0", "NA", "NA", "NA", "0", "NA", "NA", "0", "NA", "1", "Peter Crouch", "Stoke City", "NA", "0", "NA", "NA", "0", "0", "NA", "NA", "NA", "0", "NA", "NA", "NA", "NA", "2", "71", "0", "NA", "NA", "80"], ["480847", "Attempt missed. Eric Maxim Choupo-Moting (Stoke City) right footed shot from the left side of the box misses to the right. Assisted by Ramadan Sobhi.", "81'", "Stoke City", "0", "0", "0", "0", "1", "0", "missed", "NA", "Stoke City", "right", "the left side of the box", "right", "Ramadan Sobhi", "0", "NA", "NA", "0", "NA", "0", "0", "NA", "NA", "NA", "0", "NA", "NA", "NA", "0", "NA", "NA", "0", "NA", "0", "NA", "NA", "NA", "0", "NA", "NA", "0", "0", "NA", "NA", "NA", "0", "NA", "NA", "NA", "NA", "2", "72", "0", "NA", "NA", "81"], ["480847", "Goal!  Stoke City 0, Chelsea 4. Álvaro Morata (Chelsea) right footed shot from very close range to the bottom right corner. Assisted by César Azpilicueta.", "82'", "Stoke City", "0", "0", "0", "0", "1", "0", "goal", "Álvaro Morata", "Chelsea", "right", "right shot very close range", "bottom right corner", "César Azpilicueta", "0", "NA", "NA", "0", "NA", "0", "0", "NA", "NA", "NA", "0", "NA", "NA", "NA", "0", "NA", "NA", "0", "NA", "0", "NA", "NA", "NA", "0", "NA", "NA", "0", "0", "NA", "NA", "NA", "0", "NA", "NA", "NA", "NA", "2", "73", "0", "NA", "NA", "82"], ["480847", "Attempt missed. Álvaro Morata (Chelsea) right footed shot from the centre of the box is close, but misses to the right. Assisted by Cesc Fàbregas.", "87'", "Stoke City", "0", "0", "0", "0", "1", "0", "missed", "Álvaro Morata", "Chelsea", "right", "the centre of the box", "close, but right", "Cesc Fàbregas", "0", "NA", "NA", "0", "NA", "0", "0", "NA", "NA", "NA", "0", "NA", "NA", "NA", "0", "NA", "NA", "0", "NA", "0", "NA", "NA", "NA", "0", "NA", "NA", "0", "0", "NA", "NA", "NA", "0", "NA", "NA", "NA", "NA", "2", "74", "0", "NA", "NA", "87"], ["480847", "Attempt missed. Victor Moses (Chelsea) right footed shot from the right side of the box misses to the left. Assisted by N'Golo Kanté.", "88'", "Stoke City", "0", "0", "0", "0", "1", "0", "missed", "Victor Moses", "Chelsea", "right", "the right side of the box", "left", "N'Golo Kanté", "0", "NA", "NA", "0", "NA", "0", "0", "NA", "NA", "NA", "0", "NA", "NA", "NA", "0", "NA", "NA", "0", "NA", "0", "NA", "NA", "NA", "0", "NA", "NA", "0", "0", "NA", "NA", "NA", "0", "NA", "NA", "NA", "NA", "2", "75", "0", "NA", "NA", "88"], ["480847", "Cesc Fàbregas (Chelsea) wins a free kick in the attacking half.", "89'", "Stoke City", "0", "0", "0", "0", "0", "0", "NA", "NA", "NA", "NA", "NA", "NA", "NA", "0", "NA", "NA", "0", "NA", "0", "0", "NA", "NA", "NA", "0", "NA", "NA", "NA", "0", "NA", "NA", "0", "NA", "1", "Cesc Fàbregas", "Chelsea", "attacking half", "0", "NA", "NA", "0", "0", "NA", "NA", "NA", "0", "NA", "NA", "NA", "NA", "2", "76", "0", "NA", "NA", "89"], ["480847", "Foul by Peter Crouch (Stoke City).", "89'", "Stoke City", "0", "0", "0", "0", "0", "0", "NA", "NA", "NA", "NA", "NA", "NA", "NA", "1", "Peter Crouch", "Stoke City", "0", "NA", "0", "0", "NA", "NA", "NA", "0", "NA", "NA", "NA", "0", "NA", "NA", "0", "NA", "0", "NA", "NA", "NA", "0", "NA", "NA", "0", "0", "NA", "NA", "NA", "0", "NA", "NA", "NA", "NA", "2", "77", "0", "NA", "NA", "89"], ["480847", "Peter Crouch (Stoke City) is shown the yellow card for a bad foul.", "89'", "Stoke City", "0", "0", "0", "0", "0", "0", "NA", "NA", "NA", "NA", "NA", "NA", "NA", "0", "NA", "NA", "0", "NA", "0", "0", "NA", "NA", "NA", "1", "yellow", "Peter Crouch", "Stoke City", "0", "NA", "NA", "0", "NA", "0", "NA", "NA", "NA", "0", "NA", "NA", "0", "0", "NA", "NA", "NA", "0", "NA", "NA", "NA", "NA", "2", "78", "0", "NA", "NA", "89"], ["480847", "Second Half ends, Stoke City 0, Chelsea 4.", "90'+4'", "Stoke City", "0", "1", "0", "0", "0", "0", "NA", "NA", "NA", "NA", "NA", "NA", "NA", "0", "NA", "NA", "0", "NA", "0", "0", "NA", "NA", "NA", "0", "NA", "NA", "NA", "0", "NA", "NA", "0", "NA", "0", "NA", "NA", "NA", "0", "NA", "NA", "0", "0", "NA", "NA", "NA", "0", "NA", "NA", "NA", "NA", "2", "79", "1", "NA", "NA", "94"], ["480847", "Match ends, Stoke City 0, Chelsea 4.", "90'+4'", "Stoke City", "0", "0", "1", "0", "0", "0", "NA", "NA", "NA", "NA", "NA", "NA", "NA", "0", "NA", "NA", "0", "NA", "0", "0", "NA", "NA", "NA", "0", "NA", "NA", "NA", "0", "NA", "NA", "0", "NA", "0", "NA", "NA", "NA", "0", "NA", "NA", "0", "0", "NA", "NA", "NA", "0", "NA", "NA", "NA", "NA", "2", "80", "1", "NA", "NA", "94"]], "Lineup": {"Home Player 9": "Erik Pieters", "Home Player 8": "Bruno Martins Indi", "Home Player 5": "Darren Fletcher", "Home Player 4": "Mame Diouf", "Home Player 7": "Glen Johnson", "Home Player 6": "Jese", "Home Player 1": "Joe Allen", "Home Player 3": "Eric Maxim Choupo-Moting", "Home Player 2": "Jack Butland", "Away Player 10": "Antonio Rudiger", "Away Player 11": "Willian", "Away Player 8": "Victor Moses", "Away Player 9": "Pedro", "Away Player 1": "Marcos Alonso", "Away Player 2": "Cesar Azpilicueta", "Away Player 3": "Tiemoue Bakayoko", "Away Player 4": "Andreas Christensen", "Away Player 5": "Thibaut Courtois", "Away Player 6": "N'Golo Kanté", "Away Player 7": "Alvaro Morata", "Game ID": "g_1_baCHsHc5", "Home Player 11": "Ramadan Sobhi", "Home Player 10": "Xherdan Shaqiri"}}