{"Stats": {"Full Time Result": "D", "Away Team Corners": 4, "Referee": "K Friend", "Home Team Fouls Committed": 6, "Away Team Shots": 16, "Away Team Red Cards": 0, "Home Team Red Cards": 0, "Half Time Away Team Goals": 0, "Full Time Home Team Goals": 1, "Away Team Yellow Cards": 0, "Away Team Shots on Target": 6, "Half Time Home Team Goals": 0, "Half Time Result": "D", "Away Team Fouls Committed": 5, "Home Team Yellow Cards": 1, "Home Team Shots": 8, "Div": "E0", "Home Team Corners": 3, "Home Team Shots on Target": 5, "Full Time Away Team Goals": 1}, "Description": "Delay in match Anthony Knockaert (Brighton and Hove Albion) because of an injury. at minute 2. Delay over. They are ready to continue. at minute 4. Corner,  Tottenham Hotspur. Conceded by Bruno. at minute 5. Anthony Knockaert (Brighton and Hove Albion) wins a free kick in the defensive half. at minute 7. Foul by Ben Davies (Tottenham Hotspur). at minute 7. Foul by Lewis Dunk (Brighton and Hove Albion). at minute 11. Lucas Moura (Tottenham Hotspur) wins a free kick in the attacking half. at minute 11. Lewis Dunk (Brighton and Hove Albion) is shown the yellow card for a bad foul. at minute 11. Attempt blocked. Christian Eriksen (Tottenham Hotspur) right footed shot from outside the box is blocked. at minute 12. Foul by Victor Wanyama (Tottenham Hotspur). at minute 14. Glenn Murray (Brighton and Hove Albion) wins a free kick in the defensive half. at minute 14. Corner,  Brighton and Hove Albion. Conceded by Jan Vertonghen. at minute 18. Attempt saved. Lewis Dunk (Brighton and Hove Albion) header from the centre of the box is saved in the centre of the goal. Assisted by Pascal Groß with a cross. at minute 18. Attempt blocked. Jan Vertonghen (Tottenham Hotspur) left footed shot from outside the box is blocked. Assisted by Son Heung-Min. at minute 20. Attempt saved. Anthony Knockaert (Brighton and Hove Albion) left footed shot from outside the box is saved in the bottom left corner. Assisted by Shane Duffy. at minute 20. Attempt saved. Son Heung-Min (Tottenham Hotspur) left footed shot from the left side of the box is saved in the centre of the goal. Assisted by Moussa Sissoko. at minute 23. Attempt saved. Gaëtan Bong (Brighton and Hove Albion) left footed shot from outside the box is saved in the centre of the goal. Assisted by Beram Kayal. at minute 25. Foul by Bruno (Brighton and Hove Albion). at minute 26. Son Heung-Min (Tottenham Hotspur) wins a free kick on the left wing. at minute 26. Attempt blocked. Dale Stephens (Brighton and Hove Albion) right footed shot from the centre of the box is blocked. Assisted by Pascal Groß with a cross. at minute 27. Attempt missed. Lewis Dunk (Brighton and Hove Albion) right footed shot from outside the box is high and wide to the right. at minute 30. Attempt missed. Harry Kane (Tottenham Hotspur) left footed shot from the centre of the box is high and wide to the left. Assisted by Lucas Moura. at minute 31. Attempt saved. Lucas Moura (Tottenham Hotspur) right footed shot from outside the box is saved in the top right corner. Assisted by Christian Eriksen. at minute 32. Corner,  Tottenham Hotspur. Conceded by Mat Ryan. at minute 32. Foul by Anthony Knockaert (Brighton and Hove Albion). at minute 39. Son Heung-Min (Tottenham Hotspur) wins a free kick on the left wing. at minute 39. Foul by Anthony Knockaert (Brighton and Hove Albion). at minute 46. Harry Kane (Tottenham Hotspur) wins a free kick in the attacking half. at minute 46. Delay in match Lucas Moura (Tottenham Hotspur) because of an injury. at minute 46. Delay over. They are ready to continue. at minute 47. Attempt saved. Harry Kane (Tottenham Hotspur) right footed shot from outside the box is saved in the bottom right corner. Assisted by Christian Eriksen. at minute 48. Attempt saved. Son Heung-Min (Tottenham Hotspur) right footed shot from the centre of the box is saved in the bottom right corner. Assisted by Harry Kane. at minute 49. Corner,  Tottenham Hotspur. Conceded by Mat Ryan. at minute 49. First Half ends, Brighton and Hove Albion 0, Tottenham Hotspur 0. at minute 49. Second Half begins Brighton and Hove Albion 0, Tottenham Hotspur 0. at minute 45. Goal!  Brighton and Hove Albion 0, Tottenham Hotspur 1. Harry Kane (Tottenham Hotspur) right footed shot from the centre of the box to the centre of the goal. Assisted by Son Heung-Min. at minute 48. Penalty Brighton and Hove Albion. José Izquierdo draws a foul in the penalty area. at minute 49. Penalty conceded by Serge Aurier (Tottenham Hotspur) after a foul in the penalty area. at minute 49. Goal!  Brighton and Hove Albion 1, Tottenham Hotspur 1. Pascal Groß (Brighton and Hove Albion) converts the penalty with a right footed shot to the bottom left corner. at minute 50. Beram Kayal (Brighton and Hove Albion) wins a free kick in the defensive half. at minute 55. Foul by Christian Eriksen (Tottenham Hotspur). at minute 55. Attempt missed. Lucas Moura (Tottenham Hotspur) right footed shot from the left side of the box is close, but misses to the left. Assisted by Christian Eriksen. at minute 55. Hand ball by Beram Kayal (Brighton and Hove Albion). at minute 57. Attempt blocked. Christian Eriksen (Tottenham Hotspur) right footed shot from outside the box is blocked. at minute 58. Attempt blocked. Ben Davies (Tottenham Hotspur) right footed shot from outside the box is blocked. at minute 58. Foul by Dale Stephens (Brighton and Hove Albion). at minute 65. Son Heung-Min (Tottenham Hotspur) wins a free kick in the attacking half. at minute 65. Attempt missed. Son Heung-Min (Tottenham Hotspur) right footed shot from outside the box misses to the right. Assisted by Christian Eriksen. at minute 69. Attempt blocked. Christian Eriksen (Tottenham Hotspur) left footed shot from outside the box is blocked. Assisted by Serge Aurier. at minute 72. Corner,  Tottenham Hotspur. Conceded by Shane Duffy. at minute 73. Attempt missed. Toby Alderweireld (Tottenham Hotspur) left footed shot from the left side of the box is close, but misses to the left following a corner. at minute 73. Substitution, Brighton and Hove Albion. Leonardo Ulloa replaces Glenn Murray. at minute 74. Substitution, Tottenham Hotspur. Erik Lamela replaces Lucas Moura. at minute 74. Substitution, Tottenham Hotspur. Mousa Dembélé replaces Moussa Sissoko. at minute 74. Attempt saved. José Izquierdo (Brighton and Hove Albion) right footed shot from the left side of the box is saved in the centre of the goal. Assisted by Anthony Knockaert. at minute 75. Substitution, Brighton and Hove Albion. Solly March replaces José Izquierdo. at minute 77. Attempt missed. Harry Kane (Tottenham Hotspur) right footed shot from outside the box misses to the left. Assisted by Ben Davies. at minute 85. Substitution, Tottenham Hotspur. Fernando Llorente replaces Harry Kane. at minute 85. Attempt missed. Pascal Groß (Brighton and Hove Albion) right footed shot from the left side of the box is too high. Assisted by Leonardo Ulloa. at minute 86. Attempt saved. Erik Lamela (Tottenham Hotspur) right footed shot from the centre of the box is saved in the top centre of the goal. at minute 88. Corner,  Brighton and Hove Albion. Conceded by Toby Alderweireld. at minute 89. Corner,  Brighton and Hove Albion. Conceded by Toby Alderweireld. at minute 89. Corner,  Tottenham Hotspur. Conceded by Bruno. at minute 92. Beram Kayal (Brighton and Hove Albion) wins a free kick in the defensive half. at minute 93. Foul by Erik Lamela (Tottenham Hotspur). at minute 93. Second Half ends, Brighton and Hove Albion 1, Tottenham Hotspur 1. at minute 94. Match ends, Brighton and Hove Albion 1, Tottenham Hotspur 1. at minute 94. ", "Home Team": "Brighton & Hove Albion", "Away Team": "Tottenham Hotspur", "Date": "2018-04-17", "Commentary": [["480564", "First Half begins.", "-", "Brighton & Hove Albion", "0", "0", "0", "1", "0", "0", "NA", "NA", "NA", "NA", "NA", "NA", "NA", "0", "NA", "NA", "0", "NA", "0", "0", "NA", "NA", "NA", "0", "NA", "NA", "NA", "0", "NA", "NA", "0", "NA", "0", "NA", "NA", "NA", "0", "NA", "NA", "0", "0", "NA", "NA", "NA", "0", "NA", "NA", "NA", "NA", "1", "1", "0", "NA", "NA", "NA"], ["480564", "Lineups are announced and players are warming up.", "-", "Brighton & Hove Albion", "0", "0", "0", "0", "0", "0", "NA", "NA", "NA", "NA", "NA", "NA", "NA", "0", "NA", "NA", "0", "NA", "0", "0", "NA", "NA", "NA", "0", "NA", "NA", "NA", "0", "NA", "NA", "0", "NA", "0", "NA", "NA", "NA", "0", "NA", "NA", "0", "0", "NA", "NA", "NA", "0", "NA", "NA", "NA", "NA", "1", "2", "0", "NA", "NA", "NA"], ["480564", "Delay in match Anthony Knockaert (Brighton and Hove Albion) because of an injury.", "2'", "Brighton & Hove Albion", "0", "0", "0", "0", "0", "0", "NA", "NA", "NA", "NA", "NA", "NA", "NA", "0", "NA", "NA", "0", "NA", "0", "0", "NA", "NA", "NA", "0", "NA", "NA", "NA", "0", "NA", "NA", "1", "Brighton and Hove Albion", "0", "NA", "NA", "NA", "0", "NA", "NA", "0", "0", "NA", "NA", "NA", "0", "NA", "NA", "NA", "NA", "1", "3", "0", "NA", "NA", "2"], ["480564", "Delay over. They are ready to continue.", "4'", "Brighton & Hove Albion", "0", "0", "0", "0", "0", "0", "NA", "NA", "NA", "NA", "NA", "NA", "NA", "0", "NA", "NA", "0", "NA", "0", "0", "NA", "NA", "NA", "0", "NA", "NA", "NA", "0", "NA", "NA", "0", "NA", "0", "NA", "NA", "NA", "0", "NA", "NA", "0", "0", "NA", "NA", "NA", "0", "NA", "NA", "NA", "NA", "1", "4", "0", "NA", "NA", "4"], ["480564", "Corner,  Tottenham Hotspur. Conceded by Bruno.", "5'", "Brighton & Hove Albion", "0", "0", "0", "0", "0", "0", "NA", "NA", "NA", "NA", "NA", "NA", "NA", "0", "NA", "NA", "0", "NA", "0", "0", "NA", "NA", "NA", "0", "NA", "NA", "NA", "0", "NA", "NA", "0", "NA", "0", "NA", "NA", "NA", "1", "Tottenham Hotspur", "Bruno", "0", "0", "NA", "NA", "NA", "0", "NA", "NA", "NA", "NA", "1", "5", "0", "NA", "NA", "5"], ["480564", "Anthony Knockaert (Brighton and Hove Albion) wins a free kick in the defensive half.", "7'", "Brighton & Hove Albion", "0", "0", "0", "0", "0", "0", "NA", "NA", "NA", "NA", "NA", "NA", "NA", "0", "NA", "NA", "0", "NA", "0", "0", "NA", "NA", "NA", "0", "NA", "NA", "NA", "0", "NA", "NA", "0", "NA", "1", "Anthony Knockaert", "Brighton and Hove Albion", "defensive half", "0", "NA", "NA", "0", "0", "NA", "NA", "NA", "0", "NA", "NA", "NA", "NA", "1", "6", "0", "NA", "NA", "7"], ["480564", "Foul by Ben Davies (Tottenham Hotspur).", "7'", "Brighton & Hove Albion", "0", "0", "0", "0", "0", "0", "NA", "NA", "NA", "NA", "NA", "NA", "NA", "1", "Ben Davies", "Tottenham Hotspur", "0", "NA", "0", "0", "NA", "NA", "NA", "0", "NA", "NA", "NA", "0", "NA", "NA", "0", "NA", "0", "NA", "NA", "NA", "0", "NA", "NA", "0", "0", "NA", "NA", "NA", "0", "NA", "NA", "NA", "NA", "1", "7", "0", "NA", "NA", "7"], ["480564", "Foul by Lewis Dunk (Brighton and Hove Albion).", "11'", "Brighton & Hove Albion", "0", "0", "0", "0", "0", "0", "NA", "NA", "NA", "NA", "NA", "NA", "NA", "1", "Lewis Dunk", "Brighton and Hove Albion", "0", "NA", "0", "0", "NA", "NA", "NA", "0", "NA", "NA", "NA", "0", "NA", "NA", "0", "NA", "0", "NA", "NA", "NA", "0", "NA", "NA", "0", "0", "NA", "NA", "NA", "0", "NA", "NA", "NA", "NA", "1", "8", "0", "NA", "NA", "11"], ["480564", "Lucas Moura (Tottenham Hotspur) wins a free kick in the attacking half.", "11'", "Brighton & Hove Albion", "0", "0", "0", "0", "0", "0", "NA", "NA", "NA", "NA", "NA", "NA", "NA", "0", "NA", "NA", "0", "NA", "0", "0", "NA", "NA", "NA", "0", "NA", "NA", "NA", "0", "NA", "NA", "0", "NA", "1", "Lucas Moura", "Tottenham Hotspur", "attacking half", "0", "NA", "NA", "0", "0", "NA", "NA", "NA", "0", "NA", "NA", "NA", "NA", "1", "9", "0", "NA", "NA", "11"], ["480564", "Lewis Dunk (Brighton and Hove Albion) is shown the yellow card for a bad foul.", "11'", "Brighton & Hove Albion", "0", "0", "0", "0", "0", "0", "NA", "NA", "NA", "NA", "NA", "NA", "NA", "0", "NA", "NA", "0", "NA", "0", "0", "NA", "NA", "NA", "1", "yellow", "Lewis Dunk", "Brighton and Hove Albion", "0", "NA", "NA", "0", "NA", "0", "NA", "NA", "NA", "0", "NA", "NA", "0", "0", "NA", "NA", "NA", "0", "NA", "NA", "NA", "NA", "1", "10", "0", "NA", "NA", "11"], ["480564", "Attempt blocked. Christian Eriksen (Tottenham Hotspur) right footed shot from outside the box is blocked.", "12'", "Brighton & Hove Albion", "0", "0", "0", "0", "1", "0", "blocked", "Christian Eriksen", "Tottenham Hotspur", "right", "outside the box", "NA", "NA", "0", "NA", "NA", "0", "NA", "0", "0", "NA", "NA", "NA", "0", "NA", "NA", "NA", "0", "NA", "NA", "0", "NA", "0", "NA", "NA", "NA", "0", "NA", "NA", "0", "0", "NA", "NA", "NA", "0", "NA", "NA", "NA", "NA", "1", "11", "0", "NA", "NA", "12"], ["480564", "Foul by Victor Wanyama (Tottenham Hotspur).", "14'", "Brighton & Hove Albion", "0", "0", "0", "0", "0", "0", "NA", "NA", "NA", "NA", "NA", "NA", "NA", "1", "Victor Wanyama", "Tottenham Hotspur", "0", "NA", "0", "0", "NA", "NA", "NA", "0", "NA", "NA", "NA", "0", "NA", "NA", "0", "NA", "0", "NA", "NA", "NA", "0", "NA", "NA", "0", "0", "NA", "NA", "NA", "0", "NA", "NA", "NA", "NA", "1", "12", "0", "NA", "NA", "14"], ["480564", "Glenn Murray (Brighton and Hove Albion) wins a free kick in the defensive half.", "14'", "Brighton & Hove Albion", "0", "0", "0", "0", "0", "0", "NA", "NA", "NA", "NA", "NA", "NA", "NA", "0", "NA", "NA", "0", "NA", "0", "0", "NA", "NA", "NA", "0", "NA", "NA", "NA", "0", "NA", "NA", "0", "NA", "1", "Glenn Murray", "Brighton and Hove Albion", "defensive half", "0", "NA", "NA", "0", "0", "NA", "NA", "NA", "0", "NA", "NA", "NA", "NA", "1", "13", "0", "NA", "NA", "14"], ["480564", "Corner,  Brighton and Hove Albion. Conceded by Jan Vertonghen.", "18'", "Brighton & Hove Albion", "0", "0", "0", "0", "0", "0", "NA", "NA", "NA", "NA", "NA", "NA", "NA", "0", "NA", "NA", "0", "NA", "0", "0", "NA", "NA", "NA", "0", "NA", "NA", "NA", "0", "NA", "NA", "0", "NA", "0", "NA", "NA", "NA", "1", "Brighton and Hove Albion", "Jan Vertonghen", "0", "0", "NA", "NA", "NA", "0", "NA", "NA", "NA", "NA", "1", "14", "0", "NA", "NA", "18"], ["480564", "Attempt saved. Lewis Dunk (Brighton and Hove Albion) header from the centre of the box is saved in the centre of the goal. Assisted by Pascal Groß with a cross.", "18'", "Brighton & Hove Albion", "0", "0", "0", "0", "1", "0", "saved", "Lewis Dunk", "Brighton and Hove Albion", "header", "the centre of the box", "the centre of the goal", "Pascal Groß", "0", "NA", "NA", "0", "cross", "0", "0", "NA", "NA", "NA", "0", "NA", "NA", "NA", "0", "NA", "NA", "0", "NA", "0", "NA", "NA", "NA", "0", "NA", "NA", "0", "0", "NA", "NA", "NA", "0", "NA", "NA", "NA", "NA", "1", "15", "0", "NA", "NA", "18"], ["480564", "Attempt blocked. Jan Vertonghen (Tottenham Hotspur) left footed shot from outside the box is blocked. Assisted by Son Heung-Min.", "20'", "Brighton & Hove Albion", "0", "0", "0", "0", "1", "0", "blocked", "Jan Vertonghen", "Tottenham Hotspur", "left", "outside the box", "NA", "Son Heung-Min", "0", "NA", "NA", "0", "NA", "0", "0", "NA", "NA", "NA", "0", "NA", "NA", "NA", "0", "NA", "NA", "0", "NA", "0", "NA", "NA", "NA", "0", "NA", "NA", "0", "0", "NA", "NA", "NA", "0", "NA", "NA", "NA", "NA", "1", "16", "0", "NA", "NA", "20"], ["480564", "Attempt saved. Anthony Knockaert (Brighton and Hove Albion) left footed shot from outside the box is saved in the bottom left corner. Assisted by Shane Duffy.", "20'", "Brighton & Hove Albion", "0", "0", "0", "0", "1", "0", "saved", "Anthony Knockaert", "Brighton and Hove Albion", "left", "outside the box", "the bottom left corner", "Shane Duffy", "0", "NA", "NA", "0", "NA", "0", "0", "NA", "NA", "NA", "0", "NA", "NA", "NA", "0", "NA", "NA", "0", "NA", "0", "NA", "NA", "NA", "0", "NA", "NA", "0", "0", "NA", "NA", "NA", "0", "NA", "NA", "NA", "NA", "1", "17", "0", "NA", "NA", "20"], ["480564", "Attempt saved. Son Heung-Min (Tottenham Hotspur) left footed shot from the left side of the box is saved in the centre of the goal. Assisted by Moussa Sissoko.", "23'", "Brighton & Hove Albion", "0", "0", "0", "0", "1", "0", "saved", "Son Heung-Min", "Tottenham Hotspur", "left", "the left side of the box", "the centre of the goal", "Moussa Sissoko", "0", "NA", "NA", "0", "NA", "0", "0", "NA", "NA", "NA", "0", "NA", "NA", "NA", "0", "NA", "NA", "0", "NA", "0", "NA", "NA", "NA", "0", "NA", "NA", "0", "0", "NA", "NA", "NA", "0", "NA", "NA", "NA", "NA", "1", "18", "0", "NA", "NA", "23"], ["480564", "Attempt saved. Gaëtan Bong (Brighton and Hove Albion) left footed shot from outside the box is saved in the centre of the goal. Assisted by Beram Kayal.", "25'", "Brighton & Hove Albion", "0", "0", "0", "0", "1", "0", "saved", "Gaëtan Bong", "Brighton and Hove Albion", "left", "outside the box", "the centre of the goal", "Beram Kayal", "0", "NA", "NA", "0", "NA", "0", "0", "NA", "NA", "NA", "0", "NA", "NA", "NA", "0", "NA", "NA", "0", "NA", "0", "NA", "NA", "NA", "0", "NA", "NA", "0", "0", "NA", "NA", "NA", "0", "NA", "NA", "NA", "NA", "1", "19", "0", "NA", "NA", "25"], ["480564", "Foul by Bruno (Brighton and Hove Albion).", "26'", "Brighton & Hove Albion", "0", "0", "0", "0", "0", "0", "NA", "NA", "NA", "NA", "NA", "NA", "NA", "1", "Bruno", "Brighton and Hove Albion", "0", "NA", "0", "0", "NA", "NA", "NA", "0", "NA", "NA", "NA", "0", "NA", "NA", "0", "NA", "0", "NA", "NA", "NA", "0", "NA", "NA", "0", "0", "NA", "NA", "NA", "0", "NA", "NA", "NA", "NA", "1", "20", "0", "NA", "NA", "26"], ["480564", "Son Heung-Min (Tottenham Hotspur) wins a free kick on the left wing.", "26'", "Brighton & Hove Albion", "0", "0", "0", "0", "0", "0", "NA", "NA", "NA", "NA", "NA", "NA", "NA", "0", "NA", "NA", "0", "NA", "0", "0", "NA", "NA", "NA", "0", "NA", "NA", "NA", "0", "NA", "NA", "0", "NA", "1", "Son Heung-Min", "Tottenham Hotspur", "NA", "0", "NA", "NA", "0", "0", "NA", "NA", "NA", "0", "NA", "NA", "NA", "NA", "1", "21", "0", "NA", "NA", "26"], ["480564", "Attempt blocked. Dale Stephens (Brighton and Hove Albion) right footed shot from the centre of the box is blocked. Assisted by Pascal Groß with a cross.", "27'", "Brighton & Hove Albion", "0", "0", "0", "0", "1", "0", "blocked", "Dale Stephens", "Brighton and Hove Albion", "right", "the centre of the box", "NA", "Pascal Groß", "0", "NA", "NA", "0", "cross", "0", "0", "NA", "NA", "NA", "0", "NA", "NA", "NA", "0", "NA", "NA", "0", "NA", "0", "NA", "NA", "NA", "0", "NA", "NA", "0", "0", "NA", "NA", "NA", "0", "NA", "NA", "NA", "NA", "1", "22", "0", "NA", "NA", "27"], ["480564", "Attempt missed. Lewis Dunk (Brighton and Hove Albion) right footed shot from outside the box is high and wide to the right.", "30'", "Brighton & Hove Albion", "0", "0", "0", "0", "1", "0", "missed", "Lewis Dunk", "Brighton and Hove Albion", "right", "outside the box", "high and wide to the right", "NA", "0", "NA", "NA", "0", "NA", "0", "0", "NA", "NA", "NA", "0", "NA", "NA", "NA", "0", "NA", "NA", "0", "NA", "0", "NA", "NA", "NA", "0", "NA", "NA", "0", "0", "NA", "NA", "NA", "0", "NA", "NA", "NA", "NA", "1", "23", "0", "NA", "NA", "30"], ["480564", "Attempt missed. Harry Kane (Tottenham Hotspur) left footed shot from the centre of the box is high and wide to the left. Assisted by Lucas Moura.", "31'", "Brighton & Hove Albion", "0", "0", "0", "0", "1", "0", "missed", "Harry Kane", "Tottenham Hotspur", "left", "the centre of the box", "high and wide to the left", "Lucas Moura", "0", "NA", "NA", "0", "NA", "0", "0", "NA", "NA", "NA", "0", "NA", "NA", "NA", "0", "NA", "NA", "0", "NA", "0", "NA", "NA", "NA", "0", "NA", "NA", "0", "0", "NA", "NA", "NA", "0", "NA", "NA", "NA", "NA", "1", "24", "0", "NA", "NA", "31"], ["480564", "Attempt saved. Lucas Moura (Tottenham Hotspur) right footed shot from outside the box is saved in the top right corner. Assisted by Christian Eriksen.", "32'", "Brighton & Hove Albion", "0", "0", "0", "0", "1", "0", "saved", "Lucas Moura", "Tottenham Hotspur", "right", "outside the box", "the top right corner", "Christian Eriksen", "0", "NA", "NA", "0", "NA", "0", "0", "NA", "NA", "NA", "0", "NA", "NA", "NA", "0", "NA", "NA", "0", "NA", "0", "NA", "NA", "NA", "0", "NA", "NA", "0", "0", "NA", "NA", "NA", "0", "NA", "NA", "NA", "NA", "1", "25", "0", "NA", "NA", "32"], ["480564", "Corner,  Tottenham Hotspur. Conceded by Mat Ryan.", "32'", "Brighton & Hove Albion", "0", "0", "0", "0", "0", "0", "NA", "NA", "NA", "NA", "NA", "NA", "NA", "0", "NA", "NA", "0", "NA", "0", "0", "NA", "NA", "NA", "0", "NA", "NA", "NA", "0", "NA", "NA", "0", "NA", "0", "NA", "NA", "NA", "1", "Tottenham Hotspur", "Mat Ryan", "0", "0", "NA", "NA", "NA", "0", "NA", "NA", "NA", "NA", "1", "26", "0", "NA", "NA", "32"], ["480564", "Foul by Anthony Knockaert (Brighton and Hove Albion).", "39'", "Brighton & Hove Albion", "0", "0", "0", "0", "0", "0", "NA", "NA", "NA", "NA", "NA", "NA", "NA", "1", "Anthony Knockaert", "Brighton and Hove Albion", "0", "NA", "0", "0", "NA", "NA", "NA", "0", "NA", "NA", "NA", "0", "NA", "NA", "0", "NA", "0", "NA", "NA", "NA", "0", "NA", "NA", "0", "0", "NA", "NA", "NA", "0", "NA", "NA", "NA", "NA", "1", "27", "0", "NA", "NA", "39"], ["480564", "Son Heung-Min (Tottenham Hotspur) wins a free kick on the left wing.", "39'", "Brighton & Hove Albion", "0", "0", "0", "0", "0", "0", "NA", "NA", "NA", "NA", "NA", "NA", "NA", "0", "NA", "NA", "0", "NA", "0", "0", "NA", "NA", "NA", "0", "NA", "NA", "NA", "0", "NA", "NA", "0", "NA", "1", "Son Heung-Min", "Tottenham Hotspur", "NA", "0", "NA", "NA", "0", "0", "NA", "NA", "NA", "0", "NA", "NA", "NA", "NA", "1", "28", "0", "NA", "NA", "39"], ["480564", "Foul by Anthony Knockaert (Brighton and Hove Albion).", "45'+1'", "Brighton & Hove Albion", "0", "0", "0", "0", "0", "0", "NA", "NA", "NA", "NA", "NA", "NA", "NA", "1", "Anthony Knockaert", "Brighton and Hove Albion", "0", "NA", "0", "0", "NA", "NA", "NA", "0", "NA", "NA", "NA", "0", "NA", "NA", "0", "NA", "0", "NA", "NA", "NA", "0", "NA", "NA", "0", "0", "NA", "NA", "NA", "0", "NA", "NA", "NA", "NA", "1", "29", "1", "NA", "NA", "46"], ["480564", "Harry Kane (Tottenham Hotspur) wins a free kick in the attacking half.", "45'+1'", "Brighton & Hove Albion", "0", "0", "0", "0", "0", "0", "NA", "NA", "NA", "NA", "NA", "NA", "NA", "0", "NA", "NA", "0", "NA", "0", "0", "NA", "NA", "NA", "0", "NA", "NA", "NA", "0", "NA", "NA", "0", "NA", "1", "Harry Kane", "Tottenham Hotspur", "attacking half", "0", "NA", "NA", "0", "0", "NA", "NA", "NA", "0", "NA", "NA", "NA", "NA", "1", "30", "1", "NA", "NA", "46"], ["480564", "Delay in match Lucas Moura (Tottenham Hotspur) because of an injury.", "45'+1'", "Brighton & Hove Albion", "0", "0", "0", "0", "0", "0", "NA", "NA", "NA", "NA", "NA", "NA", "NA", "0", "NA", "NA", "0", "NA", "0", "0", "NA", "NA", "NA", "0", "NA", "NA", "NA", "0", "NA", "NA", "1", "Tottenham Hotspur", "0", "NA", "NA", "NA", "0", "NA", "NA", "0", "0", "NA", "NA", "NA", "0", "NA", "NA", "NA", "NA", "1", "31", "1", "NA", "NA", "46"], ["480564", "Delay over. They are ready to continue.", "45'+2'", "Brighton & Hove Albion", "0", "0", "0", "0", "0", "0", "NA", "NA", "NA", "NA", "NA", "NA", "NA", "0", "NA", "NA", "0", "NA", "0", "0", "NA", "NA", "NA", "0", "NA", "NA", "NA", "0", "NA", "NA", "0", "NA", "0", "NA", "NA", "NA", "0", "NA", "NA", "0", "0", "NA", "NA", "NA", "0", "NA", "NA", "NA", "NA", "1", "32", "1", "NA", "NA", "47"], ["480564", "Attempt saved. Harry Kane (Tottenham Hotspur) right footed shot from outside the box is saved in the bottom right corner. Assisted by Christian Eriksen.", "45'+3'", "Brighton & Hove Albion", "0", "0", "0", "0", "1", "0", "saved", "Harry Kane", "Tottenham Hotspur", "right", "outside the box", "the bottom right corner", "Christian Eriksen", "0", "NA", "NA", "0", "NA", "0", "0", "NA", "NA", "NA", "0", "NA", "NA", "NA", "0", "NA", "NA", "0", "NA", "0", "NA", "NA", "NA", "0", "NA", "NA", "0", "0", "NA", "NA", "NA", "0", "NA", "NA", "NA", "NA", "1", "33", "1", "NA", "NA", "48"], ["480564", "Attempt saved. Son Heung-Min (Tottenham Hotspur) right footed shot from the centre of the box is saved in the bottom right corner. Assisted by Harry Kane.", "45'+4'", "Brighton & Hove Albion", "0", "0", "0", "0", "1", "0", "saved", "Son Heung-Min", "Tottenham Hotspur", "right", "the centre of the box", "the bottom right corner", "Harry Kane", "0", "NA", "NA", "0", "NA", "0", "0", "NA", "NA", "NA", "0", "NA", "NA", "NA", "0", "NA", "NA", "0", "NA", "0", "NA", "NA", "NA", "0", "NA", "NA", "0", "0", "NA", "NA", "NA", "0", "NA", "NA", "NA", "NA", "1", "34", "1", "NA", "NA", "49"], ["480564", "Corner,  Tottenham Hotspur. Conceded by Mat Ryan.", "45'+4'", "Brighton & Hove Albion", "0", "0", "0", "0", "0", "0", "NA", "NA", "NA", "NA", "NA", "NA", "NA", "0", "NA", "NA", "0", "NA", "0", "0", "NA", "NA", "NA", "0", "NA", "NA", "NA", "0", "NA", "NA", "0", "NA", "0", "NA", "NA", "NA", "1", "Tottenham Hotspur", "Mat Ryan", "0", "0", "NA", "NA", "NA", "0", "NA", "NA", "NA", "NA", "1", "35", "1", "NA", "NA", "49"], ["480564", "First Half ends, Brighton and Hove Albion 0, Tottenham Hotspur 0.", "45'+4'", "Brighton & Hove Albion", "0", "1", "0", "0", "0", "0", "NA", "NA", "NA", "NA", "NA", "NA", "NA", "0", "NA", "NA", "0", "NA", "0", "0", "NA", "NA", "NA", "0", "NA", "NA", "NA", "0", "NA", "NA", "0", "NA", "0", "NA", "NA", "NA", "0", "NA", "NA", "0", "0", "NA", "NA", "NA", "0", "NA", "NA", "NA", "NA", "1", "36", "1", "NA", "NA", "49"], ["480564", "Second Half begins Brighton and Hove Albion 0, Tottenham Hotspur 0.", "45'", "Brighton & Hove Albion", "0", "0", "0", "1", "0", "0", "NA", "NA", "NA", "NA", "NA", "NA", "NA", "0", "NA", "NA", "0", "NA", "0", "0", "NA", "NA", "NA", "0", "NA", "NA", "NA", "0", "NA", "NA", "0", "NA", "0", "NA", "NA", "NA", "0", "NA", "NA", "0", "0", "NA", "NA", "NA", "0", "NA", "NA", "NA", "NA", "2", "37", "0", "NA", "NA", "45"], ["480564", "Goal!  Brighton and Hove Albion 0, Tottenham Hotspur 1. Harry Kane (Tottenham Hotspur) right footed shot from the centre of the box to the centre of the goal. Assisted by Son Heung-Min.", "48'", "Brighton & Hove Albion", "0", "0", "0", "0", "1", "0", "goal", "Harry Kane", "Tottenham Hotspur", "right", "the centre of the box", "centre of the goal", "Son Heung-Min", "0", "NA", "NA", "0", "NA", "0", "0", "NA", "NA", "NA", "0", "NA", "NA", "NA", "0", "NA", "NA", "0", "NA", "0", "NA", "NA", "NA", "0", "NA", "NA", "0", "0", "NA", "NA", "NA", "0", "NA", "NA", "NA", "NA", "2", "38", "0", "NA", "NA", "48"], ["480564", "Penalty Brighton and Hove Albion. José Izquierdo draws a foul in the penalty area.", "49'", "Brighton & Hove Albion", "0", "0", "0", "0", "0", "0", "NA", "NA", "NA", "NA", "NA", "NA", "NA", "0", "NA", "NA", "0", "NA", "0", "0", "NA", "NA", "NA", "0", "NA", "NA", "NA", "0", "NA", "NA", "0", "NA", "0", "NA", "NA", "NA", "0", "NA", "NA", "0", "0", "NA", "NA", "NA", "1", "Brighton and Hove Albion", "José Izquierdo", "NA", "NA", "2", "39", "0", "NA", "NA", "49"], ["480564", "Penalty conceded by Serge Aurier (Tottenham Hotspur) after a foul in the penalty area.", "49'", "Brighton & Hove Albion", "0", "0", "0", "0", "0", "0", "NA", "NA", "NA", "NA", "NA", "NA", "NA", "0", "NA", "NA", "0", "NA", "0", "0", "NA", "NA", "NA", "0", "NA", "NA", "NA", "0", "NA", "NA", "0", "NA", "0", "NA", "NA", "NA", "0", "NA", "NA", "0", "0", "NA", "NA", "NA", "1", "Tottenham Hotspur", "NA", "Serge Aurier", "Tottenham Hotspur", "2", "40", "0", "NA", "NA", "49"], ["480564", "Goal!  Brighton and Hove Albion 1, Tottenham Hotspur 1. Pascal Groß (Brighton and Hove Albion) converts the penalty with a right footed shot to the bottom left corner.", "50'", "Brighton & Hove Albion", "1", "0", "0", "0", "1", "0", "goal", "Pascal Groß", "Brighton and Hove Albion", "right", "NA", "bottom left corner", "NA", "0", "NA", "NA", "0", "NA", "0", "0", "NA", "NA", "NA", "0", "NA", "NA", "NA", "0", "NA", "NA", "0", "NA", "0", "NA", "NA", "NA", "0", "NA", "NA", "0", "0", "NA", "NA", "NA", "0", "NA", "NA", "NA", "NA", "2", "41", "0", "NA", "NA", "50"], ["480564", "Beram Kayal (Brighton and Hove Albion) wins a free kick in the defensive half.", "55'", "Brighton & Hove Albion", "1", "0", "0", "0", "0", "0", "NA", "NA", "NA", "NA", "NA", "NA", "NA", "0", "NA", "NA", "0", "NA", "0", "0", "NA", "NA", "NA", "0", "NA", "NA", "NA", "0", "NA", "NA", "0", "NA", "1", "Beram Kayal", "Brighton and Hove Albion", "defensive half", "0", "NA", "NA", "0", "0", "NA", "NA", "NA", "0", "NA", "NA", "NA", "NA", "2", "42", "0", "NA", "NA", "55"], ["480564", "Foul by Christian Eriksen (Tottenham Hotspur).", "55'", "Brighton & Hove Albion", "1", "0", "0", "0", "0", "0", "NA", "NA", "NA", "NA", "NA", "NA", "NA", "1", "Christian Eriksen", "Tottenham Hotspur", "0", "NA", "0", "0", "NA", "NA", "NA", "0", "NA", "NA", "NA", "0", "NA", "NA", "0", "NA", "0", "NA", "NA", "NA", "0", "NA", "NA", "0", "0", "NA", "NA", "NA", "0", "NA", "NA", "NA", "NA", "2", "43", "0", "NA", "NA", "55"], ["480564", "Attempt missed. Lucas Moura (Tottenham Hotspur) right footed shot from the left side of the box is close, but misses to the left. Assisted by Christian Eriksen.", "55'", "Brighton & Hove Albion", "1", "0", "0", "0", "1", "0", "missed", "Lucas Moura", "Tottenham Hotspur", "right", "the left side of the box", "close, but left", "Christian Eriksen", "0", "NA", "NA", "0", "NA", "0", "0", "NA", "NA", "NA", "0", "NA", "NA", "NA", "0", "NA", "NA", "0", "NA", "0", "NA", "NA", "NA", "0", "NA", "NA", "0", "0", "NA", "NA", "NA", "0", "NA", "NA", "NA", "NA", "2", "44", "0", "NA", "NA", "55"], ["480564", "Hand ball by Beram Kayal (Brighton and Hove Albion).", "57'", "Brighton & Hove Albion", "1", "0", "0", "0", "0", "0", "NA", "NA", "NA", "NA", "NA", "NA", "NA", "0", "NA", "NA", "0", "NA", "0", "0", "NA", "NA", "NA", "0", "NA", "NA", "NA", "0", "NA", "NA", "0", "NA", "0", "NA", "NA", "NA", "0", "NA", "NA", "0", "0", "NA", "NA", "NA", "0", "NA", "NA", "NA", "NA", "2", "45", "0", "NA", "NA", "57"], ["480564", "Attempt blocked. Christian Eriksen (Tottenham Hotspur) right footed shot from outside the box is blocked.", "58'", "Brighton & Hove Albion", "1", "0", "0", "0", "1", "0", "blocked", "Christian Eriksen", "Tottenham Hotspur", "right", "outside the box", "NA", "NA", "0", "NA", "NA", "0", "NA", "0", "0", "NA", "NA", "NA", "0", "NA", "NA", "NA", "0", "NA", "NA", "0", "NA", "0", "NA", "NA", "NA", "0", "NA", "NA", "0", "0", "NA", "NA", "NA", "0", "NA", "NA", "NA", "NA", "2", "46", "0", "NA", "NA", "58"], ["480564", "Attempt blocked. Ben Davies (Tottenham Hotspur) right footed shot from outside the box is blocked.", "58'", "Brighton & Hove Albion", "1", "0", "0", "0", "1", "0", "blocked", "Ben Davies", "Tottenham Hotspur", "right", "outside the box", "NA", "NA", "0", "NA", "NA", "0", "NA", "0", "0", "NA", "NA", "NA", "0", "NA", "NA", "NA", "0", "NA", "NA", "0", "NA", "0", "NA", "NA", "NA", "0", "NA", "NA", "0", "0", "NA", "NA", "NA", "0", "NA", "NA", "NA", "NA", "2", "47", "0", "NA", "NA", "58"], ["480564", "Foul by Dale Stephens (Brighton and Hove Albion).", "65'", "Brighton & Hove Albion", "1", "0", "0", "0", "0", "0", "NA", "NA", "NA", "NA", "NA", "NA", "NA", "1", "Dale Stephens", "Brighton and Hove Albion", "0", "NA", "0", "0", "NA", "NA", "NA", "0", "NA", "NA", "NA", "0", "NA", "NA", "0", "NA", "0", "NA", "NA", "NA", "0", "NA", "NA", "0", "0", "NA", "NA", "NA", "0", "NA", "NA", "NA", "NA", "2", "48", "0", "NA", "NA", "65"], ["480564", "Son Heung-Min (Tottenham Hotspur) wins a free kick in the attacking half.", "65'", "Brighton & Hove Albion", "1", "0", "0", "0", "0", "0", "NA", "NA", "NA", "NA", "NA", "NA", "NA", "0", "NA", "NA", "0", "NA", "0", "0", "NA", "NA", "NA", "0", "NA", "NA", "NA", "0", "NA", "NA", "0", "NA", "1", "Son Heung-Min", "Tottenham Hotspur", "attacking half", "0", "NA", "NA", "0", "0", "NA", "NA", "NA", "0", "NA", "NA", "NA", "NA", "2", "49", "0", "NA", "NA", "65"], ["480564", "Attempt missed. Son Heung-Min (Tottenham Hotspur) right footed shot from outside the box misses to the right. Assisted by Christian Eriksen.", "69'", "Brighton & Hove Albion", "1", "0", "0", "0", "1", "0", "missed", "Son Heung-Min", "Tottenham Hotspur", "right", "outside the box", "right", "Christian Eriksen", "0", "NA", "NA", "0", "NA", "0", "0", "NA", "NA", "NA", "0", "NA", "NA", "NA", "0", "NA", "NA", "0", "NA", "0", "NA", "NA", "NA", "0", "NA", "NA", "0", "0", "NA", "NA", "NA", "0", "NA", "NA", "NA", "NA", "2", "50", "0", "NA", "NA", "69"], ["480564", "Attempt blocked. Christian Eriksen (Tottenham Hotspur) left footed shot from outside the box is blocked. Assisted by Serge Aurier.", "72'", "Brighton & Hove Albion", "1", "0", "0", "0", "1", "0", "blocked", "Christian Eriksen", "Tottenham Hotspur", "left", "outside the box", "NA", "Serge Aurier", "0", "NA", "NA", "0", "NA", "0", "0", "NA", "NA", "NA", "0", "NA", "NA", "NA", "0", "NA", "NA", "0", "NA", "0", "NA", "NA", "NA", "0", "NA", "NA", "0", "0", "NA", "NA", "NA", "0", "NA", "NA", "NA", "NA", "2", "51", "0", "NA", "NA", "72"], ["480564", "Corner,  Tottenham Hotspur. Conceded by Shane Duffy.", "73'", "Brighton & Hove Albion", "1", "0", "0", "0", "0", "0", "NA", "NA", "NA", "NA", "NA", "NA", "NA", "0", "NA", "NA", "0", "NA", "0", "0", "NA", "NA", "NA", "0", "NA", "NA", "NA", "0", "NA", "NA", "0", "NA", "0", "NA", "NA", "NA", "1", "Tottenham Hotspur", "Shane Duffy", "0", "0", "NA", "NA", "NA", "0", "NA", "NA", "NA", "NA", "2", "52", "0", "NA", "NA", "73"], ["480564", "Attempt missed. Toby Alderweireld (Tottenham Hotspur) left footed shot from the left side of the box is close, but misses to the left following a corner.", "73'", "Brighton & Hove Albion", "1", "0", "0", "0", "1", "0", "missed", "Toby Alderweireld", "Tottenham Hotspur", "left", "the left side of the box", "close, but left", "NA", "0", "NA", "NA", "0", "NA", "1", "0", "NA", "NA", "NA", "0", "NA", "NA", "NA", "0", "NA", "NA", "0", "NA", "0", "NA", "NA", "NA", "0", "NA", "NA", "0", "0", "NA", "NA", "NA", "0", "NA", "NA", "NA", "NA", "2", "53", "0", "NA", "NA", "73"], ["480564", "Substitution, Brighton and Hove Albion. Leonardo Ulloa replaces Glenn Murray.", "74'", "Brighton & Hove Albion", "1", "0", "0", "0", "0", "0", "NA", "NA", "NA", "NA", "NA", "NA", "NA", "0", "NA", "NA", "0", "NA", "0", "0", "NA", "NA", "NA", "0", "NA", "NA", "NA", "0", "NA", "NA", "0", "NA", "0", "NA", "NA", "NA", "0", "NA", "NA", "1", "0", "Brighton and Hove Albion", "Leonardo Ulloa", "Glenn Murray", "0", "NA", "NA", "NA", "NA", "2", "54", "0", "NA", "NA", "74"], ["480564", "Substitution, Tottenham Hotspur. Erik Lamela replaces Lucas Moura.", "74'", "Brighton & Hove Albion", "1", "0", "0", "0", "0", "0", "NA", "NA", "NA", "NA", "NA", "NA", "NA", "0", "NA", "NA", "0", "NA", "0", "0", "NA", "NA", "NA", "0", "NA", "NA", "NA", "0", "NA", "NA", "0", "NA", "0", "NA", "NA", "NA", "0", "NA", "NA", "1", "0", "Tottenham Hotspur", "Erik Lamela", "Lucas Moura", "0", "NA", "NA", "NA", "NA", "2", "55", "0", "NA", "NA", "74"], ["480564", "Substitution, Tottenham Hotspur. Mousa Dembélé replaces Moussa Sissoko.", "74'", "Brighton & Hove Albion", "1", "0", "0", "0", "0", "0", "NA", "NA", "NA", "NA", "NA", "NA", "NA", "0", "NA", "NA", "0", "NA", "0", "0", "NA", "NA", "NA", "0", "NA", "NA", "NA", "0", "NA", "NA", "0", "NA", "0", "NA", "NA", "NA", "0", "NA", "NA", "1", "0", "Tottenham Hotspur", "Mousa Dembélé", "Moussa Sissoko", "0", "NA", "NA", "NA", "NA", "2", "56", "0", "NA", "NA", "74"], ["480564", "Attempt saved. José Izquierdo (Brighton and Hove Albion) right footed shot from the left side of the box is saved in the centre of the goal. Assisted by Anthony Knockaert.", "75'", "Brighton & Hove Albion", "1", "0", "0", "0", "1", "0", "saved", "José Izquierdo", "Brighton and Hove Albion", "right", "the left side of the box", "the centre of the goal", "Anthony Knockaert", "0", "NA", "NA", "0", "NA", "0", "0", "NA", "NA", "NA", "0", "NA", "NA", "NA", "0", "NA", "NA", "0", "NA", "0", "NA", "NA", "NA", "0", "NA", "NA", "0", "0", "NA", "NA", "NA", "0", "NA", "NA", "NA", "NA", "2", "57", "0", "NA", "NA", "75"], ["480564", "Substitution, Brighton and Hove Albion. Solly March replaces José Izquierdo.", "77'", "Brighton & Hove Albion", "1", "0", "0", "0", "0", "0", "NA", "NA", "NA", "NA", "NA", "NA", "NA", "0", "NA", "NA", "0", "NA", "0", "0", "NA", "NA", "NA", "0", "NA", "NA", "NA", "0", "NA", "NA", "0", "NA", "0", "NA", "NA", "NA", "0", "NA", "NA", "1", "0", "Brighton and Hove Albion", "Solly March", "José Izquierdo", "0", "NA", "NA", "NA", "NA", "2", "58", "0", "NA", "NA", "77"], ["480564", "Attempt missed. Harry Kane (Tottenham Hotspur) right footed shot from outside the box misses to the left. Assisted by Ben Davies.", "85'", "Brighton & Hove Albion", "1", "0", "0", "0", "1", "0", "missed", "Harry Kane", "Tottenham Hotspur", "right", "outside the box", "left", "Ben Davies", "0", "NA", "NA", "0", "NA", "0", "0", "NA", "NA", "NA", "0", "NA", "NA", "NA", "0", "NA", "NA", "0", "NA", "0", "NA", "NA", "NA", "0", "NA", "NA", "0", "0", "NA", "NA", "NA", "0", "NA", "NA", "NA", "NA", "2", "59", "0", "NA", "NA", "85"], ["480564", "Substitution, Tottenham Hotspur. Fernando Llorente replaces Harry Kane.", "85'", "Brighton & Hove Albion", "1", "0", "0", "0", "0", "0", "NA", "NA", "NA", "NA", "NA", "NA", "NA", "0", "NA", "NA", "0", "NA", "0", "0", "NA", "NA", "NA", "0", "NA", "NA", "NA", "0", "NA", "NA", "0", "NA", "0", "NA", "NA", "NA", "0", "NA", "NA", "1", "0", "Tottenham Hotspur", "Fernando Llorente", "Harry Kane", "0", "NA", "NA", "NA", "NA", "2", "60", "0", "NA", "NA", "85"], ["480564", "Attempt missed. Pascal Groß (Brighton and Hove Albion) right footed shot from the left side of the box is too high. Assisted by Leonardo Ulloa.", "86'", "Brighton & Hove Albion", "1", "0", "0", "0", "1", "0", "missed", "Pascal Groß", "Brighton and Hove Albion", "right", "the left side of the box", "too high", "Leonardo Ulloa", "0", "NA", "NA", "0", "NA", "0", "0", "NA", "NA", "NA", "0", "NA", "NA", "NA", "0", "NA", "NA", "0", "NA", "0", "NA", "NA", "NA", "0", "NA", "NA", "0", "0", "NA", "NA", "NA", "0", "NA", "NA", "NA", "NA", "2", "61", "0", "NA", "NA", "86"], ["480564", "Attempt saved. Erik Lamela (Tottenham Hotspur) right footed shot from the centre of the box is saved in the top centre of the goal.", "88'", "Brighton & Hove Albion", "1", "0", "0", "0", "1", "0", "saved", "Erik Lamela", "Tottenham Hotspur", "right", "the centre of the box", "the top centre of the goal", "NA", "0", "NA", "NA", "0", "NA", "0", "0", "NA", "NA", "NA", "0", "NA", "NA", "NA", "0", "NA", "NA", "0", "NA", "0", "NA", "NA", "NA", "0", "NA", "NA", "0", "0", "NA", "NA", "NA", "0", "NA", "NA", "NA", "NA", "2", "62", "0", "NA", "NA", "88"], ["480564", "Corner,  Brighton and Hove Albion. Conceded by Toby Alderweireld.", "89'", "Brighton & Hove Albion", "1", "0", "0", "0", "0", "0", "NA", "NA", "NA", "NA", "NA", "NA", "NA", "0", "NA", "NA", "0", "NA", "0", "0", "NA", "NA", "NA", "0", "NA", "NA", "NA", "0", "NA", "NA", "0", "NA", "0", "NA", "NA", "NA", "1", "Brighton and Hove Albion", "Toby Alderweireld", "0", "0", "NA", "NA", "NA", "0", "NA", "NA", "NA", "NA", "2", "63", "0", "NA", "NA", "89"], ["480564", "Corner,  Brighton and Hove Albion. Conceded by Toby Alderweireld.", "89'", "Brighton & Hove Albion", "1", "0", "0", "0", "0", "0", "NA", "NA", "NA", "NA", "NA", "NA", "NA", "0", "NA", "NA", "0", "NA", "0", "0", "NA", "NA", "NA", "0", "NA", "NA", "NA", "0", "NA", "NA", "0", "NA", "0", "NA", "NA", "NA", "1", "Brighton and Hove Albion", "Toby Alderweireld", "0", "0", "NA", "NA", "NA", "0", "NA", "NA", "NA", "NA", "2", "64", "0", "NA", "NA", "89"], ["480564", "Corner,  Tottenham Hotspur. Conceded by Bruno.", "90'+2'", "Brighton & Hove Albion", "1", "0", "0", "0", "0", "0", "NA", "NA", "NA", "NA", "NA", "NA", "NA", "0", "NA", "NA", "0", "NA", "0", "0", "NA", "NA", "NA", "0", "NA", "NA", "NA", "0", "NA", "NA", "0", "NA", "0", "NA", "NA", "NA", "1", "Tottenham Hotspur", "Bruno", "0", "0", "NA", "NA", "NA", "0", "NA", "NA", "NA", "NA", "2", "65", "1", "NA", "NA", "92"], ["480564", "Beram Kayal (Brighton and Hove Albion) wins a free kick in the defensive half.", "90'+3'", "Brighton & Hove Albion", "1", "0", "0", "0", "0", "0", "NA", "NA", "NA", "NA", "NA", "NA", "NA", "0", "NA", "NA", "0", "NA", "0", "0", "NA", "NA", "NA", "0", "NA", "NA", "NA", "0", "NA", "NA", "0", "NA", "1", "Beram Kayal", "Brighton and Hove Albion", "defensive half", "0", "NA", "NA", "0", "0", "NA", "NA", "NA", "0", "NA", "NA", "NA", "NA", "2", "66", "1", "NA", "NA", "93"], ["480564", "Foul by Erik Lamela (Tottenham Hotspur).", "90'+3'", "Brighton & Hove Albion", "1", "0", "0", "0", "0", "0", "NA", "NA", "NA", "NA", "NA", "NA", "NA", "1", "Erik Lamela", "Tottenham Hotspur", "0", "NA", "0", "0", "NA", "NA", "NA", "0", "NA", "NA", "NA", "0", "NA", "NA", "0", "NA", "0", "NA", "NA", "NA", "0", "NA", "NA", "0", "0", "NA", "NA", "NA", "0", "NA", "NA", "NA", "NA", "2", "67", "1", "NA", "NA", "93"], ["480564", "Second Half ends, Brighton and Hove Albion 1, Tottenham Hotspur 1.", "90'+4'", "Brighton & Hove Albion", "1", "1", "0", "0", "0", "0", "NA", "NA", "NA", "NA", "NA", "NA", "NA", "0", "NA", "NA", "0", "NA", "0", "0", "NA", "NA", "NA", "0", "NA", "NA", "NA", "0", "NA", "NA", "0", "NA", "0", "NA", "NA", "NA", "0", "NA", "NA", "0", "0", "NA", "NA", "NA", "0", "NA", "NA", "NA", "NA", "2", "68", "1", "NA", "NA", "94"], ["480564", "Match ends, Brighton and Hove Albion 1, Tottenham Hotspur 1.", "90'+4'", "Brighton & Hove Albion", "1", "0", "1", "0", "0", "0", "NA", "NA", "NA", "NA", "NA", "NA", "NA", "0", "NA", "NA", "0", "NA", "0", "0", "NA", "NA", "NA", "0", "NA", "NA", "NA", "0", "NA", "NA", "0", "NA", "0", "NA", "NA", "NA", "0", "NA", "NA", "0", "0", "NA", "NA", "NA", "0", "NA", "NA", "NA", "NA", "2", "69", "1", "NA", "NA", "94"]], "Lineup": {"Home Player 9": "Mathew Ryan", "Home Player 8": "Glenn Murray", "Home Player 5": "Jose Izquierdo", "Home Player 4": "Pascal Gross", "Home Player 7": "Anthony Knockaert", "Home Player 6": "Biram Kayal", "Home Player 1": "Gaetan Bong", "Home Player 3": "Lewis Dunk", "Home Player 2": "Shane Duffy", "Away Player 10": "Jan Vertonghen", "Away Player 11": "Victor Wanyama", "Away Player 8": "Moussa Sissoko", "Away Player 9": "Son Heung-min", "Away Player 1": "Toby Alderweireld", "Away Player 2": "Serge Aurier", "Away Player 3": "Ben Davies", "Away Player 4": "Christian Eriksen", "Away Player 5": "Harry Kane", "Away Player 6": "Hugo Lloris", "Away Player 7": "Lucas", "Game ID": "g_1_jwiTAPKL", "Home Player 11": "Dale Stephens", "Home Player 10": "Bruno Saltor"}}