{"Stats": {"Full Time Result": "H", "Away Team Corners": 1, "Referee": "A Taylor", "Home Team Fouls Committed": 5, "Away Team Shots": 4, "Away Team Red Cards": 0, "Home Team Red Cards": 0, "Half Time Away Team Goals": 0, "Full Time Home Team Goals": 5, "Away Team Yellow Cards": 0, "Away Team Shots on Target": 1, "Half Time Home Team Goals": 2, "Half Time Result": "H", "Away Team Fouls Committed": 4, "Home Team Yellow Cards": 1, "Home Team Shots": 13, "Div": "E0", "Home Team Corners": 6, "Home Team Shots on Target": 10, "Full Time Away Team Goals": 0}, "Description": "Offside, Watford. José Holebas tries a through ball, but Richarlison is caught offside. at minute 2. Goal!  Liverpool 1, Watford 0. Mohamed Salah (Liverpool) right footed shot from the right side of the box to the bottom right corner. Assisted by Sadio Mané. at minute 4. Corner,  Liverpool. Conceded by Miguel Britos. at minute 12. Offside, Liverpool. Mohamed Salah tries a through ball, but Roberto Firmino is caught offside. at minute 16. Foul by Adrian Mariappa (Watford). at minute 19. Sadio Mané (Liverpool) wins a free kick in the attacking half. at minute 19. Corner,  Liverpool. Conceded by José Holebas. at minute 20. Corner,  Liverpool. Conceded by Adrian Mariappa. at minute 22. Attempt blocked. Georginio Wijnaldum (Liverpool) left footed shot from outside the box is blocked. at minute 23. Substitution, Liverpool. James Milner replaces Emre Can because of an injury. at minute 27. Etienne Capoue (Watford) wins a free kick in the attacking half. at minute 30. Foul by Georginio Wijnaldum (Liverpool). at minute 30. Offside, Watford. José Holebas tries a through ball, but Sebastian Prödl is caught offside. at minute 31. Offside, Liverpool. Joel Matip tries a through ball, but Roberto Firmino is caught offside. at minute 33. Corner,  Liverpool. Conceded by Sebastian Prödl. at minute 34. Offside, Liverpool. Jordan Henderson tries a through ball, but Sadio Mané is caught offside. at minute 36. Attempt saved. Richarlison (Watford) header from the centre of the box is saved in the top centre of the goal. Assisted by Roberto Pereyra with a cross. at minute 37. Attempt saved. Roberto Firmino (Liverpool) left footed shot from the centre of the box is saved in the top left corner. Assisted by Mohamed Salah. at minute 39. Corner,  Liverpool. Conceded by Orestis Karnezis. at minute 39. Corner,  Liverpool. Conceded by Miguel Britos. at minute 40. Goal!  Liverpool 2, Watford 0. Mohamed Salah (Liverpool) right footed shot from very close range to the centre of the goal. Assisted by Andrew Robertson with a cross. at minute 43. Offside, Watford. Kiko Femenía tries a through ball, but Abdoulaye Doucouré is caught offside. at minute 45. First Half ends, Liverpool 2, Watford 0. at minute 47. Second Half begins Liverpool 2, Watford 0. at minute 45. Attempt saved. Roberto Firmino (Liverpool) header from the centre of the box is saved in the centre of the goal. Assisted by Jordan Henderson with a cross. at minute 46. Offside, Liverpool. Jordan Henderson tries a through ball, but Mohamed Salah is caught offside. at minute 47. Goal!  Liverpool 3, Watford 0. Roberto Firmino (Liverpool) right footed shot from very close range to the bottom left corner. Assisted by Mohamed Salah with a cross. at minute 49. Etienne Capoue (Watford) wins a free kick in the defensive half. at minute 51. Foul by James Milner (Liverpool). at minute 51. Attempt missed. José Holebas (Watford) right footed shot from outside the box is close, but misses to the left. Assisted by Miguel Britos. at minute 51. Foul by Joseph Gomez (Liverpool). at minute 51. Richarlison (Watford) wins a free kick on the left wing. at minute 51. Joseph Gomez (Liverpool) is shown the yellow card for a bad foul. at minute 52. Roberto Pereyra (Watford) hits the bar with a right footed shot from a difficult angle and long range on the left from a direct free kick. at minute 52. Foul by Mohamed Salah (Liverpool). at minute 59. José Holebas (Watford) wins a free kick in the defensive half. at minute 59. Attempt missed. Roberto Firmino (Liverpool) header from the centre of the box misses to the left. Assisted by Joseph Gomez with a cross. at minute 61. Substitution, Watford. Will Hughes replaces Richarlison. at minute 65. Substitution, Watford. Stefano Okaka replaces Troy Deeney. at minute 70. Substitution, Liverpool. Alex Oxlade-Chamberlain replaces Georginio Wijnaldum. at minute 71. Foul by Adrian Mariappa (Watford). at minute 75. Sadio Mané (Liverpool) wins a free kick in the attacking half. at minute 75. Attempt saved. Alex Oxlade-Chamberlain (Liverpool) right footed shot from outside the box is saved in the centre of the goal. at minute 77. Goal!  Liverpool 4, Watford 0. Mohamed Salah (Liverpool) left footed shot from the centre of the box to the bottom left corner. Assisted by Sadio Mané. at minute 77. Foul by Roberto Firmino (Liverpool). at minute 79. Will Hughes (Watford) wins a free kick in the defensive half. at minute 79. Substitution, Liverpool. Danny Ings replaces Roberto Firmino. at minute 79. Attempt blocked. Stefano Okaka (Watford) right footed shot from the left side of the box is blocked. Assisted by Abdoulaye Doucouré with a through ball. at minute 80. Substitution, Watford. Daryl Janmaat replaces Miguel Britos. at minute 81. Attempt saved. Danny Ings (Liverpool) right footed shot from the centre of the box is saved in the top centre of the goal. Assisted by Sadio Mané with a through ball. at minute 84. Attempt blocked. James Milner (Liverpool) right footed shot from outside the box is blocked. at minute 84. Offside, Liverpool. James Milner tries a through ball, but Danny Ings is caught offside. at minute 84. Attempt saved. Danny Ings (Liverpool) right footed shot from the centre of the box is saved in the bottom right corner. Assisted by Mohamed Salah. at minute 85. Goal!  Liverpool 5, Watford 0. Mohamed Salah (Liverpool) left footed shot from the centre of the box to the top right corner. at minute 85. Foul by Roberto Pereyra (Watford). at minute 88. Virgil van Dijk (Liverpool) wins a free kick in the defensive half. at minute 88. Foul by Stefano Okaka (Watford). at minute 88. Jordan Henderson (Liverpool) wins a free kick in the defensive half. at minute 88. Offside, Liverpool. James Milner tries a through ball, but Danny Ings is caught offside. at minute 89. Corner,  Watford. Conceded by Joel Matip. at minute 92. Second Half ends, Liverpool 5, Watford 0. at minute 93. Match ends, Liverpool 5, Watford 0. at minute 93. ", "Home Team": "Liverpool", "Away Team": "Watford", "Date": "2018-03-17", "Commentary": [["480604", "First Half begins.", "-", "Liverpool", "0", "0", "0", "1", "0", "0", "NA", "NA", "NA", "NA", "NA", "NA", "NA", "0", "NA", "NA", "0", "NA", "0", "0", "NA", "NA", "NA", "0", "NA", "NA", "NA", "0", "NA", "NA", "0", "NA", "0", "NA", "NA", "NA", "0", "NA", "NA", "0", "0", "NA", "NA", "NA", "0", "NA", "NA", "NA", "NA", "1", "1", "0", "NA", "NA", "NA"], ["480604", "Lineups are announced and players are warming up.", "-", "Liverpool", "0", "0", "0", "0", "0", "0", "NA", "NA", "NA", "NA", "NA", "NA", "NA", "0", "NA", "NA", "0", "NA", "0", "0", "NA", "NA", "NA", "0", "NA", "NA", "NA", "0", "NA", "NA", "0", "NA", "0", "NA", "NA", "NA", "0", "NA", "NA", "0", "0", "NA", "NA", "NA", "0", "NA", "NA", "NA", "NA", "1", "2", "0", "NA", "NA", "NA"], ["480604", "Offside, Watford. José Holebas tries a through ball, but Richarlison is caught offside.", "2'", "Liverpool", "0", "0", "0", "0", "0", "0", "NA", "NA", "NA", "NA", "NA", "NA", "NA", "0", "NA", "NA", "0", "NA", "0", "1", "Watford", "Richarlison", "José Holebas", "0", "NA", "NA", "NA", "0", "NA", "NA", "0", "NA", "0", "NA", "NA", "NA", "0", "NA", "NA", "0", "0", "NA", "NA", "NA", "0", "NA", "NA", "NA", "NA", "1", "3", "0", "NA", "NA", "2"], ["480604", "Goal!  Liverpool 1, Watford 0. Mohamed Salah (Liverpool) right footed shot from the right side of the box to the bottom right corner. Assisted by Sadio Mané.", "4'", "Liverpool", "1", "0", "0", "0", "1", "0", "goal", "Mohamed Salah", "Liverpool", "right", "the right side of the box", "bottom right corner", "Sadio Mané", "0", "NA", "NA", "0", "NA", "0", "0", "NA", "NA", "NA", "0", "NA", "NA", "NA", "0", "NA", "NA", "0", "NA", "0", "NA", "NA", "NA", "0", "NA", "NA", "0", "0", "NA", "NA", "NA", "0", "NA", "NA", "NA", "NA", "1", "4", "0", "NA", "NA", "4"], ["480604", "Corner,  Liverpool. Conceded by Miguel Britos.", "12'", "Liverpool", "1", "0", "0", "0", "0", "0", "NA", "NA", "NA", "NA", "NA", "NA", "NA", "0", "NA", "NA", "0", "NA", "0", "0", "NA", "NA", "NA", "0", "NA", "NA", "NA", "0", "NA", "NA", "0", "NA", "0", "NA", "NA", "NA", "1", "Liverpool", "Miguel Britos", "0", "0", "NA", "NA", "NA", "0", "NA", "NA", "NA", "NA", "1", "5", "0", "NA", "NA", "12"], ["480604", "Offside, Liverpool. Mohamed Salah tries a through ball, but Roberto Firmino is caught offside.", "16'", "Liverpool", "1", "0", "0", "0", "0", "0", "NA", "NA", "NA", "NA", "NA", "NA", "NA", "0", "NA", "NA", "0", "NA", "0", "1", "Liverpool", "Roberto Firmino", "Mohamed Salah", "0", "NA", "NA", "NA", "0", "NA", "NA", "0", "NA", "0", "NA", "NA", "NA", "0", "NA", "NA", "0", "0", "NA", "NA", "NA", "0", "NA", "NA", "NA", "NA", "1", "6", "0", "NA", "NA", "16"], ["480604", "Foul by Adrian Mariappa (Watford).", "19'", "Liverpool", "1", "0", "0", "0", "0", "0", "NA", "NA", "NA", "NA", "NA", "NA", "NA", "1", "Adrian Mariappa", "Watford", "0", "NA", "0", "0", "NA", "NA", "NA", "0", "NA", "NA", "NA", "0", "NA", "NA", "0", "NA", "0", "NA", "NA", "NA", "0", "NA", "NA", "0", "0", "NA", "NA", "NA", "0", "NA", "NA", "NA", "NA", "1", "7", "0", "NA", "NA", "19"], ["480604", "Sadio Mané (Liverpool) wins a free kick in the attacking half.", "19'", "Liverpool", "1", "0", "0", "0", "0", "0", "NA", "NA", "NA", "NA", "NA", "NA", "NA", "0", "NA", "NA", "0", "NA", "0", "0", "NA", "NA", "NA", "0", "NA", "NA", "NA", "0", "NA", "NA", "0", "NA", "1", "Sadio Mané", "Liverpool", "attacking half", "0", "NA", "NA", "0", "0", "NA", "NA", "NA", "0", "NA", "NA", "NA", "NA", "1", "8", "0", "NA", "NA", "19"], ["480604", "Corner,  Liverpool. Conceded by José Holebas.", "20'", "Liverpool", "1", "0", "0", "0", "0", "0", "NA", "NA", "NA", "NA", "NA", "NA", "NA", "0", "NA", "NA", "0", "NA", "0", "0", "NA", "NA", "NA", "0", "NA", "NA", "NA", "0", "NA", "NA", "0", "NA", "0", "NA", "NA", "NA", "1", "Liverpool", "José Holebas", "0", "0", "NA", "NA", "NA", "0", "NA", "NA", "NA", "NA", "1", "9", "0", "NA", "NA", "20"], ["480604", "Corner,  Liverpool. Conceded by Adrian Mariappa.", "22'", "Liverpool", "1", "0", "0", "0", "0", "0", "NA", "NA", "NA", "NA", "NA", "NA", "NA", "0", "NA", "NA", "0", "NA", "0", "0", "NA", "NA", "NA", "0", "NA", "NA", "NA", "0", "NA", "NA", "0", "NA", "0", "NA", "NA", "NA", "1", "Liverpool", "Adrian Mariappa", "0", "0", "NA", "NA", "NA", "0", "NA", "NA", "NA", "NA", "1", "10", "0", "NA", "NA", "22"], ["480604", "Attempt blocked. Georginio Wijnaldum (Liverpool) left footed shot from outside the box is blocked.", "23'", "Liverpool", "1", "0", "0", "0", "1", "0", "blocked", "Georginio Wijnaldum", "Liverpool", "left", "outside the box", "NA", "NA", "0", "NA", "NA", "0", "NA", "0", "0", "NA", "NA", "NA", "0", "NA", "NA", "NA", "0", "NA", "NA", "0", "NA", "0", "NA", "NA", "NA", "0", "NA", "NA", "0", "0", "NA", "NA", "NA", "0", "NA", "NA", "NA", "NA", "1", "11", "0", "NA", "NA", "23"], ["480604", "Substitution, Liverpool. James Milner replaces Emre Can because of an injury.", "27'", "Liverpool", "1", "0", "0", "0", "0", "0", "NA", "NA", "NA", "NA", "NA", "NA", "NA", "0", "NA", "NA", "0", "NA", "0", "0", "NA", "NA", "NA", "0", "NA", "NA", "NA", "0", "NA", "NA", "0", "NA", "0", "NA", "NA", "NA", "0", "NA", "NA", "1", "1", "Liverpool", "James Milner", "Emre Can", "0", "NA", "NA", "NA", "NA", "1", "12", "0", "NA", "NA", "27"], ["480604", "Etienne Capoue (Watford) wins a free kick in the attacking half.", "30'", "Liverpool", "1", "0", "0", "0", "0", "0", "NA", "NA", "NA", "NA", "NA", "NA", "NA", "0", "NA", "NA", "0", "NA", "0", "0", "NA", "NA", "NA", "0", "NA", "NA", "NA", "0", "NA", "NA", "0", "NA", "1", "Etienne Capoue", "Watford", "attacking half", "0", "NA", "NA", "0", "0", "NA", "NA", "NA", "0", "NA", "NA", "NA", "NA", "1", "13", "0", "NA", "NA", "30"], ["480604", "Foul by Georginio Wijnaldum (Liverpool).", "30'", "Liverpool", "1", "0", "0", "0", "0", "0", "NA", "NA", "NA", "NA", "NA", "NA", "NA", "1", "Georginio Wijnaldum", "Liverpool", "0", "NA", "0", "0", "NA", "NA", "NA", "0", "NA", "NA", "NA", "0", "NA", "NA", "0", "NA", "0", "NA", "NA", "NA", "0", "NA", "NA", "0", "0", "NA", "NA", "NA", "0", "NA", "NA", "NA", "NA", "1", "14", "0", "NA", "NA", "30"], ["480604", "Offside, Watford. José Holebas tries a through ball, but Sebastian Prödl is caught offside.", "31'", "Liverpool", "1", "0", "0", "0", "0", "0", "NA", "NA", "NA", "NA", "NA", "NA", "NA", "0", "NA", "NA", "0", "NA", "0", "1", "Watford", "Sebastian Prödl", "José Holebas", "0", "NA", "NA", "NA", "0", "NA", "NA", "0", "NA", "0", "NA", "NA", "NA", "0", "NA", "NA", "0", "0", "NA", "NA", "NA", "0", "NA", "NA", "NA", "NA", "1", "15", "0", "NA", "NA", "31"], ["480604", "Offside, Liverpool. Joel Matip tries a through ball, but Roberto Firmino is caught offside.", "33'", "Liverpool", "1", "0", "0", "0", "0", "0", "NA", "NA", "NA", "NA", "NA", "NA", "NA", "0", "NA", "NA", "0", "NA", "0", "1", "Liverpool", "Roberto Firmino", "Joel Matip", "0", "NA", "NA", "NA", "0", "NA", "NA", "0", "NA", "0", "NA", "NA", "NA", "0", "NA", "NA", "0", "0", "NA", "NA", "NA", "0", "NA", "NA", "NA", "NA", "1", "16", "0", "NA", "NA", "33"], ["480604", "Corner,  Liverpool. Conceded by Sebastian Prödl.", "34'", "Liverpool", "1", "0", "0", "0", "0", "0", "NA", "NA", "NA", "NA", "NA", "NA", "NA", "0", "NA", "NA", "0", "NA", "0", "0", "NA", "NA", "NA", "0", "NA", "NA", "NA", "0", "NA", "NA", "0", "NA", "0", "NA", "NA", "NA", "1", "Liverpool", "Sebastian Prödl", "0", "0", "NA", "NA", "NA", "0", "NA", "NA", "NA", "NA", "1", "17", "0", "NA", "NA", "34"], ["480604", "Offside, Liverpool. Jordan Henderson tries a through ball, but Sadio Mané is caught offside.", "36'", "Liverpool", "1", "0", "0", "0", "0", "0", "NA", "NA", "NA", "NA", "NA", "NA", "NA", "0", "NA", "NA", "0", "NA", "0", "1", "Liverpool", "Sadio Mané", "Jordan Henderson", "0", "NA", "NA", "NA", "0", "NA", "NA", "0", "NA", "0", "NA", "NA", "NA", "0", "NA", "NA", "0", "0", "NA", "NA", "NA", "0", "NA", "NA", "NA", "NA", "1", "18", "0", "NA", "NA", "36"], ["480604", "Attempt saved. Richarlison (Watford) header from the centre of the box is saved in the top centre of the goal. Assisted by Roberto Pereyra with a cross.", "37'", "Liverpool", "1", "0", "0", "0", "1", "0", "saved", "Richarlison", "Watford", "header", "the centre of the box", "the top centre of the goal", "Roberto Pereyra", "0", "NA", "NA", "0", "cross", "0", "0", "NA", "NA", "NA", "0", "NA", "NA", "NA", "0", "NA", "NA", "0", "NA", "0", "NA", "NA", "NA", "0", "NA", "NA", "0", "0", "NA", "NA", "NA", "0", "NA", "NA", "NA", "NA", "1", "19", "0", "NA", "NA", "37"], ["480604", "Attempt saved. Roberto Firmino (Liverpool) left footed shot from the centre of the box is saved in the top left corner. Assisted by Mohamed Salah.", "39'", "Liverpool", "1", "0", "0", "0", "1", "0", "saved", "Roberto Firmino", "Liverpool", "left", "the centre of the box", "the top left corner", "Mohamed Salah", "0", "NA", "NA", "0", "NA", "0", "0", "NA", "NA", "NA", "0", "NA", "NA", "NA", "0", "NA", "NA", "0", "NA", "0", "NA", "NA", "NA", "0", "NA", "NA", "0", "0", "NA", "NA", "NA", "0", "NA", "NA", "NA", "NA", "1", "20", "0", "NA", "NA", "39"], ["480604", "Corner,  Liverpool. Conceded by Orestis Karnezis.", "39'", "Liverpool", "1", "0", "0", "0", "0", "0", "NA", "NA", "NA", "NA", "NA", "NA", "NA", "0", "NA", "NA", "0", "NA", "0", "0", "NA", "NA", "NA", "0", "NA", "NA", "NA", "0", "NA", "NA", "0", "NA", "0", "NA", "NA", "NA", "1", "Liverpool", "Orestis Karnezis", "0", "0", "NA", "NA", "NA", "0", "NA", "NA", "NA", "NA", "1", "21", "0", "NA", "NA", "39"], ["480604", "Corner,  Liverpool. Conceded by Miguel Britos.", "40'", "Liverpool", "1", "0", "0", "0", "0", "0", "NA", "NA", "NA", "NA", "NA", "NA", "NA", "0", "NA", "NA", "0", "NA", "0", "0", "NA", "NA", "NA", "0", "NA", "NA", "NA", "0", "NA", "NA", "0", "NA", "0", "NA", "NA", "NA", "1", "Liverpool", "Miguel Britos", "0", "0", "NA", "NA", "NA", "0", "NA", "NA", "NA", "NA", "1", "22", "0", "NA", "NA", "40"], ["480604", "Goal!  Liverpool 2, Watford 0. Mohamed Salah (Liverpool) right footed shot from very close range to the centre of the goal. Assisted by Andrew Robertson with a cross.", "43'", "Liverpool", "2", "0", "0", "0", "1", "0", "goal", "Mohamed Salah", "Liverpool", "right", "right shot very close range", "centre of the goal", "Andrew Robertson", "0", "NA", "NA", "0", "cross", "0", "0", "NA", "NA", "NA", "0", "NA", "NA", "NA", "0", "NA", "NA", "0", "NA", "0", "NA", "NA", "NA", "0", "NA", "NA", "0", "0", "NA", "NA", "NA", "0", "NA", "NA", "NA", "NA", "1", "23", "0", "NA", "NA", "43"], ["480604", "Offside, Watford. Kiko Femenía tries a through ball, but Abdoulaye Doucouré is caught offside.", "45'", "Liverpool", "2", "0", "0", "0", "0", "0", "NA", "NA", "NA", "NA", "NA", "NA", "NA", "0", "NA", "NA", "0", "NA", "0", "1", "Watford", "Abdoulaye Doucouré", "Kiko Femenía", "0", "NA", "NA", "NA", "0", "NA", "NA", "0", "NA", "0", "NA", "NA", "NA", "0", "NA", "NA", "0", "0", "NA", "NA", "NA", "0", "NA", "NA", "NA", "NA", "1", "24", "0", "NA", "NA", "45"], ["480604", "First Half ends, Liverpool 2, Watford 0.", "45'+2'", "Liverpool", "2", "1", "0", "0", "0", "0", "NA", "NA", "NA", "NA", "NA", "NA", "NA", "0", "NA", "NA", "0", "NA", "0", "0", "NA", "NA", "NA", "0", "NA", "NA", "NA", "0", "NA", "NA", "0", "NA", "0", "NA", "NA", "NA", "0", "NA", "NA", "0", "0", "NA", "NA", "NA", "0", "NA", "NA", "NA", "NA", "1", "25", "1", "NA", "NA", "47"], ["480604", "Second Half begins Liverpool 2, Watford 0.", "45'", "Liverpool", "2", "0", "0", "1", "0", "0", "NA", "NA", "NA", "NA", "NA", "NA", "NA", "0", "NA", "NA", "0", "NA", "0", "0", "NA", "NA", "NA", "0", "NA", "NA", "NA", "0", "NA", "NA", "0", "NA", "0", "NA", "NA", "NA", "0", "NA", "NA", "0", "0", "NA", "NA", "NA", "0", "NA", "NA", "NA", "NA", "2", "26", "0", "NA", "NA", "45"], ["480604", "Attempt saved. Roberto Firmino (Liverpool) header from the centre of the box is saved in the centre of the goal. Assisted by Jordan Henderson with a cross.", "46'", "Liverpool", "2", "0", "0", "0", "1", "0", "saved", "Roberto Firmino", "Liverpool", "header", "the centre of the box", "the centre of the goal", "Jordan Henderson", "0", "NA", "NA", "0", "cross", "0", "0", "NA", "NA", "NA", "0", "NA", "NA", "NA", "0", "NA", "NA", "0", "NA", "0", "NA", "NA", "NA", "0", "NA", "NA", "0", "0", "NA", "NA", "NA", "0", "NA", "NA", "NA", "NA", "2", "27", "0", "NA", "NA", "46"], ["480604", "Offside, Liverpool. Jordan Henderson tries a through ball, but Mohamed Salah is caught offside.", "47'", "Liverpool", "2", "0", "0", "0", "0", "0", "NA", "NA", "NA", "NA", "NA", "NA", "NA", "0", "NA", "NA", "0", "NA", "0", "1", "Liverpool", "Mohamed Salah", "Jordan Henderson", "0", "NA", "NA", "NA", "0", "NA", "NA", "0", "NA", "0", "NA", "NA", "NA", "0", "NA", "NA", "0", "0", "NA", "NA", "NA", "0", "NA", "NA", "NA", "NA", "2", "28", "0", "NA", "NA", "47"], ["480604", "Goal!  Liverpool 3, Watford 0. Roberto Firmino (Liverpool) right footed shot from very close range to the bottom left corner. Assisted by Mohamed Salah with a cross.", "49'", "Liverpool", "3", "0", "0", "0", "1", "0", "goal", "Roberto Firmino", "Liverpool", "right", "right shot very close range", "bottom left corner", "Mohamed Salah", "0", "NA", "NA", "0", "cross", "0", "0", "NA", "NA", "NA", "0", "NA", "NA", "NA", "0", "NA", "NA", "0", "NA", "0", "NA", "NA", "NA", "0", "NA", "NA", "0", "0", "NA", "NA", "NA", "0", "NA", "NA", "NA", "NA", "2", "29", "0", "NA", "NA", "49"], ["480604", "Etienne Capoue (Watford) wins a free kick in the defensive half.", "51'", "Liverpool", "3", "0", "0", "0", "0", "0", "NA", "NA", "NA", "NA", "NA", "NA", "NA", "0", "NA", "NA", "0", "NA", "0", "0", "NA", "NA", "NA", "0", "NA", "NA", "NA", "0", "NA", "NA", "0", "NA", "1", "Etienne Capoue", "Watford", "defensive half", "0", "NA", "NA", "0", "0", "NA", "NA", "NA", "0", "NA", "NA", "NA", "NA", "2", "30", "0", "NA", "NA", "51"], ["480604", "Foul by James Milner (Liverpool).", "51'", "Liverpool", "3", "0", "0", "0", "0", "0", "NA", "NA", "NA", "NA", "NA", "NA", "NA", "1", "James Milner", "Liverpool", "0", "NA", "0", "0", "NA", "NA", "NA", "0", "NA", "NA", "NA", "0", "NA", "NA", "0", "NA", "0", "NA", "NA", "NA", "0", "NA", "NA", "0", "0", "NA", "NA", "NA", "0", "NA", "NA", "NA", "NA", "2", "31", "0", "NA", "NA", "51"], ["480604", "Attempt missed. José Holebas (Watford) right footed shot from outside the box is close, but misses to the left. Assisted by Miguel Britos.", "51'", "Liverpool", "3", "0", "0", "0", "1", "0", "missed", "José Holebas", "Watford", "right", "outside the box", "close, but left", "Miguel Britos", "0", "NA", "NA", "0", "NA", "0", "0", "NA", "NA", "NA", "0", "NA", "NA", "NA", "0", "NA", "NA", "0", "NA", "0", "NA", "NA", "NA", "0", "NA", "NA", "0", "0", "NA", "NA", "NA", "0", "NA", "NA", "NA", "NA", "2", "32", "0", "NA", "NA", "51"], ["480604", "Foul by Joseph Gomez (Liverpool).", "51'", "Liverpool", "3", "0", "0", "0", "0", "0", "NA", "NA", "NA", "NA", "NA", "NA", "NA", "1", "Joseph Gomez", "Liverpool", "0", "NA", "0", "0", "NA", "NA", "NA", "0", "NA", "NA", "NA", "0", "NA", "NA", "0", "NA", "0", "NA", "NA", "NA", "0", "NA", "NA", "0", "0", "NA", "NA", "NA", "0", "NA", "NA", "NA", "NA", "2", "33", "0", "NA", "NA", "51"], ["480604", "Richarlison (Watford) wins a free kick on the left wing.", "51'", "Liverpool", "3", "0", "0", "0", "0", "0", "NA", "NA", "NA", "NA", "NA", "NA", "NA", "0", "NA", "NA", "0", "NA", "0", "0", "NA", "NA", "NA", "0", "NA", "NA", "NA", "0", "NA", "NA", "0", "NA", "1", "Richarlison", "Watford", "NA", "0", "NA", "NA", "0", "0", "NA", "NA", "NA", "0", "NA", "NA", "NA", "NA", "2", "34", "0", "NA", "NA", "51"], ["480604", "Joseph Gomez (Liverpool) is shown the yellow card for a bad foul.", "52'", "Liverpool", "3", "0", "0", "0", "0", "0", "NA", "NA", "NA", "NA", "NA", "NA", "NA", "0", "NA", "NA", "0", "NA", "0", "0", "NA", "NA", "NA", "1", "yellow", "Joseph Gomez", "Liverpool", "0", "NA", "NA", "0", "NA", "0", "NA", "NA", "NA", "0", "NA", "NA", "0", "0", "NA", "NA", "NA", "0", "NA", "NA", "NA", "NA", "2", "35", "0", "NA", "NA", "52"], ["480604", "Roberto Pereyra (Watford) hits the bar with a right footed shot from a difficult angle and long range on the left from a direct free kick.", "52'", "Liverpool", "3", "0", "0", "0", "0", "0", "NA", "NA", "NA", "NA", "NA", "NA", "NA", "0", "NA", "NA", "0", "NA", "0", "0", "NA", "NA", "NA", "0", "NA", "NA", "NA", "0", "NA", "NA", "0", "NA", "0", "NA", "NA", "NA", "0", "NA", "NA", "0", "0", "NA", "NA", "NA", "0", "NA", "NA", "NA", "NA", "2", "36", "0", "NA", "NA", "52"], ["480604", "Foul by Mohamed Salah (Liverpool).", "59'", "Liverpool", "3", "0", "0", "0", "0", "0", "NA", "NA", "NA", "NA", "NA", "NA", "NA", "1", "Mohamed Salah", "Liverpool", "0", "NA", "0", "0", "NA", "NA", "NA", "0", "NA", "NA", "NA", "0", "NA", "NA", "0", "NA", "0", "NA", "NA", "NA", "0", "NA", "NA", "0", "0", "NA", "NA", "NA", "0", "NA", "NA", "NA", "NA", "2", "37", "0", "NA", "NA", "59"], ["480604", "José Holebas (Watford) wins a free kick in the defensive half.", "59'", "Liverpool", "3", "0", "0", "0", "0", "0", "NA", "NA", "NA", "NA", "NA", "NA", "NA", "0", "NA", "NA", "0", "NA", "0", "0", "NA", "NA", "NA", "0", "NA", "NA", "NA", "0", "NA", "NA", "0", "NA", "1", "José Holebas", "Watford", "defensive half", "0", "NA", "NA", "0", "0", "NA", "NA", "NA", "0", "NA", "NA", "NA", "NA", "2", "38", "0", "NA", "NA", "59"], ["480604", "Attempt missed. Roberto Firmino (Liverpool) header from the centre of the box misses to the left. Assisted by Joseph Gomez with a cross.", "61'", "Liverpool", "3", "0", "0", "0", "1", "0", "missed", "Roberto Firmino", "Liverpool", "header", "the centre of the box", "left", "Joseph Gomez", "0", "NA", "NA", "0", "cross", "0", "0", "NA", "NA", "NA", "0", "NA", "NA", "NA", "0", "NA", "NA", "0", "NA", "0", "NA", "NA", "NA", "0", "NA", "NA", "0", "0", "NA", "NA", "NA", "0", "NA", "NA", "NA", "NA", "2", "39", "0", "NA", "NA", "61"], ["480604", "Substitution, Watford. Will Hughes replaces Richarlison.", "65'", "Liverpool", "3", "0", "0", "0", "0", "0", "NA", "NA", "NA", "NA", "NA", "NA", "NA", "0", "NA", "NA", "0", "NA", "0", "0", "NA", "NA", "NA", "0", "NA", "NA", "NA", "0", "NA", "NA", "0", "NA", "0", "NA", "NA", "NA", "0", "NA", "NA", "1", "0", "Watford", "Will Hughes", "Richarlison", "0", "NA", "NA", "NA", "NA", "2", "40", "0", "NA", "NA", "65"], ["480604", "Substitution, Watford. Stefano Okaka replaces Troy Deeney.", "70'", "Liverpool", "3", "0", "0", "0", "0", "0", "NA", "NA", "NA", "NA", "NA", "NA", "NA", "0", "NA", "NA", "0", "NA", "0", "0", "NA", "NA", "NA", "0", "NA", "NA", "NA", "0", "NA", "NA", "0", "NA", "0", "NA", "NA", "NA", "0", "NA", "NA", "1", "0", "Watford", "Stefano Okaka", "Troy Deeney", "0", "NA", "NA", "NA", "NA", "2", "41", "0", "NA", "NA", "70"], ["480604", "Substitution, Liverpool. Alex Oxlade-Chamberlain replaces Georginio Wijnaldum.", "71'", "Liverpool", "3", "0", "0", "0", "0", "0", "NA", "NA", "NA", "NA", "NA", "NA", "NA", "0", "NA", "NA", "0", "NA", "0", "0", "NA", "NA", "NA", "0", "NA", "NA", "NA", "0", "NA", "NA", "0", "NA", "0", "NA", "NA", "NA", "0", "NA", "NA", "1", "0", "Liverpool", "Alex Oxlade-Chamberlain", "Georginio Wijnaldum", "0", "NA", "NA", "NA", "NA", "2", "42", "0", "NA", "NA", "71"], ["480604", "Foul by Adrian Mariappa (Watford).", "75'", "Liverpool", "3", "0", "0", "0", "0", "0", "NA", "NA", "NA", "NA", "NA", "NA", "NA", "1", "Adrian Mariappa", "Watford", "0", "NA", "0", "0", "NA", "NA", "NA", "0", "NA", "NA", "NA", "0", "NA", "NA", "0", "NA", "0", "NA", "NA", "NA", "0", "NA", "NA", "0", "0", "NA", "NA", "NA", "0", "NA", "NA", "NA", "NA", "2", "43", "0", "NA", "NA", "75"], ["480604", "Sadio Mané (Liverpool) wins a free kick in the attacking half.", "75'", "Liverpool", "3", "0", "0", "0", "0", "0", "NA", "NA", "NA", "NA", "NA", "NA", "NA", "0", "NA", "NA", "0", "NA", "0", "0", "NA", "NA", "NA", "0", "NA", "NA", "NA", "0", "NA", "NA", "0", "NA", "1", "Sadio Mané", "Liverpool", "attacking half", "0", "NA", "NA", "0", "0", "NA", "NA", "NA", "0", "NA", "NA", "NA", "NA", "2", "44", "0", "NA", "NA", "75"], ["480604", "Attempt saved. Alex Oxlade-Chamberlain (Liverpool) right footed shot from outside the box is saved in the centre of the goal.", "77'", "Liverpool", "3", "0", "0", "0", "1", "0", "saved", "Alex Oxlade-Chamberlain", "Liverpool", "right", "outside the box", "the centre of the goal", "NA", "0", "NA", "NA", "0", "NA", "0", "0", "NA", "NA", "NA", "0", "NA", "NA", "NA", "0", "NA", "NA", "0", "NA", "0", "NA", "NA", "NA", "0", "NA", "NA", "0", "0", "NA", "NA", "NA", "0", "NA", "NA", "NA", "NA", "2", "45", "0", "NA", "NA", "77"], ["480604", "Goal!  Liverpool 4, Watford 0. Mohamed Salah (Liverpool) left footed shot from the centre of the box to the bottom left corner. Assisted by Sadio Mané.", "77'", "Liverpool", "4", "0", "0", "0", "1", "0", "goal", "Mohamed Salah", "Liverpool", "left", "the centre of the box", "bottom left corner", "Sadio Mané", "0", "NA", "NA", "0", "NA", "0", "0", "NA", "NA", "NA", "0", "NA", "NA", "NA", "0", "NA", "NA", "0", "NA", "0", "NA", "NA", "NA", "0", "NA", "NA", "0", "0", "NA", "NA", "NA", "0", "NA", "NA", "NA", "NA", "2", "46", "0", "NA", "NA", "77"], ["480604", "Foul by Roberto Firmino (Liverpool).", "79'", "Liverpool", "4", "0", "0", "0", "0", "0", "NA", "NA", "NA", "NA", "NA", "NA", "NA", "1", "Roberto Firmino", "Liverpool", "0", "NA", "0", "0", "NA", "NA", "NA", "0", "NA", "NA", "NA", "0", "NA", "NA", "0", "NA", "0", "NA", "NA", "NA", "0", "NA", "NA", "0", "0", "NA", "NA", "NA", "0", "NA", "NA", "NA", "NA", "2", "47", "0", "NA", "NA", "79"], ["480604", "Will Hughes (Watford) wins a free kick in the defensive half.", "79'", "Liverpool", "4", "0", "0", "0", "0", "0", "NA", "NA", "NA", "NA", "NA", "NA", "NA", "0", "NA", "NA", "0", "NA", "0", "0", "NA", "NA", "NA", "0", "NA", "NA", "NA", "0", "NA", "NA", "0", "NA", "1", "Will Hughes", "Watford", "defensive half", "0", "NA", "NA", "0", "0", "NA", "NA", "NA", "0", "NA", "NA", "NA", "NA", "2", "48", "0", "NA", "NA", "79"], ["480604", "Substitution, Liverpool. Danny Ings replaces Roberto Firmino.", "79'", "Liverpool", "4", "0", "0", "0", "0", "0", "NA", "NA", "NA", "NA", "NA", "NA", "NA", "0", "NA", "NA", "0", "NA", "0", "0", "NA", "NA", "NA", "0", "NA", "NA", "NA", "0", "NA", "NA", "0", "NA", "0", "NA", "NA", "NA", "0", "NA", "NA", "1", "0", "Liverpool", "Danny Ings", "Roberto Firmino", "0", "NA", "NA", "NA", "NA", "2", "49", "0", "NA", "NA", "79"], ["480604", "Attempt blocked. Stefano Okaka (Watford) right footed shot from the left side of the box is blocked. Assisted by Abdoulaye Doucouré with a through ball.", "80'", "Liverpool", "4", "0", "0", "0", "1", "0", "blocked", "Stefano Okaka", "Watford", "right", "the left side of the box", "NA", "Abdoulaye Doucouré", "0", "NA", "NA", "0", "through", "0", "0", "NA", "NA", "NA", "0", "NA", "NA", "NA", "0", "NA", "NA", "0", "NA", "0", "NA", "NA", "NA", "0", "NA", "NA", "0", "0", "NA", "NA", "NA", "0", "NA", "NA", "NA", "NA", "2", "50", "0", "NA", "NA", "80"], ["480604", "Substitution, Watford. Daryl Janmaat replaces Miguel Britos.", "81'", "Liverpool", "4", "0", "0", "0", "0", "0", "NA", "NA", "NA", "NA", "NA", "NA", "NA", "0", "NA", "NA", "0", "NA", "0", "0", "NA", "NA", "NA", "0", "NA", "NA", "NA", "0", "NA", "NA", "0", "NA", "0", "NA", "NA", "NA", "0", "NA", "NA", "1", "0", "Watford", "Daryl Janmaat", "Miguel Britos", "0", "NA", "NA", "NA", "NA", "2", "51", "0", "NA", "NA", "81"], ["480604", "Attempt saved. Danny Ings (Liverpool) right footed shot from the centre of the box is saved in the top centre of the goal. Assisted by Sadio Mané with a through ball.", "84'", "Liverpool", "4", "0", "0", "0", "1", "0", "saved", "Danny Ings", "Liverpool", "right", "the centre of the box", "the top centre of the goal", "Sadio Mané", "0", "NA", "NA", "0", "through", "0", "0", "NA", "NA", "NA", "0", "NA", "NA", "NA", "0", "NA", "NA", "0", "NA", "0", "NA", "NA", "NA", "0", "NA", "NA", "0", "0", "NA", "NA", "NA", "0", "NA", "NA", "NA", "NA", "2", "52", "0", "NA", "NA", "84"], ["480604", "Attempt blocked. James Milner (Liverpool) right footed shot from outside the box is blocked.", "84'", "Liverpool", "4", "0", "0", "0", "1", "0", "blocked", "James Milner", "Liverpool", "right", "outside the box", "NA", "NA", "0", "NA", "NA", "0", "NA", "0", "0", "NA", "NA", "NA", "0", "NA", "NA", "NA", "0", "NA", "NA", "0", "NA", "0", "NA", "NA", "NA", "0", "NA", "NA", "0", "0", "NA", "NA", "NA", "0", "NA", "NA", "NA", "NA", "2", "53", "0", "NA", "NA", "84"], ["480604", "Offside, Liverpool. James Milner tries a through ball, but Danny Ings is caught offside.", "84'", "Liverpool", "4", "0", "0", "0", "0", "0", "NA", "NA", "NA", "NA", "NA", "NA", "NA", "0", "NA", "NA", "0", "NA", "0", "1", "Liverpool", "Danny Ings", "James Milner", "0", "NA", "NA", "NA", "0", "NA", "NA", "0", "NA", "0", "NA", "NA", "NA", "0", "NA", "NA", "0", "0", "NA", "NA", "NA", "0", "NA", "NA", "NA", "NA", "2", "54", "0", "NA", "NA", "84"], ["480604", "Attempt saved. Danny Ings (Liverpool) right footed shot from the centre of the box is saved in the bottom right corner. Assisted by Mohamed Salah.", "85'", "Liverpool", "4", "0", "0", "0", "1", "0", "saved", "Danny Ings", "Liverpool", "right", "the centre of the box", "the bottom right corner", "Mohamed Salah", "0", "NA", "NA", "0", "NA", "0", "0", "NA", "NA", "NA", "0", "NA", "NA", "NA", "0", "NA", "NA", "0", "NA", "0", "NA", "NA", "NA", "0", "NA", "NA", "0", "0", "NA", "NA", "NA", "0", "NA", "NA", "NA", "NA", "2", "55", "0", "NA", "NA", "85"], ["480604", "Goal!  Liverpool 5, Watford 0. Mohamed Salah (Liverpool) left footed shot from the centre of the box to the top right corner.", "85'", "Liverpool", "5", "0", "0", "0", "1", "0", "goal", "Mohamed Salah", "Liverpool", "left", "the centre of the box", "top right corner", "NA", "0", "NA", "NA", "0", "NA", "0", "0", "NA", "NA", "NA", "0", "NA", "NA", "NA", "0", "NA", "NA", "0", "NA", "0", "NA", "NA", "NA", "0", "NA", "NA", "0", "0", "NA", "NA", "NA", "0", "NA", "NA", "NA", "NA", "2", "56", "0", "NA", "NA", "85"], ["480604", "Foul by Roberto Pereyra (Watford).", "88'", "Liverpool", "5", "0", "0", "0", "0", "0", "NA", "NA", "NA", "NA", "NA", "NA", "NA", "1", "Roberto Pereyra", "Watford", "0", "NA", "0", "0", "NA", "NA", "NA", "0", "NA", "NA", "NA", "0", "NA", "NA", "0", "NA", "0", "NA", "NA", "NA", "0", "NA", "NA", "0", "0", "NA", "NA", "NA", "0", "NA", "NA", "NA", "NA", "2", "57", "0", "NA", "NA", "88"], ["480604", "Virgil van Dijk (Liverpool) wins a free kick in the defensive half.", "88'", "Liverpool", "5", "0", "0", "0", "0", "0", "NA", "NA", "NA", "NA", "NA", "NA", "NA", "0", "NA", "NA", "0", "NA", "0", "0", "NA", "NA", "NA", "0", "NA", "NA", "NA", "0", "NA", "NA", "0", "NA", "1", "Virgil van Dijk", "Liverpool", "defensive half", "0", "NA", "NA", "0", "0", "NA", "NA", "NA", "0", "NA", "NA", "NA", "NA", "2", "58", "0", "NA", "NA", "88"], ["480604", "Foul by Stefano Okaka (Watford).", "88'", "Liverpool", "5", "0", "0", "0", "0", "0", "NA", "NA", "NA", "NA", "NA", "NA", "NA", "1", "Stefano Okaka", "Watford", "0", "NA", "0", "0", "NA", "NA", "NA", "0", "NA", "NA", "NA", "0", "NA", "NA", "0", "NA", "0", "NA", "NA", "NA", "0", "NA", "NA", "0", "0", "NA", "NA", "NA", "0", "NA", "NA", "NA", "NA", "2", "59", "0", "NA", "NA", "88"], ["480604", "Jordan Henderson (Liverpool) wins a free kick in the defensive half.", "88'", "Liverpool", "5", "0", "0", "0", "0", "0", "NA", "NA", "NA", "NA", "NA", "NA", "NA", "0", "NA", "NA", "0", "NA", "0", "0", "NA", "NA", "NA", "0", "NA", "NA", "NA", "0", "NA", "NA", "0", "NA", "1", "Jordan Henderson", "Liverpool", "defensive half", "0", "NA", "NA", "0", "0", "NA", "NA", "NA", "0", "NA", "NA", "NA", "NA", "2", "60", "0", "NA", "NA", "88"], ["480604", "Offside, Liverpool. James Milner tries a through ball, but Danny Ings is caught offside.", "89'", "Liverpool", "5", "0", "0", "0", "0", "0", "NA", "NA", "NA", "NA", "NA", "NA", "NA", "0", "NA", "NA", "0", "NA", "0", "1", "Liverpool", "Danny Ings", "James Milner", "0", "NA", "NA", "NA", "0", "NA", "NA", "0", "NA", "0", "NA", "NA", "NA", "0", "NA", "NA", "0", "0", "NA", "NA", "NA", "0", "NA", "NA", "NA", "NA", "2", "61", "0", "NA", "NA", "89"], ["480604", "Corner,  Watford. Conceded by Joel Matip.", "90'+2'", "Liverpool", "5", "0", "0", "0", "0", "0", "NA", "NA", "NA", "NA", "NA", "NA", "NA", "0", "NA", "NA", "0", "NA", "0", "0", "NA", "NA", "NA", "0", "NA", "NA", "NA", "0", "NA", "NA", "0", "NA", "0", "NA", "NA", "NA", "1", "Watford", "Joel Matip", "0", "0", "NA", "NA", "NA", "0", "NA", "NA", "NA", "NA", "2", "62", "1", "NA", "NA", "92"], ["480604", "Second Half ends, Liverpool 5, Watford 0.", "90'+3'", "Liverpool", "5", "1", "0", "0", "0", "0", "NA", "NA", "NA", "NA", "NA", "NA", "NA", "0", "NA", "NA", "0", "NA", "0", "0", "NA", "NA", "NA", "0", "NA", "NA", "NA", "0", "NA", "NA", "0", "NA", "0", "NA", "NA", "NA", "0", "NA", "NA", "0", "0", "NA", "NA", "NA", "0", "NA", "NA", "NA", "NA", "2", "63", "1", "NA", "NA", "93"], ["480604", "Match ends, Liverpool 5, Watford 0.", "90'+3'", "Liverpool", "5", "0", "1", "0", "0", "0", "NA", "NA", "NA", "NA", "NA", "NA", "NA", "0", "NA", "NA", "0", "NA", "0", "0", "NA", "NA", "NA", "0", "NA", "NA", "NA", "0", "NA", "NA", "0", "NA", "0", "NA", "NA", "NA", "0", "NA", "NA", "0", "0", "NA", "NA", "NA", "0", "NA", "NA", "NA", "NA", "2", "64", "1", "NA", "NA", "93"]], "Lineup": {"Home Player 9": "Mohamed Salah", "Home Player 8": "Andrew Robertson", "Home Player 5": "Loris Karius", "Home Player 4": "Jordan Henderson", "Home Player 7": "Joel Matip", "Home Player 6": "Sadio Mane", "Home Player 1": "Emre Can", "Home Player 3": "Joe Gomez", "Home Player 2": "Roberto Firmino", "Away Player 10": "Sebastian Prodl", "Away Player 11": "Richarlison", "Away Player 8": "Adrian Mariappa", "Away Player 9": "Roberto Pereyra", "Away Player 1": "Miguel Britos", "Away Player 2": "Etienne Capoue", "Away Player 3": "Troy Deeney", "Away Player 4": "Abdoulaye Doucoure", "Away Player 5": "Jose Holebas", "Away Player 6": "Orestis Karnezis", "Away Player 7": "Kiko", "Game ID": "g_1_CAUFh5st", "Home Player 11": "Georginio Wijnaldum", "Home Player 10": "Virgil van Dijk"}}