{"Stats": {"Full Time Result": "D", "Away Team Corners": 3, "Referee": "A Taylor", "Home Team Fouls Committed": 9, "Home Team Corners": 3, "Away Team Shots": 3, "Away Team Red Cards": 0, "Home Team Red Cards": 0, "Half Time Away Team Goals": 0, "Full Time Home Team Goals": 1, "Away Team Yellow Cards": 0, "Away Team Shots on Target": 1, "Half Time Home Team Goals": 1, "Half Time Result": "H", "Home Team Yellow Cards": 1, "Home Team Shots": 13, "Div": "E0", "Away Team Fouls Committed": 8, "Home Team Shots on Target": 5, "Full Time Away Team Goals": 1}, "Description": "Foul by Fousseni Diabaté (Leicester City). at minute 3. Sam Clucas (Swansea City) wins a free kick on the left wing. at minute 3. Fousseni Diabaté (Leicester City) is shown the yellow card for a bad foul. at minute 3. Offside, Leicester City. Kelechi Iheanacho tries a through ball, but Jamie Vardy is caught offside. at minute 8. Foul by Leroy Fer (Swansea City). at minute 15. Wilfred Ndidi (Leicester City) wins a free kick in the attacking half. at minute 15. Goal!  Leicester City 1, Swansea City 0. Jamie Vardy (Leicester City) right footed shot from the centre of the box to the bottom right corner. Assisted by Kelechi Iheanacho with a through ball. at minute 17. Foul by Wilfred Ndidi (Leicester City). at minute 18. Jordan Ayew (Swansea City) wins a free kick in the defensive half. at minute 18. Corner,  Swansea City. Conceded by Wilfred Ndidi. at minute 21. Foul by Leroy Fer (Swansea City). at minute 23. Wilfred Ndidi (Leicester City) wins a free kick in the attacking half. at minute 23. Attempt saved. Marc Albrighton (Leicester City) right footed shot from outside the box is saved in the centre of the goal. at minute 24. Offside, Leicester City. Wilfred Ndidi tries a through ball, but Jamie Vardy is caught offside. at minute 27. Attempt saved. Fousseni Diabaté (Leicester City) left footed shot from the left side of the box is saved in the top centre of the goal. Assisted by Kelechi Iheanacho. at minute 29. Attempt blocked. Kelechi Iheanacho (Leicester City) left footed shot from the centre of the box is blocked. at minute 29. Offside, Leicester City. Harry Maguire tries a through ball, but Fousseni Diabaté is caught offside. at minute 30. Delay in match Leroy Fer (Swansea City) because of an injury. at minute 33. Delay over. They are ready to continue. at minute 35. Substitution, Swansea City. Tom Carroll replaces Leroy Fer because of an injury. at minute 36. Foul by Kelechi Iheanacho (Leicester City). at minute 38. Nathan Dyer (Swansea City) wins a free kick in the defensive half. at minute 38. Foul by Kelechi Iheanacho (Leicester City). at minute 41. Kyle Naughton (Swansea City) wins a free kick on the right wing. at minute 41. Federico Fernández (Swansea City) wins a free kick in the defensive half. at minute 44. Foul by Jamie Vardy (Leicester City). at minute 44. First Half ends, Leicester City 1, Swansea City 0. at minute 48. Second Half begins Leicester City 1, Swansea City 0. at minute 45. Foul by Kelechi Iheanacho (Leicester City). at minute 47. Ki Sung-yueng (Swansea City) wins a free kick in the defensive half. at minute 47. Corner,  Swansea City. Conceded by Marc Albrighton. at minute 50. Foul by Wilfred Ndidi (Leicester City). at minute 51. Jordan Ayew (Swansea City) wins a free kick in the attacking half. at minute 51. Corner,  Swansea City. Conceded by Wilfred Ndidi. at minute 52. Goal!  Leicester City 1, Swansea City 1. Federico Fernández (Swansea City) header from very close range to the bottom right corner. Assisted by Ki Sung-yueng with a cross following a corner. at minute 53. Foul by Sam Clucas (Swansea City). at minute 54. Jamie Vardy (Leicester City) wins a free kick on the right wing. at minute 54. Attempt missed. Harry Maguire (Leicester City) header from the centre of the box misses to the left. Assisted by Marc Albrighton with a cross following a set piece situation. at minute 54. Attempt saved. Kelechi Iheanacho (Leicester City) left footed shot from outside the box is saved in the centre of the goal. at minute 56. Attempt missed. Sam Clucas (Swansea City) header from the centre of the box misses to the right. Assisted by Mike van der Hoorn with a cross. at minute 58. Adrien Silva (Leicester City) wins a free kick in the defensive half. at minute 61. Foul by Jordan Ayew (Swansea City). at minute 61. Attempt blocked. Sam Clucas (Swansea City) left footed shot from the centre of the box is blocked. Assisted by Alfie Mawson. at minute 62. Attempt missed. Jamie Vardy (Leicester City) right footed shot from a difficult angle and long range on the right misses to the left. Assisted by Marc Albrighton. at minute 63. Attempt missed. Fousseni Diabaté (Leicester City) left footed shot from the centre of the box misses to the left. Assisted by Jamie Vardy following a fast break. at minute 64. Substitution, Leicester City. Matty James replaces Adrien Silva. at minute 68. Substitution, Leicester City. Demarai Gray replaces Kelechi Iheanacho. at minute 68. Foul by Ki Sung-yueng (Swansea City). at minute 69. Marc Albrighton (Leicester City) wins a free kick in the defensive half. at minute 69. Substitution, Swansea City. Wilfried Bony replaces Nathan Dyer. at minute 71. Attempt missed. Demarai Gray (Leicester City) right footed shot from the centre of the box is too high. Assisted by Christian Fuchs with a cross. at minute 73. Foul by Federico Fernández (Swansea City). at minute 76. Fousseni Diabaté (Leicester City) wins a free kick in the attacking half. at minute 76. Attempt missed. Harry Maguire (Leicester City) header from the left side of the six yard box is close, but misses to the left following a set piece situation. at minute 77. Demarai Gray (Leicester City) wins a free kick in the attacking half. at minute 78. Foul by Tom Carroll (Swansea City). at minute 78. Foul by Matty James (Leicester City). at minute 80. Tom Carroll (Swansea City) wins a free kick in the attacking half. at minute 80. Substitution, Leicester City. Shinji Okazaki replaces Danny Simpson. at minute 80. Corner,  Leicester City. Conceded by Alfie Mawson. at minute 83. Attempt blocked. Wilfred Ndidi (Leicester City) left footed shot from outside the box is blocked. at minute 84. Attempt blocked. Demarai Gray (Leicester City) right footed shot from the centre of the box is blocked. Assisted by Harry Maguire with a headed pass. at minute 84. Corner,  Leicester City. Conceded by Tom Carroll. at minute 84. Corner,  Leicester City. Conceded by Kyle Naughton. at minute 86. Offside, Leicester City. Harry Maguire tries a through ball, but Jamie Vardy is caught offside. at minute 88. Offside, Leicester City. Christian Fuchs tries a through ball, but Jamie Vardy is caught offside. at minute 90. Demarai Gray (Leicester City) wins a free kick in the defensive half. at minute 91. Foul by Jordan Ayew (Swansea City). at minute 91. Substitution, Swansea City. Wayne Routledge replaces Jordan Ayew. at minute 91. Attempt blocked. Marc Albrighton (Leicester City) right footed shot from the right side of the box is blocked. at minute 93. Foul by Harry Maguire (Leicester City). at minute 93. Mike van der Hoorn (Swansea City) wins a free kick in the defensive half. at minute 93. Second Half ends, Leicester City 1, Swansea City 1. at minute 95. Match ends, Leicester City 1, Swansea City 1. at minute 95. ", "Home Team": "Leicester City", "Away Team": "Swansea City", "Date": "03-02-2018", "Commentary": [["480653", "First Half begins.", "-", "Leicester City", "0", "0", "0", "1", "0", "0", "NA", "NA", "NA", "NA", "NA", "NA", "NA", "0", "NA", "NA", "0", "NA", "0", "0", "NA", "NA", "NA", "0", "NA", "NA", "NA", "0", "NA", "NA", "0", "NA", "0", "NA", "NA", "NA", "0", "NA", "NA", "0", "0", "NA", "NA", "NA", "0", "NA", "NA", "NA", "NA", "1", "1", "0", "NA", "NA", "NA"], ["480653", "Lineups are announced and players are warming up.", "-", "Leicester City", "0", "0", "0", "0", "0", "0", "NA", "NA", "NA", "NA", "NA", "NA", "NA", "0", "NA", "NA", "0", "NA", "0", "0", "NA", "NA", "NA", "0", "NA", "NA", "NA", "0", "NA", "NA", "0", "NA", "0", "NA", "NA", "NA", "0", "NA", "NA", "0", "0", "NA", "NA", "NA", "0", "NA", "NA", "NA", "NA", "1", "2", "0", "NA", "NA", "NA"], ["480653", "Foul by Fousseni Diabaté (Leicester City).", "3'", "Leicester City", "0", "0", "0", "0", "0", "0", "NA", "NA", "NA", "NA", "NA", "NA", "NA", "1", "Fousseni Diabaté", "Leicester City", "0", "NA", "0", "0", "NA", "NA", "NA", "0", "NA", "NA", "NA", "0", "NA", "NA", "0", "NA", "0", "NA", "NA", "NA", "0", "NA", "NA", "0", "0", "NA", "NA", "NA", "0", "NA", "NA", "NA", "NA", "1", "3", "0", "NA", "NA", "3"], ["480653", "Sam Clucas (Swansea City) wins a free kick on the left wing.", "3'", "Leicester City", "0", "0", "0", "0", "0", "0", "NA", "NA", "NA", "NA", "NA", "NA", "NA", "0", "NA", "NA", "0", "NA", "0", "0", "NA", "NA", "NA", "0", "NA", "NA", "NA", "0", "NA", "NA", "0", "NA", "1", "Sam Clucas", "Swansea City", "NA", "0", "NA", "NA", "0", "0", "NA", "NA", "NA", "0", "NA", "NA", "NA", "NA", "1", "4", "0", "NA", "NA", "3"], ["480653", "Fousseni Diabaté (Leicester City) is shown the yellow card for a bad foul.", "3'", "Leicester City", "0", "0", "0", "0", "0", "0", "NA", "NA", "NA", "NA", "NA", "NA", "NA", "0", "NA", "NA", "0", "NA", "0", "0", "NA", "NA", "NA", "1", "yellow", "Fousseni Diabaté", "Leicester City", "0", "NA", "NA", "0", "NA", "0", "NA", "NA", "NA", "0", "NA", "NA", "0", "0", "NA", "NA", "NA", "0", "NA", "NA", "NA", "NA", "1", "5", "0", "NA", "NA", "3"], ["480653", "Offside, Leicester City. Kelechi Iheanacho tries a through ball, but Jamie Vardy is caught offside.", "8'", "Leicester City", "0", "0", "0", "0", "0", "0", "NA", "NA", "NA", "NA", "NA", "NA", "NA", "0", "NA", "NA", "0", "NA", "0", "1", "Leicester City", "Jamie Vardy", "Kelechi Iheanacho", "0", "NA", "NA", "NA", "0", "NA", "NA", "0", "NA", "0", "NA", "NA", "NA", "0", "NA", "NA", "0", "0", "NA", "NA", "NA", "0", "NA", "NA", "NA", "NA", "1", "6", "0", "NA", "NA", "8"], ["480653", "Foul by Leroy Fer (Swansea City).", "15'", "Leicester City", "0", "0", "0", "0", "0", "0", "NA", "NA", "NA", "NA", "NA", "NA", "NA", "1", "Leroy Fer", "Swansea City", "0", "NA", "0", "0", "NA", "NA", "NA", "0", "NA", "NA", "NA", "0", "NA", "NA", "0", "NA", "0", "NA", "NA", "NA", "0", "NA", "NA", "0", "0", "NA", "NA", "NA", "0", "NA", "NA", "NA", "NA", "1", "7", "0", "NA", "NA", "15"], ["480653", "Wilfred Ndidi (Leicester City) wins a free kick in the attacking half.", "15'", "Leicester City", "0", "0", "0", "0", "0", "0", "NA", "NA", "NA", "NA", "NA", "NA", "NA", "0", "NA", "NA", "0", "NA", "0", "0", "NA", "NA", "NA", "0", "NA", "NA", "NA", "0", "NA", "NA", "0", "NA", "1", "Wilfred Ndidi", "Leicester City", "attacking half", "0", "NA", "NA", "0", "0", "NA", "NA", "NA", "0", "NA", "NA", "NA", "NA", "1", "8", "0", "NA", "NA", "15"], ["480653", "Goal!  Leicester City 1, Swansea City 0. Jamie Vardy (Leicester City) right footed shot from the centre of the box to the bottom right corner. Assisted by Kelechi Iheanacho with a through ball.", "17'", "Leicester City", "1", "0", "0", "0", "1", "0", "goal", "Jamie Vardy", "Leicester City", "right", "the centre of the box", "bottom right corner", "Kelechi Iheanacho", "0", "NA", "NA", "0", "through", "0", "0", "NA", "NA", "NA", "0", "NA", "NA", "NA", "0", "NA", "NA", "0", "NA", "0", "NA", "NA", "NA", "0", "NA", "NA", "0", "0", "NA", "NA", "NA", "0", "NA", "NA", "NA", "NA", "1", "9", "0", "NA", "NA", "17"], ["480653", "Foul by Wilfred Ndidi (Leicester City).", "18'", "Leicester City", "1", "0", "0", "0", "0", "0", "NA", "NA", "NA", "NA", "NA", "NA", "NA", "1", "Wilfred Ndidi", "Leicester City", "0", "NA", "0", "0", "NA", "NA", "NA", "0", "NA", "NA", "NA", "0", "NA", "NA", "0", "NA", "0", "NA", "NA", "NA", "0", "NA", "NA", "0", "0", "NA", "NA", "NA", "0", "NA", "NA", "NA", "NA", "1", "10", "0", "NA", "NA", "18"], ["480653", "Jordan Ayew (Swansea City) wins a free kick in the defensive half.", "18'", "Leicester City", "1", "0", "0", "0", "0", "0", "NA", "NA", "NA", "NA", "NA", "NA", "NA", "0", "NA", "NA", "0", "NA", "0", "0", "NA", "NA", "NA", "0", "NA", "NA", "NA", "0", "NA", "NA", "0", "NA", "1", "Jordan Ayew", "Swansea City", "defensive half", "0", "NA", "NA", "0", "0", "NA", "NA", "NA", "0", "NA", "NA", "NA", "NA", "1", "11", "0", "NA", "NA", "18"], ["480653", "Corner,  Swansea City. Conceded by Wilfred Ndidi.", "21'", "Leicester City", "1", "0", "0", "0", "0", "0", "NA", "NA", "NA", "NA", "NA", "NA", "NA", "0", "NA", "NA", "0", "NA", "0", "0", "NA", "NA", "NA", "0", "NA", "NA", "NA", "0", "NA", "NA", "0", "NA", "0", "NA", "NA", "NA", "1", "Swansea City", "Wilfred Ndidi", "0", "0", "NA", "NA", "NA", "0", "NA", "NA", "NA", "NA", "1", "12", "0", "NA", "NA", "21"], ["480653", "Foul by Leroy Fer (Swansea City).", "23'", "Leicester City", "1", "0", "0", "0", "0", "0", "NA", "NA", "NA", "NA", "NA", "NA", "NA", "1", "Leroy Fer", "Swansea City", "0", "NA", "0", "0", "NA", "NA", "NA", "0", "NA", "NA", "NA", "0", "NA", "NA", "0", "NA", "0", "NA", "NA", "NA", "0", "NA", "NA", "0", "0", "NA", "NA", "NA", "0", "NA", "NA", "NA", "NA", "1", "13", "0", "NA", "NA", "23"], ["480653", "Wilfred Ndidi (Leicester City) wins a free kick in the attacking half.", "23'", "Leicester City", "1", "0", "0", "0", "0", "0", "NA", "NA", "NA", "NA", "NA", "NA", "NA", "0", "NA", "NA", "0", "NA", "0", "0", "NA", "NA", "NA", "0", "NA", "NA", "NA", "0", "NA", "NA", "0", "NA", "1", "Wilfred Ndidi", "Leicester City", "attacking half", "0", "NA", "NA", "0", "0", "NA", "NA", "NA", "0", "NA", "NA", "NA", "NA", "1", "14", "0", "NA", "NA", "23"], ["480653", "Attempt saved. Marc Albrighton (Leicester City) right footed shot from outside the box is saved in the centre of the goal.", "24'", "Leicester City", "1", "0", "0", "0", "1", "0", "saved", "Marc Albrighton", "Leicester City", "right", "outside the box", "the centre of the goal", "NA", "0", "NA", "NA", "0", "NA", "0", "0", "NA", "NA", "NA", "0", "NA", "NA", "NA", "0", "NA", "NA", "0", "NA", "0", "NA", "NA", "NA", "0", "NA", "NA", "0", "0", "NA", "NA", "NA", "0", "NA", "NA", "NA", "NA", "1", "15", "0", "NA", "NA", "24"], ["480653", "Offside, Leicester City. Wilfred Ndidi tries a through ball, but Jamie Vardy is caught offside.", "27'", "Leicester City", "1", "0", "0", "0", "0", "0", "NA", "NA", "NA", "NA", "NA", "NA", "NA", "0", "NA", "NA", "0", "NA", "0", "1", "Leicester City", "Jamie Vardy", "Wilfred Ndidi", "0", "NA", "NA", "NA", "0", "NA", "NA", "0", "NA", "0", "NA", "NA", "NA", "0", "NA", "NA", "0", "0", "NA", "NA", "NA", "0", "NA", "NA", "NA", "NA", "1", "16", "0", "NA", "NA", "27"], ["480653", "Attempt saved. Fousseni Diabaté (Leicester City) left footed shot from the left side of the box is saved in the top centre of the goal. Assisted by Kelechi Iheanacho.", "29'", "Leicester City", "1", "0", "0", "0", "1", "0", "saved", "Fousseni Diabaté", "Leicester City", "left", "the left side of the box", "the top centre of the goal", "Kelechi Iheanacho", "0", "NA", "NA", "0", "NA", "0", "0", "NA", "NA", "NA", "0", "NA", "NA", "NA", "0", "NA", "NA", "0", "NA", "0", "NA", "NA", "NA", "0", "NA", "NA", "0", "0", "NA", "NA", "NA", "0", "NA", "NA", "NA", "NA", "1", "17", "0", "NA", "NA", "29"], ["480653", "Attempt blocked. Kelechi Iheanacho (Leicester City) left footed shot from the centre of the box is blocked.", "29'", "Leicester City", "1", "0", "0", "0", "1", "0", "blocked", "Kelechi Iheanacho", "Leicester City", "left", "the centre of the box", "NA", "NA", "0", "NA", "NA", "0", "NA", "0", "0", "NA", "NA", "NA", "0", "NA", "NA", "NA", "0", "NA", "NA", "0", "NA", "0", "NA", "NA", "NA", "0", "NA", "NA", "0", "0", "NA", "NA", "NA", "0", "NA", "NA", "NA", "NA", "1", "18", "0", "NA", "NA", "29"], ["480653", "Offside, Leicester City. Harry Maguire tries a through ball, but Fousseni Diabaté is caught offside.", "30'", "Leicester City", "1", "0", "0", "0", "0", "0", "NA", "NA", "NA", "NA", "NA", "NA", "NA", "0", "NA", "NA", "0", "NA", "0", "1", "Leicester City", "Fousseni Diabaté", "Harry Maguire", "0", "NA", "NA", "NA", "0", "NA", "NA", "0", "NA", "0", "NA", "NA", "NA", "0", "NA", "NA", "0", "0", "NA", "NA", "NA", "0", "NA", "NA", "NA", "NA", "1", "19", "0", "NA", "NA", "30"], ["480653", "Delay in match Leroy Fer (Swansea City) because of an injury.", "33'", "Leicester City", "1", "0", "0", "0", "0", "0", "NA", "NA", "NA", "NA", "NA", "NA", "NA", "0", "NA", "NA", "0", "NA", "0", "0", "NA", "NA", "NA", "0", "NA", "NA", "NA", "0", "NA", "NA", "1", "Swansea City", "0", "NA", "NA", "NA", "0", "NA", "NA", "0", "0", "NA", "NA", "NA", "0", "NA", "NA", "NA", "NA", "1", "20", "0", "NA", "NA", "33"], ["480653", "Delay over. They are ready to continue.", "35'", "Leicester City", "1", "0", "0", "0", "0", "0", "NA", "NA", "NA", "NA", "NA", "NA", "NA", "0", "NA", "NA", "0", "NA", "0", "0", "NA", "NA", "NA", "0", "NA", "NA", "NA", "0", "NA", "NA", "0", "NA", "0", "NA", "NA", "NA", "0", "NA", "NA", "0", "0", "NA", "NA", "NA", "0", "NA", "NA", "NA", "NA", "1", "21", "0", "NA", "NA", "35"], ["480653", "Substitution, Swansea City. Tom Carroll replaces Leroy Fer because of an injury.", "36'", "Leicester City", "1", "0", "0", "0", "0", "0", "NA", "NA", "NA", "NA", "NA", "NA", "NA", "0", "NA", "NA", "0", "NA", "0", "0", "NA", "NA", "NA", "0", "NA", "NA", "NA", "0", "NA", "NA", "0", "NA", "0", "NA", "NA", "NA", "0", "NA", "NA", "1", "1", "Swansea City", "Tom Carroll", "Leroy Fer", "0", "NA", "NA", "NA", "NA", "1", "22", "0", "NA", "NA", "36"], ["480653", "Foul by Kelechi Iheanacho (Leicester City).", "38'", "Leicester City", "1", "0", "0", "0", "0", "0", "NA", "NA", "NA", "NA", "NA", "NA", "NA", "1", "Kelechi Iheanacho", "Leicester City", "0", "NA", "0", "0", "NA", "NA", "NA", "0", "NA", "NA", "NA", "0", "NA", "NA", "0", "NA", "0", "NA", "NA", "NA", "0", "NA", "NA", "0", "0", "NA", "NA", "NA", "0", "NA", "NA", "NA", "NA", "1", "23", "0", "NA", "NA", "38"], ["480653", "Nathan Dyer (Swansea City) wins a free kick in the defensive half.", "38'", "Leicester City", "1", "0", "0", "0", "0", "0", "NA", "NA", "NA", "NA", "NA", "NA", "NA", "0", "NA", "NA", "0", "NA", "0", "0", "NA", "NA", "NA", "0", "NA", "NA", "NA", "0", "NA", "NA", "0", "NA", "1", "Nathan Dyer", "Swansea City", "defensive half", "0", "NA", "NA", "0", "0", "NA", "NA", "NA", "0", "NA", "NA", "NA", "NA", "1", "24", "0", "NA", "NA", "38"], ["480653", "Foul by Kelechi Iheanacho (Leicester City).", "41'", "Leicester City", "1", "0", "0", "0", "0", "0", "NA", "NA", "NA", "NA", "NA", "NA", "NA", "1", "Kelechi Iheanacho", "Leicester City", "0", "NA", "0", "0", "NA", "NA", "NA", "0", "NA", "NA", "NA", "0", "NA", "NA", "0", "NA", "0", "NA", "NA", "NA", "0", "NA", "NA", "0", "0", "NA", "NA", "NA", "0", "NA", "NA", "NA", "NA", "1", "25", "0", "NA", "NA", "41"], ["480653", "Kyle Naughton (Swansea City) wins a free kick on the right wing.", "41'", "Leicester City", "1", "0", "0", "0", "0", "0", "NA", "NA", "NA", "NA", "NA", "NA", "NA", "0", "NA", "NA", "0", "NA", "0", "0", "NA", "NA", "NA", "0", "NA", "NA", "NA", "0", "NA", "NA", "0", "NA", "1", "Kyle Naughton", "Swansea City", "NA", "0", "NA", "NA", "0", "0", "NA", "NA", "NA", "0", "NA", "NA", "NA", "NA", "1", "26", "0", "NA", "NA", "41"], ["480653", "Federico Fernández (Swansea City) wins a free kick in the defensive half.", "44'", "Leicester City", "1", "0", "0", "0", "0", "0", "NA", "NA", "NA", "NA", "NA", "NA", "NA", "0", "NA", "NA", "0", "NA", "0", "0", "NA", "NA", "NA", "0", "NA", "NA", "NA", "0", "NA", "NA", "0", "NA", "1", "Federico Fernández", "Swansea City", "defensive half", "0", "NA", "NA", "0", "0", "NA", "NA", "NA", "0", "NA", "NA", "NA", "NA", "1", "27", "0", "NA", "NA", "44"], ["480653", "Foul by Jamie Vardy (Leicester City).", "44'", "Leicester City", "1", "0", "0", "0", "0", "0", "NA", "NA", "NA", "NA", "NA", "NA", "NA", "1", "Jamie Vardy", "Leicester City", "0", "NA", "0", "0", "NA", "NA", "NA", "0", "NA", "NA", "NA", "0", "NA", "NA", "0", "NA", "0", "NA", "NA", "NA", "0", "NA", "NA", "0", "0", "NA", "NA", "NA", "0", "NA", "NA", "NA", "NA", "1", "28", "0", "NA", "NA", "44"], ["480653", "First Half ends, Leicester City 1, Swansea City 0.", "45'+3'", "Leicester City", "1", "1", "0", "0", "0", "0", "NA", "NA", "NA", "NA", "NA", "NA", "NA", "0", "NA", "NA", "0", "NA", "0", "0", "NA", "NA", "NA", "0", "NA", "NA", "NA", "0", "NA", "NA", "0", "NA", "0", "NA", "NA", "NA", "0", "NA", "NA", "0", "0", "NA", "NA", "NA", "0", "NA", "NA", "NA", "NA", "1", "29", "1", "NA", "NA", "48"], ["480653", "Second Half begins Leicester City 1, Swansea City 0.", "45'", "Leicester City", "1", "0", "0", "1", "0", "0", "NA", "NA", "NA", "NA", "NA", "NA", "NA", "0", "NA", "NA", "0", "NA", "0", "0", "NA", "NA", "NA", "0", "NA", "NA", "NA", "0", "NA", "NA", "0", "NA", "0", "NA", "NA", "NA", "0", "NA", "NA", "0", "0", "NA", "NA", "NA", "0", "NA", "NA", "NA", "NA", "2", "30", "0", "NA", "NA", "45"], ["480653", "Foul by Kelechi Iheanacho (Leicester City).", "47'", "Leicester City", "1", "0", "0", "0", "0", "0", "NA", "NA", "NA", "NA", "NA", "NA", "NA", "1", "Kelechi Iheanacho", "Leicester City", "0", "NA", "0", "0", "NA", "NA", "NA", "0", "NA", "NA", "NA", "0", "NA", "NA", "0", "NA", "0", "NA", "NA", "NA", "0", "NA", "NA", "0", "0", "NA", "NA", "NA", "0", "NA", "NA", "NA", "NA", "2", "31", "0", "NA", "NA", "47"], ["480653", "Ki Sung-yueng (Swansea City) wins a free kick in the defensive half.", "47'", "Leicester City", "1", "0", "0", "0", "0", "0", "NA", "NA", "NA", "NA", "NA", "NA", "NA", "0", "NA", "NA", "0", "NA", "0", "0", "NA", "NA", "NA", "0", "NA", "NA", "NA", "0", "NA", "NA", "0", "NA", "1", "Ki Sung-yueng", "Swansea City", "defensive half", "0", "NA", "NA", "0", "0", "NA", "NA", "NA", "0", "NA", "NA", "NA", "NA", "2", "32", "0", "NA", "NA", "47"], ["480653", "Corner,  Swansea City. Conceded by Marc Albrighton.", "50'", "Leicester City", "1", "0", "0", "0", "0", "0", "NA", "NA", "NA", "NA", "NA", "NA", "NA", "0", "NA", "NA", "0", "NA", "0", "0", "NA", "NA", "NA", "0", "NA", "NA", "NA", "0", "NA", "NA", "0", "NA", "0", "NA", "NA", "NA", "1", "Swansea City", "Marc Albrighton", "0", "0", "NA", "NA", "NA", "0", "NA", "NA", "NA", "NA", "2", "33", "0", "NA", "NA", "50"], ["480653", "Foul by Wilfred Ndidi (Leicester City).", "51'", "Leicester City", "1", "0", "0", "0", "0", "0", "NA", "NA", "NA", "NA", "NA", "NA", "NA", "1", "Wilfred Ndidi", "Leicester City", "0", "NA", "0", "0", "NA", "NA", "NA", "0", "NA", "NA", "NA", "0", "NA", "NA", "0", "NA", "0", "NA", "NA", "NA", "0", "NA", "NA", "0", "0", "NA", "NA", "NA", "0", "NA", "NA", "NA", "NA", "2", "34", "0", "NA", "NA", "51"], ["480653", "Jordan Ayew (Swansea City) wins a free kick in the attacking half.", "51'", "Leicester City", "1", "0", "0", "0", "0", "0", "NA", "NA", "NA", "NA", "NA", "NA", "NA", "0", "NA", "NA", "0", "NA", "0", "0", "NA", "NA", "NA", "0", "NA", "NA", "NA", "0", "NA", "NA", "0", "NA", "1", "Jordan Ayew", "Swansea City", "attacking half", "0", "NA", "NA", "0", "0", "NA", "NA", "NA", "0", "NA", "NA", "NA", "NA", "2", "35", "0", "NA", "NA", "51"], ["480653", "Corner,  Swansea City. Conceded by Wilfred Ndidi.", "52'", "Leicester City", "1", "0", "0", "0", "0", "0", "NA", "NA", "NA", "NA", "NA", "NA", "NA", "0", "NA", "NA", "0", "NA", "0", "0", "NA", "NA", "NA", "0", "NA", "NA", "NA", "0", "NA", "NA", "0", "NA", "0", "NA", "NA", "NA", "1", "Swansea City", "Wilfred Ndidi", "0", "0", "NA", "NA", "NA", "0", "NA", "NA", "NA", "NA", "2", "36", "0", "NA", "NA", "52"], ["480653", "Goal!  Leicester City 1, Swansea City 1. Federico Fernández (Swansea City) header from very close range to the bottom right corner. Assisted by Ki Sung-yueng with a cross following a corner.", "53'", "Leicester City", "1", "0", "0", "0", "1", "0", "goal", "Federico Fernández", "Swansea City", "header", "very close range", "bottom right corner", "Ki Sung-yueng", "0", "NA", "NA", "0", "cross", "1", "0", "NA", "NA", "NA", "0", "NA", "NA", "NA", "0", "NA", "NA", "0", "NA", "0", "NA", "NA", "NA", "0", "NA", "NA", "0", "0", "NA", "NA", "NA", "0", "NA", "NA", "NA", "NA", "2", "37", "0", "NA", "NA", "53"], ["480653", "Foul by Sam Clucas (Swansea City).", "54'", "Leicester City", "1", "0", "0", "0", "0", "0", "NA", "NA", "NA", "NA", "NA", "NA", "NA", "1", "Sam Clucas", "Swansea City", "0", "NA", "0", "0", "NA", "NA", "NA", "0", "NA", "NA", "NA", "0", "NA", "NA", "0", "NA", "0", "NA", "NA", "NA", "0", "NA", "NA", "0", "0", "NA", "NA", "NA", "0", "NA", "NA", "NA", "NA", "2", "38", "0", "NA", "NA", "54"], ["480653", "Jamie Vardy (Leicester City) wins a free kick on the right wing.", "54'", "Leicester City", "1", "0", "0", "0", "0", "0", "NA", "NA", "NA", "NA", "NA", "NA", "NA", "0", "NA", "NA", "0", "NA", "0", "0", "NA", "NA", "NA", "0", "NA", "NA", "NA", "0", "NA", "NA", "0", "NA", "1", "Jamie Vardy", "Leicester City", "NA", "0", "NA", "NA", "0", "0", "NA", "NA", "NA", "0", "NA", "NA", "NA", "NA", "2", "39", "0", "NA", "NA", "54"], ["480653", "Attempt missed. Harry Maguire (Leicester City) header from the centre of the box misses to the left. Assisted by Marc Albrighton with a cross following a set piece situation.", "54'", "Leicester City", "1", "0", "0", "0", "1", "0", "missed", "Harry Maguire", "Leicester City", "header", "the centre of the box", "left", "Marc Albrighton", "0", "NA", "NA", "1", "cross", "0", "0", "NA", "NA", "NA", "0", "NA", "NA", "NA", "0", "NA", "NA", "0", "NA", "0", "NA", "NA", "NA", "0", "NA", "NA", "0", "0", "NA", "NA", "NA", "0", "NA", "NA", "NA", "NA", "2", "40", "0", "NA", "NA", "54"], ["480653", "Attempt saved. Kelechi Iheanacho (Leicester City) left footed shot from outside the box is saved in the centre of the goal.", "56'", "Leicester City", "1", "0", "0", "0", "1", "0", "saved", "Kelechi Iheanacho", "Leicester City", "left", "outside the box", "the centre of the goal", "NA", "0", "NA", "NA", "0", "NA", "0", "0", "NA", "NA", "NA", "0", "NA", "NA", "NA", "0", "NA", "NA", "0", "NA", "0", "NA", "NA", "NA", "0", "NA", "NA", "0", "0", "NA", "NA", "NA", "0", "NA", "NA", "NA", "NA", "2", "41", "0", "NA", "NA", "56"], ["480653", "Attempt missed. Sam Clucas (Swansea City) header from the centre of the box misses to the right. Assisted by Mike van der Hoorn with a cross.", "58'", "Leicester City", "1", "0", "0", "0", "1", "0", "missed", "Sam Clucas", "Swansea City", "header", "the centre of the box", "right", "Mike van der", "0", "NA", "NA", "0", "cross", "0", "0", "NA", "NA", "NA", "0", "NA", "NA", "NA", "0", "NA", "NA", "0", "NA", "0", "NA", "NA", "NA", "0", "NA", "NA", "0", "0", "NA", "NA", "NA", "0", "NA", "NA", "NA", "NA", "2", "42", "0", "NA", "NA", "58"], ["480653", "Adrien Silva (Leicester City) wins a free kick in the defensive half.", "61'", "Leicester City", "1", "0", "0", "0", "0", "0", "NA", "NA", "NA", "NA", "NA", "NA", "NA", "0", "NA", "NA", "0", "NA", "0", "0", "NA", "NA", "NA", "0", "NA", "NA", "NA", "0", "NA", "NA", "0", "NA", "1", "Adrien Silva", "Leicester City", "defensive half", "0", "NA", "NA", "0", "0", "NA", "NA", "NA", "0", "NA", "NA", "NA", "NA", "2", "43", "0", "NA", "NA", "61"], ["480653", "Foul by Jordan Ayew (Swansea City).", "61'", "Leicester City", "1", "0", "0", "0", "0", "0", "NA", "NA", "NA", "NA", "NA", "NA", "NA", "1", "Jordan Ayew", "Swansea City", "0", "NA", "0", "0", "NA", "NA", "NA", "0", "NA", "NA", "NA", "0", "NA", "NA", "0", "NA", "0", "NA", "NA", "NA", "0", "NA", "NA", "0", "0", "NA", "NA", "NA", "0", "NA", "NA", "NA", "NA", "2", "44", "0", "NA", "NA", "61"], ["480653", "Attempt blocked. Sam Clucas (Swansea City) left footed shot from the centre of the box is blocked. Assisted by Alfie Mawson.", "62'", "Leicester City", "1", "0", "0", "0", "1", "0", "blocked", "Sam Clucas", "Swansea City", "left", "the centre of the box", "NA", "Alfie Mawson", "0", "NA", "NA", "0", "NA", "0", "0", "NA", "NA", "NA", "0", "NA", "NA", "NA", "0", "NA", "NA", "0", "NA", "0", "NA", "NA", "NA", "0", "NA", "NA", "0", "0", "NA", "NA", "NA", "0", "NA", "NA", "NA", "NA", "2", "45", "0", "NA", "NA", "62"], ["480653", "Attempt missed. Jamie Vardy (Leicester City) right footed shot from a difficult angle and long range on the right misses to the left. Assisted by Marc Albrighton.", "63'", "Leicester City", "1", "0", "0", "0", "1", "0", "missed", "Jamie Vardy", "Leicester City", "right", "right shot a difficult angle and long range", "NA", "Marc Albrighton", "0", "NA", "NA", "0", "NA", "0", "0", "NA", "NA", "NA", "0", "NA", "NA", "NA", "0", "NA", "NA", "0", "NA", "0", "NA", "NA", "NA", "0", "NA", "NA", "0", "0", "NA", "NA", "NA", "0", "NA", "NA", "NA", "NA", "2", "46", "0", "NA", "NA", "63"], ["480653", "Attempt missed. Fousseni Diabaté (Leicester City) left footed shot from the centre of the box misses to the left. Assisted by Jamie Vardy following a fast break.", "64'", "Leicester City", "1", "0", "0", "0", "1", "0", "missed", "Fousseni Diabaté", "Leicester City", "left", "the centre of the box", "left", "Jamie Vardy", "0", "NA", "NA", "0", "NA", "0", "0", "NA", "NA", "NA", "0", "NA", "NA", "NA", "0", "NA", "NA", "0", "NA", "0", "NA", "NA", "NA", "0", "NA", "NA", "0", "0", "NA", "NA", "NA", "0", "NA", "NA", "NA", "NA", "2", "47", "0", "NA", "NA", "64"], ["480653", "Substitution, Leicester City. Matty James replaces Adrien Silva.", "68'", "Leicester City", "1", "0", "0", "0", "0", "0", "NA", "NA", "NA", "NA", "NA", "NA", "NA", "0", "NA", "NA", "0", "NA", "0", "0", "NA", "NA", "NA", "0", "NA", "NA", "NA", "0", "NA", "NA", "0", "NA", "0", "NA", "NA", "NA", "0", "NA", "NA", "1", "0", "Leicester City", "Matty James", "Adrien Silva", "0", "NA", "NA", "NA", "NA", "2", "48", "0", "NA", "NA", "68"], ["480653", "Substitution, Leicester City. Demarai Gray replaces Kelechi Iheanacho.", "68'", "Leicester City", "1", "0", "0", "0", "0", "0", "NA", "NA", "NA", "NA", "NA", "NA", "NA", "0", "NA", "NA", "0", "NA", "0", "0", "NA", "NA", "NA", "0", "NA", "NA", "NA", "0", "NA", "NA", "0", "NA", "0", "NA", "NA", "NA", "0", "NA", "NA", "1", "0", "Leicester City", "Demarai Gray", "Kelechi Iheanacho", "0", "NA", "NA", "NA", "NA", "2", "49", "0", "NA", "NA", "68"], ["480653", "Foul by Ki Sung-yueng (Swansea City).", "69'", "Leicester City", "1", "0", "0", "0", "0", "0", "NA", "NA", "NA", "NA", "NA", "NA", "NA", "1", "Ki Sung-yueng", "Swansea City", "0", "NA", "0", "0", "NA", "NA", "NA", "0", "NA", "NA", "NA", "0", "NA", "NA", "0", "NA", "0", "NA", "NA", "NA", "0", "NA", "NA", "0", "0", "NA", "NA", "NA", "0", "NA", "NA", "NA", "NA", "2", "50", "0", "NA", "NA", "69"], ["480653", "Marc Albrighton (Leicester City) wins a free kick in the defensive half.", "69'", "Leicester City", "1", "0", "0", "0", "0", "0", "NA", "NA", "NA", "NA", "NA", "NA", "NA", "0", "NA", "NA", "0", "NA", "0", "0", "NA", "NA", "NA", "0", "NA", "NA", "NA", "0", "NA", "NA", "0", "NA", "1", "Marc Albrighton", "Leicester City", "defensive half", "0", "NA", "NA", "0", "0", "NA", "NA", "NA", "0", "NA", "NA", "NA", "NA", "2", "51", "0", "NA", "NA", "69"], ["480653", "Substitution, Swansea City. Wilfried Bony replaces Nathan Dyer.", "71'", "Leicester City", "1", "0", "0", "0", "0", "0", "NA", "NA", "NA", "NA", "NA", "NA", "NA", "0", "NA", "NA", "0", "NA", "0", "0", "NA", "NA", "NA", "0", "NA", "NA", "NA", "0", "NA", "NA", "0", "NA", "0", "NA", "NA", "NA", "0", "NA", "NA", "1", "0", "Swansea City", "Wilfried Bony", "Nathan Dyer", "0", "NA", "NA", "NA", "NA", "2", "52", "0", "NA", "NA", "71"], ["480653", "Attempt missed. Demarai Gray (Leicester City) right footed shot from the centre of the box is too high. Assisted by Christian Fuchs with a cross.", "73'", "Leicester City", "1", "0", "0", "0", "1", "0", "missed", "Demarai Gray", "Leicester City", "right", "the centre of the box", "too high", "Christian Fuchs", "0", "NA", "NA", "0", "cross", "0", "0", "NA", "NA", "NA", "0", "NA", "NA", "NA", "0", "NA", "NA", "0", "NA", "0", "NA", "NA", "NA", "0", "NA", "NA", "0", "0", "NA", "NA", "NA", "0", "NA", "NA", "NA", "NA", "2", "53", "0", "NA", "NA", "73"], ["480653", "Foul by Federico Fernández (Swansea City).", "76'", "Leicester City", "1", "0", "0", "0", "0", "0", "NA", "NA", "NA", "NA", "NA", "NA", "NA", "1", "Federico Fernández", "Swansea City", "0", "NA", "0", "0", "NA", "NA", "NA", "0", "NA", "NA", "NA", "0", "NA", "NA", "0", "NA", "0", "NA", "NA", "NA", "0", "NA", "NA", "0", "0", "NA", "NA", "NA", "0", "NA", "NA", "NA", "NA", "2", "54", "0", "NA", "NA", "76"], ["480653", "Fousseni Diabaté (Leicester City) wins a free kick in the attacking half.", "76'", "Leicester City", "1", "0", "0", "0", "0", "0", "NA", "NA", "NA", "NA", "NA", "NA", "NA", "0", "NA", "NA", "0", "NA", "0", "0", "NA", "NA", "NA", "0", "NA", "NA", "NA", "0", "NA", "NA", "0", "NA", "1", "Fousseni Diabaté", "Leicester City", "attacking half", "0", "NA", "NA", "0", "0", "NA", "NA", "NA", "0", "NA", "NA", "NA", "NA", "2", "55", "0", "NA", "NA", "76"], ["480653", "Attempt missed. Harry Maguire (Leicester City) header from the left side of the six yard box is close, but misses to the left following a set piece situation.", "77'", "Leicester City", "1", "0", "0", "0", "1", "0", "missed", "Harry Maguire", "Leicester City", "header", "the left side of the six yard box", "close, but left", "NA", "0", "NA", "NA", "1", "NA", "0", "0", "NA", "NA", "NA", "0", "NA", "NA", "NA", "0", "NA", "NA", "0", "NA", "0", "NA", "NA", "NA", "0", "NA", "NA", "0", "0", "NA", "NA", "NA", "0", "NA", "NA", "NA", "NA", "2", "56", "0", "NA", "NA", "77"], ["480653", "Demarai Gray (Leicester City) wins a free kick in the attacking half.", "78'", "Leicester City", "1", "0", "0", "0", "0", "0", "NA", "NA", "NA", "NA", "NA", "NA", "NA", "0", "NA", "NA", "0", "NA", "0", "0", "NA", "NA", "NA", "0", "NA", "NA", "NA", "0", "NA", "NA", "0", "NA", "1", "Demarai Gray", "Leicester City", "attacking half", "0", "NA", "NA", "0", "0", "NA", "NA", "NA", "0", "NA", "NA", "NA", "NA", "2", "57", "0", "NA", "NA", "78"], ["480653", "Foul by Tom Carroll (Swansea City).", "78'", "Leicester City", "1", "0", "0", "0", "0", "0", "NA", "NA", "NA", "NA", "NA", "NA", "NA", "1", "Tom Carroll", "Swansea City", "0", "NA", "0", "0", "NA", "NA", "NA", "0", "NA", "NA", "NA", "0", "NA", "NA", "0", "NA", "0", "NA", "NA", "NA", "0", "NA", "NA", "0", "0", "NA", "NA", "NA", "0", "NA", "NA", "NA", "NA", "2", "58", "0", "NA", "NA", "78"], ["480653", "Foul by Matty James (Leicester City).", "80'", "Leicester City", "1", "0", "0", "0", "0", "0", "NA", "NA", "NA", "NA", "NA", "NA", "NA", "1", "Matty James", "Leicester City", "0", "NA", "0", "0", "NA", "NA", "NA", "0", "NA", "NA", "NA", "0", "NA", "NA", "0", "NA", "0", "NA", "NA", "NA", "0", "NA", "NA", "0", "0", "NA", "NA", "NA", "0", "NA", "NA", "NA", "NA", "2", "59", "0", "NA", "NA", "80"], ["480653", "Tom Carroll (Swansea City) wins a free kick in the attacking half.", "80'", "Leicester City", "1", "0", "0", "0", "0", "0", "NA", "NA", "NA", "NA", "NA", "NA", "NA", "0", "NA", "NA", "0", "NA", "0", "0", "NA", "NA", "NA", "0", "NA", "NA", "NA", "0", "NA", "NA", "0", "NA", "1", "Tom Carroll", "Swansea City", "attacking half", "0", "NA", "NA", "0", "0", "NA", "NA", "NA", "0", "NA", "NA", "NA", "NA", "2", "60", "0", "NA", "NA", "80"], ["480653", "Substitution, Leicester City. Shinji Okazaki replaces Danny Simpson.", "80'", "Leicester City", "1", "0", "0", "0", "0", "0", "NA", "NA", "NA", "NA", "NA", "NA", "NA", "0", "NA", "NA", "0", "NA", "0", "0", "NA", "NA", "NA", "0", "NA", "NA", "NA", "0", "NA", "NA", "0", "NA", "0", "NA", "NA", "NA", "0", "NA", "NA", "1", "0", "Leicester City", "Shinji Okazaki", "Danny Simpson", "0", "NA", "NA", "NA", "NA", "2", "61", "0", "NA", "NA", "80"], ["480653", "Corner,  Leicester City. Conceded by Alfie Mawson.", "83'", "Leicester City", "1", "0", "0", "0", "0", "0", "NA", "NA", "NA", "NA", "NA", "NA", "NA", "0", "NA", "NA", "0", "NA", "0", "0", "NA", "NA", "NA", "0", "NA", "NA", "NA", "0", "NA", "NA", "0", "NA", "0", "NA", "NA", "NA", "1", "Leicester City", "Alfie Mawson", "0", "0", "NA", "NA", "NA", "0", "NA", "NA", "NA", "NA", "2", "62", "0", "NA", "NA", "83"], ["480653", "Attempt blocked. Wilfred Ndidi (Leicester City) left footed shot from outside the box is blocked.", "84'", "Leicester City", "1", "0", "0", "0", "1", "0", "blocked", "Wilfred Ndidi", "Leicester City", "left", "outside the box", "NA", "NA", "0", "NA", "NA", "0", "NA", "0", "0", "NA", "NA", "NA", "0", "NA", "NA", "NA", "0", "NA", "NA", "0", "NA", "0", "NA", "NA", "NA", "0", "NA", "NA", "0", "0", "NA", "NA", "NA", "0", "NA", "NA", "NA", "NA", "2", "63", "0", "NA", "NA", "84"], ["480653", "Attempt blocked. Demarai Gray (Leicester City) right footed shot from the centre of the box is blocked. Assisted by Harry Maguire with a headed pass.", "84'", "Leicester City", "1", "0", "0", "0", "1", "0", "blocked", "Demarai Gray", "Leicester City", "right", "the centre of the box", "NA", "Harry Maguire", "0", "NA", "NA", "0", "NA", "0", "0", "NA", "NA", "NA", "0", "NA", "NA", "NA", "0", "NA", "NA", "0", "NA", "0", "NA", "NA", "NA", "0", "NA", "NA", "0", "0", "NA", "NA", "NA", "0", "NA", "NA", "NA", "NA", "2", "64", "0", "NA", "NA", "84"], ["480653", "Corner,  Leicester City. Conceded by Tom Carroll.", "84'", "Leicester City", "1", "0", "0", "0", "0", "0", "NA", "NA", "NA", "NA", "NA", "NA", "NA", "0", "NA", "NA", "0", "NA", "0", "0", "NA", "NA", "NA", "0", "NA", "NA", "NA", "0", "NA", "NA", "0", "NA", "0", "NA", "NA", "NA", "1", "Leicester City", "Tom Carroll", "0", "0", "NA", "NA", "NA", "0", "NA", "NA", "NA", "NA", "2", "65", "0", "NA", "NA", "84"], ["480653", "Corner,  Leicester City. Conceded by Kyle Naughton.", "86'", "Leicester City", "1", "0", "0", "0", "0", "0", "NA", "NA", "NA", "NA", "NA", "NA", "NA", "0", "NA", "NA", "0", "NA", "0", "0", "NA", "NA", "NA", "0", "NA", "NA", "NA", "0", "NA", "NA", "0", "NA", "0", "NA", "NA", "NA", "1", "Leicester City", "Kyle Naughton", "0", "0", "NA", "NA", "NA", "0", "NA", "NA", "NA", "NA", "2", "66", "0", "NA", "NA", "86"], ["480653", "Offside, Leicester City. Harry Maguire tries a through ball, but Jamie Vardy is caught offside.", "88'", "Leicester City", "1", "0", "0", "0", "0", "0", "NA", "NA", "NA", "NA", "NA", "NA", "NA", "0", "NA", "NA", "0", "NA", "0", "1", "Leicester City", "Jamie Vardy", "Harry Maguire", "0", "NA", "NA", "NA", "0", "NA", "NA", "0", "NA", "0", "NA", "NA", "NA", "0", "NA", "NA", "0", "0", "NA", "NA", "NA", "0", "NA", "NA", "NA", "NA", "2", "67", "0", "NA", "NA", "88"], ["480653", "Offside, Leicester City. Christian Fuchs tries a through ball, but Jamie Vardy is caught offside.", "90'", "Leicester City", "1", "0", "0", "0", "0", "0", "NA", "NA", "NA", "NA", "NA", "NA", "NA", "0", "NA", "NA", "0", "NA", "0", "1", "Leicester City", "Jamie Vardy", "Christian Fuchs", "0", "NA", "NA", "NA", "0", "NA", "NA", "0", "NA", "0", "NA", "NA", "NA", "0", "NA", "NA", "0", "0", "NA", "NA", "NA", "0", "NA", "NA", "NA", "NA", "2", "68", "0", "NA", "NA", "90"], ["480653", "Demarai Gray (Leicester City) wins a free kick in the defensive half.", "90'+1'", "Leicester City", "1", "0", "0", "0", "0", "0", "NA", "NA", "NA", "NA", "NA", "NA", "NA", "0", "NA", "NA", "0", "NA", "0", "0", "NA", "NA", "NA", "0", "NA", "NA", "NA", "0", "NA", "NA", "0", "NA", "1", "Demarai Gray", "Leicester City", "defensive half", "0", "NA", "NA", "0", "0", "NA", "NA", "NA", "0", "NA", "NA", "NA", "NA", "2", "69", "1", "NA", "NA", "91"], ["480653", "Foul by Jordan Ayew (Swansea City).", "90'+1'", "Leicester City", "1", "0", "0", "0", "0", "0", "NA", "NA", "NA", "NA", "NA", "NA", "NA", "1", "Jordan Ayew", "Swansea City", "0", "NA", "0", "0", "NA", "NA", "NA", "0", "NA", "NA", "NA", "0", "NA", "NA", "0", "NA", "0", "NA", "NA", "NA", "0", "NA", "NA", "0", "0", "NA", "NA", "NA", "0", "NA", "NA", "NA", "NA", "2", "70", "1", "NA", "NA", "91"], ["480653", "Substitution, Swansea City. Wayne Routledge replaces Jordan Ayew.", "90'+1'", "Leicester City", "1", "0", "0", "0", "0", "0", "NA", "NA", "NA", "NA", "NA", "NA", "NA", "0", "NA", "NA", "0", "NA", "0", "0", "NA", "NA", "NA", "0", "NA", "NA", "NA", "0", "NA", "NA", "0", "NA", "0", "NA", "NA", "NA", "0", "NA", "NA", "1", "0", "Swansea City", "Wayne Routledge", "Jordan Ayew", "0", "NA", "NA", "NA", "NA", "2", "71", "1", "NA", "NA", "91"], ["480653", "Attempt blocked. Marc Albrighton (Leicester City) right footed shot from the right side of the box is blocked.", "90'+3'", "Leicester City", "1", "0", "0", "0", "1", "0", "blocked", "Marc Albrighton", "Leicester City", "right", "the right side of the box", "NA", "NA", "0", "NA", "NA", "0", "NA", "0", "0", "NA", "NA", "NA", "0", "NA", "NA", "NA", "0", "NA", "NA", "0", "NA", "0", "NA", "NA", "NA", "0", "NA", "NA", "0", "0", "NA", "NA", "NA", "0", "NA", "NA", "NA", "NA", "2", "72", "1", "NA", "NA", "93"], ["480653", "Foul by Harry Maguire (Leicester City).", "90'+3'", "Leicester City", "1", "0", "0", "0", "0", "0", "NA", "NA", "NA", "NA", "NA", "NA", "NA", "1", "Harry Maguire", "Leicester City", "0", "NA", "0", "0", "NA", "NA", "NA", "0", "NA", "NA", "NA", "0", "NA", "NA", "0", "NA", "0", "NA", "NA", "NA", "0", "NA", "NA", "0", "0", "NA", "NA", "NA", "0", "NA", "NA", "NA", "NA", "2", "73", "1", "NA", "NA", "93"], ["480653", "Mike van der Hoorn (Swansea City) wins a free kick in the defensive half.", "90'+3'", "Leicester City", "1", "0", "0", "0", "0", "0", "NA", "NA", "NA", "NA", "NA", "NA", "NA", "0", "NA", "NA", "0", "NA", "0", "0", "NA", "NA", "NA", "0", "NA", "NA", "NA", "0", "NA", "NA", "0", "NA", "1", "NA", "Swansea City", "defensive half", "0", "NA", "NA", "0", "0", "NA", "NA", "NA", "0", "NA", "NA", "NA", "NA", "2", "74", "1", "NA", "NA", "93"], ["480653", "Second Half ends, Leicester City 1, Swansea City 1.", "90'+5'", "Leicester City", "1", "1", "0", "0", "0", "0", "NA", "NA", "NA", "NA", "NA", "NA", "NA", "0", "NA", "NA", "0", "NA", "0", "0", "NA", "NA", "NA", "0", "NA", "NA", "NA", "0", "NA", "NA", "0", "NA", "0", "NA", "NA", "NA", "0", "NA", "NA", "0", "0", "NA", "NA", "NA", "0", "NA", "NA", "NA", "NA", "2", "75", "1", "NA", "NA", "95"], ["480653", "Match ends, Leicester City 1, Swansea City 1.", "90'+5'", "Leicester City", "1", "0", "1", "0", "0", "0", "NA", "NA", "NA", "NA", "NA", "NA", "NA", "0", "NA", "NA", "0", "NA", "0", "0", "NA", "NA", "NA", "0", "NA", "NA", "NA", "0", "NA", "NA", "0", "NA", "0", "NA", "NA", "NA", "0", "NA", "NA", "0", "0", "NA", "NA", "NA", "0", "NA", "NA", "NA", "NA", "2", "76", "1", "NA", "NA", "95"]], "Lineup": {"Home Player 9": "Adrien Silva", "Home Player 8": "Kasper Schmeichel", "Home Player 5": "Kelechi Iheanacho", "Home Player 4": "Christian Fuchs", "Home Player 7": "Wilfred Ndidi", "Home Player 6": "Harry Maguire", "Home Player 1": "Marc Albrighton", "Home Player 3": "Aleksandar Dragovic", "Home Player 2": "Fousseni Diabate", "Away Player 10": "Martin Olsson", "Away Player 11": "Mike van der Hoorn", "Away Player 8": "Alfie Mawson", "Away Player 9": "Kyle Naughton", "Away Player 1": "Jordan Ayew", "Away Player 2": "Sam Clucas", "Away Player 3": "Nathan Dyer", "Away Player 4": "Lukasz Fabianski", "Away Player 5": "Leroy Fer", "Away Player 6": "Federico Fernandez", "Away Player 7": "Ki Sung-yueng", "Game ID": "g_1_42lCR81U", "Home Player 11": "Jamie Vardy", "Home Player 10": "Danny Simpson"}}