{"Stats": {"Full Time Result": "H", "Away Team Corners": 3, "Referee": "G Scott", "Home Team Fouls Committed": 7, "Home Team Corners": 8, "Away Team Shots": 7, "Away Team Red Cards": 0, "Home Team Red Cards": 0, "Half Time Away Team Goals": 0, "Full Time Home Team Goals": 2, "Away Team Yellow Cards": 0, "Away Team Shots on Target": 2, "Half Time Home Team Goals": 1, "Half Time Result": "H", "Home Team Yellow Cards": 0, "Home Team Shots": 14, "Div": "E0", "Away Team Fouls Committed": 9, "Home Team Shots on Target": 3, "Full Time Away Team Goals": 0}, "Description": "Offside, Liverpool. Sadio Mané tries a through ball, but Andrew Robertson is caught offside. at minute 6. Attempt blocked. Mohamed Salah (Liverpool) left footed shot from the centre of the box is blocked. Assisted by Roberto Firmino with a headed pass. at minute 12. Alex Oxlade-Chamberlain (Liverpool) wins a free kick on the left wing. at minute 12. Foul by Mikel Merino (Newcastle United). at minute 12. Attempt missed. Mohamed Salah (Liverpool) left footed shot from the left side of the box is close, but misses to the left. Assisted by Emre Can with a through ball. at minute 16. Foul by Mikel Merino (Newcastle United). at minute 18. Mohamed Salah (Liverpool) wins a free kick in the attacking half. at minute 18. Attempt missed. Emre Can (Liverpool) header from the centre of the box is close, but misses to the left. Assisted by Trent Alexander-Arnold with a cross following a set piece situation. at minute 18. Foul by Alex Oxlade-Chamberlain (Liverpool). at minute 22. Kenedy (Newcastle United) wins a free kick in the defensive half. at minute 22. Foul by Roberto Firmino (Liverpool). at minute 23. Mikel Merino (Newcastle United) wins a free kick in the attacking half. at minute 23. Attempt saved. Florian Lejeune (Newcastle United) right footed shot from outside the box is saved in the bottom left corner. at minute 23. Foul by Dwight Gayle (Newcastle United). at minute 24. Virgil van Dijk (Liverpool) wins a free kick in the defensive half. at minute 24. Corner,  Liverpool. Conceded by Florian Lejeune. at minute 26. Attempt saved. Dejan Lovren (Liverpool) header from the centre of the box is saved in the top left corner. Assisted by Mohamed Salah with a cross. at minute 27. Attempt blocked. Dejan Lovren (Liverpool) header from the left side of the six yard box is blocked. at minute 27. Attempt blocked. Mohamed Salah (Liverpool) right footed shot from the centre of the box is blocked. Assisted by Roberto Firmino. at minute 28. Corner,  Liverpool. Conceded by Florian Lejeune. at minute 28. Christian Atsu (Newcastle United) wins a free kick on the right wing. at minute 29. Foul by Sadio Mané (Liverpool). at minute 29. Attempt missed. Dwight Gayle (Newcastle United) right footed shot from outside the box is too high. Assisted by Christian Atsu. at minute 29. Offside, Liverpool. Virgil van Dijk tries a through ball, but Andrew Robertson is caught offside. at minute 31. Corner,  Liverpool. Conceded by Paul Dummett. at minute 33. Attempt blocked. Roberto Firmino (Liverpool) header from the right side of the six yard box is blocked. Assisted by Mohamed Salah with a cross. at minute 33. Corner,  Liverpool. Conceded by Mohamed Diamé. at minute 33. Offside, Newcastle United. Mikel Merino tries a through ball, but Dwight Gayle is caught offside. at minute 34. Foul by Florian Lejeune (Newcastle United). at minute 38. Mohamed Salah (Liverpool) wins a free kick in the attacking half. at minute 38. Goal!  Liverpool 1, Newcastle United 0. Mohamed Salah (Liverpool) left footed shot from the centre of the box to the high centre of the goal. Assisted by Alex Oxlade-Chamberlain. at minute 40. Attempt missed. Sadio Mané (Liverpool) left footed shot from the centre of the box is high and wide to the left. Assisted by Roberto Firmino. at minute 42. Attempt saved. Mohamed Diamé (Newcastle United) left footed shot from outside the box is saved in the top left corner. Assisted by Mikel Merino. at minute 46. Corner,  Newcastle United. Conceded by Loris Karius. at minute 46. Corner,  Newcastle United. Conceded by Virgil van Dijk. at minute 46. First Half ends, Liverpool 1, Newcastle United 0. at minute 47. Second Half begins Liverpool 1, Newcastle United 0. at minute 45. Corner,  Liverpool. Conceded by Paul Dummett. at minute 48. Hand ball by Jacob Murphy (Newcastle United). at minute 48. Attempt blocked. Mohamed Salah (Liverpool) left footed shot from the centre of the box is blocked. Assisted by Andrew Robertson. at minute 52. Foul by Alex Oxlade-Chamberlain (Liverpool). at minute 52. Kenedy (Newcastle United) wins a free kick on the left wing. at minute 52. Goal!  Liverpool 2, Newcastle United 0. Sadio Mané (Liverpool) right footed shot from the centre of the box to the bottom right corner. Assisted by Roberto Firmino. at minute 55. Foul by Andrew Robertson (Liverpool). at minute 61. Mikel Merino (Newcastle United) wins a free kick on the right wing. at minute 61. Substitution, Newcastle United. Joselu replaces Dwight Gayle. at minute 66. Corner,  Liverpool. Conceded by Kenedy. at minute 67. Attempt blocked. Virgil van Dijk (Liverpool) right footed shot from the centre of the box is blocked. Assisted by Dejan Lovren with a headed pass. at minute 68. Andrew Robertson (Liverpool) wins a free kick on the left wing. at minute 68. Foul by DeAndre Yedlin (Newcastle United). at minute 68. Emre Can (Liverpool) wins a free kick in the defensive half. at minute 69. Foul by Mohamed Diamé (Newcastle United). at minute 69. Offside, Liverpool. Emre Can tries a through ball, but Andrew Robertson is caught offside. at minute 69. Attempt blocked. Jacob Murphy (Newcastle United) right footed shot from outside the box is blocked. Assisted by Christian Atsu. at minute 73. Substitution, Newcastle United. Isaac Hayden replaces Mikel Merino. at minute 73. Substitution, Liverpool. Adam Lallana replaces Sadio Mané. at minute 74. Offside, Liverpool. Alex Oxlade-Chamberlain tries a through ball, but Adam Lallana is caught offside. at minute 76. Attempt blocked. Kenedy (Newcastle United) right footed shot from outside the box is blocked. at minute 77. Corner,  Newcastle United. Conceded by Dejan Lovren. at minute 77. Attempt missed. Isaac Hayden (Newcastle United) header from the centre of the box is close, but misses to the right. Assisted by Christian Atsu with a cross following a corner. at minute 77. Substitution, Liverpool. James Milner replaces Alex Oxlade-Chamberlain. at minute 79. Emre Can (Liverpool) wins a free kick in the defensive half. at minute 80. Foul by Kenedy (Newcastle United). at minute 80. Attempt blocked. Roberto Firmino (Liverpool) right footed shot from outside the box is blocked. at minute 81. Attempt blocked. Jordan Henderson (Liverpool) right footed shot from outside the box is blocked. at minute 81. Corner,  Liverpool. Conceded by Isaac Hayden. at minute 81. Foul by Jordan Henderson (Liverpool). at minute 82. Isaac Hayden (Newcastle United) wins a free kick on the right wing. at minute 82. Attempt blocked. Joselu (Newcastle United) left footed shot from outside the box is blocked. Assisted by Jamaal Lascelles with a headed pass. at minute 83. Substitution, Newcastle United. Ayoze Pérez replaces Jacob Murphy. at minute 84. Adam Lallana (Liverpool) wins a free kick on the left wing. at minute 87. Foul by DeAndre Yedlin (Newcastle United). at minute 87. Substitution, Liverpool. Joel Matip replaces Roberto Firmino. at minute 88. Corner,  Liverpool. Conceded by Mohamed Diamé. at minute 89. Ayoze Pérez (Newcastle United) wins a free kick in the defensive half. at minute 91. Foul by Virgil van Dijk (Liverpool). at minute 91. Second Half ends, Liverpool 2, Newcastle United 0. at minute 95. Match ends, Liverpool 2, Newcastle United 0. at minute 95. ", "Home Team": "Liverpool", "Away Team": "Newcastle United", "Date": "03-03-2018", "Commentary": [["480622", "First Half begins.", "-", "Liverpool", "0", "0", "0", "1", "0", "0", "NA", "NA", "NA", "NA", "NA", "NA", "NA", "0", "NA", "NA", "0", "NA", "0", "0", "NA", "NA", "NA", "0", "NA", "NA", "NA", "0", "NA", "NA", "0", "NA", "0", "NA", "NA", "NA", "0", "NA", "NA", "0", "0", "NA", "NA", "NA", "0", "NA", "NA", "NA", "NA", "1", "1", "0", "NA", "NA", "NA"], ["480622", "Lineups are announced and players are warming up.", "-", "Liverpool", "0", "0", "0", "0", "0", "0", "NA", "NA", "NA", "NA", "NA", "NA", "NA", "0", "NA", "NA", "0", "NA", "0", "0", "NA", "NA", "NA", "0", "NA", "NA", "NA", "0", "NA", "NA", "0", "NA", "0", "NA", "NA", "NA", "0", "NA", "NA", "0", "0", "NA", "NA", "NA", "0", "NA", "NA", "NA", "NA", "1", "2", "0", "NA", "NA", "NA"], ["480622", "Offside, Liverpool. Sadio Mané tries a through ball, but Andrew Robertson is caught offside.", "6'", "Liverpool", "0", "0", "0", "0", "0", "0", "NA", "NA", "NA", "NA", "NA", "NA", "NA", "0", "NA", "NA", "0", "NA", "0", "1", "Liverpool", "Andrew Robertson", "Sadio Mané", "0", "NA", "NA", "NA", "0", "NA", "NA", "0", "NA", "0", "NA", "NA", "NA", "0", "NA", "NA", "0", "0", "NA", "NA", "NA", "0", "NA", "NA", "NA", "NA", "1", "3", "0", "NA", "NA", "6"], ["480622", "Attempt blocked. Mohamed Salah (Liverpool) left footed shot from the centre of the box is blocked. Assisted by Roberto Firmino with a headed pass.", "12'", "Liverpool", "0", "0", "0", "0", "1", "0", "blocked", "Mohamed Salah", "Liverpool", "left", "the centre of the box", "NA", "Roberto Firmino", "0", "NA", "NA", "0", "NA", "0", "0", "NA", "NA", "NA", "0", "NA", "NA", "NA", "0", "NA", "NA", "0", "NA", "0", "NA", "NA", "NA", "0", "NA", "NA", "0", "0", "NA", "NA", "NA", "0", "NA", "NA", "NA", "NA", "1", "4", "0", "NA", "NA", "12"], ["480622", "Alex Oxlade-Chamberlain (Liverpool) wins a free kick on the left wing.", "12'", "Liverpool", "0", "0", "0", "0", "0", "0", "NA", "NA", "NA", "NA", "NA", "NA", "NA", "0", "NA", "NA", "0", "NA", "0", "0", "NA", "NA", "NA", "0", "NA", "NA", "NA", "0", "NA", "NA", "0", "NA", "1", "Alex Oxlade-Chamberlain", "Liverpool", "NA", "0", "NA", "NA", "0", "0", "NA", "NA", "NA", "0", "NA", "NA", "NA", "NA", "1", "5", "0", "NA", "NA", "12"], ["480622", "Foul by Mikel Merino (Newcastle United).", "12'", "Liverpool", "0", "0", "0", "0", "0", "0", "NA", "NA", "NA", "NA", "NA", "NA", "NA", "1", "Mikel Merino", "Newcastle United", "0", "NA", "0", "0", "NA", "NA", "NA", "0", "NA", "NA", "NA", "0", "NA", "NA", "0", "NA", "0", "NA", "NA", "NA", "0", "NA", "NA", "0", "0", "NA", "NA", "NA", "0", "NA", "NA", "NA", "NA", "1", "6", "0", "NA", "NA", "12"], ["480622", "Attempt missed. Mohamed Salah (Liverpool) left footed shot from the left side of the box is close, but misses to the left. Assisted by Emre Can with a through ball.", "16'", "Liverpool", "0", "0", "0", "0", "1", "0", "missed", "Mohamed Salah", "Liverpool", "left", "the left side of the box", "close, but left", "Emre Can", "0", "NA", "NA", "0", "through", "0", "0", "NA", "NA", "NA", "0", "NA", "NA", "NA", "0", "NA", "NA", "0", "NA", "0", "NA", "NA", "NA", "0", "NA", "NA", "0", "0", "NA", "NA", "NA", "0", "NA", "NA", "NA", "NA", "1", "7", "0", "NA", "NA", "16"], ["480622", "Foul by Mikel Merino (Newcastle United).", "18'", "Liverpool", "0", "0", "0", "0", "0", "0", "NA", "NA", "NA", "NA", "NA", "NA", "NA", "1", "Mikel Merino", "Newcastle United", "0", "NA", "0", "0", "NA", "NA", "NA", "0", "NA", "NA", "NA", "0", "NA", "NA", "0", "NA", "0", "NA", "NA", "NA", "0", "NA", "NA", "0", "0", "NA", "NA", "NA", "0", "NA", "NA", "NA", "NA", "1", "8", "0", "NA", "NA", "18"], ["480622", "Mohamed Salah (Liverpool) wins a free kick in the attacking half.", "18'", "Liverpool", "0", "0", "0", "0", "0", "0", "NA", "NA", "NA", "NA", "NA", "NA", "NA", "0", "NA", "NA", "0", "NA", "0", "0", "NA", "NA", "NA", "0", "NA", "NA", "NA", "0", "NA", "NA", "0", "NA", "1", "Mohamed Salah", "Liverpool", "attacking half", "0", "NA", "NA", "0", "0", "NA", "NA", "NA", "0", "NA", "NA", "NA", "NA", "1", "9", "0", "NA", "NA", "18"], ["480622", "Attempt missed. Emre Can (Liverpool) header from the centre of the box is close, but misses to the left. Assisted by Trent Alexander-Arnold with a cross following a set piece situation.", "18'", "Liverpool", "0", "0", "0", "0", "1", "0", "missed", "Emre Can", "Liverpool", "header", "the centre of the box", "close, but left", "Trent Alexander-Arnold", "0", "NA", "NA", "1", "cross", "0", "0", "NA", "NA", "NA", "0", "NA", "NA", "NA", "0", "NA", "NA", "0", "NA", "0", "NA", "NA", "NA", "0", "NA", "NA", "0", "0", "NA", "NA", "NA", "0", "NA", "NA", "NA", "NA", "1", "10", "0", "NA", "NA", "18"], ["480622", "Foul by Alex Oxlade-Chamberlain (Liverpool).", "22'", "Liverpool", "0", "0", "0", "0", "0", "0", "NA", "NA", "NA", "NA", "NA", "NA", "NA", "1", "Alex Oxlade-Chamberlain", "Liverpool", "0", "NA", "0", "0", "NA", "NA", "NA", "0", "NA", "NA", "NA", "0", "NA", "NA", "0", "NA", "0", "NA", "NA", "NA", "0", "NA", "NA", "0", "0", "NA", "NA", "NA", "0", "NA", "NA", "NA", "NA", "1", "11", "0", "NA", "NA", "22"], ["480622", "Kenedy (Newcastle United) wins a free kick in the defensive half.", "22'", "Liverpool", "0", "0", "0", "0", "0", "0", "NA", "NA", "NA", "NA", "NA", "NA", "NA", "0", "NA", "NA", "0", "NA", "0", "0", "NA", "NA", "NA", "0", "NA", "NA", "NA", "0", "NA", "NA", "0", "NA", "1", "Kenedy", "Newcastle United", "defensive half", "0", "NA", "NA", "0", "0", "NA", "NA", "NA", "0", "NA", "NA", "NA", "NA", "1", "12", "0", "NA", "NA", "22"], ["480622", "Foul by Roberto Firmino (Liverpool).", "23'", "Liverpool", "0", "0", "0", "0", "0", "0", "NA", "NA", "NA", "NA", "NA", "NA", "NA", "1", "Roberto Firmino", "Liverpool", "0", "NA", "0", "0", "NA", "NA", "NA", "0", "NA", "NA", "NA", "0", "NA", "NA", "0", "NA", "0", "NA", "NA", "NA", "0", "NA", "NA", "0", "0", "NA", "NA", "NA", "0", "NA", "NA", "NA", "NA", "1", "13", "0", "NA", "NA", "23"], ["480622", "Mikel Merino (Newcastle United) wins a free kick in the attacking half.", "23'", "Liverpool", "0", "0", "0", "0", "0", "0", "NA", "NA", "NA", "NA", "NA", "NA", "NA", "0", "NA", "NA", "0", "NA", "0", "0", "NA", "NA", "NA", "0", "NA", "NA", "NA", "0", "NA", "NA", "0", "NA", "1", "Mikel Merino", "Newcastle United", "attacking half", "0", "NA", "NA", "0", "0", "NA", "NA", "NA", "0", "NA", "NA", "NA", "NA", "1", "14", "0", "NA", "NA", "23"], ["480622", "Attempt saved. Florian Lejeune (Newcastle United) right footed shot from outside the box is saved in the bottom left corner.", "23'", "Liverpool", "0", "0", "0", "0", "1", "0", "saved", "Florian Lejeune", "Newcastle United", "right", "outside the box", "the bottom left corner", "NA", "0", "NA", "NA", "0", "NA", "0", "0", "NA", "NA", "NA", "0", "NA", "NA", "NA", "0", "NA", "NA", "0", "NA", "0", "NA", "NA", "NA", "0", "NA", "NA", "0", "0", "NA", "NA", "NA", "0", "NA", "NA", "NA", "NA", "1", "15", "0", "NA", "NA", "23"], ["480622", "Foul by Dwight Gayle (Newcastle United).", "24'", "Liverpool", "0", "0", "0", "0", "0", "0", "NA", "NA", "NA", "NA", "NA", "NA", "NA", "1", "Dwight Gayle", "Newcastle United", "0", "NA", "0", "0", "NA", "NA", "NA", "0", "NA", "NA", "NA", "0", "NA", "NA", "0", "NA", "0", "NA", "NA", "NA", "0", "NA", "NA", "0", "0", "NA", "NA", "NA", "0", "NA", "NA", "NA", "NA", "1", "16", "0", "NA", "NA", "24"], ["480622", "Virgil van Dijk (Liverpool) wins a free kick in the defensive half.", "24'", "Liverpool", "0", "0", "0", "0", "0", "0", "NA", "NA", "NA", "NA", "NA", "NA", "NA", "0", "NA", "NA", "0", "NA", "0", "0", "NA", "NA", "NA", "0", "NA", "NA", "NA", "0", "NA", "NA", "0", "NA", "1", "Virgil van Dijk", "Liverpool", "defensive half", "0", "NA", "NA", "0", "0", "NA", "NA", "NA", "0", "NA", "NA", "NA", "NA", "1", "17", "0", "NA", "NA", "24"], ["480622", "Corner,  Liverpool. Conceded by Florian Lejeune.", "26'", "Liverpool", "0", "0", "0", "0", "0", "0", "NA", "NA", "NA", "NA", "NA", "NA", "NA", "0", "NA", "NA", "0", "NA", "0", "0", "NA", "NA", "NA", "0", "NA", "NA", "NA", "0", "NA", "NA", "0", "NA", "0", "NA", "NA", "NA", "1", "Liverpool", "Florian Lejeune", "0", "0", "NA", "NA", "NA", "0", "NA", "NA", "NA", "NA", "1", "18", "0", "NA", "NA", "26"], ["480622", "Attempt saved. Dejan Lovren (Liverpool) header from the centre of the box is saved in the top left corner. Assisted by Mohamed Salah with a cross.", "27'", "Liverpool", "0", "0", "0", "0", "1", "0", "saved", "Dejan Lovren", "Liverpool", "header", "the centre of the box", "the top left corner", "Mohamed Salah", "0", "NA", "NA", "0", "cross", "0", "0", "NA", "NA", "NA", "0", "NA", "NA", "NA", "0", "NA", "NA", "0", "NA", "0", "NA", "NA", "NA", "0", "NA", "NA", "0", "0", "NA", "NA", "NA", "0", "NA", "NA", "NA", "NA", "1", "19", "0", "NA", "NA", "27"], ["480622", "Attempt blocked. Dejan Lovren (Liverpool) header from the left side of the six yard box is blocked.", "27'", "Liverpool", "0", "0", "0", "0", "1", "0", "blocked", "Dejan Lovren", "Liverpool", "header", "the left side of the six yard box", "NA", "NA", "0", "NA", "NA", "0", "NA", "0", "0", "NA", "NA", "NA", "0", "NA", "NA", "NA", "0", "NA", "NA", "0", "NA", "0", "NA", "NA", "NA", "0", "NA", "NA", "0", "0", "NA", "NA", "NA", "0", "NA", "NA", "NA", "NA", "1", "20", "0", "NA", "NA", "27"], ["480622", "Attempt blocked. Mohamed Salah (Liverpool) right footed shot from the centre of the box is blocked. Assisted by Roberto Firmino.", "28'", "Liverpool", "0", "0", "0", "0", "1", "0", "blocked", "Mohamed Salah", "Liverpool", "right", "the centre of the box", "NA", "Roberto Firmino", "0", "NA", "NA", "0", "NA", "0", "0", "NA", "NA", "NA", "0", "NA", "NA", "NA", "0", "NA", "NA", "0", "NA", "0", "NA", "NA", "NA", "0", "NA", "NA", "0", "0", "NA", "NA", "NA", "0", "NA", "NA", "NA", "NA", "1", "21", "0", "NA", "NA", "28"], ["480622", "Corner,  Liverpool. Conceded by Florian Lejeune.", "28'", "Liverpool", "0", "0", "0", "0", "0", "0", "NA", "NA", "NA", "NA", "NA", "NA", "NA", "0", "NA", "NA", "0", "NA", "0", "0", "NA", "NA", "NA", "0", "NA", "NA", "NA", "0", "NA", "NA", "0", "NA", "0", "NA", "NA", "NA", "1", "Liverpool", "Florian Lejeune", "0", "0", "NA", "NA", "NA", "0", "NA", "NA", "NA", "NA", "1", "22", "0", "NA", "NA", "28"], ["480622", "Christian Atsu (Newcastle United) wins a free kick on the right wing.", "29'", "Liverpool", "0", "0", "0", "0", "0", "0", "NA", "NA", "NA", "NA", "NA", "NA", "NA", "0", "NA", "NA", "0", "NA", "0", "0", "NA", "NA", "NA", "0", "NA", "NA", "NA", "0", "NA", "NA", "0", "NA", "1", "Christian Atsu", "Newcastle United", "NA", "0", "NA", "NA", "0", "0", "NA", "NA", "NA", "0", "NA", "NA", "NA", "NA", "1", "23", "0", "NA", "NA", "29"], ["480622", "Foul by Sadio Mané (Liverpool).", "29'", "Liverpool", "0", "0", "0", "0", "0", "0", "NA", "NA", "NA", "NA", "NA", "NA", "NA", "1", "Sadio Mané", "Liverpool", "0", "NA", "0", "0", "NA", "NA", "NA", "0", "NA", "NA", "NA", "0", "NA", "NA", "0", "NA", "0", "NA", "NA", "NA", "0", "NA", "NA", "0", "0", "NA", "NA", "NA", "0", "NA", "NA", "NA", "NA", "1", "24", "0", "NA", "NA", "29"], ["480622", "Attempt missed. Dwight Gayle (Newcastle United) right footed shot from outside the box is too high. Assisted by Christian Atsu.", "29'", "Liverpool", "0", "0", "0", "0", "1", "0", "missed", "Dwight Gayle", "Newcastle United", "right", "outside the box", "too high", "Christian Atsu", "0", "NA", "NA", "0", "NA", "0", "0", "NA", "NA", "NA", "0", "NA", "NA", "NA", "0", "NA", "NA", "0", "NA", "0", "NA", "NA", "NA", "0", "NA", "NA", "0", "0", "NA", "NA", "NA", "0", "NA", "NA", "NA", "NA", "1", "25", "0", "NA", "NA", "29"], ["480622", "Offside, Liverpool. Virgil van Dijk tries a through ball, but Andrew Robertson is caught offside.", "31'", "Liverpool", "0", "0", "0", "0", "0", "0", "NA", "NA", "NA", "NA", "NA", "NA", "NA", "0", "NA", "NA", "0", "NA", "0", "1", "Liverpool", "Andrew Robertson", "Virgil van Dijk", "0", "NA", "NA", "NA", "0", "NA", "NA", "0", "NA", "0", "NA", "NA", "NA", "0", "NA", "NA", "0", "0", "NA", "NA", "NA", "0", "NA", "NA", "NA", "NA", "1", "26", "0", "NA", "NA", "31"], ["480622", "Corner,  Liverpool. Conceded by Paul Dummett.", "33'", "Liverpool", "0", "0", "0", "0", "0", "0", "NA", "NA", "NA", "NA", "NA", "NA", "NA", "0", "NA", "NA", "0", "NA", "0", "0", "NA", "NA", "NA", "0", "NA", "NA", "NA", "0", "NA", "NA", "0", "NA", "0", "NA", "NA", "NA", "1", "Liverpool", "Paul Dummett", "0", "0", "NA", "NA", "NA", "0", "NA", "NA", "NA", "NA", "1", "27", "0", "NA", "NA", "33"], ["480622", "Attempt blocked. Roberto Firmino (Liverpool) header from the right side of the six yard box is blocked. Assisted by Mohamed Salah with a cross.", "33'", "Liverpool", "0", "0", "0", "0", "1", "0", "blocked", "Roberto Firmino", "Liverpool", "header", "the right side of the six yard box", "NA", "Mohamed Salah", "0", "NA", "NA", "0", "cross", "0", "0", "NA", "NA", "NA", "0", "NA", "NA", "NA", "0", "NA", "NA", "0", "NA", "0", "NA", "NA", "NA", "0", "NA", "NA", "0", "0", "NA", "NA", "NA", "0", "NA", "NA", "NA", "NA", "1", "28", "0", "NA", "NA", "33"], ["480622", "Corner,  Liverpool. Conceded by Mohamed Diamé.", "33'", "Liverpool", "0", "0", "0", "0", "0", "0", "NA", "NA", "NA", "NA", "NA", "NA", "NA", "0", "NA", "NA", "0", "NA", "0", "0", "NA", "NA", "NA", "0", "NA", "NA", "NA", "0", "NA", "NA", "0", "NA", "0", "NA", "NA", "NA", "1", "Liverpool", "Mohamed Diamé", "0", "0", "NA", "NA", "NA", "0", "NA", "NA", "NA", "NA", "1", "29", "0", "NA", "NA", "33"], ["480622", "Offside, Newcastle United. Mikel Merino tries a through ball, but Dwight Gayle is caught offside.", "34'", "Liverpool", "0", "0", "0", "0", "0", "0", "NA", "NA", "NA", "NA", "NA", "NA", "NA", "0", "NA", "NA", "0", "NA", "0", "1", "Newcastle United", "Dwight Gayle", "Mikel Merino", "0", "NA", "NA", "NA", "0", "NA", "NA", "0", "NA", "0", "NA", "NA", "NA", "0", "NA", "NA", "0", "0", "NA", "NA", "NA", "0", "NA", "NA", "NA", "NA", "1", "30", "0", "NA", "NA", "34"], ["480622", "Foul by Florian Lejeune (Newcastle United).", "38'", "Liverpool", "0", "0", "0", "0", "0", "0", "NA", "NA", "NA", "NA", "NA", "NA", "NA", "1", "Florian Lejeune", "Newcastle United", "0", "NA", "0", "0", "NA", "NA", "NA", "0", "NA", "NA", "NA", "0", "NA", "NA", "0", "NA", "0", "NA", "NA", "NA", "0", "NA", "NA", "0", "0", "NA", "NA", "NA", "0", "NA", "NA", "NA", "NA", "1", "31", "0", "NA", "NA", "38"], ["480622", "Mohamed Salah (Liverpool) wins a free kick in the attacking half.", "38'", "Liverpool", "0", "0", "0", "0", "0", "0", "NA", "NA", "NA", "NA", "NA", "NA", "NA", "0", "NA", "NA", "0", "NA", "0", "0", "NA", "NA", "NA", "0", "NA", "NA", "NA", "0", "NA", "NA", "0", "NA", "1", "Mohamed Salah", "Liverpool", "attacking half", "0", "NA", "NA", "0", "0", "NA", "NA", "NA", "0", "NA", "NA", "NA", "NA", "1", "32", "0", "NA", "NA", "38"], ["480622", "Goal!  Liverpool 1, Newcastle United 0. Mohamed Salah (Liverpool) left footed shot from the centre of the box to the high centre of the goal. Assisted by Alex Oxlade-Chamberlain.", "40'", "Liverpool", "1", "0", "0", "0", "1", "0", "goal", "Mohamed Salah", "Liverpool", "left", "the centre of the box", "high centre of the goal", "Alex Oxlade-Chamberlain", "0", "NA", "NA", "0", "NA", "0", "0", "NA", "NA", "NA", "0", "NA", "NA", "NA", "0", "NA", "NA", "0", "NA", "0", "NA", "NA", "NA", "0", "NA", "NA", "0", "0", "NA", "NA", "NA", "0", "NA", "NA", "NA", "NA", "1", "33", "0", "NA", "NA", "40"], ["480622", "Attempt missed. Sadio Mané (Liverpool) left footed shot from the centre of the box is high and wide to the left. Assisted by Roberto Firmino.", "42'", "Liverpool", "1", "0", "0", "0", "1", "0", "missed", "Sadio Mané", "Liverpool", "left", "the centre of the box", "high and wide to the left", "Roberto Firmino", "0", "NA", "NA", "0", "NA", "0", "0", "NA", "NA", "NA", "0", "NA", "NA", "NA", "0", "NA", "NA", "0", "NA", "0", "NA", "NA", "NA", "0", "NA", "NA", "0", "0", "NA", "NA", "NA", "0", "NA", "NA", "NA", "NA", "1", "34", "0", "NA", "NA", "42"], ["480622", "Attempt saved. Mohamed Diamé (Newcastle United) left footed shot from outside the box is saved in the top left corner. Assisted by Mikel Merino.", "45'+1'", "Liverpool", "1", "0", "0", "0", "1", "0", "saved", "Mohamed Diamé", "Newcastle United", "left", "outside the box", "the top left corner", "Mikel Merino", "0", "NA", "NA", "0", "NA", "0", "0", "NA", "NA", "NA", "0", "NA", "NA", "NA", "0", "NA", "NA", "0", "NA", "0", "NA", "NA", "NA", "0", "NA", "NA", "0", "0", "NA", "NA", "NA", "0", "NA", "NA", "NA", "NA", "1", "35", "1", "NA", "NA", "46"], ["480622", "Corner,  Newcastle United. Conceded by Loris Karius.", "45'+1'", "Liverpool", "1", "0", "0", "0", "0", "0", "NA", "NA", "NA", "NA", "NA", "NA", "NA", "0", "NA", "NA", "0", "NA", "0", "0", "NA", "NA", "NA", "0", "NA", "NA", "NA", "0", "NA", "NA", "0", "NA", "0", "NA", "NA", "NA", "1", "Newcastle United", "Loris Karius", "0", "0", "NA", "NA", "NA", "0", "NA", "NA", "NA", "NA", "1", "36", "1", "NA", "NA", "46"], ["480622", "Corner,  Newcastle United. Conceded by Virgil van Dijk.", "45'+1'", "Liverpool", "1", "0", "0", "0", "0", "0", "NA", "NA", "NA", "NA", "NA", "NA", "NA", "0", "NA", "NA", "0", "NA", "0", "0", "NA", "NA", "NA", "0", "NA", "NA", "NA", "0", "NA", "NA", "0", "NA", "0", "NA", "NA", "NA", "1", "Newcastle United", "Virgil van Dijk", "0", "0", "NA", "NA", "NA", "0", "NA", "NA", "NA", "NA", "1", "37", "1", "NA", "NA", "46"], ["480622", "First Half ends, Liverpool 1, Newcastle United 0.", "45'+2'", "Liverpool", "1", "1", "0", "0", "0", "0", "NA", "NA", "NA", "NA", "NA", "NA", "NA", "0", "NA", "NA", "0", "NA", "0", "0", "NA", "NA", "NA", "0", "NA", "NA", "NA", "0", "NA", "NA", "0", "NA", "0", "NA", "NA", "NA", "0", "NA", "NA", "0", "0", "NA", "NA", "NA", "0", "NA", "NA", "NA", "NA", "1", "38", "1", "NA", "NA", "47"], ["480622", "Second Half begins Liverpool 1, Newcastle United 0.", "45'", "Liverpool", "1", "0", "0", "1", "0", "0", "NA", "NA", "NA", "NA", "NA", "NA", "NA", "0", "NA", "NA", "0", "NA", "0", "0", "NA", "NA", "NA", "0", "NA", "NA", "NA", "0", "NA", "NA", "0", "NA", "0", "NA", "NA", "NA", "0", "NA", "NA", "0", "0", "NA", "NA", "NA", "0", "NA", "NA", "NA", "NA", "2", "39", "0", "NA", "NA", "45"], ["480622", "Corner,  Liverpool. Conceded by Paul Dummett.", "48'", "Liverpool", "1", "0", "0", "0", "0", "0", "NA", "NA", "NA", "NA", "NA", "NA", "NA", "0", "NA", "NA", "0", "NA", "0", "0", "NA", "NA", "NA", "0", "NA", "NA", "NA", "0", "NA", "NA", "0", "NA", "0", "NA", "NA", "NA", "1", "Liverpool", "Paul Dummett", "0", "0", "NA", "NA", "NA", "0", "NA", "NA", "NA", "NA", "2", "40", "0", "NA", "NA", "48"], ["480622", "Hand ball by Jacob Murphy (Newcastle United).", "48'", "Liverpool", "1", "0", "0", "0", "0", "0", "NA", "NA", "NA", "NA", "NA", "NA", "NA", "0", "NA", "NA", "0", "NA", "0", "0", "NA", "NA", "NA", "0", "NA", "NA", "NA", "0", "NA", "NA", "0", "NA", "0", "NA", "NA", "NA", "0", "NA", "NA", "0", "0", "NA", "NA", "NA", "0", "NA", "NA", "NA", "NA", "2", "41", "0", "NA", "NA", "48"], ["480622", "Attempt blocked. Mohamed Salah (Liverpool) left footed shot from the centre of the box is blocked. Assisted by Andrew Robertson.", "52'", "Liverpool", "1", "0", "0", "0", "1", "0", "blocked", "Mohamed Salah", "Liverpool", "left", "the centre of the box", "NA", "Andrew Robertson", "0", "NA", "NA", "0", "NA", "0", "0", "NA", "NA", "NA", "0", "NA", "NA", "NA", "0", "NA", "NA", "0", "NA", "0", "NA", "NA", "NA", "0", "NA", "NA", "0", "0", "NA", "NA", "NA", "0", "NA", "NA", "NA", "NA", "2", "42", "0", "NA", "NA", "52"], ["480622", "Foul by Alex Oxlade-Chamberlain (Liverpool).", "52'", "Liverpool", "1", "0", "0", "0", "0", "0", "NA", "NA", "NA", "NA", "NA", "NA", "NA", "1", "Alex Oxlade-Chamberlain", "Liverpool", "0", "NA", "0", "0", "NA", "NA", "NA", "0", "NA", "NA", "NA", "0", "NA", "NA", "0", "NA", "0", "NA", "NA", "NA", "0", "NA", "NA", "0", "0", "NA", "NA", "NA", "0", "NA", "NA", "NA", "NA", "2", "43", "0", "NA", "NA", "52"], ["480622", "Kenedy (Newcastle United) wins a free kick on the left wing.", "52'", "Liverpool", "1", "0", "0", "0", "0", "0", "NA", "NA", "NA", "NA", "NA", "NA", "NA", "0", "NA", "NA", "0", "NA", "0", "0", "NA", "NA", "NA", "0", "NA", "NA", "NA", "0", "NA", "NA", "0", "NA", "1", "Kenedy", "Newcastle United", "NA", "0", "NA", "NA", "0", "0", "NA", "NA", "NA", "0", "NA", "NA", "NA", "NA", "2", "44", "0", "NA", "NA", "52"], ["480622", "Goal!  Liverpool 2, Newcastle United 0. Sadio Mané (Liverpool) right footed shot from the centre of the box to the bottom right corner. Assisted by Roberto Firmino.", "55'", "Liverpool", "2", "0", "0", "0", "1", "0", "goal", "Sadio Mané", "Liverpool", "right", "the centre of the box", "bottom right corner", "Roberto Firmino", "0", "NA", "NA", "0", "NA", "0", "0", "NA", "NA", "NA", "0", "NA", "NA", "NA", "0", "NA", "NA", "0", "NA", "0", "NA", "NA", "NA", "0", "NA", "NA", "0", "0", "NA", "NA", "NA", "0", "NA", "NA", "NA", "NA", "2", "45", "0", "NA", "NA", "55"], ["480622", "Foul by Andrew Robertson (Liverpool).", "61'", "Liverpool", "2", "0", "0", "0", "0", "0", "NA", "NA", "NA", "NA", "NA", "NA", "NA", "1", "Andrew Robertson", "Liverpool", "0", "NA", "0", "0", "NA", "NA", "NA", "0", "NA", "NA", "NA", "0", "NA", "NA", "0", "NA", "0", "NA", "NA", "NA", "0", "NA", "NA", "0", "0", "NA", "NA", "NA", "0", "NA", "NA", "NA", "NA", "2", "46", "0", "NA", "NA", "61"], ["480622", "Mikel Merino (Newcastle United) wins a free kick on the right wing.", "61'", "Liverpool", "2", "0", "0", "0", "0", "0", "NA", "NA", "NA", "NA", "NA", "NA", "NA", "0", "NA", "NA", "0", "NA", "0", "0", "NA", "NA", "NA", "0", "NA", "NA", "NA", "0", "NA", "NA", "0", "NA", "1", "Mikel Merino", "Newcastle United", "NA", "0", "NA", "NA", "0", "0", "NA", "NA", "NA", "0", "NA", "NA", "NA", "NA", "2", "47", "0", "NA", "NA", "61"], ["480622", "Substitution, Newcastle United. Joselu replaces Dwight Gayle.", "66'", "Liverpool", "2", "0", "0", "0", "0", "0", "NA", "NA", "NA", "NA", "NA", "NA", "NA", "0", "NA", "NA", "0", "NA", "0", "0", "NA", "NA", "NA", "0", "NA", "NA", "NA", "0", "NA", "NA", "0", "NA", "0", "NA", "NA", "NA", "0", "NA", "NA", "1", "0", "Newcastle United", "Joselu", "Dwight Gayle", "0", "NA", "NA", "NA", "NA", "2", "48", "0", "NA", "NA", "66"], ["480622", "Corner,  Liverpool. Conceded by Kenedy.", "67'", "Liverpool", "2", "0", "0", "0", "0", "0", "NA", "NA", "NA", "NA", "NA", "NA", "NA", "0", "NA", "NA", "0", "NA", "0", "0", "NA", "NA", "NA", "0", "NA", "NA", "NA", "0", "NA", "NA", "0", "NA", "0", "NA", "NA", "NA", "1", "Liverpool", "Kenedy", "0", "0", "NA", "NA", "NA", "0", "NA", "NA", "NA", "NA", "2", "49", "0", "NA", "NA", "67"], ["480622", "Attempt blocked. Virgil van Dijk (Liverpool) right footed shot from the centre of the box is blocked. Assisted by Dejan Lovren with a headed pass.", "68'", "Liverpool", "2", "0", "0", "0", "1", "0", "blocked", "Virgil van Dijk", "Liverpool", "right", "the centre of the box", "NA", "Dejan Lovren", "0", "NA", "NA", "0", "NA", "0", "0", "NA", "NA", "NA", "0", "NA", "NA", "NA", "0", "NA", "NA", "0", "NA", "0", "NA", "NA", "NA", "0", "NA", "NA", "0", "0", "NA", "NA", "NA", "0", "NA", "NA", "NA", "NA", "2", "50", "0", "NA", "NA", "68"], ["480622", "Andrew Robertson (Liverpool) wins a free kick on the left wing.", "68'", "Liverpool", "2", "0", "0", "0", "0", "0", "NA", "NA", "NA", "NA", "NA", "NA", "NA", "0", "NA", "NA", "0", "NA", "0", "0", "NA", "NA", "NA", "0", "NA", "NA", "NA", "0", "NA", "NA", "0", "NA", "1", "Andrew Robertson", "Liverpool", "NA", "0", "NA", "NA", "0", "0", "NA", "NA", "NA", "0", "NA", "NA", "NA", "NA", "2", "51", "0", "NA", "NA", "68"], ["480622", "Foul by DeAndre Yedlin (Newcastle United).", "68'", "Liverpool", "2", "0", "0", "0", "0", "0", "NA", "NA", "NA", "NA", "NA", "NA", "NA", "1", "DeAndre Yedlin", "Newcastle United", "0", "NA", "0", "0", "NA", "NA", "NA", "0", "NA", "NA", "NA", "0", "NA", "NA", "0", "NA", "0", "NA", "NA", "NA", "0", "NA", "NA", "0", "0", "NA", "NA", "NA", "0", "NA", "NA", "NA", "NA", "2", "52", "0", "NA", "NA", "68"], ["480622", "Emre Can (Liverpool) wins a free kick in the defensive half.", "69'", "Liverpool", "2", "0", "0", "0", "0", "0", "NA", "NA", "NA", "NA", "NA", "NA", "NA", "0", "NA", "NA", "0", "NA", "0", "0", "NA", "NA", "NA", "0", "NA", "NA", "NA", "0", "NA", "NA", "0", "NA", "1", "Emre Can", "Liverpool", "defensive half", "0", "NA", "NA", "0", "0", "NA", "NA", "NA", "0", "NA", "NA", "NA", "NA", "2", "53", "0", "NA", "NA", "69"], ["480622", "Foul by Mohamed Diamé (Newcastle United).", "69'", "Liverpool", "2", "0", "0", "0", "0", "0", "NA", "NA", "NA", "NA", "NA", "NA", "NA", "1", "Mohamed Diamé", "Newcastle United", "0", "NA", "0", "0", "NA", "NA", "NA", "0", "NA", "NA", "NA", "0", "NA", "NA", "0", "NA", "0", "NA", "NA", "NA", "0", "NA", "NA", "0", "0", "NA", "NA", "NA", "0", "NA", "NA", "NA", "NA", "2", "54", "0", "NA", "NA", "69"], ["480622", "Offside, Liverpool. Emre Can tries a through ball, but Andrew Robertson is caught offside.", "69'", "Liverpool", "2", "0", "0", "0", "0", "0", "NA", "NA", "NA", "NA", "NA", "NA", "NA", "0", "NA", "NA", "0", "NA", "0", "1", "Liverpool", "Andrew Robertson", "Emre Can", "0", "NA", "NA", "NA", "0", "NA", "NA", "0", "NA", "0", "NA", "NA", "NA", "0", "NA", "NA", "0", "0", "NA", "NA", "NA", "0", "NA", "NA", "NA", "NA", "2", "55", "0", "NA", "NA", "69"], ["480622", "Attempt blocked. Jacob Murphy (Newcastle United) right footed shot from outside the box is blocked. Assisted by Christian Atsu.", "73'", "Liverpool", "2", "0", "0", "0", "1", "0", "blocked", "Jacob Murphy", "Newcastle United", "right", "outside the box", "NA", "Christian Atsu", "0", "NA", "NA", "0", "NA", "0", "0", "NA", "NA", "NA", "0", "NA", "NA", "NA", "0", "NA", "NA", "0", "NA", "0", "NA", "NA", "NA", "0", "NA", "NA", "0", "0", "NA", "NA", "NA", "0", "NA", "NA", "NA", "NA", "2", "56", "0", "NA", "NA", "73"], ["480622", "Substitution, Newcastle United. Isaac Hayden replaces Mikel Merino.", "73'", "Liverpool", "2", "0", "0", "0", "0", "0", "NA", "NA", "NA", "NA", "NA", "NA", "NA", "0", "NA", "NA", "0", "NA", "0", "0", "NA", "NA", "NA", "0", "NA", "NA", "NA", "0", "NA", "NA", "0", "NA", "0", "NA", "NA", "NA", "0", "NA", "NA", "1", "0", "Newcastle United", "Isaac Hayden", "Mikel Merino", "0", "NA", "NA", "NA", "NA", "2", "57", "0", "NA", "NA", "73"], ["480622", "Substitution, Liverpool. Adam Lallana replaces Sadio Mané.", "74'", "Liverpool", "2", "0", "0", "0", "0", "0", "NA", "NA", "NA", "NA", "NA", "NA", "NA", "0", "NA", "NA", "0", "NA", "0", "0", "NA", "NA", "NA", "0", "NA", "NA", "NA", "0", "NA", "NA", "0", "NA", "0", "NA", "NA", "NA", "0", "NA", "NA", "1", "0", "Liverpool", "Adam Lallana", "Sadio Mané", "0", "NA", "NA", "NA", "NA", "2", "58", "0", "NA", "NA", "74"], ["480622", "Offside, Liverpool. Alex Oxlade-Chamberlain tries a through ball, but Adam Lallana is caught offside.", "76'", "Liverpool", "2", "0", "0", "0", "0", "0", "NA", "NA", "NA", "NA", "NA", "NA", "NA", "0", "NA", "NA", "0", "NA", "0", "1", "Liverpool", "Adam Lallana", "Alex Oxlade-Chamberlain", "0", "NA", "NA", "NA", "0", "NA", "NA", "0", "NA", "0", "NA", "NA", "NA", "0", "NA", "NA", "0", "0", "NA", "NA", "NA", "0", "NA", "NA", "NA", "NA", "2", "59", "0", "NA", "NA", "76"], ["480622", "Attempt blocked. Kenedy (Newcastle United) right footed shot from outside the box is blocked.", "77'", "Liverpool", "2", "0", "0", "0", "1", "0", "blocked", "Kenedy", "Newcastle United", "right", "outside the box", "NA", "NA", "0", "NA", "NA", "0", "NA", "0", "0", "NA", "NA", "NA", "0", "NA", "NA", "NA", "0", "NA", "NA", "0", "NA", "0", "NA", "NA", "NA", "0", "NA", "NA", "0", "0", "NA", "NA", "NA", "0", "NA", "NA", "NA", "NA", "2", "60", "0", "NA", "NA", "77"], ["480622", "Corner,  Newcastle United. Conceded by Dejan Lovren.", "77'", "Liverpool", "2", "0", "0", "0", "0", "0", "NA", "NA", "NA", "NA", "NA", "NA", "NA", "0", "NA", "NA", "0", "NA", "0", "0", "NA", "NA", "NA", "0", "NA", "NA", "NA", "0", "NA", "NA", "0", "NA", "0", "NA", "NA", "NA", "1", "Newcastle United", "Dejan Lovren", "0", "0", "NA", "NA", "NA", "0", "NA", "NA", "NA", "NA", "2", "61", "0", "NA", "NA", "77"], ["480622", "Attempt missed. Isaac Hayden (Newcastle United) header from the centre of the box is close, but misses to the right. Assisted by Christian Atsu with a cross following a corner.", "77'", "Liverpool", "2", "0", "0", "0", "1", "0", "missed", "Isaac Hayden", "Newcastle United", "header", "the centre of the box", "close, but right", "Christian Atsu", "0", "NA", "NA", "0", "cross", "1", "0", "NA", "NA", "NA", "0", "NA", "NA", "NA", "0", "NA", "NA", "0", "NA", "0", "NA", "NA", "NA", "0", "NA", "NA", "0", "0", "NA", "NA", "NA", "0", "NA", "NA", "NA", "NA", "2", "62", "0", "NA", "NA", "77"], ["480622", "Substitution, Liverpool. James Milner replaces Alex Oxlade-Chamberlain.", "79'", "Liverpool", "2", "0", "0", "0", "0", "0", "NA", "NA", "NA", "NA", "NA", "NA", "NA", "0", "NA", "NA", "0", "NA", "0", "0", "NA", "NA", "NA", "0", "NA", "NA", "NA", "0", "NA", "NA", "0", "NA", "0", "NA", "NA", "NA", "0", "NA", "NA", "1", "0", "Liverpool", "James Milner", "Alex Oxlade-Chamberlain", "0", "NA", "NA", "NA", "NA", "2", "63", "0", "NA", "NA", "79"], ["480622", "Emre Can (Liverpool) wins a free kick in the defensive half.", "80'", "Liverpool", "2", "0", "0", "0", "0", "0", "NA", "NA", "NA", "NA", "NA", "NA", "NA", "0", "NA", "NA", "0", "NA", "0", "0", "NA", "NA", "NA", "0", "NA", "NA", "NA", "0", "NA", "NA", "0", "NA", "1", "Emre Can", "Liverpool", "defensive half", "0", "NA", "NA", "0", "0", "NA", "NA", "NA", "0", "NA", "NA", "NA", "NA", "2", "64", "0", "NA", "NA", "80"], ["480622", "Foul by Kenedy (Newcastle United).", "80'", "Liverpool", "2", "0", "0", "0", "0", "0", "NA", "NA", "NA", "NA", "NA", "NA", "NA", "1", "Kenedy", "Newcastle United", "0", "NA", "0", "0", "NA", "NA", "NA", "0", "NA", "NA", "NA", "0", "NA", "NA", "0", "NA", "0", "NA", "NA", "NA", "0", "NA", "NA", "0", "0", "NA", "NA", "NA", "0", "NA", "NA", "NA", "NA", "2", "65", "0", "NA", "NA", "80"], ["480622", "Attempt blocked. Roberto Firmino (Liverpool) right footed shot from outside the box is blocked.", "81'", "Liverpool", "2", "0", "0", "0", "1", "0", "blocked", "Roberto Firmino", "Liverpool", "right", "outside the box", "NA", "NA", "0", "NA", "NA", "0", "NA", "0", "0", "NA", "NA", "NA", "0", "NA", "NA", "NA", "0", "NA", "NA", "0", "NA", "0", "NA", "NA", "NA", "0", "NA", "NA", "0", "0", "NA", "NA", "NA", "0", "NA", "NA", "NA", "NA", "2", "66", "0", "NA", "NA", "81"], ["480622", "Attempt blocked. Jordan Henderson (Liverpool) right footed shot from outside the box is blocked.", "81'", "Liverpool", "2", "0", "0", "0", "1", "0", "blocked", "Jordan Henderson", "Liverpool", "right", "outside the box", "NA", "NA", "0", "NA", "NA", "0", "NA", "0", "0", "NA", "NA", "NA", "0", "NA", "NA", "NA", "0", "NA", "NA", "0", "NA", "0", "NA", "NA", "NA", "0", "NA", "NA", "0", "0", "NA", "NA", "NA", "0", "NA", "NA", "NA", "NA", "2", "67", "0", "NA", "NA", "81"], ["480622", "Corner,  Liverpool. Conceded by Isaac Hayden.", "81'", "Liverpool", "2", "0", "0", "0", "0", "0", "NA", "NA", "NA", "NA", "NA", "NA", "NA", "0", "NA", "NA", "0", "NA", "0", "0", "NA", "NA", "NA", "0", "NA", "NA", "NA", "0", "NA", "NA", "0", "NA", "0", "NA", "NA", "NA", "1", "Liverpool", "Isaac Hayden", "0", "0", "NA", "NA", "NA", "0", "NA", "NA", "NA", "NA", "2", "68", "0", "NA", "NA", "81"], ["480622", "Foul by Jordan Henderson (Liverpool).", "82'", "Liverpool", "2", "0", "0", "0", "0", "0", "NA", "NA", "NA", "NA", "NA", "NA", "NA", "1", "Jordan Henderson", "Liverpool", "0", "NA", "0", "0", "NA", "NA", "NA", "0", "NA", "NA", "NA", "0", "NA", "NA", "0", "NA", "0", "NA", "NA", "NA", "0", "NA", "NA", "0", "0", "NA", "NA", "NA", "0", "NA", "NA", "NA", "NA", "2", "69", "0", "NA", "NA", "82"], ["480622", "Isaac Hayden (Newcastle United) wins a free kick on the right wing.", "82'", "Liverpool", "2", "0", "0", "0", "0", "0", "NA", "NA", "NA", "NA", "NA", "NA", "NA", "0", "NA", "NA", "0", "NA", "0", "0", "NA", "NA", "NA", "0", "NA", "NA", "NA", "0", "NA", "NA", "0", "NA", "1", "Isaac Hayden", "Newcastle United", "NA", "0", "NA", "NA", "0", "0", "NA", "NA", "NA", "0", "NA", "NA", "NA", "NA", "2", "70", "0", "NA", "NA", "82"], ["480622", "Attempt blocked. Joselu (Newcastle United) left footed shot from outside the box is blocked. Assisted by Jamaal Lascelles with a headed pass.", "83'", "Liverpool", "2", "0", "0", "0", "1", "0", "blocked", "Joselu", "Newcastle United", "left", "outside the box", "NA", "Jamaal Lascelles", "0", "NA", "NA", "0", "NA", "0", "0", "NA", "NA", "NA", "0", "NA", "NA", "NA", "0", "NA", "NA", "0", "NA", "0", "NA", "NA", "NA", "0", "NA", "NA", "0", "0", "NA", "NA", "NA", "0", "NA", "NA", "NA", "NA", "2", "71", "0", "NA", "NA", "83"], ["480622", "Substitution, Newcastle United. Ayoze Pérez replaces Jacob Murphy.", "84'", "Liverpool", "2", "0", "0", "0", "0", "0", "NA", "NA", "NA", "NA", "NA", "NA", "NA", "0", "NA", "NA", "0", "NA", "0", "0", "NA", "NA", "NA", "0", "NA", "NA", "NA", "0", "NA", "NA", "0", "NA", "0", "NA", "NA", "NA", "0", "NA", "NA", "1", "0", "Newcastle United", "Ayoze Pérez", "Jacob Murphy", "0", "NA", "NA", "NA", "NA", "2", "72", "0", "NA", "NA", "84"], ["480622", "Adam Lallana (Liverpool) wins a free kick on the left wing.", "87'", "Liverpool", "2", "0", "0", "0", "0", "0", "NA", "NA", "NA", "NA", "NA", "NA", "NA", "0", "NA", "NA", "0", "NA", "0", "0", "NA", "NA", "NA", "0", "NA", "NA", "NA", "0", "NA", "NA", "0", "NA", "1", "Adam Lallana", "Liverpool", "NA", "0", "NA", "NA", "0", "0", "NA", "NA", "NA", "0", "NA", "NA", "NA", "NA", "2", "73", "0", "NA", "NA", "87"], ["480622", "Foul by DeAndre Yedlin (Newcastle United).", "87'", "Liverpool", "2", "0", "0", "0", "0", "0", "NA", "NA", "NA", "NA", "NA", "NA", "NA", "1", "DeAndre Yedlin", "Newcastle United", "0", "NA", "0", "0", "NA", "NA", "NA", "0", "NA", "NA", "NA", "0", "NA", "NA", "0", "NA", "0", "NA", "NA", "NA", "0", "NA", "NA", "0", "0", "NA", "NA", "NA", "0", "NA", "NA", "NA", "NA", "2", "74", "0", "NA", "NA", "87"], ["480622", "Substitution, Liverpool. Joel Matip replaces Roberto Firmino.", "88'", "Liverpool", "2", "0", "0", "0", "0", "0", "NA", "NA", "NA", "NA", "NA", "NA", "NA", "0", "NA", "NA", "0", "NA", "0", "0", "NA", "NA", "NA", "0", "NA", "NA", "NA", "0", "NA", "NA", "0", "NA", "0", "NA", "NA", "NA", "0", "NA", "NA", "1", "0", "Liverpool", "Joel Matip", "Roberto Firmino", "0", "NA", "NA", "NA", "NA", "2", "75", "0", "NA", "NA", "88"], ["480622", "Corner,  Liverpool. Conceded by Mohamed Diamé.", "89'", "Liverpool", "2", "0", "0", "0", "0", "0", "NA", "NA", "NA", "NA", "NA", "NA", "NA", "0", "NA", "NA", "0", "NA", "0", "0", "NA", "NA", "NA", "0", "NA", "NA", "NA", "0", "NA", "NA", "0", "NA", "0", "NA", "NA", "NA", "1", "Liverpool", "Mohamed Diamé", "0", "0", "NA", "NA", "NA", "0", "NA", "NA", "NA", "NA", "2", "76", "0", "NA", "NA", "89"], ["480622", "Ayoze Pérez (Newcastle United) wins a free kick in the defensive half.", "90'+1'", "Liverpool", "2", "0", "0", "0", "0", "0", "NA", "NA", "NA", "NA", "NA", "NA", "NA", "0", "NA", "NA", "0", "NA", "0", "0", "NA", "NA", "NA", "0", "NA", "NA", "NA", "0", "NA", "NA", "0", "NA", "1", "Ayoze Pérez", "Newcastle United", "defensive half", "0", "NA", "NA", "0", "0", "NA", "NA", "NA", "0", "NA", "NA", "NA", "NA", "2", "77", "1", "NA", "NA", "91"], ["480622", "Foul by Virgil van Dijk (Liverpool).", "90'+1'", "Liverpool", "2", "0", "0", "0", "0", "0", "NA", "NA", "NA", "NA", "NA", "NA", "NA", "1", "Virgil van Dijk", "Liverpool", "0", "NA", "0", "0", "NA", "NA", "NA", "0", "NA", "NA", "NA", "0", "NA", "NA", "0", "NA", "0", "NA", "NA", "NA", "0", "NA", "NA", "0", "0", "NA", "NA", "NA", "0", "NA", "NA", "NA", "NA", "2", "78", "1", "NA", "NA", "91"], ["480622", "Second Half ends, Liverpool 2, Newcastle United 0.", "90'+5'", "Liverpool", "2", "1", "0", "0", "0", "0", "NA", "NA", "NA", "NA", "NA", "NA", "NA", "0", "NA", "NA", "0", "NA", "0", "0", "NA", "NA", "NA", "0", "NA", "NA", "NA", "0", "NA", "NA", "0", "NA", "0", "NA", "NA", "NA", "0", "NA", "NA", "0", "0", "NA", "NA", "NA", "0", "NA", "NA", "NA", "NA", "2", "79", "1", "NA", "NA", "95"], ["480622", "Match ends, Liverpool 2, Newcastle United 0.", "90'+5'", "Liverpool", "2", "0", "1", "0", "0", "0", "NA", "NA", "NA", "NA", "NA", "NA", "NA", "0", "NA", "NA", "0", "NA", "0", "0", "NA", "NA", "NA", "0", "NA", "NA", "NA", "0", "NA", "NA", "0", "NA", "0", "NA", "NA", "NA", "0", "NA", "NA", "0", "0", "NA", "NA", "NA", "0", "NA", "NA", "NA", "NA", "2", "80", "1", "NA", "NA", "95"]], "Lineup": {"Home Player 9": "Andrew Robertson", "Home Player 8": "Alex Oxlade-Chamberlain", "Home Player 5": "Loris Karius", "Home Player 4": "Jordan Henderson", "Home Player 7": "Sadio Mane", "Home Player 6": "Dejan Lovren", "Home Player 1": "Trent Alexander-Arnold", "Home Player 3": "Roberto Firmino", "Home Player 2": "Emre Can", "Away Player 10": "Jacob Murphy", "Away Player 11": "Deandre Yedlin", "Away Player 8": "Florian Lejeune", "Away Player 9": "Mikel Merino", "Away Player 1": "Christian Atsu", "Away Player 2": "Mohamed Diame", "Away Player 3": "Martin Dubravka", "Away Player 4": "Paul Dummett", "Away Player 5": "Dwight Gayle", "Away Player 6": "Kenedy", "Away Player 7": "Jamaal Lascelles", "Game ID": "g_1_YcMZsFTK", "Home Player 11": "Virgil van Dijk", "Home Player 10": "Mohamed Salah"}}