{"Stats": {"Full Time Result": "A", "Away Team Corners": 3, "Referee": "A Marriner", "Home Team Fouls Committed": 11, "Away Team Shots": 12, "Away Team Red Cards": 0, "Home Team Red Cards": 0, "Half Time Away Team Goals": 2, "Full Time Home Team Goals": 1, "Away Team Yellow Cards": 0, "Away Team Shots on Target": 5, "Half Time Home Team Goals": 0, "Half Time Result": "A", "Away Team Fouls Committed": 4, "Home Team Yellow Cards": 0, "Home Team Shots": 7, "Div": "E0", "Home Team Corners": 1, "Home Team Shots on Target": 2, "Full Time Away Team Goals": 3}, "Description": "Offside, Chelsea. Marcos Alonso tries a through ball, but Pedro is caught offside. at minute 1. Elias Kachunga (Huddersfield Town) wins a free kick in the defensive half. at minute 2. Foul by Antonio Rüdiger (Chelsea). at minute 2. Offside, Chelsea. Willian tries a through ball, but Pedro is caught offside. at minute 6. Attempt blocked. Aaron Mooy (Huddersfield Town) left footed shot from outside the box is blocked. Assisted by Elias Kachunga. at minute 10. Eden Hazard (Chelsea) wins a free kick in the attacking half. at minute 13. Foul by Jonathan Hogg (Huddersfield Town). at minute 13. Attempt blocked. Willian (Chelsea) right footed shot from the left side of the box is blocked. Assisted by Marcos Alonso. at minute 16. Offside, Chelsea. Victor Moses tries a through ball, but Eden Hazard is caught offside. at minute 16. Corner,  Huddersfield Town. Conceded by Victor Moses. at minute 18. Offside, Huddersfield Town. Jonathan Hogg tries a through ball, but Steve Mounie is caught offside. at minute 19. Attempt blocked. Tiemoué Bakayoko (Chelsea) right footed shot from outside the box is blocked. Assisted by Marcos Alonso. at minute 19. César Azpilicueta (Chelsea) wins a free kick in the defensive half. at minute 21. Foul by Tom Ince (Huddersfield Town). at minute 21. Goal!  Huddersfield Town 0, Chelsea 1. Tiemoué Bakayoko (Chelsea) left footed shot from the left side of the six yard box to the bottom right corner. Assisted by Willian. at minute 23. Delay in match Chris Löwe (Huddersfield Town) because of an injury. at minute 24. Delay over. They are ready to continue. at minute 25. Eden Hazard (Chelsea) wins a free kick in the attacking half. at minute 29. Foul by Jonathan Hogg (Huddersfield Town). at minute 29. Offside, Chelsea. Willian tries a through ball, but Eden Hazard is caught offside. at minute 33. Corner,  Chelsea. Conceded by Chris Löwe. at minute 35. Foul by Tommy Smith (Huddersfield Town). at minute 36. Marcos Alonso (Chelsea) wins a free kick on the left wing. at minute 36. Attempt missed. N'Golo Kanté (Chelsea) left footed shot from outside the box is high and wide to the left. Assisted by Marcos Alonso following a set piece situation. at minute 37. Eden Hazard (Chelsea) wins a free kick on the right wing. at minute 40. Foul by Zanka (Huddersfield Town). at minute 40. Attempt missed. Tiemoué Bakayoko (Chelsea) header from the centre of the box misses to the left. Assisted by Willian with a cross following a set piece situation. at minute 40. Goal!  Huddersfield Town 0, Chelsea 2. Willian (Chelsea) header from very close range to the centre of the goal. Assisted by Marcos Alonso with a cross. at minute 43. Attempt saved. Pedro (Chelsea) left footed shot from the centre of the box is saved in the centre of the goal. Assisted by Eden Hazard. at minute 45. Eden Hazard (Chelsea) wins a free kick in the attacking half. at minute 46. Foul by Danny Williams (Huddersfield Town). at minute 46. First Half ends, Huddersfield Town 0, Chelsea 2. at minute 47. Second Half begins Huddersfield Town 0, Chelsea 2. at minute 45. Substitution, Huddersfield Town. Dean Whitehead replaces Jonathan Hogg. at minute 45. Offside, Chelsea. Marcos Alonso tries a through ball, but Pedro is caught offside. at minute 47. Goal!  Huddersfield Town 0, Chelsea 3. Pedro (Chelsea) right footed shot from the centre of the box to the top right corner. Assisted by Willian. at minute 50. Elias Kachunga (Huddersfield Town) wins a free kick in the defensive half. at minute 52. Foul by Tiemoué Bakayoko (Chelsea). at minute 52. Eden Hazard (Chelsea) wins a free kick on the left wing. at minute 53. Foul by Zanka (Huddersfield Town). at minute 53. Offside, Chelsea. Willian tries a through ball, but Victor Moses is caught offside. at minute 55. Offside, Huddersfield Town. Christopher Schindler tries a through ball, but Steve Mounie is caught offside. at minute 58. Attempt blocked. Victor Moses (Chelsea) right footed shot from the right side of the box is blocked. Assisted by Eden Hazard. at minute 60. Corner,  Chelsea. Conceded by Zanka. at minute 60. Attempt saved. Eden Hazard (Chelsea) right footed shot from a difficult angle on the right is saved in the bottom right corner. at minute 60. Corner,  Chelsea. Conceded by Jonas Lössl. at minute 60. Attempt saved. Tom Ince (Huddersfield Town) left footed shot from the left side of the box is saved in the bottom right corner. Assisted by Steve Mounie. at minute 61. Attempt missed. Zanka (Huddersfield Town) right footed shot from outside the box is just a bit too high. at minute 62. Attempt missed. Tom Ince (Huddersfield Town) left footed shot from outside the box is high and wide to the left. at minute 66. Substitution, Huddersfield Town. Florent Hadergjonaj replaces Chris Löwe. at minute 67. Attempt missed. Pedro (Chelsea) right footed shot from the centre of the box is too high. at minute 67. Attempt missed. Pedro (Chelsea) left footed shot from the centre of the box is close, but misses to the right. Assisted by Eden Hazard. at minute 68. Substitution, Chelsea. Michy Batshuayi replaces Eden Hazard. at minute 69. Offside, Chelsea. N'Golo Kanté tries a through ball, but Michy Batshuayi is caught offside. at minute 69. Substitution, Chelsea. Daniel Drinkwater replaces N'Golo Kanté. at minute 71. Foul by Tommy Smith (Huddersfield Town). at minute 73. Marcos Alonso (Chelsea) wins a free kick in the defensive half. at minute 73. Substitution, Huddersfield Town. Laurent Depoitre replaces Steve Mounie. at minute 74. Foul by Christopher Schindler (Huddersfield Town). at minute 76. Michy Batshuayi (Chelsea) wins a free kick in the attacking half. at minute 76. Foul by Aaron Mooy (Huddersfield Town). at minute 79. Victor Moses (Chelsea) wins a free kick in the defensive half. at minute 79. Substitution, Chelsea. Ethan Ampadu replaces Andreas Christensen. at minute 80. Offside, Chelsea. Marcos Alonso tries a through ball, but Michy Batshuayi is caught offside. at minute 80. Offside, Chelsea. Michy Batshuayi tries a through ball, but Pedro is caught offside. at minute 82. Offside, Chelsea. Antonio Rüdiger tries a through ball, but Victor Moses is caught offside. at minute 86. Foul by Laurent Depoitre (Huddersfield Town). at minute 87. Tiemoué Bakayoko (Chelsea) wins a free kick in the defensive half. at minute 87. Hand ball by Michy Batshuayi (Chelsea). at minute 88. Attempt missed. Danny Williams (Huddersfield Town) right footed shot from outside the box is close, but misses to the left. at minute 90. Attempt missed. Laurent Depoitre (Huddersfield Town) right footed shot from the centre of the box is close, but misses to the left. Assisted by Danny Williams. at minute 90. Aaron Mooy (Huddersfield Town) wins a free kick in the attacking half. at minute 90. Foul by Daniel Drinkwater (Chelsea). at minute 90. Goal!  Huddersfield Town 1, Chelsea 3. Laurent Depoitre (Huddersfield Town) header from the centre of the box to the bottom right corner. Assisted by Florent Hadergjonaj with a cross. at minute 92. Second Half ends, Huddersfield Town 1, Chelsea 3. at minute 93. Match ends, Huddersfield Town 1, Chelsea 3. at minute 93. ", "Home Team": "Huddersfield Town", "Away Team": "Chelsea", "Date": "2017-12-12", "Commentary": [["480743", "First Half begins.", "-", "Huddersfield Town", "0", "0", "0", "1", "0", "0", "NA", "NA", "NA", "NA", "NA", "NA", "NA", "0", "NA", "NA", "0", "NA", "0", "0", "NA", "NA", "NA", "0", "NA", "NA", "NA", "0", "NA", "NA", "0", "NA", "0", "NA", "NA", "NA", "0", "NA", "NA", "0", "0", "NA", "NA", "NA", "0", "NA", "NA", "NA", "NA", "1", "1", "0", "NA", "NA", "NA"], ["480743", "Lineups are announced and players are warming up.", "-", "Huddersfield Town", "0", "0", "0", "0", "0", "0", "NA", "NA", "NA", "NA", "NA", "NA", "NA", "0", "NA", "NA", "0", "NA", "0", "0", "NA", "NA", "NA", "0", "NA", "NA", "NA", "0", "NA", "NA", "0", "NA", "0", "NA", "NA", "NA", "0", "NA", "NA", "0", "0", "NA", "NA", "NA", "0", "NA", "NA", "NA", "NA", "1", "2", "0", "NA", "NA", "NA"], ["480743", "Offside, Chelsea. Marcos Alonso tries a through ball, but Pedro is caught offside.", "1'", "Huddersfield Town", "0", "0", "0", "0", "0", "0", "NA", "NA", "NA", "NA", "NA", "NA", "NA", "0", "NA", "NA", "0", "NA", "0", "1", "Chelsea", "Pedro", "Marcos Alonso", "0", "NA", "NA", "NA", "0", "NA", "NA", "0", "NA", "0", "NA", "NA", "NA", "0", "NA", "NA", "0", "0", "NA", "NA", "NA", "0", "NA", "NA", "NA", "NA", "1", "3", "0", "NA", "NA", "1"], ["480743", "Elias Kachunga (Huddersfield Town) wins a free kick in the defensive half.", "2'", "Huddersfield Town", "0", "0", "0", "0", "0", "0", "NA", "NA", "NA", "NA", "NA", "NA", "NA", "0", "NA", "NA", "0", "NA", "0", "0", "NA", "NA", "NA", "0", "NA", "NA", "NA", "0", "NA", "NA", "0", "NA", "1", "Elias Kachunga", "Huddersfield Town", "defensive half", "0", "NA", "NA", "0", "0", "NA", "NA", "NA", "0", "NA", "NA", "NA", "NA", "1", "4", "0", "NA", "NA", "2"], ["480743", "Foul by Antonio Rüdiger (Chelsea).", "2'", "Huddersfield Town", "0", "0", "0", "0", "0", "0", "NA", "NA", "NA", "NA", "NA", "NA", "NA", "1", "Antonio Rüdiger", "Chelsea", "0", "NA", "0", "0", "NA", "NA", "NA", "0", "NA", "NA", "NA", "0", "NA", "NA", "0", "NA", "0", "NA", "NA", "NA", "0", "NA", "NA", "0", "0", "NA", "NA", "NA", "0", "NA", "NA", "NA", "NA", "1", "5", "0", "NA", "NA", "2"], ["480743", "Offside, Chelsea. Willian tries a through ball, but Pedro is caught offside.", "6'", "Huddersfield Town", "0", "0", "0", "0", "0", "0", "NA", "NA", "NA", "NA", "NA", "NA", "NA", "0", "NA", "NA", "0", "NA", "0", "1", "Chelsea", "Pedro", "Willian", "0", "NA", "NA", "NA", "0", "NA", "NA", "0", "NA", "0", "NA", "NA", "NA", "0", "NA", "NA", "0", "0", "NA", "NA", "NA", "0", "NA", "NA", "NA", "NA", "1", "6", "0", "NA", "NA", "6"], ["480743", "Attempt blocked. Aaron Mooy (Huddersfield Town) left footed shot from outside the box is blocked. Assisted by Elias Kachunga.", "10'", "Huddersfield Town", "0", "0", "0", "0", "1", "0", "blocked", "Aaron Mooy", "Huddersfield Town", "left", "outside the box", "NA", "Elias Kachunga", "0", "NA", "NA", "0", "NA", "0", "0", "NA", "NA", "NA", "0", "NA", "NA", "NA", "0", "NA", "NA", "0", "NA", "0", "NA", "NA", "NA", "0", "NA", "NA", "0", "0", "NA", "NA", "NA", "0", "NA", "NA", "NA", "NA", "1", "7", "0", "NA", "NA", "10"], ["480743", "Eden Hazard (Chelsea) wins a free kick in the attacking half.", "13'", "Huddersfield Town", "0", "0", "0", "0", "0", "0", "NA", "NA", "NA", "NA", "NA", "NA", "NA", "0", "NA", "NA", "0", "NA", "0", "0", "NA", "NA", "NA", "0", "NA", "NA", "NA", "0", "NA", "NA", "0", "NA", "1", "Eden Hazard", "Chelsea", "attacking half", "0", "NA", "NA", "0", "0", "NA", "NA", "NA", "0", "NA", "NA", "NA", "NA", "1", "8", "0", "NA", "NA", "13"], ["480743", "Foul by Jonathan Hogg (Huddersfield Town).", "13'", "Huddersfield Town", "0", "0", "0", "0", "0", "0", "NA", "NA", "NA", "NA", "NA", "NA", "NA", "1", "Jonathan Hogg", "Huddersfield Town", "0", "NA", "0", "0", "NA", "NA", "NA", "0", "NA", "NA", "NA", "0", "NA", "NA", "0", "NA", "0", "NA", "NA", "NA", "0", "NA", "NA", "0", "0", "NA", "NA", "NA", "0", "NA", "NA", "NA", "NA", "1", "9", "0", "NA", "NA", "13"], ["480743", "Attempt blocked. Willian (Chelsea) right footed shot from the left side of the box is blocked. Assisted by Marcos Alonso.", "16'", "Huddersfield Town", "0", "0", "0", "0", "1", "0", "blocked", "Willian", "Chelsea", "right", "the left side of the box", "NA", "Marcos Alonso", "0", "NA", "NA", "0", "NA", "0", "0", "NA", "NA", "NA", "0", "NA", "NA", "NA", "0", "NA", "NA", "0", "NA", "0", "NA", "NA", "NA", "0", "NA", "NA", "0", "0", "NA", "NA", "NA", "0", "NA", "NA", "NA", "NA", "1", "10", "0", "NA", "NA", "16"], ["480743", "Offside, Chelsea. Victor Moses tries a through ball, but Eden Hazard is caught offside.", "16'", "Huddersfield Town", "0", "0", "0", "0", "0", "0", "NA", "NA", "NA", "NA", "NA", "NA", "NA", "0", "NA", "NA", "0", "NA", "0", "1", "Chelsea", "Eden Hazard", "Victor Moses", "0", "NA", "NA", "NA", "0", "NA", "NA", "0", "NA", "0", "NA", "NA", "NA", "0", "NA", "NA", "0", "0", "NA", "NA", "NA", "0", "NA", "NA", "NA", "NA", "1", "11", "0", "NA", "NA", "16"], ["480743", "Corner,  Huddersfield Town. Conceded by Victor Moses.", "18'", "Huddersfield Town", "0", "0", "0", "0", "0", "0", "NA", "NA", "NA", "NA", "NA", "NA", "NA", "0", "NA", "NA", "0", "NA", "0", "0", "NA", "NA", "NA", "0", "NA", "NA", "NA", "0", "NA", "NA", "0", "NA", "0", "NA", "NA", "NA", "1", "Huddersfield Town", "Victor Moses", "0", "0", "NA", "NA", "NA", "0", "NA", "NA", "NA", "NA", "1", "12", "0", "NA", "NA", "18"], ["480743", "Offside, Huddersfield Town. Jonathan Hogg tries a through ball, but Steve Mounie is caught offside.", "19'", "Huddersfield Town", "0", "0", "0", "0", "0", "0", "NA", "NA", "NA", "NA", "NA", "NA", "NA", "0", "NA", "NA", "0", "NA", "0", "1", "Huddersfield Town", "Steve Mounie", "Jonathan Hogg", "0", "NA", "NA", "NA", "0", "NA", "NA", "0", "NA", "0", "NA", "NA", "NA", "0", "NA", "NA", "0", "0", "NA", "NA", "NA", "0", "NA", "NA", "NA", "NA", "1", "13", "0", "NA", "NA", "19"], ["480743", "Attempt blocked. Tiemoué Bakayoko (Chelsea) right footed shot from outside the box is blocked. Assisted by Marcos Alonso.", "19'", "Huddersfield Town", "0", "0", "0", "0", "1", "0", "blocked", "Tiemoué Bakayoko", "Chelsea", "right", "outside the box", "NA", "Marcos Alonso", "0", "NA", "NA", "0", "NA", "0", "0", "NA", "NA", "NA", "0", "NA", "NA", "NA", "0", "NA", "NA", "0", "NA", "0", "NA", "NA", "NA", "0", "NA", "NA", "0", "0", "NA", "NA", "NA", "0", "NA", "NA", "NA", "NA", "1", "14", "0", "NA", "NA", "19"], ["480743", "César Azpilicueta (Chelsea) wins a free kick in the defensive half.", "21'", "Huddersfield Town", "0", "0", "0", "0", "0", "0", "NA", "NA", "NA", "NA", "NA", "NA", "NA", "0", "NA", "NA", "0", "NA", "0", "0", "NA", "NA", "NA", "0", "NA", "NA", "NA", "0", "NA", "NA", "0", "NA", "1", "César Azpilicueta", "Chelsea", "defensive half", "0", "NA", "NA", "0", "0", "NA", "NA", "NA", "0", "NA", "NA", "NA", "NA", "1", "15", "0", "NA", "NA", "21"], ["480743", "Foul by Tom Ince (Huddersfield Town).", "21'", "Huddersfield Town", "0", "0", "0", "0", "0", "0", "NA", "NA", "NA", "NA", "NA", "NA", "NA", "1", "Tom Ince", "Huddersfield Town", "0", "NA", "0", "0", "NA", "NA", "NA", "0", "NA", "NA", "NA", "0", "NA", "NA", "0", "NA", "0", "NA", "NA", "NA", "0", "NA", "NA", "0", "0", "NA", "NA", "NA", "0", "NA", "NA", "NA", "NA", "1", "16", "0", "NA", "NA", "21"], ["480743", "Goal!  Huddersfield Town 0, Chelsea 1. Tiemoué Bakayoko (Chelsea) left footed shot from the left side of the six yard box to the bottom right corner. Assisted by Willian.", "23'", "Huddersfield Town", "0", "0", "0", "0", "1", "0", "goal", "Tiemoué Bakayoko", "Chelsea", "left", "the left side of the six yard box", "bottom right corner", "Willian", "0", "NA", "NA", "0", "NA", "0", "0", "NA", "NA", "NA", "0", "NA", "NA", "NA", "0", "NA", "NA", "0", "NA", "0", "NA", "NA", "NA", "0", "NA", "NA", "0", "0", "NA", "NA", "NA", "0", "NA", "NA", "NA", "NA", "1", "17", "0", "NA", "NA", "23"], ["480743", "Delay in match Chris Löwe (Huddersfield Town) because of an injury.", "24'", "Huddersfield Town", "0", "0", "0", "0", "0", "0", "NA", "NA", "NA", "NA", "NA", "NA", "NA", "0", "NA", "NA", "0", "NA", "0", "0", "NA", "NA", "NA", "0", "NA", "NA", "NA", "0", "NA", "NA", "1", "Huddersfield Town", "0", "NA", "NA", "NA", "0", "NA", "NA", "0", "0", "NA", "NA", "NA", "0", "NA", "NA", "NA", "NA", "1", "18", "0", "NA", "NA", "24"], ["480743", "Delay over. They are ready to continue.", "25'", "Huddersfield Town", "0", "0", "0", "0", "0", "0", "NA", "NA", "NA", "NA", "NA", "NA", "NA", "0", "NA", "NA", "0", "NA", "0", "0", "NA", "NA", "NA", "0", "NA", "NA", "NA", "0", "NA", "NA", "0", "NA", "0", "NA", "NA", "NA", "0", "NA", "NA", "0", "0", "NA", "NA", "NA", "0", "NA", "NA", "NA", "NA", "1", "19", "0", "NA", "NA", "25"], ["480743", "Eden Hazard (Chelsea) wins a free kick in the attacking half.", "29'", "Huddersfield Town", "0", "0", "0", "0", "0", "0", "NA", "NA", "NA", "NA", "NA", "NA", "NA", "0", "NA", "NA", "0", "NA", "0", "0", "NA", "NA", "NA", "0", "NA", "NA", "NA", "0", "NA", "NA", "0", "NA", "1", "Eden Hazard", "Chelsea", "attacking half", "0", "NA", "NA", "0", "0", "NA", "NA", "NA", "0", "NA", "NA", "NA", "NA", "1", "20", "0", "NA", "NA", "29"], ["480743", "Foul by Jonathan Hogg (Huddersfield Town).", "29'", "Huddersfield Town", "0", "0", "0", "0", "0", "0", "NA", "NA", "NA", "NA", "NA", "NA", "NA", "1", "Jonathan Hogg", "Huddersfield Town", "0", "NA", "0", "0", "NA", "NA", "NA", "0", "NA", "NA", "NA", "0", "NA", "NA", "0", "NA", "0", "NA", "NA", "NA", "0", "NA", "NA", "0", "0", "NA", "NA", "NA", "0", "NA", "NA", "NA", "NA", "1", "21", "0", "NA", "NA", "29"], ["480743", "Offside, Chelsea. Willian tries a through ball, but Eden Hazard is caught offside.", "33'", "Huddersfield Town", "0", "0", "0", "0", "0", "0", "NA", "NA", "NA", "NA", "NA", "NA", "NA", "0", "NA", "NA", "0", "NA", "0", "1", "Chelsea", "Eden Hazard", "Willian", "0", "NA", "NA", "NA", "0", "NA", "NA", "0", "NA", "0", "NA", "NA", "NA", "0", "NA", "NA", "0", "0", "NA", "NA", "NA", "0", "NA", "NA", "NA", "NA", "1", "22", "0", "NA", "NA", "33"], ["480743", "Corner,  Chelsea. Conceded by Chris Löwe.", "35'", "Huddersfield Town", "0", "0", "0", "0", "0", "0", "NA", "NA", "NA", "NA", "NA", "NA", "NA", "0", "NA", "NA", "0", "NA", "0", "0", "NA", "NA", "NA", "0", "NA", "NA", "NA", "0", "NA", "NA", "0", "NA", "0", "NA", "NA", "NA", "1", "Chelsea", "Chris Löwe", "0", "0", "NA", "NA", "NA", "0", "NA", "NA", "NA", "NA", "1", "23", "0", "NA", "NA", "35"], ["480743", "Foul by Tommy Smith (Huddersfield Town).", "36'", "Huddersfield Town", "0", "0", "0", "0", "0", "0", "NA", "NA", "NA", "NA", "NA", "NA", "NA", "1", "Tommy Smith", "Huddersfield Town", "0", "NA", "0", "0", "NA", "NA", "NA", "0", "NA", "NA", "NA", "0", "NA", "NA", "0", "NA", "0", "NA", "NA", "NA", "0", "NA", "NA", "0", "0", "NA", "NA", "NA", "0", "NA", "NA", "NA", "NA", "1", "24", "0", "NA", "NA", "36"], ["480743", "Marcos Alonso (Chelsea) wins a free kick on the left wing.", "36'", "Huddersfield Town", "0", "0", "0", "0", "0", "0", "NA", "NA", "NA", "NA", "NA", "NA", "NA", "0", "NA", "NA", "0", "NA", "0", "0", "NA", "NA", "NA", "0", "NA", "NA", "NA", "0", "NA", "NA", "0", "NA", "1", "Marcos Alonso", "Chelsea", "NA", "0", "NA", "NA", "0", "0", "NA", "NA", "NA", "0", "NA", "NA", "NA", "NA", "1", "25", "0", "NA", "NA", "36"], ["480743", "Attempt missed. N'Golo Kanté (Chelsea) left footed shot from outside the box is high and wide to the left. Assisted by Marcos Alonso following a set piece situation.", "37'", "Huddersfield Town", "0", "0", "0", "0", "1", "0", "missed", "N'Golo Kanté", "Chelsea", "left", "outside the box", "high and wide to the left", "Marcos Alonso", "0", "NA", "NA", "1", "NA", "0", "0", "NA", "NA", "NA", "0", "NA", "NA", "NA", "0", "NA", "NA", "0", "NA", "0", "NA", "NA", "NA", "0", "NA", "NA", "0", "0", "NA", "NA", "NA", "0", "NA", "NA", "NA", "NA", "1", "26", "0", "NA", "NA", "37"], ["480743", "Eden Hazard (Chelsea) wins a free kick on the right wing.", "40'", "Huddersfield Town", "0", "0", "0", "0", "0", "0", "NA", "NA", "NA", "NA", "NA", "NA", "NA", "0", "NA", "NA", "0", "NA", "0", "0", "NA", "NA", "NA", "0", "NA", "NA", "NA", "0", "NA", "NA", "0", "NA", "1", "Eden Hazard", "Chelsea", "NA", "0", "NA", "NA", "0", "0", "NA", "NA", "NA", "0", "NA", "NA", "NA", "NA", "1", "27", "0", "NA", "NA", "40"], ["480743", "Foul by Zanka (Huddersfield Town).", "40'", "Huddersfield Town", "0", "0", "0", "0", "0", "0", "NA", "NA", "NA", "NA", "NA", "NA", "NA", "1", "Zanka", "Huddersfield Town", "0", "NA", "0", "0", "NA", "NA", "NA", "0", "NA", "NA", "NA", "0", "NA", "NA", "0", "NA", "0", "NA", "NA", "NA", "0", "NA", "NA", "0", "0", "NA", "NA", "NA", "0", "NA", "NA", "NA", "NA", "1", "28", "0", "NA", "NA", "40"], ["480743", "Attempt missed. Tiemoué Bakayoko (Chelsea) header from the centre of the box misses to the left. Assisted by Willian with a cross following a set piece situation.", "40'", "Huddersfield Town", "0", "0", "0", "0", "1", "0", "missed", "Tiemoué Bakayoko", "Chelsea", "header", "the centre of the box", "left", "Willian a", "0", "NA", "NA", "1", "cross", "0", "0", "NA", "NA", "NA", "0", "NA", "NA", "NA", "0", "NA", "NA", "0", "NA", "0", "NA", "NA", "NA", "0", "NA", "NA", "0", "0", "NA", "NA", "NA", "0", "NA", "NA", "NA", "NA", "1", "29", "0", "NA", "NA", "40"], ["480743", "Goal!  Huddersfield Town 0, Chelsea 2. Willian (Chelsea) header from very close range to the centre of the goal. Assisted by Marcos Alonso with a cross.", "43'", "Huddersfield Town", "0", "0", "0", "0", "1", "0", "goal", "Willian", "Chelsea", "header", "very close range", "centre of the goal", "Marcos Alonso", "0", "NA", "NA", "0", "cross", "0", "0", "NA", "NA", "NA", "0", "NA", "NA", "NA", "0", "NA", "NA", "0", "NA", "0", "NA", "NA", "NA", "0", "NA", "NA", "0", "0", "NA", "NA", "NA", "0", "NA", "NA", "NA", "NA", "1", "30", "0", "NA", "NA", "43"], ["480743", "Attempt saved. Pedro (Chelsea) left footed shot from the centre of the box is saved in the centre of the goal. Assisted by Eden Hazard.", "45'", "Huddersfield Town", "0", "0", "0", "0", "1", "0", "saved", "Pedro", "Chelsea", "left", "the centre of the box", "the centre of the goal", "Eden Hazard", "0", "NA", "NA", "0", "NA", "0", "0", "NA", "NA", "NA", "0", "NA", "NA", "NA", "0", "NA", "NA", "0", "NA", "0", "NA", "NA", "NA", "0", "NA", "NA", "0", "0", "NA", "NA", "NA", "0", "NA", "NA", "NA", "NA", "1", "31", "0", "NA", "NA", "45"], ["480743", "Eden Hazard (Chelsea) wins a free kick in the attacking half.", "45'+1'", "Huddersfield Town", "0", "0", "0", "0", "0", "0", "NA", "NA", "NA", "NA", "NA", "NA", "NA", "0", "NA", "NA", "0", "NA", "0", "0", "NA", "NA", "NA", "0", "NA", "NA", "NA", "0", "NA", "NA", "0", "NA", "1", "Eden Hazard", "Chelsea", "attacking half", "0", "NA", "NA", "0", "0", "NA", "NA", "NA", "0", "NA", "NA", "NA", "NA", "1", "32", "1", "NA", "NA", "46"], ["480743", "Foul by Danny Williams (Huddersfield Town).", "45'+1'", "Huddersfield Town", "0", "0", "0", "0", "0", "0", "NA", "NA", "NA", "NA", "NA", "NA", "NA", "1", "Danny Williams", "Huddersfield Town", "0", "NA", "0", "0", "NA", "NA", "NA", "0", "NA", "NA", "NA", "0", "NA", "NA", "0", "NA", "0", "NA", "NA", "NA", "0", "NA", "NA", "0", "0", "NA", "NA", "NA", "0", "NA", "NA", "NA", "NA", "1", "33", "1", "NA", "NA", "46"], ["480743", "First Half ends, Huddersfield Town 0, Chelsea 2.", "45'+2'", "Huddersfield Town", "0", "1", "0", "0", "0", "0", "NA", "NA", "NA", "NA", "NA", "NA", "NA", "0", "NA", "NA", "0", "NA", "0", "0", "NA", "NA", "NA", "0", "NA", "NA", "NA", "0", "NA", "NA", "0", "NA", "0", "NA", "NA", "NA", "0", "NA", "NA", "0", "0", "NA", "NA", "NA", "0", "NA", "NA", "NA", "NA", "1", "34", "1", "NA", "NA", "47"], ["480743", "Second Half begins Huddersfield Town 0, Chelsea 2.", "45'", "Huddersfield Town", "0", "0", "0", "1", "0", "0", "NA", "NA", "NA", "NA", "NA", "NA", "NA", "0", "NA", "NA", "0", "NA", "0", "0", "NA", "NA", "NA", "0", "NA", "NA", "NA", "0", "NA", "NA", "0", "NA", "0", "NA", "NA", "NA", "0", "NA", "NA", "0", "0", "NA", "NA", "NA", "0", "NA", "NA", "NA", "NA", "2", "35", "0", "NA", "NA", "45"], ["480743", "Substitution, Huddersfield Town. Dean Whitehead replaces Jonathan Hogg.", "45'", "Huddersfield Town", "0", "0", "0", "0", "0", "0", "NA", "NA", "NA", "NA", "NA", "NA", "NA", "0", "NA", "NA", "0", "NA", "0", "0", "NA", "NA", "NA", "0", "NA", "NA", "NA", "0", "NA", "NA", "0", "NA", "0", "NA", "NA", "NA", "0", "NA", "NA", "1", "0", "Huddersfield Town", "Dean Whitehead", "Jonathan Hogg", "0", "NA", "NA", "NA", "NA", "2", "36", "0", "NA", "NA", "45"], ["480743", "Offside, Chelsea. Marcos Alonso tries a through ball, but Pedro is caught offside.", "47'", "Huddersfield Town", "0", "0", "0", "0", "0", "0", "NA", "NA", "NA", "NA", "NA", "NA", "NA", "0", "NA", "NA", "0", "NA", "0", "1", "Chelsea", "Pedro", "Marcos Alonso", "0", "NA", "NA", "NA", "0", "NA", "NA", "0", "NA", "0", "NA", "NA", "NA", "0", "NA", "NA", "0", "0", "NA", "NA", "NA", "0", "NA", "NA", "NA", "NA", "2", "37", "0", "NA", "NA", "47"], ["480743", "Goal!  Huddersfield Town 0, Chelsea 3. Pedro (Chelsea) right footed shot from the centre of the box to the top right corner. Assisted by Willian.", "50'", "Huddersfield Town", "0", "0", "0", "0", "1", "0", "goal", "Pedro", "Chelsea", "right", "the centre of the box", "top right corner", "Willian", "0", "NA", "NA", "0", "NA", "0", "0", "NA", "NA", "NA", "0", "NA", "NA", "NA", "0", "NA", "NA", "0", "NA", "0", "NA", "NA", "NA", "0", "NA", "NA", "0", "0", "NA", "NA", "NA", "0", "NA", "NA", "NA", "NA", "2", "38", "0", "NA", "NA", "50"], ["480743", "Elias Kachunga (Huddersfield Town) wins a free kick in the defensive half.", "52'", "Huddersfield Town", "0", "0", "0", "0", "0", "0", "NA", "NA", "NA", "NA", "NA", "NA", "NA", "0", "NA", "NA", "0", "NA", "0", "0", "NA", "NA", "NA", "0", "NA", "NA", "NA", "0", "NA", "NA", "0", "NA", "1", "Elias Kachunga", "Huddersfield Town", "defensive half", "0", "NA", "NA", "0", "0", "NA", "NA", "NA", "0", "NA", "NA", "NA", "NA", "2", "39", "0", "NA", "NA", "52"], ["480743", "Foul by Tiemoué Bakayoko (Chelsea).", "52'", "Huddersfield Town", "0", "0", "0", "0", "0", "0", "NA", "NA", "NA", "NA", "NA", "NA", "NA", "1", "Tiemoué Bakayoko", "Chelsea", "0", "NA", "0", "0", "NA", "NA", "NA", "0", "NA", "NA", "NA", "0", "NA", "NA", "0", "NA", "0", "NA", "NA", "NA", "0", "NA", "NA", "0", "0", "NA", "NA", "NA", "0", "NA", "NA", "NA", "NA", "2", "40", "0", "NA", "NA", "52"], ["480743", "Eden Hazard (Chelsea) wins a free kick on the left wing.", "53'", "Huddersfield Town", "0", "0", "0", "0", "0", "0", "NA", "NA", "NA", "NA", "NA", "NA", "NA", "0", "NA", "NA", "0", "NA", "0", "0", "NA", "NA", "NA", "0", "NA", "NA", "NA", "0", "NA", "NA", "0", "NA", "1", "Eden Hazard", "Chelsea", "NA", "0", "NA", "NA", "0", "0", "NA", "NA", "NA", "0", "NA", "NA", "NA", "NA", "2", "41", "0", "NA", "NA", "53"], ["480743", "Foul by Zanka (Huddersfield Town).", "53'", "Huddersfield Town", "0", "0", "0", "0", "0", "0", "NA", "NA", "NA", "NA", "NA", "NA", "NA", "1", "Zanka", "Huddersfield Town", "0", "NA", "0", "0", "NA", "NA", "NA", "0", "NA", "NA", "NA", "0", "NA", "NA", "0", "NA", "0", "NA", "NA", "NA", "0", "NA", "NA", "0", "0", "NA", "NA", "NA", "0", "NA", "NA", "NA", "NA", "2", "42", "0", "NA", "NA", "53"], ["480743", "Offside, Chelsea. Willian tries a through ball, but Victor Moses is caught offside.", "55'", "Huddersfield Town", "0", "0", "0", "0", "0", "0", "NA", "NA", "NA", "NA", "NA", "NA", "NA", "0", "NA", "NA", "0", "NA", "0", "1", "Chelsea", "Victor Moses", "Willian", "0", "NA", "NA", "NA", "0", "NA", "NA", "0", "NA", "0", "NA", "NA", "NA", "0", "NA", "NA", "0", "0", "NA", "NA", "NA", "0", "NA", "NA", "NA", "NA", "2", "43", "0", "NA", "NA", "55"], ["480743", "Offside, Huddersfield Town. Christopher Schindler tries a through ball, but Steve Mounie is caught offside.", "58'", "Huddersfield Town", "0", "0", "0", "0", "0", "0", "NA", "NA", "NA", "NA", "NA", "NA", "NA", "0", "NA", "NA", "0", "NA", "0", "1", "Huddersfield Town", "Steve Mounie", "Christopher Schindler", "0", "NA", "NA", "NA", "0", "NA", "NA", "0", "NA", "0", "NA", "NA", "NA", "0", "NA", "NA", "0", "0", "NA", "NA", "NA", "0", "NA", "NA", "NA", "NA", "2", "44", "0", "NA", "NA", "58"], ["480743", "Attempt blocked. Victor Moses (Chelsea) right footed shot from the right side of the box is blocked. Assisted by Eden Hazard.", "60'", "Huddersfield Town", "0", "0", "0", "0", "1", "0", "blocked", "Victor Moses", "Chelsea", "right", "the right side of the box", "NA", "Eden Hazard", "0", "NA", "NA", "0", "NA", "0", "0", "NA", "NA", "NA", "0", "NA", "NA", "NA", "0", "NA", "NA", "0", "NA", "0", "NA", "NA", "NA", "0", "NA", "NA", "0", "0", "NA", "NA", "NA", "0", "NA", "NA", "NA", "NA", "2", "45", "0", "NA", "NA", "60"], ["480743", "Corner,  Chelsea. Conceded by Zanka.", "60'", "Huddersfield Town", "0", "0", "0", "0", "0", "0", "NA", "NA", "NA", "NA", "NA", "NA", "NA", "0", "NA", "NA", "0", "NA", "0", "0", "NA", "NA", "NA", "0", "NA", "NA", "NA", "0", "NA", "NA", "0", "NA", "0", "NA", "NA", "NA", "1", "Chelsea", "Zanka", "0", "0", "NA", "NA", "NA", "0", "NA", "NA", "NA", "NA", "2", "46", "0", "NA", "NA", "60"], ["480743", "Attempt saved. Eden Hazard (Chelsea) right footed shot from a difficult angle on the right is saved in the bottom right corner.", "60'", "Huddersfield Town", "0", "0", "0", "0", "1", "0", "saved", "Eden Hazard", "Chelsea", "right", "NA", "the bottom right corner", "NA", "0", "NA", "NA", "0", "NA", "0", "0", "NA", "NA", "NA", "0", "NA", "NA", "NA", "0", "NA", "NA", "0", "NA", "0", "NA", "NA", "NA", "0", "NA", "NA", "0", "0", "NA", "NA", "NA", "0", "NA", "NA", "NA", "NA", "2", "47", "0", "NA", "NA", "60"], ["480743", "Corner,  Chelsea. Conceded by Jonas Lössl.", "60'", "Huddersfield Town", "0", "0", "0", "0", "0", "0", "NA", "NA", "NA", "NA", "NA", "NA", "NA", "0", "NA", "NA", "0", "NA", "0", "0", "NA", "NA", "NA", "0", "NA", "NA", "NA", "0", "NA", "NA", "0", "NA", "0", "NA", "NA", "NA", "1", "Chelsea", "Jonas Lössl", "0", "0", "NA", "NA", "NA", "0", "NA", "NA", "NA", "NA", "2", "48", "0", "NA", "NA", "60"], ["480743", "Attempt saved. Tom Ince (Huddersfield Town) left footed shot from the left side of the box is saved in the bottom right corner. Assisted by Steve Mounie.", "61'", "Huddersfield Town", "0", "0", "0", "0", "1", "0", "saved", "Tom Ince", "Huddersfield Town", "left", "the left side of the box", "the bottom right corner", "Steve Mounie", "0", "NA", "NA", "0", "NA", "0", "0", "NA", "NA", "NA", "0", "NA", "NA", "NA", "0", "NA", "NA", "0", "NA", "0", "NA", "NA", "NA", "0", "NA", "NA", "0", "0", "NA", "NA", "NA", "0", "NA", "NA", "NA", "NA", "2", "49", "0", "NA", "NA", "61"], ["480743", "Attempt missed. Zanka (Huddersfield Town) right footed shot from outside the box is just a bit too high.", "62'", "Huddersfield Town", "0", "0", "0", "0", "1", "0", "missed", "Zanka", "Huddersfield Town", "right", "outside the box", "just a bit too high", "NA", "0", "NA", "NA", "0", "NA", "0", "0", "NA", "NA", "NA", "0", "NA", "NA", "NA", "0", "NA", "NA", "0", "NA", "0", "NA", "NA", "NA", "0", "NA", "NA", "0", "0", "NA", "NA", "NA", "0", "NA", "NA", "NA", "NA", "2", "50", "0", "NA", "NA", "62"], ["480743", "Attempt missed. Tom Ince (Huddersfield Town) left footed shot from outside the box is high and wide to the left.", "66'", "Huddersfield Town", "0", "0", "0", "0", "1", "0", "missed", "Tom Ince", "Huddersfield Town", "left", "outside the box", "high and wide to the left", "NA", "0", "NA", "NA", "0", "NA", "0", "0", "NA", "NA", "NA", "0", "NA", "NA", "NA", "0", "NA", "NA", "0", "NA", "0", "NA", "NA", "NA", "0", "NA", "NA", "0", "0", "NA", "NA", "NA", "0", "NA", "NA", "NA", "NA", "2", "51", "0", "NA", "NA", "66"], ["480743", "Substitution, Huddersfield Town. Florent Hadergjonaj replaces Chris Löwe.", "67'", "Huddersfield Town", "0", "0", "0", "0", "0", "0", "NA", "NA", "NA", "NA", "NA", "NA", "NA", "0", "NA", "NA", "0", "NA", "0", "0", "NA", "NA", "NA", "0", "NA", "NA", "NA", "0", "NA", "NA", "0", "NA", "0", "NA", "NA", "NA", "0", "NA", "NA", "1", "0", "Huddersfield Town", "Florent Hadergjonaj", "Chris Löwe", "0", "NA", "NA", "NA", "NA", "2", "52", "0", "NA", "NA", "67"], ["480743", "Attempt missed. Pedro (Chelsea) right footed shot from the centre of the box is too high.", "67'", "Huddersfield Town", "0", "0", "0", "0", "1", "0", "missed", "Pedro", "Chelsea", "right", "the centre of the box", "too high", "NA", "0", "NA", "NA", "0", "NA", "0", "0", "NA", "NA", "NA", "0", "NA", "NA", "NA", "0", "NA", "NA", "0", "NA", "0", "NA", "NA", "NA", "0", "NA", "NA", "0", "0", "NA", "NA", "NA", "0", "NA", "NA", "NA", "NA", "2", "53", "0", "NA", "NA", "67"], ["480743", "Attempt missed. Pedro (Chelsea) left footed shot from the centre of the box is close, but misses to the right. Assisted by Eden Hazard.", "68'", "Huddersfield Town", "0", "0", "0", "0", "1", "0", "missed", "Pedro", "Chelsea", "left", "the centre of the box", "close, but right", "Eden Hazard", "0", "NA", "NA", "0", "NA", "0", "0", "NA", "NA", "NA", "0", "NA", "NA", "NA", "0", "NA", "NA", "0", "NA", "0", "NA", "NA", "NA", "0", "NA", "NA", "0", "0", "NA", "NA", "NA", "0", "NA", "NA", "NA", "NA", "2", "54", "0", "NA", "NA", "68"], ["480743", "Substitution, Chelsea. Michy Batshuayi replaces Eden Hazard.", "69'", "Huddersfield Town", "0", "0", "0", "0", "0", "0", "NA", "NA", "NA", "NA", "NA", "NA", "NA", "0", "NA", "NA", "0", "NA", "0", "0", "NA", "NA", "NA", "0", "NA", "NA", "NA", "0", "NA", "NA", "0", "NA", "0", "NA", "NA", "NA", "0", "NA", "NA", "1", "0", "Chelsea", "Michy Batshuayi", "Eden Hazard", "0", "NA", "NA", "NA", "NA", "2", "55", "0", "NA", "NA", "69"], ["480743", "Offside, Chelsea. N'Golo Kanté tries a through ball, but Michy Batshuayi is caught offside.", "69'", "Huddersfield Town", "0", "0", "0", "0", "0", "0", "NA", "NA", "NA", "NA", "NA", "NA", "NA", "0", "NA", "NA", "0", "NA", "0", "1", "Chelsea", "Michy Batshuayi", "N'Golo Kanté", "0", "NA", "NA", "NA", "0", "NA", "NA", "0", "NA", "0", "NA", "NA", "NA", "0", "NA", "NA", "0", "0", "NA", "NA", "NA", "0", "NA", "NA", "NA", "NA", "2", "56", "0", "NA", "NA", "69"], ["480743", "Substitution, Chelsea. Daniel Drinkwater replaces N'Golo Kanté.", "71'", "Huddersfield Town", "0", "0", "0", "0", "0", "0", "NA", "NA", "NA", "NA", "NA", "NA", "NA", "0", "NA", "NA", "0", "NA", "0", "0", "NA", "NA", "NA", "0", "NA", "NA", "NA", "0", "NA", "NA", "0", "NA", "0", "NA", "NA", "NA", "0", "NA", "NA", "1", "0", "Chelsea", "Daniel Drinkwater", "N'Golo Kanté", "0", "NA", "NA", "NA", "NA", "2", "57", "0", "NA", "NA", "71"], ["480743", "Foul by Tommy Smith (Huddersfield Town).", "73'", "Huddersfield Town", "0", "0", "0", "0", "0", "0", "NA", "NA", "NA", "NA", "NA", "NA", "NA", "1", "Tommy Smith", "Huddersfield Town", "0", "NA", "0", "0", "NA", "NA", "NA", "0", "NA", "NA", "NA", "0", "NA", "NA", "0", "NA", "0", "NA", "NA", "NA", "0", "NA", "NA", "0", "0", "NA", "NA", "NA", "0", "NA", "NA", "NA", "NA", "2", "58", "0", "NA", "NA", "73"], ["480743", "Marcos Alonso (Chelsea) wins a free kick in the defensive half.", "73'", "Huddersfield Town", "0", "0", "0", "0", "0", "0", "NA", "NA", "NA", "NA", "NA", "NA", "NA", "0", "NA", "NA", "0", "NA", "0", "0", "NA", "NA", "NA", "0", "NA", "NA", "NA", "0", "NA", "NA", "0", "NA", "1", "Marcos Alonso", "Chelsea", "defensive half", "0", "NA", "NA", "0", "0", "NA", "NA", "NA", "0", "NA", "NA", "NA", "NA", "2", "59", "0", "NA", "NA", "73"], ["480743", "Substitution, Huddersfield Town. Laurent Depoitre replaces Steve Mounie.", "74'", "Huddersfield Town", "0", "0", "0", "0", "0", "0", "NA", "NA", "NA", "NA", "NA", "NA", "NA", "0", "NA", "NA", "0", "NA", "0", "0", "NA", "NA", "NA", "0", "NA", "NA", "NA", "0", "NA", "NA", "0", "NA", "0", "NA", "NA", "NA", "0", "NA", "NA", "1", "0", "Huddersfield Town", "Laurent Depoitre", "Steve Mounie", "0", "NA", "NA", "NA", "NA", "2", "60", "0", "NA", "NA", "74"], ["480743", "Foul by Christopher Schindler (Huddersfield Town).", "76'", "Huddersfield Town", "0", "0", "0", "0", "0", "0", "NA", "NA", "NA", "NA", "NA", "NA", "NA", "1", "Christopher Schindler", "Huddersfield Town", "0", "NA", "0", "0", "NA", "NA", "NA", "0", "NA", "NA", "NA", "0", "NA", "NA", "0", "NA", "0", "NA", "NA", "NA", "0", "NA", "NA", "0", "0", "NA", "NA", "NA", "0", "NA", "NA", "NA", "NA", "2", "61", "0", "NA", "NA", "76"], ["480743", "Michy Batshuayi (Chelsea) wins a free kick in the attacking half.", "76'", "Huddersfield Town", "0", "0", "0", "0", "0", "0", "NA", "NA", "NA", "NA", "NA", "NA", "NA", "0", "NA", "NA", "0", "NA", "0", "0", "NA", "NA", "NA", "0", "NA", "NA", "NA", "0", "NA", "NA", "0", "NA", "1", "Michy Batshuayi", "Chelsea", "attacking half", "0", "NA", "NA", "0", "0", "NA", "NA", "NA", "0", "NA", "NA", "NA", "NA", "2", "62", "0", "NA", "NA", "76"], ["480743", "Foul by Aaron Mooy (Huddersfield Town).", "79'", "Huddersfield Town", "0", "0", "0", "0", "0", "0", "NA", "NA", "NA", "NA", "NA", "NA", "NA", "1", "Aaron Mooy", "Huddersfield Town", "0", "NA", "0", "0", "NA", "NA", "NA", "0", "NA", "NA", "NA", "0", "NA", "NA", "0", "NA", "0", "NA", "NA", "NA", "0", "NA", "NA", "0", "0", "NA", "NA", "NA", "0", "NA", "NA", "NA", "NA", "2", "63", "0", "NA", "NA", "79"], ["480743", "Victor Moses (Chelsea) wins a free kick in the defensive half.", "79'", "Huddersfield Town", "0", "0", "0", "0", "0", "0", "NA", "NA", "NA", "NA", "NA", "NA", "NA", "0", "NA", "NA", "0", "NA", "0", "0", "NA", "NA", "NA", "0", "NA", "NA", "NA", "0", "NA", "NA", "0", "NA", "1", "Victor Moses", "Chelsea", "defensive half", "0", "NA", "NA", "0", "0", "NA", "NA", "NA", "0", "NA", "NA", "NA", "NA", "2", "64", "0", "NA", "NA", "79"], ["480743", "Substitution, Chelsea. Ethan Ampadu replaces Andreas Christensen.", "80'", "Huddersfield Town", "0", "0", "0", "0", "0", "0", "NA", "NA", "NA", "NA", "NA", "NA", "NA", "0", "NA", "NA", "0", "NA", "0", "0", "NA", "NA", "NA", "0", "NA", "NA", "NA", "0", "NA", "NA", "0", "NA", "0", "NA", "NA", "NA", "0", "NA", "NA", "1", "0", "Chelsea", "Ethan Ampadu", "Andreas Christensen", "0", "NA", "NA", "NA", "NA", "2", "65", "0", "NA", "NA", "80"], ["480743", "Offside, Chelsea. Marcos Alonso tries a through ball, but Michy Batshuayi is caught offside.", "80'", "Huddersfield Town", "0", "0", "0", "0", "0", "0", "NA", "NA", "NA", "NA", "NA", "NA", "NA", "0", "NA", "NA", "0", "NA", "0", "1", "Chelsea", "Michy Batshuayi", "Marcos Alonso", "0", "NA", "NA", "NA", "0", "NA", "NA", "0", "NA", "0", "NA", "NA", "NA", "0", "NA", "NA", "0", "0", "NA", "NA", "NA", "0", "NA", "NA", "NA", "NA", "2", "66", "0", "NA", "NA", "80"], ["480743", "Offside, Chelsea. Michy Batshuayi tries a through ball, but Pedro is caught offside.", "82'", "Huddersfield Town", "0", "0", "0", "0", "0", "0", "NA", "NA", "NA", "NA", "NA", "NA", "NA", "0", "NA", "NA", "0", "NA", "0", "1", "Chelsea", "Pedro", "Michy Batshuayi", "0", "NA", "NA", "NA", "0", "NA", "NA", "0", "NA", "0", "NA", "NA", "NA", "0", "NA", "NA", "0", "0", "NA", "NA", "NA", "0", "NA", "NA", "NA", "NA", "2", "67", "0", "NA", "NA", "82"], ["480743", "Offside, Chelsea. Antonio Rüdiger tries a through ball, but Victor Moses is caught offside.", "86'", "Huddersfield Town", "0", "0", "0", "0", "0", "0", "NA", "NA", "NA", "NA", "NA", "NA", "NA", "0", "NA", "NA", "0", "NA", "0", "1", "Chelsea", "Victor Moses", "Antonio Rüdiger", "0", "NA", "NA", "NA", "0", "NA", "NA", "0", "NA", "0", "NA", "NA", "NA", "0", "NA", "NA", "0", "0", "NA", "NA", "NA", "0", "NA", "NA", "NA", "NA", "2", "68", "0", "NA", "NA", "86"], ["480743", "Foul by Laurent Depoitre (Huddersfield Town).", "87'", "Huddersfield Town", "0", "0", "0", "0", "0", "0", "NA", "NA", "NA", "NA", "NA", "NA", "NA", "1", "Laurent Depoitre", "Huddersfield Town", "0", "NA", "0", "0", "NA", "NA", "NA", "0", "NA", "NA", "NA", "0", "NA", "NA", "0", "NA", "0", "NA", "NA", "NA", "0", "NA", "NA", "0", "0", "NA", "NA", "NA", "0", "NA", "NA", "NA", "NA", "2", "69", "0", "NA", "NA", "87"], ["480743", "Tiemoué Bakayoko (Chelsea) wins a free kick in the defensive half.", "87'", "Huddersfield Town", "0", "0", "0", "0", "0", "0", "NA", "NA", "NA", "NA", "NA", "NA", "NA", "0", "NA", "NA", "0", "NA", "0", "0", "NA", "NA", "NA", "0", "NA", "NA", "NA", "0", "NA", "NA", "0", "NA", "1", "Tiemoué Bakayoko", "Chelsea", "defensive half", "0", "NA", "NA", "0", "0", "NA", "NA", "NA", "0", "NA", "NA", "NA", "NA", "2", "70", "0", "NA", "NA", "87"], ["480743", "Hand ball by Michy Batshuayi (Chelsea).", "88'", "Huddersfield Town", "0", "0", "0", "0", "0", "0", "NA", "NA", "NA", "NA", "NA", "NA", "NA", "0", "NA", "NA", "0", "NA", "0", "0", "NA", "NA", "NA", "0", "NA", "NA", "NA", "0", "NA", "NA", "0", "NA", "0", "NA", "NA", "NA", "0", "NA", "NA", "0", "0", "NA", "NA", "NA", "0", "NA", "NA", "NA", "NA", "2", "71", "0", "NA", "NA", "88"], ["480743", "Attempt missed. Danny Williams (Huddersfield Town) right footed shot from outside the box is close, but misses to the left.", "90'", "Huddersfield Town", "0", "0", "0", "0", "1", "0", "missed", "Danny Williams", "Huddersfield Town", "right", "outside the box", "close, but left", "NA", "0", "NA", "NA", "0", "NA", "0", "0", "NA", "NA", "NA", "0", "NA", "NA", "NA", "0", "NA", "NA", "0", "NA", "0", "NA", "NA", "NA", "0", "NA", "NA", "0", "0", "NA", "NA", "NA", "0", "NA", "NA", "NA", "NA", "2", "72", "0", "NA", "NA", "90"], ["480743", "Attempt missed. Laurent Depoitre (Huddersfield Town) right footed shot from the centre of the box is close, but misses to the left. Assisted by Danny Williams.", "90'", "Huddersfield Town", "0", "0", "0", "0", "1", "0", "missed", "Laurent Depoitre", "Huddersfield Town", "right", "the centre of the box", "close, but left", "Danny Williams", "0", "NA", "NA", "0", "NA", "0", "0", "NA", "NA", "NA", "0", "NA", "NA", "NA", "0", "NA", "NA", "0", "NA", "0", "NA", "NA", "NA", "0", "NA", "NA", "0", "0", "NA", "NA", "NA", "0", "NA", "NA", "NA", "NA", "2", "73", "0", "NA", "NA", "90"], ["480743", "Aaron Mooy (Huddersfield Town) wins a free kick in the attacking half.", "90'", "Huddersfield Town", "0", "0", "0", "0", "0", "0", "NA", "NA", "NA", "NA", "NA", "NA", "NA", "0", "NA", "NA", "0", "NA", "0", "0", "NA", "NA", "NA", "0", "NA", "NA", "NA", "0", "NA", "NA", "0", "NA", "1", "Aaron Mooy", "Huddersfield Town", "attacking half", "0", "NA", "NA", "0", "0", "NA", "NA", "NA", "0", "NA", "NA", "NA", "NA", "2", "74", "0", "NA", "NA", "90"], ["480743", "Foul by Daniel Drinkwater (Chelsea).", "90'", "Huddersfield Town", "0", "0", "0", "0", "0", "0", "NA", "NA", "NA", "NA", "NA", "NA", "NA", "1", "Daniel Drinkwater", "Chelsea", "0", "NA", "0", "0", "NA", "NA", "NA", "0", "NA", "NA", "NA", "0", "NA", "NA", "0", "NA", "0", "NA", "NA", "NA", "0", "NA", "NA", "0", "0", "NA", "NA", "NA", "0", "NA", "NA", "NA", "NA", "2", "75", "0", "NA", "NA", "90"], ["480743", "Goal!  Huddersfield Town 1, Chelsea 3. Laurent Depoitre (Huddersfield Town) header from the centre of the box to the bottom right corner. Assisted by Florent Hadergjonaj with a cross.", "90'+2'", "Huddersfield Town", "1", "0", "0", "0", "1", "0", "goal", "Laurent Depoitre", "Huddersfield Town", "header", "the centre of the box", "bottom right corner", "Florent Hadergjonaj", "0", "NA", "NA", "0", "cross", "0", "0", "NA", "NA", "NA", "0", "NA", "NA", "NA", "0", "NA", "NA", "0", "NA", "0", "NA", "NA", "NA", "0", "NA", "NA", "0", "0", "NA", "NA", "NA", "0", "NA", "NA", "NA", "NA", "2", "76", "1", "NA", "NA", "92"], ["480743", "Second Half ends, Huddersfield Town 1, Chelsea 3.", "90'+3'", "Huddersfield Town", "1", "1", "0", "0", "0", "0", "NA", "NA", "NA", "NA", "NA", "NA", "NA", "0", "NA", "NA", "0", "NA", "0", "0", "NA", "NA", "NA", "0", "NA", "NA", "NA", "0", "NA", "NA", "0", "NA", "0", "NA", "NA", "NA", "0", "NA", "NA", "0", "0", "NA", "NA", "NA", "0", "NA", "NA", "NA", "NA", "2", "77", "1", "NA", "NA", "93"], ["480743", "Match ends, Huddersfield Town 1, Chelsea 3.", "90'+3'", "Huddersfield Town", "1", "0", "1", "0", "0", "0", "NA", "NA", "NA", "NA", "NA", "NA", "NA", "0", "NA", "NA", "0", "NA", "0", "0", "NA", "NA", "NA", "0", "NA", "NA", "NA", "0", "NA", "NA", "0", "NA", "0", "NA", "NA", "NA", "0", "NA", "NA", "0", "0", "NA", "NA", "NA", "0", "NA", "NA", "NA", "NA", "2", "78", "1", "NA", "NA", "93"]], "Lineup": {"Home Player 9": "Christopher Schindler", "Home Player 8": "Steve Mounie", "Home Player 5": "Jonas Lossl", "Home Player 4": "Elias Kachunga", "Home Player 7": "Aaron Mooy", "Home Player 6": "Chris Lowe", "Home Player 1": "Jonathan Hogg", "Home Player 3": "Mathias Jorgensen", "Home Player 2": "Tom Ince", "Away Player 10": "Antonio Rudiger", "Away Player 11": "Willian", "Away Player 8": "Victor Moses", "Away Player 9": "Pedro", "Away Player 1": "Marcos Alonso", "Away Player 2": "Cesar Azpilicueta", "Away Player 3": "Tiemoue Bakayoko", "Away Player 4": "Andreas Christensen", "Away Player 5": "Thibaut Courtois", "Away Player 6": "Eden Hazard", "Away Player 7": "N'Golo Kanté", "Game ID": "g_1_xvmHtjV1", "Home Player 11": "Daniel Williams", "Home Player 10": "Tom Smith"}}