{"Stats": {"Full Time Result": "A", "Away Team Corners": 1, "Referee": "A Marriner", "Home Team Fouls Committed": 11, "Away Team Shots": 9, "Away Team Red Cards": 0, "Home Team Red Cards": 0, "Half Time Away Team Goals": 3, "Full Time Home Team Goals": 0, "Away Team Yellow Cards": 1, "Away Team Shots on Target": 5, "Half Time Home Team Goals": 0, "Half Time Result": "A", "Away Team Fouls Committed": 11, "Home Team Yellow Cards": 1, "Home Team Shots": 10, "Div": "E0", "Home Team Corners": 6, "Home Team Shots on Target": 5, "Full Time Away Team Goals": 3}, "Description": "Bernardo Silva (Manchester City) wins a free kick in the defensive half. at minute 1. Foul by Granit Xhaka (Arsenal). at minute 1. Attempt missed. Sergio Agüero (Manchester City) right footed shot from a difficult angle on the right is close, but misses to the right. Assisted by Kevin De Bruyne with a through ball. at minute 9. Corner,  Manchester City. Conceded by Héctor Bellerín. at minute 10. Attempt blocked. Sergio Agüero (Manchester City) left footed shot from outside the box is blocked. at minute 11. Attempt saved. Henrikh Mkhitaryan (Arsenal) left footed shot from outside the box is saved in the centre of the goal. Assisted by Mesut Özil. at minute 13. Goal!  Arsenal 0, Manchester City 1. Bernardo Silva (Manchester City) left footed shot from the right side of the box to the top left corner. Assisted by Leroy Sané. at minute 15. Foul by David Silva (Manchester City). at minute 18. Granit Xhaka (Arsenal) wins a free kick in the attacking half. at minute 18. Danny Welbeck (Arsenal) wins a free kick in the attacking half. at minute 19. Foul by Nicolás Otamendi (Manchester City). at minute 19. Nicolás Otamendi (Manchester City) is shown the yellow card for a bad foul. at minute 19. Attempt saved. Granit Xhaka (Arsenal) left footed shot from outside the box is saved in the bottom right corner. at minute 20. Corner,  Arsenal. Conceded by Ederson. at minute 20. David Silva (Manchester City) wins a free kick in the defensive half. at minute 21. Foul by Aaron Ramsey (Arsenal). at minute 21. Attempt saved. Aaron Ramsey (Arsenal) right footed shot from the centre of the box is saved in the top centre of the goal. Assisted by Héctor Bellerín. at minute 23. Foul by Granit Xhaka (Arsenal). at minute 25. Sergio Agüero (Manchester City) wins a free kick on the left wing. at minute 25. Offside, Manchester City. Kevin De Bruyne tries a through ball, but Sergio Agüero is caught offside. at minute 26. Goal!  Arsenal 0, Manchester City 2. David Silva (Manchester City) left footed shot from the centre of the box to the top left corner. Assisted by Sergio Agüero. at minute 28. Bernardo Silva (Manchester City) wins a free kick in the defensive half. at minute 32. Foul by Sead Kolasinac (Arsenal). at minute 32. Sead Kolasinac (Arsenal) is shown the yellow card for a bad foul. at minute 32. Goal!  Arsenal 0, Manchester City 3. Leroy Sané (Manchester City) left footed shot from the centre of the box to the bottom right corner. Assisted by Kyle Walker. at minute 33. Attempt blocked. Aaron Ramsey (Arsenal) right footed shot from outside the box is blocked. Assisted by Mesut Özil. at minute 38. Corner,  Arsenal. Conceded by Danilo. at minute 38. Attempt missed. Henrikh Mkhitaryan (Arsenal) left footed shot from outside the box is close, but misses to the right following a corner. at minute 38. Attempt saved. Sergio Agüero (Manchester City) left footed shot from the right side of the six yard box is saved in the centre of the goal. Assisted by Kevin De Bruyne. at minute 39. Aaron Ramsey (Arsenal) wins a free kick in the attacking half. at minute 40. Foul by Bernardo Silva (Manchester City). at minute 40. Attempt blocked. Mesut Özil (Arsenal) left footed shot from the centre of the box is blocked. Assisted by Pierre-Emerick Aubameyang. at minute 42. Corner,  Arsenal. Conceded by David Silva. at minute 42. Danny Welbeck (Arsenal) wins a free kick in the defensive half. at minute 44. Foul by Sergio Agüero (Manchester City). at minute 44. Attempt blocked. Danny Welbeck (Arsenal) right footed shot from the centre of the box is blocked. Assisted by Henrikh Mkhitaryan. at minute 45. Corner,  Arsenal. Conceded by Nicolás Otamendi. at minute 45. Attempt saved. Granit Xhaka (Arsenal) left footed shot from outside the box is saved in the centre of the goal. at minute 46. First Half ends, Arsenal 0, Manchester City 3. at minute 48. Second Half begins Arsenal 0, Manchester City 3. at minute 45. Foul by Sead Kolasinac (Arsenal). at minute 46. Kyle Walker (Manchester City) wins a free kick in the defensive half. at minute 46. Bernardo Silva (Manchester City) wins a free kick in the defensive half. at minute 50. Foul by Mesut Özil (Arsenal). at minute 50. Penalty Arsenal. Henrikh Mkhitaryan draws a foul in the penalty area. at minute 52. Penalty conceded by Nicolás Otamendi (Manchester City) after a foul in the penalty area. at minute 52. Penalty saved! Pierre-Emerick Aubameyang (Arsenal) fails to capitalise on this great opportunity,  right footed shot saved  in the bottom right corner. at minute 53. David Silva (Manchester City) wins a free kick on the left wing. at minute 54. Foul by Aaron Ramsey (Arsenal). at minute 54. Danny Welbeck (Arsenal) wins a free kick in the defensive half. at minute 58. Foul by Ilkay Gündogan (Manchester City). at minute 58. Corner,  Arsenal. Conceded by Ilkay Gündogan. at minute 58. Attempt missed. Pierre-Emerick Aubameyang (Arsenal) right footed shot from the centre of the box is close, but misses to the left. Assisted by Aaron Ramsey following a corner. at minute 58. Aaron Ramsey (Arsenal) wins a free kick in the attacking half. at minute 60. Foul by Vincent Kompany (Manchester City). at minute 60. Bernardo Silva (Manchester City) wins a free kick in the defensive half. at minute 66. Foul by Aaron Ramsey (Arsenal). at minute 66. Bernardo Silva (Manchester City) wins a free kick in the defensive half. at minute 70. Foul by Sead Kolasinac (Arsenal). at minute 70. Substitution, Manchester City. Oleksandr Zinchenko replaces Kyle Walker because of an injury. at minute 72. Foul by Laurent Koscielny (Arsenal). at minute 73. Kevin De Bruyne (Manchester City) wins a free kick in the defensive half. at minute 73. Foul by Henrikh Mkhitaryan (Arsenal). at minute 75. Oleksandr Zinchenko (Manchester City) wins a free kick in the defensive half. at minute 75. Attempt saved. Sergio Agüero (Manchester City) right footed shot from the right side of the box is saved in the centre of the goal. Assisted by Ilkay Gündogan. at minute 78. Substitution, Manchester City. Yaya Touré replaces Sergio Agüero. at minute 82. Foul by Oleksandr Zinchenko (Manchester City). at minute 83. Mesut Özil (Arsenal) wins a free kick on the right wing. at minute 83. Substitution, Manchester City. Gabriel Jesus replaces David Silva. at minute 87. Foul by Gabriel Jesus (Manchester City). at minute 88. Granit Xhaka (Arsenal) wins a free kick in the defensive half. at minute 88. Attempt blocked. Gabriel Jesus (Manchester City) right footed shot from the left side of the box is blocked. at minute 89. Attempt blocked. Kevin De Bruyne (Manchester City) right footed shot from outside the box is blocked. at minute 89. Aaron Ramsey (Arsenal) wins a free kick in the defensive half. at minute 89. Foul by Oleksandr Zinchenko (Manchester City). at minute 89. Corner,  Arsenal. Conceded by Bernardo Silva. at minute 91. Foul by Leroy Sané (Manchester City). at minute 92. Henrikh Mkhitaryan (Arsenal) wins a free kick on the right wing. at minute 92. Second Half ends, Arsenal 0, Manchester City 3. at minute 93. Match ends, Arsenal 0, Manchester City 3. at minute 93. ", "Home Team": "Arsenal", "Away Team": "Manchester City", "Date": "2018-03-01", "Commentary": [["480629", "First Half begins.", "-", "Arsenal", "0", "0", "0", "1", "0", "0", "NA", "NA", "NA", "NA", "NA", "NA", "NA", "0", "NA", "NA", "0", "NA", "0", "0", "NA", "NA", "NA", "0", "NA", "NA", "NA", "0", "NA", "NA", "0", "NA", "0", "NA", "NA", "NA", "0", "NA", "NA", "0", "0", "NA", "NA", "NA", "0", "NA", "NA", "NA", "NA", "1", "1", "0", "NA", "NA", "NA"], ["480629", "Lineups are announced and players are warming up.", "-", "Arsenal", "0", "0", "0", "0", "0", "0", "NA", "NA", "NA", "NA", "NA", "NA", "NA", "0", "NA", "NA", "0", "NA", "0", "0", "NA", "NA", "NA", "0", "NA", "NA", "NA", "0", "NA", "NA", "0", "NA", "0", "NA", "NA", "NA", "0", "NA", "NA", "0", "0", "NA", "NA", "NA", "0", "NA", "NA", "NA", "NA", "1", "2", "0", "NA", "NA", "NA"], ["480629", "Bernardo Silva (Manchester City) wins a free kick in the defensive half.", "1'", "Arsenal", "0", "0", "0", "0", "0", "0", "NA", "NA", "NA", "NA", "NA", "NA", "NA", "0", "NA", "NA", "0", "NA", "0", "0", "NA", "NA", "NA", "0", "NA", "NA", "NA", "0", "NA", "NA", "0", "NA", "1", "Bernardo Silva", "Manchester City", "defensive half", "0", "NA", "NA", "0", "0", "NA", "NA", "NA", "0", "NA", "NA", "NA", "NA", "1", "3", "0", "NA", "NA", "1"], ["480629", "Foul by Granit Xhaka (Arsenal).", "1'", "Arsenal", "0", "0", "0", "0", "0", "0", "NA", "NA", "NA", "NA", "NA", "NA", "NA", "1", "Granit Xhaka", "Arsenal", "0", "NA", "0", "0", "NA", "NA", "NA", "0", "NA", "NA", "NA", "0", "NA", "NA", "0", "NA", "0", "NA", "NA", "NA", "0", "NA", "NA", "0", "0", "NA", "NA", "NA", "0", "NA", "NA", "NA", "NA", "1", "4", "0", "NA", "NA", "1"], ["480629", "Attempt missed. Sergio Agüero (Manchester City) right footed shot from a difficult angle on the right is close, but misses to the right. Assisted by Kevin De Bruyne with a through ball.", "9'", "Arsenal", "0", "0", "0", "0", "1", "0", "missed", "Sergio Agüero", "Manchester City", "right", "NA", "NA", "Kevin De Bruyne", "0", "NA", "NA", "0", "through", "0", "0", "NA", "NA", "NA", "0", "NA", "NA", "NA", "0", "NA", "NA", "0", "NA", "0", "NA", "NA", "NA", "0", "NA", "NA", "0", "0", "NA", "NA", "NA", "0", "NA", "NA", "NA", "NA", "1", "5", "0", "NA", "NA", "9"], ["480629", "Corner,  Manchester City. Conceded by Héctor Bellerín.", "10'", "Arsenal", "0", "0", "0", "0", "0", "0", "NA", "NA", "NA", "NA", "NA", "NA", "NA", "0", "NA", "NA", "0", "NA", "0", "0", "NA", "NA", "NA", "0", "NA", "NA", "NA", "0", "NA", "NA", "0", "NA", "0", "NA", "NA", "NA", "1", "Manchester City", "Héctor Bellerín", "0", "0", "NA", "NA", "NA", "0", "NA", "NA", "NA", "NA", "1", "6", "0", "NA", "NA", "10"], ["480629", "Attempt blocked. Sergio Agüero (Manchester City) left footed shot from outside the box is blocked.", "11'", "Arsenal", "0", "0", "0", "0", "1", "0", "blocked", "Sergio Agüero", "Manchester City", "left", "outside the box", "NA", "NA", "0", "NA", "NA", "0", "NA", "0", "0", "NA", "NA", "NA", "0", "NA", "NA", "NA", "0", "NA", "NA", "0", "NA", "0", "NA", "NA", "NA", "0", "NA", "NA", "0", "0", "NA", "NA", "NA", "0", "NA", "NA", "NA", "NA", "1", "7", "0", "NA", "NA", "11"], ["480629", "Attempt saved. Henrikh Mkhitaryan (Arsenal) left footed shot from outside the box is saved in the centre of the goal. Assisted by Mesut Özil.", "13'", "Arsenal", "0", "0", "0", "0", "1", "0", "saved", "Henrikh Mkhitaryan", "Arsenal", "left", "outside the box", "the centre of the goal", "Mesut Özil", "0", "NA", "NA", "0", "NA", "0", "0", "NA", "NA", "NA", "0", "NA", "NA", "NA", "0", "NA", "NA", "0", "NA", "0", "NA", "NA", "NA", "0", "NA", "NA", "0", "0", "NA", "NA", "NA", "0", "NA", "NA", "NA", "NA", "1", "8", "0", "NA", "NA", "13"], ["480629", "Goal!  Arsenal 0, Manchester City 1. Bernardo Silva (Manchester City) left footed shot from the right side of the box to the top left corner. Assisted by Leroy Sané.", "15'", "Arsenal", "0", "0", "0", "0", "1", "0", "goal", "Bernardo Silva", "Manchester City", "left", "the right side of the box", "top left corner", "Leroy Sané", "0", "NA", "NA", "0", "NA", "0", "0", "NA", "NA", "NA", "0", "NA", "NA", "NA", "0", "NA", "NA", "0", "NA", "0", "NA", "NA", "NA", "0", "NA", "NA", "0", "0", "NA", "NA", "NA", "0", "NA", "NA", "NA", "NA", "1", "9", "0", "NA", "NA", "15"], ["480629", "Foul by David Silva (Manchester City).", "18'", "Arsenal", "0", "0", "0", "0", "0", "0", "NA", "NA", "NA", "NA", "NA", "NA", "NA", "1", "David Silva", "Manchester City", "0", "NA", "0", "0", "NA", "NA", "NA", "0", "NA", "NA", "NA", "0", "NA", "NA", "0", "NA", "0", "NA", "NA", "NA", "0", "NA", "NA", "0", "0", "NA", "NA", "NA", "0", "NA", "NA", "NA", "NA", "1", "10", "0", "NA", "NA", "18"], ["480629", "Granit Xhaka (Arsenal) wins a free kick in the attacking half.", "18'", "Arsenal", "0", "0", "0", "0", "0", "0", "NA", "NA", "NA", "NA", "NA", "NA", "NA", "0", "NA", "NA", "0", "NA", "0", "0", "NA", "NA", "NA", "0", "NA", "NA", "NA", "0", "NA", "NA", "0", "NA", "1", "Granit Xhaka", "Arsenal", "attacking half", "0", "NA", "NA", "0", "0", "NA", "NA", "NA", "0", "NA", "NA", "NA", "NA", "1", "11", "0", "NA", "NA", "18"], ["480629", "Danny Welbeck (Arsenal) wins a free kick in the attacking half.", "19'", "Arsenal", "0", "0", "0", "0", "0", "0", "NA", "NA", "NA", "NA", "NA", "NA", "NA", "0", "NA", "NA", "0", "NA", "0", "0", "NA", "NA", "NA", "0", "NA", "NA", "NA", "0", "NA", "NA", "0", "NA", "1", "Danny Welbeck", "Arsenal", "attacking half", "0", "NA", "NA", "0", "0", "NA", "NA", "NA", "0", "NA", "NA", "NA", "NA", "1", "12", "0", "NA", "NA", "19"], ["480629", "Foul by Nicolás Otamendi (Manchester City).", "19'", "Arsenal", "0", "0", "0", "0", "0", "0", "NA", "NA", "NA", "NA", "NA", "NA", "NA", "1", "Nicolás Otamendi", "Manchester City", "0", "NA", "0", "0", "NA", "NA", "NA", "0", "NA", "NA", "NA", "0", "NA", "NA", "0", "NA", "0", "NA", "NA", "NA", "0", "NA", "NA", "0", "0", "NA", "NA", "NA", "0", "NA", "NA", "NA", "NA", "1", "13", "0", "NA", "NA", "19"], ["480629", "Nicolás Otamendi (Manchester City) is shown the yellow card for a bad foul.", "19'", "Arsenal", "0", "0", "0", "0", "0", "0", "NA", "NA", "NA", "NA", "NA", "NA", "NA", "0", "NA", "NA", "0", "NA", "0", "0", "NA", "NA", "NA", "1", "yellow", "Nicolás Otamendi", "Manchester City", "0", "NA", "NA", "0", "NA", "0", "NA", "NA", "NA", "0", "NA", "NA", "0", "0", "NA", "NA", "NA", "0", "NA", "NA", "NA", "NA", "1", "14", "0", "NA", "NA", "19"], ["480629", "Attempt saved. Granit Xhaka (Arsenal) left footed shot from outside the box is saved in the bottom right corner.", "20'", "Arsenal", "0", "0", "0", "0", "1", "0", "saved", "Granit Xhaka", "Arsenal", "left", "outside the box", "the bottom right corner", "NA", "0", "NA", "NA", "0", "NA", "0", "0", "NA", "NA", "NA", "0", "NA", "NA", "NA", "0", "NA", "NA", "0", "NA", "0", "NA", "NA", "NA", "0", "NA", "NA", "0", "0", "NA", "NA", "NA", "0", "NA", "NA", "NA", "NA", "1", "15", "0", "NA", "NA", "20"], ["480629", "Corner,  Arsenal. Conceded by Ederson.", "20'", "Arsenal", "0", "0", "0", "0", "0", "0", "NA", "NA", "NA", "NA", "NA", "NA", "NA", "0", "NA", "NA", "0", "NA", "0", "0", "NA", "NA", "NA", "0", "NA", "NA", "NA", "0", "NA", "NA", "0", "NA", "0", "NA", "NA", "NA", "1", "Arsenal", "Ederson", "0", "0", "NA", "NA", "NA", "0", "NA", "NA", "NA", "NA", "1", "16", "0", "NA", "NA", "20"], ["480629", "David Silva (Manchester City) wins a free kick in the defensive half.", "21'", "Arsenal", "0", "0", "0", "0", "0", "0", "NA", "NA", "NA", "NA", "NA", "NA", "NA", "0", "NA", "NA", "0", "NA", "0", "0", "NA", "NA", "NA", "0", "NA", "NA", "NA", "0", "NA", "NA", "0", "NA", "1", "David Silva", "Manchester City", "defensive half", "0", "NA", "NA", "0", "0", "NA", "NA", "NA", "0", "NA", "NA", "NA", "NA", "1", "17", "0", "NA", "NA", "21"], ["480629", "Foul by Aaron Ramsey (Arsenal).", "21'", "Arsenal", "0", "0", "0", "0", "0", "0", "NA", "NA", "NA", "NA", "NA", "NA", "NA", "1", "Aaron Ramsey", "Arsenal", "0", "NA", "0", "0", "NA", "NA", "NA", "0", "NA", "NA", "NA", "0", "NA", "NA", "0", "NA", "0", "NA", "NA", "NA", "0", "NA", "NA", "0", "0", "NA", "NA", "NA", "0", "NA", "NA", "NA", "NA", "1", "18", "0", "NA", "NA", "21"], ["480629", "Attempt saved. Aaron Ramsey (Arsenal) right footed shot from the centre of the box is saved in the top centre of the goal. Assisted by Héctor Bellerín.", "23'", "Arsenal", "0", "0", "0", "0", "1", "0", "saved", "Aaron Ramsey", "Arsenal", "right", "the centre of the box", "the top centre of the goal", "Héctor Bellerín", "0", "NA", "NA", "0", "NA", "0", "0", "NA", "NA", "NA", "0", "NA", "NA", "NA", "0", "NA", "NA", "0", "NA", "0", "NA", "NA", "NA", "0", "NA", "NA", "0", "0", "NA", "NA", "NA", "0", "NA", "NA", "NA", "NA", "1", "19", "0", "NA", "NA", "23"], ["480629", "Foul by Granit Xhaka (Arsenal).", "25'", "Arsenal", "0", "0", "0", "0", "0", "0", "NA", "NA", "NA", "NA", "NA", "NA", "NA", "1", "Granit Xhaka", "Arsenal", "0", "NA", "0", "0", "NA", "NA", "NA", "0", "NA", "NA", "NA", "0", "NA", "NA", "0", "NA", "0", "NA", "NA", "NA", "0", "NA", "NA", "0", "0", "NA", "NA", "NA", "0", "NA", "NA", "NA", "NA", "1", "20", "0", "NA", "NA", "25"], ["480629", "Sergio Agüero (Manchester City) wins a free kick on the left wing.", "25'", "Arsenal", "0", "0", "0", "0", "0", "0", "NA", "NA", "NA", "NA", "NA", "NA", "NA", "0", "NA", "NA", "0", "NA", "0", "0", "NA", "NA", "NA", "0", "NA", "NA", "NA", "0", "NA", "NA", "0", "NA", "1", "Sergio Agüero", "Manchester City", "NA", "0", "NA", "NA", "0", "0", "NA", "NA", "NA", "0", "NA", "NA", "NA", "NA", "1", "21", "0", "NA", "NA", "25"], ["480629", "Offside, Manchester City. Kevin De Bruyne tries a through ball, but Sergio Agüero is caught offside.", "26'", "Arsenal", "0", "0", "0", "0", "0", "0", "NA", "NA", "NA", "NA", "NA", "NA", "NA", "0", "NA", "NA", "0", "NA", "0", "1", "Manchester City", "Sergio Agüero", "Kevin De Bruyne", "0", "NA", "NA", "NA", "0", "NA", "NA", "0", "NA", "0", "NA", "NA", "NA", "0", "NA", "NA", "0", "0", "NA", "NA", "NA", "0", "NA", "NA", "NA", "NA", "1", "22", "0", "NA", "NA", "26"], ["480629", "Goal!  Arsenal 0, Manchester City 2. David Silva (Manchester City) left footed shot from the centre of the box to the top left corner. Assisted by Sergio Agüero.", "28'", "Arsenal", "0", "0", "0", "0", "1", "0", "goal", "David Silva", "Manchester City", "left", "the centre of the box", "top left corner", "Sergio Agüero", "0", "NA", "NA", "0", "NA", "0", "0", "NA", "NA", "NA", "0", "NA", "NA", "NA", "0", "NA", "NA", "0", "NA", "0", "NA", "NA", "NA", "0", "NA", "NA", "0", "0", "NA", "NA", "NA", "0", "NA", "NA", "NA", "NA", "1", "23", "0", "NA", "NA", "28"], ["480629", "Bernardo Silva (Manchester City) wins a free kick in the defensive half.", "32'", "Arsenal", "0", "0", "0", "0", "0", "0", "NA", "NA", "NA", "NA", "NA", "NA", "NA", "0", "NA", "NA", "0", "NA", "0", "0", "NA", "NA", "NA", "0", "NA", "NA", "NA", "0", "NA", "NA", "0", "NA", "1", "Bernardo Silva", "Manchester City", "defensive half", "0", "NA", "NA", "0", "0", "NA", "NA", "NA", "0", "NA", "NA", "NA", "NA", "1", "24", "0", "NA", "NA", "32"], ["480629", "Foul by Sead Kolasinac (Arsenal).", "32'", "Arsenal", "0", "0", "0", "0", "0", "0", "NA", "NA", "NA", "NA", "NA", "NA", "NA", "1", "Sead Kolasinac", "Arsenal", "0", "NA", "0", "0", "NA", "NA", "NA", "0", "NA", "NA", "NA", "0", "NA", "NA", "0", "NA", "0", "NA", "NA", "NA", "0", "NA", "NA", "0", "0", "NA", "NA", "NA", "0", "NA", "NA", "NA", "NA", "1", "25", "0", "NA", "NA", "32"], ["480629", "Sead Kolasinac (Arsenal) is shown the yellow card for a bad foul.", "32'", "Arsenal", "0", "0", "0", "0", "0", "0", "NA", "NA", "NA", "NA", "NA", "NA", "NA", "0", "NA", "NA", "0", "NA", "0", "0", "NA", "NA", "NA", "1", "yellow", "Sead Kolasinac", "Arsenal", "0", "NA", "NA", "0", "NA", "0", "NA", "NA", "NA", "0", "NA", "NA", "0", "0", "NA", "NA", "NA", "0", "NA", "NA", "NA", "NA", "1", "26", "0", "NA", "NA", "32"], ["480629", "Goal!  Arsenal 0, Manchester City 3. Leroy Sané (Manchester City) left footed shot from the centre of the box to the bottom right corner. Assisted by Kyle Walker.", "33'", "Arsenal", "0", "0", "0", "0", "1", "0", "goal", "Leroy Sané", "Manchester City", "left", "the centre of the box", "bottom right corner", "Kyle Walker", "0", "NA", "NA", "0", "NA", "0", "0", "NA", "NA", "NA", "0", "NA", "NA", "NA", "0", "NA", "NA", "0", "NA", "0", "NA", "NA", "NA", "0", "NA", "NA", "0", "0", "NA", "NA", "NA", "0", "NA", "NA", "NA", "NA", "1", "27", "0", "NA", "NA", "33"], ["480629", "Attempt blocked. Aaron Ramsey (Arsenal) right footed shot from outside the box is blocked. Assisted by Mesut Özil.", "38'", "Arsenal", "0", "0", "0", "0", "1", "0", "blocked", "Aaron Ramsey", "Arsenal", "right", "outside the box", "NA", "Mesut Özil", "0", "NA", "NA", "0", "NA", "0", "0", "NA", "NA", "NA", "0", "NA", "NA", "NA", "0", "NA", "NA", "0", "NA", "0", "NA", "NA", "NA", "0", "NA", "NA", "0", "0", "NA", "NA", "NA", "0", "NA", "NA", "NA", "NA", "1", "28", "0", "NA", "NA", "38"], ["480629", "Corner,  Arsenal. Conceded by Danilo.", "38'", "Arsenal", "0", "0", "0", "0", "0", "0", "NA", "NA", "NA", "NA", "NA", "NA", "NA", "0", "NA", "NA", "0", "NA", "0", "0", "NA", "NA", "NA", "0", "NA", "NA", "NA", "0", "NA", "NA", "0", "NA", "0", "NA", "NA", "NA", "1", "Arsenal", "Danilo", "0", "0", "NA", "NA", "NA", "0", "NA", "NA", "NA", "NA", "1", "29", "0", "NA", "NA", "38"], ["480629", "Attempt missed. Henrikh Mkhitaryan (Arsenal) left footed shot from outside the box is close, but misses to the right following a corner.", "38'", "Arsenal", "0", "0", "0", "0", "1", "0", "missed", "Henrikh Mkhitaryan", "Arsenal", "left", "outside the box", "close, but right", "NA", "0", "NA", "NA", "0", "NA", "1", "0", "NA", "NA", "NA", "0", "NA", "NA", "NA", "0", "NA", "NA", "0", "NA", "0", "NA", "NA", "NA", "0", "NA", "NA", "0", "0", "NA", "NA", "NA", "0", "NA", "NA", "NA", "NA", "1", "30", "0", "NA", "NA", "38"], ["480629", "Attempt saved. Sergio Agüero (Manchester City) left footed shot from the right side of the six yard box is saved in the centre of the goal. Assisted by Kevin De Bruyne.", "39'", "Arsenal", "0", "0", "0", "0", "1", "0", "saved", "Sergio Agüero", "Manchester City", "left", "the right side of the six yard box", "the centre of the goal", "Kevin De Bruyne", "0", "NA", "NA", "0", "NA", "0", "0", "NA", "NA", "NA", "0", "NA", "NA", "NA", "0", "NA", "NA", "0", "NA", "0", "NA", "NA", "NA", "0", "NA", "NA", "0", "0", "NA", "NA", "NA", "0", "NA", "NA", "NA", "NA", "1", "31", "0", "NA", "NA", "39"], ["480629", "Aaron Ramsey (Arsenal) wins a free kick in the attacking half.", "40'", "Arsenal", "0", "0", "0", "0", "0", "0", "NA", "NA", "NA", "NA", "NA", "NA", "NA", "0", "NA", "NA", "0", "NA", "0", "0", "NA", "NA", "NA", "0", "NA", "NA", "NA", "0", "NA", "NA", "0", "NA", "1", "Aaron Ramsey", "Arsenal", "attacking half", "0", "NA", "NA", "0", "0", "NA", "NA", "NA", "0", "NA", "NA", "NA", "NA", "1", "32", "0", "NA", "NA", "40"], ["480629", "Foul by Bernardo Silva (Manchester City).", "40'", "Arsenal", "0", "0", "0", "0", "0", "0", "NA", "NA", "NA", "NA", "NA", "NA", "NA", "1", "Bernardo Silva", "Manchester City", "0", "NA", "0", "0", "NA", "NA", "NA", "0", "NA", "NA", "NA", "0", "NA", "NA", "0", "NA", "0", "NA", "NA", "NA", "0", "NA", "NA", "0", "0", "NA", "NA", "NA", "0", "NA", "NA", "NA", "NA", "1", "33", "0", "NA", "NA", "40"], ["480629", "Attempt blocked. Mesut Özil (Arsenal) left footed shot from the centre of the box is blocked. Assisted by Pierre-Emerick Aubameyang.", "42'", "Arsenal", "0", "0", "0", "0", "1", "0", "blocked", "Mesut Özil", "Arsenal", "left", "the centre of the box", "NA", "Pierre-Emerick", "0", "NA", "NA", "0", "NA", "0", "0", "NA", "NA", "NA", "0", "NA", "NA", "NA", "0", "NA", "NA", "0", "NA", "0", "NA", "NA", "NA", "0", "NA", "NA", "0", "0", "NA", "NA", "NA", "0", "NA", "NA", "NA", "NA", "1", "34", "0", "NA", "NA", "42"], ["480629", "Corner,  Arsenal. Conceded by David Silva.", "42'", "Arsenal", "0", "0", "0", "0", "0", "0", "NA", "NA", "NA", "NA", "NA", "NA", "NA", "0", "NA", "NA", "0", "NA", "0", "0", "NA", "NA", "NA", "0", "NA", "NA", "NA", "0", "NA", "NA", "0", "NA", "0", "NA", "NA", "NA", "1", "Arsenal", "David Silva", "0", "0", "NA", "NA", "NA", "0", "NA", "NA", "NA", "NA", "1", "35", "0", "NA", "NA", "42"], ["480629", "Danny Welbeck (Arsenal) wins a free kick in the defensive half.", "44'", "Arsenal", "0", "0", "0", "0", "0", "0", "NA", "NA", "NA", "NA", "NA", "NA", "NA", "0", "NA", "NA", "0", "NA", "0", "0", "NA", "NA", "NA", "0", "NA", "NA", "NA", "0", "NA", "NA", "0", "NA", "1", "Danny Welbeck", "Arsenal", "defensive half", "0", "NA", "NA", "0", "0", "NA", "NA", "NA", "0", "NA", "NA", "NA", "NA", "1", "36", "0", "NA", "NA", "44"], ["480629", "Foul by Sergio Agüero (Manchester City).", "44'", "Arsenal", "0", "0", "0", "0", "0", "0", "NA", "NA", "NA", "NA", "NA", "NA", "NA", "1", "Sergio Agüero", "Manchester City", "0", "NA", "0", "0", "NA", "NA", "NA", "0", "NA", "NA", "NA", "0", "NA", "NA", "0", "NA", "0", "NA", "NA", "NA", "0", "NA", "NA", "0", "0", "NA", "NA", "NA", "0", "NA", "NA", "NA", "NA", "1", "37", "0", "NA", "NA", "44"], ["480629", "Attempt blocked. Danny Welbeck (Arsenal) right footed shot from the centre of the box is blocked. Assisted by Henrikh Mkhitaryan.", "45'", "Arsenal", "0", "0", "0", "0", "1", "0", "blocked", "Danny Welbeck", "Arsenal", "right", "the centre of the box", "NA", "Henrikh Mkhitaryan", "0", "NA", "NA", "0", "NA", "0", "0", "NA", "NA", "NA", "0", "NA", "NA", "NA", "0", "NA", "NA", "0", "NA", "0", "NA", "NA", "NA", "0", "NA", "NA", "0", "0", "NA", "NA", "NA", "0", "NA", "NA", "NA", "NA", "1", "38", "0", "NA", "NA", "45"], ["480629", "Corner,  Arsenal. Conceded by Nicolás Otamendi.", "45'", "Arsenal", "0", "0", "0", "0", "0", "0", "NA", "NA", "NA", "NA", "NA", "NA", "NA", "0", "NA", "NA", "0", "NA", "0", "0", "NA", "NA", "NA", "0", "NA", "NA", "NA", "0", "NA", "NA", "0", "NA", "0", "NA", "NA", "NA", "1", "Arsenal", "Nicolás Otamendi", "0", "0", "NA", "NA", "NA", "0", "NA", "NA", "NA", "NA", "1", "39", "0", "NA", "NA", "45"], ["480629", "Attempt saved. Granit Xhaka (Arsenal) left footed shot from outside the box is saved in the centre of the goal.", "45'+1'", "Arsenal", "0", "0", "0", "0", "1", "0", "saved", "Granit Xhaka", "Arsenal", "left", "outside the box", "the centre of the goal", "NA", "0", "NA", "NA", "0", "NA", "0", "0", "NA", "NA", "NA", "0", "NA", "NA", "NA", "0", "NA", "NA", "0", "NA", "0", "NA", "NA", "NA", "0", "NA", "NA", "0", "0", "NA", "NA", "NA", "0", "NA", "NA", "NA", "NA", "1", "40", "1", "NA", "NA", "46"], ["480629", "First Half ends, Arsenal 0, Manchester City 3.", "45'+3'", "Arsenal", "0", "1", "0", "0", "0", "0", "NA", "NA", "NA", "NA", "NA", "NA", "NA", "0", "NA", "NA", "0", "NA", "0", "0", "NA", "NA", "NA", "0", "NA", "NA", "NA", "0", "NA", "NA", "0", "NA", "0", "NA", "NA", "NA", "0", "NA", "NA", "0", "0", "NA", "NA", "NA", "0", "NA", "NA", "NA", "NA", "1", "41", "1", "NA", "NA", "48"], ["480629", "Second Half begins Arsenal 0, Manchester City 3.", "45'", "Arsenal", "0", "0", "0", "1", "0", "0", "NA", "NA", "NA", "NA", "NA", "NA", "NA", "0", "NA", "NA", "0", "NA", "0", "0", "NA", "NA", "NA", "0", "NA", "NA", "NA", "0", "NA", "NA", "0", "NA", "0", "NA", "NA", "NA", "0", "NA", "NA", "0", "0", "NA", "NA", "NA", "0", "NA", "NA", "NA", "NA", "2", "42", "0", "NA", "NA", "45"], ["480629", "Foul by Sead Kolasinac (Arsenal).", "46'", "Arsenal", "0", "0", "0", "0", "0", "0", "NA", "NA", "NA", "NA", "NA", "NA", "NA", "1", "Sead Kolasinac", "Arsenal", "0", "NA", "0", "0", "NA", "NA", "NA", "0", "NA", "NA", "NA", "0", "NA", "NA", "0", "NA", "0", "NA", "NA", "NA", "0", "NA", "NA", "0", "0", "NA", "NA", "NA", "0", "NA", "NA", "NA", "NA", "2", "43", "0", "NA", "NA", "46"], ["480629", "Kyle Walker (Manchester City) wins a free kick in the defensive half.", "46'", "Arsenal", "0", "0", "0", "0", "0", "0", "NA", "NA", "NA", "NA", "NA", "NA", "NA", "0", "NA", "NA", "0", "NA", "0", "0", "NA", "NA", "NA", "0", "NA", "NA", "NA", "0", "NA", "NA", "0", "NA", "1", "Kyle Walker", "Manchester City", "defensive half", "0", "NA", "NA", "0", "0", "NA", "NA", "NA", "0", "NA", "NA", "NA", "NA", "2", "44", "0", "NA", "NA", "46"], ["480629", "Bernardo Silva (Manchester City) wins a free kick in the defensive half.", "50'", "Arsenal", "0", "0", "0", "0", "0", "0", "NA", "NA", "NA", "NA", "NA", "NA", "NA", "0", "NA", "NA", "0", "NA", "0", "0", "NA", "NA", "NA", "0", "NA", "NA", "NA", "0", "NA", "NA", "0", "NA", "1", "Bernardo Silva", "Manchester City", "defensive half", "0", "NA", "NA", "0", "0", "NA", "NA", "NA", "0", "NA", "NA", "NA", "NA", "2", "45", "0", "NA", "NA", "50"], ["480629", "Foul by Mesut Özil (Arsenal).", "50'", "Arsenal", "0", "0", "0", "0", "0", "0", "NA", "NA", "NA", "NA", "NA", "NA", "NA", "1", "Mesut Özil", "Arsenal", "0", "NA", "0", "0", "NA", "NA", "NA", "0", "NA", "NA", "NA", "0", "NA", "NA", "0", "NA", "0", "NA", "NA", "NA", "0", "NA", "NA", "0", "0", "NA", "NA", "NA", "0", "NA", "NA", "NA", "NA", "2", "46", "0", "NA", "NA", "50"], ["480629", "Penalty Arsenal. Henrikh Mkhitaryan draws a foul in the penalty area.", "52'", "Arsenal", "0", "0", "0", "0", "0", "0", "NA", "NA", "NA", "NA", "NA", "NA", "NA", "0", "NA", "NA", "0", "NA", "0", "0", "NA", "NA", "NA", "0", "NA", "NA", "NA", "0", "NA", "NA", "0", "NA", "0", "NA", "NA", "NA", "0", "NA", "NA", "0", "0", "NA", "NA", "NA", "1", "Arsenal", "Henrikh Mkhitaryan", "NA", "NA", "2", "47", "0", "NA", "NA", "52"], ["480629", "Penalty conceded by Nicolás Otamendi (Manchester City) after a foul in the penalty area.", "52'", "Arsenal", "0", "0", "0", "0", "0", "0", "NA", "NA", "NA", "NA", "NA", "NA", "NA", "0", "NA", "NA", "0", "NA", "0", "0", "NA", "NA", "NA", "0", "NA", "NA", "NA", "0", "NA", "NA", "0", "NA", "0", "NA", "NA", "NA", "0", "NA", "NA", "0", "0", "NA", "NA", "NA", "1", "Manchester City", "NA", "Nicolás Otamendi", "Manchester City", "2", "48", "0", "NA", "NA", "52"], ["480629", "Penalty saved! Pierre-Emerick Aubameyang (Arsenal) fails to capitalise on this great opportunity,  right footed shot saved  in the bottom right corner.", "53'", "Arsenal", "0", "0", "0", "0", "1", "1", "saved", "NA", "Arsenal", "right", "NA", "NA", "NA", "0", "NA", "NA", "0", "NA", "0", "0", "NA", "NA", "NA", "0", "NA", "NA", "NA", "0", "NA", "NA", "0", "NA", "0", "NA", "NA", "NA", "0", "NA", "NA", "0", "0", "NA", "NA", "NA", "1", "NA", "NA", "NA", "NA", "2", "49", "0", "NA", "NA", "53"], ["480629", "David Silva (Manchester City) wins a free kick on the left wing.", "54'", "Arsenal", "0", "0", "0", "0", "0", "0", "NA", "NA", "NA", "NA", "NA", "NA", "NA", "0", "NA", "NA", "0", "NA", "0", "0", "NA", "NA", "NA", "0", "NA", "NA", "NA", "0", "NA", "NA", "0", "NA", "1", "David Silva", "Manchester City", "NA", "0", "NA", "NA", "0", "0", "NA", "NA", "NA", "0", "NA", "NA", "NA", "NA", "2", "50", "0", "NA", "NA", "54"], ["480629", "Foul by Aaron Ramsey (Arsenal).", "54'", "Arsenal", "0", "0", "0", "0", "0", "0", "NA", "NA", "NA", "NA", "NA", "NA", "NA", "1", "Aaron Ramsey", "Arsenal", "0", "NA", "0", "0", "NA", "NA", "NA", "0", "NA", "NA", "NA", "0", "NA", "NA", "0", "NA", "0", "NA", "NA", "NA", "0", "NA", "NA", "0", "0", "NA", "NA", "NA", "0", "NA", "NA", "NA", "NA", "2", "51", "0", "NA", "NA", "54"], ["480629", "Danny Welbeck (Arsenal) wins a free kick in the defensive half.", "58'", "Arsenal", "0", "0", "0", "0", "0", "0", "NA", "NA", "NA", "NA", "NA", "NA", "NA", "0", "NA", "NA", "0", "NA", "0", "0", "NA", "NA", "NA", "0", "NA", "NA", "NA", "0", "NA", "NA", "0", "NA", "1", "Danny Welbeck", "Arsenal", "defensive half", "0", "NA", "NA", "0", "0", "NA", "NA", "NA", "0", "NA", "NA", "NA", "NA", "2", "52", "0", "NA", "NA", "58"], ["480629", "Foul by Ilkay Gündogan (Manchester City).", "58'", "Arsenal", "0", "0", "0", "0", "0", "0", "NA", "NA", "NA", "NA", "NA", "NA", "NA", "1", "Ilkay Gündogan", "Manchester City", "0", "NA", "0", "0", "NA", "NA", "NA", "0", "NA", "NA", "NA", "0", "NA", "NA", "0", "NA", "0", "NA", "NA", "NA", "0", "NA", "NA", "0", "0", "NA", "NA", "NA", "0", "NA", "NA", "NA", "NA", "2", "53", "0", "NA", "NA", "58"], ["480629", "Corner,  Arsenal. Conceded by Ilkay Gündogan.", "58'", "Arsenal", "0", "0", "0", "0", "0", "0", "NA", "NA", "NA", "NA", "NA", "NA", "NA", "0", "NA", "NA", "0", "NA", "0", "0", "NA", "NA", "NA", "0", "NA", "NA", "NA", "0", "NA", "NA", "0", "NA", "0", "NA", "NA", "NA", "1", "Arsenal", "Ilkay Gündogan", "0", "0", "NA", "NA", "NA", "0", "NA", "NA", "NA", "NA", "2", "54", "0", "NA", "NA", "58"], ["480629", "Attempt missed. Pierre-Emerick Aubameyang (Arsenal) right footed shot from the centre of the box is close, but misses to the left. Assisted by Aaron Ramsey following a corner.", "58'", "Arsenal", "0", "0", "0", "0", "1", "0", "missed", "NA", "Arsenal", "right", "the centre of the box", "close, but left", "Aaron Ramsey", "0", "NA", "NA", "0", "NA", "1", "0", "NA", "NA", "NA", "0", "NA", "NA", "NA", "0", "NA", "NA", "0", "NA", "0", "NA", "NA", "NA", "0", "NA", "NA", "0", "0", "NA", "NA", "NA", "0", "NA", "NA", "NA", "NA", "2", "55", "0", "NA", "NA", "58"], ["480629", "Aaron Ramsey (Arsenal) wins a free kick in the attacking half.", "60'", "Arsenal", "0", "0", "0", "0", "0", "0", "NA", "NA", "NA", "NA", "NA", "NA", "NA", "0", "NA", "NA", "0", "NA", "0", "0", "NA", "NA", "NA", "0", "NA", "NA", "NA", "0", "NA", "NA", "0", "NA", "1", "Aaron Ramsey", "Arsenal", "attacking half", "0", "NA", "NA", "0", "0", "NA", "NA", "NA", "0", "NA", "NA", "NA", "NA", "2", "56", "0", "NA", "NA", "60"], ["480629", "Foul by Vincent Kompany (Manchester City).", "60'", "Arsenal", "0", "0", "0", "0", "0", "0", "NA", "NA", "NA", "NA", "NA", "NA", "NA", "1", "Vincent Kompany", "Manchester City", "0", "NA", "0", "0", "NA", "NA", "NA", "0", "NA", "NA", "NA", "0", "NA", "NA", "0", "NA", "0", "NA", "NA", "NA", "0", "NA", "NA", "0", "0", "NA", "NA", "NA", "0", "NA", "NA", "NA", "NA", "2", "57", "0", "NA", "NA", "60"], ["480629", "Bernardo Silva (Manchester City) wins a free kick in the defensive half.", "66'", "Arsenal", "0", "0", "0", "0", "0", "0", "NA", "NA", "NA", "NA", "NA", "NA", "NA", "0", "NA", "NA", "0", "NA", "0", "0", "NA", "NA", "NA", "0", "NA", "NA", "NA", "0", "NA", "NA", "0", "NA", "1", "Bernardo Silva", "Manchester City", "defensive half", "0", "NA", "NA", "0", "0", "NA", "NA", "NA", "0", "NA", "NA", "NA", "NA", "2", "58", "0", "NA", "NA", "66"], ["480629", "Foul by Aaron Ramsey (Arsenal).", "66'", "Arsenal", "0", "0", "0", "0", "0", "0", "NA", "NA", "NA", "NA", "NA", "NA", "NA", "1", "Aaron Ramsey", "Arsenal", "0", "NA", "0", "0", "NA", "NA", "NA", "0", "NA", "NA", "NA", "0", "NA", "NA", "0", "NA", "0", "NA", "NA", "NA", "0", "NA", "NA", "0", "0", "NA", "NA", "NA", "0", "NA", "NA", "NA", "NA", "2", "59", "0", "NA", "NA", "66"], ["480629", "Bernardo Silva (Manchester City) wins a free kick in the defensive half.", "70'", "Arsenal", "0", "0", "0", "0", "0", "0", "NA", "NA", "NA", "NA", "NA", "NA", "NA", "0", "NA", "NA", "0", "NA", "0", "0", "NA", "NA", "NA", "0", "NA", "NA", "NA", "0", "NA", "NA", "0", "NA", "1", "Bernardo Silva", "Manchester City", "defensive half", "0", "NA", "NA", "0", "0", "NA", "NA", "NA", "0", "NA", "NA", "NA", "NA", "2", "60", "0", "NA", "NA", "70"], ["480629", "Foul by Sead Kolasinac (Arsenal).", "70'", "Arsenal", "0", "0", "0", "0", "0", "0", "NA", "NA", "NA", "NA", "NA", "NA", "NA", "1", "Sead Kolasinac", "Arsenal", "0", "NA", "0", "0", "NA", "NA", "NA", "0", "NA", "NA", "NA", "0", "NA", "NA", "0", "NA", "0", "NA", "NA", "NA", "0", "NA", "NA", "0", "0", "NA", "NA", "NA", "0", "NA", "NA", "NA", "NA", "2", "61", "0", "NA", "NA", "70"], ["480629", "Substitution, Manchester City. Oleksandr Zinchenko replaces Kyle Walker because of an injury.", "72'", "Arsenal", "0", "0", "0", "0", "0", "0", "NA", "NA", "NA", "NA", "NA", "NA", "NA", "0", "NA", "NA", "0", "NA", "0", "0", "NA", "NA", "NA", "0", "NA", "NA", "NA", "0", "NA", "NA", "0", "NA", "0", "NA", "NA", "NA", "0", "NA", "NA", "1", "1", "Manchester City", "Oleksandr Zinchenko", "Kyle Walker", "0", "NA", "NA", "NA", "NA", "2", "62", "0", "NA", "NA", "72"], ["480629", "Foul by Laurent Koscielny (Arsenal).", "73'", "Arsenal", "0", "0", "0", "0", "0", "0", "NA", "NA", "NA", "NA", "NA", "NA", "NA", "1", "Laurent Koscielny", "Arsenal", "0", "NA", "0", "0", "NA", "NA", "NA", "0", "NA", "NA", "NA", "0", "NA", "NA", "0", "NA", "0", "NA", "NA", "NA", "0", "NA", "NA", "0", "0", "NA", "NA", "NA", "0", "NA", "NA", "NA", "NA", "2", "63", "0", "NA", "NA", "73"], ["480629", "Kevin De Bruyne (Manchester City) wins a free kick in the defensive half.", "73'", "Arsenal", "0", "0", "0", "0", "0", "0", "NA", "NA", "NA", "NA", "NA", "NA", "NA", "0", "NA", "NA", "0", "NA", "0", "0", "NA", "NA", "NA", "0", "NA", "NA", "NA", "0", "NA", "NA", "0", "NA", "1", "Kevin De Bruyne", "Manchester City", "defensive half", "0", "NA", "NA", "0", "0", "NA", "NA", "NA", "0", "NA", "NA", "NA", "NA", "2", "64", "0", "NA", "NA", "73"], ["480629", "Foul by Henrikh Mkhitaryan (Arsenal).", "75'", "Arsenal", "0", "0", "0", "0", "0", "0", "NA", "NA", "NA", "NA", "NA", "NA", "NA", "1", "Henrikh Mkhitaryan", "Arsenal", "0", "NA", "0", "0", "NA", "NA", "NA", "0", "NA", "NA", "NA", "0", "NA", "NA", "0", "NA", "0", "NA", "NA", "NA", "0", "NA", "NA", "0", "0", "NA", "NA", "NA", "0", "NA", "NA", "NA", "NA", "2", "65", "0", "NA", "NA", "75"], ["480629", "Oleksandr Zinchenko (Manchester City) wins a free kick in the defensive half.", "75'", "Arsenal", "0", "0", "0", "0", "0", "0", "NA", "NA", "NA", "NA", "NA", "NA", "NA", "0", "NA", "NA", "0", "NA", "0", "0", "NA", "NA", "NA", "0", "NA", "NA", "NA", "0", "NA", "NA", "0", "NA", "1", "Oleksandr Zinchenko", "Manchester City", "defensive half", "0", "NA", "NA", "0", "0", "NA", "NA", "NA", "0", "NA", "NA", "NA", "NA", "2", "66", "0", "NA", "NA", "75"], ["480629", "Attempt saved. Sergio Agüero (Manchester City) right footed shot from the right side of the box is saved in the centre of the goal. Assisted by Ilkay Gündogan.", "78'", "Arsenal", "0", "0", "0", "0", "1", "0", "saved", "Sergio Agüero", "Manchester City", "right", "the right side of the box", "the centre of the goal", "Ilkay Gündogan", "0", "NA", "NA", "0", "NA", "0", "0", "NA", "NA", "NA", "0", "NA", "NA", "NA", "0", "NA", "NA", "0", "NA", "0", "NA", "NA", "NA", "0", "NA", "NA", "0", "0", "NA", "NA", "NA", "0", "NA", "NA", "NA", "NA", "2", "67", "0", "NA", "NA", "78"], ["480629", "Substitution, Manchester City. Yaya Touré replaces Sergio Agüero.", "82'", "Arsenal", "0", "0", "0", "0", "0", "0", "NA", "NA", "NA", "NA", "NA", "NA", "NA", "0", "NA", "NA", "0", "NA", "0", "0", "NA", "NA", "NA", "0", "NA", "NA", "NA", "0", "NA", "NA", "0", "NA", "0", "NA", "NA", "NA", "0", "NA", "NA", "1", "0", "Manchester City", "Yaya Touré", "Sergio Agüero", "0", "NA", "NA", "NA", "NA", "2", "68", "0", "NA", "NA", "82"], ["480629", "Foul by Oleksandr Zinchenko (Manchester City).", "83'", "Arsenal", "0", "0", "0", "0", "0", "0", "NA", "NA", "NA", "NA", "NA", "NA", "NA", "1", "Oleksandr Zinchenko", "Manchester City", "0", "NA", "0", "0", "NA", "NA", "NA", "0", "NA", "NA", "NA", "0", "NA", "NA", "0", "NA", "0", "NA", "NA", "NA", "0", "NA", "NA", "0", "0", "NA", "NA", "NA", "0", "NA", "NA", "NA", "NA", "2", "69", "0", "NA", "NA", "83"], ["480629", "Mesut Özil (Arsenal) wins a free kick on the right wing.", "83'", "Arsenal", "0", "0", "0", "0", "0", "0", "NA", "NA", "NA", "NA", "NA", "NA", "NA", "0", "NA", "NA", "0", "NA", "0", "0", "NA", "NA", "NA", "0", "NA", "NA", "NA", "0", "NA", "NA", "0", "NA", "1", "Mesut Özil", "Arsenal", "NA", "0", "NA", "NA", "0", "0", "NA", "NA", "NA", "0", "NA", "NA", "NA", "NA", "2", "70", "0", "NA", "NA", "83"], ["480629", "Substitution, Manchester City. Gabriel Jesus replaces David Silva.", "87'", "Arsenal", "0", "0", "0", "0", "0", "0", "NA", "NA", "NA", "NA", "NA", "NA", "NA", "0", "NA", "NA", "0", "NA", "0", "0", "NA", "NA", "NA", "0", "NA", "NA", "NA", "0", "NA", "NA", "0", "NA", "0", "NA", "NA", "NA", "0", "NA", "NA", "1", "0", "Manchester City", "Gabriel Jesus", "David Silva", "0", "NA", "NA", "NA", "NA", "2", "71", "0", "NA", "NA", "87"], ["480629", "Foul by Gabriel Jesus (Manchester City).", "88'", "Arsenal", "0", "0", "0", "0", "0", "0", "NA", "NA", "NA", "NA", "NA", "NA", "NA", "1", "Gabriel Jesus", "Manchester City", "0", "NA", "0", "0", "NA", "NA", "NA", "0", "NA", "NA", "NA", "0", "NA", "NA", "0", "NA", "0", "NA", "NA", "NA", "0", "NA", "NA", "0", "0", "NA", "NA", "NA", "0", "NA", "NA", "NA", "NA", "2", "72", "0", "NA", "NA", "88"], ["480629", "Granit Xhaka (Arsenal) wins a free kick in the defensive half.", "88'", "Arsenal", "0", "0", "0", "0", "0", "0", "NA", "NA", "NA", "NA", "NA", "NA", "NA", "0", "NA", "NA", "0", "NA", "0", "0", "NA", "NA", "NA", "0", "NA", "NA", "NA", "0", "NA", "NA", "0", "NA", "1", "Granit Xhaka", "Arsenal", "defensive half", "0", "NA", "NA", "0", "0", "NA", "NA", "NA", "0", "NA", "NA", "NA", "NA", "2", "73", "0", "NA", "NA", "88"], ["480629", "Attempt blocked. Gabriel Jesus (Manchester City) right footed shot from the left side of the box is blocked.", "89'", "Arsenal", "0", "0", "0", "0", "1", "0", "blocked", "Gabriel Jesus", "Manchester City", "right", "the left side of the box", "NA", "NA", "0", "NA", "NA", "0", "NA", "0", "0", "NA", "NA", "NA", "0", "NA", "NA", "NA", "0", "NA", "NA", "0", "NA", "0", "NA", "NA", "NA", "0", "NA", "NA", "0", "0", "NA", "NA", "NA", "0", "NA", "NA", "NA", "NA", "2", "74", "0", "NA", "NA", "89"], ["480629", "Attempt blocked. Kevin De Bruyne (Manchester City) right footed shot from outside the box is blocked.", "89'", "Arsenal", "0", "0", "0", "0", "1", "0", "blocked", "Kevin De Bruyne", "Manchester City", "right", "outside the box", "NA", "NA", "0", "NA", "NA", "0", "NA", "0", "0", "NA", "NA", "NA", "0", "NA", "NA", "NA", "0", "NA", "NA", "0", "NA", "0", "NA", "NA", "NA", "0", "NA", "NA", "0", "0", "NA", "NA", "NA", "0", "NA", "NA", "NA", "NA", "2", "75", "0", "NA", "NA", "89"], ["480629", "Aaron Ramsey (Arsenal) wins a free kick in the defensive half.", "89'", "Arsenal", "0", "0", "0", "0", "0", "0", "NA", "NA", "NA", "NA", "NA", "NA", "NA", "0", "NA", "NA", "0", "NA", "0", "0", "NA", "NA", "NA", "0", "NA", "NA", "NA", "0", "NA", "NA", "0", "NA", "1", "Aaron Ramsey", "Arsenal", "defensive half", "0", "NA", "NA", "0", "0", "NA", "NA", "NA", "0", "NA", "NA", "NA", "NA", "2", "76", "0", "NA", "NA", "89"], ["480629", "Foul by Oleksandr Zinchenko (Manchester City).", "89'", "Arsenal", "0", "0", "0", "0", "0", "0", "NA", "NA", "NA", "NA", "NA", "NA", "NA", "1", "Oleksandr Zinchenko", "Manchester City", "0", "NA", "0", "0", "NA", "NA", "NA", "0", "NA", "NA", "NA", "0", "NA", "NA", "0", "NA", "0", "NA", "NA", "NA", "0", "NA", "NA", "0", "0", "NA", "NA", "NA", "0", "NA", "NA", "NA", "NA", "2", "77", "0", "NA", "NA", "89"], ["480629", "Corner,  Arsenal. Conceded by Bernardo Silva.", "90'+1'", "Arsenal", "0", "0", "0", "0", "0", "0", "NA", "NA", "NA", "NA", "NA", "NA", "NA", "0", "NA", "NA", "0", "NA", "0", "0", "NA", "NA", "NA", "0", "NA", "NA", "NA", "0", "NA", "NA", "0", "NA", "0", "NA", "NA", "NA", "1", "Arsenal", "Bernardo Silva", "0", "0", "NA", "NA", "NA", "0", "NA", "NA", "NA", "NA", "2", "78", "1", "NA", "NA", "91"], ["480629", "Foul by Leroy Sané (Manchester City).", "90'+2'", "Arsenal", "0", "0", "0", "0", "0", "0", "NA", "NA", "NA", "NA", "NA", "NA", "NA", "1", "Leroy Sané", "Manchester City", "0", "NA", "0", "0", "NA", "NA", "NA", "0", "NA", "NA", "NA", "0", "NA", "NA", "0", "NA", "0", "NA", "NA", "NA", "0", "NA", "NA", "0", "0", "NA", "NA", "NA", "0", "NA", "NA", "NA", "NA", "2", "79", "1", "NA", "NA", "92"], ["480629", "Henrikh Mkhitaryan (Arsenal) wins a free kick on the right wing.", "90'+2'", "Arsenal", "0", "0", "0", "0", "0", "0", "NA", "NA", "NA", "NA", "NA", "NA", "NA", "0", "NA", "NA", "0", "NA", "0", "0", "NA", "NA", "NA", "0", "NA", "NA", "NA", "0", "NA", "NA", "0", "NA", "1", "Henrikh Mkhitaryan", "Arsenal", "NA", "0", "NA", "NA", "0", "0", "NA", "NA", "NA", "0", "NA", "NA", "NA", "NA", "2", "80", "1", "NA", "NA", "92"], ["480629", "Second Half ends, Arsenal 0, Manchester City 3.", "90'+3'", "Arsenal", "0", "1", "0", "0", "0", "0", "NA", "NA", "NA", "NA", "NA", "NA", "NA", "0", "NA", "NA", "0", "NA", "0", "0", "NA", "NA", "NA", "0", "NA", "NA", "NA", "0", "NA", "NA", "0", "NA", "0", "NA", "NA", "NA", "0", "NA", "NA", "0", "0", "NA", "NA", "NA", "0", "NA", "NA", "NA", "NA", "2", "81", "1", "NA", "NA", "93"], ["480629", "Match ends, Arsenal 0, Manchester City 3.", "90'+3'", "Arsenal", "0", "0", "1", "0", "0", "0", "NA", "NA", "NA", "NA", "NA", "NA", "NA", "0", "NA", "NA", "0", "NA", "0", "0", "NA", "NA", "NA", "0", "NA", "NA", "NA", "0", "NA", "NA", "0", "NA", "0", "NA", "NA", "NA", "0", "NA", "NA", "0", "0", "NA", "NA", "NA", "0", "NA", "NA", "NA", "NA", "2", "82", "1", "NA", "NA", "93"]], "Lineup": {"Home Player 9": "Aaron Ramsey", "Home Player 8": "Mesut Ozil", "Home Player 5": "Laurent Koscielny", "Home Player 4": "Sead Kolasinac", "Home Player 7": "Shkodran Mustafi", "Home Player 6": "Henrikh Mkhitaryan", "Home Player 1": "Pierre-Emerick Aubameyang", "Home Player 3": "Petr Cech", "Home Player 2": "Hector Bellerin", "Away Player 10": "David Silva", "Away Player 11": "Kyle Walker", "Away Player 8": "Leroy Sane", "Away Player 9": "Bernardo Silva", "Away Player 1": "Sergio Aguero", "Away Player 2": "Danilo", "Away Player 3": "Kevin De Bruyne", "Away Player 4": "Ederson", "Away Player 5": "Ilkay Gundogan", "Away Player 6": "Vincent Kompany", "Away Player 7": "Nicolas Otamendi", "Game ID": "g_1_v1SiXcF2", "Home Player 11": "Granit Xhaka", "Home Player 10": "Danny Welbeck"}}