{"Stats": {"Full Time Result": "H", "Away Team Corners": 5, "Referee": "N Swarbrick", "Home Team Fouls Committed": 8, "Home Team Corners": 2, "Away Team Shots": 9, "Away Team Red Cards": 0, "Home Team Red Cards": 0, "Half Time Away Team Goals": 1, "Full Time Home Team Goals": 2, "Away Team Yellow Cards": 0, "Away Team Shots on Target": 6, "Half Time Home Team Goals": 0, "Half Time Result": "A", "Home Team Yellow Cards": 1, "Home Team Shots": 11, "Div": "E0", "Away Team Fouls Committed": 10, "Home Team Shots on Target": 2, "Full Time Away Team Goals": 1}, "Description": "Danny Welbeck (Arsenal) wins a free kick on the left wing. at minute 4. Foul by Adrian Mariappa (Watford). at minute 4. Delay in match Richarlison (Watford) because of an injury. at minute 8. Delay over. They are ready to continue. at minute 10. Foul by Andre Gray (Watford). at minute 14. Granit Xhaka (Arsenal) wins a free kick in the defensive half. at minute 14. Foul by Nacho Monreal (Arsenal). at minute 17. Roberto Pereyra (Watford) wins a free kick in the defensive half. at minute 17. Attempt missed. Roberto Pereyra (Watford) header from very close range misses to the right. Assisted by Abdoulaye Doucouré with a cross. at minute 19. Foul by Nacho Monreal (Arsenal). at minute 20. Roberto Pereyra (Watford) wins a free kick in the defensive half. at minute 20. Foul by Héctor Bellerín (Arsenal). at minute 22. José Holebas (Watford) wins a free kick on the left wing. at minute 22. Foul by Granit Xhaka (Arsenal). at minute 23. Tom Cleverley (Watford) wins a free kick in the defensive half. at minute 23. Attempt missed. Mohamed El Neny (Arsenal) right footed shot from outside the box is just a bit too high. Assisted by Héctor Bellerín. at minute 29. Adrian Mariappa (Watford) wins a free kick in the defensive half. at minute 32. Foul by Danny Welbeck (Arsenal). at minute 32. Attempt missed. Richarlison (Watford) header from the centre of the box misses to the left. Assisted by Tom Cleverley. at minute 38. Corner,  Arsenal. Conceded by José Holebas. at minute 39. Goal!  Watford 0, Arsenal 1. Per Mertesacker (Arsenal) header from the centre of the box to the high centre of the goal. Assisted by Granit Xhaka with a cross following a corner. at minute 39. Attempt saved. Granit Xhaka (Arsenal) left footed shot from outside the box is saved in the bottom left corner. Assisted by Danny Welbeck. at minute 43. Attempt missed. Héctor Bellerín (Arsenal) left footed shot from the centre of the box is close, but misses to the right. Assisted by Danny Welbeck. at minute 43. Attempt saved. Granit Xhaka (Arsenal) left footed shot from outside the box is saved in the bottom left corner. Assisted by Danny Welbeck. at minute 44. Foul by Richarlison (Watford). at minute 44. Laurent Koscielny (Arsenal) wins a free kick in the defensive half. at minute 44. Foul by Héctor Bellerín (Arsenal). at minute 45. Richarlison (Watford) wins a free kick in the defensive half. at minute 45. Alexandre Lacazette (Arsenal) wins a free kick in the attacking half. at minute 47. Foul by Adrian Mariappa (Watford). at minute 47. Delay in match Alexandre Lacazette (Arsenal) because of an injury. at minute 47. Delay over. They are ready to continue. at minute 48. First Half ends, Watford 0, Arsenal 1. at minute 49. Second Half begins Watford 0, Arsenal 1. at minute 45. Offside, Watford. Christian Kabasele tries a through ball, but Andre Gray is caught offside. at minute 48. Corner,  Arsenal. Conceded by Kiko Femenía. at minute 50. Attempt missed. Richarlison (Watford) right footed shot from outside the box is close, but misses to the right. Assisted by Abdoulaye Doucouré. at minute 52. Corner,  Watford. Conceded by Petr Cech. at minute 59. Delay in match Danny Welbeck (Arsenal) because of an injury. at minute 59. Substitution, Arsenal. Mesut Özil replaces Danny Welbeck because of an injury. at minute 61. Delay over. They are ready to continue. at minute 61. Foul by José Holebas (Watford). at minute 62. Sead Kolasinac (Arsenal) wins a free kick in the defensive half. at minute 62. Substitution, Watford. Troy Deeney replaces Andre Gray. at minute 63. Substitution, Watford. André Carrillo replaces Adrian Mariappa. at minute 63. Attempt saved. Alex Iwobi (Arsenal) right footed shot from the left side of the box is saved in the bottom right corner. Assisted by Mesut Özil with a through ball. at minute 63. Corner,  Arsenal. Conceded by Heurelho Gomes. at minute 63. Christian Kabasele (Watford) is shown the yellow card for a bad foul. at minute 64. Corner,  Arsenal. Conceded by Christian Kabasele. at minute 64. Hand ball by Mesut Özil (Arsenal). at minute 66. Corner,  Watford. Conceded by Per Mertesacker. at minute 67. Substitution, Arsenal. Olivier Giroud replaces Alexandre Lacazette. at minute 68. Attempt saved. Mesut Özil (Arsenal) left footed shot from the centre of the box is saved in the centre of the goal. Assisted by Alex Iwobi with a through ball. at minute 70. Penalty Watford. Richarlison draws a foul in the penalty area. at minute 71. Penalty conceded by Héctor Bellerín (Arsenal) after a foul in the penalty area. at minute 71. Goal!  Watford 1, Arsenal 1. Troy Deeney (Watford) converts the penalty with a right footed shot to the bottom right corner. at minute 71. Attempt missed. Richarlison (Watford) right footed shot from the left side of the box is close, but misses to the left. Assisted by Troy Deeney with a headed pass. at minute 75. Abdoulaye Doucouré (Watford) wins a free kick in the defensive half. at minute 75. Foul by Mesut Özil (Arsenal). at minute 75. Foul by Richarlison (Watford). at minute 76. Laurent Koscielny (Arsenal) wins a free kick in the defensive half. at minute 76. Foul by José Holebas (Watford). at minute 77. Mesut Özil (Arsenal) wins a free kick in the defensive half. at minute 77. Substitution, Watford. Etienne Capoue replaces Roberto Pereyra. at minute 81. Attempt blocked. Etienne Capoue (Watford) right footed shot from outside the box is blocked. Assisted by Troy Deeney. at minute 83. Foul by Richarlison (Watford). at minute 84. Per Mertesacker (Arsenal) wins a free kick in the defensive half. at minute 84. Substitution, Arsenal. Rob Holding replaces Laurent Koscielny because of an injury. at minute 85. Foul by Olivier Giroud (Arsenal). at minute 85. Miguel Britos (Watford) wins a free kick in the defensive half. at minute 85. Attempt missed. André Carrillo (Watford) right footed shot from outside the box is too high. Assisted by Richarlison. at minute 87. Corner,  Arsenal. Conceded by Christian Kabasele. at minute 89. Attempt missed. Nacho Monreal (Arsenal) left footed shot from outside the box is high and wide to the left following a corner. at minute 89. Attempt blocked. Troy Deeney (Watford) right footed shot from the left side of the box is blocked. Assisted by André Carrillo. at minute 91. Attempt missed. José Holebas (Watford) left footed shot from outside the box is close, but misses to the right. Assisted by Abdoulaye Doucouré. at minute 92. Attempt blocked. Etienne Capoue (Watford) right footed shot from the centre of the box is blocked. at minute 92. Goal!  Watford 2, Arsenal 1. Tom Cleverley (Watford) right footed shot from the centre of the box to the high centre of the goal. at minute 92. Attempt saved. Olivier Giroud (Arsenal) header from the centre of the box is saved in the centre of the goal. Assisted by Mesut Özil. at minute 94. Second Half ends, Watford 2, Arsenal 1. at minute 95. Match ends, Watford 2, Arsenal 1. at minute 95. ", "Home Team": "Watford", "Away Team": "Arsenal", "Date": "14-10-2017", "Commentary": [["480826", "First Half begins.", "-", "Watford", "0", "0", "0", "1", "0", "0", "NA", "NA", "NA", "NA", "NA", "NA", "NA", "0", "NA", "NA", "0", "NA", "0", "0", "NA", "NA", "NA", "0", "NA", "NA", "NA", "0", "NA", "NA", "0", "NA", "0", "NA", "NA", "NA", "0", "NA", "NA", "0", "0", "NA", "NA", "NA", "0", "NA", "NA", "NA", "NA", "1", "1", "0", "NA", "NA", "NA"], ["480826", "Lineups are announced and players are warming up.", "-", "Watford", "0", "0", "0", "0", "0", "0", "NA", "NA", "NA", "NA", "NA", "NA", "NA", "0", "NA", "NA", "0", "NA", "0", "0", "NA", "NA", "NA", "0", "NA", "NA", "NA", "0", "NA", "NA", "0", "NA", "0", "NA", "NA", "NA", "0", "NA", "NA", "0", "0", "NA", "NA", "NA", "0", "NA", "NA", "NA", "NA", "1", "2", "0", "NA", "NA", "NA"], ["480826", "Danny Welbeck (Arsenal) wins a free kick on the left wing.", "4'", "Watford", "0", "0", "0", "0", "0", "0", "NA", "NA", "NA", "NA", "NA", "NA", "NA", "0", "NA", "NA", "0", "NA", "0", "0", "NA", "NA", "NA", "0", "NA", "NA", "NA", "0", "NA", "NA", "0", "NA", "1", "Danny Welbeck", "Arsenal", "NA", "0", "NA", "NA", "0", "0", "NA", "NA", "NA", "0", "NA", "NA", "NA", "NA", "1", "3", "0", "NA", "NA", "4"], ["480826", "Foul by Adrian Mariappa (Watford).", "4'", "Watford", "0", "0", "0", "0", "0", "0", "NA", "NA", "NA", "NA", "NA", "NA", "NA", "1", "Adrian Mariappa", "Watford", "0", "NA", "0", "0", "NA", "NA", "NA", "0", "NA", "NA", "NA", "0", "NA", "NA", "0", "NA", "0", "NA", "NA", "NA", "0", "NA", "NA", "0", "0", "NA", "NA", "NA", "0", "NA", "NA", "NA", "NA", "1", "4", "0", "NA", "NA", "4"], ["480826", "Delay in match Richarlison (Watford) because of an injury.", "8'", "Watford", "0", "0", "0", "0", "0", "0", "NA", "NA", "NA", "NA", "NA", "NA", "NA", "0", "NA", "NA", "0", "NA", "0", "0", "NA", "NA", "NA", "0", "NA", "NA", "NA", "0", "NA", "NA", "1", "Watford", "0", "NA", "NA", "NA", "0", "NA", "NA", "0", "0", "NA", "NA", "NA", "0", "NA", "NA", "NA", "NA", "1", "5", "0", "NA", "NA", "8"], ["480826", "Delay over. They are ready to continue.", "10'", "Watford", "0", "0", "0", "0", "0", "0", "NA", "NA", "NA", "NA", "NA", "NA", "NA", "0", "NA", "NA", "0", "NA", "0", "0", "NA", "NA", "NA", "0", "NA", "NA", "NA", "0", "NA", "NA", "0", "NA", "0", "NA", "NA", "NA", "0", "NA", "NA", "0", "0", "NA", "NA", "NA", "0", "NA", "NA", "NA", "NA", "1", "6", "0", "NA", "NA", "10"], ["480826", "Foul by Andre Gray (Watford).", "14'", "Watford", "0", "0", "0", "0", "0", "0", "NA", "NA", "NA", "NA", "NA", "NA", "NA", "1", "Andre Gray", "Watford", "0", "NA", "0", "0", "NA", "NA", "NA", "0", "NA", "NA", "NA", "0", "NA", "NA", "0", "NA", "0", "NA", "NA", "NA", "0", "NA", "NA", "0", "0", "NA", "NA", "NA", "0", "NA", "NA", "NA", "NA", "1", "7", "0", "NA", "NA", "14"], ["480826", "Granit Xhaka (Arsenal) wins a free kick in the defensive half.", "14'", "Watford", "0", "0", "0", "0", "0", "0", "NA", "NA", "NA", "NA", "NA", "NA", "NA", "0", "NA", "NA", "0", "NA", "0", "0", "NA", "NA", "NA", "0", "NA", "NA", "NA", "0", "NA", "NA", "0", "NA", "1", "Granit Xhaka", "Arsenal", "defensive half", "0", "NA", "NA", "0", "0", "NA", "NA", "NA", "0", "NA", "NA", "NA", "NA", "1", "8", "0", "NA", "NA", "14"], ["480826", "Foul by Nacho Monreal (Arsenal).", "17'", "Watford", "0", "0", "0", "0", "0", "0", "NA", "NA", "NA", "NA", "NA", "NA", "NA", "1", "Nacho Monreal", "Arsenal", "0", "NA", "0", "0", "NA", "NA", "NA", "0", "NA", "NA", "NA", "0", "NA", "NA", "0", "NA", "0", "NA", "NA", "NA", "0", "NA", "NA", "0", "0", "NA", "NA", "NA", "0", "NA", "NA", "NA", "NA", "1", "9", "0", "NA", "NA", "17"], ["480826", "Roberto Pereyra (Watford) wins a free kick in the defensive half.", "17'", "Watford", "0", "0", "0", "0", "0", "0", "NA", "NA", "NA", "NA", "NA", "NA", "NA", "0", "NA", "NA", "0", "NA", "0", "0", "NA", "NA", "NA", "0", "NA", "NA", "NA", "0", "NA", "NA", "0", "NA", "1", "Roberto Pereyra", "Watford", "defensive half", "0", "NA", "NA", "0", "0", "NA", "NA", "NA", "0", "NA", "NA", "NA", "NA", "1", "10", "0", "NA", "NA", "17"], ["480826", "Attempt missed. Roberto Pereyra (Watford) header from very close range misses to the right. Assisted by Abdoulaye Doucouré with a cross.", "19'", "Watford", "0", "0", "0", "0", "1", "0", "missed", "Roberto Pereyra", "Watford", "header", "very close range", "right", "Abdoulaye Doucouré", "0", "NA", "NA", "0", "cross", "0", "0", "NA", "NA", "NA", "0", "NA", "NA", "NA", "0", "NA", "NA", "0", "NA", "0", "NA", "NA", "NA", "0", "NA", "NA", "0", "0", "NA", "NA", "NA", "0", "NA", "NA", "NA", "NA", "1", "11", "0", "NA", "NA", "19"], ["480826", "Foul by Nacho Monreal (Arsenal).", "20'", "Watford", "0", "0", "0", "0", "0", "0", "NA", "NA", "NA", "NA", "NA", "NA", "NA", "1", "Nacho Monreal", "Arsenal", "0", "NA", "0", "0", "NA", "NA", "NA", "0", "NA", "NA", "NA", "0", "NA", "NA", "0", "NA", "0", "NA", "NA", "NA", "0", "NA", "NA", "0", "0", "NA", "NA", "NA", "0", "NA", "NA", "NA", "NA", "1", "12", "0", "NA", "NA", "20"], ["480826", "Roberto Pereyra (Watford) wins a free kick in the defensive half.", "20'", "Watford", "0", "0", "0", "0", "0", "0", "NA", "NA", "NA", "NA", "NA", "NA", "NA", "0", "NA", "NA", "0", "NA", "0", "0", "NA", "NA", "NA", "0", "NA", "NA", "NA", "0", "NA", "NA", "0", "NA", "1", "Roberto Pereyra", "Watford", "defensive half", "0", "NA", "NA", "0", "0", "NA", "NA", "NA", "0", "NA", "NA", "NA", "NA", "1", "13", "0", "NA", "NA", "20"], ["480826", "Foul by Héctor Bellerín (Arsenal).", "22'", "Watford", "0", "0", "0", "0", "0", "0", "NA", "NA", "NA", "NA", "NA", "NA", "NA", "1", "Héctor Bellerín", "Arsenal", "0", "NA", "0", "0", "NA", "NA", "NA", "0", "NA", "NA", "NA", "0", "NA", "NA", "0", "NA", "0", "NA", "NA", "NA", "0", "NA", "NA", "0", "0", "NA", "NA", "NA", "0", "NA", "NA", "NA", "NA", "1", "14", "0", "NA", "NA", "22"], ["480826", "José Holebas (Watford) wins a free kick on the left wing.", "22'", "Watford", "0", "0", "0", "0", "0", "0", "NA", "NA", "NA", "NA", "NA", "NA", "NA", "0", "NA", "NA", "0", "NA", "0", "0", "NA", "NA", "NA", "0", "NA", "NA", "NA", "0", "NA", "NA", "0", "NA", "1", "José Holebas", "Watford", "NA", "0", "NA", "NA", "0", "0", "NA", "NA", "NA", "0", "NA", "NA", "NA", "NA", "1", "15", "0", "NA", "NA", "22"], ["480826", "Foul by Granit Xhaka (Arsenal).", "23'", "Watford", "0", "0", "0", "0", "0", "0", "NA", "NA", "NA", "NA", "NA", "NA", "NA", "1", "Granit Xhaka", "Arsenal", "0", "NA", "0", "0", "NA", "NA", "NA", "0", "NA", "NA", "NA", "0", "NA", "NA", "0", "NA", "0", "NA", "NA", "NA", "0", "NA", "NA", "0", "0", "NA", "NA", "NA", "0", "NA", "NA", "NA", "NA", "1", "16", "0", "NA", "NA", "23"], ["480826", "Tom Cleverley (Watford) wins a free kick in the defensive half.", "23'", "Watford", "0", "0", "0", "0", "0", "0", "NA", "NA", "NA", "NA", "NA", "NA", "NA", "0", "NA", "NA", "0", "NA", "0", "0", "NA", "NA", "NA", "0", "NA", "NA", "NA", "0", "NA", "NA", "0", "NA", "1", "Tom Cleverley", "Watford", "defensive half", "0", "NA", "NA", "0", "0", "NA", "NA", "NA", "0", "NA", "NA", "NA", "NA", "1", "17", "0", "NA", "NA", "23"], ["480826", "Attempt missed. Mohamed El Neny (Arsenal) right footed shot from outside the box is just a bit too high. Assisted by Héctor Bellerín.", "29'", "Watford", "0", "0", "0", "0", "1", "0", "missed", "Mohamed El Neny", "Arsenal", "right", "outside the box", "just a bit too high", "Héctor Bellerín", "0", "NA", "NA", "0", "NA", "0", "0", "NA", "NA", "NA", "0", "NA", "NA", "NA", "0", "NA", "NA", "0", "NA", "0", "NA", "NA", "NA", "0", "NA", "NA", "0", "0", "NA", "NA", "NA", "0", "NA", "NA", "NA", "NA", "1", "18", "0", "NA", "NA", "29"], ["480826", "Adrian Mariappa (Watford) wins a free kick in the defensive half.", "32'", "Watford", "0", "0", "0", "0", "0", "0", "NA", "NA", "NA", "NA", "NA", "NA", "NA", "0", "NA", "NA", "0", "NA", "0", "0", "NA", "NA", "NA", "0", "NA", "NA", "NA", "0", "NA", "NA", "0", "NA", "1", "Adrian Mariappa", "Watford", "defensive half", "0", "NA", "NA", "0", "0", "NA", "NA", "NA", "0", "NA", "NA", "NA", "NA", "1", "19", "0", "NA", "NA", "32"], ["480826", "Foul by Danny Welbeck (Arsenal).", "32'", "Watford", "0", "0", "0", "0", "0", "0", "NA", "NA", "NA", "NA", "NA", "NA", "NA", "1", "Danny Welbeck", "Arsenal", "0", "NA", "0", "0", "NA", "NA", "NA", "0", "NA", "NA", "NA", "0", "NA", "NA", "0", "NA", "0", "NA", "NA", "NA", "0", "NA", "NA", "0", "0", "NA", "NA", "NA", "0", "NA", "NA", "NA", "NA", "1", "20", "0", "NA", "NA", "32"], ["480826", "Attempt missed. Richarlison (Watford) header from the centre of the box misses to the left. Assisted by Tom Cleverley.", "38'", "Watford", "0", "0", "0", "0", "1", "0", "missed", "Richarlison", "Watford", "header", "the centre of the box", "left", "Tom Cleverley", "0", "NA", "NA", "0", "NA", "0", "0", "NA", "NA", "NA", "0", "NA", "NA", "NA", "0", "NA", "NA", "0", "NA", "0", "NA", "NA", "NA", "0", "NA", "NA", "0", "0", "NA", "NA", "NA", "0", "NA", "NA", "NA", "NA", "1", "21", "0", "NA", "NA", "38"], ["480826", "Corner,  Arsenal. Conceded by José Holebas.", "39'", "Watford", "0", "0", "0", "0", "0", "0", "NA", "NA", "NA", "NA", "NA", "NA", "NA", "0", "NA", "NA", "0", "NA", "0", "0", "NA", "NA", "NA", "0", "NA", "NA", "NA", "0", "NA", "NA", "0", "NA", "0", "NA", "NA", "NA", "1", "Arsenal", "José Holebas", "0", "0", "NA", "NA", "NA", "0", "NA", "NA", "NA", "NA", "1", "22", "0", "NA", "NA", "39"], ["480826", "Goal!  Watford 0, Arsenal 1. Per Mertesacker (Arsenal) header from the centre of the box to the high centre of the goal. Assisted by Granit Xhaka with a cross following a corner.", "39'", "Watford", "0", "0", "0", "0", "1", "0", "goal", "Per Mertesacker", "Arsenal", "header", "the centre of the box", "high centre of the goal", "Granit Xhaka", "0", "NA", "NA", "0", "cross", "1", "0", "NA", "NA", "NA", "0", "NA", "NA", "NA", "0", "NA", "NA", "0", "NA", "0", "NA", "NA", "NA", "0", "NA", "NA", "0", "0", "NA", "NA", "NA", "0", "NA", "NA", "NA", "NA", "1", "23", "0", "NA", "NA", "39"], ["480826", "Attempt saved. Granit Xhaka (Arsenal) left footed shot from outside the box is saved in the bottom left corner. Assisted by Danny Welbeck.", "43'", "Watford", "0", "0", "0", "0", "1", "0", "saved", "Granit Xhaka", "Arsenal", "left", "outside the box", "the bottom left corner", "Danny Welbeck", "0", "NA", "NA", "0", "NA", "0", "0", "NA", "NA", "NA", "0", "NA", "NA", "NA", "0", "NA", "NA", "0", "NA", "0", "NA", "NA", "NA", "0", "NA", "NA", "0", "0", "NA", "NA", "NA", "0", "NA", "NA", "NA", "NA", "1", "24", "0", "NA", "NA", "43"], ["480826", "Attempt missed. Héctor Bellerín (Arsenal) left footed shot from the centre of the box is close, but misses to the right. Assisted by Danny Welbeck.", "43'", "Watford", "0", "0", "0", "0", "1", "0", "missed", "Héctor Bellerín", "Arsenal", "left", "the centre of the box", "close, but right", "Danny Welbeck", "0", "NA", "NA", "0", "NA", "0", "0", "NA", "NA", "NA", "0", "NA", "NA", "NA", "0", "NA", "NA", "0", "NA", "0", "NA", "NA", "NA", "0", "NA", "NA", "0", "0", "NA", "NA", "NA", "0", "NA", "NA", "NA", "NA", "1", "25", "0", "NA", "NA", "43"], ["480826", "Attempt saved. Granit Xhaka (Arsenal) left footed shot from outside the box is saved in the bottom left corner. Assisted by Danny Welbeck.", "44'", "Watford", "0", "0", "0", "0", "1", "0", "saved", "Granit Xhaka", "Arsenal", "left", "outside the box", "the bottom left corner", "Danny Welbeck", "0", "NA", "NA", "0", "NA", "0", "0", "NA", "NA", "NA", "0", "NA", "NA", "NA", "0", "NA", "NA", "0", "NA", "0", "NA", "NA", "NA", "0", "NA", "NA", "0", "0", "NA", "NA", "NA", "0", "NA", "NA", "NA", "NA", "1", "26", "0", "NA", "NA", "44"], ["480826", "Foul by Richarlison (Watford).", "44'", "Watford", "0", "0", "0", "0", "0", "0", "NA", "NA", "NA", "NA", "NA", "NA", "NA", "1", "Richarlison", "Watford", "0", "NA", "0", "0", "NA", "NA", "NA", "0", "NA", "NA", "NA", "0", "NA", "NA", "0", "NA", "0", "NA", "NA", "NA", "0", "NA", "NA", "0", "0", "NA", "NA", "NA", "0", "NA", "NA", "NA", "NA", "1", "27", "0", "NA", "NA", "44"], ["480826", "Laurent Koscielny (Arsenal) wins a free kick in the defensive half.", "44'", "Watford", "0", "0", "0", "0", "0", "0", "NA", "NA", "NA", "NA", "NA", "NA", "NA", "0", "NA", "NA", "0", "NA", "0", "0", "NA", "NA", "NA", "0", "NA", "NA", "NA", "0", "NA", "NA", "0", "NA", "1", "Laurent Koscielny", "Arsenal", "defensive half", "0", "NA", "NA", "0", "0", "NA", "NA", "NA", "0", "NA", "NA", "NA", "NA", "1", "28", "0", "NA", "NA", "44"], ["480826", "Foul by Héctor Bellerín (Arsenal).", "45'", "Watford", "0", "0", "0", "0", "0", "0", "NA", "NA", "NA", "NA", "NA", "NA", "NA", "1", "Héctor Bellerín", "Arsenal", "0", "NA", "0", "0", "NA", "NA", "NA", "0", "NA", "NA", "NA", "0", "NA", "NA", "0", "NA", "0", "NA", "NA", "NA", "0", "NA", "NA", "0", "0", "NA", "NA", "NA", "0", "NA", "NA", "NA", "NA", "1", "29", "0", "NA", "NA", "45"], ["480826", "Richarlison (Watford) wins a free kick in the defensive half.", "45'", "Watford", "0", "0", "0", "0", "0", "0", "NA", "NA", "NA", "NA", "NA", "NA", "NA", "0", "NA", "NA", "0", "NA", "0", "0", "NA", "NA", "NA", "0", "NA", "NA", "NA", "0", "NA", "NA", "0", "NA", "1", "Richarlison", "Watford", "defensive half", "0", "NA", "NA", "0", "0", "NA", "NA", "NA", "0", "NA", "NA", "NA", "NA", "1", "30", "0", "NA", "NA", "45"], ["480826", "Alexandre Lacazette (Arsenal) wins a free kick in the attacking half.", "45'+2'", "Watford", "0", "0", "0", "0", "0", "0", "NA", "NA", "NA", "NA", "NA", "NA", "NA", "0", "NA", "NA", "0", "NA", "0", "0", "NA", "NA", "NA", "0", "NA", "NA", "NA", "0", "NA", "NA", "0", "NA", "1", "Alexandre Lacazette", "Arsenal", "attacking half", "0", "NA", "NA", "0", "0", "NA", "NA", "NA", "0", "NA", "NA", "NA", "NA", "1", "31", "1", "NA", "NA", "47"], ["480826", "Foul by Adrian Mariappa (Watford).", "45'+2'", "Watford", "0", "0", "0", "0", "0", "0", "NA", "NA", "NA", "NA", "NA", "NA", "NA", "1", "Adrian Mariappa", "Watford", "0", "NA", "0", "0", "NA", "NA", "NA", "0", "NA", "NA", "NA", "0", "NA", "NA", "0", "NA", "0", "NA", "NA", "NA", "0", "NA", "NA", "0", "0", "NA", "NA", "NA", "0", "NA", "NA", "NA", "NA", "1", "32", "1", "NA", "NA", "47"], ["480826", "Delay in match Alexandre Lacazette (Arsenal) because of an injury.", "45'+2'", "Watford", "0", "0", "0", "0", "0", "0", "NA", "NA", "NA", "NA", "NA", "NA", "NA", "0", "NA", "NA", "0", "NA", "0", "0", "NA", "NA", "NA", "0", "NA", "NA", "NA", "0", "NA", "NA", "1", "Arsenal", "0", "NA", "NA", "NA", "0", "NA", "NA", "0", "0", "NA", "NA", "NA", "0", "NA", "NA", "NA", "NA", "1", "33", "1", "NA", "NA", "47"], ["480826", "Delay over. They are ready to continue.", "45'+3'", "Watford", "0", "0", "0", "0", "0", "0", "NA", "NA", "NA", "NA", "NA", "NA", "NA", "0", "NA", "NA", "0", "NA", "0", "0", "NA", "NA", "NA", "0", "NA", "NA", "NA", "0", "NA", "NA", "0", "NA", "0", "NA", "NA", "NA", "0", "NA", "NA", "0", "0", "NA", "NA", "NA", "0", "NA", "NA", "NA", "NA", "1", "34", "1", "NA", "NA", "48"], ["480826", "First Half ends, Watford 0, Arsenal 1.", "45'+4'", "Watford", "0", "1", "0", "0", "0", "0", "NA", "NA", "NA", "NA", "NA", "NA", "NA", "0", "NA", "NA", "0", "NA", "0", "0", "NA", "NA", "NA", "0", "NA", "NA", "NA", "0", "NA", "NA", "0", "NA", "0", "NA", "NA", "NA", "0", "NA", "NA", "0", "0", "NA", "NA", "NA", "0", "NA", "NA", "NA", "NA", "1", "35", "1", "NA", "NA", "49"], ["480826", "Second Half begins Watford 0, Arsenal 1.", "45'", "Watford", "0", "0", "0", "1", "0", "0", "NA", "NA", "NA", "NA", "NA", "NA", "NA", "0", "NA", "NA", "0", "NA", "0", "0", "NA", "NA", "NA", "0", "NA", "NA", "NA", "0", "NA", "NA", "0", "NA", "0", "NA", "NA", "NA", "0", "NA", "NA", "0", "0", "NA", "NA", "NA", "0", "NA", "NA", "NA", "NA", "2", "36", "0", "NA", "NA", "45"], ["480826", "Offside, Watford. Christian Kabasele tries a through ball, but Andre Gray is caught offside.", "48'", "Watford", "0", "0", "0", "0", "0", "0", "NA", "NA", "NA", "NA", "NA", "NA", "NA", "0", "NA", "NA", "0", "NA", "0", "1", "Watford", "Andre Gray", "Christian Kabasele", "0", "NA", "NA", "NA", "0", "NA", "NA", "0", "NA", "0", "NA", "NA", "NA", "0", "NA", "NA", "0", "0", "NA", "NA", "NA", "0", "NA", "NA", "NA", "NA", "2", "37", "0", "NA", "NA", "48"], ["480826", "Corner,  Arsenal. Conceded by Kiko Femenía.", "50'", "Watford", "0", "0", "0", "0", "0", "0", "NA", "NA", "NA", "NA", "NA", "NA", "NA", "0", "NA", "NA", "0", "NA", "0", "0", "NA", "NA", "NA", "0", "NA", "NA", "NA", "0", "NA", "NA", "0", "NA", "0", "NA", "NA", "NA", "1", "Arsenal", "Kiko Femenía", "0", "0", "NA", "NA", "NA", "0", "NA", "NA", "NA", "NA", "2", "38", "0", "NA", "NA", "50"], ["480826", "Attempt missed. Richarlison (Watford) right footed shot from outside the box is close, but misses to the right. Assisted by Abdoulaye Doucouré.", "52'", "Watford", "0", "0", "0", "0", "1", "0", "missed", "Richarlison", "Watford", "right", "outside the box", "close, but right", "Abdoulaye Doucouré", "0", "NA", "NA", "0", "NA", "0", "0", "NA", "NA", "NA", "0", "NA", "NA", "NA", "0", "NA", "NA", "0", "NA", "0", "NA", "NA", "NA", "0", "NA", "NA", "0", "0", "NA", "NA", "NA", "0", "NA", "NA", "NA", "NA", "2", "39", "0", "NA", "NA", "52"], ["480826", "Corner,  Watford. Conceded by Petr Cech.", "59'", "Watford", "0", "0", "0", "0", "0", "0", "NA", "NA", "NA", "NA", "NA", "NA", "NA", "0", "NA", "NA", "0", "NA", "0", "0", "NA", "NA", "NA", "0", "NA", "NA", "NA", "0", "NA", "NA", "0", "NA", "0", "NA", "NA", "NA", "1", "Watford", "Petr Cech", "0", "0", "NA", "NA", "NA", "0", "NA", "NA", "NA", "NA", "2", "40", "0", "NA", "NA", "59"], ["480826", "Delay in match Danny Welbeck (Arsenal) because of an injury.", "59'", "Watford", "0", "0", "0", "0", "0", "0", "NA", "NA", "NA", "NA", "NA", "NA", "NA", "0", "NA", "NA", "0", "NA", "0", "0", "NA", "NA", "NA", "0", "NA", "NA", "NA", "0", "NA", "NA", "1", "Arsenal", "0", "NA", "NA", "NA", "0", "NA", "NA", "0", "0", "NA", "NA", "NA", "0", "NA", "NA", "NA", "NA", "2", "41", "0", "NA", "NA", "59"], ["480826", "Substitution, Arsenal. Mesut Özil replaces Danny Welbeck because of an injury.", "61'", "Watford", "0", "0", "0", "0", "0", "0", "NA", "NA", "NA", "NA", "NA", "NA", "NA", "0", "NA", "NA", "0", "NA", "0", "0", "NA", "NA", "NA", "0", "NA", "NA", "NA", "0", "NA", "NA", "0", "NA", "0", "NA", "NA", "NA", "0", "NA", "NA", "1", "1", "Arsenal", "Mesut Özil", "Danny Welbeck", "0", "NA", "NA", "NA", "NA", "2", "42", "0", "NA", "NA", "61"], ["480826", "Delay over. They are ready to continue.", "61'", "Watford", "0", "0", "0", "0", "0", "0", "NA", "NA", "NA", "NA", "NA", "NA", "NA", "0", "NA", "NA", "0", "NA", "0", "0", "NA", "NA", "NA", "0", "NA", "NA", "NA", "0", "NA", "NA", "0", "NA", "0", "NA", "NA", "NA", "0", "NA", "NA", "0", "0", "NA", "NA", "NA", "0", "NA", "NA", "NA", "NA", "2", "43", "0", "NA", "NA", "61"], ["480826", "Foul by José Holebas (Watford).", "62'", "Watford", "0", "0", "0", "0", "0", "0", "NA", "NA", "NA", "NA", "NA", "NA", "NA", "1", "José Holebas", "Watford", "0", "NA", "0", "0", "NA", "NA", "NA", "0", "NA", "NA", "NA", "0", "NA", "NA", "0", "NA", "0", "NA", "NA", "NA", "0", "NA", "NA", "0", "0", "NA", "NA", "NA", "0", "NA", "NA", "NA", "NA", "2", "44", "0", "NA", "NA", "62"], ["480826", "Sead Kolasinac (Arsenal) wins a free kick in the defensive half.", "62'", "Watford", "0", "0", "0", "0", "0", "0", "NA", "NA", "NA", "NA", "NA", "NA", "NA", "0", "NA", "NA", "0", "NA", "0", "0", "NA", "NA", "NA", "0", "NA", "NA", "NA", "0", "NA", "NA", "0", "NA", "1", "Sead Kolasinac", "Arsenal", "defensive half", "0", "NA", "NA", "0", "0", "NA", "NA", "NA", "0", "NA", "NA", "NA", "NA", "2", "45", "0", "NA", "NA", "62"], ["480826", "Substitution, Watford. Troy Deeney replaces Andre Gray.", "63'", "Watford", "0", "0", "0", "0", "0", "0", "NA", "NA", "NA", "NA", "NA", "NA", "NA", "0", "NA", "NA", "0", "NA", "0", "0", "NA", "NA", "NA", "0", "NA", "NA", "NA", "0", "NA", "NA", "0", "NA", "0", "NA", "NA", "NA", "0", "NA", "NA", "1", "0", "Watford", "Troy Deeney", "Andre Gray", "0", "NA", "NA", "NA", "NA", "2", "46", "0", "NA", "NA", "63"], ["480826", "Substitution, Watford. André Carrillo replaces Adrian Mariappa.", "63'", "Watford", "0", "0", "0", "0", "0", "0", "NA", "NA", "NA", "NA", "NA", "NA", "NA", "0", "NA", "NA", "0", "NA", "0", "0", "NA", "NA", "NA", "0", "NA", "NA", "NA", "0", "NA", "NA", "0", "NA", "0", "NA", "NA", "NA", "0", "NA", "NA", "1", "0", "Watford", "André Carrillo", "Adrian Mariappa", "0", "NA", "NA", "NA", "NA", "2", "47", "0", "NA", "NA", "63"], ["480826", "Attempt saved. Alex Iwobi (Arsenal) right footed shot from the left side of the box is saved in the bottom right corner. Assisted by Mesut Özil with a through ball.", "63'", "Watford", "0", "0", "0", "0", "1", "0", "saved", "Alex Iwobi", "Arsenal", "right", "the left side of the box", "the bottom right corner", "Mesut Özil", "0", "NA", "NA", "0", "through", "0", "0", "NA", "NA", "NA", "0", "NA", "NA", "NA", "0", "NA", "NA", "0", "NA", "0", "NA", "NA", "NA", "0", "NA", "NA", "0", "0", "NA", "NA", "NA", "0", "NA", "NA", "NA", "NA", "2", "48", "0", "NA", "NA", "63"], ["480826", "Corner,  Arsenal. Conceded by Heurelho Gomes.", "63'", "Watford", "0", "0", "0", "0", "0", "0", "NA", "NA", "NA", "NA", "NA", "NA", "NA", "0", "NA", "NA", "0", "NA", "0", "0", "NA", "NA", "NA", "0", "NA", "NA", "NA", "0", "NA", "NA", "0", "NA", "0", "NA", "NA", "NA", "1", "Arsenal", "Heurelho Gomes", "0", "0", "NA", "NA", "NA", "0", "NA", "NA", "NA", "NA", "2", "49", "0", "NA", "NA", "63"], ["480826", "Christian Kabasele (Watford) is shown the yellow card for a bad foul.", "64'", "Watford", "0", "0", "0", "0", "0", "0", "NA", "NA", "NA", "NA", "NA", "NA", "NA", "0", "NA", "NA", "0", "NA", "0", "0", "NA", "NA", "NA", "1", "yellow", "Christian Kabasele", "Watford", "0", "NA", "NA", "0", "NA", "0", "NA", "NA", "NA", "0", "NA", "NA", "0", "0", "NA", "NA", "NA", "0", "NA", "NA", "NA", "NA", "2", "50", "0", "NA", "NA", "64"], ["480826", "Corner,  Arsenal. Conceded by Christian Kabasele.", "64'", "Watford", "0", "0", "0", "0", "0", "0", "NA", "NA", "NA", "NA", "NA", "NA", "NA", "0", "NA", "NA", "0", "NA", "0", "0", "NA", "NA", "NA", "0", "NA", "NA", "NA", "0", "NA", "NA", "0", "NA", "0", "NA", "NA", "NA", "1", "Arsenal", "Christian Kabasele", "0", "0", "NA", "NA", "NA", "0", "NA", "NA", "NA", "NA", "2", "51", "0", "NA", "NA", "64"], ["480826", "Hand ball by Mesut Özil (Arsenal).", "66'", "Watford", "0", "0", "0", "0", "0", "0", "NA", "NA", "NA", "NA", "NA", "NA", "NA", "0", "NA", "NA", "0", "NA", "0", "0", "NA", "NA", "NA", "0", "NA", "NA", "NA", "0", "NA", "NA", "0", "NA", "0", "NA", "NA", "NA", "0", "NA", "NA", "0", "0", "NA", "NA", "NA", "0", "NA", "NA", "NA", "NA", "2", "52", "0", "NA", "NA", "66"], ["480826", "Corner,  Watford. Conceded by Per Mertesacker.", "67'", "Watford", "0", "0", "0", "0", "0", "0", "NA", "NA", "NA", "NA", "NA", "NA", "NA", "0", "NA", "NA", "0", "NA", "0", "0", "NA", "NA", "NA", "0", "NA", "NA", "NA", "0", "NA", "NA", "0", "NA", "0", "NA", "NA", "NA", "1", "Watford", "Per Mertesacker", "0", "0", "NA", "NA", "NA", "0", "NA", "NA", "NA", "NA", "2", "53", "0", "NA", "NA", "67"], ["480826", "Substitution, Arsenal. Olivier Giroud replaces Alexandre Lacazette.", "68'", "Watford", "0", "0", "0", "0", "0", "0", "NA", "NA", "NA", "NA", "NA", "NA", "NA", "0", "NA", "NA", "0", "NA", "0", "0", "NA", "NA", "NA", "0", "NA", "NA", "NA", "0", "NA", "NA", "0", "NA", "0", "NA", "NA", "NA", "0", "NA", "NA", "1", "0", "Arsenal", "Olivier Giroud", "Alexandre Lacazette", "0", "NA", "NA", "NA", "NA", "2", "54", "0", "NA", "NA", "68"], ["480826", "Attempt saved. Mesut Özil (Arsenal) left footed shot from the centre of the box is saved in the centre of the goal. Assisted by Alex Iwobi with a through ball.", "70'", "Watford", "0", "0", "0", "0", "1", "0", "saved", "Mesut Özil", "Arsenal", "left", "the centre of the box", "the centre of the goal", "Alex Iwobi", "0", "NA", "NA", "0", "through", "0", "0", "NA", "NA", "NA", "0", "NA", "NA", "NA", "0", "NA", "NA", "0", "NA", "0", "NA", "NA", "NA", "0", "NA", "NA", "0", "0", "NA", "NA", "NA", "0", "NA", "NA", "NA", "NA", "2", "55", "0", "NA", "NA", "70"], ["480826", "Penalty Watford. Richarlison draws a foul in the penalty area.", "71'", "Watford", "0", "0", "0", "0", "0", "0", "NA", "NA", "NA", "NA", "NA", "NA", "NA", "0", "NA", "NA", "0", "NA", "0", "0", "NA", "NA", "NA", "0", "NA", "NA", "NA", "0", "NA", "NA", "0", "NA", "0", "NA", "NA", "NA", "0", "NA", "NA", "0", "0", "NA", "NA", "NA", "1", "Watford", "Richarlison", "NA", "NA", "2", "56", "0", "NA", "NA", "71"], ["480826", "Penalty conceded by Héctor Bellerín (Arsenal) after a foul in the penalty area.", "71'", "Watford", "0", "0", "0", "0", "0", "0", "NA", "NA", "NA", "NA", "NA", "NA", "NA", "0", "NA", "NA", "0", "NA", "0", "0", "NA", "NA", "NA", "0", "NA", "NA", "NA", "0", "NA", "NA", "0", "NA", "0", "NA", "NA", "NA", "0", "NA", "NA", "0", "0", "NA", "NA", "NA", "1", "Arsenal", "NA", "Héctor Bellerín", "Arsenal", "2", "57", "0", "NA", "NA", "71"], ["480826", "Goal!  Watford 1, Arsenal 1. Troy Deeney (Watford) converts the penalty with a right footed shot to the bottom right corner.", "71'", "Watford", "1", "0", "0", "0", "1", "0", "goal", "Troy Deeney", "Watford", "right", "NA", "bottom right corner", "NA", "0", "NA", "NA", "0", "NA", "0", "0", "NA", "NA", "NA", "0", "NA", "NA", "NA", "0", "NA", "NA", "0", "NA", "0", "NA", "NA", "NA", "0", "NA", "NA", "0", "0", "NA", "NA", "NA", "0", "NA", "NA", "NA", "NA", "2", "58", "0", "NA", "NA", "71"], ["480826", "Attempt missed. Richarlison (Watford) right footed shot from the left side of the box is close, but misses to the left. Assisted by Troy Deeney with a headed pass.", "75'", "Watford", "1", "0", "0", "0", "1", "0", "missed", "Richarlison", "Watford", "right", "the left side of the box", "close, but left", "Troy Deeney", "0", "NA", "NA", "0", "NA", "0", "0", "NA", "NA", "NA", "0", "NA", "NA", "NA", "0", "NA", "NA", "0", "NA", "0", "NA", "NA", "NA", "0", "NA", "NA", "0", "0", "NA", "NA", "NA", "0", "NA", "NA", "NA", "NA", "2", "59", "0", "NA", "NA", "75"], ["480826", "Abdoulaye Doucouré (Watford) wins a free kick in the defensive half.", "75'", "Watford", "1", "0", "0", "0", "0", "0", "NA", "NA", "NA", "NA", "NA", "NA", "NA", "0", "NA", "NA", "0", "NA", "0", "0", "NA", "NA", "NA", "0", "NA", "NA", "NA", "0", "NA", "NA", "0", "NA", "1", "Abdoulaye Doucouré", "Watford", "defensive half", "0", "NA", "NA", "0", "0", "NA", "NA", "NA", "0", "NA", "NA", "NA", "NA", "2", "60", "0", "NA", "NA", "75"], ["480826", "Foul by Mesut Özil (Arsenal).", "75'", "Watford", "1", "0", "0", "0", "0", "0", "NA", "NA", "NA", "NA", "NA", "NA", "NA", "1", "Mesut Özil", "Arsenal", "0", "NA", "0", "0", "NA", "NA", "NA", "0", "NA", "NA", "NA", "0", "NA", "NA", "0", "NA", "0", "NA", "NA", "NA", "0", "NA", "NA", "0", "0", "NA", "NA", "NA", "0", "NA", "NA", "NA", "NA", "2", "61", "0", "NA", "NA", "75"], ["480826", "Foul by Richarlison (Watford).", "76'", "Watford", "1", "0", "0", "0", "0", "0", "NA", "NA", "NA", "NA", "NA", "NA", "NA", "1", "Richarlison", "Watford", "0", "NA", "0", "0", "NA", "NA", "NA", "0", "NA", "NA", "NA", "0", "NA", "NA", "0", "NA", "0", "NA", "NA", "NA", "0", "NA", "NA", "0", "0", "NA", "NA", "NA", "0", "NA", "NA", "NA", "NA", "2", "62", "0", "NA", "NA", "76"], ["480826", "Laurent Koscielny (Arsenal) wins a free kick in the defensive half.", "76'", "Watford", "1", "0", "0", "0", "0", "0", "NA", "NA", "NA", "NA", "NA", "NA", "NA", "0", "NA", "NA", "0", "NA", "0", "0", "NA", "NA", "NA", "0", "NA", "NA", "NA", "0", "NA", "NA", "0", "NA", "1", "Laurent Koscielny", "Arsenal", "defensive half", "0", "NA", "NA", "0", "0", "NA", "NA", "NA", "0", "NA", "NA", "NA", "NA", "2", "63", "0", "NA", "NA", "76"], ["480826", "Foul by José Holebas (Watford).", "77'", "Watford", "1", "0", "0", "0", "0", "0", "NA", "NA", "NA", "NA", "NA", "NA", "NA", "1", "José Holebas", "Watford", "0", "NA", "0", "0", "NA", "NA", "NA", "0", "NA", "NA", "NA", "0", "NA", "NA", "0", "NA", "0", "NA", "NA", "NA", "0", "NA", "NA", "0", "0", "NA", "NA", "NA", "0", "NA", "NA", "NA", "NA", "2", "64", "0", "NA", "NA", "77"], ["480826", "Mesut Özil (Arsenal) wins a free kick in the defensive half.", "77'", "Watford", "1", "0", "0", "0", "0", "0", "NA", "NA", "NA", "NA", "NA", "NA", "NA", "0", "NA", "NA", "0", "NA", "0", "0", "NA", "NA", "NA", "0", "NA", "NA", "NA", "0", "NA", "NA", "0", "NA", "1", "Mesut Özil", "Arsenal", "defensive half", "0", "NA", "NA", "0", "0", "NA", "NA", "NA", "0", "NA", "NA", "NA", "NA", "2", "65", "0", "NA", "NA", "77"], ["480826", "Substitution, Watford. Etienne Capoue replaces Roberto Pereyra.", "81'", "Watford", "1", "0", "0", "0", "0", "0", "NA", "NA", "NA", "NA", "NA", "NA", "NA", "0", "NA", "NA", "0", "NA", "0", "0", "NA", "NA", "NA", "0", "NA", "NA", "NA", "0", "NA", "NA", "0", "NA", "0", "NA", "NA", "NA", "0", "NA", "NA", "1", "0", "Watford", "Etienne Capoue", "Roberto Pereyra", "0", "NA", "NA", "NA", "NA", "2", "66", "0", "NA", "NA", "81"], ["480826", "Attempt blocked. Etienne Capoue (Watford) right footed shot from outside the box is blocked. Assisted by Troy Deeney.", "83'", "Watford", "1", "0", "0", "0", "1", "0", "blocked", "Etienne Capoue", "Watford", "right", "outside the box", "NA", "Troy Deeney", "0", "NA", "NA", "0", "NA", "0", "0", "NA", "NA", "NA", "0", "NA", "NA", "NA", "0", "NA", "NA", "0", "NA", "0", "NA", "NA", "NA", "0", "NA", "NA", "0", "0", "NA", "NA", "NA", "0", "NA", "NA", "NA", "NA", "2", "67", "0", "NA", "NA", "83"], ["480826", "Foul by Richarlison (Watford).", "84'", "Watford", "1", "0", "0", "0", "0", "0", "NA", "NA", "NA", "NA", "NA", "NA", "NA", "1", "Richarlison", "Watford", "0", "NA", "0", "0", "NA", "NA", "NA", "0", "NA", "NA", "NA", "0", "NA", "NA", "0", "NA", "0", "NA", "NA", "NA", "0", "NA", "NA", "0", "0", "NA", "NA", "NA", "0", "NA", "NA", "NA", "NA", "2", "68", "0", "NA", "NA", "84"], ["480826", "Per Mertesacker (Arsenal) wins a free kick in the defensive half.", "84'", "Watford", "1", "0", "0", "0", "0", "0", "NA", "NA", "NA", "NA", "NA", "NA", "NA", "0", "NA", "NA", "0", "NA", "0", "0", "NA", "NA", "NA", "0", "NA", "NA", "NA", "0", "NA", "NA", "0", "NA", "1", "Per Mertesacker", "Arsenal", "defensive half", "0", "NA", "NA", "0", "0", "NA", "NA", "NA", "0", "NA", "NA", "NA", "NA", "2", "69", "0", "NA", "NA", "84"], ["480826", "Substitution, Arsenal. Rob Holding replaces Laurent Koscielny because of an injury.", "85'", "Watford", "1", "0", "0", "0", "0", "0", "NA", "NA", "NA", "NA", "NA", "NA", "NA", "0", "NA", "NA", "0", "NA", "0", "0", "NA", "NA", "NA", "0", "NA", "NA", "NA", "0", "NA", "NA", "0", "NA", "0", "NA", "NA", "NA", "0", "NA", "NA", "1", "1", "Arsenal", "Rob Holding", "Laurent Koscielny", "0", "NA", "NA", "NA", "NA", "2", "70", "0", "NA", "NA", "85"], ["480826", "Foul by Olivier Giroud (Arsenal).", "85'", "Watford", "1", "0", "0", "0", "0", "0", "NA", "NA", "NA", "NA", "NA", "NA", "NA", "1", "Olivier Giroud", "Arsenal", "0", "NA", "0", "0", "NA", "NA", "NA", "0", "NA", "NA", "NA", "0", "NA", "NA", "0", "NA", "0", "NA", "NA", "NA", "0", "NA", "NA", "0", "0", "NA", "NA", "NA", "0", "NA", "NA", "NA", "NA", "2", "71", "0", "NA", "NA", "85"], ["480826", "Miguel Britos (Watford) wins a free kick in the defensive half.", "85'", "Watford", "1", "0", "0", "0", "0", "0", "NA", "NA", "NA", "NA", "NA", "NA", "NA", "0", "NA", "NA", "0", "NA", "0", "0", "NA", "NA", "NA", "0", "NA", "NA", "NA", "0", "NA", "NA", "0", "NA", "1", "Miguel Britos", "Watford", "defensive half", "0", "NA", "NA", "0", "0", "NA", "NA", "NA", "0", "NA", "NA", "NA", "NA", "2", "72", "0", "NA", "NA", "85"], ["480826", "Attempt missed. André Carrillo (Watford) right footed shot from outside the box is too high. Assisted by Richarlison.", "87'", "Watford", "1", "0", "0", "0", "1", "0", "missed", "André Carrillo", "Watford", "right", "outside the box", "too high", "Richarlison", "0", "NA", "NA", "0", "NA", "0", "0", "NA", "NA", "NA", "0", "NA", "NA", "NA", "0", "NA", "NA", "0", "NA", "0", "NA", "NA", "NA", "0", "NA", "NA", "0", "0", "NA", "NA", "NA", "0", "NA", "NA", "NA", "NA", "2", "73", "0", "NA", "NA", "87"], ["480826", "Corner,  Arsenal. Conceded by Christian Kabasele.", "89'", "Watford", "1", "0", "0", "0", "0", "0", "NA", "NA", "NA", "NA", "NA", "NA", "NA", "0", "NA", "NA", "0", "NA", "0", "0", "NA", "NA", "NA", "0", "NA", "NA", "NA", "0", "NA", "NA", "0", "NA", "0", "NA", "NA", "NA", "1", "Arsenal", "Christian Kabasele", "0", "0", "NA", "NA", "NA", "0", "NA", "NA", "NA", "NA", "2", "74", "0", "NA", "NA", "89"], ["480826", "Attempt missed. Nacho Monreal (Arsenal) left footed shot from outside the box is high and wide to the left following a corner.", "89'", "Watford", "1", "0", "0", "0", "1", "0", "missed", "Nacho Monreal", "Arsenal", "left", "outside the box", "high and wide to the left", "NA", "0", "NA", "NA", "0", "NA", "1", "0", "NA", "NA", "NA", "0", "NA", "NA", "NA", "0", "NA", "NA", "0", "NA", "0", "NA", "NA", "NA", "0", "NA", "NA", "0", "0", "NA", "NA", "NA", "0", "NA", "NA", "NA", "NA", "2", "75", "0", "NA", "NA", "89"], ["480826", "Attempt blocked. Troy Deeney (Watford) right footed shot from the left side of the box is blocked. Assisted by André Carrillo.", "90'+1'", "Watford", "1", "0", "0", "0", "1", "0", "blocked", "Troy Deeney", "Watford", "right", "the left side of the box", "NA", "André Carrillo", "0", "NA", "NA", "0", "NA", "0", "0", "NA", "NA", "NA", "0", "NA", "NA", "NA", "0", "NA", "NA", "0", "NA", "0", "NA", "NA", "NA", "0", "NA", "NA", "0", "0", "NA", "NA", "NA", "0", "NA", "NA", "NA", "NA", "2", "76", "1", "NA", "NA", "91"], ["480826", "Attempt missed. José Holebas (Watford) left footed shot from outside the box is close, but misses to the right. Assisted by Abdoulaye Doucouré.", "90'+2'", "Watford", "1", "0", "0", "0", "1", "0", "missed", "José Holebas", "Watford", "left", "outside the box", "close, but right", "Abdoulaye Doucouré", "0", "NA", "NA", "0", "NA", "0", "0", "NA", "NA", "NA", "0", "NA", "NA", "NA", "0", "NA", "NA", "0", "NA", "0", "NA", "NA", "NA", "0", "NA", "NA", "0", "0", "NA", "NA", "NA", "0", "NA", "NA", "NA", "NA", "2", "77", "1", "NA", "NA", "92"], ["480826", "Attempt blocked. Etienne Capoue (Watford) right footed shot from the centre of the box is blocked.", "90'+2'", "Watford", "1", "0", "0", "0", "1", "0", "blocked", "Etienne Capoue", "Watford", "right", "the centre of the box", "NA", "NA", "0", "NA", "NA", "0", "NA", "0", "0", "NA", "NA", "NA", "0", "NA", "NA", "NA", "0", "NA", "NA", "0", "NA", "0", "NA", "NA", "NA", "0", "NA", "NA", "0", "0", "NA", "NA", "NA", "0", "NA", "NA", "NA", "NA", "2", "78", "1", "NA", "NA", "92"], ["480826", "Goal!  Watford 2, Arsenal 1. Tom Cleverley (Watford) right footed shot from the centre of the box to the high centre of the goal.", "90'+2'", "Watford", "2", "0", "0", "0", "1", "0", "goal", "Tom Cleverley", "Watford", "right", "the centre of the box", "high centre of the goal", "NA", "0", "NA", "NA", "0", "NA", "0", "0", "NA", "NA", "NA", "0", "NA", "NA", "NA", "0", "NA", "NA", "0", "NA", "0", "NA", "NA", "NA", "0", "NA", "NA", "0", "0", "NA", "NA", "NA", "0", "NA", "NA", "NA", "NA", "2", "79", "1", "NA", "NA", "92"], ["480826", "Attempt saved. Olivier Giroud (Arsenal) header from the centre of the box is saved in the centre of the goal. Assisted by Mesut Özil.", "90'+4'", "Watford", "2", "0", "0", "0", "1", "0", "saved", "Olivier Giroud", "Arsenal", "header", "the centre of the box", "the centre of the goal", "Mesut Özil", "0", "NA", "NA", "0", "NA", "0", "0", "NA", "NA", "NA", "0", "NA", "NA", "NA", "0", "NA", "NA", "0", "NA", "0", "NA", "NA", "NA", "0", "NA", "NA", "0", "0", "NA", "NA", "NA", "0", "NA", "NA", "NA", "NA", "2", "80", "1", "NA", "NA", "94"], ["480826", "Second Half ends, Watford 2, Arsenal 1.", "90'+5'", "Watford", "2", "1", "0", "0", "0", "0", "NA", "NA", "NA", "NA", "NA", "NA", "NA", "0", "NA", "NA", "0", "NA", "0", "0", "NA", "NA", "NA", "0", "NA", "NA", "NA", "0", "NA", "NA", "0", "NA", "0", "NA", "NA", "NA", "0", "NA", "NA", "0", "0", "NA", "NA", "NA", "0", "NA", "NA", "NA", "NA", "2", "81", "1", "NA", "NA", "95"], ["480826", "Match ends, Watford 2, Arsenal 1.", "90'+5'", "Watford", "2", "0", "1", "0", "0", "0", "NA", "NA", "NA", "NA", "NA", "NA", "NA", "0", "NA", "NA", "0", "NA", "0", "0", "NA", "NA", "NA", "0", "NA", "NA", "NA", "0", "NA", "NA", "0", "NA", "0", "NA", "NA", "NA", "0", "NA", "NA", "0", "0", "NA", "NA", "NA", "0", "NA", "NA", "NA", "NA", "2", "82", "1", "NA", "NA", "95"]], "Lineup": {"Home Player 9": "Adrian Mariappa", "Home Player 8": "Kiko", "Home Player 5": "Andre Gray", "Home Player 4": "Heurelho Gomes", "Home Player 7": "Christian Kabasele", "Home Player 6": "Jose Holebas", "Home Player 1": "Miguel Britos", "Home Player 3": "Abdoulaye Doucoure", "Home Player 2": "Tom Cleverley", "Away Player 10": "Danny Welbeck", "Away Player 11": "Granit Xhaka", "Away Player 8": "Per Mertesacker", "Away Player 9": "Nacho Monreal", "Away Player 1": "Hector Bellerin", "Away Player 2": "Petr Cech", "Away Player 3": "Mohamed Elneny", "Away Player 4": "Alex Iwobi", "Away Player 5": "Sead Kolasinac", "Away Player 6": "Laurent Koscielny", "Away Player 7": "Alexandre Lacazette", "Game ID": "g_1_S8XU7DBA", "Home Player 11": "Richarlison", "Home Player 10": "Roberto Pereyra"}}