{"Stats": {"Full Time Result": "D", "Away Team Corners": 4, "Referee": "S Attwell", "Home Team Fouls Committed": 12, "Home Team Corners": 7, "Away Team Shots": 9, "Away Team Red Cards": 0, "Home Team Red Cards": 0, "Half Time Away Team Goals": 1, "Full Time Home Team Goals": 2, "Away Team Yellow Cards": 1, "Away Team Shots on Target": 3, "Half Time Home Team Goals": 0, "Half Time Result": "A", "Home Team Yellow Cards": 0, "Home Team Shots": 13, "Div": "E0", "Away Team Fouls Committed": 5, "Home Team Shots on Target": 6, "Full Time Away Team Goals": 2}, "Description": "Foul by Salomón Rondón (West Bromwich Albion). at minute 2. Ragnar Klavan (Liverpool) wins a free kick in the defensive half. at minute 2. Corner,  Liverpool. Conceded by Craig Dawson. at minute 3. Corner,  Liverpool. Conceded by Allan Nyom. at minute 4. Goal!  West Bromwich Albion 0, Liverpool 1. Danny Ings (Liverpool) left footed shot from the centre of the box to the centre of the goal. Assisted by Georginio Wijnaldum following a corner. at minute 4. Foul by Allan Nyom (West Bromwich Albion). at minute 5. Sadio Mané (Liverpool) wins a free kick in the defensive half. at minute 5. Attempt blocked. Mohamed Salah (Liverpool) left footed shot from the right side of the box is blocked. Assisted by Joseph Gomez. at minute 11. Corner,  Liverpool. Conceded by Jake Livermore. at minute 11. Corner,  West Bromwich Albion. Conceded by Joseph Gomez. at minute 15. Offside, West Bromwich Albion. Craig Dawson tries a through ball, but Jake Livermore is caught offside. at minute 16. Attempt missed. Chris Brunt (West Bromwich Albion) right footed shot from outside the box is high and wide to the right. at minute 18. Attempt saved. Matt Phillips (West Bromwich Albion) left footed shot from the right side of the box is saved in the bottom right corner. Assisted by Jay Rodriguez. at minute 22. Attempt missed. Danny Ings (Liverpool) header from the centre of the box is too high. Assisted by James Milner with a cross. at minute 24. Foul by Ahmed Hegazi (West Bromwich Albion). at minute 25. Mohamed Salah (Liverpool) wins a free kick in the attacking half. at minute 25. Attempt missed. Mohamed Salah (Liverpool) left footed shot from outside the box is close, but misses to the right from a direct free kick. at minute 26. Foul by Kieran Gibbs (West Bromwich Albion). at minute 27. Mohamed Salah (Liverpool) wins a free kick in the attacking half. at minute 27. Danny Ings (Liverpool) wins a free kick in the defensive half. at minute 29. Foul by Salomón Rondón (West Bromwich Albion). at minute 29. Corner,  West Bromwich Albion. Conceded by Joseph Gomez. at minute 33. Corner,  West Bromwich Albion. Conceded by Joseph Gomez. at minute 34. Corner,  West Bromwich Albion. Conceded by Ragnar Klavan. at minute 35. Corner,  West Bromwich Albion. Conceded by Danny Ings. at minute 36. Attempt missed. James McClean (West Bromwich Albion) left footed shot from a difficult angle on the left misses to the right. Assisted by Jake Livermore with a cross. at minute 37. Attempt saved. Danny Ings (Liverpool) left footed shot from the centre of the box is saved in the centre of the goal. at minute 42. Corner,  Liverpool. Conceded by Ahmed Hegazi. at minute 42. Attempt missed. Allan Nyom (West Bromwich Albion) right footed shot from more than 35 yards misses to the right. at minute 44. First Half ends, West Bromwich Albion 0, Liverpool 1. at minute 47. Second Half begins West Bromwich Albion 0, Liverpool 1. at minute 45. Attempt missed. James McClean (West Bromwich Albion) left footed shot from outside the box misses to the right. Assisted by Matt Phillips. at minute 50. Foul by Kieran Gibbs (West Bromwich Albion). at minute 51. Sadio Mané (Liverpool) wins a free kick in the attacking half. at minute 51. Foul by James Milner (Liverpool). at minute 52. Kieran Gibbs (West Bromwich Albion) wins a free kick in the defensive half. at minute 52. Ahmed Hegazi (West Bromwich Albion) wins a free kick in the attacking half. at minute 55. Foul by Danny Ings (Liverpool). at minute 55. Attempt missed. Ahmed Hegazi (West Bromwich Albion) header from the centre of the box is high and wide to the left. Assisted by Chris Brunt with a cross following a set piece situation. at minute 56. Ahmed Hegazi (West Bromwich Albion) wins a free kick in the defensive half. at minute 58. Foul by Danny Ings (Liverpool). at minute 58. Corner,  West Bromwich Albion. Conceded by Virgil van Dijk. at minute 59. Offside, Liverpool. James Milner tries a through ball, but Mohamed Salah is caught offside. at minute 62. Attempt blocked. Mohamed Salah (Liverpool) left footed shot from outside the box is blocked. Assisted by James Milner. at minute 63. Foul by James McClean (West Bromwich Albion). at minute 64. Joseph Gomez (Liverpool) wins a free kick on the right wing. at minute 64. Substitution, Liverpool. Roberto Firmino replaces Danny Ings. at minute 66. Substitution, Liverpool. Alex Oxlade-Chamberlain replaces Sadio Mané. at minute 66. Foul by Alberto Moreno (Liverpool). at minute 69. Matt Phillips (West Bromwich Albion) wins a free kick on the right wing. at minute 69. Alberto Moreno (Liverpool) is shown the yellow card for a bad foul. at minute 69. Attempt missed. Craig Dawson (West Bromwich Albion) right footed shot from the centre of the box is close, but misses to the right following a set piece situation. at minute 70. Attempt saved. Salomón Rondón (West Bromwich Albion) right footed shot from the centre of the box is saved in the bottom right corner. at minute 70. Substitution, West Bromwich Albion. Jonny Evans replaces James McClean. at minute 71. Goal!  West Bromwich Albion 0, Liverpool 2. Mohamed Salah (Liverpool) left footed shot from the centre of the box to the high centre of the goal. Assisted by Alex Oxlade-Chamberlain. at minute 72. Alex Oxlade-Chamberlain (Liverpool) wins a free kick in the attacking half. at minute 74. Foul by Jonny Evans (West Bromwich Albion). at minute 74. Substitution, West Bromwich Albion. Oliver Burke replaces Kieran Gibbs. at minute 76. Corner,  West Bromwich Albion. Conceded by Ragnar Klavan. at minute 78. Attempt saved. Craig Dawson (West Bromwich Albion) left footed shot from the centre of the box is saved in the centre of the goal. Assisted by Jay Rodriguez. at minute 79. Goal!  West Bromwich Albion 1, Liverpool 2. Jake Livermore (West Bromwich Albion) right footed shot from very close range to the centre of the goal following a corner. at minute 79. Offside, Liverpool. Loris Karius tries a through ball, but Mohamed Salah is caught offside. at minute 80. Hand ball by Jonny Evans (West Bromwich Albion). at minute 80. Foul by Salomón Rondón (West Bromwich Albion). at minute 83. Ragnar Klavan (Liverpool) wins a free kick in the defensive half. at minute 83. Substitution, Liverpool. Dejan Lovren replaces Mohamed Salah. at minute 84. Foul by Allan Nyom (West Bromwich Albion). at minute 84. James Milner (Liverpool) wins a free kick on the left wing. at minute 84. Attempt missed. Roberto Firmino (Liverpool) header from the left side of the box misses to the right. Assisted by Alex Oxlade-Chamberlain with a cross. at minute 86. Attempt saved. Salomón Rondón (West Bromwich Albion) right footed shot from the centre of the box is saved in the centre of the goal. at minute 86. Foul by Joseph Gomez (Liverpool). at minute 88. Oliver Burke (West Bromwich Albion) wins a free kick on the left wing. at minute 88. Goal!  West Bromwich Albion 2, Liverpool 2. Salomón Rondón (West Bromwich Albion) header from the centre of the box to the bottom left corner. Assisted by Chris Brunt with a cross following a set piece situation. at minute 88. Substitution, West Bromwich Albion. Hal Robson-Kanu replaces Jay Rodriguez. at minute 89. Attempt blocked. Matt Phillips (West Bromwich Albion) header from the centre of the box is blocked. Assisted by Salomón Rondón with a cross. at minute 92. Attempt missed. James Milner (Liverpool) left footed shot from outside the box is too high. Assisted by Alex Oxlade-Chamberlain. at minute 93. Foul by Craig Dawson (West Bromwich Albion). at minute 94. Roberto Firmino (Liverpool) wins a free kick in the defensive half. at minute 94. Second Half ends, West Bromwich Albion 2, Liverpool 2. at minute 95. Match ends, West Bromwich Albion 2, Liverpool 2. at minute 95. ", "Home Team": "West Bromwich Albion", "Away Team": "Liverpool", "Date": "21-04-2018", "Commentary": [["480559", "First Half begins.", "-", "West Bromwich Albion", "0", "0", "0", "1", "0", "0", "NA", "NA", "NA", "NA", "NA", "NA", "NA", "0", "NA", "NA", "0", "NA", "0", "0", "NA", "NA", "NA", "0", "NA", "NA", "NA", "0", "NA", "NA", "0", "NA", "0", "NA", "NA", "NA", "0", "NA", "NA", "0", "0", "NA", "NA", "NA", "0", "NA", "NA", "NA", "NA", "1", "1", "0", "NA", "NA", "NA"], ["480559", "Lineups are announced and players are warming up.", "-", "West Bromwich Albion", "0", "0", "0", "0", "0", "0", "NA", "NA", "NA", "NA", "NA", "NA", "NA", "0", "NA", "NA", "0", "NA", "0", "0", "NA", "NA", "NA", "0", "NA", "NA", "NA", "0", "NA", "NA", "0", "NA", "0", "NA", "NA", "NA", "0", "NA", "NA", "0", "0", "NA", "NA", "NA", "0", "NA", "NA", "NA", "NA", "1", "2", "0", "NA", "NA", "NA"], ["480559", "Foul by Salomón Rondón (West Bromwich Albion).", "2'", "West Bromwich Albion", "0", "0", "0", "0", "0", "0", "NA", "NA", "NA", "NA", "NA", "NA", "NA", "1", "Salomón Rondón", "West Bromwich Albion", "0", "NA", "0", "0", "NA", "NA", "NA", "0", "NA", "NA", "NA", "0", "NA", "NA", "0", "NA", "0", "NA", "NA", "NA", "0", "NA", "NA", "0", "0", "NA", "NA", "NA", "0", "NA", "NA", "NA", "NA", "1", "3", "0", "NA", "NA", "2"], ["480559", "Ragnar Klavan (Liverpool) wins a free kick in the defensive half.", "2'", "West Bromwich Albion", "0", "0", "0", "0", "0", "0", "NA", "NA", "NA", "NA", "NA", "NA", "NA", "0", "NA", "NA", "0", "NA", "0", "0", "NA", "NA", "NA", "0", "NA", "NA", "NA", "0", "NA", "NA", "0", "NA", "1", "Ragnar Klavan", "Liverpool", "defensive half", "0", "NA", "NA", "0", "0", "NA", "NA", "NA", "0", "NA", "NA", "NA", "NA", "1", "4", "0", "NA", "NA", "2"], ["480559", "Corner,  Liverpool. Conceded by Craig Dawson.", "3'", "West Bromwich Albion", "0", "0", "0", "0", "0", "0", "NA", "NA", "NA", "NA", "NA", "NA", "NA", "0", "NA", "NA", "0", "NA", "0", "0", "NA", "NA", "NA", "0", "NA", "NA", "NA", "0", "NA", "NA", "0", "NA", "0", "NA", "NA", "NA", "1", "Liverpool", "Craig Dawson", "0", "0", "NA", "NA", "NA", "0", "NA", "NA", "NA", "NA", "1", "5", "0", "NA", "NA", "3"], ["480559", "Corner,  Liverpool. Conceded by Allan Nyom.", "4'", "West Bromwich Albion", "0", "0", "0", "0", "0", "0", "NA", "NA", "NA", "NA", "NA", "NA", "NA", "0", "NA", "NA", "0", "NA", "0", "0", "NA", "NA", "NA", "0", "NA", "NA", "NA", "0", "NA", "NA", "0", "NA", "0", "NA", "NA", "NA", "1", "Liverpool", "Allan Nyom", "0", "0", "NA", "NA", "NA", "0", "NA", "NA", "NA", "NA", "1", "6", "0", "NA", "NA", "4"], ["480559", "Goal!  West Bromwich Albion 0, Liverpool 1. Danny Ings (Liverpool) left footed shot from the centre of the box to the centre of the goal. Assisted by Georginio Wijnaldum following a corner.", "4'", "West Bromwich Albion", "0", "0", "0", "0", "1", "0", "goal", "Danny Ings", "Liverpool", "left", "the centre of the box", "centre of the goal", "Georginio Wijnaldum", "0", "NA", "NA", "0", "NA", "1", "0", "NA", "NA", "NA", "0", "NA", "NA", "NA", "0", "NA", "NA", "0", "NA", "0", "NA", "NA", "NA", "0", "NA", "NA", "0", "0", "NA", "NA", "NA", "0", "NA", "NA", "NA", "NA", "1", "7", "0", "NA", "NA", "4"], ["480559", "Foul by Allan Nyom (West Bromwich Albion).", "5'", "West Bromwich Albion", "0", "0", "0", "0", "0", "0", "NA", "NA", "NA", "NA", "NA", "NA", "NA", "1", "Allan Nyom", "West Bromwich Albion", "0", "NA", "0", "0", "NA", "NA", "NA", "0", "NA", "NA", "NA", "0", "NA", "NA", "0", "NA", "0", "NA", "NA", "NA", "0", "NA", "NA", "0", "0", "NA", "NA", "NA", "0", "NA", "NA", "NA", "NA", "1", "8", "0", "NA", "NA", "5"], ["480559", "Sadio Mané (Liverpool) wins a free kick in the defensive half.", "5'", "West Bromwich Albion", "0", "0", "0", "0", "0", "0", "NA", "NA", "NA", "NA", "NA", "NA", "NA", "0", "NA", "NA", "0", "NA", "0", "0", "NA", "NA", "NA", "0", "NA", "NA", "NA", "0", "NA", "NA", "0", "NA", "1", "Sadio Mané", "Liverpool", "defensive half", "0", "NA", "NA", "0", "0", "NA", "NA", "NA", "0", "NA", "NA", "NA", "NA", "1", "9", "0", "NA", "NA", "5"], ["480559", "Attempt blocked. Mohamed Salah (Liverpool) left footed shot from the right side of the box is blocked. Assisted by Joseph Gomez.", "11'", "West Bromwich Albion", "0", "0", "0", "0", "1", "0", "blocked", "Mohamed Salah", "Liverpool", "left", "the right side of the box", "NA", "Joseph Gomez", "0", "NA", "NA", "0", "NA", "0", "0", "NA", "NA", "NA", "0", "NA", "NA", "NA", "0", "NA", "NA", "0", "NA", "0", "NA", "NA", "NA", "0", "NA", "NA", "0", "0", "NA", "NA", "NA", "0", "NA", "NA", "NA", "NA", "1", "10", "0", "NA", "NA", "11"], ["480559", "Corner,  Liverpool. Conceded by Jake Livermore.", "11'", "West Bromwich Albion", "0", "0", "0", "0", "0", "0", "NA", "NA", "NA", "NA", "NA", "NA", "NA", "0", "NA", "NA", "0", "NA", "0", "0", "NA", "NA", "NA", "0", "NA", "NA", "NA", "0", "NA", "NA", "0", "NA", "0", "NA", "NA", "NA", "1", "Liverpool", "Jake Livermore", "0", "0", "NA", "NA", "NA", "0", "NA", "NA", "NA", "NA", "1", "11", "0", "NA", "NA", "11"], ["480559", "Corner,  West Bromwich Albion. Conceded by Joseph Gomez.", "15'", "West Bromwich Albion", "0", "0", "0", "0", "0", "0", "NA", "NA", "NA", "NA", "NA", "NA", "NA", "0", "NA", "NA", "0", "NA", "0", "0", "NA", "NA", "NA", "0", "NA", "NA", "NA", "0", "NA", "NA", "0", "NA", "0", "NA", "NA", "NA", "1", "West Bromwich Albion", "Joseph Gomez", "0", "0", "NA", "NA", "NA", "0", "NA", "NA", "NA", "NA", "1", "12", "0", "NA", "NA", "15"], ["480559", "Offside, West Bromwich Albion. Craig Dawson tries a through ball, but Jake Livermore is caught offside.", "16'", "West Bromwich Albion", "0", "0", "0", "0", "0", "0", "NA", "NA", "NA", "NA", "NA", "NA", "NA", "0", "NA", "NA", "0", "NA", "0", "1", "West Bromwich Albion", "Jake Livermore", "Craig Dawson", "0", "NA", "NA", "NA", "0", "NA", "NA", "0", "NA", "0", "NA", "NA", "NA", "0", "NA", "NA", "0", "0", "NA", "NA", "NA", "0", "NA", "NA", "NA", "NA", "1", "13", "0", "NA", "NA", "16"], ["480559", "Attempt missed. Chris Brunt (West Bromwich Albion) right footed shot from outside the box is high and wide to the right.", "18'", "West Bromwich Albion", "0", "0", "0", "0", "1", "0", "missed", "Chris Brunt", "West Bromwich Albion", "right", "outside the box", "high and wide to the right", "NA", "0", "NA", "NA", "0", "NA", "0", "0", "NA", "NA", "NA", "0", "NA", "NA", "NA", "0", "NA", "NA", "0", "NA", "0", "NA", "NA", "NA", "0", "NA", "NA", "0", "0", "NA", "NA", "NA", "0", "NA", "NA", "NA", "NA", "1", "14", "0", "NA", "NA", "18"], ["480559", "Attempt saved. Matt Phillips (West Bromwich Albion) left footed shot from the right side of the box is saved in the bottom right corner. Assisted by Jay Rodriguez.", "22'", "West Bromwich Albion", "0", "0", "0", "0", "1", "0", "saved", "Matt Phillips", "West Bromwich Albion", "left", "the right side of the box", "the bottom right corner", "Jay Rodriguez", "0", "NA", "NA", "0", "NA", "0", "0", "NA", "NA", "NA", "0", "NA", "NA", "NA", "0", "NA", "NA", "0", "NA", "0", "NA", "NA", "NA", "0", "NA", "NA", "0", "0", "NA", "NA", "NA", "0", "NA", "NA", "NA", "NA", "1", "15", "0", "NA", "NA", "22"], ["480559", "Attempt missed. Danny Ings (Liverpool) header from the centre of the box is too high. Assisted by James Milner with a cross.", "24'", "West Bromwich Albion", "0", "0", "0", "0", "1", "0", "missed", "Danny Ings", "Liverpool", "header", "the centre of the box", "too high", "James Milner", "0", "NA", "NA", "0", "cross", "0", "0", "NA", "NA", "NA", "0", "NA", "NA", "NA", "0", "NA", "NA", "0", "NA", "0", "NA", "NA", "NA", "0", "NA", "NA", "0", "0", "NA", "NA", "NA", "0", "NA", "NA", "NA", "NA", "1", "16", "0", "NA", "NA", "24"], ["480559", "Foul by Ahmed Hegazi (West Bromwich Albion).", "25'", "West Bromwich Albion", "0", "0", "0", "0", "0", "0", "NA", "NA", "NA", "NA", "NA", "NA", "NA", "1", "Ahmed Hegazi", "West Bromwich Albion", "0", "NA", "0", "0", "NA", "NA", "NA", "0", "NA", "NA", "NA", "0", "NA", "NA", "0", "NA", "0", "NA", "NA", "NA", "0", "NA", "NA", "0", "0", "NA", "NA", "NA", "0", "NA", "NA", "NA", "NA", "1", "17", "0", "NA", "NA", "25"], ["480559", "Mohamed Salah (Liverpool) wins a free kick in the attacking half.", "25'", "West Bromwich Albion", "0", "0", "0", "0", "0", "0", "NA", "NA", "NA", "NA", "NA", "NA", "NA", "0", "NA", "NA", "0", "NA", "0", "0", "NA", "NA", "NA", "0", "NA", "NA", "NA", "0", "NA", "NA", "0", "NA", "1", "Mohamed Salah", "Liverpool", "attacking half", "0", "NA", "NA", "0", "0", "NA", "NA", "NA", "0", "NA", "NA", "NA", "NA", "1", "18", "0", "NA", "NA", "25"], ["480559", "Attempt missed. Mohamed Salah (Liverpool) left footed shot from outside the box is close, but misses to the right from a direct free kick.", "26'", "West Bromwich Albion", "0", "0", "0", "0", "1", "0", "missed", "Mohamed Salah", "Liverpool", "left", "outside the box", "close, but right", "NA", "0", "NA", "NA", "0", "NA", "0", "0", "NA", "NA", "NA", "0", "NA", "NA", "NA", "0", "NA", "NA", "0", "NA", "0", "NA", "NA", "NA", "0", "NA", "NA", "0", "0", "NA", "NA", "NA", "0", "NA", "NA", "NA", "NA", "1", "19", "0", "NA", "NA", "26"], ["480559", "Foul by Kieran Gibbs (West Bromwich Albion).", "27'", "West Bromwich Albion", "0", "0", "0", "0", "0", "0", "NA", "NA", "NA", "NA", "NA", "NA", "NA", "1", "Kieran Gibbs", "West Bromwich Albion", "0", "NA", "0", "0", "NA", "NA", "NA", "0", "NA", "NA", "NA", "0", "NA", "NA", "0", "NA", "0", "NA", "NA", "NA", "0", "NA", "NA", "0", "0", "NA", "NA", "NA", "0", "NA", "NA", "NA", "NA", "1", "20", "0", "NA", "NA", "27"], ["480559", "Mohamed Salah (Liverpool) wins a free kick in the attacking half.", "27'", "West Bromwich Albion", "0", "0", "0", "0", "0", "0", "NA", "NA", "NA", "NA", "NA", "NA", "NA", "0", "NA", "NA", "0", "NA", "0", "0", "NA", "NA", "NA", "0", "NA", "NA", "NA", "0", "NA", "NA", "0", "NA", "1", "Mohamed Salah", "Liverpool", "attacking half", "0", "NA", "NA", "0", "0", "NA", "NA", "NA", "0", "NA", "NA", "NA", "NA", "1", "21", "0", "NA", "NA", "27"], ["480559", "Danny Ings (Liverpool) wins a free kick in the defensive half.", "29'", "West Bromwich Albion", "0", "0", "0", "0", "0", "0", "NA", "NA", "NA", "NA", "NA", "NA", "NA", "0", "NA", "NA", "0", "NA", "0", "0", "NA", "NA", "NA", "0", "NA", "NA", "NA", "0", "NA", "NA", "0", "NA", "1", "Danny Ings", "Liverpool", "defensive half", "0", "NA", "NA", "0", "0", "NA", "NA", "NA", "0", "NA", "NA", "NA", "NA", "1", "22", "0", "NA", "NA", "29"], ["480559", "Foul by Salomón Rondón (West Bromwich Albion).", "29'", "West Bromwich Albion", "0", "0", "0", "0", "0", "0", "NA", "NA", "NA", "NA", "NA", "NA", "NA", "1", "Salomón Rondón", "West Bromwich Albion", "0", "NA", "0", "0", "NA", "NA", "NA", "0", "NA", "NA", "NA", "0", "NA", "NA", "0", "NA", "0", "NA", "NA", "NA", "0", "NA", "NA", "0", "0", "NA", "NA", "NA", "0", "NA", "NA", "NA", "NA", "1", "23", "0", "NA", "NA", "29"], ["480559", "Corner,  West Bromwich Albion. Conceded by Joseph Gomez.", "33'", "West Bromwich Albion", "0", "0", "0", "0", "0", "0", "NA", "NA", "NA", "NA", "NA", "NA", "NA", "0", "NA", "NA", "0", "NA", "0", "0", "NA", "NA", "NA", "0", "NA", "NA", "NA", "0", "NA", "NA", "0", "NA", "0", "NA", "NA", "NA", "1", "West Bromwich Albion", "Joseph Gomez", "0", "0", "NA", "NA", "NA", "0", "NA", "NA", "NA", "NA", "1", "24", "0", "NA", "NA", "33"], ["480559", "Corner,  West Bromwich Albion. Conceded by Joseph Gomez.", "34'", "West Bromwich Albion", "0", "0", "0", "0", "0", "0", "NA", "NA", "NA", "NA", "NA", "NA", "NA", "0", "NA", "NA", "0", "NA", "0", "0", "NA", "NA", "NA", "0", "NA", "NA", "NA", "0", "NA", "NA", "0", "NA", "0", "NA", "NA", "NA", "1", "West Bromwich Albion", "Joseph Gomez", "0", "0", "NA", "NA", "NA", "0", "NA", "NA", "NA", "NA", "1", "25", "0", "NA", "NA", "34"], ["480559", "Corner,  West Bromwich Albion. Conceded by Ragnar Klavan.", "35'", "West Bromwich Albion", "0", "0", "0", "0", "0", "0", "NA", "NA", "NA", "NA", "NA", "NA", "NA", "0", "NA", "NA", "0", "NA", "0", "0", "NA", "NA", "NA", "0", "NA", "NA", "NA", "0", "NA", "NA", "0", "NA", "0", "NA", "NA", "NA", "1", "West Bromwich Albion", "Ragnar Klavan", "0", "0", "NA", "NA", "NA", "0", "NA", "NA", "NA", "NA", "1", "26", "0", "NA", "NA", "35"], ["480559", "Corner,  West Bromwich Albion. Conceded by Danny Ings.", "36'", "West Bromwich Albion", "0", "0", "0", "0", "0", "0", "NA", "NA", "NA", "NA", "NA", "NA", "NA", "0", "NA", "NA", "0", "NA", "0", "0", "NA", "NA", "NA", "0", "NA", "NA", "NA", "0", "NA", "NA", "0", "NA", "0", "NA", "NA", "NA", "1", "West Bromwich Albion", "Danny Ings", "0", "0", "NA", "NA", "NA", "0", "NA", "NA", "NA", "NA", "1", "27", "0", "NA", "NA", "36"], ["480559", "Attempt missed. James McClean (West Bromwich Albion) left footed shot from a difficult angle on the left misses to the right. Assisted by Jake Livermore with a cross.", "37'", "West Bromwich Albion", "0", "0", "0", "0", "1", "0", "missed", "James McClean", "West Bromwich Albion", "left", "NA", "NA", "Jake Livermore", "0", "NA", "NA", "0", "cross", "0", "0", "NA", "NA", "NA", "0", "NA", "NA", "NA", "0", "NA", "NA", "0", "NA", "0", "NA", "NA", "NA", "0", "NA", "NA", "0", "0", "NA", "NA", "NA", "0", "NA", "NA", "NA", "NA", "1", "28", "0", "NA", "NA", "37"], ["480559", "Attempt saved. Danny Ings (Liverpool) left footed shot from the centre of the box is saved in the centre of the goal.", "42'", "West Bromwich Albion", "0", "0", "0", "0", "1", "0", "saved", "Danny Ings", "Liverpool", "left", "the centre of the box", "the centre of the goal", "NA", "0", "NA", "NA", "0", "NA", "0", "0", "NA", "NA", "NA", "0", "NA", "NA", "NA", "0", "NA", "NA", "0", "NA", "0", "NA", "NA", "NA", "0", "NA", "NA", "0", "0", "NA", "NA", "NA", "0", "NA", "NA", "NA", "NA", "1", "29", "0", "NA", "NA", "42"], ["480559", "Corner,  Liverpool. Conceded by Ahmed Hegazi.", "42'", "West Bromwich Albion", "0", "0", "0", "0", "0", "0", "NA", "NA", "NA", "NA", "NA", "NA", "NA", "0", "NA", "NA", "0", "NA", "0", "0", "NA", "NA", "NA", "0", "NA", "NA", "NA", "0", "NA", "NA", "0", "NA", "0", "NA", "NA", "NA", "1", "Liverpool", "Ahmed Hegazi", "0", "0", "NA", "NA", "NA", "0", "NA", "NA", "NA", "NA", "1", "30", "0", "NA", "NA", "42"], ["480559", "Attempt missed. Allan Nyom (West Bromwich Albion) right footed shot from more than 35 yards misses to the right.", "44'", "West Bromwich Albion", "0", "0", "0", "0", "1", "0", "missed", "Allan Nyom", "West Bromwich Albion", "right", "NA", "NA", "NA", "0", "NA", "NA", "0", "NA", "0", "0", "NA", "NA", "NA", "0", "NA", "NA", "NA", "0", "NA", "NA", "0", "NA", "0", "NA", "NA", "NA", "0", "NA", "NA", "0", "0", "NA", "NA", "NA", "0", "NA", "NA", "NA", "NA", "1", "31", "0", "NA", "NA", "44"], ["480559", "First Half ends, West Bromwich Albion 0, Liverpool 1.", "45'+2'", "West Bromwich Albion", "0", "1", "0", "0", "0", "0", "NA", "NA", "NA", "NA", "NA", "NA", "NA", "0", "NA", "NA", "0", "NA", "0", "0", "NA", "NA", "NA", "0", "NA", "NA", "NA", "0", "NA", "NA", "0", "NA", "0", "NA", "NA", "NA", "0", "NA", "NA", "0", "0", "NA", "NA", "NA", "0", "NA", "NA", "NA", "NA", "1", "32", "1", "NA", "NA", "47"], ["480559", "Second Half begins West Bromwich Albion 0, Liverpool 1.", "45'", "West Bromwich Albion", "0", "0", "0", "1", "0", "0", "NA", "NA", "NA", "NA", "NA", "NA", "NA", "0", "NA", "NA", "0", "NA", "0", "0", "NA", "NA", "NA", "0", "NA", "NA", "NA", "0", "NA", "NA", "0", "NA", "0", "NA", "NA", "NA", "0", "NA", "NA", "0", "0", "NA", "NA", "NA", "0", "NA", "NA", "NA", "NA", "2", "33", "0", "NA", "NA", "45"], ["480559", "Attempt missed. James McClean (West Bromwich Albion) left footed shot from outside the box misses to the right. Assisted by Matt Phillips.", "50'", "West Bromwich Albion", "0", "0", "0", "0", "1", "0", "missed", "James McClean", "West Bromwich Albion", "left", "outside the box", "right", "Matt Phillips", "0", "NA", "NA", "0", "NA", "0", "0", "NA", "NA", "NA", "0", "NA", "NA", "NA", "0", "NA", "NA", "0", "NA", "0", "NA", "NA", "NA", "0", "NA", "NA", "0", "0", "NA", "NA", "NA", "0", "NA", "NA", "NA", "NA", "2", "34", "0", "NA", "NA", "50"], ["480559", "Foul by Kieran Gibbs (West Bromwich Albion).", "51'", "West Bromwich Albion", "0", "0", "0", "0", "0", "0", "NA", "NA", "NA", "NA", "NA", "NA", "NA", "1", "Kieran Gibbs", "West Bromwich Albion", "0", "NA", "0", "0", "NA", "NA", "NA", "0", "NA", "NA", "NA", "0", "NA", "NA", "0", "NA", "0", "NA", "NA", "NA", "0", "NA", "NA", "0", "0", "NA", "NA", "NA", "0", "NA", "NA", "NA", "NA", "2", "35", "0", "NA", "NA", "51"], ["480559", "Sadio Mané (Liverpool) wins a free kick in the attacking half.", "51'", "West Bromwich Albion", "0", "0", "0", "0", "0", "0", "NA", "NA", "NA", "NA", "NA", "NA", "NA", "0", "NA", "NA", "0", "NA", "0", "0", "NA", "NA", "NA", "0", "NA", "NA", "NA", "0", "NA", "NA", "0", "NA", "1", "Sadio Mané", "Liverpool", "attacking half", "0", "NA", "NA", "0", "0", "NA", "NA", "NA", "0", "NA", "NA", "NA", "NA", "2", "36", "0", "NA", "NA", "51"], ["480559", "Foul by James Milner (Liverpool).", "52'", "West Bromwich Albion", "0", "0", "0", "0", "0", "0", "NA", "NA", "NA", "NA", "NA", "NA", "NA", "1", "James Milner", "Liverpool", "0", "NA", "0", "0", "NA", "NA", "NA", "0", "NA", "NA", "NA", "0", "NA", "NA", "0", "NA", "0", "NA", "NA", "NA", "0", "NA", "NA", "0", "0", "NA", "NA", "NA", "0", "NA", "NA", "NA", "NA", "2", "37", "0", "NA", "NA", "52"], ["480559", "Kieran Gibbs (West Bromwich Albion) wins a free kick in the defensive half.", "52'", "West Bromwich Albion", "0", "0", "0", "0", "0", "0", "NA", "NA", "NA", "NA", "NA", "NA", "NA", "0", "NA", "NA", "0", "NA", "0", "0", "NA", "NA", "NA", "0", "NA", "NA", "NA", "0", "NA", "NA", "0", "NA", "1", "Kieran Gibbs", "West Bromwich Albion", "defensive half", "0", "NA", "NA", "0", "0", "NA", "NA", "NA", "0", "NA", "NA", "NA", "NA", "2", "38", "0", "NA", "NA", "52"], ["480559", "Ahmed Hegazi (West Bromwich Albion) wins a free kick in the attacking half.", "55'", "West Bromwich Albion", "0", "0", "0", "0", "0", "0", "NA", "NA", "NA", "NA", "NA", "NA", "NA", "0", "NA", "NA", "0", "NA", "0", "0", "NA", "NA", "NA", "0", "NA", "NA", "NA", "0", "NA", "NA", "0", "NA", "1", "Ahmed Hegazi", "West Bromwich Albion", "attacking half", "0", "NA", "NA", "0", "0", "NA", "NA", "NA", "0", "NA", "NA", "NA", "NA", "2", "39", "0", "NA", "NA", "55"], ["480559", "Foul by Danny Ings (Liverpool).", "55'", "West Bromwich Albion", "0", "0", "0", "0", "0", "0", "NA", "NA", "NA", "NA", "NA", "NA", "NA", "1", "Danny Ings", "Liverpool", "0", "NA", "0", "0", "NA", "NA", "NA", "0", "NA", "NA", "NA", "0", "NA", "NA", "0", "NA", "0", "NA", "NA", "NA", "0", "NA", "NA", "0", "0", "NA", "NA", "NA", "0", "NA", "NA", "NA", "NA", "2", "40", "0", "NA", "NA", "55"], ["480559", "Attempt missed. Ahmed Hegazi (West Bromwich Albion) header from the centre of the box is high and wide to the left. Assisted by Chris Brunt with a cross following a set piece situation.", "56'", "West Bromwich Albion", "0", "0", "0", "0", "1", "0", "missed", "Ahmed Hegazi", "West Bromwich Albion", "header", "the centre of the box", "high and wide to the left", "Chris Brunt", "0", "NA", "NA", "1", "cross", "0", "0", "NA", "NA", "NA", "0", "NA", "NA", "NA", "0", "NA", "NA", "0", "NA", "0", "NA", "NA", "NA", "0", "NA", "NA", "0", "0", "NA", "NA", "NA", "0", "NA", "NA", "NA", "NA", "2", "41", "0", "NA", "NA", "56"], ["480559", "Ahmed Hegazi (West Bromwich Albion) wins a free kick in the defensive half.", "58'", "West Bromwich Albion", "0", "0", "0", "0", "0", "0", "NA", "NA", "NA", "NA", "NA", "NA", "NA", "0", "NA", "NA", "0", "NA", "0", "0", "NA", "NA", "NA", "0", "NA", "NA", "NA", "0", "NA", "NA", "0", "NA", "1", "Ahmed Hegazi", "West Bromwich Albion", "defensive half", "0", "NA", "NA", "0", "0", "NA", "NA", "NA", "0", "NA", "NA", "NA", "NA", "2", "42", "0", "NA", "NA", "58"], ["480559", "Foul by Danny Ings (Liverpool).", "58'", "West Bromwich Albion", "0", "0", "0", "0", "0", "0", "NA", "NA", "NA", "NA", "NA", "NA", "NA", "1", "Danny Ings", "Liverpool", "0", "NA", "0", "0", "NA", "NA", "NA", "0", "NA", "NA", "NA", "0", "NA", "NA", "0", "NA", "0", "NA", "NA", "NA", "0", "NA", "NA", "0", "0", "NA", "NA", "NA", "0", "NA", "NA", "NA", "NA", "2", "43", "0", "NA", "NA", "58"], ["480559", "Corner,  West Bromwich Albion. Conceded by Virgil van Dijk.", "59'", "West Bromwich Albion", "0", "0", "0", "0", "0", "0", "NA", "NA", "NA", "NA", "NA", "NA", "NA", "0", "NA", "NA", "0", "NA", "0", "0", "NA", "NA", "NA", "0", "NA", "NA", "NA", "0", "NA", "NA", "0", "NA", "0", "NA", "NA", "NA", "1", "West Bromwich Albion", "Virgil van Dijk", "0", "0", "NA", "NA", "NA", "0", "NA", "NA", "NA", "NA", "2", "44", "0", "NA", "NA", "59"], ["480559", "Offside, Liverpool. James Milner tries a through ball, but Mohamed Salah is caught offside.", "62'", "West Bromwich Albion", "0", "0", "0", "0", "0", "0", "NA", "NA", "NA", "NA", "NA", "NA", "NA", "0", "NA", "NA", "0", "NA", "0", "1", "Liverpool", "Mohamed Salah", "James Milner", "0", "NA", "NA", "NA", "0", "NA", "NA", "0", "NA", "0", "NA", "NA", "NA", "0", "NA", "NA", "0", "0", "NA", "NA", "NA", "0", "NA", "NA", "NA", "NA", "2", "45", "0", "NA", "NA", "62"], ["480559", "Attempt blocked. Mohamed Salah (Liverpool) left footed shot from outside the box is blocked. Assisted by James Milner.", "63'", "West Bromwich Albion", "0", "0", "0", "0", "1", "0", "blocked", "Mohamed Salah", "Liverpool", "left", "outside the box", "NA", "James Milner", "0", "NA", "NA", "0", "NA", "0", "0", "NA", "NA", "NA", "0", "NA", "NA", "NA", "0", "NA", "NA", "0", "NA", "0", "NA", "NA", "NA", "0", "NA", "NA", "0", "0", "NA", "NA", "NA", "0", "NA", "NA", "NA", "NA", "2", "46", "0", "NA", "NA", "63"], ["480559", "Foul by James McClean (West Bromwich Albion).", "64'", "West Bromwich Albion", "0", "0", "0", "0", "0", "0", "NA", "NA", "NA", "NA", "NA", "NA", "NA", "1", "James McClean", "West Bromwich Albion", "0", "NA", "0", "0", "NA", "NA", "NA", "0", "NA", "NA", "NA", "0", "NA", "NA", "0", "NA", "0", "NA", "NA", "NA", "0", "NA", "NA", "0", "0", "NA", "NA", "NA", "0", "NA", "NA", "NA", "NA", "2", "47", "0", "NA", "NA", "64"], ["480559", "Joseph Gomez (Liverpool) wins a free kick on the right wing.", "64'", "West Bromwich Albion", "0", "0", "0", "0", "0", "0", "NA", "NA", "NA", "NA", "NA", "NA", "NA", "0", "NA", "NA", "0", "NA", "0", "0", "NA", "NA", "NA", "0", "NA", "NA", "NA", "0", "NA", "NA", "0", "NA", "1", "Joseph Gomez", "Liverpool", "NA", "0", "NA", "NA", "0", "0", "NA", "NA", "NA", "0", "NA", "NA", "NA", "NA", "2", "48", "0", "NA", "NA", "64"], ["480559", "Substitution, Liverpool. Roberto Firmino replaces Danny Ings.", "66'", "West Bromwich Albion", "0", "0", "0", "0", "0", "0", "NA", "NA", "NA", "NA", "NA", "NA", "NA", "0", "NA", "NA", "0", "NA", "0", "0", "NA", "NA", "NA", "0", "NA", "NA", "NA", "0", "NA", "NA", "0", "NA", "0", "NA", "NA", "NA", "0", "NA", "NA", "1", "0", "Liverpool", "Roberto Firmino", "Danny Ings", "0", "NA", "NA", "NA", "NA", "2", "49", "0", "NA", "NA", "66"], ["480559", "Substitution, Liverpool. Alex Oxlade-Chamberlain replaces Sadio Mané.", "66'", "West Bromwich Albion", "0", "0", "0", "0", "0", "0", "NA", "NA", "NA", "NA", "NA", "NA", "NA", "0", "NA", "NA", "0", "NA", "0", "0", "NA", "NA", "NA", "0", "NA", "NA", "NA", "0", "NA", "NA", "0", "NA", "0", "NA", "NA", "NA", "0", "NA", "NA", "1", "0", "Liverpool", "Alex Oxlade-Chamberlain", "Sadio Mané", "0", "NA", "NA", "NA", "NA", "2", "50", "0", "NA", "NA", "66"], ["480559", "Foul by Alberto Moreno (Liverpool).", "69'", "West Bromwich Albion", "0", "0", "0", "0", "0", "0", "NA", "NA", "NA", "NA", "NA", "NA", "NA", "1", "Alberto Moreno", "Liverpool", "0", "NA", "0", "0", "NA", "NA", "NA", "0", "NA", "NA", "NA", "0", "NA", "NA", "0", "NA", "0", "NA", "NA", "NA", "0", "NA", "NA", "0", "0", "NA", "NA", "NA", "0", "NA", "NA", "NA", "NA", "2", "51", "0", "NA", "NA", "69"], ["480559", "Matt Phillips (West Bromwich Albion) wins a free kick on the right wing.", "69'", "West Bromwich Albion", "0", "0", "0", "0", "0", "0", "NA", "NA", "NA", "NA", "NA", "NA", "NA", "0", "NA", "NA", "0", "NA", "0", "0", "NA", "NA", "NA", "0", "NA", "NA", "NA", "0", "NA", "NA", "0", "NA", "1", "Matt Phillips", "West Bromwich Albion", "NA", "0", "NA", "NA", "0", "0", "NA", "NA", "NA", "0", "NA", "NA", "NA", "NA", "2", "52", "0", "NA", "NA", "69"], ["480559", "Alberto Moreno (Liverpool) is shown the yellow card for a bad foul.", "69'", "West Bromwich Albion", "0", "0", "0", "0", "0", "0", "NA", "NA", "NA", "NA", "NA", "NA", "NA", "0", "NA", "NA", "0", "NA", "0", "0", "NA", "NA", "NA", "1", "yellow", "Alberto Moreno", "Liverpool", "0", "NA", "NA", "0", "NA", "0", "NA", "NA", "NA", "0", "NA", "NA", "0", "0", "NA", "NA", "NA", "0", "NA", "NA", "NA", "NA", "2", "53", "0", "NA", "NA", "69"], ["480559", "Attempt missed. Craig Dawson (West Bromwich Albion) right footed shot from the centre of the box is close, but misses to the right following a set piece situation.", "70'", "West Bromwich Albion", "0", "0", "0", "0", "1", "0", "missed", "Craig Dawson", "West Bromwich Albion", "right", "the centre of the box", "close, but right", "NA", "0", "NA", "NA", "1", "NA", "0", "0", "NA", "NA", "NA", "0", "NA", "NA", "NA", "0", "NA", "NA", "0", "NA", "0", "NA", "NA", "NA", "0", "NA", "NA", "0", "0", "NA", "NA", "NA", "0", "NA", "NA", "NA", "NA", "2", "54", "0", "NA", "NA", "70"], ["480559", "Attempt saved. Salomón Rondón (West Bromwich Albion) right footed shot from the centre of the box is saved in the bottom right corner.", "70'", "West Bromwich Albion", "0", "0", "0", "0", "1", "0", "saved", "Salomón Rondón", "West Bromwich Albion", "right", "the centre of the box", "the bottom right corner", "NA", "0", "NA", "NA", "0", "NA", "0", "0", "NA", "NA", "NA", "0", "NA", "NA", "NA", "0", "NA", "NA", "0", "NA", "0", "NA", "NA", "NA", "0", "NA", "NA", "0", "0", "NA", "NA", "NA", "0", "NA", "NA", "NA", "NA", "2", "55", "0", "NA", "NA", "70"], ["480559", "Substitution, West Bromwich Albion. Jonny Evans replaces James McClean.", "71'", "West Bromwich Albion", "0", "0", "0", "0", "0", "0", "NA", "NA", "NA", "NA", "NA", "NA", "NA", "0", "NA", "NA", "0", "NA", "0", "0", "NA", "NA", "NA", "0", "NA", "NA", "NA", "0", "NA", "NA", "0", "NA", "0", "NA", "NA", "NA", "0", "NA", "NA", "1", "0", "West Bromwich Albion", "Jonny Evans", "James McClean", "0", "NA", "NA", "NA", "NA", "2", "56", "0", "NA", "NA", "71"], ["480559", "Goal!  West Bromwich Albion 0, Liverpool 2. Mohamed Salah (Liverpool) left footed shot from the centre of the box to the high centre of the goal. Assisted by Alex Oxlade-Chamberlain.", "72'", "West Bromwich Albion", "0", "0", "0", "0", "1", "0", "goal", "Mohamed Salah", "Liverpool", "left", "the centre of the box", "high centre of the goal", "Alex Oxlade-Chamberlain", "0", "NA", "NA", "0", "NA", "0", "0", "NA", "NA", "NA", "0", "NA", "NA", "NA", "0", "NA", "NA", "0", "NA", "0", "NA", "NA", "NA", "0", "NA", "NA", "0", "0", "NA", "NA", "NA", "0", "NA", "NA", "NA", "NA", "2", "57", "0", "NA", "NA", "72"], ["480559", "Alex Oxlade-Chamberlain (Liverpool) wins a free kick in the attacking half.", "74'", "West Bromwich Albion", "0", "0", "0", "0", "0", "0", "NA", "NA", "NA", "NA", "NA", "NA", "NA", "0", "NA", "NA", "0", "NA", "0", "0", "NA", "NA", "NA", "0", "NA", "NA", "NA", "0", "NA", "NA", "0", "NA", "1", "Alex Oxlade-Chamberlain", "Liverpool", "attacking half", "0", "NA", "NA", "0", "0", "NA", "NA", "NA", "0", "NA", "NA", "NA", "NA", "2", "58", "0", "NA", "NA", "74"], ["480559", "Foul by Jonny Evans (West Bromwich Albion).", "74'", "West Bromwich Albion", "0", "0", "0", "0", "0", "0", "NA", "NA", "NA", "NA", "NA", "NA", "NA", "1", "Jonny Evans", "West Bromwich Albion", "0", "NA", "0", "0", "NA", "NA", "NA", "0", "NA", "NA", "NA", "0", "NA", "NA", "0", "NA", "0", "NA", "NA", "NA", "0", "NA", "NA", "0", "0", "NA", "NA", "NA", "0", "NA", "NA", "NA", "NA", "2", "59", "0", "NA", "NA", "74"], ["480559", "Substitution, West Bromwich Albion. Oliver Burke replaces Kieran Gibbs.", "76'", "West Bromwich Albion", "0", "0", "0", "0", "0", "0", "NA", "NA", "NA", "NA", "NA", "NA", "NA", "0", "NA", "NA", "0", "NA", "0", "0", "NA", "NA", "NA", "0", "NA", "NA", "NA", "0", "NA", "NA", "0", "NA", "0", "NA", "NA", "NA", "0", "NA", "NA", "1", "0", "West Bromwich Albion", "Oliver Burke", "Kieran Gibbs", "0", "NA", "NA", "NA", "NA", "2", "60", "0", "NA", "NA", "76"], ["480559", "Corner,  West Bromwich Albion. Conceded by Ragnar Klavan.", "78'", "West Bromwich Albion", "0", "0", "0", "0", "0", "0", "NA", "NA", "NA", "NA", "NA", "NA", "NA", "0", "NA", "NA", "0", "NA", "0", "0", "NA", "NA", "NA", "0", "NA", "NA", "NA", "0", "NA", "NA", "0", "NA", "0", "NA", "NA", "NA", "1", "West Bromwich Albion", "Ragnar Klavan", "0", "0", "NA", "NA", "NA", "0", "NA", "NA", "NA", "NA", "2", "61", "0", "NA", "NA", "78"], ["480559", "Attempt saved. Craig Dawson (West Bromwich Albion) left footed shot from the centre of the box is saved in the centre of the goal. Assisted by Jay Rodriguez.", "79'", "West Bromwich Albion", "0", "0", "0", "0", "1", "0", "saved", "Craig Dawson", "West Bromwich Albion", "left", "the centre of the box", "the centre of the goal", "Jay Rodriguez", "0", "NA", "NA", "0", "NA", "0", "0", "NA", "NA", "NA", "0", "NA", "NA", "NA", "0", "NA", "NA", "0", "NA", "0", "NA", "NA", "NA", "0", "NA", "NA", "0", "0", "NA", "NA", "NA", "0", "NA", "NA", "NA", "NA", "2", "62", "0", "NA", "NA", "79"], ["480559", "Goal!  West Bromwich Albion 1, Liverpool 2. Jake Livermore (West Bromwich Albion) right footed shot from very close range to the centre of the goal following a corner.", "79'", "West Bromwich Albion", "1", "0", "0", "0", "1", "0", "goal", "Jake Livermore", "West Bromwich Albion", "right", "right shot very close range", "centre of the goal following a corner", "NA", "0", "NA", "NA", "0", "NA", "1", "0", "NA", "NA", "NA", "0", "NA", "NA", "NA", "0", "NA", "NA", "0", "NA", "0", "NA", "NA", "NA", "0", "NA", "NA", "0", "0", "NA", "NA", "NA", "0", "NA", "NA", "NA", "NA", "2", "63", "0", "NA", "NA", "79"], ["480559", "Offside, Liverpool. Loris Karius tries a through ball, but Mohamed Salah is caught offside.", "80'", "West Bromwich Albion", "1", "0", "0", "0", "0", "0", "NA", "NA", "NA", "NA", "NA", "NA", "NA", "0", "NA", "NA", "0", "NA", "0", "1", "Liverpool", "Mohamed Salah", "Loris Karius", "0", "NA", "NA", "NA", "0", "NA", "NA", "0", "NA", "0", "NA", "NA", "NA", "0", "NA", "NA", "0", "0", "NA", "NA", "NA", "0", "NA", "NA", "NA", "NA", "2", "64", "0", "NA", "NA", "80"], ["480559", "Hand ball by Jonny Evans (West Bromwich Albion).", "80'", "West Bromwich Albion", "1", "0", "0", "0", "0", "0", "NA", "NA", "NA", "NA", "NA", "NA", "NA", "0", "NA", "NA", "0", "NA", "0", "0", "NA", "NA", "NA", "0", "NA", "NA", "NA", "0", "NA", "NA", "0", "NA", "0", "NA", "NA", "NA", "0", "NA", "NA", "0", "0", "NA", "NA", "NA", "0", "NA", "NA", "NA", "NA", "2", "65", "0", "NA", "NA", "80"], ["480559", "Foul by Salomón Rondón (West Bromwich Albion).", "83'", "West Bromwich Albion", "1", "0", "0", "0", "0", "0", "NA", "NA", "NA", "NA", "NA", "NA", "NA", "1", "Salomón Rondón", "West Bromwich Albion", "0", "NA", "0", "0", "NA", "NA", "NA", "0", "NA", "NA", "NA", "0", "NA", "NA", "0", "NA", "0", "NA", "NA", "NA", "0", "NA", "NA", "0", "0", "NA", "NA", "NA", "0", "NA", "NA", "NA", "NA", "2", "66", "0", "NA", "NA", "83"], ["480559", "Ragnar Klavan (Liverpool) wins a free kick in the defensive half.", "83'", "West Bromwich Albion", "1", "0", "0", "0", "0", "0", "NA", "NA", "NA", "NA", "NA", "NA", "NA", "0", "NA", "NA", "0", "NA", "0", "0", "NA", "NA", "NA", "0", "NA", "NA", "NA", "0", "NA", "NA", "0", "NA", "1", "Ragnar Klavan", "Liverpool", "defensive half", "0", "NA", "NA", "0", "0", "NA", "NA", "NA", "0", "NA", "NA", "NA", "NA", "2", "67", "0", "NA", "NA", "83"], ["480559", "Substitution, Liverpool. Dejan Lovren replaces Mohamed Salah.", "84'", "West Bromwich Albion", "1", "0", "0", "0", "0", "0", "NA", "NA", "NA", "NA", "NA", "NA", "NA", "0", "NA", "NA", "0", "NA", "0", "0", "NA", "NA", "NA", "0", "NA", "NA", "NA", "0", "NA", "NA", "0", "NA", "0", "NA", "NA", "NA", "0", "NA", "NA", "1", "0", "Liverpool", "Dejan Lovren", "Mohamed Salah", "0", "NA", "NA", "NA", "NA", "2", "68", "0", "NA", "NA", "84"], ["480559", "Foul by Allan Nyom (West Bromwich Albion).", "84'", "West Bromwich Albion", "1", "0", "0", "0", "0", "0", "NA", "NA", "NA", "NA", "NA", "NA", "NA", "1", "Allan Nyom", "West Bromwich Albion", "0", "NA", "0", "0", "NA", "NA", "NA", "0", "NA", "NA", "NA", "0", "NA", "NA", "0", "NA", "0", "NA", "NA", "NA", "0", "NA", "NA", "0", "0", "NA", "NA", "NA", "0", "NA", "NA", "NA", "NA", "2", "69", "0", "NA", "NA", "84"], ["480559", "James Milner (Liverpool) wins a free kick on the left wing.", "84'", "West Bromwich Albion", "1", "0", "0", "0", "0", "0", "NA", "NA", "NA", "NA", "NA", "NA", "NA", "0", "NA", "NA", "0", "NA", "0", "0", "NA", "NA", "NA", "0", "NA", "NA", "NA", "0", "NA", "NA", "0", "NA", "1", "James Milner", "Liverpool", "NA", "0", "NA", "NA", "0", "0", "NA", "NA", "NA", "0", "NA", "NA", "NA", "NA", "2", "70", "0", "NA", "NA", "84"], ["480559", "Attempt missed. Roberto Firmino (Liverpool) header from the left side of the box misses to the right. Assisted by Alex Oxlade-Chamberlain with a cross.", "86'", "West Bromwich Albion", "1", "0", "0", "0", "1", "0", "missed", "Roberto Firmino", "Liverpool", "header", "the left side of the box", "right", "Alex Oxlade-Chamberlain", "0", "NA", "NA", "0", "cross", "0", "0", "NA", "NA", "NA", "0", "NA", "NA", "NA", "0", "NA", "NA", "0", "NA", "0", "NA", "NA", "NA", "0", "NA", "NA", "0", "0", "NA", "NA", "NA", "0", "NA", "NA", "NA", "NA", "2", "71", "0", "NA", "NA", "86"], ["480559", "Attempt saved. Salomón Rondón (West Bromwich Albion) right footed shot from the centre of the box is saved in the centre of the goal.", "86'", "West Bromwich Albion", "1", "0", "0", "0", "1", "0", "saved", "Salomón Rondón", "West Bromwich Albion", "right", "the centre of the box", "the centre of the goal", "NA", "0", "NA", "NA", "0", "NA", "0", "0", "NA", "NA", "NA", "0", "NA", "NA", "NA", "0", "NA", "NA", "0", "NA", "0", "NA", "NA", "NA", "0", "NA", "NA", "0", "0", "NA", "NA", "NA", "0", "NA", "NA", "NA", "NA", "2", "72", "0", "NA", "NA", "86"], ["480559", "Foul by Joseph Gomez (Liverpool).", "88'", "West Bromwich Albion", "1", "0", "0", "0", "0", "0", "NA", "NA", "NA", "NA", "NA", "NA", "NA", "1", "Joseph Gomez", "Liverpool", "0", "NA", "0", "0", "NA", "NA", "NA", "0", "NA", "NA", "NA", "0", "NA", "NA", "0", "NA", "0", "NA", "NA", "NA", "0", "NA", "NA", "0", "0", "NA", "NA", "NA", "0", "NA", "NA", "NA", "NA", "2", "73", "0", "NA", "NA", "88"], ["480559", "Oliver Burke (West Bromwich Albion) wins a free kick on the left wing.", "88'", "West Bromwich Albion", "1", "0", "0", "0", "0", "0", "NA", "NA", "NA", "NA", "NA", "NA", "NA", "0", "NA", "NA", "0", "NA", "0", "0", "NA", "NA", "NA", "0", "NA", "NA", "NA", "0", "NA", "NA", "0", "NA", "1", "Oliver Burke", "West Bromwich Albion", "NA", "0", "NA", "NA", "0", "0", "NA", "NA", "NA", "0", "NA", "NA", "NA", "NA", "2", "74", "0", "NA", "NA", "88"], ["480559", "Goal!  West Bromwich Albion 2, Liverpool 2. Salomón Rondón (West Bromwich Albion) header from the centre of the box to the bottom left corner. Assisted by Chris Brunt with a cross following a set piece situation.", "88'", "West Bromwich Albion", "2", "0", "0", "0", "1", "0", "goal", "Salomón Rondón", "West Bromwich Albion", "header", "the centre of the box", "bottom left corner", "Chris Brunt", "0", "NA", "NA", "1", "cross", "0", "0", "NA", "NA", "NA", "0", "NA", "NA", "NA", "0", "NA", "NA", "0", "NA", "0", "NA", "NA", "NA", "0", "NA", "NA", "0", "0", "NA", "NA", "NA", "0", "NA", "NA", "NA", "NA", "2", "75", "0", "NA", "NA", "88"], ["480559", "Substitution, West Bromwich Albion. Hal Robson-Kanu replaces Jay Rodriguez.", "89'", "West Bromwich Albion", "2", "0", "0", "0", "0", "0", "NA", "NA", "NA", "NA", "NA", "NA", "NA", "0", "NA", "NA", "0", "NA", "0", "0", "NA", "NA", "NA", "0", "NA", "NA", "NA", "0", "NA", "NA", "0", "NA", "0", "NA", "NA", "NA", "0", "NA", "NA", "1", "0", "West Bromwich Albion", "Hal Robson-Kanu", "Jay Rodriguez", "0", "NA", "NA", "NA", "NA", "2", "76", "0", "NA", "NA", "89"], ["480559", "Attempt blocked. Matt Phillips (West Bromwich Albion) header from the centre of the box is blocked. Assisted by Salomón Rondón with a cross.", "90'+2'", "West Bromwich Albion", "2", "0", "0", "0", "1", "0", "blocked", "Matt Phillips", "West Bromwich Albion", "header", "the centre of the box", "NA", "Salomón Rondón", "0", "NA", "NA", "0", "cross", "0", "0", "NA", "NA", "NA", "0", "NA", "NA", "NA", "0", "NA", "NA", "0", "NA", "0", "NA", "NA", "NA", "0", "NA", "NA", "0", "0", "NA", "NA", "NA", "0", "NA", "NA", "NA", "NA", "2", "77", "1", "NA", "NA", "92"], ["480559", "Attempt missed. James Milner (Liverpool) left footed shot from outside the box is too high. Assisted by Alex Oxlade-Chamberlain.", "90'+3'", "West Bromwich Albion", "2", "0", "0", "0", "1", "0", "missed", "James Milner", "Liverpool", "left", "outside the box", "too high", "Alex Oxlade-Chamberlain", "0", "NA", "NA", "0", "NA", "0", "0", "NA", "NA", "NA", "0", "NA", "NA", "NA", "0", "NA", "NA", "0", "NA", "0", "NA", "NA", "NA", "0", "NA", "NA", "0", "0", "NA", "NA", "NA", "0", "NA", "NA", "NA", "NA", "2", "78", "1", "NA", "NA", "93"], ["480559", "Foul by Craig Dawson (West Bromwich Albion).", "90'+4'", "West Bromwich Albion", "2", "0", "0", "0", "0", "0", "NA", "NA", "NA", "NA", "NA", "NA", "NA", "1", "Craig Dawson", "West Bromwich Albion", "0", "NA", "0", "0", "NA", "NA", "NA", "0", "NA", "NA", "NA", "0", "NA", "NA", "0", "NA", "0", "NA", "NA", "NA", "0", "NA", "NA", "0", "0", "NA", "NA", "NA", "0", "NA", "NA", "NA", "NA", "2", "79", "1", "NA", "NA", "94"], ["480559", "Roberto Firmino (Liverpool) wins a free kick in the defensive half.", "90'+4'", "West Bromwich Albion", "2", "0", "0", "0", "0", "0", "NA", "NA", "NA", "NA", "NA", "NA", "NA", "0", "NA", "NA", "0", "NA", "0", "0", "NA", "NA", "NA", "0", "NA", "NA", "NA", "0", "NA", "NA", "0", "NA", "1", "Roberto Firmino", "Liverpool", "defensive half", "0", "NA", "NA", "0", "0", "NA", "NA", "NA", "0", "NA", "NA", "NA", "NA", "2", "80", "1", "NA", "NA", "94"], ["480559", "Second Half ends, West Bromwich Albion 2, Liverpool 2.", "90'+5'", "West Bromwich Albion", "2", "1", "0", "0", "0", "0", "NA", "NA", "NA", "NA", "NA", "NA", "NA", "0", "NA", "NA", "0", "NA", "0", "0", "NA", "NA", "NA", "0", "NA", "NA", "NA", "0", "NA", "NA", "0", "NA", "0", "NA", "NA", "NA", "0", "NA", "NA", "0", "0", "NA", "NA", "NA", "0", "NA", "NA", "NA", "NA", "2", "81", "1", "NA", "NA", "95"], ["480559", "Match ends, West Bromwich Albion 2, Liverpool 2.", "90'+5'", "West Bromwich Albion", "2", "0", "1", "0", "0", "0", "NA", "NA", "NA", "NA", "NA", "NA", "NA", "0", "NA", "NA", "0", "NA", "0", "0", "NA", "NA", "NA", "0", "NA", "NA", "NA", "0", "NA", "NA", "0", "NA", "0", "NA", "NA", "NA", "0", "NA", "NA", "0", "0", "NA", "NA", "NA", "0", "NA", "NA", "NA", "NA", "2", "82", "1", "NA", "NA", "95"]], "Lineup": {"Home Player 9": "Matt Phillips", "Home Player 8": "Allan Nyom", "Home Player 5": "Ahmed Hegazy", "Home Player 4": "Kieran Gibbs", "Home Player 7": "James Mcclean", "Home Player 6": "Jake Livermore", "Home Player 1": "Chris Brunt", "Home Player 3": "Ben Foster", "Home Player 2": "Craig Dawson", "Away Player 10": "Virgil van Dijk", "Away Player 11": "Georginio Wijnaldum", "Away Player 8": "Alberto Moreno", "Away Player 9": "Mohamed Salah", "Away Player 1": "Joe Gomez", "Away Player 2": "Jordan Henderson", "Away Player 3": "Danny Ings", "Away Player 4": "Loris Karius", "Away Player 5": "Ragnar Klavan", "Away Player 6": "Sadio Mane", "Away Player 7": "James Milner", "Game ID": "g_1_AsOgRp52", "Home Player 11": "Salomon Rondon", "Home Player 10": "Jay Rodriguez"}}