{"Stats": {"Full Time Result": "H", "Away Team Corners": 5, "Referee": "A Marriner", "Home Team Fouls Committed": 6, "Home Team Corners": 4, "Away Team Shots": 6, "Away Team Red Cards": 0, "Home Team Red Cards": 0, "Half Time Away Team Goals": 0, "Full Time Home Team Goals": 5, "Away Team Yellow Cards": 1, "Away Team Shots on Target": 2, "Half Time Home Team Goals": 2, "Half Time Result": "H", "Home Team Yellow Cards": 0, "Home Team Shots": 16, "Div": "E0", "Away Team Fouls Committed": 7, "Home Team Shots on Target": 8, "Full Time Away Team Goals": 0}, "Description": "Attempt saved. Alex Iwobi (Arsenal) right footed shot from outside the box is saved in the bottom right corner. Assisted by Henrikh Mkhitaryan. at minute 8. Corner,  Arsenal. Conceded by Kevin Long. at minute 10. Attempt missed. Alexandre Lacazette (Arsenal) right footed shot from the right side of the box misses to the left. Assisted by Alex Iwobi with a through ball. at minute 14. Goal!  Arsenal 1, Burnley 0. Pierre-Emerick Aubameyang (Arsenal) right footed shot from very close range to the centre of the goal. Assisted by Alexandre Lacazette. at minute 14. Delay in match Ashley Barnes (Burnley) because of an injury. at minute 19. Delay in match Granit Xhaka (Arsenal) because of an injury. at minute 19. Delay over. They are ready to continue. at minute 21. Substitution, Burnley. Sam Vokes replaces Ashley Barnes because of an injury. at minute 22. Corner,  Burnley. Conceded by Héctor Bellerín. at minute 24. Foul by Héctor Bellerín (Arsenal). at minute 28. Jack Cork (Burnley) wins a free kick in the defensive half. at minute 28. Alex Iwobi (Arsenal) wins a free kick in the defensive half. at minute 30. Foul by Jack Cork (Burnley). at minute 30. Attempt missed. Henrikh Mkhitaryan (Arsenal) right footed shot from the centre of the box is too high. Assisted by Alexandre Lacazette. at minute 33. Attempt blocked. Alex Iwobi (Arsenal) right footed shot from the right side of the box is blocked. Assisted by Jack Wilshere. at minute 34. Foul by Konstantinos Mavropanos (Arsenal). at minute 35. Sam Vokes (Burnley) wins a free kick in the defensive half. at minute 35. Foul by Sam Vokes (Burnley). at minute 36. Konstantinos Mavropanos (Arsenal) wins a free kick in the defensive half. at minute 36. Corner,  Arsenal. Conceded by Kevin Long. at minute 37. Delay in match Konstantinos Mavropanos (Arsenal) because of an injury. at minute 39. Delay in match Sam Vokes (Burnley) because of an injury. at minute 39. Delay over. They are ready to continue. at minute 40. Foul by Jeff Hendrick (Burnley). at minute 43. Granit Xhaka (Arsenal) wins a free kick on the left wing. at minute 43. Attempt saved. Henrikh Mkhitaryan (Arsenal) right footed shot from outside the box is saved in the centre of the goal. Assisted by Alexandre Lacazette. at minute 43. Foul by Sam Vokes (Burnley). at minute 44. Konstantinos Mavropanos (Arsenal) wins a free kick in the defensive half. at minute 44. James Tarkowski (Burnley) is shown the yellow card for a bad foul. at minute 44. Foul by Kevin Long (Burnley). at minute 45. Pierre-Emerick Aubameyang (Arsenal) wins a free kick on the left wing. at minute 45. Goal!  Arsenal 2, Burnley 0. Alexandre Lacazette (Arsenal) left footed shot from the centre of the box to the bottom right corner. Assisted by Héctor Bellerín. at minute 48. First Half ends, Arsenal 2, Burnley 0. at minute 50. Second Half begins Arsenal 2, Burnley 0. at minute 45. Attempt missed. Jack Wilshere (Arsenal) left footed shot from the centre of the box is just a bit too high. Assisted by Pierre-Emerick Aubameyang. at minute 46. Corner,  Arsenal. Conceded by Aaron Lennon. at minute 48. Attempt saved. Sam Vokes (Burnley) header from the centre of the box is saved in the centre of the goal. Assisted by Jeff Hendrick with a cross. at minute 49. Goal!  Arsenal 3, Burnley 0. Sead Kolasinac (Arsenal) left footed shot from the left side of the box to the bottom right corner. Assisted by Jack Wilshere. at minute 54. Attempt missed. Henrikh Mkhitaryan (Arsenal) left footed shot from the right side of the box is close, but misses to the left. Assisted by Alex Iwobi. at minute 55. Aaron Lennon (Burnley) wins a free kick on the right wing. at minute 56. Foul by Sead Kolasinac (Arsenal). at minute 56. Foul by Alexandre Lacazette (Arsenal). at minute 57. Johann Berg Gudmundsson (Burnley) wins a free kick in the defensive half. at minute 57. Attempt blocked. Jeff Hendrick (Burnley) right footed shot from outside the box is blocked. Assisted by Johann Berg Gudmundsson. at minute 60. Corner,  Burnley. Conceded by Konstantinos Mavropanos. at minute 60. Attempt missed. Kevin Long (Burnley) header from the left side of the six yard box misses to the right. Assisted by Johann Berg Gudmundsson with a cross following a corner. at minute 61. Corner,  Burnley. Conceded by Calum Chambers. at minute 62. Corner,  Burnley. Conceded by Granit Xhaka. at minute 63. Attempt blocked. Kevin Long (Burnley) header from the centre of the box is blocked. Assisted by Johann Berg Gudmundsson with a cross. at minute 63. Goal!  Arsenal 4, Burnley 0. Alex Iwobi (Arsenal) left footed shot from the centre of the box to the top left corner. Assisted by Pierre-Emerick Aubameyang. at minute 64. Foul by Ashley Westwood (Burnley). at minute 66. Jack Wilshere (Arsenal) wins a free kick in the attacking half. at minute 66. Attempt blocked. Sead Kolasinac (Arsenal) right footed shot from the left side of the box is blocked. Assisted by Alexandre Lacazette. at minute 67. Foul by Granit Xhaka (Arsenal). at minute 69. Jeff Hendrick (Burnley) wins a free kick on the left wing. at minute 69. Corner,  Burnley. Conceded by Granit Xhaka. at minute 69. Substitution, Burnley. Georges-Kévin Nkoudou replaces Aaron Lennon. at minute 71. Substitution, Arsenal. Aaron Ramsey replaces Jack Wilshere. at minute 72. Substitution, Arsenal. Danny Welbeck replaces Alexandre Lacazette. at minute 72. Foul by Calum Chambers (Arsenal). at minute 73. Sam Vokes (Burnley) wins a free kick on the left wing. at minute 73. Attempt missed. Jeff Hendrick (Burnley) right footed shot from outside the box misses to the left. at minute 73. Attempt saved. Johann Berg Gudmundsson (Burnley) left footed shot from outside the box is saved in the bottom right corner. at minute 74. Goal!  Arsenal 5, Burnley 0. Pierre-Emerick Aubameyang (Arsenal) right footed shot from the centre of the box to the top left corner. Assisted by Héctor Bellerín. at minute 75. Substitution, Arsenal. Per Mertesacker replaces Calum Chambers. at minute 77. Attempt missed. Héctor Bellerín (Arsenal) left footed shot from the centre of the box is too high. at minute 81. Foul by Matthew Lowton (Burnley). at minute 82. Konstantinos Mavropanos (Arsenal) wins a free kick in the defensive half. at minute 82. Corner,  Arsenal. Conceded by Matthew Lowton. at minute 86. Attempt blocked. Danny Welbeck (Arsenal) right footed shot from outside the box is blocked. Assisted by Henrikh Mkhitaryan. at minute 88. Substitution, Burnley. Nahki Wells replaces Johann Berg Gudmundsson. at minute 89. Attempt saved. Aaron Ramsey (Arsenal) left footed shot from a difficult angle on the left is saved in the top centre of the goal. Assisted by Henrikh Mkhitaryan with a through ball. at minute 90. Second Half ends, Arsenal 5, Burnley 0. at minute 91. Match ends, Arsenal 5, Burnley 0. at minute 91. ", "Home Team": "Arsenal", "Away Team": "Burnley", "Date": "06-05-2018", "Commentary": [["480536", "First Half begins.", "-", "Arsenal", "0", "0", "0", "1", "0", "0", "NA", "NA", "NA", "NA", "NA", "NA", "NA", "0", "NA", "NA", "0", "NA", "0", "0", "NA", "NA", "NA", "0", "NA", "NA", "NA", "0", "NA", "NA", "0", "NA", "0", "NA", "NA", "NA", "0", "NA", "NA", "0", "0", "NA", "NA", "NA", "0", "NA", "NA", "NA", "NA", "1", "1", "0", "NA", "NA", "NA"], ["480536", "Lineups are announced and players are warming up.", "-", "Arsenal", "0", "0", "0", "0", "0", "0", "NA", "NA", "NA", "NA", "NA", "NA", "NA", "0", "NA", "NA", "0", "NA", "0", "0", "NA", "NA", "NA", "0", "NA", "NA", "NA", "0", "NA", "NA", "0", "NA", "0", "NA", "NA", "NA", "0", "NA", "NA", "0", "0", "NA", "NA", "NA", "0", "NA", "NA", "NA", "NA", "1", "2", "0", "NA", "NA", "NA"], ["480536", "Attempt saved. Alex Iwobi (Arsenal) right footed shot from outside the box is saved in the bottom right corner. Assisted by Henrikh Mkhitaryan.", "8'", "Arsenal", "0", "0", "0", "0", "1", "0", "saved", "Alex Iwobi", "Arsenal", "right", "outside the box", "the bottom right corner", "Henrikh Mkhitaryan", "0", "NA", "NA", "0", "NA", "0", "0", "NA", "NA", "NA", "0", "NA", "NA", "NA", "0", "NA", "NA", "0", "NA", "0", "NA", "NA", "NA", "0", "NA", "NA", "0", "0", "NA", "NA", "NA", "0", "NA", "NA", "NA", "NA", "1", "3", "0", "NA", "NA", "8"], ["480536", "Corner,  Arsenal. Conceded by Kevin Long.", "10'", "Arsenal", "0", "0", "0", "0", "0", "0", "NA", "NA", "NA", "NA", "NA", "NA", "NA", "0", "NA", "NA", "0", "NA", "0", "0", "NA", "NA", "NA", "0", "NA", "NA", "NA", "0", "NA", "NA", "0", "NA", "0", "NA", "NA", "NA", "1", "Arsenal", "Kevin Long", "0", "0", "NA", "NA", "NA", "0", "NA", "NA", "NA", "NA", "1", "4", "0", "NA", "NA", "10"], ["480536", "Attempt missed. Alexandre Lacazette (Arsenal) right footed shot from the right side of the box misses to the left. Assisted by Alex Iwobi with a through ball.", "14'", "Arsenal", "0", "0", "0", "0", "1", "0", "missed", "Alexandre Lacazette", "Arsenal", "right", "the right side of the box", "left", "Alex Iwobi", "0", "NA", "NA", "0", "through", "0", "0", "NA", "NA", "NA", "0", "NA", "NA", "NA", "0", "NA", "NA", "0", "NA", "0", "NA", "NA", "NA", "0", "NA", "NA", "0", "0", "NA", "NA", "NA", "0", "NA", "NA", "NA", "NA", "1", "5", "0", "NA", "NA", "14"], ["480536", "Goal!  Arsenal 1, Burnley 0. Pierre-Emerick Aubameyang (Arsenal) right footed shot from very close range to the centre of the goal. Assisted by Alexandre Lacazette.", "14'", "Arsenal", "1", "0", "0", "0", "1", "0", "goal", "NA", "Arsenal", "right", "right shot very close range", "centre of the goal", "Alexandre Lacazette", "0", "NA", "NA", "0", "NA", "0", "0", "NA", "NA", "NA", "0", "NA", "NA", "NA", "0", "NA", "NA", "0", "NA", "0", "NA", "NA", "NA", "0", "NA", "NA", "0", "0", "NA", "NA", "NA", "0", "NA", "NA", "NA", "NA", "1", "6", "0", "NA", "NA", "14"], ["480536", "Delay in match Ashley Barnes (Burnley) because of an injury.", "19'", "Arsenal", "1", "0", "0", "0", "0", "0", "NA", "NA", "NA", "NA", "NA", "NA", "NA", "0", "NA", "NA", "0", "NA", "0", "0", "NA", "NA", "NA", "0", "NA", "NA", "NA", "0", "NA", "NA", "1", "Burnley", "0", "NA", "NA", "NA", "0", "NA", "NA", "0", "0", "NA", "NA", "NA", "0", "NA", "NA", "NA", "NA", "1", "7", "0", "NA", "NA", "19"], ["480536", "Delay in match Granit Xhaka (Arsenal) because of an injury.", "19'", "Arsenal", "1", "0", "0", "0", "0", "0", "NA", "NA", "NA", "NA", "NA", "NA", "NA", "0", "NA", "NA", "0", "NA", "0", "0", "NA", "NA", "NA", "0", "NA", "NA", "NA", "0", "NA", "NA", "1", "Arsenal", "0", "NA", "NA", "NA", "0", "NA", "NA", "0", "0", "NA", "NA", "NA", "0", "NA", "NA", "NA", "NA", "1", "8", "0", "NA", "NA", "19"], ["480536", "Delay over. They are ready to continue.", "21'", "Arsenal", "1", "0", "0", "0", "0", "0", "NA", "NA", "NA", "NA", "NA", "NA", "NA", "0", "NA", "NA", "0", "NA", "0", "0", "NA", "NA", "NA", "0", "NA", "NA", "NA", "0", "NA", "NA", "0", "NA", "0", "NA", "NA", "NA", "0", "NA", "NA", "0", "0", "NA", "NA", "NA", "0", "NA", "NA", "NA", "NA", "1", "9", "0", "NA", "NA", "21"], ["480536", "Substitution, Burnley. Sam Vokes replaces Ashley Barnes because of an injury.", "22'", "Arsenal", "1", "0", "0", "0", "0", "0", "NA", "NA", "NA", "NA", "NA", "NA", "NA", "0", "NA", "NA", "0", "NA", "0", "0", "NA", "NA", "NA", "0", "NA", "NA", "NA", "0", "NA", "NA", "0", "NA", "0", "NA", "NA", "NA", "0", "NA", "NA", "1", "1", "Burnley", "Sam Vokes", "Ashley Barnes", "0", "NA", "NA", "NA", "NA", "1", "10", "0", "NA", "NA", "22"], ["480536", "Corner,  Burnley. Conceded by Héctor Bellerín.", "24'", "Arsenal", "1", "0", "0", "0", "0", "0", "NA", "NA", "NA", "NA", "NA", "NA", "NA", "0", "NA", "NA", "0", "NA", "0", "0", "NA", "NA", "NA", "0", "NA", "NA", "NA", "0", "NA", "NA", "0", "NA", "0", "NA", "NA", "NA", "1", "Burnley", "Héctor Bellerín", "0", "0", "NA", "NA", "NA", "0", "NA", "NA", "NA", "NA", "1", "11", "0", "NA", "NA", "24"], ["480536", "Foul by Héctor Bellerín (Arsenal).", "28'", "Arsenal", "1", "0", "0", "0", "0", "0", "NA", "NA", "NA", "NA", "NA", "NA", "NA", "1", "Héctor Bellerín", "Arsenal", "0", "NA", "0", "0", "NA", "NA", "NA", "0", "NA", "NA", "NA", "0", "NA", "NA", "0", "NA", "0", "NA", "NA", "NA", "0", "NA", "NA", "0", "0", "NA", "NA", "NA", "0", "NA", "NA", "NA", "NA", "1", "12", "0", "NA", "NA", "28"], ["480536", "Jack Cork (Burnley) wins a free kick in the defensive half.", "28'", "Arsenal", "1", "0", "0", "0", "0", "0", "NA", "NA", "NA", "NA", "NA", "NA", "NA", "0", "NA", "NA", "0", "NA", "0", "0", "NA", "NA", "NA", "0", "NA", "NA", "NA", "0", "NA", "NA", "0", "NA", "1", "Jack Cork", "Burnley", "defensive half", "0", "NA", "NA", "0", "0", "NA", "NA", "NA", "0", "NA", "NA", "NA", "NA", "1", "13", "0", "NA", "NA", "28"], ["480536", "Alex Iwobi (Arsenal) wins a free kick in the defensive half.", "30'", "Arsenal", "1", "0", "0", "0", "0", "0", "NA", "NA", "NA", "NA", "NA", "NA", "NA", "0", "NA", "NA", "0", "NA", "0", "0", "NA", "NA", "NA", "0", "NA", "NA", "NA", "0", "NA", "NA", "0", "NA", "1", "Alex Iwobi", "Arsenal", "defensive half", "0", "NA", "NA", "0", "0", "NA", "NA", "NA", "0", "NA", "NA", "NA", "NA", "1", "14", "0", "NA", "NA", "30"], ["480536", "Foul by Jack Cork (Burnley).", "30'", "Arsenal", "1", "0", "0", "0", "0", "0", "NA", "NA", "NA", "NA", "NA", "NA", "NA", "1", "Jack Cork", "Burnley", "0", "NA", "0", "0", "NA", "NA", "NA", "0", "NA", "NA", "NA", "0", "NA", "NA", "0", "NA", "0", "NA", "NA", "NA", "0", "NA", "NA", "0", "0", "NA", "NA", "NA", "0", "NA", "NA", "NA", "NA", "1", "15", "0", "NA", "NA", "30"], ["480536", "Attempt missed. Henrikh Mkhitaryan (Arsenal) right footed shot from the centre of the box is too high. Assisted by Alexandre Lacazette.", "33'", "Arsenal", "1", "0", "0", "0", "1", "0", "missed", "Henrikh Mkhitaryan", "Arsenal", "right", "the centre of the box", "too high", "Alexandre Lacazette", "0", "NA", "NA", "0", "NA", "0", "0", "NA", "NA", "NA", "0", "NA", "NA", "NA", "0", "NA", "NA", "0", "NA", "0", "NA", "NA", "NA", "0", "NA", "NA", "0", "0", "NA", "NA", "NA", "0", "NA", "NA", "NA", "NA", "1", "16", "0", "NA", "NA", "33"], ["480536", "Attempt blocked. Alex Iwobi (Arsenal) right footed shot from the right side of the box is blocked. Assisted by Jack Wilshere.", "34'", "Arsenal", "1", "0", "0", "0", "1", "0", "blocked", "Alex Iwobi", "Arsenal", "right", "the right side of the box", "NA", "Jack Wilshere", "0", "NA", "NA", "0", "NA", "0", "0", "NA", "NA", "NA", "0", "NA", "NA", "NA", "0", "NA", "NA", "0", "NA", "0", "NA", "NA", "NA", "0", "NA", "NA", "0", "0", "NA", "NA", "NA", "0", "NA", "NA", "NA", "NA", "1", "17", "0", "NA", "NA", "34"], ["480536", "Foul by Konstantinos Mavropanos (Arsenal).", "35'", "Arsenal", "1", "0", "0", "0", "0", "0", "NA", "NA", "NA", "NA", "NA", "NA", "NA", "1", "Konstantinos Mavropanos", "Arsenal", "0", "NA", "0", "0", "NA", "NA", "NA", "0", "NA", "NA", "NA", "0", "NA", "NA", "0", "NA", "0", "NA", "NA", "NA", "0", "NA", "NA", "0", "0", "NA", "NA", "NA", "0", "NA", "NA", "NA", "NA", "1", "18", "0", "NA", "NA", "35"], ["480536", "Sam Vokes (Burnley) wins a free kick in the defensive half.", "35'", "Arsenal", "1", "0", "0", "0", "0", "0", "NA", "NA", "NA", "NA", "NA", "NA", "NA", "0", "NA", "NA", "0", "NA", "0", "0", "NA", "NA", "NA", "0", "NA", "NA", "NA", "0", "NA", "NA", "0", "NA", "1", "Sam Vokes", "Burnley", "defensive half", "0", "NA", "NA", "0", "0", "NA", "NA", "NA", "0", "NA", "NA", "NA", "NA", "1", "19", "0", "NA", "NA", "35"], ["480536", "Foul by Sam Vokes (Burnley).", "36'", "Arsenal", "1", "0", "0", "0", "0", "0", "NA", "NA", "NA", "NA", "NA", "NA", "NA", "1", "Sam Vokes", "Burnley", "0", "NA", "0", "0", "NA", "NA", "NA", "0", "NA", "NA", "NA", "0", "NA", "NA", "0", "NA", "0", "NA", "NA", "NA", "0", "NA", "NA", "0", "0", "NA", "NA", "NA", "0", "NA", "NA", "NA", "NA", "1", "20", "0", "NA", "NA", "36"], ["480536", "Konstantinos Mavropanos (Arsenal) wins a free kick in the defensive half.", "36'", "Arsenal", "1", "0", "0", "0", "0", "0", "NA", "NA", "NA", "NA", "NA", "NA", "NA", "0", "NA", "NA", "0", "NA", "0", "0", "NA", "NA", "NA", "0", "NA", "NA", "NA", "0", "NA", "NA", "0", "NA", "1", "Konstantinos Mavropanos", "Arsenal", "defensive half", "0", "NA", "NA", "0", "0", "NA", "NA", "NA", "0", "NA", "NA", "NA", "NA", "1", "21", "0", "NA", "NA", "36"], ["480536", "Corner,  Arsenal. Conceded by Kevin Long.", "37'", "Arsenal", "1", "0", "0", "0", "0", "0", "NA", "NA", "NA", "NA", "NA", "NA", "NA", "0", "NA", "NA", "0", "NA", "0", "0", "NA", "NA", "NA", "0", "NA", "NA", "NA", "0", "NA", "NA", "0", "NA", "0", "NA", "NA", "NA", "1", "Arsenal", "Kevin Long", "0", "0", "NA", "NA", "NA", "0", "NA", "NA", "NA", "NA", "1", "22", "0", "NA", "NA", "37"], ["480536", "Delay in match Konstantinos Mavropanos (Arsenal) because of an injury.", "39'", "Arsenal", "1", "0", "0", "0", "0", "0", "NA", "NA", "NA", "NA", "NA", "NA", "NA", "0", "NA", "NA", "0", "NA", "0", "0", "NA", "NA", "NA", "0", "NA", "NA", "NA", "0", "NA", "NA", "1", "Arsenal", "0", "NA", "NA", "NA", "0", "NA", "NA", "0", "0", "NA", "NA", "NA", "0", "NA", "NA", "NA", "NA", "1", "23", "0", "NA", "NA", "39"], ["480536", "Delay in match Sam Vokes (Burnley) because of an injury.", "39'", "Arsenal", "1", "0", "0", "0", "0", "0", "NA", "NA", "NA", "NA", "NA", "NA", "NA", "0", "NA", "NA", "0", "NA", "0", "0", "NA", "NA", "NA", "0", "NA", "NA", "NA", "0", "NA", "NA", "1", "Burnley", "0", "NA", "NA", "NA", "0", "NA", "NA", "0", "0", "NA", "NA", "NA", "0", "NA", "NA", "NA", "NA", "1", "24", "0", "NA", "NA", "39"], ["480536", "Delay over. They are ready to continue.", "40'", "Arsenal", "1", "0", "0", "0", "0", "0", "NA", "NA", "NA", "NA", "NA", "NA", "NA", "0", "NA", "NA", "0", "NA", "0", "0", "NA", "NA", "NA", "0", "NA", "NA", "NA", "0", "NA", "NA", "0", "NA", "0", "NA", "NA", "NA", "0", "NA", "NA", "0", "0", "NA", "NA", "NA", "0", "NA", "NA", "NA", "NA", "1", "25", "0", "NA", "NA", "40"], ["480536", "Foul by Jeff Hendrick (Burnley).", "43'", "Arsenal", "1", "0", "0", "0", "0", "0", "NA", "NA", "NA", "NA", "NA", "NA", "NA", "1", "Jeff Hendrick", "Burnley", "0", "NA", "0", "0", "NA", "NA", "NA", "0", "NA", "NA", "NA", "0", "NA", "NA", "0", "NA", "0", "NA", "NA", "NA", "0", "NA", "NA", "0", "0", "NA", "NA", "NA", "0", "NA", "NA", "NA", "NA", "1", "26", "0", "NA", "NA", "43"], ["480536", "Granit Xhaka (Arsenal) wins a free kick on the left wing.", "43'", "Arsenal", "1", "0", "0", "0", "0", "0", "NA", "NA", "NA", "NA", "NA", "NA", "NA", "0", "NA", "NA", "0", "NA", "0", "0", "NA", "NA", "NA", "0", "NA", "NA", "NA", "0", "NA", "NA", "0", "NA", "1", "Granit Xhaka", "Arsenal", "NA", "0", "NA", "NA", "0", "0", "NA", "NA", "NA", "0", "NA", "NA", "NA", "NA", "1", "27", "0", "NA", "NA", "43"], ["480536", "Attempt saved. Henrikh Mkhitaryan (Arsenal) right footed shot from outside the box is saved in the centre of the goal. Assisted by Alexandre Lacazette.", "43'", "Arsenal", "1", "0", "0", "0", "1", "0", "saved", "Henrikh Mkhitaryan", "Arsenal", "right", "outside the box", "the centre of the goal", "Alexandre Lacazette", "0", "NA", "NA", "0", "NA", "0", "0", "NA", "NA", "NA", "0", "NA", "NA", "NA", "0", "NA", "NA", "0", "NA", "0", "NA", "NA", "NA", "0", "NA", "NA", "0", "0", "NA", "NA", "NA", "0", "NA", "NA", "NA", "NA", "1", "28", "0", "NA", "NA", "43"], ["480536", "Foul by Sam Vokes (Burnley).", "44'", "Arsenal", "1", "0", "0", "0", "0", "0", "NA", "NA", "NA", "NA", "NA", "NA", "NA", "1", "Sam Vokes", "Burnley", "0", "NA", "0", "0", "NA", "NA", "NA", "0", "NA", "NA", "NA", "0", "NA", "NA", "0", "NA", "0", "NA", "NA", "NA", "0", "NA", "NA", "0", "0", "NA", "NA", "NA", "0", "NA", "NA", "NA", "NA", "1", "29", "0", "NA", "NA", "44"], ["480536", "Konstantinos Mavropanos (Arsenal) wins a free kick in the defensive half.", "44'", "Arsenal", "1", "0", "0", "0", "0", "0", "NA", "NA", "NA", "NA", "NA", "NA", "NA", "0", "NA", "NA", "0", "NA", "0", "0", "NA", "NA", "NA", "0", "NA", "NA", "NA", "0", "NA", "NA", "0", "NA", "1", "Konstantinos Mavropanos", "Arsenal", "defensive half", "0", "NA", "NA", "0", "0", "NA", "NA", "NA", "0", "NA", "NA", "NA", "NA", "1", "30", "0", "NA", "NA", "44"], ["480536", "James Tarkowski (Burnley) is shown the yellow card for a bad foul.", "44'", "Arsenal", "1", "0", "0", "0", "0", "0", "NA", "NA", "NA", "NA", "NA", "NA", "NA", "0", "NA", "NA", "0", "NA", "0", "0", "NA", "NA", "NA", "1", "yellow", "James Tarkowski", "Burnley", "0", "NA", "NA", "0", "NA", "0", "NA", "NA", "NA", "0", "NA", "NA", "0", "0", "NA", "NA", "NA", "0", "NA", "NA", "NA", "NA", "1", "31", "0", "NA", "NA", "44"], ["480536", "Foul by Kevin Long (Burnley).", "45'", "Arsenal", "1", "0", "0", "0", "0", "0", "NA", "NA", "NA", "NA", "NA", "NA", "NA", "1", "Kevin Long", "Burnley", "0", "NA", "0", "0", "NA", "NA", "NA", "0", "NA", "NA", "NA", "0", "NA", "NA", "0", "NA", "0", "NA", "NA", "NA", "0", "NA", "NA", "0", "0", "NA", "NA", "NA", "0", "NA", "NA", "NA", "NA", "1", "32", "0", "NA", "NA", "45"], ["480536", "Pierre-Emerick Aubameyang (Arsenal) wins a free kick on the left wing.", "45'", "Arsenal", "1", "0", "0", "0", "0", "0", "NA", "NA", "NA", "NA", "NA", "NA", "NA", "0", "NA", "NA", "0", "NA", "0", "0", "NA", "NA", "NA", "0", "NA", "NA", "NA", "0", "NA", "NA", "0", "NA", "1", "NA", "Arsenal", "NA", "0", "NA", "NA", "0", "0", "NA", "NA", "NA", "0", "NA", "NA", "NA", "NA", "1", "33", "0", "NA", "NA", "45"], ["480536", "Goal!  Arsenal 2, Burnley 0. Alexandre Lacazette (Arsenal) left footed shot from the centre of the box to the bottom right corner. Assisted by Héctor Bellerín.", "45'+3'", "Arsenal", "2", "0", "0", "0", "1", "0", "goal", "Alexandre Lacazette", "Arsenal", "left", "the centre of the box", "bottom right corner", "Héctor Bellerín", "0", "NA", "NA", "0", "NA", "0", "0", "NA", "NA", "NA", "0", "NA", "NA", "NA", "0", "NA", "NA", "0", "NA", "0", "NA", "NA", "NA", "0", "NA", "NA", "0", "0", "NA", "NA", "NA", "0", "NA", "NA", "NA", "NA", "1", "34", "1", "NA", "NA", "48"], ["480536", "First Half ends, Arsenal 2, Burnley 0.", "45'+5'", "Arsenal", "2", "1", "0", "0", "0", "0", "NA", "NA", "NA", "NA", "NA", "NA", "NA", "0", "NA", "NA", "0", "NA", "0", "0", "NA", "NA", "NA", "0", "NA", "NA", "NA", "0", "NA", "NA", "0", "NA", "0", "NA", "NA", "NA", "0", "NA", "NA", "0", "0", "NA", "NA", "NA", "0", "NA", "NA", "NA", "NA", "1", "35", "1", "NA", "NA", "50"], ["480536", "Second Half begins Arsenal 2, Burnley 0.", "45'", "Arsenal", "2", "0", "0", "1", "0", "0", "NA", "NA", "NA", "NA", "NA", "NA", "NA", "0", "NA", "NA", "0", "NA", "0", "0", "NA", "NA", "NA", "0", "NA", "NA", "NA", "0", "NA", "NA", "0", "NA", "0", "NA", "NA", "NA", "0", "NA", "NA", "0", "0", "NA", "NA", "NA", "0", "NA", "NA", "NA", "NA", "2", "36", "0", "NA", "NA", "45"], ["480536", "Attempt missed. Jack Wilshere (Arsenal) left footed shot from the centre of the box is just a bit too high. Assisted by Pierre-Emerick Aubameyang.", "46'", "Arsenal", "2", "0", "0", "0", "1", "0", "missed", "Jack Wilshere", "Arsenal", "left", "the centre of the box", "just a bit too high", "Pierre-Emerick", "0", "NA", "NA", "0", "NA", "0", "0", "NA", "NA", "NA", "0", "NA", "NA", "NA", "0", "NA", "NA", "0", "NA", "0", "NA", "NA", "NA", "0", "NA", "NA", "0", "0", "NA", "NA", "NA", "0", "NA", "NA", "NA", "NA", "2", "37", "0", "NA", "NA", "46"], ["480536", "Corner,  Arsenal. Conceded by Aaron Lennon.", "48'", "Arsenal", "2", "0", "0", "0", "0", "0", "NA", "NA", "NA", "NA", "NA", "NA", "NA", "0", "NA", "NA", "0", "NA", "0", "0", "NA", "NA", "NA", "0", "NA", "NA", "NA", "0", "NA", "NA", "0", "NA", "0", "NA", "NA", "NA", "1", "Arsenal", "Aaron Lennon", "0", "0", "NA", "NA", "NA", "0", "NA", "NA", "NA", "NA", "2", "38", "0", "NA", "NA", "48"], ["480536", "Attempt saved. Sam Vokes (Burnley) header from the centre of the box is saved in the centre of the goal. Assisted by Jeff Hendrick with a cross.", "49'", "Arsenal", "2", "0", "0", "0", "1", "0", "saved", "Sam Vokes", "Burnley", "header", "the centre of the box", "the centre of the goal", "Jeff Hendrick", "0", "NA", "NA", "0", "cross", "0", "0", "NA", "NA", "NA", "0", "NA", "NA", "NA", "0", "NA", "NA", "0", "NA", "0", "NA", "NA", "NA", "0", "NA", "NA", "0", "0", "NA", "NA", "NA", "0", "NA", "NA", "NA", "NA", "2", "39", "0", "NA", "NA", "49"], ["480536", "Goal!  Arsenal 3, Burnley 0. Sead Kolasinac (Arsenal) left footed shot from the left side of the box to the bottom right corner. Assisted by Jack Wilshere.", "54'", "Arsenal", "3", "0", "0", "0", "1", "0", "goal", "Sead Kolasinac", "Arsenal", "left", "the left side of the box", "bottom right corner", "Jack Wilshere", "0", "NA", "NA", "0", "NA", "0", "0", "NA", "NA", "NA", "0", "NA", "NA", "NA", "0", "NA", "NA", "0", "NA", "0", "NA", "NA", "NA", "0", "NA", "NA", "0", "0", "NA", "NA", "NA", "0", "NA", "NA", "NA", "NA", "2", "40", "0", "NA", "NA", "54"], ["480536", "Attempt missed. Henrikh Mkhitaryan (Arsenal) left footed shot from the right side of the box is close, but misses to the left. Assisted by Alex Iwobi.", "55'", "Arsenal", "3", "0", "0", "0", "1", "0", "missed", "Henrikh Mkhitaryan", "Arsenal", "left", "the right side of the box", "close, but left", "Alex Iwobi", "0", "NA", "NA", "0", "NA", "0", "0", "NA", "NA", "NA", "0", "NA", "NA", "NA", "0", "NA", "NA", "0", "NA", "0", "NA", "NA", "NA", "0", "NA", "NA", "0", "0", "NA", "NA", "NA", "0", "NA", "NA", "NA", "NA", "2", "41", "0", "NA", "NA", "55"], ["480536", "Aaron Lennon (Burnley) wins a free kick on the right wing.", "56'", "Arsenal", "3", "0", "0", "0", "0", "0", "NA", "NA", "NA", "NA", "NA", "NA", "NA", "0", "NA", "NA", "0", "NA", "0", "0", "NA", "NA", "NA", "0", "NA", "NA", "NA", "0", "NA", "NA", "0", "NA", "1", "Aaron Lennon", "Burnley", "NA", "0", "NA", "NA", "0", "0", "NA", "NA", "NA", "0", "NA", "NA", "NA", "NA", "2", "42", "0", "NA", "NA", "56"], ["480536", "Foul by Sead Kolasinac (Arsenal).", "56'", "Arsenal", "3", "0", "0", "0", "0", "0", "NA", "NA", "NA", "NA", "NA", "NA", "NA", "1", "Sead Kolasinac", "Arsenal", "0", "NA", "0", "0", "NA", "NA", "NA", "0", "NA", "NA", "NA", "0", "NA", "NA", "0", "NA", "0", "NA", "NA", "NA", "0", "NA", "NA", "0", "0", "NA", "NA", "NA", "0", "NA", "NA", "NA", "NA", "2", "43", "0", "NA", "NA", "56"], ["480536", "Foul by Alexandre Lacazette (Arsenal).", "57'", "Arsenal", "3", "0", "0", "0", "0", "0", "NA", "NA", "NA", "NA", "NA", "NA", "NA", "1", "Alexandre Lacazette", "Arsenal", "0", "NA", "0", "0", "NA", "NA", "NA", "0", "NA", "NA", "NA", "0", "NA", "NA", "0", "NA", "0", "NA", "NA", "NA", "0", "NA", "NA", "0", "0", "NA", "NA", "NA", "0", "NA", "NA", "NA", "NA", "2", "44", "0", "NA", "NA", "57"], ["480536", "Johann Berg Gudmundsson (Burnley) wins a free kick in the defensive half.", "57'", "Arsenal", "3", "0", "0", "0", "0", "0", "NA", "NA", "NA", "NA", "NA", "NA", "NA", "0", "NA", "NA", "0", "NA", "0", "0", "NA", "NA", "NA", "0", "NA", "NA", "NA", "0", "NA", "NA", "0", "NA", "1", "Johann Berg Gudmundsson", "Burnley", "defensive half", "0", "NA", "NA", "0", "0", "NA", "NA", "NA", "0", "NA", "NA", "NA", "NA", "2", "45", "0", "NA", "NA", "57"], ["480536", "Attempt blocked. Jeff Hendrick (Burnley) right footed shot from outside the box is blocked. Assisted by Johann Berg Gudmundsson.", "60'", "Arsenal", "3", "0", "0", "0", "1", "0", "blocked", "Jeff Hendrick", "Burnley", "right", "outside the box", "NA", "Johann Berg Gudmundsson", "0", "NA", "NA", "0", "NA", "0", "0", "NA", "NA", "NA", "0", "NA", "NA", "NA", "0", "NA", "NA", "0", "NA", "0", "NA", "NA", "NA", "0", "NA", "NA", "0", "0", "NA", "NA", "NA", "0", "NA", "NA", "NA", "NA", "2", "46", "0", "NA", "NA", "60"], ["480536", "Corner,  Burnley. Conceded by Konstantinos Mavropanos.", "60'", "Arsenal", "3", "0", "0", "0", "0", "0", "NA", "NA", "NA", "NA", "NA", "NA", "NA", "0", "NA", "NA", "0", "NA", "0", "0", "NA", "NA", "NA", "0", "NA", "NA", "NA", "0", "NA", "NA", "0", "NA", "0", "NA", "NA", "NA", "1", "Burnley", "Konstantinos Mavropanos", "0", "0", "NA", "NA", "NA", "0", "NA", "NA", "NA", "NA", "2", "47", "0", "NA", "NA", "60"], ["480536", "Attempt missed. Kevin Long (Burnley) header from the left side of the six yard box misses to the right. Assisted by Johann Berg Gudmundsson with a cross following a corner.", "61'", "Arsenal", "3", "0", "0", "0", "1", "0", "missed", "Kevin Long", "Burnley", "header", "the left side of the six yard box", "right", "Johann Berg Gudmundsson", "0", "NA", "NA", "0", "cross", "1", "0", "NA", "NA", "NA", "0", "NA", "NA", "NA", "0", "NA", "NA", "0", "NA", "0", "NA", "NA", "NA", "0", "NA", "NA", "0", "0", "NA", "NA", "NA", "0", "NA", "NA", "NA", "NA", "2", "48", "0", "NA", "NA", "61"], ["480536", "Corner,  Burnley. Conceded by Calum Chambers.", "62'", "Arsenal", "3", "0", "0", "0", "0", "0", "NA", "NA", "NA", "NA", "NA", "NA", "NA", "0", "NA", "NA", "0", "NA", "0", "0", "NA", "NA", "NA", "0", "NA", "NA", "NA", "0", "NA", "NA", "0", "NA", "0", "NA", "NA", "NA", "1", "Burnley", "Calum Chambers", "0", "0", "NA", "NA", "NA", "0", "NA", "NA", "NA", "NA", "2", "49", "0", "NA", "NA", "62"], ["480536", "Corner,  Burnley. Conceded by Granit Xhaka.", "63'", "Arsenal", "3", "0", "0", "0", "0", "0", "NA", "NA", "NA", "NA", "NA", "NA", "NA", "0", "NA", "NA", "0", "NA", "0", "0", "NA", "NA", "NA", "0", "NA", "NA", "NA", "0", "NA", "NA", "0", "NA", "0", "NA", "NA", "NA", "1", "Burnley", "Granit Xhaka", "0", "0", "NA", "NA", "NA", "0", "NA", "NA", "NA", "NA", "2", "50", "0", "NA", "NA", "63"], ["480536", "Attempt blocked. Kevin Long (Burnley) header from the centre of the box is blocked. Assisted by Johann Berg Gudmundsson with a cross.", "63'", "Arsenal", "3", "0", "0", "0", "1", "0", "blocked", "Kevin Long", "Burnley", "header", "the centre of the box", "NA", "Johann Berg Gudmundsson", "0", "NA", "NA", "0", "cross", "0", "0", "NA", "NA", "NA", "0", "NA", "NA", "NA", "0", "NA", "NA", "0", "NA", "0", "NA", "NA", "NA", "0", "NA", "NA", "0", "0", "NA", "NA", "NA", "0", "NA", "NA", "NA", "NA", "2", "51", "0", "NA", "NA", "63"], ["480536", "Goal!  Arsenal 4, Burnley 0. Alex Iwobi (Arsenal) left footed shot from the centre of the box to the top left corner. Assisted by Pierre-Emerick Aubameyang.", "64'", "Arsenal", "4", "0", "0", "0", "1", "0", "goal", "Alex Iwobi", "Arsenal", "left", "the centre of the box", "top left corner", "Pierre-Emerick", "0", "NA", "NA", "0", "NA", "0", "0", "NA", "NA", "NA", "0", "NA", "NA", "NA", "0", "NA", "NA", "0", "NA", "0", "NA", "NA", "NA", "0", "NA", "NA", "0", "0", "NA", "NA", "NA", "0", "NA", "NA", "NA", "NA", "2", "52", "0", "NA", "NA", "64"], ["480536", "Foul by Ashley Westwood (Burnley).", "66'", "Arsenal", "4", "0", "0", "0", "0", "0", "NA", "NA", "NA", "NA", "NA", "NA", "NA", "1", "Ashley Westwood", "Burnley", "0", "NA", "0", "0", "NA", "NA", "NA", "0", "NA", "NA", "NA", "0", "NA", "NA", "0", "NA", "0", "NA", "NA", "NA", "0", "NA", "NA", "0", "0", "NA", "NA", "NA", "0", "NA", "NA", "NA", "NA", "2", "53", "0", "NA", "NA", "66"], ["480536", "Jack Wilshere (Arsenal) wins a free kick in the attacking half.", "66'", "Arsenal", "4", "0", "0", "0", "0", "0", "NA", "NA", "NA", "NA", "NA", "NA", "NA", "0", "NA", "NA", "0", "NA", "0", "0", "NA", "NA", "NA", "0", "NA", "NA", "NA", "0", "NA", "NA", "0", "NA", "1", "Jack Wilshere", "Arsenal", "attacking half", "0", "NA", "NA", "0", "0", "NA", "NA", "NA", "0", "NA", "NA", "NA", "NA", "2", "54", "0", "NA", "NA", "66"], ["480536", "Attempt blocked. Sead Kolasinac (Arsenal) right footed shot from the left side of the box is blocked. Assisted by Alexandre Lacazette.", "67'", "Arsenal", "4", "0", "0", "0", "1", "0", "blocked", "Sead Kolasinac", "Arsenal", "right", "the left side of the box", "NA", "Alexandre Lacazette", "0", "NA", "NA", "0", "NA", "0", "0", "NA", "NA", "NA", "0", "NA", "NA", "NA", "0", "NA", "NA", "0", "NA", "0", "NA", "NA", "NA", "0", "NA", "NA", "0", "0", "NA", "NA", "NA", "0", "NA", "NA", "NA", "NA", "2", "55", "0", "NA", "NA", "67"], ["480536", "Foul by Granit Xhaka (Arsenal).", "69'", "Arsenal", "4", "0", "0", "0", "0", "0", "NA", "NA", "NA", "NA", "NA", "NA", "NA", "1", "Granit Xhaka", "Arsenal", "0", "NA", "0", "0", "NA", "NA", "NA", "0", "NA", "NA", "NA", "0", "NA", "NA", "0", "NA", "0", "NA", "NA", "NA", "0", "NA", "NA", "0", "0", "NA", "NA", "NA", "0", "NA", "NA", "NA", "NA", "2", "56", "0", "NA", "NA", "69"], ["480536", "Jeff Hendrick (Burnley) wins a free kick on the left wing.", "69'", "Arsenal", "4", "0", "0", "0", "0", "0", "NA", "NA", "NA", "NA", "NA", "NA", "NA", "0", "NA", "NA", "0", "NA", "0", "0", "NA", "NA", "NA", "0", "NA", "NA", "NA", "0", "NA", "NA", "0", "NA", "1", "Jeff Hendrick", "Burnley", "NA", "0", "NA", "NA", "0", "0", "NA", "NA", "NA", "0", "NA", "NA", "NA", "NA", "2", "57", "0", "NA", "NA", "69"], ["480536", "Corner,  Burnley. Conceded by Granit Xhaka.", "69'", "Arsenal", "4", "0", "0", "0", "0", "0", "NA", "NA", "NA", "NA", "NA", "NA", "NA", "0", "NA", "NA", "0", "NA", "0", "0", "NA", "NA", "NA", "0", "NA", "NA", "NA", "0", "NA", "NA", "0", "NA", "0", "NA", "NA", "NA", "1", "Burnley", "Granit Xhaka", "0", "0", "NA", "NA", "NA", "0", "NA", "NA", "NA", "NA", "2", "58", "0", "NA", "NA", "69"], ["480536", "Substitution, Burnley. Georges-Kévin Nkoudou replaces Aaron Lennon.", "71'", "Arsenal", "4", "0", "0", "0", "0", "0", "NA", "NA", "NA", "NA", "NA", "NA", "NA", "0", "NA", "NA", "0", "NA", "0", "0", "NA", "NA", "NA", "0", "NA", "NA", "NA", "0", "NA", "NA", "0", "NA", "0", "NA", "NA", "NA", "0", "NA", "NA", "1", "0", "Burnley", "Kévin Nkoudou", "Aaron Lennon", "0", "NA", "NA", "NA", "NA", "2", "59", "0", "NA", "NA", "71"], ["480536", "Substitution, Arsenal. Aaron Ramsey replaces Jack Wilshere.", "72'", "Arsenal", "4", "0", "0", "0", "0", "0", "NA", "NA", "NA", "NA", "NA", "NA", "NA", "0", "NA", "NA", "0", "NA", "0", "0", "NA", "NA", "NA", "0", "NA", "NA", "NA", "0", "NA", "NA", "0", "NA", "0", "NA", "NA", "NA", "0", "NA", "NA", "1", "0", "Arsenal", "Aaron Ramsey", "Jack Wilshere", "0", "NA", "NA", "NA", "NA", "2", "60", "0", "NA", "NA", "72"], ["480536", "Substitution, Arsenal. Danny Welbeck replaces Alexandre Lacazette.", "72'", "Arsenal", "4", "0", "0", "0", "0", "0", "NA", "NA", "NA", "NA", "NA", "NA", "NA", "0", "NA", "NA", "0", "NA", "0", "0", "NA", "NA", "NA", "0", "NA", "NA", "NA", "0", "NA", "NA", "0", "NA", "0", "NA", "NA", "NA", "0", "NA", "NA", "1", "0", "Arsenal", "Danny Welbeck", "Alexandre Lacazette", "0", "NA", "NA", "NA", "NA", "2", "61", "0", "NA", "NA", "72"], ["480536", "Foul by Calum Chambers (Arsenal).", "73'", "Arsenal", "4", "0", "0", "0", "0", "0", "NA", "NA", "NA", "NA", "NA", "NA", "NA", "1", "Calum Chambers", "Arsenal", "0", "NA", "0", "0", "NA", "NA", "NA", "0", "NA", "NA", "NA", "0", "NA", "NA", "0", "NA", "0", "NA", "NA", "NA", "0", "NA", "NA", "0", "0", "NA", "NA", "NA", "0", "NA", "NA", "NA", "NA", "2", "62", "0", "NA", "NA", "73"], ["480536", "Sam Vokes (Burnley) wins a free kick on the left wing.", "73'", "Arsenal", "4", "0", "0", "0", "0", "0", "NA", "NA", "NA", "NA", "NA", "NA", "NA", "0", "NA", "NA", "0", "NA", "0", "0", "NA", "NA", "NA", "0", "NA", "NA", "NA", "0", "NA", "NA", "0", "NA", "1", "Sam Vokes", "Burnley", "NA", "0", "NA", "NA", "0", "0", "NA", "NA", "NA", "0", "NA", "NA", "NA", "NA", "2", "63", "0", "NA", "NA", "73"], ["480536", "Attempt missed. Jeff Hendrick (Burnley) right footed shot from outside the box misses to the left.", "73'", "Arsenal", "4", "0", "0", "0", "1", "0", "missed", "Jeff Hendrick", "Burnley", "right", "outside the box", "left", "NA", "0", "NA", "NA", "0", "NA", "0", "0", "NA", "NA", "NA", "0", "NA", "NA", "NA", "0", "NA", "NA", "0", "NA", "0", "NA", "NA", "NA", "0", "NA", "NA", "0", "0", "NA", "NA", "NA", "0", "NA", "NA", "NA", "NA", "2", "64", "0", "NA", "NA", "73"], ["480536", "Attempt saved. Johann Berg Gudmundsson (Burnley) left footed shot from outside the box is saved in the bottom right corner.", "74'", "Arsenal", "4", "0", "0", "0", "1", "0", "saved", "Johann Berg Gudmundsson", "Burnley", "left", "outside the box", "the bottom right corner", "NA", "0", "NA", "NA", "0", "NA", "0", "0", "NA", "NA", "NA", "0", "NA", "NA", "NA", "0", "NA", "NA", "0", "NA", "0", "NA", "NA", "NA", "0", "NA", "NA", "0", "0", "NA", "NA", "NA", "0", "NA", "NA", "NA", "NA", "2", "65", "0", "NA", "NA", "74"], ["480536", "Goal!  Arsenal 5, Burnley 0. Pierre-Emerick Aubameyang (Arsenal) right footed shot from the centre of the box to the top left corner. Assisted by Héctor Bellerín.", "75'", "Arsenal", "5", "0", "0", "0", "1", "0", "goal", "NA", "Arsenal", "right", "the centre of the box", "top left corner", "Héctor Bellerín", "0", "NA", "NA", "0", "NA", "0", "0", "NA", "NA", "NA", "0", "NA", "NA", "NA", "0", "NA", "NA", "0", "NA", "0", "NA", "NA", "NA", "0", "NA", "NA", "0", "0", "NA", "NA", "NA", "0", "NA", "NA", "NA", "NA", "2", "66", "0", "NA", "NA", "75"], ["480536", "Substitution, Arsenal. Per Mertesacker replaces Calum Chambers.", "77'", "Arsenal", "5", "0", "0", "0", "0", "0", "NA", "NA", "NA", "NA", "NA", "NA", "NA", "0", "NA", "NA", "0", "NA", "0", "0", "NA", "NA", "NA", "0", "NA", "NA", "NA", "0", "NA", "NA", "0", "NA", "0", "NA", "NA", "NA", "0", "NA", "NA", "1", "0", "Arsenal", "Per Mertesacker", "Calum Chambers", "0", "NA", "NA", "NA", "NA", "2", "67", "0", "NA", "NA", "77"], ["480536", "Attempt missed. Héctor Bellerín (Arsenal) left footed shot from the centre of the box is too high.", "81'", "Arsenal", "5", "0", "0", "0", "1", "0", "missed", "Héctor Bellerín", "Arsenal", "left", "the centre of the box", "too high", "NA", "0", "NA", "NA", "0", "NA", "0", "0", "NA", "NA", "NA", "0", "NA", "NA", "NA", "0", "NA", "NA", "0", "NA", "0", "NA", "NA", "NA", "0", "NA", "NA", "0", "0", "NA", "NA", "NA", "0", "NA", "NA", "NA", "NA", "2", "68", "0", "NA", "NA", "81"], ["480536", "Foul by Matthew Lowton (Burnley).", "82'", "Arsenal", "5", "0", "0", "0", "0", "0", "NA", "NA", "NA", "NA", "NA", "NA", "NA", "1", "Matthew Lowton", "Burnley", "0", "NA", "0", "0", "NA", "NA", "NA", "0", "NA", "NA", "NA", "0", "NA", "NA", "0", "NA", "0", "NA", "NA", "NA", "0", "NA", "NA", "0", "0", "NA", "NA", "NA", "0", "NA", "NA", "NA", "NA", "2", "69", "0", "NA", "NA", "82"], ["480536", "Konstantinos Mavropanos (Arsenal) wins a free kick in the defensive half.", "82'", "Arsenal", "5", "0", "0", "0", "0", "0", "NA", "NA", "NA", "NA", "NA", "NA", "NA", "0", "NA", "NA", "0", "NA", "0", "0", "NA", "NA", "NA", "0", "NA", "NA", "NA", "0", "NA", "NA", "0", "NA", "1", "Konstantinos Mavropanos", "Arsenal", "defensive half", "0", "NA", "NA", "0", "0", "NA", "NA", "NA", "0", "NA", "NA", "NA", "NA", "2", "70", "0", "NA", "NA", "82"], ["480536", "Corner,  Arsenal. Conceded by Matthew Lowton.", "86'", "Arsenal", "5", "0", "0", "0", "0", "0", "NA", "NA", "NA", "NA", "NA", "NA", "NA", "0", "NA", "NA", "0", "NA", "0", "0", "NA", "NA", "NA", "0", "NA", "NA", "NA", "0", "NA", "NA", "0", "NA", "0", "NA", "NA", "NA", "1", "Arsenal", "Matthew Lowton", "0", "0", "NA", "NA", "NA", "0", "NA", "NA", "NA", "NA", "2", "71", "0", "NA", "NA", "86"], ["480536", "Attempt blocked. Danny Welbeck (Arsenal) right footed shot from outside the box is blocked. Assisted by Henrikh Mkhitaryan.", "88'", "Arsenal", "5", "0", "0", "0", "1", "0", "blocked", "Danny Welbeck", "Arsenal", "right", "outside the box", "NA", "Henrikh Mkhitaryan", "0", "NA", "NA", "0", "NA", "0", "0", "NA", "NA", "NA", "0", "NA", "NA", "NA", "0", "NA", "NA", "0", "NA", "0", "NA", "NA", "NA", "0", "NA", "NA", "0", "0", "NA", "NA", "NA", "0", "NA", "NA", "NA", "NA", "2", "72", "0", "NA", "NA", "88"], ["480536", "Substitution, Burnley. Nahki Wells replaces Johann Berg Gudmundsson.", "89'", "Arsenal", "5", "0", "0", "0", "0", "0", "NA", "NA", "NA", "NA", "NA", "NA", "NA", "0", "NA", "NA", "0", "NA", "0", "0", "NA", "NA", "NA", "0", "NA", "NA", "NA", "0", "NA", "NA", "0", "NA", "0", "NA", "NA", "NA", "0", "NA", "NA", "1", "0", "Burnley", "Nahki Wells", "Johann Berg Gudmundsson", "0", "NA", "NA", "NA", "NA", "2", "73", "0", "NA", "NA", "89"], ["480536", "Attempt saved. Aaron Ramsey (Arsenal) left footed shot from a difficult angle on the left is saved in the top centre of the goal. Assisted by Henrikh Mkhitaryan with a through ball.", "90'", "Arsenal", "5", "0", "0", "0", "1", "0", "saved", "Aaron Ramsey", "Arsenal", "left", "NA", "the top centre of the goal", "Henrikh Mkhitaryan", "0", "NA", "NA", "0", "through", "0", "0", "NA", "NA", "NA", "0", "NA", "NA", "NA", "0", "NA", "NA", "0", "NA", "0", "NA", "NA", "NA", "0", "NA", "NA", "0", "0", "NA", "NA", "NA", "0", "NA", "NA", "NA", "NA", "2", "74", "0", "NA", "NA", "90"], ["480536", "Second Half ends, Arsenal 5, Burnley 0.", "90'+1'", "Arsenal", "5", "1", "0", "0", "0", "0", "NA", "NA", "NA", "NA", "NA", "NA", "NA", "0", "NA", "NA", "0", "NA", "0", "0", "NA", "NA", "NA", "0", "NA", "NA", "NA", "0", "NA", "NA", "0", "NA", "0", "NA", "NA", "NA", "0", "NA", "NA", "0", "0", "NA", "NA", "NA", "0", "NA", "NA", "NA", "NA", "2", "75", "1", "NA", "NA", "91"], ["480536", "Match ends, Arsenal 5, Burnley 0.", "90'+1'", "Arsenal", "5", "0", "1", "0", "0", "0", "NA", "NA", "NA", "NA", "NA", "NA", "NA", "0", "NA", "NA", "0", "NA", "0", "0", "NA", "NA", "NA", "0", "NA", "NA", "NA", "0", "NA", "NA", "0", "NA", "0", "NA", "NA", "NA", "0", "NA", "NA", "0", "0", "NA", "NA", "NA", "0", "NA", "NA", "NA", "NA", "2", "76", "1", "NA", "NA", "91"]], "Lineup": {"Home Player 9": "Henrikh Mkhitaryan", "Home Player 8": "Konstantinos Mavropanos", "Home Player 5": "Alex Iwobi", "Home Player 4": "Calum Chambers", "Home Player 7": "Alexandre Lacazette", "Home Player 6": "Sead Kolasinac", "Home Player 1": "Pierre-Emerick Aubameyang", "Home Player 3": "Petr Cech", "Home Player 2": "Hector Bellerin", "Away Player 10": "Stephen Ward", "Away Player 11": "Ashley Westwood", "Away Player 8": "Nick Pope", "Away Player 9": "James Tarkowski", "Away Player 1": "Ashley Barnes", "Away Player 2": "Jack Cork", "Away Player 3": "Johann Gudmundsson", "Away Player 4": "Jeff Hendrick", "Away Player 5": "Aaron Lennon", "Away Player 6": "Kevin Long", "Away Player 7": "Matthew Lowton", "Game ID": "g_1_I3uWQyBJ", "Home Player 11": "Granit Xhaka", "Home Player 10": "Jack Wilshere"}}