{"Stats": {"Full Time Result": "H", "Away Team Corners": 2, "Referee": "M Oliver", "Home Team Fouls Committed": 8, "Away Team Shots": 3, "Away Team Red Cards": 0, "Home Team Red Cards": 0, "Half Time Away Team Goals": 0, "Full Time Home Team Goals": 1, "Away Team Yellow Cards": 1, "Away Team Shots on Target": 0, "Half Time Home Team Goals": 0, "Half Time Result": "D", "Away Team Fouls Committed": 9, "Home Team Yellow Cards": 2, "Home Team Shots": 13, "Div": "E0", "Home Team Corners": 5, "Home Team Shots on Target": 3, "Full Time Away Team Goals": 0}, "Description": "Corner,  Manchester City. Conceded by César Azpilicueta. at minute 3. Bernardo Silva (Manchester City) wins a free kick in the attacking half. at minute 5. Foul by Marcos Alonso (Chelsea). at minute 5. Foul by Kevin De Bruyne (Manchester City). at minute 7. Pedro (Chelsea) wins a free kick in the defensive half. at minute 7. Attempt blocked. Leroy Sané (Manchester City) left footed shot from the centre of the box is blocked. Assisted by David Silva with a cross. at minute 11. Corner,  Manchester City. Conceded by Antonio Rüdiger. at minute 11. Attempt blocked. Sergio Agüero (Manchester City) right footed shot from the centre of the box is blocked. Assisted by Leroy Sané. at minute 13. Attempt blocked. Leroy Sané (Manchester City) left footed shot from the left side of the box is blocked. Assisted by Sergio Agüero. at minute 14. Offside, Manchester City. Leroy Sané tries a through ball, but Sergio Agüero is caught offside. at minute 14. Attempt missed. Leroy Sané (Manchester City) left footed shot from the left side of the box is high and wide to the left. Assisted by Kevin De Bruyne. at minute 16. Daniel Drinkwater (Chelsea) wins a free kick in the defensive half. at minute 19. Foul by Bernardo Silva (Manchester City). at minute 19. Attempt missed. Bernardo Silva (Manchester City) left footed shot from the right side of the box is just a bit too high. Assisted by Sergio Agüero. at minute 20. Oleksandr Zinchenko (Manchester City) is shown the yellow card for a bad foul. at minute 24. Foul by Antonio Rüdiger (Chelsea). at minute 26. Sergio Agüero (Manchester City) wins a free kick on the right wing. at minute 26. Attempt blocked. Leroy Sané (Manchester City) right footed shot from the left side of the box is blocked. Assisted by Kevin De Bruyne with a cross. at minute 27. Hand ball by Pedro (Chelsea). at minute 27. Foul by Eden Hazard (Chelsea). at minute 31. Nicolás Otamendi (Manchester City) wins a free kick in the defensive half. at minute 31. Antonio Rüdiger (Chelsea) wins a free kick in the defensive half. at minute 31. Foul by Kevin De Bruyne (Manchester City). at minute 31. Attempt missed. Bernardo Silva (Manchester City) left footed shot from the right side of the box is high and wide to the left. Assisted by Leroy Sané. at minute 33. Attempt blocked. David Silva (Manchester City) left footed shot from outside the box is blocked. Assisted by Sergio Agüero. at minute 34. Eden Hazard (Chelsea) wins a free kick in the defensive half. at minute 38. Foul by Bernardo Silva (Manchester City). at minute 38. Bernardo Silva (Manchester City) wins a free kick on the right wing. at minute 41. Foul by Antonio Rüdiger (Chelsea). at minute 41. Offside, Manchester City. Kevin De Bruyne tries a through ball, but Sergio Agüero is caught offside. at minute 42. Corner,  Chelsea. Conceded by Kyle Walker. at minute 42. Corner,  Manchester City. Conceded by César Azpilicueta. at minute 43. Andreas Christensen (Chelsea) wins a free kick in the defensive half. at minute 44. Foul by David Silva (Manchester City). at minute 44. Foul by Kevin De Bruyne (Manchester City). at minute 45. Pedro (Chelsea) wins a free kick in the defensive half. at minute 45. First Half ends, Manchester City 0, Chelsea 0. at minute 47. Second Half begins Manchester City 0, Chelsea 0. at minute 45. Goal!  Manchester City 1, Chelsea 0. Bernardo Silva (Manchester City) left footed shot from the centre of the box to the centre of the goal. Assisted by David Silva with a cross. at minute 46. Eden Hazard (Chelsea) wins a free kick in the attacking half. at minute 47. Foul by Ilkay Gündogan (Manchester City). at minute 47. Ilkay Gündogan (Manchester City) is shown the yellow card for a bad foul. at minute 47. Delay in match Eden Hazard (Chelsea) because of an injury. at minute 48. Delay over. They are ready to continue. at minute 48. Attempt missed. Victor Moses (Chelsea) right footed shot from a difficult angle on the right misses to the right. Assisted by Cesc Fàbregas. at minute 54. Attempt saved. David Silva (Manchester City) left footed shot from the left side of the box is saved in the top left corner. Assisted by Kevin De Bruyne. at minute 56. Bernardo Silva (Manchester City) wins a free kick on the right wing. at minute 57. Foul by Antonio Rüdiger (Chelsea). at minute 57. Antonio Rüdiger (Chelsea) is shown the yellow card. at minute 57. Attempt blocked. David Silva (Manchester City) left footed shot from outside the box is blocked. Assisted by Sergio Agüero. at minute 58. Corner,  Manchester City. Conceded by Daniel Drinkwater. at minute 58. Corner,  Manchester City. Conceded by Marcos Alonso. at minute 58. Foul by Oleksandr Zinchenko (Manchester City). at minute 61. Victor Moses (Chelsea) wins a free kick in the defensive half. at minute 61. Attempt missed. Kevin De Bruyne (Manchester City) right footed shot from outside the box is too high. Assisted by David Silva. at minute 66. Substitution, Chelsea. Olivier Giroud replaces Willian. at minute 78. Corner,  Chelsea. Conceded by Bernardo Silva. at minute 80. Attempt missed. Olivier Giroud (Chelsea) header from outside the box misses to the left. Assisted by Cesc Fàbregas. at minute 81. Substitution, Chelsea. Emerson replaces Pedro. at minute 82. Substitution, Manchester City. Gabriel Jesus replaces Sergio Agüero. at minute 85. Substitution, Manchester City. Danilo replaces Oleksandr Zinchenko. at minute 87. Offside, Chelsea. César Azpilicueta tries a through ball, but Eden Hazard is caught offside. at minute 88. Foul by Emerson (Chelsea). at minute 89. Kyle Walker (Manchester City) wins a free kick in the defensive half. at minute 89. David Silva (Manchester City) wins a free kick on the left wing. at minute 89. Foul by Daniel Drinkwater (Chelsea). at minute 89. Substitution, Chelsea. Álvaro Morata replaces Eden Hazard. at minute 90. Foul by Daniel Drinkwater (Chelsea). at minute 91. Kevin De Bruyne (Manchester City) wins a free kick in the defensive half. at minute 91. Attempt missed. Leroy Sané (Manchester City) right footed shot from outside the box is too high. Assisted by Kevin De Bruyne. at minute 92. Substitution, Manchester City. Phil Foden replaces David Silva. at minute 93. Attempt missed. Marcos Alonso (Chelsea) left footed shot from outside the box misses to the left. Assisted by Daniel Drinkwater. at minute 94. Second Half ends, Manchester City 1, Chelsea 0. at minute 95. Match ends, Manchester City 1, Chelsea 0. at minute 95. ", "Home Team": "Manchester City", "Away Team": "Chelsea", "Date": "2018-03-04", "Commentary": [["480618", "First Half begins.", "-", "Manchester City", "0", "0", "0", "1", "0", "0", "NA", "NA", "NA", "NA", "NA", "NA", "NA", "0", "NA", "NA", "0", "NA", "0", "0", "NA", "NA", "NA", "0", "NA", "NA", "NA", "0", "NA", "NA", "0", "NA", "0", "NA", "NA", "NA", "0", "NA", "NA", "0", "0", "NA", "NA", "NA", "0", "NA", "NA", "NA", "NA", "1", "1", "0", "NA", "NA", "NA"], ["480618", "Lineups are announced and players are warming up.", "-", "Manchester City", "0", "0", "0", "0", "0", "0", "NA", "NA", "NA", "NA", "NA", "NA", "NA", "0", "NA", "NA", "0", "NA", "0", "0", "NA", "NA", "NA", "0", "NA", "NA", "NA", "0", "NA", "NA", "0", "NA", "0", "NA", "NA", "NA", "0", "NA", "NA", "0", "0", "NA", "NA", "NA", "0", "NA", "NA", "NA", "NA", "1", "2", "0", "NA", "NA", "NA"], ["480618", "Corner,  Manchester City. Conceded by César Azpilicueta.", "3'", "Manchester City", "0", "0", "0", "0", "0", "0", "NA", "NA", "NA", "NA", "NA", "NA", "NA", "0", "NA", "NA", "0", "NA", "0", "0", "NA", "NA", "NA", "0", "NA", "NA", "NA", "0", "NA", "NA", "0", "NA", "0", "NA", "NA", "NA", "1", "Manchester City", "César Azpilicueta", "0", "0", "NA", "NA", "NA", "0", "NA", "NA", "NA", "NA", "1", "3", "0", "NA", "NA", "3"], ["480618", "Bernardo Silva (Manchester City) wins a free kick in the attacking half.", "5'", "Manchester City", "0", "0", "0", "0", "0", "0", "NA", "NA", "NA", "NA", "NA", "NA", "NA", "0", "NA", "NA", "0", "NA", "0", "0", "NA", "NA", "NA", "0", "NA", "NA", "NA", "0", "NA", "NA", "0", "NA", "1", "Bernardo Silva", "Manchester City", "attacking half", "0", "NA", "NA", "0", "0", "NA", "NA", "NA", "0", "NA", "NA", "NA", "NA", "1", "4", "0", "NA", "NA", "5"], ["480618", "Foul by Marcos Alonso (Chelsea).", "5'", "Manchester City", "0", "0", "0", "0", "0", "0", "NA", "NA", "NA", "NA", "NA", "NA", "NA", "1", "Marcos Alonso", "Chelsea", "0", "NA", "0", "0", "NA", "NA", "NA", "0", "NA", "NA", "NA", "0", "NA", "NA", "0", "NA", "0", "NA", "NA", "NA", "0", "NA", "NA", "0", "0", "NA", "NA", "NA", "0", "NA", "NA", "NA", "NA", "1", "5", "0", "NA", "NA", "5"], ["480618", "Foul by Kevin De Bruyne (Manchester City).", "7'", "Manchester City", "0", "0", "0", "0", "0", "0", "NA", "NA", "NA", "NA", "NA", "NA", "NA", "1", "Kevin De Bruyne", "Manchester City", "0", "NA", "0", "0", "NA", "NA", "NA", "0", "NA", "NA", "NA", "0", "NA", "NA", "0", "NA", "0", "NA", "NA", "NA", "0", "NA", "NA", "0", "0", "NA", "NA", "NA", "0", "NA", "NA", "NA", "NA", "1", "6", "0", "NA", "NA", "7"], ["480618", "Pedro (Chelsea) wins a free kick in the defensive half.", "7'", "Manchester City", "0", "0", "0", "0", "0", "0", "NA", "NA", "NA", "NA", "NA", "NA", "NA", "0", "NA", "NA", "0", "NA", "0", "0", "NA", "NA", "NA", "0", "NA", "NA", "NA", "0", "NA", "NA", "0", "NA", "1", "Pedro", "Chelsea", "defensive half", "0", "NA", "NA", "0", "0", "NA", "NA", "NA", "0", "NA", "NA", "NA", "NA", "1", "7", "0", "NA", "NA", "7"], ["480618", "Attempt blocked. Leroy Sané (Manchester City) left footed shot from the centre of the box is blocked. Assisted by David Silva with a cross.", "11'", "Manchester City", "0", "0", "0", "0", "1", "0", "blocked", "Leroy Sané", "Manchester City", "left", "the centre of the box", "NA", "David Silva", "0", "NA", "NA", "0", "cross", "0", "0", "NA", "NA", "NA", "0", "NA", "NA", "NA", "0", "NA", "NA", "0", "NA", "0", "NA", "NA", "NA", "0", "NA", "NA", "0", "0", "NA", "NA", "NA", "0", "NA", "NA", "NA", "NA", "1", "8", "0", "NA", "NA", "11"], ["480618", "Corner,  Manchester City. Conceded by Antonio Rüdiger.", "11'", "Manchester City", "0", "0", "0", "0", "0", "0", "NA", "NA", "NA", "NA", "NA", "NA", "NA", "0", "NA", "NA", "0", "NA", "0", "0", "NA", "NA", "NA", "0", "NA", "NA", "NA", "0", "NA", "NA", "0", "NA", "0", "NA", "NA", "NA", "1", "Manchester City", "Antonio Rüdiger", "0", "0", "NA", "NA", "NA", "0", "NA", "NA", "NA", "NA", "1", "9", "0", "NA", "NA", "11"], ["480618", "Attempt blocked. Sergio Agüero (Manchester City) right footed shot from the centre of the box is blocked. Assisted by Leroy Sané.", "13'", "Manchester City", "0", "0", "0", "0", "1", "0", "blocked", "Sergio Agüero", "Manchester City", "right", "the centre of the box", "NA", "Leroy Sané", "0", "NA", "NA", "0", "NA", "0", "0", "NA", "NA", "NA", "0", "NA", "NA", "NA", "0", "NA", "NA", "0", "NA", "0", "NA", "NA", "NA", "0", "NA", "NA", "0", "0", "NA", "NA", "NA", "0", "NA", "NA", "NA", "NA", "1", "10", "0", "NA", "NA", "13"], ["480618", "Attempt blocked. Leroy Sané (Manchester City) left footed shot from the left side of the box is blocked. Assisted by Sergio Agüero.", "14'", "Manchester City", "0", "0", "0", "0", "1", "0", "blocked", "Leroy Sané", "Manchester City", "left", "the left side of the box", "NA", "Sergio Agüero", "0", "NA", "NA", "0", "NA", "0", "0", "NA", "NA", "NA", "0", "NA", "NA", "NA", "0", "NA", "NA", "0", "NA", "0", "NA", "NA", "NA", "0", "NA", "NA", "0", "0", "NA", "NA", "NA", "0", "NA", "NA", "NA", "NA", "1", "11", "0", "NA", "NA", "14"], ["480618", "Offside, Manchester City. Leroy Sané tries a through ball, but Sergio Agüero is caught offside.", "14'", "Manchester City", "0", "0", "0", "0", "0", "0", "NA", "NA", "NA", "NA", "NA", "NA", "NA", "0", "NA", "NA", "0", "NA", "0", "1", "Manchester City", "Sergio Agüero", "Leroy Sané", "0", "NA", "NA", "NA", "0", "NA", "NA", "0", "NA", "0", "NA", "NA", "NA", "0", "NA", "NA", "0", "0", "NA", "NA", "NA", "0", "NA", "NA", "NA", "NA", "1", "12", "0", "NA", "NA", "14"], ["480618", "Attempt missed. Leroy Sané (Manchester City) left footed shot from the left side of the box is high and wide to the left. Assisted by Kevin De Bruyne.", "16'", "Manchester City", "0", "0", "0", "0", "1", "0", "missed", "Leroy Sané", "Manchester City", "left", "the left side of the box", "high and wide to the left", "Kevin De Bruyne", "0", "NA", "NA", "0", "NA", "0", "0", "NA", "NA", "NA", "0", "NA", "NA", "NA", "0", "NA", "NA", "0", "NA", "0", "NA", "NA", "NA", "0", "NA", "NA", "0", "0", "NA", "NA", "NA", "0", "NA", "NA", "NA", "NA", "1", "13", "0", "NA", "NA", "16"], ["480618", "Daniel Drinkwater (Chelsea) wins a free kick in the defensive half.", "19'", "Manchester City", "0", "0", "0", "0", "0", "0", "NA", "NA", "NA", "NA", "NA", "NA", "NA", "0", "NA", "NA", "0", "NA", "0", "0", "NA", "NA", "NA", "0", "NA", "NA", "NA", "0", "NA", "NA", "0", "NA", "1", "Daniel Drinkwater", "Chelsea", "defensive half", "0", "NA", "NA", "0", "0", "NA", "NA", "NA", "0", "NA", "NA", "NA", "NA", "1", "14", "0", "NA", "NA", "19"], ["480618", "Foul by Bernardo Silva (Manchester City).", "19'", "Manchester City", "0", "0", "0", "0", "0", "0", "NA", "NA", "NA", "NA", "NA", "NA", "NA", "1", "Bernardo Silva", "Manchester City", "0", "NA", "0", "0", "NA", "NA", "NA", "0", "NA", "NA", "NA", "0", "NA", "NA", "0", "NA", "0", "NA", "NA", "NA", "0", "NA", "NA", "0", "0", "NA", "NA", "NA", "0", "NA", "NA", "NA", "NA", "1", "15", "0", "NA", "NA", "19"], ["480618", "Attempt missed. Bernardo Silva (Manchester City) left footed shot from the right side of the box is just a bit too high. Assisted by Sergio Agüero.", "20'", "Manchester City", "0", "0", "0", "0", "1", "0", "missed", "Bernardo Silva", "Manchester City", "left", "the right side of the box", "just a bit too high", "Sergio Agüero", "0", "NA", "NA", "0", "NA", "0", "0", "NA", "NA", "NA", "0", "NA", "NA", "NA", "0", "NA", "NA", "0", "NA", "0", "NA", "NA", "NA", "0", "NA", "NA", "0", "0", "NA", "NA", "NA", "0", "NA", "NA", "NA", "NA", "1", "16", "0", "NA", "NA", "20"], ["480618", "Oleksandr Zinchenko (Manchester City) is shown the yellow card for a bad foul.", "24'", "Manchester City", "0", "0", "0", "0", "0", "0", "NA", "NA", "NA", "NA", "NA", "NA", "NA", "0", "NA", "NA", "0", "NA", "0", "0", "NA", "NA", "NA", "1", "yellow", "Oleksandr Zinchenko", "Manchester City", "0", "NA", "NA", "0", "NA", "0", "NA", "NA", "NA", "0", "NA", "NA", "0", "0", "NA", "NA", "NA", "0", "NA", "NA", "NA", "NA", "1", "17", "0", "NA", "NA", "24"], ["480618", "Foul by Antonio Rüdiger (Chelsea).", "26'", "Manchester City", "0", "0", "0", "0", "0", "0", "NA", "NA", "NA", "NA", "NA", "NA", "NA", "1", "Antonio Rüdiger", "Chelsea", "0", "NA", "0", "0", "NA", "NA", "NA", "0", "NA", "NA", "NA", "0", "NA", "NA", "0", "NA", "0", "NA", "NA", "NA", "0", "NA", "NA", "0", "0", "NA", "NA", "NA", "0", "NA", "NA", "NA", "NA", "1", "18", "0", "NA", "NA", "26"], ["480618", "Sergio Agüero (Manchester City) wins a free kick on the right wing.", "26'", "Manchester City", "0", "0", "0", "0", "0", "0", "NA", "NA", "NA", "NA", "NA", "NA", "NA", "0", "NA", "NA", "0", "NA", "0", "0", "NA", "NA", "NA", "0", "NA", "NA", "NA", "0", "NA", "NA", "0", "NA", "1", "Sergio Agüero", "Manchester City", "NA", "0", "NA", "NA", "0", "0", "NA", "NA", "NA", "0", "NA", "NA", "NA", "NA", "1", "19", "0", "NA", "NA", "26"], ["480618", "Attempt blocked. Leroy Sané (Manchester City) right footed shot from the left side of the box is blocked. Assisted by Kevin De Bruyne with a cross.", "27'", "Manchester City", "0", "0", "0", "0", "1", "0", "blocked", "Leroy Sané", "Manchester City", "right", "the left side of the box", "NA", "Kevin De Bruyne", "0", "NA", "NA", "0", "cross", "0", "0", "NA", "NA", "NA", "0", "NA", "NA", "NA", "0", "NA", "NA", "0", "NA", "0", "NA", "NA", "NA", "0", "NA", "NA", "0", "0", "NA", "NA", "NA", "0", "NA", "NA", "NA", "NA", "1", "20", "0", "NA", "NA", "27"], ["480618", "Hand ball by Pedro (Chelsea).", "27'", "Manchester City", "0", "0", "0", "0", "0", "0", "NA", "NA", "NA", "NA", "NA", "NA", "NA", "0", "NA", "NA", "0", "NA", "0", "0", "NA", "NA", "NA", "0", "NA", "NA", "NA", "0", "NA", "NA", "0", "NA", "0", "NA", "NA", "NA", "0", "NA", "NA", "0", "0", "NA", "NA", "NA", "0", "NA", "NA", "NA", "NA", "1", "21", "0", "NA", "NA", "27"], ["480618", "Foul by Eden Hazard (Chelsea).", "31'", "Manchester City", "0", "0", "0", "0", "0", "0", "NA", "NA", "NA", "NA", "NA", "NA", "NA", "1", "Eden Hazard", "Chelsea", "0", "NA", "0", "0", "NA", "NA", "NA", "0", "NA", "NA", "NA", "0", "NA", "NA", "0", "NA", "0", "NA", "NA", "NA", "0", "NA", "NA", "0", "0", "NA", "NA", "NA", "0", "NA", "NA", "NA", "NA", "1", "22", "0", "NA", "NA", "31"], ["480618", "Nicolás Otamendi (Manchester City) wins a free kick in the defensive half.", "31'", "Manchester City", "0", "0", "0", "0", "0", "0", "NA", "NA", "NA", "NA", "NA", "NA", "NA", "0", "NA", "NA", "0", "NA", "0", "0", "NA", "NA", "NA", "0", "NA", "NA", "NA", "0", "NA", "NA", "0", "NA", "1", "Nicolás Otamendi", "Manchester City", "defensive half", "0", "NA", "NA", "0", "0", "NA", "NA", "NA", "0", "NA", "NA", "NA", "NA", "1", "23", "0", "NA", "NA", "31"], ["480618", "Antonio Rüdiger (Chelsea) wins a free kick in the defensive half.", "31'", "Manchester City", "0", "0", "0", "0", "0", "0", "NA", "NA", "NA", "NA", "NA", "NA", "NA", "0", "NA", "NA", "0", "NA", "0", "0", "NA", "NA", "NA", "0", "NA", "NA", "NA", "0", "NA", "NA", "0", "NA", "1", "Antonio Rüdiger", "Chelsea", "defensive half", "0", "NA", "NA", "0", "0", "NA", "NA", "NA", "0", "NA", "NA", "NA", "NA", "1", "24", "0", "NA", "NA", "31"], ["480618", "Foul by Kevin De Bruyne (Manchester City).", "31'", "Manchester City", "0", "0", "0", "0", "0", "0", "NA", "NA", "NA", "NA", "NA", "NA", "NA", "1", "Kevin De Bruyne", "Manchester City", "0", "NA", "0", "0", "NA", "NA", "NA", "0", "NA", "NA", "NA", "0", "NA", "NA", "0", "NA", "0", "NA", "NA", "NA", "0", "NA", "NA", "0", "0", "NA", "NA", "NA", "0", "NA", "NA", "NA", "NA", "1", "25", "0", "NA", "NA", "31"], ["480618", "Attempt missed. Bernardo Silva (Manchester City) left footed shot from the right side of the box is high and wide to the left. Assisted by Leroy Sané.", "33'", "Manchester City", "0", "0", "0", "0", "1", "0", "missed", "Bernardo Silva", "Manchester City", "left", "the right side of the box", "high and wide to the left", "Leroy Sané", "0", "NA", "NA", "0", "NA", "0", "0", "NA", "NA", "NA", "0", "NA", "NA", "NA", "0", "NA", "NA", "0", "NA", "0", "NA", "NA", "NA", "0", "NA", "NA", "0", "0", "NA", "NA", "NA", "0", "NA", "NA", "NA", "NA", "1", "26", "0", "NA", "NA", "33"], ["480618", "Attempt blocked. David Silva (Manchester City) left footed shot from outside the box is blocked. Assisted by Sergio Agüero.", "34'", "Manchester City", "0", "0", "0", "0", "1", "0", "blocked", "David Silva", "Manchester City", "left", "outside the box", "NA", "Sergio Agüero", "0", "NA", "NA", "0", "NA", "0", "0", "NA", "NA", "NA", "0", "NA", "NA", "NA", "0", "NA", "NA", "0", "NA", "0", "NA", "NA", "NA", "0", "NA", "NA", "0", "0", "NA", "NA", "NA", "0", "NA", "NA", "NA", "NA", "1", "27", "0", "NA", "NA", "34"], ["480618", "Eden Hazard (Chelsea) wins a free kick in the defensive half.", "38'", "Manchester City", "0", "0", "0", "0", "0", "0", "NA", "NA", "NA", "NA", "NA", "NA", "NA", "0", "NA", "NA", "0", "NA", "0", "0", "NA", "NA", "NA", "0", "NA", "NA", "NA", "0", "NA", "NA", "0", "NA", "1", "Eden Hazard", "Chelsea", "defensive half", "0", "NA", "NA", "0", "0", "NA", "NA", "NA", "0", "NA", "NA", "NA", "NA", "1", "28", "0", "NA", "NA", "38"], ["480618", "Foul by Bernardo Silva (Manchester City).", "38'", "Manchester City", "0", "0", "0", "0", "0", "0", "NA", "NA", "NA", "NA", "NA", "NA", "NA", "1", "Bernardo Silva", "Manchester City", "0", "NA", "0", "0", "NA", "NA", "NA", "0", "NA", "NA", "NA", "0", "NA", "NA", "0", "NA", "0", "NA", "NA", "NA", "0", "NA", "NA", "0", "0", "NA", "NA", "NA", "0", "NA", "NA", "NA", "NA", "1", "29", "0", "NA", "NA", "38"], ["480618", "Bernardo Silva (Manchester City) wins a free kick on the right wing.", "41'", "Manchester City", "0", "0", "0", "0", "0", "0", "NA", "NA", "NA", "NA", "NA", "NA", "NA", "0", "NA", "NA", "0", "NA", "0", "0", "NA", "NA", "NA", "0", "NA", "NA", "NA", "0", "NA", "NA", "0", "NA", "1", "Bernardo Silva", "Manchester City", "NA", "0", "NA", "NA", "0", "0", "NA", "NA", "NA", "0", "NA", "NA", "NA", "NA", "1", "30", "0", "NA", "NA", "41"], ["480618", "Foul by Antonio Rüdiger (Chelsea).", "41'", "Manchester City", "0", "0", "0", "0", "0", "0", "NA", "NA", "NA", "NA", "NA", "NA", "NA", "1", "Antonio Rüdiger", "Chelsea", "0", "NA", "0", "0", "NA", "NA", "NA", "0", "NA", "NA", "NA", "0", "NA", "NA", "0", "NA", "0", "NA", "NA", "NA", "0", "NA", "NA", "0", "0", "NA", "NA", "NA", "0", "NA", "NA", "NA", "NA", "1", "31", "0", "NA", "NA", "41"], ["480618", "Offside, Manchester City. Kevin De Bruyne tries a through ball, but Sergio Agüero is caught offside.", "42'", "Manchester City", "0", "0", "0", "0", "0", "0", "NA", "NA", "NA", "NA", "NA", "NA", "NA", "0", "NA", "NA", "0", "NA", "0", "1", "Manchester City", "Sergio Agüero", "Kevin De Bruyne", "0", "NA", "NA", "NA", "0", "NA", "NA", "0", "NA", "0", "NA", "NA", "NA", "0", "NA", "NA", "0", "0", "NA", "NA", "NA", "0", "NA", "NA", "NA", "NA", "1", "32", "0", "NA", "NA", "42"], ["480618", "Corner,  Chelsea. Conceded by Kyle Walker.", "42'", "Manchester City", "0", "0", "0", "0", "0", "0", "NA", "NA", "NA", "NA", "NA", "NA", "NA", "0", "NA", "NA", "0", "NA", "0", "0", "NA", "NA", "NA", "0", "NA", "NA", "NA", "0", "NA", "NA", "0", "NA", "0", "NA", "NA", "NA", "1", "Chelsea", "Kyle Walker", "0", "0", "NA", "NA", "NA", "0", "NA", "NA", "NA", "NA", "1", "33", "0", "NA", "NA", "42"], ["480618", "Corner,  Manchester City. Conceded by César Azpilicueta.", "43'", "Manchester City", "0", "0", "0", "0", "0", "0", "NA", "NA", "NA", "NA", "NA", "NA", "NA", "0", "NA", "NA", "0", "NA", "0", "0", "NA", "NA", "NA", "0", "NA", "NA", "NA", "0", "NA", "NA", "0", "NA", "0", "NA", "NA", "NA", "1", "Manchester City", "César Azpilicueta", "0", "0", "NA", "NA", "NA", "0", "NA", "NA", "NA", "NA", "1", "34", "0", "NA", "NA", "43"], ["480618", "Andreas Christensen (Chelsea) wins a free kick in the defensive half.", "44'", "Manchester City", "0", "0", "0", "0", "0", "0", "NA", "NA", "NA", "NA", "NA", "NA", "NA", "0", "NA", "NA", "0", "NA", "0", "0", "NA", "NA", "NA", "0", "NA", "NA", "NA", "0", "NA", "NA", "0", "NA", "1", "Andreas Christensen", "Chelsea", "defensive half", "0", "NA", "NA", "0", "0", "NA", "NA", "NA", "0", "NA", "NA", "NA", "NA", "1", "35", "0", "NA", "NA", "44"], ["480618", "Foul by David Silva (Manchester City).", "44'", "Manchester City", "0", "0", "0", "0", "0", "0", "NA", "NA", "NA", "NA", "NA", "NA", "NA", "1", "David Silva", "Manchester City", "0", "NA", "0", "0", "NA", "NA", "NA", "0", "NA", "NA", "NA", "0", "NA", "NA", "0", "NA", "0", "NA", "NA", "NA", "0", "NA", "NA", "0", "0", "NA", "NA", "NA", "0", "NA", "NA", "NA", "NA", "1", "36", "0", "NA", "NA", "44"], ["480618", "Foul by Kevin De Bruyne (Manchester City).", "45'", "Manchester City", "0", "0", "0", "0", "0", "0", "NA", "NA", "NA", "NA", "NA", "NA", "NA", "1", "Kevin De Bruyne", "Manchester City", "0", "NA", "0", "0", "NA", "NA", "NA", "0", "NA", "NA", "NA", "0", "NA", "NA", "0", "NA", "0", "NA", "NA", "NA", "0", "NA", "NA", "0", "0", "NA", "NA", "NA", "0", "NA", "NA", "NA", "NA", "1", "37", "0", "NA", "NA", "45"], ["480618", "Pedro (Chelsea) wins a free kick in the defensive half.", "45'", "Manchester City", "0", "0", "0", "0", "0", "0", "NA", "NA", "NA", "NA", "NA", "NA", "NA", "0", "NA", "NA", "0", "NA", "0", "0", "NA", "NA", "NA", "0", "NA", "NA", "NA", "0", "NA", "NA", "0", "NA", "1", "Pedro", "Chelsea", "defensive half", "0", "NA", "NA", "0", "0", "NA", "NA", "NA", "0", "NA", "NA", "NA", "NA", "1", "38", "0", "NA", "NA", "45"], ["480618", "First Half ends, Manchester City 0, Chelsea 0.", "45'+2'", "Manchester City", "0", "1", "0", "0", "0", "0", "NA", "NA", "NA", "NA", "NA", "NA", "NA", "0", "NA", "NA", "0", "NA", "0", "0", "NA", "NA", "NA", "0", "NA", "NA", "NA", "0", "NA", "NA", "0", "NA", "0", "NA", "NA", "NA", "0", "NA", "NA", "0", "0", "NA", "NA", "NA", "0", "NA", "NA", "NA", "NA", "1", "39", "1", "NA", "NA", "47"], ["480618", "Second Half begins Manchester City 0, Chelsea 0.", "45'", "Manchester City", "0", "0", "0", "1", "0", "0", "NA", "NA", "NA", "NA", "NA", "NA", "NA", "0", "NA", "NA", "0", "NA", "0", "0", "NA", "NA", "NA", "0", "NA", "NA", "NA", "0", "NA", "NA", "0", "NA", "0", "NA", "NA", "NA", "0", "NA", "NA", "0", "0", "NA", "NA", "NA", "0", "NA", "NA", "NA", "NA", "2", "40", "0", "NA", "NA", "45"], ["480618", "Goal!  Manchester City 1, Chelsea 0. Bernardo Silva (Manchester City) left footed shot from the centre of the box to the centre of the goal. Assisted by David Silva with a cross.", "46'", "Manchester City", "1", "0", "0", "0", "1", "0", "goal", "Bernardo Silva", "Manchester City", "left", "the centre of the box", "centre of the goal", "David Silva", "0", "NA", "NA", "0", "cross", "0", "0", "NA", "NA", "NA", "0", "NA", "NA", "NA", "0", "NA", "NA", "0", "NA", "0", "NA", "NA", "NA", "0", "NA", "NA", "0", "0", "NA", "NA", "NA", "0", "NA", "NA", "NA", "NA", "2", "41", "0", "NA", "NA", "46"], ["480618", "Eden Hazard (Chelsea) wins a free kick in the attacking half.", "47'", "Manchester City", "1", "0", "0", "0", "0", "0", "NA", "NA", "NA", "NA", "NA", "NA", "NA", "0", "NA", "NA", "0", "NA", "0", "0", "NA", "NA", "NA", "0", "NA", "NA", "NA", "0", "NA", "NA", "0", "NA", "1", "Eden Hazard", "Chelsea", "attacking half", "0", "NA", "NA", "0", "0", "NA", "NA", "NA", "0", "NA", "NA", "NA", "NA", "2", "42", "0", "NA", "NA", "47"], ["480618", "Foul by Ilkay Gündogan (Manchester City).", "47'", "Manchester City", "1", "0", "0", "0", "0", "0", "NA", "NA", "NA", "NA", "NA", "NA", "NA", "1", "Ilkay Gündogan", "Manchester City", "0", "NA", "0", "0", "NA", "NA", "NA", "0", "NA", "NA", "NA", "0", "NA", "NA", "0", "NA", "0", "NA", "NA", "NA", "0", "NA", "NA", "0", "0", "NA", "NA", "NA", "0", "NA", "NA", "NA", "NA", "2", "43", "0", "NA", "NA", "47"], ["480618", "Ilkay Gündogan (Manchester City) is shown the yellow card for a bad foul.", "47'", "Manchester City", "1", "0", "0", "0", "0", "0", "NA", "NA", "NA", "NA", "NA", "NA", "NA", "0", "NA", "NA", "0", "NA", "0", "0", "NA", "NA", "NA", "1", "yellow", "Ilkay Gündogan", "Manchester City", "0", "NA", "NA", "0", "NA", "0", "NA", "NA", "NA", "0", "NA", "NA", "0", "0", "NA", "NA", "NA", "0", "NA", "NA", "NA", "NA", "2", "44", "0", "NA", "NA", "47"], ["480618", "Delay in match Eden Hazard (Chelsea) because of an injury.", "48'", "Manchester City", "1", "0", "0", "0", "0", "0", "NA", "NA", "NA", "NA", "NA", "NA", "NA", "0", "NA", "NA", "0", "NA", "0", "0", "NA", "NA", "NA", "0", "NA", "NA", "NA", "0", "NA", "NA", "1", "Chelsea", "0", "NA", "NA", "NA", "0", "NA", "NA", "0", "0", "NA", "NA", "NA", "0", "NA", "NA", "NA", "NA", "2", "45", "0", "NA", "NA", "48"], ["480618", "Delay over. They are ready to continue.", "48'", "Manchester City", "1", "0", "0", "0", "0", "0", "NA", "NA", "NA", "NA", "NA", "NA", "NA", "0", "NA", "NA", "0", "NA", "0", "0", "NA", "NA", "NA", "0", "NA", "NA", "NA", "0", "NA", "NA", "0", "NA", "0", "NA", "NA", "NA", "0", "NA", "NA", "0", "0", "NA", "NA", "NA", "0", "NA", "NA", "NA", "NA", "2", "46", "0", "NA", "NA", "48"], ["480618", "Attempt missed. Victor Moses (Chelsea) right footed shot from a difficult angle on the right misses to the right. Assisted by Cesc Fàbregas.", "54'", "Manchester City", "1", "0", "0", "0", "1", "0", "missed", "Victor Moses", "Chelsea", "right", "NA", "NA", "Cesc Fàbregas", "0", "NA", "NA", "0", "NA", "0", "0", "NA", "NA", "NA", "0", "NA", "NA", "NA", "0", "NA", "NA", "0", "NA", "0", "NA", "NA", "NA", "0", "NA", "NA", "0", "0", "NA", "NA", "NA", "0", "NA", "NA", "NA", "NA", "2", "47", "0", "NA", "NA", "54"], ["480618", "Attempt saved. David Silva (Manchester City) left footed shot from the left side of the box is saved in the top left corner. Assisted by Kevin De Bruyne.", "56'", "Manchester City", "1", "0", "0", "0", "1", "0", "saved", "David Silva", "Manchester City", "left", "the left side of the box", "the top left corner", "Kevin De Bruyne", "0", "NA", "NA", "0", "NA", "0", "0", "NA", "NA", "NA", "0", "NA", "NA", "NA", "0", "NA", "NA", "0", "NA", "0", "NA", "NA", "NA", "0", "NA", "NA", "0", "0", "NA", "NA", "NA", "0", "NA", "NA", "NA", "NA", "2", "48", "0", "NA", "NA", "56"], ["480618", "Bernardo Silva (Manchester City) wins a free kick on the right wing.", "57'", "Manchester City", "1", "0", "0", "0", "0", "0", "NA", "NA", "NA", "NA", "NA", "NA", "NA", "0", "NA", "NA", "0", "NA", "0", "0", "NA", "NA", "NA", "0", "NA", "NA", "NA", "0", "NA", "NA", "0", "NA", "1", "Bernardo Silva", "Manchester City", "NA", "0", "NA", "NA", "0", "0", "NA", "NA", "NA", "0", "NA", "NA", "NA", "NA", "2", "49", "0", "NA", "NA", "57"], ["480618", "Foul by Antonio Rüdiger (Chelsea).", "57'", "Manchester City", "1", "0", "0", "0", "0", "0", "NA", "NA", "NA", "NA", "NA", "NA", "NA", "1", "Antonio Rüdiger", "Chelsea", "0", "NA", "0", "0", "NA", "NA", "NA", "0", "NA", "NA", "NA", "0", "NA", "NA", "0", "NA", "0", "NA", "NA", "NA", "0", "NA", "NA", "0", "0", "NA", "NA", "NA", "0", "NA", "NA", "NA", "NA", "2", "50", "0", "NA", "NA", "57"], ["480618", "Antonio Rüdiger (Chelsea) is shown the yellow card.", "57'", "Manchester City", "1", "0", "0", "0", "0", "0", "NA", "NA", "NA", "NA", "NA", "NA", "NA", "0", "NA", "NA", "0", "NA", "0", "0", "NA", "NA", "NA", "1", "yellow", "Antonio Rüdiger", "Chelsea", "0", "NA", "NA", "0", "NA", "0", "NA", "NA", "NA", "0", "NA", "NA", "0", "0", "NA", "NA", "NA", "0", "NA", "NA", "NA", "NA", "2", "51", "0", "NA", "NA", "57"], ["480618", "Attempt blocked. David Silva (Manchester City) left footed shot from outside the box is blocked. Assisted by Sergio Agüero.", "58'", "Manchester City", "1", "0", "0", "0", "1", "0", "blocked", "David Silva", "Manchester City", "left", "outside the box", "NA", "Sergio Agüero", "0", "NA", "NA", "0", "NA", "0", "0", "NA", "NA", "NA", "0", "NA", "NA", "NA", "0", "NA", "NA", "0", "NA", "0", "NA", "NA", "NA", "0", "NA", "NA", "0", "0", "NA", "NA", "NA", "0", "NA", "NA", "NA", "NA", "2", "52", "0", "NA", "NA", "58"], ["480618", "Corner,  Manchester City. Conceded by Daniel Drinkwater.", "58'", "Manchester City", "1", "0", "0", "0", "0", "0", "NA", "NA", "NA", "NA", "NA", "NA", "NA", "0", "NA", "NA", "0", "NA", "0", "0", "NA", "NA", "NA", "0", "NA", "NA", "NA", "0", "NA", "NA", "0", "NA", "0", "NA", "NA", "NA", "1", "Manchester City", "Daniel Drinkwater", "0", "0", "NA", "NA", "NA", "0", "NA", "NA", "NA", "NA", "2", "53", "0", "NA", "NA", "58"], ["480618", "Corner,  Manchester City. Conceded by Marcos Alonso.", "58'", "Manchester City", "1", "0", "0", "0", "0", "0", "NA", "NA", "NA", "NA", "NA", "NA", "NA", "0", "NA", "NA", "0", "NA", "0", "0", "NA", "NA", "NA", "0", "NA", "NA", "NA", "0", "NA", "NA", "0", "NA", "0", "NA", "NA", "NA", "1", "Manchester City", "Marcos Alonso", "0", "0", "NA", "NA", "NA", "0", "NA", "NA", "NA", "NA", "2", "54", "0", "NA", "NA", "58"], ["480618", "Foul by Oleksandr Zinchenko (Manchester City).", "61'", "Manchester City", "1", "0", "0", "0", "0", "0", "NA", "NA", "NA", "NA", "NA", "NA", "NA", "1", "Oleksandr Zinchenko", "Manchester City", "0", "NA", "0", "0", "NA", "NA", "NA", "0", "NA", "NA", "NA", "0", "NA", "NA", "0", "NA", "0", "NA", "NA", "NA", "0", "NA", "NA", "0", "0", "NA", "NA", "NA", "0", "NA", "NA", "NA", "NA", "2", "55", "0", "NA", "NA", "61"], ["480618", "Victor Moses (Chelsea) wins a free kick in the defensive half.", "61'", "Manchester City", "1", "0", "0", "0", "0", "0", "NA", "NA", "NA", "NA", "NA", "NA", "NA", "0", "NA", "NA", "0", "NA", "0", "0", "NA", "NA", "NA", "0", "NA", "NA", "NA", "0", "NA", "NA", "0", "NA", "1", "Victor Moses", "Chelsea", "defensive half", "0", "NA", "NA", "0", "0", "NA", "NA", "NA", "0", "NA", "NA", "NA", "NA", "2", "56", "0", "NA", "NA", "61"], ["480618", "Attempt missed. Kevin De Bruyne (Manchester City) right footed shot from outside the box is too high. Assisted by David Silva.", "66'", "Manchester City", "1", "0", "0", "0", "1", "0", "missed", "Kevin De Bruyne", "Manchester City", "right", "outside the box", "too high", "David Silva", "0", "NA", "NA", "0", "NA", "0", "0", "NA", "NA", "NA", "0", "NA", "NA", "NA", "0", "NA", "NA", "0", "NA", "0", "NA", "NA", "NA", "0", "NA", "NA", "0", "0", "NA", "NA", "NA", "0", "NA", "NA", "NA", "NA", "2", "57", "0", "NA", "NA", "66"], ["480618", "Substitution, Chelsea. Olivier Giroud replaces Willian.", "78'", "Manchester City", "1", "0", "0", "0", "0", "0", "NA", "NA", "NA", "NA", "NA", "NA", "NA", "0", "NA", "NA", "0", "NA", "0", "0", "NA", "NA", "NA", "0", "NA", "NA", "NA", "0", "NA", "NA", "0", "NA", "0", "NA", "NA", "NA", "0", "NA", "NA", "1", "0", "Chelsea", "Olivier Giroud", "Willian", "0", "NA", "NA", "NA", "NA", "2", "58", "0", "NA", "NA", "78"], ["480618", "Corner,  Chelsea. Conceded by Bernardo Silva.", "80'", "Manchester City", "1", "0", "0", "0", "0", "0", "NA", "NA", "NA", "NA", "NA", "NA", "NA", "0", "NA", "NA", "0", "NA", "0", "0", "NA", "NA", "NA", "0", "NA", "NA", "NA", "0", "NA", "NA", "0", "NA", "0", "NA", "NA", "NA", "1", "Chelsea", "Bernardo Silva", "0", "0", "NA", "NA", "NA", "0", "NA", "NA", "NA", "NA", "2", "59", "0", "NA", "NA", "80"], ["480618", "Attempt missed. Olivier Giroud (Chelsea) header from outside the box misses to the left. Assisted by Cesc Fàbregas.", "81'", "Manchester City", "1", "0", "0", "0", "1", "0", "missed", "Olivier Giroud", "Chelsea", "header", "outside the box", "left", "Cesc Fàbregas", "0", "NA", "NA", "0", "NA", "0", "0", "NA", "NA", "NA", "0", "NA", "NA", "NA", "0", "NA", "NA", "0", "NA", "0", "NA", "NA", "NA", "0", "NA", "NA", "0", "0", "NA", "NA", "NA", "0", "NA", "NA", "NA", "NA", "2", "60", "0", "NA", "NA", "81"], ["480618", "Substitution, Chelsea. Emerson replaces Pedro.", "82'", "Manchester City", "1", "0", "0", "0", "0", "0", "NA", "NA", "NA", "NA", "NA", "NA", "NA", "0", "NA", "NA", "0", "NA", "0", "0", "NA", "NA", "NA", "0", "NA", "NA", "NA", "0", "NA", "NA", "0", "NA", "0", "NA", "NA", "NA", "0", "NA", "NA", "1", "0", "Chelsea", "Emerson", "Pedro", "0", "NA", "NA", "NA", "NA", "2", "61", "0", "NA", "NA", "82"], ["480618", "Substitution, Manchester City. Gabriel Jesus replaces Sergio Agüero.", "85'", "Manchester City", "1", "0", "0", "0", "0", "0", "NA", "NA", "NA", "NA", "NA", "NA", "NA", "0", "NA", "NA", "0", "NA", "0", "0", "NA", "NA", "NA", "0", "NA", "NA", "NA", "0", "NA", "NA", "0", "NA", "0", "NA", "NA", "NA", "0", "NA", "NA", "1", "0", "Manchester City", "Gabriel Jesus", "Sergio Agüero", "0", "NA", "NA", "NA", "NA", "2", "62", "0", "NA", "NA", "85"], ["480618", "Substitution, Manchester City. Danilo replaces Oleksandr Zinchenko.", "87'", "Manchester City", "1", "0", "0", "0", "0", "0", "NA", "NA", "NA", "NA", "NA", "NA", "NA", "0", "NA", "NA", "0", "NA", "0", "0", "NA", "NA", "NA", "0", "NA", "NA", "NA", "0", "NA", "NA", "0", "NA", "0", "NA", "NA", "NA", "0", "NA", "NA", "1", "0", "Manchester City", "Danilo", "Oleksandr Zinchenko", "0", "NA", "NA", "NA", "NA", "2", "63", "0", "NA", "NA", "87"], ["480618", "Offside, Chelsea. César Azpilicueta tries a through ball, but Eden Hazard is caught offside.", "88'", "Manchester City", "1", "0", "0", "0", "0", "0", "NA", "NA", "NA", "NA", "NA", "NA", "NA", "0", "NA", "NA", "0", "NA", "0", "1", "Chelsea", "Eden Hazard", "César Azpilicueta", "0", "NA", "NA", "NA", "0", "NA", "NA", "0", "NA", "0", "NA", "NA", "NA", "0", "NA", "NA", "0", "0", "NA", "NA", "NA", "0", "NA", "NA", "NA", "NA", "2", "64", "0", "NA", "NA", "88"], ["480618", "Foul by Emerson (Chelsea).", "89'", "Manchester City", "1", "0", "0", "0", "0", "0", "NA", "NA", "NA", "NA", "NA", "NA", "NA", "1", "Emerson", "Chelsea", "0", "NA", "0", "0", "NA", "NA", "NA", "0", "NA", "NA", "NA", "0", "NA", "NA", "0", "NA", "0", "NA", "NA", "NA", "0", "NA", "NA", "0", "0", "NA", "NA", "NA", "0", "NA", "NA", "NA", "NA", "2", "65", "0", "NA", "NA", "89"], ["480618", "Kyle Walker (Manchester City) wins a free kick in the defensive half.", "89'", "Manchester City", "1", "0", "0", "0", "0", "0", "NA", "NA", "NA", "NA", "NA", "NA", "NA", "0", "NA", "NA", "0", "NA", "0", "0", "NA", "NA", "NA", "0", "NA", "NA", "NA", "0", "NA", "NA", "0", "NA", "1", "Kyle Walker", "Manchester City", "defensive half", "0", "NA", "NA", "0", "0", "NA", "NA", "NA", "0", "NA", "NA", "NA", "NA", "2", "66", "0", "NA", "NA", "89"], ["480618", "David Silva (Manchester City) wins a free kick on the left wing.", "89'", "Manchester City", "1", "0", "0", "0", "0", "0", "NA", "NA", "NA", "NA", "NA", "NA", "NA", "0", "NA", "NA", "0", "NA", "0", "0", "NA", "NA", "NA", "0", "NA", "NA", "NA", "0", "NA", "NA", "0", "NA", "1", "David Silva", "Manchester City", "NA", "0", "NA", "NA", "0", "0", "NA", "NA", "NA", "0", "NA", "NA", "NA", "NA", "2", "67", "0", "NA", "NA", "89"], ["480618", "Foul by Daniel Drinkwater (Chelsea).", "89'", "Manchester City", "1", "0", "0", "0", "0", "0", "NA", "NA", "NA", "NA", "NA", "NA", "NA", "1", "Daniel Drinkwater", "Chelsea", "0", "NA", "0", "0", "NA", "NA", "NA", "0", "NA", "NA", "NA", "0", "NA", "NA", "0", "NA", "0", "NA", "NA", "NA", "0", "NA", "NA", "0", "0", "NA", "NA", "NA", "0", "NA", "NA", "NA", "NA", "2", "68", "0", "NA", "NA", "89"], ["480618", "Substitution, Chelsea. Álvaro Morata replaces Eden Hazard.", "90'", "Manchester City", "1", "0", "0", "0", "0", "0", "NA", "NA", "NA", "NA", "NA", "NA", "NA", "0", "NA", "NA", "0", "NA", "0", "0", "NA", "NA", "NA", "0", "NA", "NA", "NA", "0", "NA", "NA", "0", "NA", "0", "NA", "NA", "NA", "0", "NA", "NA", "1", "0", "Chelsea", "Álvaro Morata", "Eden Hazard", "0", "NA", "NA", "NA", "NA", "2", "69", "0", "NA", "NA", "90"], ["480618", "Foul by Daniel Drinkwater (Chelsea).", "90'+1'", "Manchester City", "1", "0", "0", "0", "0", "0", "NA", "NA", "NA", "NA", "NA", "NA", "NA", "1", "Daniel Drinkwater", "Chelsea", "0", "NA", "0", "0", "NA", "NA", "NA", "0", "NA", "NA", "NA", "0", "NA", "NA", "0", "NA", "0", "NA", "NA", "NA", "0", "NA", "NA", "0", "0", "NA", "NA", "NA", "0", "NA", "NA", "NA", "NA", "2", "70", "1", "NA", "NA", "91"], ["480618", "Kevin De Bruyne (Manchester City) wins a free kick in the defensive half.", "90'+1'", "Manchester City", "1", "0", "0", "0", "0", "0", "NA", "NA", "NA", "NA", "NA", "NA", "NA", "0", "NA", "NA", "0", "NA", "0", "0", "NA", "NA", "NA", "0", "NA", "NA", "NA", "0", "NA", "NA", "0", "NA", "1", "Kevin De Bruyne", "Manchester City", "defensive half", "0", "NA", "NA", "0", "0", "NA", "NA", "NA", "0", "NA", "NA", "NA", "NA", "2", "71", "1", "NA", "NA", "91"], ["480618", "Attempt missed. Leroy Sané (Manchester City) right footed shot from outside the box is too high. Assisted by Kevin De Bruyne.", "90'+2'", "Manchester City", "1", "0", "0", "0", "1", "0", "missed", "Leroy Sané", "Manchester City", "right", "outside the box", "too high", "Kevin De Bruyne", "0", "NA", "NA", "0", "NA", "0", "0", "NA", "NA", "NA", "0", "NA", "NA", "NA", "0", "NA", "NA", "0", "NA", "0", "NA", "NA", "NA", "0", "NA", "NA", "0", "0", "NA", "NA", "NA", "0", "NA", "NA", "NA", "NA", "2", "72", "1", "NA", "NA", "92"], ["480618", "Substitution, Manchester City. Phil Foden replaces David Silva.", "90'+3'", "Manchester City", "1", "0", "0", "0", "0", "0", "NA", "NA", "NA", "NA", "NA", "NA", "NA", "0", "NA", "NA", "0", "NA", "0", "0", "NA", "NA", "NA", "0", "NA", "NA", "NA", "0", "NA", "NA", "0", "NA", "0", "NA", "NA", "NA", "0", "NA", "NA", "1", "0", "Manchester City", "Phil Foden", "David Silva", "0", "NA", "NA", "NA", "NA", "2", "73", "1", "NA", "NA", "93"], ["480618", "Attempt missed. Marcos Alonso (Chelsea) left footed shot from outside the box misses to the left. Assisted by Daniel Drinkwater.", "90'+4'", "Manchester City", "1", "0", "0", "0", "1", "0", "missed", "Marcos Alonso", "Chelsea", "left", "outside the box", "left", "Daniel Drinkwater", "0", "NA", "NA", "0", "NA", "0", "0", "NA", "NA", "NA", "0", "NA", "NA", "NA", "0", "NA", "NA", "0", "NA", "0", "NA", "NA", "NA", "0", "NA", "NA", "0", "0", "NA", "NA", "NA", "0", "NA", "NA", "NA", "NA", "2", "74", "1", "NA", "NA", "94"], ["480618", "Second Half ends, Manchester City 1, Chelsea 0.", "90'+5'", "Manchester City", "1", "1", "0", "0", "0", "0", "NA", "NA", "NA", "NA", "NA", "NA", "NA", "0", "NA", "NA", "0", "NA", "0", "0", "NA", "NA", "NA", "0", "NA", "NA", "NA", "0", "NA", "NA", "0", "NA", "0", "NA", "NA", "NA", "0", "NA", "NA", "0", "0", "NA", "NA", "NA", "0", "NA", "NA", "NA", "NA", "2", "75", "1", "NA", "NA", "95"], ["480618", "Match ends, Manchester City 1, Chelsea 0.", "90'+5'", "Manchester City", "1", "0", "1", "0", "0", "0", "NA", "NA", "NA", "NA", "NA", "NA", "NA", "0", "NA", "NA", "0", "NA", "0", "0", "NA", "NA", "NA", "0", "NA", "NA", "NA", "0", "NA", "NA", "0", "NA", "0", "NA", "NA", "NA", "0", "NA", "NA", "0", "0", "NA", "NA", "NA", "0", "NA", "NA", "NA", "NA", "2", "76", "1", "NA", "NA", "95"]], "Lineup": {"Home Player 9": "David Silva", "Home Player 8": "Bernardo Silva", "Home Player 5": "Aymeric Laporte", "Home Player 4": "Ilkay Gundogan", "Home Player 7": "Leroy Sane", "Home Player 6": "Nicolas Otamendi", "Home Player 1": "Sergio Aguero", "Home Player 3": "Ederson", "Home Player 2": "Kevin De Bruyne", "Away Player 10": "Antonio Rudiger", "Away Player 11": "Willian", "Away Player 8": "Victor Moses", "Away Player 9": "Pedro", "Away Player 1": "Marcos Alonso", "Away Player 2": "Cesar Azpilicueta", "Away Player 3": "Andreas Christensen", "Away Player 4": "Thibaut Courtois", "Away Player 5": "Daniel Drinkwater", "Away Player 6": "Cesc Fabregas", "Away Player 7": "Eden Hazard", "Game ID": "g_1_ClLwsZrR", "Home Player 11": "Oleksandr Zinchenko", "Home Player 10": "Kyle Walker"}}