{"Stats": {"Full Time Result": "D", "Away Team Corners": 1, "Referee": "M Dean", "Home Team Fouls Committed": 9, "Away Team Shots": 5, "Away Team Red Cards": 0, "Home Team Red Cards": 0, "Half Time Away Team Goals": 0, "Full Time Home Team Goals": 0, "Away Team Yellow Cards": 3, "Away Team Shots on Target": 3, "Half Time Home Team Goals": 0, "Half Time Result": "D", "Away Team Fouls Committed": 4, "Home Team Yellow Cards": 0, "Home Team Shots": 15, "Div": "E0", "Home Team Corners": 10, "Home Team Shots on Target": 2, "Full Time Away Team Goals": 0}, "Description": "Corner,  Manchester City. Conceded by Christopher Schindler. at minute 3. Attempt saved. David Silva (Manchester City) left footed shot from the left side of the box is saved in the bottom right corner. at minute 6. Attempt blocked. Fernandinho (Manchester City) right footed shot from outside the box is blocked. Assisted by Kyle Walker. at minute 6. Attempt missed. Kevin De Bruyne (Manchester City) right footed shot from long range on the right is too high. Assisted by Nicolás Otamendi. at minute 7. Offside, Huddersfield Town. Alex Pritchard tries a through ball, but Steve Mounie is caught offside. at minute 8. Aaron Mooy (Huddersfield Town) wins a free kick in the attacking half. at minute 9. Dangerous play by Fernandinho (Manchester City). at minute 9. Attempt missed. Aaron Mooy (Huddersfield Town) left footed shot from outside the box is close, but misses to the right. at minute 10. Alex Pritchard (Huddersfield Town) wins a free kick in the attacking half. at minute 11. Foul by David Silva (Manchester City). at minute 11. Attempt saved. Florent Hadergjonaj (Huddersfield Town) right footed shot from the centre of the box is saved in the centre of the goal. Assisted by Alex Pritchard. at minute 11. Attempt missed. Kevin De Bruyne (Manchester City) left footed shot from the centre of the box is close, but misses to the left. Assisted by Leroy Sané. at minute 13. Offside, Manchester City. David Silva tries a through ball, but Raheem Sterling is caught offside. at minute 14. Attempt saved. Alex Pritchard (Huddersfield Town) right footed shot from outside the box is saved in the bottom left corner. Assisted by Florent Hadergjonaj. at minute 20. Corner,  Huddersfield Town. Conceded by Ederson. at minute 20. Foul by Gabriel Jesus (Manchester City). at minute 23. Jonathan Hogg (Huddersfield Town) wins a free kick in the defensive half. at minute 23. Alex Pritchard (Huddersfield Town) wins a free kick in the defensive half. at minute 29. Foul by Fabian Delph (Manchester City). at minute 29. Attempt missed. Chris Löwe (Huddersfield Town) left footed shot from the left side of the box misses to the left. Assisted by Aaron Mooy. at minute 30. Corner,  Manchester City. Conceded by Aaron Mooy. at minute 34. Attempt saved. Kevin De Bruyne (Manchester City) left footed shot from the right side of the box is saved in the centre of the goal. Assisted by Gabriel Jesus. at minute 35. Attempt missed. Gabriel Jesus (Manchester City) header from very close range is high and wide to the left. Assisted by Kyle Walker with a cross. at minute 38. Foul by David Silva (Manchester City). at minute 43. Jonathan Hogg (Huddersfield Town) wins a free kick in the defensive half. at minute 43. First Half ends, Manchester City 0, Huddersfield Town 0. at minute 46. Second Half begins Manchester City 0, Huddersfield Town 0. at minute 45. Fernandinho (Manchester City) wins a free kick in the attacking half. at minute 47. Foul by Steve Mounie (Huddersfield Town). at minute 47. Corner,  Manchester City. Conceded by Zanka. at minute 54. Substitution, Manchester City. Benjamin Mendy replaces Fabian Delph. at minute 57. Substitution, Huddersfield Town. Laurent Depoitre replaces Steve Mounie. at minute 60. Foul by Leroy Sané (Manchester City). at minute 61. Jonathan Hogg (Huddersfield Town) wins a free kick in the defensive half. at minute 61. Alex Pritchard (Huddersfield Town) wins a free kick in the attacking half. at minute 64. Foul by Nicolás Otamendi (Manchester City). at minute 64. Foul by Gabriel Jesus (Manchester City). at minute 66. Zanka (Huddersfield Town) wins a free kick in the attacking half. at minute 66. Tommy Smith (Huddersfield Town) is shown the yellow card. at minute 66. Substitution, Manchester City. Ilkay Gündogan replaces Kevin De Bruyne. at minute 67. Attempt blocked. Leroy Sané (Manchester City) right footed shot from the left side of the box is blocked. Assisted by David Silva. at minute 68. Foul by Tommy Smith (Huddersfield Town). at minute 69. Leroy Sané (Manchester City) wins a free kick on the left wing. at minute 69. Attempt missed. John Stones (Manchester City) right footed shot from the centre of the box misses to the right following a set piece situation. at minute 69. Corner,  Manchester City. Conceded by Florent Hadergjonaj. at minute 71. Corner,  Manchester City. Conceded by Tommy Smith. at minute 71. Corner,  Manchester City. Conceded by Terence Kongolo. at minute 72. Alex Pritchard (Huddersfield Town) wins a free kick in the defensive half. at minute 72. Foul by Kyle Walker (Manchester City). at minute 72. Substitution, Manchester City. Bernardo Silva replaces John Stones. at minute 73. Foul by Chris Löwe (Huddersfield Town). at minute 76. Raheem Sterling (Manchester City) wins a free kick on the right wing. at minute 76. Chris Löwe (Huddersfield Town) is shown the yellow card for a bad foul. at minute 76. Corner,  Manchester City. Conceded by Chris Löwe. at minute 77. Substitution, Huddersfield Town. Scott Malone replaces Chris Löwe. at minute 78. Attempt missed. Fernandinho (Manchester City) header from the centre of the box is too high. Assisted by Ilkay Gündogan with a cross following a corner. at minute 78. Attempt missed. Gabriel Jesus (Manchester City) header from the centre of the box is too high. Assisted by Benjamin Mendy with a cross. at minute 80. Substitution, Huddersfield Town. Rajiv van La Parra replaces Alex Pritchard. at minute 82. Corner,  Manchester City. Conceded by Tommy Smith. at minute 83. Attempt missed. Bernardo Silva (Manchester City) left footed shot from outside the box is close, but misses to the right following a corner. at minute 84. Corner,  Manchester City. Conceded by Aaron Mooy. at minute 85. Attempt missed. Benjamin Mendy (Manchester City) left footed shot from outside the box is close, but misses the top right corner. Assisted by Kyle Walker following a corner. at minute 85. Corner,  Manchester City. Conceded by Terence Kongolo. at minute 86. Attempt missed. Benjamin Mendy (Manchester City) left footed shot from outside the box misses to the left. Assisted by Raheem Sterling with a cross following a corner. at minute 87. Foul by Laurent Depoitre (Huddersfield Town). at minute 87. Ilkay Gündogan (Manchester City) wins a free kick in the defensive half. at minute 87. Rajiv van La Parra (Huddersfield Town) is shown the yellow card. at minute 87. Attempt blocked. Kyle Walker (Manchester City) right footed shot from outside the box is blocked. Assisted by Nicolás Otamendi. at minute 88. Attempt saved. Scott Malone (Huddersfield Town) left footed shot from outside the box is saved in the bottom right corner. at minute 91. Attempt missed. Nicolás Otamendi (Manchester City) right footed shot from the centre of the box is close, but misses to the right. Assisted by Gabriel Jesus. at minute 94. Delay in match  (Manchester City). at minute 94. Delay over. They are ready to continue. at minute 95. Second Half ends, Manchester City 0, Huddersfield Town 0. at minute 95. Match ends, Manchester City 0, Huddersfield Town 0. at minute 95. ", "Home Team": "Manchester City", "Away Team": "Huddersfield Town", "Date": "2018-05-06", "Commentary": [["480538", "First Half begins.", "-", "Manchester City", "0", "0", "0", "1", "0", "0", "NA", "NA", "NA", "NA", "NA", "NA", "NA", "0", "NA", "NA", "0", "NA", "0", "0", "NA", "NA", "NA", "0", "NA", "NA", "NA", "0", "NA", "NA", "0", "NA", "0", "NA", "NA", "NA", "0", "NA", "NA", "0", "0", "NA", "NA", "NA", "0", "NA", "NA", "NA", "NA", "1", "1", "0", "NA", "NA", "NA"], ["480538", "Lineups are announced and players are warming up.", "-", "Manchester City", "0", "0", "0", "0", "0", "0", "NA", "NA", "NA", "NA", "NA", "NA", "NA", "0", "NA", "NA", "0", "NA", "0", "0", "NA", "NA", "NA", "0", "NA", "NA", "NA", "0", "NA", "NA", "0", "NA", "0", "NA", "NA", "NA", "0", "NA", "NA", "0", "0", "NA", "NA", "NA", "0", "NA", "NA", "NA", "NA", "1", "2", "0", "NA", "NA", "NA"], ["480538", "Corner,  Manchester City. Conceded by Christopher Schindler.", "3'", "Manchester City", "0", "0", "0", "0", "0", "0", "NA", "NA", "NA", "NA", "NA", "NA", "NA", "0", "NA", "NA", "0", "NA", "0", "0", "NA", "NA", "NA", "0", "NA", "NA", "NA", "0", "NA", "NA", "0", "NA", "0", "NA", "NA", "NA", "1", "Manchester City", "Christopher Schindler", "0", "0", "NA", "NA", "NA", "0", "NA", "NA", "NA", "NA", "1", "3", "0", "NA", "NA", "3"], ["480538", "Attempt saved. David Silva (Manchester City) left footed shot from the left side of the box is saved in the bottom right corner.", "6'", "Manchester City", "0", "0", "0", "0", "1", "0", "saved", "David Silva", "Manchester City", "left", "the left side of the box", "the bottom right corner", "NA", "0", "NA", "NA", "0", "NA", "0", "0", "NA", "NA", "NA", "0", "NA", "NA", "NA", "0", "NA", "NA", "0", "NA", "0", "NA", "NA", "NA", "0", "NA", "NA", "0", "0", "NA", "NA", "NA", "0", "NA", "NA", "NA", "NA", "1", "4", "0", "NA", "NA", "6"], ["480538", "Attempt blocked. Fernandinho (Manchester City) right footed shot from outside the box is blocked. Assisted by Kyle Walker.", "6'", "Manchester City", "0", "0", "0", "0", "1", "0", "blocked", "Fernandinho", "Manchester City", "right", "outside the box", "NA", "Kyle Walker", "0", "NA", "NA", "0", "NA", "0", "0", "NA", "NA", "NA", "0", "NA", "NA", "NA", "0", "NA", "NA", "0", "NA", "0", "NA", "NA", "NA", "0", "NA", "NA", "0", "0", "NA", "NA", "NA", "0", "NA", "NA", "NA", "NA", "1", "5", "0", "NA", "NA", "6"], ["480538", "Attempt missed. Kevin De Bruyne (Manchester City) right footed shot from long range on the right is too high. Assisted by Nicolás Otamendi.", "7'", "Manchester City", "0", "0", "0", "0", "1", "0", "missed", "Kevin De Bruyne", "Manchester City", "right", "right shot long range", "NA", "Nicolás Otamendi", "0", "NA", "NA", "0", "NA", "0", "0", "NA", "NA", "NA", "0", "NA", "NA", "NA", "0", "NA", "NA", "0", "NA", "0", "NA", "NA", "NA", "0", "NA", "NA", "0", "0", "NA", "NA", "NA", "0", "NA", "NA", "NA", "NA", "1", "6", "0", "NA", "NA", "7"], ["480538", "Offside, Huddersfield Town. Alex Pritchard tries a through ball, but Steve Mounie is caught offside.", "8'", "Manchester City", "0", "0", "0", "0", "0", "0", "NA", "NA", "NA", "NA", "NA", "NA", "NA", "0", "NA", "NA", "0", "NA", "0", "1", "Huddersfield Town", "Steve Mounie", "Alex Pritchard", "0", "NA", "NA", "NA", "0", "NA", "NA", "0", "NA", "0", "NA", "NA", "NA", "0", "NA", "NA", "0", "0", "NA", "NA", "NA", "0", "NA", "NA", "NA", "NA", "1", "7", "0", "NA", "NA", "8"], ["480538", "Aaron Mooy (Huddersfield Town) wins a free kick in the attacking half.", "9'", "Manchester City", "0", "0", "0", "0", "0", "0", "NA", "NA", "NA", "NA", "NA", "NA", "NA", "0", "NA", "NA", "0", "NA", "0", "0", "NA", "NA", "NA", "0", "NA", "NA", "NA", "0", "NA", "NA", "0", "NA", "1", "Aaron Mooy", "Huddersfield Town", "attacking half", "0", "NA", "NA", "0", "0", "NA", "NA", "NA", "0", "NA", "NA", "NA", "NA", "1", "8", "0", "NA", "NA", "9"], ["480538", "Dangerous play by Fernandinho (Manchester City).", "9'", "Manchester City", "0", "0", "0", "0", "0", "0", "NA", "NA", "NA", "NA", "NA", "NA", "NA", "0", "NA", "NA", "0", "NA", "0", "0", "NA", "NA", "NA", "0", "NA", "NA", "NA", "0", "NA", "NA", "0", "NA", "0", "NA", "NA", "NA", "0", "NA", "NA", "0", "0", "NA", "NA", "NA", "0", "NA", "NA", "NA", "NA", "1", "9", "0", "NA", "NA", "9"], ["480538", "Attempt missed. Aaron Mooy (Huddersfield Town) left footed shot from outside the box is close, but misses to the right.", "10'", "Manchester City", "0", "0", "0", "0", "1", "0", "missed", "Aaron Mooy", "Huddersfield Town", "left", "outside the box", "close, but right", "NA", "0", "NA", "NA", "0", "NA", "0", "0", "NA", "NA", "NA", "0", "NA", "NA", "NA", "0", "NA", "NA", "0", "NA", "0", "NA", "NA", "NA", "0", "NA", "NA", "0", "0", "NA", "NA", "NA", "0", "NA", "NA", "NA", "NA", "1", "10", "0", "NA", "NA", "10"], ["480538", "Alex Pritchard (Huddersfield Town) wins a free kick in the attacking half.", "11'", "Manchester City", "0", "0", "0", "0", "0", "0", "NA", "NA", "NA", "NA", "NA", "NA", "NA", "0", "NA", "NA", "0", "NA", "0", "0", "NA", "NA", "NA", "0", "NA", "NA", "NA", "0", "NA", "NA", "0", "NA", "1", "Alex Pritchard", "Huddersfield Town", "attacking half", "0", "NA", "NA", "0", "0", "NA", "NA", "NA", "0", "NA", "NA", "NA", "NA", "1", "11", "0", "NA", "NA", "11"], ["480538", "Foul by David Silva (Manchester City).", "11'", "Manchester City", "0", "0", "0", "0", "0", "0", "NA", "NA", "NA", "NA", "NA", "NA", "NA", "1", "David Silva", "Manchester City", "0", "NA", "0", "0", "NA", "NA", "NA", "0", "NA", "NA", "NA", "0", "NA", "NA", "0", "NA", "0", "NA", "NA", "NA", "0", "NA", "NA", "0", "0", "NA", "NA", "NA", "0", "NA", "NA", "NA", "NA", "1", "12", "0", "NA", "NA", "11"], ["480538", "Attempt saved. Florent Hadergjonaj (Huddersfield Town) right footed shot from the centre of the box is saved in the centre of the goal. Assisted by Alex Pritchard.", "11'", "Manchester City", "0", "0", "0", "0", "1", "0", "saved", "Florent Hadergjonaj", "Huddersfield Town", "right", "the centre of the box", "the centre of the goal", "Alex Pritchard", "0", "NA", "NA", "0", "NA", "0", "0", "NA", "NA", "NA", "0", "NA", "NA", "NA", "0", "NA", "NA", "0", "NA", "0", "NA", "NA", "NA", "0", "NA", "NA", "0", "0", "NA", "NA", "NA", "0", "NA", "NA", "NA", "NA", "1", "13", "0", "NA", "NA", "11"], ["480538", "Attempt missed. Kevin De Bruyne (Manchester City) left footed shot from the centre of the box is close, but misses to the left. Assisted by Leroy Sané.", "13'", "Manchester City", "0", "0", "0", "0", "1", "0", "missed", "Kevin De Bruyne", "Manchester City", "left", "the centre of the box", "close, but left", "Leroy Sané", "0", "NA", "NA", "0", "NA", "0", "0", "NA", "NA", "NA", "0", "NA", "NA", "NA", "0", "NA", "NA", "0", "NA", "0", "NA", "NA", "NA", "0", "NA", "NA", "0", "0", "NA", "NA", "NA", "0", "NA", "NA", "NA", "NA", "1", "14", "0", "NA", "NA", "13"], ["480538", "Offside, Manchester City. David Silva tries a through ball, but Raheem Sterling is caught offside.", "14'", "Manchester City", "0", "0", "0", "0", "0", "0", "NA", "NA", "NA", "NA", "NA", "NA", "NA", "0", "NA", "NA", "0", "NA", "0", "1", "Manchester City", "Raheem Sterling", "David Silva", "0", "NA", "NA", "NA", "0", "NA", "NA", "0", "NA", "0", "NA", "NA", "NA", "0", "NA", "NA", "0", "0", "NA", "NA", "NA", "0", "NA", "NA", "NA", "NA", "1", "15", "0", "NA", "NA", "14"], ["480538", "Attempt saved. Alex Pritchard (Huddersfield Town) right footed shot from outside the box is saved in the bottom left corner. Assisted by Florent Hadergjonaj.", "20'", "Manchester City", "0", "0", "0", "0", "1", "0", "saved", "Alex Pritchard", "Huddersfield Town", "right", "outside the box", "the bottom left corner", "Florent Hadergjonaj", "0", "NA", "NA", "0", "NA", "0", "0", "NA", "NA", "NA", "0", "NA", "NA", "NA", "0", "NA", "NA", "0", "NA", "0", "NA", "NA", "NA", "0", "NA", "NA", "0", "0", "NA", "NA", "NA", "0", "NA", "NA", "NA", "NA", "1", "16", "0", "NA", "NA", "20"], ["480538", "Corner,  Huddersfield Town. Conceded by Ederson.", "20'", "Manchester City", "0", "0", "0", "0", "0", "0", "NA", "NA", "NA", "NA", "NA", "NA", "NA", "0", "NA", "NA", "0", "NA", "0", "0", "NA", "NA", "NA", "0", "NA", "NA", "NA", "0", "NA", "NA", "0", "NA", "0", "NA", "NA", "NA", "1", "Huddersfield Town", "Ederson", "0", "0", "NA", "NA", "NA", "0", "NA", "NA", "NA", "NA", "1", "17", "0", "NA", "NA", "20"], ["480538", "Foul by Gabriel Jesus (Manchester City).", "23'", "Manchester City", "0", "0", "0", "0", "0", "0", "NA", "NA", "NA", "NA", "NA", "NA", "NA", "1", "Gabriel Jesus", "Manchester City", "0", "NA", "0", "0", "NA", "NA", "NA", "0", "NA", "NA", "NA", "0", "NA", "NA", "0", "NA", "0", "NA", "NA", "NA", "0", "NA", "NA", "0", "0", "NA", "NA", "NA", "0", "NA", "NA", "NA", "NA", "1", "18", "0", "NA", "NA", "23"], ["480538", "Jonathan Hogg (Huddersfield Town) wins a free kick in the defensive half.", "23'", "Manchester City", "0", "0", "0", "0", "0", "0", "NA", "NA", "NA", "NA", "NA", "NA", "NA", "0", "NA", "NA", "0", "NA", "0", "0", "NA", "NA", "NA", "0", "NA", "NA", "NA", "0", "NA", "NA", "0", "NA", "1", "Jonathan Hogg", "Huddersfield Town", "defensive half", "0", "NA", "NA", "0", "0", "NA", "NA", "NA", "0", "NA", "NA", "NA", "NA", "1", "19", "0", "NA", "NA", "23"], ["480538", "Alex Pritchard (Huddersfield Town) wins a free kick in the defensive half.", "29'", "Manchester City", "0", "0", "0", "0", "0", "0", "NA", "NA", "NA", "NA", "NA", "NA", "NA", "0", "NA", "NA", "0", "NA", "0", "0", "NA", "NA", "NA", "0", "NA", "NA", "NA", "0", "NA", "NA", "0", "NA", "1", "Alex Pritchard", "Huddersfield Town", "defensive half", "0", "NA", "NA", "0", "0", "NA", "NA", "NA", "0", "NA", "NA", "NA", "NA", "1", "20", "0", "NA", "NA", "29"], ["480538", "Foul by Fabian Delph (Manchester City).", "29'", "Manchester City", "0", "0", "0", "0", "0", "0", "NA", "NA", "NA", "NA", "NA", "NA", "NA", "1", "Fabian Delph", "Manchester City", "0", "NA", "0", "0", "NA", "NA", "NA", "0", "NA", "NA", "NA", "0", "NA", "NA", "0", "NA", "0", "NA", "NA", "NA", "0", "NA", "NA", "0", "0", "NA", "NA", "NA", "0", "NA", "NA", "NA", "NA", "1", "21", "0", "NA", "NA", "29"], ["480538", "Attempt missed. Chris Löwe (Huddersfield Town) left footed shot from the left side of the box misses to the left. Assisted by Aaron Mooy.", "30'", "Manchester City", "0", "0", "0", "0", "1", "0", "missed", "Chris Löwe", "Huddersfield Town", "left", "the left side of the box", "left", "Aaron Mooy", "0", "NA", "NA", "0", "NA", "0", "0", "NA", "NA", "NA", "0", "NA", "NA", "NA", "0", "NA", "NA", "0", "NA", "0", "NA", "NA", "NA", "0", "NA", "NA", "0", "0", "NA", "NA", "NA", "0", "NA", "NA", "NA", "NA", "1", "22", "0", "NA", "NA", "30"], ["480538", "Corner,  Manchester City. Conceded by Aaron Mooy.", "34'", "Manchester City", "0", "0", "0", "0", "0", "0", "NA", "NA", "NA", "NA", "NA", "NA", "NA", "0", "NA", "NA", "0", "NA", "0", "0", "NA", "NA", "NA", "0", "NA", "NA", "NA", "0", "NA", "NA", "0", "NA", "0", "NA", "NA", "NA", "1", "Manchester City", "Aaron Mooy", "0", "0", "NA", "NA", "NA", "0", "NA", "NA", "NA", "NA", "1", "23", "0", "NA", "NA", "34"], ["480538", "Attempt saved. Kevin De Bruyne (Manchester City) left footed shot from the right side of the box is saved in the centre of the goal. Assisted by Gabriel Jesus.", "35'", "Manchester City", "0", "0", "0", "0", "1", "0", "saved", "Kevin De Bruyne", "Manchester City", "left", "the right side of the box", "the centre of the goal", "Gabriel Jesus", "0", "NA", "NA", "0", "NA", "0", "0", "NA", "NA", "NA", "0", "NA", "NA", "NA", "0", "NA", "NA", "0", "NA", "0", "NA", "NA", "NA", "0", "NA", "NA", "0", "0", "NA", "NA", "NA", "0", "NA", "NA", "NA", "NA", "1", "24", "0", "NA", "NA", "35"], ["480538", "Attempt missed. Gabriel Jesus (Manchester City) header from very close range is high and wide to the left. Assisted by Kyle Walker with a cross.", "38'", "Manchester City", "0", "0", "0", "0", "1", "0", "missed", "Gabriel Jesus", "Manchester City", "header", "very close range", "high and wide to the left", "Kyle Walker", "0", "NA", "NA", "0", "cross", "0", "0", "NA", "NA", "NA", "0", "NA", "NA", "NA", "0", "NA", "NA", "0", "NA", "0", "NA", "NA", "NA", "0", "NA", "NA", "0", "0", "NA", "NA", "NA", "0", "NA", "NA", "NA", "NA", "1", "25", "0", "NA", "NA", "38"], ["480538", "Foul by David Silva (Manchester City).", "43'", "Manchester City", "0", "0", "0", "0", "0", "0", "NA", "NA", "NA", "NA", "NA", "NA", "NA", "1", "David Silva", "Manchester City", "0", "NA", "0", "0", "NA", "NA", "NA", "0", "NA", "NA", "NA", "0", "NA", "NA", "0", "NA", "0", "NA", "NA", "NA", "0", "NA", "NA", "0", "0", "NA", "NA", "NA", "0", "NA", "NA", "NA", "NA", "1", "26", "0", "NA", "NA", "43"], ["480538", "Jonathan Hogg (Huddersfield Town) wins a free kick in the defensive half.", "43'", "Manchester City", "0", "0", "0", "0", "0", "0", "NA", "NA", "NA", "NA", "NA", "NA", "NA", "0", "NA", "NA", "0", "NA", "0", "0", "NA", "NA", "NA", "0", "NA", "NA", "NA", "0", "NA", "NA", "0", "NA", "1", "Jonathan Hogg", "Huddersfield Town", "defensive half", "0", "NA", "NA", "0", "0", "NA", "NA", "NA", "0", "NA", "NA", "NA", "NA", "1", "27", "0", "NA", "NA", "43"], ["480538", "First Half ends, Manchester City 0, Huddersfield Town 0.", "45'+1'", "Manchester City", "0", "1", "0", "0", "0", "0", "NA", "NA", "NA", "NA", "NA", "NA", "NA", "0", "NA", "NA", "0", "NA", "0", "0", "NA", "NA", "NA", "0", "NA", "NA", "NA", "0", "NA", "NA", "0", "NA", "0", "NA", "NA", "NA", "0", "NA", "NA", "0", "0", "NA", "NA", "NA", "0", "NA", "NA", "NA", "NA", "1", "28", "1", "NA", "NA", "46"], ["480538", "Second Half begins Manchester City 0, Huddersfield Town 0.", "45'", "Manchester City", "0", "0", "0", "1", "0", "0", "NA", "NA", "NA", "NA", "NA", "NA", "NA", "0", "NA", "NA", "0", "NA", "0", "0", "NA", "NA", "NA", "0", "NA", "NA", "NA", "0", "NA", "NA", "0", "NA", "0", "NA", "NA", "NA", "0", "NA", "NA", "0", "0", "NA", "NA", "NA", "0", "NA", "NA", "NA", "NA", "2", "29", "0", "NA", "NA", "45"], ["480538", "Fernandinho (Manchester City) wins a free kick in the attacking half.", "47'", "Manchester City", "0", "0", "0", "0", "0", "0", "NA", "NA", "NA", "NA", "NA", "NA", "NA", "0", "NA", "NA", "0", "NA", "0", "0", "NA", "NA", "NA", "0", "NA", "NA", "NA", "0", "NA", "NA", "0", "NA", "1", "Fernandinho", "Manchester City", "attacking half", "0", "NA", "NA", "0", "0", "NA", "NA", "NA", "0", "NA", "NA", "NA", "NA", "2", "30", "0", "NA", "NA", "47"], ["480538", "Foul by Steve Mounie (Huddersfield Town).", "47'", "Manchester City", "0", "0", "0", "0", "0", "0", "NA", "NA", "NA", "NA", "NA", "NA", "NA", "1", "Steve Mounie", "Huddersfield Town", "0", "NA", "0", "0", "NA", "NA", "NA", "0", "NA", "NA", "NA", "0", "NA", "NA", "0", "NA", "0", "NA", "NA", "NA", "0", "NA", "NA", "0", "0", "NA", "NA", "NA", "0", "NA", "NA", "NA", "NA", "2", "31", "0", "NA", "NA", "47"], ["480538", "Corner,  Manchester City. Conceded by Zanka.", "54'", "Manchester City", "0", "0", "0", "0", "0", "0", "NA", "NA", "NA", "NA", "NA", "NA", "NA", "0", "NA", "NA", "0", "NA", "0", "0", "NA", "NA", "NA", "0", "NA", "NA", "NA", "0", "NA", "NA", "0", "NA", "0", "NA", "NA", "NA", "1", "Manchester City", "Zanka", "0", "0", "NA", "NA", "NA", "0", "NA", "NA", "NA", "NA", "2", "32", "0", "NA", "NA", "54"], ["480538", "Substitution, Manchester City. Benjamin Mendy replaces Fabian Delph.", "57'", "Manchester City", "0", "0", "0", "0", "0", "0", "NA", "NA", "NA", "NA", "NA", "NA", "NA", "0", "NA", "NA", "0", "NA", "0", "0", "NA", "NA", "NA", "0", "NA", "NA", "NA", "0", "NA", "NA", "0", "NA", "0", "NA", "NA", "NA", "0", "NA", "NA", "1", "0", "Manchester City", "Benjamin Mendy", "Fabian Delph", "0", "NA", "NA", "NA", "NA", "2", "33", "0", "NA", "NA", "57"], ["480538", "Substitution, Huddersfield Town. Laurent Depoitre replaces Steve Mounie.", "60'", "Manchester City", "0", "0", "0", "0", "0", "0", "NA", "NA", "NA", "NA", "NA", "NA", "NA", "0", "NA", "NA", "0", "NA", "0", "0", "NA", "NA", "NA", "0", "NA", "NA", "NA", "0", "NA", "NA", "0", "NA", "0", "NA", "NA", "NA", "0", "NA", "NA", "1", "0", "Huddersfield Town", "Laurent Depoitre", "Steve Mounie", "0", "NA", "NA", "NA", "NA", "2", "34", "0", "NA", "NA", "60"], ["480538", "Foul by Leroy Sané (Manchester City).", "61'", "Manchester City", "0", "0", "0", "0", "0", "0", "NA", "NA", "NA", "NA", "NA", "NA", "NA", "1", "Leroy Sané", "Manchester City", "0", "NA", "0", "0", "NA", "NA", "NA", "0", "NA", "NA", "NA", "0", "NA", "NA", "0", "NA", "0", "NA", "NA", "NA", "0", "NA", "NA", "0", "0", "NA", "NA", "NA", "0", "NA", "NA", "NA", "NA", "2", "35", "0", "NA", "NA", "61"], ["480538", "Jonathan Hogg (Huddersfield Town) wins a free kick in the defensive half.", "61'", "Manchester City", "0", "0", "0", "0", "0", "0", "NA", "NA", "NA", "NA", "NA", "NA", "NA", "0", "NA", "NA", "0", "NA", "0", "0", "NA", "NA", "NA", "0", "NA", "NA", "NA", "0", "NA", "NA", "0", "NA", "1", "Jonathan Hogg", "Huddersfield Town", "defensive half", "0", "NA", "NA", "0", "0", "NA", "NA", "NA", "0", "NA", "NA", "NA", "NA", "2", "36", "0", "NA", "NA", "61"], ["480538", "Alex Pritchard (Huddersfield Town) wins a free kick in the attacking half.", "64'", "Manchester City", "0", "0", "0", "0", "0", "0", "NA", "NA", "NA", "NA", "NA", "NA", "NA", "0", "NA", "NA", "0", "NA", "0", "0", "NA", "NA", "NA", "0", "NA", "NA", "NA", "0", "NA", "NA", "0", "NA", "1", "Alex Pritchard", "Huddersfield Town", "attacking half", "0", "NA", "NA", "0", "0", "NA", "NA", "NA", "0", "NA", "NA", "NA", "NA", "2", "37", "0", "NA", "NA", "64"], ["480538", "Foul by Nicolás Otamendi (Manchester City).", "64'", "Manchester City", "0", "0", "0", "0", "0", "0", "NA", "NA", "NA", "NA", "NA", "NA", "NA", "1", "Nicolás Otamendi", "Manchester City", "0", "NA", "0", "0", "NA", "NA", "NA", "0", "NA", "NA", "NA", "0", "NA", "NA", "0", "NA", "0", "NA", "NA", "NA", "0", "NA", "NA", "0", "0", "NA", "NA", "NA", "0", "NA", "NA", "NA", "NA", "2", "38", "0", "NA", "NA", "64"], ["480538", "Foul by Gabriel Jesus (Manchester City).", "66'", "Manchester City", "0", "0", "0", "0", "0", "0", "NA", "NA", "NA", "NA", "NA", "NA", "NA", "1", "Gabriel Jesus", "Manchester City", "0", "NA", "0", "0", "NA", "NA", "NA", "0", "NA", "NA", "NA", "0", "NA", "NA", "0", "NA", "0", "NA", "NA", "NA", "0", "NA", "NA", "0", "0", "NA", "NA", "NA", "0", "NA", "NA", "NA", "NA", "2", "39", "0", "NA", "NA", "66"], ["480538", "Zanka (Huddersfield Town) wins a free kick in the attacking half.", "66'", "Manchester City", "0", "0", "0", "0", "0", "0", "NA", "NA", "NA", "NA", "NA", "NA", "NA", "0", "NA", "NA", "0", "NA", "0", "0", "NA", "NA", "NA", "0", "NA", "NA", "NA", "0", "NA", "NA", "0", "NA", "1", "Zanka", "Huddersfield Town", "attacking half", "0", "NA", "NA", "0", "0", "NA", "NA", "NA", "0", "NA", "NA", "NA", "NA", "2", "40", "0", "NA", "NA", "66"], ["480538", "Tommy Smith (Huddersfield Town) is shown the yellow card.", "66'", "Manchester City", "0", "0", "0", "0", "0", "0", "NA", "NA", "NA", "NA", "NA", "NA", "NA", "0", "NA", "NA", "0", "NA", "0", "0", "NA", "NA", "NA", "1", "yellow", "Tommy Smith", "Huddersfield Town", "0", "NA", "NA", "0", "NA", "0", "NA", "NA", "NA", "0", "NA", "NA", "0", "0", "NA", "NA", "NA", "0", "NA", "NA", "NA", "NA", "2", "41", "0", "NA", "NA", "66"], ["480538", "Substitution, Manchester City. Ilkay Gündogan replaces Kevin De Bruyne.", "67'", "Manchester City", "0", "0", "0", "0", "0", "0", "NA", "NA", "NA", "NA", "NA", "NA", "NA", "0", "NA", "NA", "0", "NA", "0", "0", "NA", "NA", "NA", "0", "NA", "NA", "NA", "0", "NA", "NA", "0", "NA", "0", "NA", "NA", "NA", "0", "NA", "NA", "1", "0", "Manchester City", "Ilkay Gündogan", "Kevin De Bruyne", "0", "NA", "NA", "NA", "NA", "2", "42", "0", "NA", "NA", "67"], ["480538", "Attempt blocked. Leroy Sané (Manchester City) right footed shot from the left side of the box is blocked. Assisted by David Silva.", "68'", "Manchester City", "0", "0", "0", "0", "1", "0", "blocked", "Leroy Sané", "Manchester City", "right", "the left side of the box", "NA", "David Silva", "0", "NA", "NA", "0", "NA", "0", "0", "NA", "NA", "NA", "0", "NA", "NA", "NA", "0", "NA", "NA", "0", "NA", "0", "NA", "NA", "NA", "0", "NA", "NA", "0", "0", "NA", "NA", "NA", "0", "NA", "NA", "NA", "NA", "2", "43", "0", "NA", "NA", "68"], ["480538", "Foul by Tommy Smith (Huddersfield Town).", "69'", "Manchester City", "0", "0", "0", "0", "0", "0", "NA", "NA", "NA", "NA", "NA", "NA", "NA", "1", "Tommy Smith", "Huddersfield Town", "0", "NA", "0", "0", "NA", "NA", "NA", "0", "NA", "NA", "NA", "0", "NA", "NA", "0", "NA", "0", "NA", "NA", "NA", "0", "NA", "NA", "0", "0", "NA", "NA", "NA", "0", "NA", "NA", "NA", "NA", "2", "44", "0", "NA", "NA", "69"], ["480538", "Leroy Sané (Manchester City) wins a free kick on the left wing.", "69'", "Manchester City", "0", "0", "0", "0", "0", "0", "NA", "NA", "NA", "NA", "NA", "NA", "NA", "0", "NA", "NA", "0", "NA", "0", "0", "NA", "NA", "NA", "0", "NA", "NA", "NA", "0", "NA", "NA", "0", "NA", "1", "Leroy Sané", "Manchester City", "NA", "0", "NA", "NA", "0", "0", "NA", "NA", "NA", "0", "NA", "NA", "NA", "NA", "2", "45", "0", "NA", "NA", "69"], ["480538", "Attempt missed. John Stones (Manchester City) right footed shot from the centre of the box misses to the right following a set piece situation.", "69'", "Manchester City", "0", "0", "0", "0", "1", "0", "missed", "John Stones", "Manchester City", "right", "the centre of the box", "right", "NA", "0", "NA", "NA", "1", "NA", "0", "0", "NA", "NA", "NA", "0", "NA", "NA", "NA", "0", "NA", "NA", "0", "NA", "0", "NA", "NA", "NA", "0", "NA", "NA", "0", "0", "NA", "NA", "NA", "0", "NA", "NA", "NA", "NA", "2", "46", "0", "NA", "NA", "69"], ["480538", "Corner,  Manchester City. Conceded by Florent Hadergjonaj.", "71'", "Manchester City", "0", "0", "0", "0", "0", "0", "NA", "NA", "NA", "NA", "NA", "NA", "NA", "0", "NA", "NA", "0", "NA", "0", "0", "NA", "NA", "NA", "0", "NA", "NA", "NA", "0", "NA", "NA", "0", "NA", "0", "NA", "NA", "NA", "1", "Manchester City", "Florent Hadergjonaj", "0", "0", "NA", "NA", "NA", "0", "NA", "NA", "NA", "NA", "2", "47", "0", "NA", "NA", "71"], ["480538", "Corner,  Manchester City. Conceded by Tommy Smith.", "71'", "Manchester City", "0", "0", "0", "0", "0", "0", "NA", "NA", "NA", "NA", "NA", "NA", "NA", "0", "NA", "NA", "0", "NA", "0", "0", "NA", "NA", "NA", "0", "NA", "NA", "NA", "0", "NA", "NA", "0", "NA", "0", "NA", "NA", "NA", "1", "Manchester City", "Tommy Smith", "0", "0", "NA", "NA", "NA", "0", "NA", "NA", "NA", "NA", "2", "48", "0", "NA", "NA", "71"], ["480538", "Corner,  Manchester City. Conceded by Terence Kongolo.", "72'", "Manchester City", "0", "0", "0", "0", "0", "0", "NA", "NA", "NA", "NA", "NA", "NA", "NA", "0", "NA", "NA", "0", "NA", "0", "0", "NA", "NA", "NA", "0", "NA", "NA", "NA", "0", "NA", "NA", "0", "NA", "0", "NA", "NA", "NA", "1", "Manchester City", "Terence Kongolo", "0", "0", "NA", "NA", "NA", "0", "NA", "NA", "NA", "NA", "2", "49", "0", "NA", "NA", "72"], ["480538", "Alex Pritchard (Huddersfield Town) wins a free kick in the defensive half.", "72'", "Manchester City", "0", "0", "0", "0", "0", "0", "NA", "NA", "NA", "NA", "NA", "NA", "NA", "0", "NA", "NA", "0", "NA", "0", "0", "NA", "NA", "NA", "0", "NA", "NA", "NA", "0", "NA", "NA", "0", "NA", "1", "Alex Pritchard", "Huddersfield Town", "defensive half", "0", "NA", "NA", "0", "0", "NA", "NA", "NA", "0", "NA", "NA", "NA", "NA", "2", "50", "0", "NA", "NA", "72"], ["480538", "Foul by Kyle Walker (Manchester City).", "72'", "Manchester City", "0", "0", "0", "0", "0", "0", "NA", "NA", "NA", "NA", "NA", "NA", "NA", "1", "Kyle Walker", "Manchester City", "0", "NA", "0", "0", "NA", "NA", "NA", "0", "NA", "NA", "NA", "0", "NA", "NA", "0", "NA", "0", "NA", "NA", "NA", "0", "NA", "NA", "0", "0", "NA", "NA", "NA", "0", "NA", "NA", "NA", "NA", "2", "51", "0", "NA", "NA", "72"], ["480538", "Substitution, Manchester City. Bernardo Silva replaces John Stones.", "73'", "Manchester City", "0", "0", "0", "0", "0", "0", "NA", "NA", "NA", "NA", "NA", "NA", "NA", "0", "NA", "NA", "0", "NA", "0", "0", "NA", "NA", "NA", "0", "NA", "NA", "NA", "0", "NA", "NA", "0", "NA", "0", "NA", "NA", "NA", "0", "NA", "NA", "1", "0", "Manchester City", "Bernardo Silva", "John Stones", "0", "NA", "NA", "NA", "NA", "2", "52", "0", "NA", "NA", "73"], ["480538", "Foul by Chris Löwe (Huddersfield Town).", "76'", "Manchester City", "0", "0", "0", "0", "0", "0", "NA", "NA", "NA", "NA", "NA", "NA", "NA", "1", "Chris Löwe", "Huddersfield Town", "0", "NA", "0", "0", "NA", "NA", "NA", "0", "NA", "NA", "NA", "0", "NA", "NA", "0", "NA", "0", "NA", "NA", "NA", "0", "NA", "NA", "0", "0", "NA", "NA", "NA", "0", "NA", "NA", "NA", "NA", "2", "53", "0", "NA", "NA", "76"], ["480538", "Raheem Sterling (Manchester City) wins a free kick on the right wing.", "76'", "Manchester City", "0", "0", "0", "0", "0", "0", "NA", "NA", "NA", "NA", "NA", "NA", "NA", "0", "NA", "NA", "0", "NA", "0", "0", "NA", "NA", "NA", "0", "NA", "NA", "NA", "0", "NA", "NA", "0", "NA", "1", "Raheem Sterling", "Manchester City", "NA", "0", "NA", "NA", "0", "0", "NA", "NA", "NA", "0", "NA", "NA", "NA", "NA", "2", "54", "0", "NA", "NA", "76"], ["480538", "Chris Löwe (Huddersfield Town) is shown the yellow card for a bad foul.", "76'", "Manchester City", "0", "0", "0", "0", "0", "0", "NA", "NA", "NA", "NA", "NA", "NA", "NA", "0", "NA", "NA", "0", "NA", "0", "0", "NA", "NA", "NA", "1", "yellow", "Chris Löwe", "Huddersfield Town", "0", "NA", "NA", "0", "NA", "0", "NA", "NA", "NA", "0", "NA", "NA", "0", "0", "NA", "NA", "NA", "0", "NA", "NA", "NA", "NA", "2", "55", "0", "NA", "NA", "76"], ["480538", "Corner,  Manchester City. Conceded by Chris Löwe.", "77'", "Manchester City", "0", "0", "0", "0", "0", "0", "NA", "NA", "NA", "NA", "NA", "NA", "NA", "0", "NA", "NA", "0", "NA", "0", "0", "NA", "NA", "NA", "0", "NA", "NA", "NA", "0", "NA", "NA", "0", "NA", "0", "NA", "NA", "NA", "1", "Manchester City", "Chris Löwe", "0", "0", "NA", "NA", "NA", "0", "NA", "NA", "NA", "NA", "2", "56", "0", "NA", "NA", "77"], ["480538", "Substitution, Huddersfield Town. Scott Malone replaces Chris Löwe.", "78'", "Manchester City", "0", "0", "0", "0", "0", "0", "NA", "NA", "NA", "NA", "NA", "NA", "NA", "0", "NA", "NA", "0", "NA", "0", "0", "NA", "NA", "NA", "0", "NA", "NA", "NA", "0", "NA", "NA", "0", "NA", "0", "NA", "NA", "NA", "0", "NA", "NA", "1", "0", "Huddersfield Town", "Scott Malone", "Chris Löwe", "0", "NA", "NA", "NA", "NA", "2", "57", "0", "NA", "NA", "78"], ["480538", "Attempt missed. Fernandinho (Manchester City) header from the centre of the box is too high. Assisted by Ilkay Gündogan with a cross following a corner.", "78'", "Manchester City", "0", "0", "0", "0", "1", "0", "missed", "Fernandinho", "Manchester City", "header", "the centre of the box", "too high", "Ilkay Gündogan", "0", "NA", "NA", "0", "cross", "1", "0", "NA", "NA", "NA", "0", "NA", "NA", "NA", "0", "NA", "NA", "0", "NA", "0", "NA", "NA", "NA", "0", "NA", "NA", "0", "0", "NA", "NA", "NA", "0", "NA", "NA", "NA", "NA", "2", "58", "0", "NA", "NA", "78"], ["480538", "Attempt missed. Gabriel Jesus (Manchester City) header from the centre of the box is too high. Assisted by Benjamin Mendy with a cross.", "80'", "Manchester City", "0", "0", "0", "0", "1", "0", "missed", "Gabriel Jesus", "Manchester City", "header", "the centre of the box", "too high", "Benjamin Mendy", "0", "NA", "NA", "0", "cross", "0", "0", "NA", "NA", "NA", "0", "NA", "NA", "NA", "0", "NA", "NA", "0", "NA", "0", "NA", "NA", "NA", "0", "NA", "NA", "0", "0", "NA", "NA", "NA", "0", "NA", "NA", "NA", "NA", "2", "59", "0", "NA", "NA", "80"], ["480538", "Substitution, Huddersfield Town. Rajiv van La Parra replaces Alex Pritchard.", "82'", "Manchester City", "0", "0", "0", "0", "0", "0", "NA", "NA", "NA", "NA", "NA", "NA", "NA", "0", "NA", "NA", "0", "NA", "0", "0", "NA", "NA", "NA", "0", "NA", "NA", "NA", "0", "NA", "NA", "0", "NA", "0", "NA", "NA", "NA", "0", "NA", "NA", "1", "0", "Huddersfield Town", "van La Parra", "Alex Pritchard", "0", "NA", "NA", "NA", "NA", "2", "60", "0", "NA", "NA", "82"], ["480538", "Corner,  Manchester City. Conceded by Tommy Smith.", "83'", "Manchester City", "0", "0", "0", "0", "0", "0", "NA", "NA", "NA", "NA", "NA", "NA", "NA", "0", "NA", "NA", "0", "NA", "0", "0", "NA", "NA", "NA", "0", "NA", "NA", "NA", "0", "NA", "NA", "0", "NA", "0", "NA", "NA", "NA", "1", "Manchester City", "Tommy Smith", "0", "0", "NA", "NA", "NA", "0", "NA", "NA", "NA", "NA", "2", "61", "0", "NA", "NA", "83"], ["480538", "Attempt missed. Bernardo Silva (Manchester City) left footed shot from outside the box is close, but misses to the right following a corner.", "84'", "Manchester City", "0", "0", "0", "0", "1", "0", "missed", "Bernardo Silva", "Manchester City", "left", "outside the box", "close, but right", "NA", "0", "NA", "NA", "0", "NA", "1", "0", "NA", "NA", "NA", "0", "NA", "NA", "NA", "0", "NA", "NA", "0", "NA", "0", "NA", "NA", "NA", "0", "NA", "NA", "0", "0", "NA", "NA", "NA", "0", "NA", "NA", "NA", "NA", "2", "62", "0", "NA", "NA", "84"], ["480538", "Corner,  Manchester City. Conceded by Aaron Mooy.", "85'", "Manchester City", "0", "0", "0", "0", "0", "0", "NA", "NA", "NA", "NA", "NA", "NA", "NA", "0", "NA", "NA", "0", "NA", "0", "0", "NA", "NA", "NA", "0", "NA", "NA", "NA", "0", "NA", "NA", "0", "NA", "0", "NA", "NA", "NA", "1", "Manchester City", "Aaron Mooy", "0", "0", "NA", "NA", "NA", "0", "NA", "NA", "NA", "NA", "2", "63", "0", "NA", "NA", "85"], ["480538", "Attempt missed. Benjamin Mendy (Manchester City) left footed shot from outside the box is close, but misses the top right corner. Assisted by Kyle Walker following a corner.", "85'", "Manchester City", "0", "0", "0", "0", "1", "0", "missed", "Benjamin Mendy", "Manchester City", "left", "outside the box", "close, but misses the top right corner", "Kyle Walker", "0", "NA", "NA", "0", "NA", "1", "0", "NA", "NA", "NA", "0", "NA", "NA", "NA", "0", "NA", "NA", "0", "NA", "0", "NA", "NA", "NA", "0", "NA", "NA", "0", "0", "NA", "NA", "NA", "0", "NA", "NA", "NA", "NA", "2", "64", "0", "NA", "NA", "85"], ["480538", "Corner,  Manchester City. Conceded by Terence Kongolo.", "86'", "Manchester City", "0", "0", "0", "0", "0", "0", "NA", "NA", "NA", "NA", "NA", "NA", "NA", "0", "NA", "NA", "0", "NA", "0", "0", "NA", "NA", "NA", "0", "NA", "NA", "NA", "0", "NA", "NA", "0", "NA", "0", "NA", "NA", "NA", "1", "Manchester City", "Terence Kongolo", "0", "0", "NA", "NA", "NA", "0", "NA", "NA", "NA", "NA", "2", "65", "0", "NA", "NA", "86"], ["480538", "Attempt missed. Benjamin Mendy (Manchester City) left footed shot from outside the box misses to the left. Assisted by Raheem Sterling with a cross following a corner.", "87'", "Manchester City", "0", "0", "0", "0", "1", "0", "missed", "Benjamin Mendy", "Manchester City", "left", "outside the box", "left", "Raheem Sterling", "0", "NA", "NA", "0", "cross", "1", "0", "NA", "NA", "NA", "0", "NA", "NA", "NA", "0", "NA", "NA", "0", "NA", "0", "NA", "NA", "NA", "0", "NA", "NA", "0", "0", "NA", "NA", "NA", "0", "NA", "NA", "NA", "NA", "2", "66", "0", "NA", "NA", "87"], ["480538", "Foul by Laurent Depoitre (Huddersfield Town).", "87'", "Manchester City", "0", "0", "0", "0", "0", "0", "NA", "NA", "NA", "NA", "NA", "NA", "NA", "1", "Laurent Depoitre", "Huddersfield Town", "0", "NA", "0", "0", "NA", "NA", "NA", "0", "NA", "NA", "NA", "0", "NA", "NA", "0", "NA", "0", "NA", "NA", "NA", "0", "NA", "NA", "0", "0", "NA", "NA", "NA", "0", "NA", "NA", "NA", "NA", "2", "67", "0", "NA", "NA", "87"], ["480538", "Ilkay Gündogan (Manchester City) wins a free kick in the defensive half.", "87'", "Manchester City", "0", "0", "0", "0", "0", "0", "NA", "NA", "NA", "NA", "NA", "NA", "NA", "0", "NA", "NA", "0", "NA", "0", "0", "NA", "NA", "NA", "0", "NA", "NA", "NA", "0", "NA", "NA", "0", "NA", "1", "Ilkay Gündogan", "Manchester City", "defensive half", "0", "NA", "NA", "0", "0", "NA", "NA", "NA", "0", "NA", "NA", "NA", "NA", "2", "68", "0", "NA", "NA", "87"], ["480538", "Rajiv van La Parra (Huddersfield Town) is shown the yellow card.", "87'", "Manchester City", "0", "0", "0", "0", "0", "0", "NA", "NA", "NA", "NA", "NA", "NA", "NA", "0", "NA", "NA", "0", "NA", "0", "0", "NA", "NA", "NA", "1", "yellow", "NA", "Huddersfield Town", "0", "NA", "NA", "0", "NA", "0", "NA", "NA", "NA", "0", "NA", "NA", "0", "0", "NA", "NA", "NA", "0", "NA", "NA", "NA", "NA", "2", "69", "0", "NA", "NA", "87"], ["480538", "Attempt blocked. Kyle Walker (Manchester City) right footed shot from outside the box is blocked. Assisted by Nicolás Otamendi.", "88'", "Manchester City", "0", "0", "0", "0", "1", "0", "blocked", "Kyle Walker", "Manchester City", "right", "outside the box", "NA", "Nicolás Otamendi", "0", "NA", "NA", "0", "NA", "0", "0", "NA", "NA", "NA", "0", "NA", "NA", "NA", "0", "NA", "NA", "0", "NA", "0", "NA", "NA", "NA", "0", "NA", "NA", "0", "0", "NA", "NA", "NA", "0", "NA", "NA", "NA", "NA", "2", "70", "0", "NA", "NA", "88"], ["480538", "Attempt saved. Scott Malone (Huddersfield Town) left footed shot from outside the box is saved in the bottom right corner.", "90'+1'", "Manchester City", "0", "0", "0", "0", "1", "0", "saved", "Scott Malone", "Huddersfield Town", "left", "outside the box", "the bottom right corner", "NA", "0", "NA", "NA", "0", "NA", "0", "0", "NA", "NA", "NA", "0", "NA", "NA", "NA", "0", "NA", "NA", "0", "NA", "0", "NA", "NA", "NA", "0", "NA", "NA", "0", "0", "NA", "NA", "NA", "0", "NA", "NA", "NA", "NA", "2", "71", "1", "NA", "NA", "91"], ["480538", "Attempt missed. Nicolás Otamendi (Manchester City) right footed shot from the centre of the box is close, but misses to the right. Assisted by Gabriel Jesus.", "90'+4'", "Manchester City", "0", "0", "0", "0", "1", "0", "missed", "Nicolás Otamendi", "Manchester City", "right", "the centre of the box", "close, but right", "Gabriel Jesus", "0", "NA", "NA", "0", "NA", "0", "0", "NA", "NA", "NA", "0", "NA", "NA", "NA", "0", "NA", "NA", "0", "NA", "0", "NA", "NA", "NA", "0", "NA", "NA", "0", "0", "NA", "NA", "NA", "0", "NA", "NA", "NA", "NA", "2", "72", "1", "NA", "NA", "94"], ["480538", "Delay in match  (Manchester City).", "90'+4'", "Manchester City", "0", "0", "0", "0", "0", "0", "NA", "NA", "NA", "NA", "NA", "NA", "NA", "0", "NA", "NA", "0", "NA", "0", "0", "NA", "NA", "NA", "0", "NA", "NA", "NA", "0", "NA", "NA", "1", "Manchester City", "0", "NA", "NA", "NA", "0", "NA", "NA", "0", "0", "NA", "NA", "NA", "0", "NA", "NA", "NA", "NA", "2", "73", "1", "NA", "NA", "94"], ["480538", "Delay over. They are ready to continue.", "90'+5'", "Manchester City", "0", "0", "0", "0", "0", "0", "NA", "NA", "NA", "NA", "NA", "NA", "NA", "0", "NA", "NA", "0", "NA", "0", "0", "NA", "NA", "NA", "0", "NA", "NA", "NA", "0", "NA", "NA", "0", "NA", "0", "NA", "NA", "NA", "0", "NA", "NA", "0", "0", "NA", "NA", "NA", "0", "NA", "NA", "NA", "NA", "2", "74", "1", "NA", "NA", "95"], ["480538", "Second Half ends, Manchester City 0, Huddersfield Town 0.", "90'+5'", "Manchester City", "0", "1", "0", "0", "0", "0", "NA", "NA", "NA", "NA", "NA", "NA", "NA", "0", "NA", "NA", "0", "NA", "0", "0", "NA", "NA", "NA", "0", "NA", "NA", "NA", "0", "NA", "NA", "0", "NA", "0", "NA", "NA", "NA", "0", "NA", "NA", "0", "0", "NA", "NA", "NA", "0", "NA", "NA", "NA", "NA", "2", "75", "1", "NA", "NA", "95"], ["480538", "Match ends, Manchester City 0, Huddersfield Town 0.", "90'+5'", "Manchester City", "0", "0", "1", "0", "0", "0", "NA", "NA", "NA", "NA", "NA", "NA", "NA", "0", "NA", "NA", "0", "NA", "0", "0", "NA", "NA", "NA", "0", "NA", "NA", "NA", "0", "NA", "NA", "0", "NA", "0", "NA", "NA", "NA", "0", "NA", "NA", "0", "0", "NA", "NA", "NA", "0", "NA", "NA", "NA", "NA", "2", "76", "1", "NA", "NA", "95"]], "Lineup": {"Home Player 9": "Raheem Sterling", "Home Player 8": "David Silva", "Home Player 5": "Jesus Gabriel", "Home Player 4": "Fernandinho", "Home Player 7": "Leroy Sane", "Home Player 6": "Nicolas Otamendi", "Home Player 1": "Kevin De Bruyne", "Home Player 3": "Ederson", "Home Player 2": "Fabian Delph", "Away Player 10": "Christopher Schindler", "Away Player 11": "Tom Smith", "Away Player 8": "Steve Mounie", "Away Player 9": "Alex Pritchard", "Away Player 1": "Florent Hadergjonaj", "Away Player 2": "Jonathan Hogg", "Away Player 3": "Mathias Jorgensen", "Away Player 4": "Terence Kongolo", "Away Player 5": "Jonas Lossl", "Away Player 6": "Chris Lowe", "Away Player 7": "Aaron Mooy", "Game ID": "g_1_lhJEIDIa", "Home Player 11": "Kyle Walker", "Home Player 10": "John Stones"}}