{"Stats": {"Full Time Result": "A", "Away Team Corners": 13, "Referee": "K Friend", "Home Team Fouls Committed": 12, "Away Team Shots": 14, "Away Team Red Cards": 0, "Home Team Red Cards": 0, "Half Time Away Team Goals": 0, "Full Time Home Team Goals": 0, "Away Team Yellow Cards": 1, "Away Team Shots on Target": 4, "Half Time Home Team Goals": 0, "Half Time Result": "D", "Away Team Fouls Committed": 5, "Home Team Yellow Cards": 0, "Home Team Shots": 5, "Div": "E0", "Home Team Corners": 2, "Home Team Shots on Target": 3, "Full Time Away Team Goals": 1}, "Description": "Foul by Victor Wanyama (Tottenham Hotspur). at minute 1. James McArthur (Crystal Palace) wins a free kick in the attacking half. at minute 1. Corner,  Crystal Palace. Conceded by Dele Alli. at minute 2. Corner,  Tottenham Hotspur. Conceded by James Tomkins. at minute 4. Dele Alli (Tottenham Hotspur) wins a free kick in the attacking half. at minute 8. Foul by Timothy Fosu-Mensah (Crystal Palace). at minute 8. Corner,  Tottenham Hotspur. Conceded by James Tomkins. at minute 8. Attempt saved. Harry Kane (Tottenham Hotspur) right footed shot from the centre of the box is saved in the centre of the goal. at minute 10. Corner,  Tottenham Hotspur. Conceded by Wayne Hennessey. at minute 10. Christian Benteke (Crystal Palace) wins a free kick in the attacking half. at minute 11. Foul by Victor Wanyama (Tottenham Hotspur). at minute 11. Attempt saved. James Tomkins (Crystal Palace) header from the centre of the box is saved in the top centre of the goal. Assisted by Luka Milivojevic. at minute 12. Foul by Christian Benteke (Crystal Palace). at minute 12. Mousa Dembélé (Tottenham Hotspur) wins a free kick in the defensive half. at minute 12. Foul by Patrick van Aanholt (Crystal Palace). at minute 13. Serge Aurier (Tottenham Hotspur) wins a free kick in the attacking half. at minute 13. Attempt blocked. James McArthur (Crystal Palace) left footed shot from the centre of the box is blocked. Assisted by Andros Townsend. at minute 18. Attempt saved. Alexander Sørloth (Crystal Palace) header from the left side of the box is saved in the centre of the goal. Assisted by Andros Townsend. at minute 20. Foul by Christian Benteke (Crystal Palace). at minute 21. Mousa Dembélé (Tottenham Hotspur) wins a free kick on the left wing. at minute 21. Andros Townsend (Crystal Palace) wins a free kick on the right wing. at minute 22. Foul by Erik Lamela (Tottenham Hotspur). at minute 22. Attempt missed. Christian Eriksen (Tottenham Hotspur) right footed shot from more than 35 yards misses to the left. Assisted by Ben Davies. at minute 22. Foul by Mousa Dembélé (Tottenham Hotspur). at minute 26. Luka Milivojevic (Crystal Palace) wins a free kick in the defensive half. at minute 26. Foul by Christian Benteke (Crystal Palace). at minute 28. Victor Wanyama (Tottenham Hotspur) wins a free kick in the attacking half. at minute 28. Attempt blocked. Dele Alli (Tottenham Hotspur) right footed shot from outside the box is blocked. at minute 29. Offside, Tottenham Hotspur. Dele Alli tries a through ball, but Harry Kane is caught offside. at minute 30. Hand ball by Christian Benteke (Crystal Palace). at minute 34. Corner,  Crystal Palace. Conceded by Eric Dier. at minute 35. Attempt missed. Patrick van Aanholt (Crystal Palace) left footed shot from the left side of the box misses to the left following a corner. at minute 35. Foul by James McArthur (Crystal Palace). at minute 43. Mousa Dembélé (Tottenham Hotspur) wins a free kick on the right wing. at minute 43. Attempt saved. Andros Townsend (Crystal Palace) left footed shot from outside the box is saved in the centre of the goal. Assisted by James McArthur. at minute 45. Attempt blocked. Christian Eriksen (Tottenham Hotspur) right footed shot from outside the box is blocked. Assisted by Erik Lamela. at minute 45. Andros Townsend (Crystal Palace) wins a free kick in the defensive half. at minute 45. Foul by Mousa Dembélé (Tottenham Hotspur). at minute 45. Mousa Dembélé (Tottenham Hotspur) is shown the yellow card. at minute 46. Corner,  Crystal Palace. Conceded by Davinson Sánchez. at minute 46. First Half ends, Crystal Palace 0, Tottenham Hotspur 0. at minute 47. Second Half begins Crystal Palace 0, Tottenham Hotspur 0. at minute 45. Attempt missed. Harry Kane (Tottenham Hotspur) right footed shot from outside the box is high and wide to the right. Assisted by Dele Alli. at minute 48. Attempt missed. Christian Eriksen (Tottenham Hotspur) right footed shot from the centre of the box is too high. at minute 51. Hand ball by Jairo Riedewald (Crystal Palace). at minute 52. Attempt missed. Harry Kane (Tottenham Hotspur) left footed shot from very close range is close, but misses to the right. Assisted by Christian Eriksen. at minute 54. Attempt saved. Serge Aurier (Tottenham Hotspur) right footed shot from the right side of the box is saved in the centre of the goal. Assisted by Dele Alli. at minute 59. Attempt blocked. Christian Eriksen (Tottenham Hotspur) left footed shot from the centre of the box is blocked. at minute 59. Corner,  Tottenham Hotspur. Conceded by James Tomkins. at minute 60. Corner,  Tottenham Hotspur. Conceded by Jairo Riedewald. at minute 64. Substitution, Tottenham Hotspur. Lucas Moura replaces Erik Lamela. at minute 66. Dele Alli (Tottenham Hotspur) wins a free kick in the defensive half. at minute 68. Foul by James McArthur (Crystal Palace). at minute 68. Corner,  Tottenham Hotspur. Conceded by Aaron Wan-Bissaka. at minute 69. Corner,  Tottenham Hotspur. Conceded by Luka Milivojevic. at minute 71. Corner,  Tottenham Hotspur. Conceded by James Tomkins. at minute 72. Attempt saved. Ben Davies (Tottenham Hotspur) left footed shot from the centre of the box is saved in the bottom left corner. at minute 73. Corner,  Tottenham Hotspur. Conceded by Wayne Hennessey. at minute 73. Davinson Sánchez (Tottenham Hotspur) wins a free kick in the defensive half. at minute 76. Foul by Jairo Riedewald (Crystal Palace). at minute 76. Delay in match James Tomkins (Crystal Palace) because of an injury. at minute 80. Substitution, Tottenham Hotspur. Son Heung-Min replaces Mousa Dembélé. at minute 80. Delay over. They are ready to continue. at minute 81. Corner,  Tottenham Hotspur. Conceded by James McArthur. at minute 82. Attempt missed. Harry Kane (Tottenham Hotspur) right footed shot from the right side of the box misses to the left following a corner. at minute 83. Substitution, Crystal Palace. Damien Delaney replaces James Tomkins because of an injury. at minute 85. Foul by Alexander Sørloth (Crystal Palace). at minute 85. Victor Wanyama (Tottenham Hotspur) wins a free kick in the defensive half. at minute 85. Attempt missed. Harry Kane (Tottenham Hotspur) right footed shot from the right side of the box is close, but misses to the left. at minute 86. Substitution, Crystal Palace. Lee Chung-yong replaces Andros Townsend. at minute 87. Corner,  Tottenham Hotspur. Conceded by Luka Milivojevic. at minute 88. Goal!  Crystal Palace 0, Tottenham Hotspur 1. Harry Kane (Tottenham Hotspur) header from the right side of the six yard box to the top left corner. Assisted by Christian Eriksen with a cross following a corner. at minute 88. Foul by Timothy Fosu-Mensah (Crystal Palace). at minute 92. Lucas Moura (Tottenham Hotspur) wins a free kick in the attacking half. at minute 92. Attempt blocked. Christian Eriksen (Tottenham Hotspur) right footed shot from outside the box is blocked. at minute 93. Corner,  Tottenham Hotspur. Conceded by Damien Delaney. at minute 93. Corner,  Tottenham Hotspur. Conceded by Patrick van Aanholt. at minute 94. Second Half ends, Crystal Palace 0, Tottenham Hotspur 1. at minute 95. Match ends, Crystal Palace 0, Tottenham Hotspur 1. at minute 95. ", "Home Team": "Crystal Palace", "Away Team": "Tottenham Hotspur", "Date": "2018-02-25", "Commentary": [["480634", "First Half begins.", "-", "Crystal Palace", "0", "0", "0", "1", "0", "0", "NA", "NA", "NA", "NA", "NA", "NA", "NA", "0", "NA", "NA", "0", "NA", "0", "0", "NA", "NA", "NA", "0", "NA", "NA", "NA", "0", "NA", "NA", "0", "NA", "0", "NA", "NA", "NA", "0", "NA", "NA", "0", "0", "NA", "NA", "NA", "0", "NA", "NA", "NA", "NA", "1", "1", "0", "NA", "NA", "NA"], ["480634", "Lineups are announced and players are warming up.", "-", "Crystal Palace", "0", "0", "0", "0", "0", "0", "NA", "NA", "NA", "NA", "NA", "NA", "NA", "0", "NA", "NA", "0", "NA", "0", "0", "NA", "NA", "NA", "0", "NA", "NA", "NA", "0", "NA", "NA", "0", "NA", "0", "NA", "NA", "NA", "0", "NA", "NA", "0", "0", "NA", "NA", "NA", "0", "NA", "NA", "NA", "NA", "1", "2", "0", "NA", "NA", "NA"], ["480634", "Foul by Victor Wanyama (Tottenham Hotspur).", "1'", "Crystal Palace", "0", "0", "0", "0", "0", "0", "NA", "NA", "NA", "NA", "NA", "NA", "NA", "1", "Victor Wanyama", "Tottenham Hotspur", "0", "NA", "0", "0", "NA", "NA", "NA", "0", "NA", "NA", "NA", "0", "NA", "NA", "0", "NA", "0", "NA", "NA", "NA", "0", "NA", "NA", "0", "0", "NA", "NA", "NA", "0", "NA", "NA", "NA", "NA", "1", "3", "0", "NA", "NA", "1"], ["480634", "James McArthur (Crystal Palace) wins a free kick in the attacking half.", "1'", "Crystal Palace", "0", "0", "0", "0", "0", "0", "NA", "NA", "NA", "NA", "NA", "NA", "NA", "0", "NA", "NA", "0", "NA", "0", "0", "NA", "NA", "NA", "0", "NA", "NA", "NA", "0", "NA", "NA", "0", "NA", "1", "James McArthur", "Crystal Palace", "attacking half", "0", "NA", "NA", "0", "0", "NA", "NA", "NA", "0", "NA", "NA", "NA", "NA", "1", "4", "0", "NA", "NA", "1"], ["480634", "Corner,  Crystal Palace. Conceded by Dele Alli.", "2'", "Crystal Palace", "0", "0", "0", "0", "0", "0", "NA", "NA", "NA", "NA", "NA", "NA", "NA", "0", "NA", "NA", "0", "NA", "0", "0", "NA", "NA", "NA", "0", "NA", "NA", "NA", "0", "NA", "NA", "0", "NA", "0", "NA", "NA", "NA", "1", "Crystal Palace", "Dele Alli", "0", "0", "NA", "NA", "NA", "0", "NA", "NA", "NA", "NA", "1", "5", "0", "NA", "NA", "2"], ["480634", "Corner,  Tottenham Hotspur. Conceded by James Tomkins.", "4'", "Crystal Palace", "0", "0", "0", "0", "0", "0", "NA", "NA", "NA", "NA", "NA", "NA", "NA", "0", "NA", "NA", "0", "NA", "0", "0", "NA", "NA", "NA", "0", "NA", "NA", "NA", "0", "NA", "NA", "0", "NA", "0", "NA", "NA", "NA", "1", "Tottenham Hotspur", "James Tomkins", "0", "0", "NA", "NA", "NA", "0", "NA", "NA", "NA", "NA", "1", "6", "0", "NA", "NA", "4"], ["480634", "Dele Alli (Tottenham Hotspur) wins a free kick in the attacking half.", "8'", "Crystal Palace", "0", "0", "0", "0", "0", "0", "NA", "NA", "NA", "NA", "NA", "NA", "NA", "0", "NA", "NA", "0", "NA", "0", "0", "NA", "NA", "NA", "0", "NA", "NA", "NA", "0", "NA", "NA", "0", "NA", "1", "Dele Alli", "Tottenham Hotspur", "attacking half", "0", "NA", "NA", "0", "0", "NA", "NA", "NA", "0", "NA", "NA", "NA", "NA", "1", "7", "0", "NA", "NA", "8"], ["480634", "Foul by Timothy Fosu-Mensah (Crystal Palace).", "8'", "Crystal Palace", "0", "0", "0", "0", "0", "0", "NA", "NA", "NA", "NA", "NA", "NA", "NA", "1", "Timothy Fosu-Mensah", "Crystal Palace", "0", "NA", "0", "0", "NA", "NA", "NA", "0", "NA", "NA", "NA", "0", "NA", "NA", "0", "NA", "0", "NA", "NA", "NA", "0", "NA", "NA", "0", "0", "NA", "NA", "NA", "0", "NA", "NA", "NA", "NA", "1", "8", "0", "NA", "NA", "8"], ["480634", "Corner,  Tottenham Hotspur. Conceded by James Tomkins.", "8'", "Crystal Palace", "0", "0", "0", "0", "0", "0", "NA", "NA", "NA", "NA", "NA", "NA", "NA", "0", "NA", "NA", "0", "NA", "0", "0", "NA", "NA", "NA", "0", "NA", "NA", "NA", "0", "NA", "NA", "0", "NA", "0", "NA", "NA", "NA", "1", "Tottenham Hotspur", "James Tomkins", "0", "0", "NA", "NA", "NA", "0", "NA", "NA", "NA", "NA", "1", "9", "0", "NA", "NA", "8"], ["480634", "Attempt saved. Harry Kane (Tottenham Hotspur) right footed shot from the centre of the box is saved in the centre of the goal.", "10'", "Crystal Palace", "0", "0", "0", "0", "1", "0", "saved", "Harry Kane", "Tottenham Hotspur", "right", "the centre of the box", "the centre of the goal", "NA", "0", "NA", "NA", "0", "NA", "0", "0", "NA", "NA", "NA", "0", "NA", "NA", "NA", "0", "NA", "NA", "0", "NA", "0", "NA", "NA", "NA", "0", "NA", "NA", "0", "0", "NA", "NA", "NA", "0", "NA", "NA", "NA", "NA", "1", "10", "0", "NA", "NA", "10"], ["480634", "Corner,  Tottenham Hotspur. Conceded by Wayne Hennessey.", "10'", "Crystal Palace", "0", "0", "0", "0", "0", "0", "NA", "NA", "NA", "NA", "NA", "NA", "NA", "0", "NA", "NA", "0", "NA", "0", "0", "NA", "NA", "NA", "0", "NA", "NA", "NA", "0", "NA", "NA", "0", "NA", "0", "NA", "NA", "NA", "1", "Tottenham Hotspur", "Wayne Hennessey", "0", "0", "NA", "NA", "NA", "0", "NA", "NA", "NA", "NA", "1", "11", "0", "NA", "NA", "10"], ["480634", "Christian Benteke (Crystal Palace) wins a free kick in the attacking half.", "11'", "Crystal Palace", "0", "0", "0", "0", "0", "0", "NA", "NA", "NA", "NA", "NA", "NA", "NA", "0", "NA", "NA", "0", "NA", "0", "0", "NA", "NA", "NA", "0", "NA", "NA", "NA", "0", "NA", "NA", "0", "NA", "1", "Christian Benteke", "Crystal Palace", "attacking half", "0", "NA", "NA", "0", "0", "NA", "NA", "NA", "0", "NA", "NA", "NA", "NA", "1", "12", "0", "NA", "NA", "11"], ["480634", "Foul by Victor Wanyama (Tottenham Hotspur).", "11'", "Crystal Palace", "0", "0", "0", "0", "0", "0", "NA", "NA", "NA", "NA", "NA", "NA", "NA", "1", "Victor Wanyama", "Tottenham Hotspur", "0", "NA", "0", "0", "NA", "NA", "NA", "0", "NA", "NA", "NA", "0", "NA", "NA", "0", "NA", "0", "NA", "NA", "NA", "0", "NA", "NA", "0", "0", "NA", "NA", "NA", "0", "NA", "NA", "NA", "NA", "1", "13", "0", "NA", "NA", "11"], ["480634", "Attempt saved. James Tomkins (Crystal Palace) header from the centre of the box is saved in the top centre of the goal. Assisted by Luka Milivojevic.", "12'", "Crystal Palace", "0", "0", "0", "0", "1", "0", "saved", "James Tomkins", "Crystal Palace", "header", "the centre of the box", "the top centre of the goal", "Luka Milivojevic", "0", "NA", "NA", "0", "NA", "0", "0", "NA", "NA", "NA", "0", "NA", "NA", "NA", "0", "NA", "NA", "0", "NA", "0", "NA", "NA", "NA", "0", "NA", "NA", "0", "0", "NA", "NA", "NA", "0", "NA", "NA", "NA", "NA", "1", "14", "0", "NA", "NA", "12"], ["480634", "Foul by Christian Benteke (Crystal Palace).", "12'", "Crystal Palace", "0", "0", "0", "0", "0", "0", "NA", "NA", "NA", "NA", "NA", "NA", "NA", "1", "Christian Benteke", "Crystal Palace", "0", "NA", "0", "0", "NA", "NA", "NA", "0", "NA", "NA", "NA", "0", "NA", "NA", "0", "NA", "0", "NA", "NA", "NA", "0", "NA", "NA", "0", "0", "NA", "NA", "NA", "0", "NA", "NA", "NA", "NA", "1", "15", "0", "NA", "NA", "12"], ["480634", "Mousa Dembélé (Tottenham Hotspur) wins a free kick in the defensive half.", "12'", "Crystal Palace", "0", "0", "0", "0", "0", "0", "NA", "NA", "NA", "NA", "NA", "NA", "NA", "0", "NA", "NA", "0", "NA", "0", "0", "NA", "NA", "NA", "0", "NA", "NA", "NA", "0", "NA", "NA", "0", "NA", "1", "Mousa Dembélé", "Tottenham Hotspur", "defensive half", "0", "NA", "NA", "0", "0", "NA", "NA", "NA", "0", "NA", "NA", "NA", "NA", "1", "16", "0", "NA", "NA", "12"], ["480634", "Foul by Patrick van Aanholt (Crystal Palace).", "13'", "Crystal Palace", "0", "0", "0", "0", "0", "0", "NA", "NA", "NA", "NA", "NA", "NA", "NA", "1", "Patrick van Aanholt", "Crystal Palace", "0", "NA", "0", "0", "NA", "NA", "NA", "0", "NA", "NA", "NA", "0", "NA", "NA", "0", "NA", "0", "NA", "NA", "NA", "0", "NA", "NA", "0", "0", "NA", "NA", "NA", "0", "NA", "NA", "NA", "NA", "1", "17", "0", "NA", "NA", "13"], ["480634", "Serge Aurier (Tottenham Hotspur) wins a free kick in the attacking half.", "13'", "Crystal Palace", "0", "0", "0", "0", "0", "0", "NA", "NA", "NA", "NA", "NA", "NA", "NA", "0", "NA", "NA", "0", "NA", "0", "0", "NA", "NA", "NA", "0", "NA", "NA", "NA", "0", "NA", "NA", "0", "NA", "1", "Serge Aurier", "Tottenham Hotspur", "attacking half", "0", "NA", "NA", "0", "0", "NA", "NA", "NA", "0", "NA", "NA", "NA", "NA", "1", "18", "0", "NA", "NA", "13"], ["480634", "Attempt blocked. James McArthur (Crystal Palace) left footed shot from the centre of the box is blocked. Assisted by Andros Townsend.", "18'", "Crystal Palace", "0", "0", "0", "0", "1", "0", "blocked", "James McArthur", "Crystal Palace", "left", "the centre of the box", "NA", "Andros Townsend", "0", "NA", "NA", "0", "NA", "0", "0", "NA", "NA", "NA", "0", "NA", "NA", "NA", "0", "NA", "NA", "0", "NA", "0", "NA", "NA", "NA", "0", "NA", "NA", "0", "0", "NA", "NA", "NA", "0", "NA", "NA", "NA", "NA", "1", "19", "0", "NA", "NA", "18"], ["480634", "Attempt saved. Alexander Sørloth (Crystal Palace) header from the left side of the box is saved in the centre of the goal. Assisted by Andros Townsend.", "20'", "Crystal Palace", "0", "0", "0", "0", "1", "0", "saved", "Alexander Sørloth", "Crystal Palace", "header", "the left side of the box", "the centre of the goal", "Andros Townsend", "0", "NA", "NA", "0", "NA", "0", "0", "NA", "NA", "NA", "0", "NA", "NA", "NA", "0", "NA", "NA", "0", "NA", "0", "NA", "NA", "NA", "0", "NA", "NA", "0", "0", "NA", "NA", "NA", "0", "NA", "NA", "NA", "NA", "1", "20", "0", "NA", "NA", "20"], ["480634", "Foul by Christian Benteke (Crystal Palace).", "21'", "Crystal Palace", "0", "0", "0", "0", "0", "0", "NA", "NA", "NA", "NA", "NA", "NA", "NA", "1", "Christian Benteke", "Crystal Palace", "0", "NA", "0", "0", "NA", "NA", "NA", "0", "NA", "NA", "NA", "0", "NA", "NA", "0", "NA", "0", "NA", "NA", "NA", "0", "NA", "NA", "0", "0", "NA", "NA", "NA", "0", "NA", "NA", "NA", "NA", "1", "21", "0", "NA", "NA", "21"], ["480634", "Mousa Dembélé (Tottenham Hotspur) wins a free kick on the left wing.", "21'", "Crystal Palace", "0", "0", "0", "0", "0", "0", "NA", "NA", "NA", "NA", "NA", "NA", "NA", "0", "NA", "NA", "0", "NA", "0", "0", "NA", "NA", "NA", "0", "NA", "NA", "NA", "0", "NA", "NA", "0", "NA", "1", "Mousa Dembélé", "Tottenham Hotspur", "NA", "0", "NA", "NA", "0", "0", "NA", "NA", "NA", "0", "NA", "NA", "NA", "NA", "1", "22", "0", "NA", "NA", "21"], ["480634", "Andros Townsend (Crystal Palace) wins a free kick on the right wing.", "22'", "Crystal Palace", "0", "0", "0", "0", "0", "0", "NA", "NA", "NA", "NA", "NA", "NA", "NA", "0", "NA", "NA", "0", "NA", "0", "0", "NA", "NA", "NA", "0", "NA", "NA", "NA", "0", "NA", "NA", "0", "NA", "1", "Andros Townsend", "Crystal Palace", "NA", "0", "NA", "NA", "0", "0", "NA", "NA", "NA", "0", "NA", "NA", "NA", "NA", "1", "23", "0", "NA", "NA", "22"], ["480634", "Foul by Erik Lamela (Tottenham Hotspur).", "22'", "Crystal Palace", "0", "0", "0", "0", "0", "0", "NA", "NA", "NA", "NA", "NA", "NA", "NA", "1", "Erik Lamela", "Tottenham Hotspur", "0", "NA", "0", "0", "NA", "NA", "NA", "0", "NA", "NA", "NA", "0", "NA", "NA", "0", "NA", "0", "NA", "NA", "NA", "0", "NA", "NA", "0", "0", "NA", "NA", "NA", "0", "NA", "NA", "NA", "NA", "1", "24", "0", "NA", "NA", "22"], ["480634", "Attempt missed. Christian Eriksen (Tottenham Hotspur) right footed shot from more than 35 yards misses to the left. Assisted by Ben Davies.", "22'", "Crystal Palace", "0", "0", "0", "0", "1", "0", "missed", "Christian Eriksen", "Tottenham Hotspur", "right", "NA", "NA", "Ben Davies", "0", "NA", "NA", "0", "NA", "0", "0", "NA", "NA", "NA", "0", "NA", "NA", "NA", "0", "NA", "NA", "0", "NA", "0", "NA", "NA", "NA", "0", "NA", "NA", "0", "0", "NA", "NA", "NA", "0", "NA", "NA", "NA", "NA", "1", "25", "0", "NA", "NA", "22"], ["480634", "Foul by Mousa Dembélé (Tottenham Hotspur).", "26'", "Crystal Palace", "0", "0", "0", "0", "0", "0", "NA", "NA", "NA", "NA", "NA", "NA", "NA", "1", "Mousa Dembélé", "Tottenham Hotspur", "0", "NA", "0", "0", "NA", "NA", "NA", "0", "NA", "NA", "NA", "0", "NA", "NA", "0", "NA", "0", "NA", "NA", "NA", "0", "NA", "NA", "0", "0", "NA", "NA", "NA", "0", "NA", "NA", "NA", "NA", "1", "26", "0", "NA", "NA", "26"], ["480634", "Luka Milivojevic (Crystal Palace) wins a free kick in the defensive half.", "26'", "Crystal Palace", "0", "0", "0", "0", "0", "0", "NA", "NA", "NA", "NA", "NA", "NA", "NA", "0", "NA", "NA", "0", "NA", "0", "0", "NA", "NA", "NA", "0", "NA", "NA", "NA", "0", "NA", "NA", "0", "NA", "1", "Luka Milivojevic", "Crystal Palace", "defensive half", "0", "NA", "NA", "0", "0", "NA", "NA", "NA", "0", "NA", "NA", "NA", "NA", "1", "27", "0", "NA", "NA", "26"], ["480634", "Foul by Christian Benteke (Crystal Palace).", "28'", "Crystal Palace", "0", "0", "0", "0", "0", "0", "NA", "NA", "NA", "NA", "NA", "NA", "NA", "1", "Christian Benteke", "Crystal Palace", "0", "NA", "0", "0", "NA", "NA", "NA", "0", "NA", "NA", "NA", "0", "NA", "NA", "0", "NA", "0", "NA", "NA", "NA", "0", "NA", "NA", "0", "0", "NA", "NA", "NA", "0", "NA", "NA", "NA", "NA", "1", "28", "0", "NA", "NA", "28"], ["480634", "Victor Wanyama (Tottenham Hotspur) wins a free kick in the attacking half.", "28'", "Crystal Palace", "0", "0", "0", "0", "0", "0", "NA", "NA", "NA", "NA", "NA", "NA", "NA", "0", "NA", "NA", "0", "NA", "0", "0", "NA", "NA", "NA", "0", "NA", "NA", "NA", "0", "NA", "NA", "0", "NA", "1", "Victor Wanyama", "Tottenham Hotspur", "attacking half", "0", "NA", "NA", "0", "0", "NA", "NA", "NA", "0", "NA", "NA", "NA", "NA", "1", "29", "0", "NA", "NA", "28"], ["480634", "Attempt blocked. Dele Alli (Tottenham Hotspur) right footed shot from outside the box is blocked.", "29'", "Crystal Palace", "0", "0", "0", "0", "1", "0", "blocked", "Dele Alli", "Tottenham Hotspur", "right", "outside the box", "NA", "NA", "0", "NA", "NA", "0", "NA", "0", "0", "NA", "NA", "NA", "0", "NA", "NA", "NA", "0", "NA", "NA", "0", "NA", "0", "NA", "NA", "NA", "0", "NA", "NA", "0", "0", "NA", "NA", "NA", "0", "NA", "NA", "NA", "NA", "1", "30", "0", "NA", "NA", "29"], ["480634", "Offside, Tottenham Hotspur. Dele Alli tries a through ball, but Harry Kane is caught offside.", "30'", "Crystal Palace", "0", "0", "0", "0", "0", "0", "NA", "NA", "NA", "NA", "NA", "NA", "NA", "0", "NA", "NA", "0", "NA", "0", "1", "Tottenham Hotspur", "Harry Kane", "Dele Alli", "0", "NA", "NA", "NA", "0", "NA", "NA", "0", "NA", "0", "NA", "NA", "NA", "0", "NA", "NA", "0", "0", "NA", "NA", "NA", "0", "NA", "NA", "NA", "NA", "1", "31", "0", "NA", "NA", "30"], ["480634", "Hand ball by Christian Benteke (Crystal Palace).", "34'", "Crystal Palace", "0", "0", "0", "0", "0", "0", "NA", "NA", "NA", "NA", "NA", "NA", "NA", "0", "NA", "NA", "0", "NA", "0", "0", "NA", "NA", "NA", "0", "NA", "NA", "NA", "0", "NA", "NA", "0", "NA", "0", "NA", "NA", "NA", "0", "NA", "NA", "0", "0", "NA", "NA", "NA", "0", "NA", "NA", "NA", "NA", "1", "32", "0", "NA", "NA", "34"], ["480634", "Corner,  Crystal Palace. Conceded by Eric Dier.", "35'", "Crystal Palace", "0", "0", "0", "0", "0", "0", "NA", "NA", "NA", "NA", "NA", "NA", "NA", "0", "NA", "NA", "0", "NA", "0", "0", "NA", "NA", "NA", "0", "NA", "NA", "NA", "0", "NA", "NA", "0", "NA", "0", "NA", "NA", "NA", "1", "Crystal Palace", "Eric Dier", "0", "0", "NA", "NA", "NA", "0", "NA", "NA", "NA", "NA", "1", "33", "0", "NA", "NA", "35"], ["480634", "Attempt missed. Patrick van Aanholt (Crystal Palace) left footed shot from the left side of the box misses to the left following a corner.", "35'", "Crystal Palace", "0", "0", "0", "0", "1", "0", "missed", "Patrick van Aanholt", "Crystal Palace", "left", "the left side of the box", "left", "NA", "0", "NA", "NA", "0", "NA", "1", "0", "NA", "NA", "NA", "0", "NA", "NA", "NA", "0", "NA", "NA", "0", "NA", "0", "NA", "NA", "NA", "0", "NA", "NA", "0", "0", "NA", "NA", "NA", "0", "NA", "NA", "NA", "NA", "1", "34", "0", "NA", "NA", "35"], ["480634", "Foul by James McArthur (Crystal Palace).", "43'", "Crystal Palace", "0", "0", "0", "0", "0", "0", "NA", "NA", "NA", "NA", "NA", "NA", "NA", "1", "James McArthur", "Crystal Palace", "0", "NA", "0", "0", "NA", "NA", "NA", "0", "NA", "NA", "NA", "0", "NA", "NA", "0", "NA", "0", "NA", "NA", "NA", "0", "NA", "NA", "0", "0", "NA", "NA", "NA", "0", "NA", "NA", "NA", "NA", "1", "35", "0", "NA", "NA", "43"], ["480634", "Mousa Dembélé (Tottenham Hotspur) wins a free kick on the right wing.", "43'", "Crystal Palace", "0", "0", "0", "0", "0", "0", "NA", "NA", "NA", "NA", "NA", "NA", "NA", "0", "NA", "NA", "0", "NA", "0", "0", "NA", "NA", "NA", "0", "NA", "NA", "NA", "0", "NA", "NA", "0", "NA", "1", "Mousa Dembélé", "Tottenham Hotspur", "NA", "0", "NA", "NA", "0", "0", "NA", "NA", "NA", "0", "NA", "NA", "NA", "NA", "1", "36", "0", "NA", "NA", "43"], ["480634", "Attempt saved. Andros Townsend (Crystal Palace) left footed shot from outside the box is saved in the centre of the goal. Assisted by James McArthur.", "45'", "Crystal Palace", "0", "0", "0", "0", "1", "0", "saved", "Andros Townsend", "Crystal Palace", "left", "outside the box", "the centre of the goal", "James McArthur", "0", "NA", "NA", "0", "NA", "0", "0", "NA", "NA", "NA", "0", "NA", "NA", "NA", "0", "NA", "NA", "0", "NA", "0", "NA", "NA", "NA", "0", "NA", "NA", "0", "0", "NA", "NA", "NA", "0", "NA", "NA", "NA", "NA", "1", "37", "0", "NA", "NA", "45"], ["480634", "Attempt blocked. Christian Eriksen (Tottenham Hotspur) right footed shot from outside the box is blocked. Assisted by Erik Lamela.", "45'", "Crystal Palace", "0", "0", "0", "0", "1", "0", "blocked", "Christian Eriksen", "Tottenham Hotspur", "right", "outside the box", "NA", "Erik Lamela", "0", "NA", "NA", "0", "NA", "0", "0", "NA", "NA", "NA", "0", "NA", "NA", "NA", "0", "NA", "NA", "0", "NA", "0", "NA", "NA", "NA", "0", "NA", "NA", "0", "0", "NA", "NA", "NA", "0", "NA", "NA", "NA", "NA", "1", "38", "0", "NA", "NA", "45"], ["480634", "Andros Townsend (Crystal Palace) wins a free kick in the defensive half.", "45'", "Crystal Palace", "0", "0", "0", "0", "0", "0", "NA", "NA", "NA", "NA", "NA", "NA", "NA", "0", "NA", "NA", "0", "NA", "0", "0", "NA", "NA", "NA", "0", "NA", "NA", "NA", "0", "NA", "NA", "0", "NA", "1", "Andros Townsend", "Crystal Palace", "defensive half", "0", "NA", "NA", "0", "0", "NA", "NA", "NA", "0", "NA", "NA", "NA", "NA", "1", "39", "0", "NA", "NA", "45"], ["480634", "Foul by Mousa Dembélé (Tottenham Hotspur).", "45'", "Crystal Palace", "0", "0", "0", "0", "0", "0", "NA", "NA", "NA", "NA", "NA", "NA", "NA", "1", "Mousa Dembélé", "Tottenham Hotspur", "0", "NA", "0", "0", "NA", "NA", "NA", "0", "NA", "NA", "NA", "0", "NA", "NA", "0", "NA", "0", "NA", "NA", "NA", "0", "NA", "NA", "0", "0", "NA", "NA", "NA", "0", "NA", "NA", "NA", "NA", "1", "40", "0", "NA", "NA", "45"], ["480634", "Mousa Dembélé (Tottenham Hotspur) is shown the yellow card.", "45'+1'", "Crystal Palace", "0", "0", "0", "0", "0", "0", "NA", "NA", "NA", "NA", "NA", "NA", "NA", "0", "NA", "NA", "0", "NA", "0", "0", "NA", "NA", "NA", "1", "yellow", "Mousa Dembélé", "Tottenham Hotspur", "0", "NA", "NA", "0", "NA", "0", "NA", "NA", "NA", "0", "NA", "NA", "0", "0", "NA", "NA", "NA", "0", "NA", "NA", "NA", "NA", "1", "41", "1", "NA", "NA", "46"], ["480634", "Corner,  Crystal Palace. Conceded by Davinson Sánchez.", "45'+1'", "Crystal Palace", "0", "0", "0", "0", "0", "0", "NA", "NA", "NA", "NA", "NA", "NA", "NA", "0", "NA", "NA", "0", "NA", "0", "0", "NA", "NA", "NA", "0", "NA", "NA", "NA", "0", "NA", "NA", "0", "NA", "0", "NA", "NA", "NA", "1", "Crystal Palace", "Davinson Sánchez", "0", "0", "NA", "NA", "NA", "0", "NA", "NA", "NA", "NA", "1", "42", "1", "NA", "NA", "46"], ["480634", "First Half ends, Crystal Palace 0, Tottenham Hotspur 0.", "45'+2'", "Crystal Palace", "0", "1", "0", "0", "0", "0", "NA", "NA", "NA", "NA", "NA", "NA", "NA", "0", "NA", "NA", "0", "NA", "0", "0", "NA", "NA", "NA", "0", "NA", "NA", "NA", "0", "NA", "NA", "0", "NA", "0", "NA", "NA", "NA", "0", "NA", "NA", "0", "0", "NA", "NA", "NA", "0", "NA", "NA", "NA", "NA", "1", "43", "1", "NA", "NA", "47"], ["480634", "Second Half begins Crystal Palace 0, Tottenham Hotspur 0.", "45'", "Crystal Palace", "0", "0", "0", "1", "0", "0", "NA", "NA", "NA", "NA", "NA", "NA", "NA", "0", "NA", "NA", "0", "NA", "0", "0", "NA", "NA", "NA", "0", "NA", "NA", "NA", "0", "NA", "NA", "0", "NA", "0", "NA", "NA", "NA", "0", "NA", "NA", "0", "0", "NA", "NA", "NA", "0", "NA", "NA", "NA", "NA", "2", "44", "0", "NA", "NA", "45"], ["480634", "Attempt missed. Harry Kane (Tottenham Hotspur) right footed shot from outside the box is high and wide to the right. Assisted by Dele Alli.", "48'", "Crystal Palace", "0", "0", "0", "0", "1", "0", "missed", "Harry Kane", "Tottenham Hotspur", "right", "outside the box", "high and wide to the right", "Dele Alli", "0", "NA", "NA", "0", "NA", "0", "0", "NA", "NA", "NA", "0", "NA", "NA", "NA", "0", "NA", "NA", "0", "NA", "0", "NA", "NA", "NA", "0", "NA", "NA", "0", "0", "NA", "NA", "NA", "0", "NA", "NA", "NA", "NA", "2", "45", "0", "NA", "NA", "48"], ["480634", "Attempt missed. Christian Eriksen (Tottenham Hotspur) right footed shot from the centre of the box is too high.", "51'", "Crystal Palace", "0", "0", "0", "0", "1", "0", "missed", "Christian Eriksen", "Tottenham Hotspur", "right", "the centre of the box", "too high", "NA", "0", "NA", "NA", "0", "NA", "0", "0", "NA", "NA", "NA", "0", "NA", "NA", "NA", "0", "NA", "NA", "0", "NA", "0", "NA", "NA", "NA", "0", "NA", "NA", "0", "0", "NA", "NA", "NA", "0", "NA", "NA", "NA", "NA", "2", "46", "0", "NA", "NA", "51"], ["480634", "Hand ball by Jairo Riedewald (Crystal Palace).", "52'", "Crystal Palace", "0", "0", "0", "0", "0", "0", "NA", "NA", "NA", "NA", "NA", "NA", "NA", "0", "NA", "NA", "0", "NA", "0", "0", "NA", "NA", "NA", "0", "NA", "NA", "NA", "0", "NA", "NA", "0", "NA", "0", "NA", "NA", "NA", "0", "NA", "NA", "0", "0", "NA", "NA", "NA", "0", "NA", "NA", "NA", "NA", "2", "47", "0", "NA", "NA", "52"], ["480634", "Attempt missed. Harry Kane (Tottenham Hotspur) left footed shot from very close range is close, but misses to the right. Assisted by Christian Eriksen.", "54'", "Crystal Palace", "0", "0", "0", "0", "1", "0", "missed", "Harry Kane", "Tottenham Hotspur", "left", "left shot very close range", "close, but right", "Christian Eriksen", "0", "NA", "NA", "0", "NA", "0", "0", "NA", "NA", "NA", "0", "NA", "NA", "NA", "0", "NA", "NA", "0", "NA", "0", "NA", "NA", "NA", "0", "NA", "NA", "0", "0", "NA", "NA", "NA", "0", "NA", "NA", "NA", "NA", "2", "48", "0", "NA", "NA", "54"], ["480634", "Attempt saved. Serge Aurier (Tottenham Hotspur) right footed shot from the right side of the box is saved in the centre of the goal. Assisted by Dele Alli.", "59'", "Crystal Palace", "0", "0", "0", "0", "1", "0", "saved", "Serge Aurier", "Tottenham Hotspur", "right", "the right side of the box", "the centre of the goal", "Dele Alli", "0", "NA", "NA", "0", "NA", "0", "0", "NA", "NA", "NA", "0", "NA", "NA", "NA", "0", "NA", "NA", "0", "NA", "0", "NA", "NA", "NA", "0", "NA", "NA", "0", "0", "NA", "NA", "NA", "0", "NA", "NA", "NA", "NA", "2", "49", "0", "NA", "NA", "59"], ["480634", "Attempt blocked. Christian Eriksen (Tottenham Hotspur) left footed shot from the centre of the box is blocked.", "59'", "Crystal Palace", "0", "0", "0", "0", "1", "0", "blocked", "Christian Eriksen", "Tottenham Hotspur", "left", "the centre of the box", "NA", "NA", "0", "NA", "NA", "0", "NA", "0", "0", "NA", "NA", "NA", "0", "NA", "NA", "NA", "0", "NA", "NA", "0", "NA", "0", "NA", "NA", "NA", "0", "NA", "NA", "0", "0", "NA", "NA", "NA", "0", "NA", "NA", "NA", "NA", "2", "50", "0", "NA", "NA", "59"], ["480634", "Corner,  Tottenham Hotspur. Conceded by James Tomkins.", "60'", "Crystal Palace", "0", "0", "0", "0", "0", "0", "NA", "NA", "NA", "NA", "NA", "NA", "NA", "0", "NA", "NA", "0", "NA", "0", "0", "NA", "NA", "NA", "0", "NA", "NA", "NA", "0", "NA", "NA", "0", "NA", "0", "NA", "NA", "NA", "1", "Tottenham Hotspur", "James Tomkins", "0", "0", "NA", "NA", "NA", "0", "NA", "NA", "NA", "NA", "2", "51", "0", "NA", "NA", "60"], ["480634", "Corner,  Tottenham Hotspur. Conceded by Jairo Riedewald.", "64'", "Crystal Palace", "0", "0", "0", "0", "0", "0", "NA", "NA", "NA", "NA", "NA", "NA", "NA", "0", "NA", "NA", "0", "NA", "0", "0", "NA", "NA", "NA", "0", "NA", "NA", "NA", "0", "NA", "NA", "0", "NA", "0", "NA", "NA", "NA", "1", "Tottenham Hotspur", "Jairo Riedewald", "0", "0", "NA", "NA", "NA", "0", "NA", "NA", "NA", "NA", "2", "52", "0", "NA", "NA", "64"], ["480634", "Substitution, Tottenham Hotspur. Lucas Moura replaces Erik Lamela.", "66'", "Crystal Palace", "0", "0", "0", "0", "0", "0", "NA", "NA", "NA", "NA", "NA", "NA", "NA", "0", "NA", "NA", "0", "NA", "0", "0", "NA", "NA", "NA", "0", "NA", "NA", "NA", "0", "NA", "NA", "0", "NA", "0", "NA", "NA", "NA", "0", "NA", "NA", "1", "0", "Tottenham Hotspur", "Lucas Moura", "Erik Lamela", "0", "NA", "NA", "NA", "NA", "2", "53", "0", "NA", "NA", "66"], ["480634", "Dele Alli (Tottenham Hotspur) wins a free kick in the defensive half.", "68'", "Crystal Palace", "0", "0", "0", "0", "0", "0", "NA", "NA", "NA", "NA", "NA", "NA", "NA", "0", "NA", "NA", "0", "NA", "0", "0", "NA", "NA", "NA", "0", "NA", "NA", "NA", "0", "NA", "NA", "0", "NA", "1", "Dele Alli", "Tottenham Hotspur", "defensive half", "0", "NA", "NA", "0", "0", "NA", "NA", "NA", "0", "NA", "NA", "NA", "NA", "2", "54", "0", "NA", "NA", "68"], ["480634", "Foul by James McArthur (Crystal Palace).", "68'", "Crystal Palace", "0", "0", "0", "0", "0", "0", "NA", "NA", "NA", "NA", "NA", "NA", "NA", "1", "James McArthur", "Crystal Palace", "0", "NA", "0", "0", "NA", "NA", "NA", "0", "NA", "NA", "NA", "0", "NA", "NA", "0", "NA", "0", "NA", "NA", "NA", "0", "NA", "NA", "0", "0", "NA", "NA", "NA", "0", "NA", "NA", "NA", "NA", "2", "55", "0", "NA", "NA", "68"], ["480634", "Corner,  Tottenham Hotspur. Conceded by Aaron Wan-Bissaka.", "69'", "Crystal Palace", "0", "0", "0", "0", "0", "0", "NA", "NA", "NA", "NA", "NA", "NA", "NA", "0", "NA", "NA", "0", "NA", "0", "0", "NA", "NA", "NA", "0", "NA", "NA", "NA", "0", "NA", "NA", "0", "NA", "0", "NA", "NA", "NA", "1", "Tottenham Hotspur", "Aaron Wan-Bissaka", "0", "0", "NA", "NA", "NA", "0", "NA", "NA", "NA", "NA", "2", "56", "0", "NA", "NA", "69"], ["480634", "Corner,  Tottenham Hotspur. Conceded by Luka Milivojevic.", "71'", "Crystal Palace", "0", "0", "0", "0", "0", "0", "NA", "NA", "NA", "NA", "NA", "NA", "NA", "0", "NA", "NA", "0", "NA", "0", "0", "NA", "NA", "NA", "0", "NA", "NA", "NA", "0", "NA", "NA", "0", "NA", "0", "NA", "NA", "NA", "1", "Tottenham Hotspur", "Luka Milivojevic", "0", "0", "NA", "NA", "NA", "0", "NA", "NA", "NA", "NA", "2", "57", "0", "NA", "NA", "71"], ["480634", "Corner,  Tottenham Hotspur. Conceded by James Tomkins.", "72'", "Crystal Palace", "0", "0", "0", "0", "0", "0", "NA", "NA", "NA", "NA", "NA", "NA", "NA", "0", "NA", "NA", "0", "NA", "0", "0", "NA", "NA", "NA", "0", "NA", "NA", "NA", "0", "NA", "NA", "0", "NA", "0", "NA", "NA", "NA", "1", "Tottenham Hotspur", "James Tomkins", "0", "0", "NA", "NA", "NA", "0", "NA", "NA", "NA", "NA", "2", "58", "0", "NA", "NA", "72"], ["480634", "Attempt saved. Ben Davies (Tottenham Hotspur) left footed shot from the centre of the box is saved in the bottom left corner.", "73'", "Crystal Palace", "0", "0", "0", "0", "1", "0", "saved", "Ben Davies", "Tottenham Hotspur", "left", "the centre of the box", "the bottom left corner", "NA", "0", "NA", "NA", "0", "NA", "0", "0", "NA", "NA", "NA", "0", "NA", "NA", "NA", "0", "NA", "NA", "0", "NA", "0", "NA", "NA", "NA", "0", "NA", "NA", "0", "0", "NA", "NA", "NA", "0", "NA", "NA", "NA", "NA", "2", "59", "0", "NA", "NA", "73"], ["480634", "Corner,  Tottenham Hotspur. Conceded by Wayne Hennessey.", "73'", "Crystal Palace", "0", "0", "0", "0", "0", "0", "NA", "NA", "NA", "NA", "NA", "NA", "NA", "0", "NA", "NA", "0", "NA", "0", "0", "NA", "NA", "NA", "0", "NA", "NA", "NA", "0", "NA", "NA", "0", "NA", "0", "NA", "NA", "NA", "1", "Tottenham Hotspur", "Wayne Hennessey", "0", "0", "NA", "NA", "NA", "0", "NA", "NA", "NA", "NA", "2", "60", "0", "NA", "NA", "73"], ["480634", "Davinson Sánchez (Tottenham Hotspur) wins a free kick in the defensive half.", "76'", "Crystal Palace", "0", "0", "0", "0", "0", "0", "NA", "NA", "NA", "NA", "NA", "NA", "NA", "0", "NA", "NA", "0", "NA", "0", "0", "NA", "NA", "NA", "0", "NA", "NA", "NA", "0", "NA", "NA", "0", "NA", "1", "Davinson Sánchez", "Tottenham Hotspur", "defensive half", "0", "NA", "NA", "0", "0", "NA", "NA", "NA", "0", "NA", "NA", "NA", "NA", "2", "61", "0", "NA", "NA", "76"], ["480634", "Foul by Jairo Riedewald (Crystal Palace).", "76'", "Crystal Palace", "0", "0", "0", "0", "0", "0", "NA", "NA", "NA", "NA", "NA", "NA", "NA", "1", "Jairo Riedewald", "Crystal Palace", "0", "NA", "0", "0", "NA", "NA", "NA", "0", "NA", "NA", "NA", "0", "NA", "NA", "0", "NA", "0", "NA", "NA", "NA", "0", "NA", "NA", "0", "0", "NA", "NA", "NA", "0", "NA", "NA", "NA", "NA", "2", "62", "0", "NA", "NA", "76"], ["480634", "Delay in match James Tomkins (Crystal Palace) because of an injury.", "80'", "Crystal Palace", "0", "0", "0", "0", "0", "0", "NA", "NA", "NA", "NA", "NA", "NA", "NA", "0", "NA", "NA", "0", "NA", "0", "0", "NA", "NA", "NA", "0", "NA", "NA", "NA", "0", "NA", "NA", "1", "Crystal Palace", "0", "NA", "NA", "NA", "0", "NA", "NA", "0", "0", "NA", "NA", "NA", "0", "NA", "NA", "NA", "NA", "2", "63", "0", "NA", "NA", "80"], ["480634", "Substitution, Tottenham Hotspur. Son Heung-Min replaces Mousa Dembélé.", "80'", "Crystal Palace", "0", "0", "0", "0", "0", "0", "NA", "NA", "NA", "NA", "NA", "NA", "NA", "0", "NA", "NA", "0", "NA", "0", "0", "NA", "NA", "NA", "0", "NA", "NA", "NA", "0", "NA", "NA", "0", "NA", "0", "NA", "NA", "NA", "0", "NA", "NA", "1", "0", "Tottenham Hotspur", "Son Heung-Min", "Mousa Dembélé", "0", "NA", "NA", "NA", "NA", "2", "64", "0", "NA", "NA", "80"], ["480634", "Delay over. They are ready to continue.", "81'", "Crystal Palace", "0", "0", "0", "0", "0", "0", "NA", "NA", "NA", "NA", "NA", "NA", "NA", "0", "NA", "NA", "0", "NA", "0", "0", "NA", "NA", "NA", "0", "NA", "NA", "NA", "0", "NA", "NA", "0", "NA", "0", "NA", "NA", "NA", "0", "NA", "NA", "0", "0", "NA", "NA", "NA", "0", "NA", "NA", "NA", "NA", "2", "65", "0", "NA", "NA", "81"], ["480634", "Corner,  Tottenham Hotspur. Conceded by James McArthur.", "82'", "Crystal Palace", "0", "0", "0", "0", "0", "0", "NA", "NA", "NA", "NA", "NA", "NA", "NA", "0", "NA", "NA", "0", "NA", "0", "0", "NA", "NA", "NA", "0", "NA", "NA", "NA", "0", "NA", "NA", "0", "NA", "0", "NA", "NA", "NA", "1", "Tottenham Hotspur", "James McArthur", "0", "0", "NA", "NA", "NA", "0", "NA", "NA", "NA", "NA", "2", "66", "0", "NA", "NA", "82"], ["480634", "Attempt missed. Harry Kane (Tottenham Hotspur) right footed shot from the right side of the box misses to the left following a corner.", "83'", "Crystal Palace", "0", "0", "0", "0", "1", "0", "missed", "Harry Kane", "Tottenham Hotspur", "right", "the right side of the box", "left", "NA", "0", "NA", "NA", "0", "NA", "1", "0", "NA", "NA", "NA", "0", "NA", "NA", "NA", "0", "NA", "NA", "0", "NA", "0", "NA", "NA", "NA", "0", "NA", "NA", "0", "0", "NA", "NA", "NA", "0", "NA", "NA", "NA", "NA", "2", "67", "0", "NA", "NA", "83"], ["480634", "Substitution, Crystal Palace. Damien Delaney replaces James Tomkins because of an injury.", "85'", "Crystal Palace", "0", "0", "0", "0", "0", "0", "NA", "NA", "NA", "NA", "NA", "NA", "NA", "0", "NA", "NA", "0", "NA", "0", "0", "NA", "NA", "NA", "0", "NA", "NA", "NA", "0", "NA", "NA", "0", "NA", "0", "NA", "NA", "NA", "0", "NA", "NA", "1", "1", "Crystal Palace", "Damien Delaney", "James Tomkins", "0", "NA", "NA", "NA", "NA", "2", "68", "0", "NA", "NA", "85"], ["480634", "Foul by Alexander Sørloth (Crystal Palace).", "85'", "Crystal Palace", "0", "0", "0", "0", "0", "0", "NA", "NA", "NA", "NA", "NA", "NA", "NA", "1", "Alexander Sørloth", "Crystal Palace", "0", "NA", "0", "0", "NA", "NA", "NA", "0", "NA", "NA", "NA", "0", "NA", "NA", "0", "NA", "0", "NA", "NA", "NA", "0", "NA", "NA", "0", "0", "NA", "NA", "NA", "0", "NA", "NA", "NA", "NA", "2", "69", "0", "NA", "NA", "85"], ["480634", "Victor Wanyama (Tottenham Hotspur) wins a free kick in the defensive half.", "85'", "Crystal Palace", "0", "0", "0", "0", "0", "0", "NA", "NA", "NA", "NA", "NA", "NA", "NA", "0", "NA", "NA", "0", "NA", "0", "0", "NA", "NA", "NA", "0", "NA", "NA", "NA", "0", "NA", "NA", "0", "NA", "1", "Victor Wanyama", "Tottenham Hotspur", "defensive half", "0", "NA", "NA", "0", "0", "NA", "NA", "NA", "0", "NA", "NA", "NA", "NA", "2", "70", "0", "NA", "NA", "85"], ["480634", "Attempt missed. Harry Kane (Tottenham Hotspur) right footed shot from the right side of the box is close, but misses to the left.", "86'", "Crystal Palace", "0", "0", "0", "0", "1", "0", "missed", "Harry Kane", "Tottenham Hotspur", "right", "the right side of the box", "close, but left", "NA", "0", "NA", "NA", "0", "NA", "0", "0", "NA", "NA", "NA", "0", "NA", "NA", "NA", "0", "NA", "NA", "0", "NA", "0", "NA", "NA", "NA", "0", "NA", "NA", "0", "0", "NA", "NA", "NA", "0", "NA", "NA", "NA", "NA", "2", "71", "0", "NA", "NA", "86"], ["480634", "Substitution, Crystal Palace. Lee Chung-yong replaces Andros Townsend.", "87'", "Crystal Palace", "0", "0", "0", "0", "0", "0", "NA", "NA", "NA", "NA", "NA", "NA", "NA", "0", "NA", "NA", "0", "NA", "0", "0", "NA", "NA", "NA", "0", "NA", "NA", "NA", "0", "NA", "NA", "0", "NA", "0", "NA", "NA", "NA", "0", "NA", "NA", "1", "0", "Crystal Palace", "Lee Chung-yong", "Andros Townsend", "0", "NA", "NA", "NA", "NA", "2", "72", "0", "NA", "NA", "87"], ["480634", "Corner,  Tottenham Hotspur. Conceded by Luka Milivojevic.", "88'", "Crystal Palace", "0", "0", "0", "0", "0", "0", "NA", "NA", "NA", "NA", "NA", "NA", "NA", "0", "NA", "NA", "0", "NA", "0", "0", "NA", "NA", "NA", "0", "NA", "NA", "NA", "0", "NA", "NA", "0", "NA", "0", "NA", "NA", "NA", "1", "Tottenham Hotspur", "Luka Milivojevic", "0", "0", "NA", "NA", "NA", "0", "NA", "NA", "NA", "NA", "2", "73", "0", "NA", "NA", "88"], ["480634", "Goal!  Crystal Palace 0, Tottenham Hotspur 1. Harry Kane (Tottenham Hotspur) header from the right side of the six yard box to the top left corner. Assisted by Christian Eriksen with a cross following a corner.", "88'", "Crystal Palace", "0", "0", "0", "0", "1", "0", "goal", "Harry Kane", "Tottenham Hotspur", "header", "the right side of the six yard box", "top left corner", "Christian Eriksen", "0", "NA", "NA", "0", "cross", "1", "0", "NA", "NA", "NA", "0", "NA", "NA", "NA", "0", "NA", "NA", "0", "NA", "0", "NA", "NA", "NA", "0", "NA", "NA", "0", "0", "NA", "NA", "NA", "0", "NA", "NA", "NA", "NA", "2", "74", "0", "NA", "NA", "88"], ["480634", "Foul by Timothy Fosu-Mensah (Crystal Palace).", "90'+2'", "Crystal Palace", "0", "0", "0", "0", "0", "0", "NA", "NA", "NA", "NA", "NA", "NA", "NA", "1", "Timothy Fosu-Mensah", "Crystal Palace", "0", "NA", "0", "0", "NA", "NA", "NA", "0", "NA", "NA", "NA", "0", "NA", "NA", "0", "NA", "0", "NA", "NA", "NA", "0", "NA", "NA", "0", "0", "NA", "NA", "NA", "0", "NA", "NA", "NA", "NA", "2", "75", "1", "NA", "NA", "92"], ["480634", "Lucas Moura (Tottenham Hotspur) wins a free kick in the attacking half.", "90'+2'", "Crystal Palace", "0", "0", "0", "0", "0", "0", "NA", "NA", "NA", "NA", "NA", "NA", "NA", "0", "NA", "NA", "0", "NA", "0", "0", "NA", "NA", "NA", "0", "NA", "NA", "NA", "0", "NA", "NA", "0", "NA", "1", "Lucas Moura", "Tottenham Hotspur", "attacking half", "0", "NA", "NA", "0", "0", "NA", "NA", "NA", "0", "NA", "NA", "NA", "NA", "2", "76", "1", "NA", "NA", "92"], ["480634", "Attempt blocked. Christian Eriksen (Tottenham Hotspur) right footed shot from outside the box is blocked.", "90'+3'", "Crystal Palace", "0", "0", "0", "0", "1", "0", "blocked", "Christian Eriksen", "Tottenham Hotspur", "right", "outside the box", "NA", "NA", "0", "NA", "NA", "0", "NA", "0", "0", "NA", "NA", "NA", "0", "NA", "NA", "NA", "0", "NA", "NA", "0", "NA", "0", "NA", "NA", "NA", "0", "NA", "NA", "0", "0", "NA", "NA", "NA", "0", "NA", "NA", "NA", "NA", "2", "77", "1", "NA", "NA", "93"], ["480634", "Corner,  Tottenham Hotspur. Conceded by Damien Delaney.", "90'+3'", "Crystal Palace", "0", "0", "0", "0", "0", "0", "NA", "NA", "NA", "NA", "NA", "NA", "NA", "0", "NA", "NA", "0", "NA", "0", "0", "NA", "NA", "NA", "0", "NA", "NA", "NA", "0", "NA", "NA", "0", "NA", "0", "NA", "NA", "NA", "1", "Tottenham Hotspur", "Damien Delaney", "0", "0", "NA", "NA", "NA", "0", "NA", "NA", "NA", "NA", "2", "78", "1", "NA", "NA", "93"], ["480634", "Corner,  Tottenham Hotspur. Conceded by Patrick van Aanholt.", "90'+4'", "Crystal Palace", "0", "0", "0", "0", "0", "0", "NA", "NA", "NA", "NA", "NA", "NA", "NA", "0", "NA", "NA", "0", "NA", "0", "0", "NA", "NA", "NA", "0", "NA", "NA", "NA", "0", "NA", "NA", "0", "NA", "0", "NA", "NA", "NA", "1", "Tottenham Hotspur", "Patrick van Aanholt", "0", "0", "NA", "NA", "NA", "0", "NA", "NA", "NA", "NA", "2", "79", "1", "NA", "NA", "94"], ["480634", "Second Half ends, Crystal Palace 0, Tottenham Hotspur 1.", "90'+5'", "Crystal Palace", "0", "1", "0", "0", "0", "0", "NA", "NA", "NA", "NA", "NA", "NA", "NA", "0", "NA", "NA", "0", "NA", "0", "0", "NA", "NA", "NA", "0", "NA", "NA", "NA", "0", "NA", "NA", "0", "NA", "0", "NA", "NA", "NA", "0", "NA", "NA", "0", "0", "NA", "NA", "NA", "0", "NA", "NA", "NA", "NA", "2", "80", "1", "NA", "NA", "95"], ["480634", "Match ends, Crystal Palace 0, Tottenham Hotspur 1.", "90'+5'", "Crystal Palace", "0", "0", "1", "0", "0", "0", "NA", "NA", "NA", "NA", "NA", "NA", "NA", "0", "NA", "NA", "0", "NA", "0", "0", "NA", "NA", "NA", "0", "NA", "NA", "NA", "0", "NA", "NA", "0", "NA", "0", "NA", "NA", "NA", "0", "NA", "NA", "0", "0", "NA", "NA", "NA", "0", "NA", "NA", "NA", "NA", "2", "81", "1", "NA", "NA", "95"]], "Lineup": {"Home Player 9": "Andros Townsend", "Home Player 8": "James Tomkins", "Home Player 5": "Luka Milivojevic", "Home Player 4": "James Mcarthur", "Home Player 7": "Alexander Sorloth", "Home Player 6": "Jairo Riedewald", "Home Player 1": "Christian Benteke", "Home Player 3": "Wayne Hennessey", "Home Player 2": "Timothy Fosu-Mensah", "Away Player 10": "Davinson Sanchez", "Away Player 11": "Victor Wanyama", "Away Player 8": "Erik Lamela", "Away Player 9": "Hugo Lloris", "Away Player 1": "Dele Alli", "Away Player 2": "Serge Aurier", "Away Player 3": "Ben Davies", "Away Player 4": "Mousa Dembele", "Away Player 5": "Eric Dier", "Away Player 6": "Christian Eriksen", "Away Player 7": "Harry Kane", "Game ID": "g_1_nRVaVypF", "Home Player 11": "Aaron Wan-Bissaka", "Home Player 10": "Patrick van Aanholt"}}