{"Stats": {"Full Time Result": "A", "Away Team Corners": 6, "Referee": "R Madley", "Home Team Fouls Committed": 6, "Away Team Shots": 14, "Away Team Red Cards": 0, "Home Team Red Cards": 0, "Half Time Away Team Goals": 1, "Full Time Home Team Goals": 1, "Away Team Yellow Cards": 3, "Away Team Shots on Target": 6, "Half Time Home Team Goals": 1, "Half Time Result": "D", "Away Team Fouls Committed": 7, "Home Team Yellow Cards": 1, "Home Team Shots": 6, "Div": "E0", "Home Team Corners": 7, "Home Team Shots on Target": 2, "Full Time Away Team Goals": 4}, "Description": "Attempt blocked. Demarai Gray (Leicester City) right footed shot from outside the box is blocked. Assisted by Riyad Mahrez. at minute 3. Corner,  Leicester City. Conceded by Ahmed Hegazi. at minute 3. Goal!  West Bromwich Albion 1, Leicester City 0. Salomón Rondón (West Bromwich Albion) left footed shot from the centre of the box to the centre of the goal. Assisted by Oliver Burke with a cross. at minute 8. Foul by Wes Morgan (Leicester City). at minute 10. Salomón Rondón (West Bromwich Albion) wins a free kick on the left wing. at minute 10. Attempt missed. Chris Brunt (West Bromwich Albion) left footed shot from outside the box misses to the right. at minute 13. Offside, Leicester City. Jamie Vardy tries a through ball, but Ben Chilwell is caught offside. at minute 15. Attempt saved. Grzegorz Krychowiak (West Bromwich Albion) left footed shot from outside the box is saved in the top right corner. Assisted by Salomón Rondón. at minute 16. Hand ball by Grzegorz Krychowiak (West Bromwich Albion). at minute 18. Attempt missed. Harry Maguire (Leicester City) right footed shot from outside the box misses to the left. Assisted by Vicente Iborra. at minute 21. Goal!  West Bromwich Albion 1, Leicester City 1. Jamie Vardy (Leicester City) left footed shot from the centre of the box to the bottom right corner. Assisted by Riyad Mahrez with a through ball. at minute 21. Corner,  West Bromwich Albion. Conceded by Danny Simpson. at minute 25. Corner,  West Bromwich Albion. Conceded by Wilfred Ndidi. at minute 25. Corner,  West Bromwich Albion. Conceded by Wes Morgan. at minute 27. Attempt missed. Grzegorz Krychowiak (West Bromwich Albion) left footed shot from outside the box misses to the right following a corner. at minute 28. Foul by Salomón Rondón (West Bromwich Albion). at minute 29. Vicente Iborra (Leicester City) wins a free kick in the defensive half. at minute 29. Foul by Grzegorz Krychowiak (West Bromwich Albion). at minute 31. Harry Maguire (Leicester City) wins a free kick in the defensive half. at minute 31. Corner,  Leicester City. Conceded by Craig Dawson. at minute 31. Attempt blocked. Demarai Gray (Leicester City) right footed shot from the left side of the box is blocked. Assisted by Vicente Iborra. at minute 34. Corner,  Leicester City. Conceded by Kieran Gibbs. at minute 35. Attempt saved. Shinji Okazaki (Leicester City) header from the right side of the six yard box is saved in the top centre of the goal. Assisted by Demarai Gray with a cross. at minute 36. Offside, Leicester City. Ben Chilwell tries a through ball, but Jamie Vardy is caught offside. at minute 37. Attempt missed. Chris Brunt (West Bromwich Albion) left footed shot from outside the box misses to the right. at minute 40. Allan Nyom (West Bromwich Albion) wins a free kick in the defensive half. at minute 41. Foul by Jamie Vardy (Leicester City). at minute 41. Jamie Vardy (Leicester City) is shown the yellow card for a bad foul. at minute 41. Attempt blocked. Salomón Rondón (West Bromwich Albion) right footed shot from the centre of the box is blocked. Assisted by Grzegorz Krychowiak. at minute 42. Corner,  West Bromwich Albion. Conceded by Wes Morgan. at minute 42. Allan Nyom (West Bromwich Albion) wins a free kick in the defensive half. at minute 44. Foul by Demarai Gray (Leicester City). at minute 44. First Half ends, West Bromwich Albion 1, Leicester City 1. at minute 47. Second Half begins West Bromwich Albion 1, Leicester City 1. at minute 45. Corner,  West Bromwich Albion. Conceded by Danny Simpson. at minute 49. Corner,  Leicester City. Conceded by Matt Phillips. at minute 50. Foul by Wes Morgan (Leicester City). at minute 52. Kieran Gibbs (West Bromwich Albion) wins a free kick on the left wing. at minute 52. Foul by Danny Simpson (Leicester City). at minute 53. Oliver Burke (West Bromwich Albion) wins a free kick on the left wing. at minute 53. Danny Simpson (Leicester City) is shown the yellow card for a bad foul. at minute 53. Attempt blocked. Demarai Gray (Leicester City) right footed shot from outside the box is blocked. Assisted by Vicente Iborra. at minute 56. Corner,  West Bromwich Albion. Conceded by Harry Maguire. at minute 57. Substitution, West Bromwich Albion. Sam Field replaces Grzegorz Krychowiak. at minute 59. Substitution, Leicester City. Kelechi Iheanacho replaces Shinji Okazaki. at minute 60. Goal!  West Bromwich Albion 1, Leicester City 2. Riyad Mahrez (Leicester City) left footed shot from the centre of the box to the centre of the goal. Assisted by Kelechi Iheanacho with a through ball. at minute 62. Allan Nyom (West Bromwich Albion) wins a free kick on the right wing. at minute 64. Foul by Vicente Iborra (Leicester City). at minute 64. Corner,  West Bromwich Albion. Conceded by Wes Morgan. at minute 65. Offside, West Bromwich Albion. Kieran Gibbs tries a through ball, but Ahmed Hegazi is caught offside. at minute 65. Substitution, Leicester City. Marc Albrighton replaces Demarai Gray. at minute 67. Foul by Sam Field (West Bromwich Albion). at minute 69. Vicente Iborra (Leicester City) wins a free kick in the attacking half. at minute 69. Substitution, West Bromwich Albion. Jay Rodriguez replaces Matt Phillips. at minute 70. Chris Brunt (West Bromwich Albion) wins a free kick in the attacking half. at minute 73. Foul by Wilfred Ndidi (Leicester City). at minute 73. Wilfred Ndidi (Leicester City) is shown the yellow card for a bad foul. at minute 73. Attempt saved. Jamie Vardy (Leicester City) left footed shot from the centre of the box is saved in the centre of the goal. Assisted by Kelechi Iheanacho with a through ball. at minute 74. Goal!  West Bromwich Albion 1, Leicester City 3. Kelechi Iheanacho (Leicester City) header from the centre of the box to the bottom right corner. Assisted by Ben Chilwell with a cross. at minute 76. Foul by Jake Livermore (West Bromwich Albion). at minute 80. Vicente Iborra (Leicester City) wins a free kick in the defensive half. at minute 80. Jake Livermore (West Bromwich Albion) is shown the yellow card for a bad foul. at minute 80. Attempt missed. Riyad Mahrez (Leicester City) left footed shot from the centre of the box misses to the left. Assisted by Marc Albrighton. at minute 81. Corner,  Leicester City. Conceded by Allan Nyom. at minute 81. Attempt missed. Harry Maguire (Leicester City) header from the centre of the box misses to the left. Assisted by Marc Albrighton with a cross following a corner. at minute 82. Substitution, West Bromwich Albion. Hal Robson-Kanu replaces Oliver Burke. at minute 83. Attempt missed. Riyad Mahrez (Leicester City) left footed shot from outside the box is high and wide to the left. Assisted by Kelechi Iheanacho. at minute 84. Attempt missed. Wilfred Ndidi (Leicester City) right footed shot from outside the box is close, but misses to the left. at minute 87. Substitution, Leicester City. Fousseni Diabaté replaces Riyad Mahrez. at minute 88. Foul by Jake Livermore (West Bromwich Albion). at minute 91. Vicente Iborra (Leicester City) wins a free kick on the right wing. at minute 91. Corner,  Leicester City. Conceded by Jay Rodriguez. at minute 93. Goal!  West Bromwich Albion 1, Leicester City 4. Vicente Iborra (Leicester City) header from very close range to the high centre of the goal. Assisted by Marc Albrighton with a cross following a corner. at minute 93. Second Half ends, West Bromwich Albion 1, Leicester City 4. at minute 95. Match ends, West Bromwich Albion 1, Leicester City 4. at minute 95. Match ends, West Bromwich Albion 1, Leicester City 4. at minute 95. ", "Home Team": "West Bromwich Albion", "Away Team": "Leicester City", "Date": "2018-03-10", "Commentary": [["480609", "First Half begins.", "-", "West Bromwich Albion", "0", "0", "0", "1", "0", "0", "NA", "NA", "NA", "NA", "NA", "NA", "NA", "0", "NA", "NA", "0", "NA", "0", "0", "NA", "NA", "NA", "0", "NA", "NA", "NA", "0", "NA", "NA", "0", "NA", "0", "NA", "NA", "NA", "0", "NA", "NA", "0", "0", "NA", "NA", "NA", "0", "NA", "NA", "NA", "NA", "1", "1", "0", "NA", "NA", "NA"], ["480609", "Lineups are announced and players are warming up.", "-", "West Bromwich Albion", "0", "0", "0", "0", "0", "0", "NA", "NA", "NA", "NA", "NA", "NA", "NA", "0", "NA", "NA", "0", "NA", "0", "0", "NA", "NA", "NA", "0", "NA", "NA", "NA", "0", "NA", "NA", "0", "NA", "0", "NA", "NA", "NA", "0", "NA", "NA", "0", "0", "NA", "NA", "NA", "0", "NA", "NA", "NA", "NA", "1", "2", "0", "NA", "NA", "NA"], ["480609", "Attempt blocked. Demarai Gray (Leicester City) right footed shot from outside the box is blocked. Assisted by Riyad Mahrez.", "3'", "West Bromwich Albion", "0", "0", "0", "0", "1", "0", "blocked", "Demarai Gray", "Leicester City", "right", "outside the box", "NA", "Riyad Mahrez", "0", "NA", "NA", "0", "NA", "0", "0", "NA", "NA", "NA", "0", "NA", "NA", "NA", "0", "NA", "NA", "0", "NA", "0", "NA", "NA", "NA", "0", "NA", "NA", "0", "0", "NA", "NA", "NA", "0", "NA", "NA", "NA", "NA", "1", "3", "0", "NA", "NA", "3"], ["480609", "Corner,  Leicester City. Conceded by Ahmed Hegazi.", "3'", "West Bromwich Albion", "0", "0", "0", "0", "0", "0", "NA", "NA", "NA", "NA", "NA", "NA", "NA", "0", "NA", "NA", "0", "NA", "0", "0", "NA", "NA", "NA", "0", "NA", "NA", "NA", "0", "NA", "NA", "0", "NA", "0", "NA", "NA", "NA", "1", "Leicester City", "Ahmed Hegazi", "0", "0", "NA", "NA", "NA", "0", "NA", "NA", "NA", "NA", "1", "4", "0", "NA", "NA", "3"], ["480609", "Goal!  West Bromwich Albion 1, Leicester City 0. Salomón Rondón (West Bromwich Albion) left footed shot from the centre of the box to the centre of the goal. Assisted by Oliver Burke with a cross.", "8'", "West Bromwich Albion", "1", "0", "0", "0", "1", "0", "goal", "Salomón Rondón", "West Bromwich Albion", "left", "the centre of the box", "centre of the goal", "Oliver Burke", "0", "NA", "NA", "0", "cross", "0", "0", "NA", "NA", "NA", "0", "NA", "NA", "NA", "0", "NA", "NA", "0", "NA", "0", "NA", "NA", "NA", "0", "NA", "NA", "0", "0", "NA", "NA", "NA", "0", "NA", "NA", "NA", "NA", "1", "5", "0", "NA", "NA", "8"], ["480609", "Foul by Wes Morgan (Leicester City).", "10'", "West Bromwich Albion", "1", "0", "0", "0", "0", "0", "NA", "NA", "NA", "NA", "NA", "NA", "NA", "1", "Wes Morgan", "Leicester City", "0", "NA", "0", "0", "NA", "NA", "NA", "0", "NA", "NA", "NA", "0", "NA", "NA", "0", "NA", "0", "NA", "NA", "NA", "0", "NA", "NA", "0", "0", "NA", "NA", "NA", "0", "NA", "NA", "NA", "NA", "1", "6", "0", "NA", "NA", "10"], ["480609", "Salomón Rondón (West Bromwich Albion) wins a free kick on the left wing.", "10'", "West Bromwich Albion", "1", "0", "0", "0", "0", "0", "NA", "NA", "NA", "NA", "NA", "NA", "NA", "0", "NA", "NA", "0", "NA", "0", "0", "NA", "NA", "NA", "0", "NA", "NA", "NA", "0", "NA", "NA", "0", "NA", "1", "Salomón Rondón", "West Bromwich Albion", "NA", "0", "NA", "NA", "0", "0", "NA", "NA", "NA", "0", "NA", "NA", "NA", "NA", "1", "7", "0", "NA", "NA", "10"], ["480609", "Attempt missed. Chris Brunt (West Bromwich Albion) left footed shot from outside the box misses to the right.", "13'", "West Bromwich Albion", "1", "0", "0", "0", "1", "0", "missed", "Chris Brunt", "West Bromwich Albion", "left", "outside the box", "right", "NA", "0", "NA", "NA", "0", "NA", "0", "0", "NA", "NA", "NA", "0", "NA", "NA", "NA", "0", "NA", "NA", "0", "NA", "0", "NA", "NA", "NA", "0", "NA", "NA", "0", "0", "NA", "NA", "NA", "0", "NA", "NA", "NA", "NA", "1", "8", "0", "NA", "NA", "13"], ["480609", "Offside, Leicester City. Jamie Vardy tries a through ball, but Ben Chilwell is caught offside.", "15'", "West Bromwich Albion", "1", "0", "0", "0", "0", "0", "NA", "NA", "NA", "NA", "NA", "NA", "NA", "0", "NA", "NA", "0", "NA", "0", "1", "Leicester City", "Ben Chilwell", "Jamie Vardy", "0", "NA", "NA", "NA", "0", "NA", "NA", "0", "NA", "0", "NA", "NA", "NA", "0", "NA", "NA", "0", "0", "NA", "NA", "NA", "0", "NA", "NA", "NA", "NA", "1", "9", "0", "NA", "NA", "15"], ["480609", "Attempt saved. Grzegorz Krychowiak (West Bromwich Albion) left footed shot from outside the box is saved in the top right corner. Assisted by Salomón Rondón.", "16'", "West Bromwich Albion", "1", "0", "0", "0", "1", "0", "saved", "Grzegorz Krychowiak", "West Bromwich Albion", "left", "outside the box", "the top right corner", "Salomón Rondón", "0", "NA", "NA", "0", "NA", "0", "0", "NA", "NA", "NA", "0", "NA", "NA", "NA", "0", "NA", "NA", "0", "NA", "0", "NA", "NA", "NA", "0", "NA", "NA", "0", "0", "NA", "NA", "NA", "0", "NA", "NA", "NA", "NA", "1", "10", "0", "NA", "NA", "16"], ["480609", "Hand ball by Grzegorz Krychowiak (West Bromwich Albion).", "18'", "West Bromwich Albion", "1", "0", "0", "0", "0", "0", "NA", "NA", "NA", "NA", "NA", "NA", "NA", "0", "NA", "NA", "0", "NA", "0", "0", "NA", "NA", "NA", "0", "NA", "NA", "NA", "0", "NA", "NA", "0", "NA", "0", "NA", "NA", "NA", "0", "NA", "NA", "0", "0", "NA", "NA", "NA", "0", "NA", "NA", "NA", "NA", "1", "11", "0", "NA", "NA", "18"], ["480609", "Attempt missed. Harry Maguire (Leicester City) right footed shot from outside the box misses to the left. Assisted by Vicente Iborra.", "21'", "West Bromwich Albion", "1", "0", "0", "0", "1", "0", "missed", "Harry Maguire", "Leicester City", "right", "outside the box", "left", "Vicente Iborra", "0", "NA", "NA", "0", "NA", "0", "0", "NA", "NA", "NA", "0", "NA", "NA", "NA", "0", "NA", "NA", "0", "NA", "0", "NA", "NA", "NA", "0", "NA", "NA", "0", "0", "NA", "NA", "NA", "0", "NA", "NA", "NA", "NA", "1", "12", "0", "NA", "NA", "21"], ["480609", "Goal!  West Bromwich Albion 1, Leicester City 1. Jamie Vardy (Leicester City) left footed shot from the centre of the box to the bottom right corner. Assisted by Riyad Mahrez with a through ball.", "21'", "West Bromwich Albion", "1", "0", "0", "0", "1", "0", "goal", "Jamie Vardy", "Leicester City", "left", "the centre of the box", "bottom right corner", "Riyad Mahrez", "0", "NA", "NA", "0", "through", "0", "0", "NA", "NA", "NA", "0", "NA", "NA", "NA", "0", "NA", "NA", "0", "NA", "0", "NA", "NA", "NA", "0", "NA", "NA", "0", "0", "NA", "NA", "NA", "0", "NA", "NA", "NA", "NA", "1", "13", "0", "NA", "NA", "21"], ["480609", "Corner,  West Bromwich Albion. Conceded by Danny Simpson.", "25'", "West Bromwich Albion", "1", "0", "0", "0", "0", "0", "NA", "NA", "NA", "NA", "NA", "NA", "NA", "0", "NA", "NA", "0", "NA", "0", "0", "NA", "NA", "NA", "0", "NA", "NA", "NA", "0", "NA", "NA", "0", "NA", "0", "NA", "NA", "NA", "1", "West Bromwich Albion", "Danny Simpson", "0", "0", "NA", "NA", "NA", "0", "NA", "NA", "NA", "NA", "1", "14", "0", "NA", "NA", "25"], ["480609", "Corner,  West Bromwich Albion. Conceded by Wilfred Ndidi.", "25'", "West Bromwich Albion", "1", "0", "0", "0", "0", "0", "NA", "NA", "NA", "NA", "NA", "NA", "NA", "0", "NA", "NA", "0", "NA", "0", "0", "NA", "NA", "NA", "0", "NA", "NA", "NA", "0", "NA", "NA", "0", "NA", "0", "NA", "NA", "NA", "1", "West Bromwich Albion", "Wilfred Ndidi", "0", "0", "NA", "NA", "NA", "0", "NA", "NA", "NA", "NA", "1", "15", "0", "NA", "NA", "25"], ["480609", "Corner,  West Bromwich Albion. Conceded by Wes Morgan.", "27'", "West Bromwich Albion", "1", "0", "0", "0", "0", "0", "NA", "NA", "NA", "NA", "NA", "NA", "NA", "0", "NA", "NA", "0", "NA", "0", "0", "NA", "NA", "NA", "0", "NA", "NA", "NA", "0", "NA", "NA", "0", "NA", "0", "NA", "NA", "NA", "1", "West Bromwich Albion", "Wes Morgan", "0", "0", "NA", "NA", "NA", "0", "NA", "NA", "NA", "NA", "1", "16", "0", "NA", "NA", "27"], ["480609", "Attempt missed. Grzegorz Krychowiak (West Bromwich Albion) left footed shot from outside the box misses to the right following a corner.", "28'", "West Bromwich Albion", "1", "0", "0", "0", "1", "0", "missed", "Grzegorz Krychowiak", "West Bromwich Albion", "left", "outside the box", "right", "NA", "0", "NA", "NA", "0", "NA", "1", "0", "NA", "NA", "NA", "0", "NA", "NA", "NA", "0", "NA", "NA", "0", "NA", "0", "NA", "NA", "NA", "0", "NA", "NA", "0", "0", "NA", "NA", "NA", "0", "NA", "NA", "NA", "NA", "1", "17", "0", "NA", "NA", "28"], ["480609", "Foul by Salomón Rondón (West Bromwich Albion).", "29'", "West Bromwich Albion", "1", "0", "0", "0", "0", "0", "NA", "NA", "NA", "NA", "NA", "NA", "NA", "1", "Salomón Rondón", "West Bromwich Albion", "0", "NA", "0", "0", "NA", "NA", "NA", "0", "NA", "NA", "NA", "0", "NA", "NA", "0", "NA", "0", "NA", "NA", "NA", "0", "NA", "NA", "0", "0", "NA", "NA", "NA", "0", "NA", "NA", "NA", "NA", "1", "18", "0", "NA", "NA", "29"], ["480609", "Vicente Iborra (Leicester City) wins a free kick in the defensive half.", "29'", "West Bromwich Albion", "1", "0", "0", "0", "0", "0", "NA", "NA", "NA", "NA", "NA", "NA", "NA", "0", "NA", "NA", "0", "NA", "0", "0", "NA", "NA", "NA", "0", "NA", "NA", "NA", "0", "NA", "NA", "0", "NA", "1", "Vicente Iborra", "Leicester City", "defensive half", "0", "NA", "NA", "0", "0", "NA", "NA", "NA", "0", "NA", "NA", "NA", "NA", "1", "19", "0", "NA", "NA", "29"], ["480609", "Foul by Grzegorz Krychowiak (West Bromwich Albion).", "31'", "West Bromwich Albion", "1", "0", "0", "0", "0", "0", "NA", "NA", "NA", "NA", "NA", "NA", "NA", "1", "Grzegorz Krychowiak", "West Bromwich Albion", "0", "NA", "0", "0", "NA", "NA", "NA", "0", "NA", "NA", "NA", "0", "NA", "NA", "0", "NA", "0", "NA", "NA", "NA", "0", "NA", "NA", "0", "0", "NA", "NA", "NA", "0", "NA", "NA", "NA", "NA", "1", "20", "0", "NA", "NA", "31"], ["480609", "Harry Maguire (Leicester City) wins a free kick in the defensive half.", "31'", "West Bromwich Albion", "1", "0", "0", "0", "0", "0", "NA", "NA", "NA", "NA", "NA", "NA", "NA", "0", "NA", "NA", "0", "NA", "0", "0", "NA", "NA", "NA", "0", "NA", "NA", "NA", "0", "NA", "NA", "0", "NA", "1", "Harry Maguire", "Leicester City", "defensive half", "0", "NA", "NA", "0", "0", "NA", "NA", "NA", "0", "NA", "NA", "NA", "NA", "1", "21", "0", "NA", "NA", "31"], ["480609", "Corner,  Leicester City. Conceded by Craig Dawson.", "31'", "West Bromwich Albion", "1", "0", "0", "0", "0", "0", "NA", "NA", "NA", "NA", "NA", "NA", "NA", "0", "NA", "NA", "0", "NA", "0", "0", "NA", "NA", "NA", "0", "NA", "NA", "NA", "0", "NA", "NA", "0", "NA", "0", "NA", "NA", "NA", "1", "Leicester City", "Craig Dawson", "0", "0", "NA", "NA", "NA", "0", "NA", "NA", "NA", "NA", "1", "22", "0", "NA", "NA", "31"], ["480609", "Attempt blocked. Demarai Gray (Leicester City) right footed shot from the left side of the box is blocked. Assisted by Vicente Iborra.", "34'", "West Bromwich Albion", "1", "0", "0", "0", "1", "0", "blocked", "Demarai Gray", "Leicester City", "right", "the left side of the box", "NA", "Vicente Iborra", "0", "NA", "NA", "0", "NA", "0", "0", "NA", "NA", "NA", "0", "NA", "NA", "NA", "0", "NA", "NA", "0", "NA", "0", "NA", "NA", "NA", "0", "NA", "NA", "0", "0", "NA", "NA", "NA", "0", "NA", "NA", "NA", "NA", "1", "23", "0", "NA", "NA", "34"], ["480609", "Corner,  Leicester City. Conceded by Kieran Gibbs.", "35'", "West Bromwich Albion", "1", "0", "0", "0", "0", "0", "NA", "NA", "NA", "NA", "NA", "NA", "NA", "0", "NA", "NA", "0", "NA", "0", "0", "NA", "NA", "NA", "0", "NA", "NA", "NA", "0", "NA", "NA", "0", "NA", "0", "NA", "NA", "NA", "1", "Leicester City", "Kieran Gibbs", "0", "0", "NA", "NA", "NA", "0", "NA", "NA", "NA", "NA", "1", "24", "0", "NA", "NA", "35"], ["480609", "Attempt saved. Shinji Okazaki (Leicester City) header from the right side of the six yard box is saved in the top centre of the goal. Assisted by Demarai Gray with a cross.", "36'", "West Bromwich Albion", "1", "0", "0", "0", "1", "0", "saved", "Shinji Okazaki", "Leicester City", "header", "the right side of the six yard box", "the top centre of the goal", "Demarai Gray", "0", "NA", "NA", "0", "cross", "0", "0", "NA", "NA", "NA", "0", "NA", "NA", "NA", "0", "NA", "NA", "0", "NA", "0", "NA", "NA", "NA", "0", "NA", "NA", "0", "0", "NA", "NA", "NA", "0", "NA", "NA", "NA", "NA", "1", "25", "0", "NA", "NA", "36"], ["480609", "Offside, Leicester City. Ben Chilwell tries a through ball, but Jamie Vardy is caught offside.", "37'", "West Bromwich Albion", "1", "0", "0", "0", "0", "0", "NA", "NA", "NA", "NA", "NA", "NA", "NA", "0", "NA", "NA", "0", "NA", "0", "1", "Leicester City", "Jamie Vardy", "Ben Chilwell", "0", "NA", "NA", "NA", "0", "NA", "NA", "0", "NA", "0", "NA", "NA", "NA", "0", "NA", "NA", "0", "0", "NA", "NA", "NA", "0", "NA", "NA", "NA", "NA", "1", "26", "0", "NA", "NA", "37"], ["480609", "Attempt missed. Chris Brunt (West Bromwich Albion) left footed shot from outside the box misses to the right.", "40'", "West Bromwich Albion", "1", "0", "0", "0", "1", "0", "missed", "Chris Brunt", "West Bromwich Albion", "left", "outside the box", "right", "NA", "0", "NA", "NA", "0", "NA", "0", "0", "NA", "NA", "NA", "0", "NA", "NA", "NA", "0", "NA", "NA", "0", "NA", "0", "NA", "NA", "NA", "0", "NA", "NA", "0", "0", "NA", "NA", "NA", "0", "NA", "NA", "NA", "NA", "1", "27", "0", "NA", "NA", "40"], ["480609", "Allan Nyom (West Bromwich Albion) wins a free kick in the defensive half.", "41'", "West Bromwich Albion", "1", "0", "0", "0", "0", "0", "NA", "NA", "NA", "NA", "NA", "NA", "NA", "0", "NA", "NA", "0", "NA", "0", "0", "NA", "NA", "NA", "0", "NA", "NA", "NA", "0", "NA", "NA", "0", "NA", "1", "Allan Nyom", "West Bromwich Albion", "defensive half", "0", "NA", "NA", "0", "0", "NA", "NA", "NA", "0", "NA", "NA", "NA", "NA", "1", "28", "0", "NA", "NA", "41"], ["480609", "Foul by Jamie Vardy (Leicester City).", "41'", "West Bromwich Albion", "1", "0", "0", "0", "0", "0", "NA", "NA", "NA", "NA", "NA", "NA", "NA", "1", "Jamie Vardy", "Leicester City", "0", "NA", "0", "0", "NA", "NA", "NA", "0", "NA", "NA", "NA", "0", "NA", "NA", "0", "NA", "0", "NA", "NA", "NA", "0", "NA", "NA", "0", "0", "NA", "NA", "NA", "0", "NA", "NA", "NA", "NA", "1", "29", "0", "NA", "NA", "41"], ["480609", "Jamie Vardy (Leicester City) is shown the yellow card for a bad foul.", "41'", "West Bromwich Albion", "1", "0", "0", "0", "0", "0", "NA", "NA", "NA", "NA", "NA", "NA", "NA", "0", "NA", "NA", "0", "NA", "0", "0", "NA", "NA", "NA", "1", "yellow", "Jamie Vardy", "Leicester City", "0", "NA", "NA", "0", "NA", "0", "NA", "NA", "NA", "0", "NA", "NA", "0", "0", "NA", "NA", "NA", "0", "NA", "NA", "NA", "NA", "1", "30", "0", "NA", "NA", "41"], ["480609", "Attempt blocked. Salomón Rondón (West Bromwich Albion) right footed shot from the centre of the box is blocked. Assisted by Grzegorz Krychowiak.", "42'", "West Bromwich Albion", "1", "0", "0", "0", "1", "0", "blocked", "Salomón Rondón", "West Bromwich Albion", "right", "the centre of the box", "NA", "Grzegorz Krychowiak", "0", "NA", "NA", "0", "NA", "0", "0", "NA", "NA", "NA", "0", "NA", "NA", "NA", "0", "NA", "NA", "0", "NA", "0", "NA", "NA", "NA", "0", "NA", "NA", "0", "0", "NA", "NA", "NA", "0", "NA", "NA", "NA", "NA", "1", "31", "0", "NA", "NA", "42"], ["480609", "Corner,  West Bromwich Albion. Conceded by Wes Morgan.", "42'", "West Bromwich Albion", "1", "0", "0", "0", "0", "0", "NA", "NA", "NA", "NA", "NA", "NA", "NA", "0", "NA", "NA", "0", "NA", "0", "0", "NA", "NA", "NA", "0", "NA", "NA", "NA", "0", "NA", "NA", "0", "NA", "0", "NA", "NA", "NA", "1", "West Bromwich Albion", "Wes Morgan", "0", "0", "NA", "NA", "NA", "0", "NA", "NA", "NA", "NA", "1", "32", "0", "NA", "NA", "42"], ["480609", "Allan Nyom (West Bromwich Albion) wins a free kick in the defensive half.", "44'", "West Bromwich Albion", "1", "0", "0", "0", "0", "0", "NA", "NA", "NA", "NA", "NA", "NA", "NA", "0", "NA", "NA", "0", "NA", "0", "0", "NA", "NA", "NA", "0", "NA", "NA", "NA", "0", "NA", "NA", "0", "NA", "1", "Allan Nyom", "West Bromwich Albion", "defensive half", "0", "NA", "NA", "0", "0", "NA", "NA", "NA", "0", "NA", "NA", "NA", "NA", "1", "33", "0", "NA", "NA", "44"], ["480609", "Foul by Demarai Gray (Leicester City).", "44'", "West Bromwich Albion", "1", "0", "0", "0", "0", "0", "NA", "NA", "NA", "NA", "NA", "NA", "NA", "1", "Demarai Gray", "Leicester City", "0", "NA", "0", "0", "NA", "NA", "NA", "0", "NA", "NA", "NA", "0", "NA", "NA", "0", "NA", "0", "NA", "NA", "NA", "0", "NA", "NA", "0", "0", "NA", "NA", "NA", "0", "NA", "NA", "NA", "NA", "1", "34", "0", "NA", "NA", "44"], ["480609", "First Half ends, West Bromwich Albion 1, Leicester City 1.", "45'+2'", "West Bromwich Albion", "1", "1", "0", "0", "0", "0", "NA", "NA", "NA", "NA", "NA", "NA", "NA", "0", "NA", "NA", "0", "NA", "0", "0", "NA", "NA", "NA", "0", "NA", "NA", "NA", "0", "NA", "NA", "0", "NA", "0", "NA", "NA", "NA", "0", "NA", "NA", "0", "0", "NA", "NA", "NA", "0", "NA", "NA", "NA", "NA", "1", "35", "1", "NA", "NA", "47"], ["480609", "Second Half begins West Bromwich Albion 1, Leicester City 1.", "45'", "West Bromwich Albion", "1", "0", "0", "1", "0", "0", "NA", "NA", "NA", "NA", "NA", "NA", "NA", "0", "NA", "NA", "0", "NA", "0", "0", "NA", "NA", "NA", "0", "NA", "NA", "NA", "0", "NA", "NA", "0", "NA", "0", "NA", "NA", "NA", "0", "NA", "NA", "0", "0", "NA", "NA", "NA", "0", "NA", "NA", "NA", "NA", "2", "36", "0", "NA", "NA", "45"], ["480609", "Corner,  West Bromwich Albion. Conceded by Danny Simpson.", "49'", "West Bromwich Albion", "1", "0", "0", "0", "0", "0", "NA", "NA", "NA", "NA", "NA", "NA", "NA", "0", "NA", "NA", "0", "NA", "0", "0", "NA", "NA", "NA", "0", "NA", "NA", "NA", "0", "NA", "NA", "0", "NA", "0", "NA", "NA", "NA", "1", "West Bromwich Albion", "Danny Simpson", "0", "0", "NA", "NA", "NA", "0", "NA", "NA", "NA", "NA", "2", "37", "0", "NA", "NA", "49"], ["480609", "Corner,  Leicester City. Conceded by Matt Phillips.", "50'", "West Bromwich Albion", "1", "0", "0", "0", "0", "0", "NA", "NA", "NA", "NA", "NA", "NA", "NA", "0", "NA", "NA", "0", "NA", "0", "0", "NA", "NA", "NA", "0", "NA", "NA", "NA", "0", "NA", "NA", "0", "NA", "0", "NA", "NA", "NA", "1", "Leicester City", "Matt Phillips", "0", "0", "NA", "NA", "NA", "0", "NA", "NA", "NA", "NA", "2", "38", "0", "NA", "NA", "50"], ["480609", "Foul by Wes Morgan (Leicester City).", "52'", "West Bromwich Albion", "1", "0", "0", "0", "0", "0", "NA", "NA", "NA", "NA", "NA", "NA", "NA", "1", "Wes Morgan", "Leicester City", "0", "NA", "0", "0", "NA", "NA", "NA", "0", "NA", "NA", "NA", "0", "NA", "NA", "0", "NA", "0", "NA", "NA", "NA", "0", "NA", "NA", "0", "0", "NA", "NA", "NA", "0", "NA", "NA", "NA", "NA", "2", "39", "0", "NA", "NA", "52"], ["480609", "Kieran Gibbs (West Bromwich Albion) wins a free kick on the left wing.", "52'", "West Bromwich Albion", "1", "0", "0", "0", "0", "0", "NA", "NA", "NA", "NA", "NA", "NA", "NA", "0", "NA", "NA", "0", "NA", "0", "0", "NA", "NA", "NA", "0", "NA", "NA", "NA", "0", "NA", "NA", "0", "NA", "1", "Kieran Gibbs", "West Bromwich Albion", "NA", "0", "NA", "NA", "0", "0", "NA", "NA", "NA", "0", "NA", "NA", "NA", "NA", "2", "40", "0", "NA", "NA", "52"], ["480609", "Foul by Danny Simpson (Leicester City).", "53'", "West Bromwich Albion", "1", "0", "0", "0", "0", "0", "NA", "NA", "NA", "NA", "NA", "NA", "NA", "1", "Danny Simpson", "Leicester City", "0", "NA", "0", "0", "NA", "NA", "NA", "0", "NA", "NA", "NA", "0", "NA", "NA", "0", "NA", "0", "NA", "NA", "NA", "0", "NA", "NA", "0", "0", "NA", "NA", "NA", "0", "NA", "NA", "NA", "NA", "2", "41", "0", "NA", "NA", "53"], ["480609", "Oliver Burke (West Bromwich Albion) wins a free kick on the left wing.", "53'", "West Bromwich Albion", "1", "0", "0", "0", "0", "0", "NA", "NA", "NA", "NA", "NA", "NA", "NA", "0", "NA", "NA", "0", "NA", "0", "0", "NA", "NA", "NA", "0", "NA", "NA", "NA", "0", "NA", "NA", "0", "NA", "1", "Oliver Burke", "West Bromwich Albion", "NA", "0", "NA", "NA", "0", "0", "NA", "NA", "NA", "0", "NA", "NA", "NA", "NA", "2", "42", "0", "NA", "NA", "53"], ["480609", "Danny Simpson (Leicester City) is shown the yellow card for a bad foul.", "53'", "West Bromwich Albion", "1", "0", "0", "0", "0", "0", "NA", "NA", "NA", "NA", "NA", "NA", "NA", "0", "NA", "NA", "0", "NA", "0", "0", "NA", "NA", "NA", "1", "yellow", "Danny Simpson", "Leicester City", "0", "NA", "NA", "0", "NA", "0", "NA", "NA", "NA", "0", "NA", "NA", "0", "0", "NA", "NA", "NA", "0", "NA", "NA", "NA", "NA", "2", "43", "0", "NA", "NA", "53"], ["480609", "Attempt blocked. Demarai Gray (Leicester City) right footed shot from outside the box is blocked. Assisted by Vicente Iborra.", "56'", "West Bromwich Albion", "1", "0", "0", "0", "1", "0", "blocked", "Demarai Gray", "Leicester City", "right", "outside the box", "NA", "Vicente Iborra", "0", "NA", "NA", "0", "NA", "0", "0", "NA", "NA", "NA", "0", "NA", "NA", "NA", "0", "NA", "NA", "0", "NA", "0", "NA", "NA", "NA", "0", "NA", "NA", "0", "0", "NA", "NA", "NA", "0", "NA", "NA", "NA", "NA", "2", "44", "0", "NA", "NA", "56"], ["480609", "Corner,  West Bromwich Albion. Conceded by Harry Maguire.", "57'", "West Bromwich Albion", "1", "0", "0", "0", "0", "0", "NA", "NA", "NA", "NA", "NA", "NA", "NA", "0", "NA", "NA", "0", "NA", "0", "0", "NA", "NA", "NA", "0", "NA", "NA", "NA", "0", "NA", "NA", "0", "NA", "0", "NA", "NA", "NA", "1", "West Bromwich Albion", "Harry Maguire", "0", "0", "NA", "NA", "NA", "0", "NA", "NA", "NA", "NA", "2", "45", "0", "NA", "NA", "57"], ["480609", "Substitution, West Bromwich Albion. Sam Field replaces Grzegorz Krychowiak.", "59'", "West Bromwich Albion", "1", "0", "0", "0", "0", "0", "NA", "NA", "NA", "NA", "NA", "NA", "NA", "0", "NA", "NA", "0", "NA", "0", "0", "NA", "NA", "NA", "0", "NA", "NA", "NA", "0", "NA", "NA", "0", "NA", "0", "NA", "NA", "NA", "0", "NA", "NA", "1", "0", "West Bromwich Albion", "Sam Field", "Grzegorz Krychowiak", "0", "NA", "NA", "NA", "NA", "2", "46", "0", "NA", "NA", "59"], ["480609", "Substitution, Leicester City. Kelechi Iheanacho replaces Shinji Okazaki.", "60'", "West Bromwich Albion", "1", "0", "0", "0", "0", "0", "NA", "NA", "NA", "NA", "NA", "NA", "NA", "0", "NA", "NA", "0", "NA", "0", "0", "NA", "NA", "NA", "0", "NA", "NA", "NA", "0", "NA", "NA", "0", "NA", "0", "NA", "NA", "NA", "0", "NA", "NA", "1", "0", "Leicester City", "Kelechi Iheanacho", "Shinji Okazaki", "0", "NA", "NA", "NA", "NA", "2", "47", "0", "NA", "NA", "60"], ["480609", "Goal!  West Bromwich Albion 1, Leicester City 2. Riyad Mahrez (Leicester City) left footed shot from the centre of the box to the centre of the goal. Assisted by Kelechi Iheanacho with a through ball.", "62'", "West Bromwich Albion", "1", "0", "0", "0", "1", "0", "goal", "Riyad Mahrez", "Leicester City", "left", "the centre of the box", "centre of the goal", "Kelechi Iheanacho", "0", "NA", "NA", "0", "through", "0", "0", "NA", "NA", "NA", "0", "NA", "NA", "NA", "0", "NA", "NA", "0", "NA", "0", "NA", "NA", "NA", "0", "NA", "NA", "0", "0", "NA", "NA", "NA", "0", "NA", "NA", "NA", "NA", "2", "48", "0", "NA", "NA", "62"], ["480609", "Allan Nyom (West Bromwich Albion) wins a free kick on the right wing.", "64'", "West Bromwich Albion", "1", "0", "0", "0", "0", "0", "NA", "NA", "NA", "NA", "NA", "NA", "NA", "0", "NA", "NA", "0", "NA", "0", "0", "NA", "NA", "NA", "0", "NA", "NA", "NA", "0", "NA", "NA", "0", "NA", "1", "Allan Nyom", "West Bromwich Albion", "NA", "0", "NA", "NA", "0", "0", "NA", "NA", "NA", "0", "NA", "NA", "NA", "NA", "2", "49", "0", "NA", "NA", "64"], ["480609", "Foul by Vicente Iborra (Leicester City).", "64'", "West Bromwich Albion", "1", "0", "0", "0", "0", "0", "NA", "NA", "NA", "NA", "NA", "NA", "NA", "1", "Vicente Iborra", "Leicester City", "0", "NA", "0", "0", "NA", "NA", "NA", "0", "NA", "NA", "NA", "0", "NA", "NA", "0", "NA", "0", "NA", "NA", "NA", "0", "NA", "NA", "0", "0", "NA", "NA", "NA", "0", "NA", "NA", "NA", "NA", "2", "50", "0", "NA", "NA", "64"], ["480609", "Corner,  West Bromwich Albion. Conceded by Wes Morgan.", "65'", "West Bromwich Albion", "1", "0", "0", "0", "0", "0", "NA", "NA", "NA", "NA", "NA", "NA", "NA", "0", "NA", "NA", "0", "NA", "0", "0", "NA", "NA", "NA", "0", "NA", "NA", "NA", "0", "NA", "NA", "0", "NA", "0", "NA", "NA", "NA", "1", "West Bromwich Albion", "Wes Morgan", "0", "0", "NA", "NA", "NA", "0", "NA", "NA", "NA", "NA", "2", "51", "0", "NA", "NA", "65"], ["480609", "Offside, West Bromwich Albion. Kieran Gibbs tries a through ball, but Ahmed Hegazi is caught offside.", "65'", "West Bromwich Albion", "1", "0", "0", "0", "0", "0", "NA", "NA", "NA", "NA", "NA", "NA", "NA", "0", "NA", "NA", "0", "NA", "0", "1", "West Bromwich Albion", "Ahmed Hegazi", "Kieran Gibbs", "0", "NA", "NA", "NA", "0", "NA", "NA", "0", "NA", "0", "NA", "NA", "NA", "0", "NA", "NA", "0", "0", "NA", "NA", "NA", "0", "NA", "NA", "NA", "NA", "2", "52", "0", "NA", "NA", "65"], ["480609", "Substitution, Leicester City. Marc Albrighton replaces Demarai Gray.", "67'", "West Bromwich Albion", "1", "0", "0", "0", "0", "0", "NA", "NA", "NA", "NA", "NA", "NA", "NA", "0", "NA", "NA", "0", "NA", "0", "0", "NA", "NA", "NA", "0", "NA", "NA", "NA", "0", "NA", "NA", "0", "NA", "0", "NA", "NA", "NA", "0", "NA", "NA", "1", "0", "Leicester City", "Marc Albrighton", "Demarai Gray", "0", "NA", "NA", "NA", "NA", "2", "53", "0", "NA", "NA", "67"], ["480609", "Foul by Sam Field (West Bromwich Albion).", "69'", "West Bromwich Albion", "1", "0", "0", "0", "0", "0", "NA", "NA", "NA", "NA", "NA", "NA", "NA", "1", "Sam Field", "West Bromwich Albion", "0", "NA", "0", "0", "NA", "NA", "NA", "0", "NA", "NA", "NA", "0", "NA", "NA", "0", "NA", "0", "NA", "NA", "NA", "0", "NA", "NA", "0", "0", "NA", "NA", "NA", "0", "NA", "NA", "NA", "NA", "2", "54", "0", "NA", "NA", "69"], ["480609", "Vicente Iborra (Leicester City) wins a free kick in the attacking half.", "69'", "West Bromwich Albion", "1", "0", "0", "0", "0", "0", "NA", "NA", "NA", "NA", "NA", "NA", "NA", "0", "NA", "NA", "0", "NA", "0", "0", "NA", "NA", "NA", "0", "NA", "NA", "NA", "0", "NA", "NA", "0", "NA", "1", "Vicente Iborra", "Leicester City", "attacking half", "0", "NA", "NA", "0", "0", "NA", "NA", "NA", "0", "NA", "NA", "NA", "NA", "2", "55", "0", "NA", "NA", "69"], ["480609", "Substitution, West Bromwich Albion. Jay Rodriguez replaces Matt Phillips.", "70'", "West Bromwich Albion", "1", "0", "0", "0", "0", "0", "NA", "NA", "NA", "NA", "NA", "NA", "NA", "0", "NA", "NA", "0", "NA", "0", "0", "NA", "NA", "NA", "0", "NA", "NA", "NA", "0", "NA", "NA", "0", "NA", "0", "NA", "NA", "NA", "0", "NA", "NA", "1", "0", "West Bromwich Albion", "Jay Rodriguez", "Matt Phillips", "0", "NA", "NA", "NA", "NA", "2", "56", "0", "NA", "NA", "70"], ["480609", "Chris Brunt (West Bromwich Albion) wins a free kick in the attacking half.", "73'", "West Bromwich Albion", "1", "0", "0", "0", "0", "0", "NA", "NA", "NA", "NA", "NA", "NA", "NA", "0", "NA", "NA", "0", "NA", "0", "0", "NA", "NA", "NA", "0", "NA", "NA", "NA", "0", "NA", "NA", "0", "NA", "1", "Chris Brunt", "West Bromwich Albion", "attacking half", "0", "NA", "NA", "0", "0", "NA", "NA", "NA", "0", "NA", "NA", "NA", "NA", "2", "57", "0", "NA", "NA", "73"], ["480609", "Foul by Wilfred Ndidi (Leicester City).", "73'", "West Bromwich Albion", "1", "0", "0", "0", "0", "0", "NA", "NA", "NA", "NA", "NA", "NA", "NA", "1", "Wilfred Ndidi", "Leicester City", "0", "NA", "0", "0", "NA", "NA", "NA", "0", "NA", "NA", "NA", "0", "NA", "NA", "0", "NA", "0", "NA", "NA", "NA", "0", "NA", "NA", "0", "0", "NA", "NA", "NA", "0", "NA", "NA", "NA", "NA", "2", "58", "0", "NA", "NA", "73"], ["480609", "Wilfred Ndidi (Leicester City) is shown the yellow card for a bad foul.", "73'", "West Bromwich Albion", "1", "0", "0", "0", "0", "0", "NA", "NA", "NA", "NA", "NA", "NA", "NA", "0", "NA", "NA", "0", "NA", "0", "0", "NA", "NA", "NA", "1", "yellow", "Wilfred Ndidi", "Leicester City", "0", "NA", "NA", "0", "NA", "0", "NA", "NA", "NA", "0", "NA", "NA", "0", "0", "NA", "NA", "NA", "0", "NA", "NA", "NA", "NA", "2", "59", "0", "NA", "NA", "73"], ["480609", "Attempt saved. Jamie Vardy (Leicester City) left footed shot from the centre of the box is saved in the centre of the goal. Assisted by Kelechi Iheanacho with a through ball.", "74'", "West Bromwich Albion", "1", "0", "0", "0", "1", "0", "saved", "Jamie Vardy", "Leicester City", "left", "the centre of the box", "the centre of the goal", "Kelechi Iheanacho", "0", "NA", "NA", "0", "through", "0", "0", "NA", "NA", "NA", "0", "NA", "NA", "NA", "0", "NA", "NA", "0", "NA", "0", "NA", "NA", "NA", "0", "NA", "NA", "0", "0", "NA", "NA", "NA", "0", "NA", "NA", "NA", "NA", "2", "60", "0", "NA", "NA", "74"], ["480609", "Goal!  West Bromwich Albion 1, Leicester City 3. Kelechi Iheanacho (Leicester City) header from the centre of the box to the bottom right corner. Assisted by Ben Chilwell with a cross.", "76'", "West Bromwich Albion", "1", "0", "0", "0", "1", "0", "goal", "Kelechi Iheanacho", "Leicester City", "header", "the centre of the box", "bottom right corner", "Ben Chilwell", "0", "NA", "NA", "0", "cross", "0", "0", "NA", "NA", "NA", "0", "NA", "NA", "NA", "0", "NA", "NA", "0", "NA", "0", "NA", "NA", "NA", "0", "NA", "NA", "0", "0", "NA", "NA", "NA", "0", "NA", "NA", "NA", "NA", "2", "61", "0", "NA", "NA", "76"], ["480609", "Foul by Jake Livermore (West Bromwich Albion).", "80'", "West Bromwich Albion", "1", "0", "0", "0", "0", "0", "NA", "NA", "NA", "NA", "NA", "NA", "NA", "1", "Jake Livermore", "West Bromwich Albion", "0", "NA", "0", "0", "NA", "NA", "NA", "0", "NA", "NA", "NA", "0", "NA", "NA", "0", "NA", "0", "NA", "NA", "NA", "0", "NA", "NA", "0", "0", "NA", "NA", "NA", "0", "NA", "NA", "NA", "NA", "2", "62", "0", "NA", "NA", "80"], ["480609", "Vicente Iborra (Leicester City) wins a free kick in the defensive half.", "80'", "West Bromwich Albion", "1", "0", "0", "0", "0", "0", "NA", "NA", "NA", "NA", "NA", "NA", "NA", "0", "NA", "NA", "0", "NA", "0", "0", "NA", "NA", "NA", "0", "NA", "NA", "NA", "0", "NA", "NA", "0", "NA", "1", "Vicente Iborra", "Leicester City", "defensive half", "0", "NA", "NA", "0", "0", "NA", "NA", "NA", "0", "NA", "NA", "NA", "NA", "2", "63", "0", "NA", "NA", "80"], ["480609", "Jake Livermore (West Bromwich Albion) is shown the yellow card for a bad foul.", "80'", "West Bromwich Albion", "1", "0", "0", "0", "0", "0", "NA", "NA", "NA", "NA", "NA", "NA", "NA", "0", "NA", "NA", "0", "NA", "0", "0", "NA", "NA", "NA", "1", "yellow", "Jake Livermore", "West Bromwich Albion", "0", "NA", "NA", "0", "NA", "0", "NA", "NA", "NA", "0", "NA", "NA", "0", "0", "NA", "NA", "NA", "0", "NA", "NA", "NA", "NA", "2", "64", "0", "NA", "NA", "80"], ["480609", "Attempt missed. Riyad Mahrez (Leicester City) left footed shot from the centre of the box misses to the left. Assisted by Marc Albrighton.", "81'", "West Bromwich Albion", "1", "0", "0", "0", "1", "0", "missed", "Riyad Mahrez", "Leicester City", "left", "the centre of the box", "left", "Marc Albrighton", "0", "NA", "NA", "0", "NA", "0", "0", "NA", "NA", "NA", "0", "NA", "NA", "NA", "0", "NA", "NA", "0", "NA", "0", "NA", "NA", "NA", "0", "NA", "NA", "0", "0", "NA", "NA", "NA", "0", "NA", "NA", "NA", "NA", "2", "65", "0", "NA", "NA", "81"], ["480609", "Corner,  Leicester City. Conceded by Allan Nyom.", "81'", "West Bromwich Albion", "1", "0", "0", "0", "0", "0", "NA", "NA", "NA", "NA", "NA", "NA", "NA", "0", "NA", "NA", "0", "NA", "0", "0", "NA", "NA", "NA", "0", "NA", "NA", "NA", "0", "NA", "NA", "0", "NA", "0", "NA", "NA", "NA", "1", "Leicester City", "Allan Nyom", "0", "0", "NA", "NA", "NA", "0", "NA", "NA", "NA", "NA", "2", "66", "0", "NA", "NA", "81"], ["480609", "Attempt missed. Harry Maguire (Leicester City) header from the centre of the box misses to the left. Assisted by Marc Albrighton with a cross following a corner.", "82'", "West Bromwich Albion", "1", "0", "0", "0", "1", "0", "missed", "Harry Maguire", "Leicester City", "header", "the centre of the box", "left", "Marc Albrighton", "0", "NA", "NA", "0", "cross", "1", "0", "NA", "NA", "NA", "0", "NA", "NA", "NA", "0", "NA", "NA", "0", "NA", "0", "NA", "NA", "NA", "0", "NA", "NA", "0", "0", "NA", "NA", "NA", "0", "NA", "NA", "NA", "NA", "2", "67", "0", "NA", "NA", "82"], ["480609", "Substitution, West Bromwich Albion. Hal Robson-Kanu replaces Oliver Burke.", "83'", "West Bromwich Albion", "1", "0", "0", "0", "0", "0", "NA", "NA", "NA", "NA", "NA", "NA", "NA", "0", "NA", "NA", "0", "NA", "0", "0", "NA", "NA", "NA", "0", "NA", "NA", "NA", "0", "NA", "NA", "0", "NA", "0", "NA", "NA", "NA", "0", "NA", "NA", "1", "0", "West Bromwich Albion", "Hal Robson-Kanu", "Oliver Burke", "0", "NA", "NA", "NA", "NA", "2", "68", "0", "NA", "NA", "83"], ["480609", "Attempt missed. Riyad Mahrez (Leicester City) left footed shot from outside the box is high and wide to the left. Assisted by Kelechi Iheanacho.", "84'", "West Bromwich Albion", "1", "0", "0", "0", "1", "0", "missed", "Riyad Mahrez", "Leicester City", "left", "outside the box", "high and wide to the left", "Kelechi Iheanacho", "0", "NA", "NA", "0", "NA", "0", "0", "NA", "NA", "NA", "0", "NA", "NA", "NA", "0", "NA", "NA", "0", "NA", "0", "NA", "NA", "NA", "0", "NA", "NA", "0", "0", "NA", "NA", "NA", "0", "NA", "NA", "NA", "NA", "2", "69", "0", "NA", "NA", "84"], ["480609", "Attempt missed. Wilfred Ndidi (Leicester City) right footed shot from outside the box is close, but misses to the left.", "87'", "West Bromwich Albion", "1", "0", "0", "0", "1", "0", "missed", "Wilfred Ndidi", "Leicester City", "right", "outside the box", "close, but left", "NA", "0", "NA", "NA", "0", "NA", "0", "0", "NA", "NA", "NA", "0", "NA", "NA", "NA", "0", "NA", "NA", "0", "NA", "0", "NA", "NA", "NA", "0", "NA", "NA", "0", "0", "NA", "NA", "NA", "0", "NA", "NA", "NA", "NA", "2", "70", "0", "NA", "NA", "87"], ["480609", "Substitution, Leicester City. Fousseni Diabaté replaces Riyad Mahrez.", "88'", "West Bromwich Albion", "1", "0", "0", "0", "0", "0", "NA", "NA", "NA", "NA", "NA", "NA", "NA", "0", "NA", "NA", "0", "NA", "0", "0", "NA", "NA", "NA", "0", "NA", "NA", "NA", "0", "NA", "NA", "0", "NA", "0", "NA", "NA", "NA", "0", "NA", "NA", "1", "0", "Leicester City", "Fousseni Diabaté", "Riyad Mahrez", "0", "NA", "NA", "NA", "NA", "2", "71", "0", "NA", "NA", "88"], ["480609", "Foul by Jake Livermore (West Bromwich Albion).", "90'+1'", "West Bromwich Albion", "1", "0", "0", "0", "0", "0", "NA", "NA", "NA", "NA", "NA", "NA", "NA", "1", "Jake Livermore", "West Bromwich Albion", "0", "NA", "0", "0", "NA", "NA", "NA", "0", "NA", "NA", "NA", "0", "NA", "NA", "0", "NA", "0", "NA", "NA", "NA", "0", "NA", "NA", "0", "0", "NA", "NA", "NA", "0", "NA", "NA", "NA", "NA", "2", "72", "1", "NA", "NA", "91"], ["480609", "Vicente Iborra (Leicester City) wins a free kick on the right wing.", "90'+1'", "West Bromwich Albion", "1", "0", "0", "0", "0", "0", "NA", "NA", "NA", "NA", "NA", "NA", "NA", "0", "NA", "NA", "0", "NA", "0", "0", "NA", "NA", "NA", "0", "NA", "NA", "NA", "0", "NA", "NA", "0", "NA", "1", "Vicente Iborra", "Leicester City", "NA", "0", "NA", "NA", "0", "0", "NA", "NA", "NA", "0", "NA", "NA", "NA", "NA", "2", "73", "1", "NA", "NA", "91"], ["480609", "Corner,  Leicester City. Conceded by Jay Rodriguez.", "90'+3'", "West Bromwich Albion", "1", "0", "0", "0", "0", "0", "NA", "NA", "NA", "NA", "NA", "NA", "NA", "0", "NA", "NA", "0", "NA", "0", "0", "NA", "NA", "NA", "0", "NA", "NA", "NA", "0", "NA", "NA", "0", "NA", "0", "NA", "NA", "NA", "1", "Leicester City", "Jay Rodriguez", "0", "0", "NA", "NA", "NA", "0", "NA", "NA", "NA", "NA", "2", "74", "1", "NA", "NA", "93"], ["480609", "Goal!  West Bromwich Albion 1, Leicester City 4. Vicente Iborra (Leicester City) header from very close range to the high centre of the goal. Assisted by Marc Albrighton with a cross following a corner.", "90'+3'", "West Bromwich Albion", "1", "0", "0", "0", "1", "0", "goal", "Vicente Iborra", "Leicester City", "header", "very close range", "high centre of the goal", "Marc Albrighton", "0", "NA", "NA", "0", "cross", "1", "0", "NA", "NA", "NA", "0", "NA", "NA", "NA", "0", "NA", "NA", "0", "NA", "0", "NA", "NA", "NA", "0", "NA", "NA", "0", "0", "NA", "NA", "NA", "0", "NA", "NA", "NA", "NA", "2", "75", "1", "NA", "NA", "93"], ["480609", "Second Half ends, West Bromwich Albion 1, Leicester City 4.", "90'+5'", "West Bromwich Albion", "1", "1", "0", "0", "0", "0", "NA", "NA", "NA", "NA", "NA", "NA", "NA", "0", "NA", "NA", "0", "NA", "0", "0", "NA", "NA", "NA", "0", "NA", "NA", "NA", "0", "NA", "NA", "0", "NA", "0", "NA", "NA", "NA", "0", "NA", "NA", "0", "0", "NA", "NA", "NA", "0", "NA", "NA", "NA", "NA", "2", "76", "1", "NA", "NA", "95"], ["480609", "Match ends, West Bromwich Albion 1, Leicester City 4.", "90'+5'", "West Bromwich Albion", "1", "0", "1", "0", "0", "0", "NA", "NA", "NA", "NA", "NA", "NA", "NA", "0", "NA", "NA", "0", "NA", "0", "0", "NA", "NA", "NA", "0", "NA", "NA", "NA", "0", "NA", "NA", "0", "NA", "0", "NA", "NA", "NA", "0", "NA", "NA", "0", "0", "NA", "NA", "NA", "0", "NA", "NA", "NA", "NA", "2", "77", "1", "NA", "NA", "95"], ["480609", "Match ends, West Bromwich Albion 1, Leicester City 4.", "90'+5'", "West Bromwich Albion", "1", "0", "1", "0", "0", "0", "NA", "NA", "NA", "NA", "NA", "NA", "NA", "0", "NA", "NA", "0", "NA", "0", "0", "NA", "NA", "NA", "0", "NA", "NA", "NA", "0", "NA", "NA", "0", "NA", "0", "NA", "NA", "NA", "0", "NA", "NA", "0", "0", "NA", "NA", "NA", "0", "NA", "NA", "NA", "NA", "2", "78", "1", "NA", "NA", "95"]], "Lineup": {"Home Player 9": "Allan Nyom", "Home Player 8": "Jake Livermore", "Home Player 5": "Kieran Gibbs", "Home Player 4": "Ben Foster", "Home Player 7": "Grzegorz Krychowiak", "Home Player 6": "Ahmed Hegazy", "Home Player 1": "Chris Brunt", "Home Player 3": "Craig Dawson", "Home Player 2": "Oliver Burke", "Away Player 10": "Danny Simpson", "Away Player 11": "Jamie Vardy", "Away Player 8": "Shinji Okazaki", "Away Player 9": "Kasper Schmeichel", "Away Player 1": "Benjamin Chilwell", "Away Player 2": "Demarai Gray", "Away Player 3": "Vicente Iborra", "Away Player 4": "Harry Maguire", "Away Player 5": "Riyad Mahrez", "Away Player 6": "Wes Morgan", "Away Player 7": "Wilfred Ndidi", "Game ID": "g_1_vaRmkWzl", "Home Player 11": "Salomon Rondon", "Home Player 10": "Matt Phillips"}}