{"Stats": {"Full Time Result": "H", "Away Team Corners": 2, "Referee": "L Mason", "Home Team Fouls Committed": 9, "Away Team Shots": 4, "Away Team Red Cards": 0, "Home Team Red Cards": 0, "Half Time Away Team Goals": 1, "Full Time Home Team Goals": 2, "Away Team Yellow Cards": 0, "Away Team Shots on Target": 2, "Half Time Home Team Goals": 0, "Half Time Result": "A", "Away Team Fouls Committed": 9, "Home Team Yellow Cards": 0, "Home Team Shots": 17, "Div": "E0", "Home Team Corners": 5, "Home Team Shots on Target": 5, "Full Time Away Team Goals": 1}, "Description": "Alexis Sánchez (Arsenal) wins a free kick in the attacking half. at minute 1. Foul by Leroy Fer (Swansea City). at minute 1. Attempt blocked. Aaron Ramsey (Arsenal) right footed shot from the centre of the box is blocked. Assisted by Alexis Sánchez. at minute 5. Alexis Sánchez (Arsenal) wins a free kick on the left wing. at minute 7. Foul by Ki Sung-yueng (Swansea City). at minute 7. Attempt saved. Per Mertesacker (Arsenal) header from the centre of the box is saved in the centre of the goal. Assisted by Alexis Sánchez with a cross. at minute 8. Foul by Nacho Monreal (Arsenal). at minute 11. Jordan Ayew (Swansea City) wins a free kick in the defensive half. at minute 11. Attempt missed. Alexis Sánchez (Arsenal) right footed shot from long range on the left is close, but misses to the left. Assisted by Nacho Monreal. at minute 18. Attempt blocked. Héctor Bellerín (Arsenal) right footed shot from outside the box is blocked. Assisted by Nacho Monreal. at minute 19. Foul by Tammy Abraham (Swansea City). at minute 20. Nacho Monreal (Arsenal) wins a free kick on the left wing. at minute 20. Attempt blocked. Nacho Monreal (Arsenal) left footed shot from outside the box is blocked. Assisted by Mesut Özil. at minute 21. Goal!  Arsenal 0, Swansea City 1. Sam Clucas (Swansea City) left footed shot from the left side of the box to the centre of the goal. Assisted by Tammy Abraham with a through ball. at minute 22. Corner,  Arsenal. Conceded by Federico Fernández. at minute 23. Foul by Per Mertesacker (Arsenal). at minute 25. Tammy Abraham (Swansea City) wins a free kick in the defensive half. at minute 25. Attempt missed. Sead Kolasinac (Arsenal) left footed shot from the left side of the box misses to the right. Assisted by Mesut Özil. at minute 27. Aaron Ramsey (Arsenal) wins a free kick on the right wing. at minute 32. Foul by Tom Carroll (Swansea City). at minute 32. Foul by Sead Kolasinac (Arsenal). at minute 33. Leroy Fer (Swansea City) wins a free kick in the defensive half. at minute 33. Corner,  Arsenal. Conceded by Alfie Mawson. at minute 37. Foul by Granit Xhaka (Arsenal). at minute 38. Jordan Ayew (Swansea City) wins a free kick in the defensive half. at minute 38. Foul by Nacho Monreal (Arsenal). at minute 40. Jordan Ayew (Swansea City) wins a free kick in the defensive half. at minute 40. Attempt missed. Sam Clucas (Swansea City) left footed shot from outside the box is close, but misses to the left. Assisted by Jordan Ayew. at minute 40. Attempt saved. Alexis Sánchez (Arsenal) right footed shot from the left side of the box is saved in the top centre of the goal. Assisted by Sead Kolasinac. at minute 41. Corner,  Arsenal. Conceded by Lukasz Fabianski. at minute 41. Corner,  Arsenal. Conceded by Federico Fernández. at minute 42. Corner,  Arsenal. Conceded by Leroy Fer. at minute 44. Attempt saved. Jordan Ayew (Swansea City) right footed shot from the centre of the box is saved in the centre of the goal. at minute 45. Corner,  Swansea City. Conceded by Petr Cech. at minute 45. First Half ends, Arsenal 0, Swansea City 1. at minute 47. Second Half begins Arsenal 0, Swansea City 1. at minute 45. Foul by Granit Xhaka (Arsenal). at minute 47. Tammy Abraham (Swansea City) wins a free kick in the defensive half. at minute 47. Foul by Jordan Ayew (Swansea City). at minute 50. Per Mertesacker (Arsenal) wins a free kick in the defensive half. at minute 50. Attempt blocked. Mesut Özil (Arsenal) right footed shot from the centre of the box is blocked. Assisted by Alexandre Lacazette. at minute 51. Goal!  Arsenal 1, Swansea City 1. Sead Kolasinac (Arsenal) left footed shot from the left side of the box to the bottom right corner. Assisted by Mesut Özil. at minute 51. Offside, Swansea City. Sam Clucas tries a through ball, but Tammy Abraham is caught offside. at minute 52. Aaron Ramsey (Arsenal) wins a free kick in the attacking half. at minute 54. Foul by Mike van der Hoorn (Swansea City). at minute 54. Attempt missed. Laurent Koscielny (Arsenal) header from the centre of the box is close, but misses to the right. Assisted by Alexis Sánchez following a set piece situation. at minute 55. Goal!  Arsenal 2, Swansea City 1. Aaron Ramsey (Arsenal) left footed shot from the centre of the box to the bottom left corner. Assisted by Sead Kolasinac. at minute 58. Attempt missed. Aaron Ramsey (Arsenal) left footed shot from the centre of the box is high and wide to the left. Assisted by Mesut Özil. at minute 60. Attempt saved. Alexandre Lacazette (Arsenal) left footed shot from the centre of the box is saved in the bottom right corner. Assisted by Héctor Bellerín. at minute 64. Corner,  Swansea City. Conceded by Per Mertesacker. at minute 65. Héctor Bellerín (Arsenal) hits the bar with a right footed shot from the right side of the six yard box. Assisted by Aaron Ramsey following a fast break. at minute 66. Foul by Alexandre Lacazette (Arsenal). at minute 66. Mike van der Hoorn (Swansea City) wins a free kick in the defensive half. at minute 66. Attempt missed. Alexis Sánchez (Arsenal) right footed shot from outside the box is high and wide to the right. Assisted by Aaron Ramsey. at minute 72. Foul by Aaron Ramsey (Arsenal). at minute 77. Tom Carroll (Swansea City) wins a free kick in the attacking half. at minute 77. Attempt missed. Tammy Abraham (Swansea City) right footed shot from the centre of the box is close, but misses to the left following a set piece situation. at minute 77. Offside, Arsenal. Aaron Ramsey tries a through ball, but Alexandre Lacazette is caught offside. at minute 78. Substitution, Arsenal. Rob Holding replaces Sead Kolasinac because of an injury. at minute 78. Foul by Granit Xhaka (Arsenal). at minute 79. Leroy Fer (Swansea City) wins a free kick in the attacking half. at minute 79. Substitution, Arsenal. Olivier Giroud replaces Alexandre Lacazette. at minute 81. Substitution, Swansea City. Luciano Narsingh replaces Jordan Ayew. at minute 81. Substitution, Swansea City. Nathan Dyer replaces Mike van der Hoorn. at minute 82. Foul by Leroy Fer (Swansea City). at minute 83. Granit Xhaka (Arsenal) wins a free kick in the defensive half. at minute 83. Substitution, Swansea City. Oliver McBurnie replaces Tom Carroll. at minute 84. Alexis Sánchez (Arsenal) wins a free kick in the attacking half. at minute 85. Foul by Federico Fernández (Swansea City). at minute 85. Attempt missed. Olivier Giroud (Arsenal) left footed shot from the left side of the six yard box is close, but misses to the left. Assisted by Nacho Monreal with a cross. at minute 86. Attempt missed. Olivier Giroud (Arsenal) left footed shot from outside the box is close, but misses to the left. Assisted by Mesut Özil. at minute 89. Offside, Arsenal. Mesut Özil tries a through ball, but Alexis Sánchez is caught offside. at minute 92. Foul by Alfie Mawson (Swansea City). at minute 93. Granit Xhaka (Arsenal) wins a free kick in the defensive half. at minute 93. Second Half ends, Arsenal 2, Swansea City 1. at minute 94. Match ends, Arsenal 2, Swansea City 1. at minute 94. ", "Home Team": "Arsenal", "Away Team": "Swansea City", "Date": "2017-10-28", "Commentary": [["480813", "First Half begins.", "-", "Arsenal", "0", "0", "0", "1", "0", "0", "NA", "NA", "NA", "NA", "NA", "NA", "NA", "0", "NA", "NA", "0", "NA", "0", "0", "NA", "NA", "NA", "0", "NA", "NA", "NA", "0", "NA", "NA", "0", "NA", "0", "NA", "NA", "NA", "0", "NA", "NA", "0", "0", "NA", "NA", "NA", "0", "NA", "NA", "NA", "NA", "1", "1", "0", "NA", "NA", "NA"], ["480813", "Lineups are announced and players are warming up.", "-", "Arsenal", "0", "0", "0", "0", "0", "0", "NA", "NA", "NA", "NA", "NA", "NA", "NA", "0", "NA", "NA", "0", "NA", "0", "0", "NA", "NA", "NA", "0", "NA", "NA", "NA", "0", "NA", "NA", "0", "NA", "0", "NA", "NA", "NA", "0", "NA", "NA", "0", "0", "NA", "NA", "NA", "0", "NA", "NA", "NA", "NA", "1", "2", "0", "NA", "NA", "NA"], ["480813", "Alexis Sánchez (Arsenal) wins a free kick in the attacking half.", "1'", "Arsenal", "0", "0", "0", "0", "0", "0", "NA", "NA", "NA", "NA", "NA", "NA", "NA", "0", "NA", "NA", "0", "NA", "0", "0", "NA", "NA", "NA", "0", "NA", "NA", "NA", "0", "NA", "NA", "0", "NA", "1", "Alexis Sánchez", "Arsenal", "attacking half", "0", "NA", "NA", "0", "0", "NA", "NA", "NA", "0", "NA", "NA", "NA", "NA", "1", "3", "0", "NA", "NA", "1"], ["480813", "Foul by Leroy Fer (Swansea City).", "1'", "Arsenal", "0", "0", "0", "0", "0", "0", "NA", "NA", "NA", "NA", "NA", "NA", "NA", "1", "Leroy Fer", "Swansea City", "0", "NA", "0", "0", "NA", "NA", "NA", "0", "NA", "NA", "NA", "0", "NA", "NA", "0", "NA", "0", "NA", "NA", "NA", "0", "NA", "NA", "0", "0", "NA", "NA", "NA", "0", "NA", "NA", "NA", "NA", "1", "4", "0", "NA", "NA", "1"], ["480813", "Attempt blocked. Aaron Ramsey (Arsenal) right footed shot from the centre of the box is blocked. Assisted by Alexis Sánchez.", "5'", "Arsenal", "0", "0", "0", "0", "1", "0", "blocked", "Aaron Ramsey", "Arsenal", "right", "the centre of the box", "NA", "Alexis Sánchez", "0", "NA", "NA", "0", "NA", "0", "0", "NA", "NA", "NA", "0", "NA", "NA", "NA", "0", "NA", "NA", "0", "NA", "0", "NA", "NA", "NA", "0", "NA", "NA", "0", "0", "NA", "NA", "NA", "0", "NA", "NA", "NA", "NA", "1", "5", "0", "NA", "NA", "5"], ["480813", "Alexis Sánchez (Arsenal) wins a free kick on the left wing.", "7'", "Arsenal", "0", "0", "0", "0", "0", "0", "NA", "NA", "NA", "NA", "NA", "NA", "NA", "0", "NA", "NA", "0", "NA", "0", "0", "NA", "NA", "NA", "0", "NA", "NA", "NA", "0", "NA", "NA", "0", "NA", "1", "Alexis Sánchez", "Arsenal", "NA", "0", "NA", "NA", "0", "0", "NA", "NA", "NA", "0", "NA", "NA", "NA", "NA", "1", "6", "0", "NA", "NA", "7"], ["480813", "Foul by Ki Sung-yueng (Swansea City).", "7'", "Arsenal", "0", "0", "0", "0", "0", "0", "NA", "NA", "NA", "NA", "NA", "NA", "NA", "1", "Ki Sung-yueng", "Swansea City", "0", "NA", "0", "0", "NA", "NA", "NA", "0", "NA", "NA", "NA", "0", "NA", "NA", "0", "NA", "0", "NA", "NA", "NA", "0", "NA", "NA", "0", "0", "NA", "NA", "NA", "0", "NA", "NA", "NA", "NA", "1", "7", "0", "NA", "NA", "7"], ["480813", "Attempt saved. Per Mertesacker (Arsenal) header from the centre of the box is saved in the centre of the goal. Assisted by Alexis Sánchez with a cross.", "8'", "Arsenal", "0", "0", "0", "0", "1", "0", "saved", "Per Mertesacker", "Arsenal", "header", "the centre of the box", "the centre of the goal", "Alexis Sánchez", "0", "NA", "NA", "0", "cross", "0", "0", "NA", "NA", "NA", "0", "NA", "NA", "NA", "0", "NA", "NA", "0", "NA", "0", "NA", "NA", "NA", "0", "NA", "NA", "0", "0", "NA", "NA", "NA", "0", "NA", "NA", "NA", "NA", "1", "8", "0", "NA", "NA", "8"], ["480813", "Foul by Nacho Monreal (Arsenal).", "11'", "Arsenal", "0", "0", "0", "0", "0", "0", "NA", "NA", "NA", "NA", "NA", "NA", "NA", "1", "Nacho Monreal", "Arsenal", "0", "NA", "0", "0", "NA", "NA", "NA", "0", "NA", "NA", "NA", "0", "NA", "NA", "0", "NA", "0", "NA", "NA", "NA", "0", "NA", "NA", "0", "0", "NA", "NA", "NA", "0", "NA", "NA", "NA", "NA", "1", "9", "0", "NA", "NA", "11"], ["480813", "Jordan Ayew (Swansea City) wins a free kick in the defensive half.", "11'", "Arsenal", "0", "0", "0", "0", "0", "0", "NA", "NA", "NA", "NA", "NA", "NA", "NA", "0", "NA", "NA", "0", "NA", "0", "0", "NA", "NA", "NA", "0", "NA", "NA", "NA", "0", "NA", "NA", "0", "NA", "1", "Jordan Ayew", "Swansea City", "defensive half", "0", "NA", "NA", "0", "0", "NA", "NA", "NA", "0", "NA", "NA", "NA", "NA", "1", "10", "0", "NA", "NA", "11"], ["480813", "Attempt missed. Alexis Sánchez (Arsenal) right footed shot from long range on the left is close, but misses to the left. Assisted by Nacho Monreal.", "18'", "Arsenal", "0", "0", "0", "0", "1", "0", "missed", "Alexis Sánchez", "Arsenal", "right", "right shot long range", "NA", "Nacho Monreal", "0", "NA", "NA", "0", "NA", "0", "0", "NA", "NA", "NA", "0", "NA", "NA", "NA", "0", "NA", "NA", "0", "NA", "0", "NA", "NA", "NA", "0", "NA", "NA", "0", "0", "NA", "NA", "NA", "0", "NA", "NA", "NA", "NA", "1", "11", "0", "NA", "NA", "18"], ["480813", "Attempt blocked. Héctor Bellerín (Arsenal) right footed shot from outside the box is blocked. Assisted by Nacho Monreal.", "19'", "Arsenal", "0", "0", "0", "0", "1", "0", "blocked", "Héctor Bellerín", "Arsenal", "right", "outside the box", "NA", "Nacho Monreal", "0", "NA", "NA", "0", "NA", "0", "0", "NA", "NA", "NA", "0", "NA", "NA", "NA", "0", "NA", "NA", "0", "NA", "0", "NA", "NA", "NA", "0", "NA", "NA", "0", "0", "NA", "NA", "NA", "0", "NA", "NA", "NA", "NA", "1", "12", "0", "NA", "NA", "19"], ["480813", "Foul by Tammy Abraham (Swansea City).", "20'", "Arsenal", "0", "0", "0", "0", "0", "0", "NA", "NA", "NA", "NA", "NA", "NA", "NA", "1", "Tammy Abraham", "Swansea City", "0", "NA", "0", "0", "NA", "NA", "NA", "0", "NA", "NA", "NA", "0", "NA", "NA", "0", "NA", "0", "NA", "NA", "NA", "0", "NA", "NA", "0", "0", "NA", "NA", "NA", "0", "NA", "NA", "NA", "NA", "1", "13", "0", "NA", "NA", "20"], ["480813", "Nacho Monreal (Arsenal) wins a free kick on the left wing.", "20'", "Arsenal", "0", "0", "0", "0", "0", "0", "NA", "NA", "NA", "NA", "NA", "NA", "NA", "0", "NA", "NA", "0", "NA", "0", "0", "NA", "NA", "NA", "0", "NA", "NA", "NA", "0", "NA", "NA", "0", "NA", "1", "Nacho Monreal", "Arsenal", "NA", "0", "NA", "NA", "0", "0", "NA", "NA", "NA", "0", "NA", "NA", "NA", "NA", "1", "14", "0", "NA", "NA", "20"], ["480813", "Attempt blocked. Nacho Monreal (Arsenal) left footed shot from outside the box is blocked. Assisted by Mesut Özil.", "21'", "Arsenal", "0", "0", "0", "0", "1", "0", "blocked", "Nacho Monreal", "Arsenal", "left", "outside the box", "NA", "Mesut Özil", "0", "NA", "NA", "0", "NA", "0", "0", "NA", "NA", "NA", "0", "NA", "NA", "NA", "0", "NA", "NA", "0", "NA", "0", "NA", "NA", "NA", "0", "NA", "NA", "0", "0", "NA", "NA", "NA", "0", "NA", "NA", "NA", "NA", "1", "15", "0", "NA", "NA", "21"], ["480813", "Goal!  Arsenal 0, Swansea City 1. Sam Clucas (Swansea City) left footed shot from the left side of the box to the centre of the goal. Assisted by Tammy Abraham with a through ball.", "22'", "Arsenal", "0", "0", "0", "0", "1", "0", "goal", "Sam Clucas", "Swansea City", "left", "the left side of the box", "centre of the goal", "Tammy Abraham", "0", "NA", "NA", "0", "through", "0", "0", "NA", "NA", "NA", "0", "NA", "NA", "NA", "0", "NA", "NA", "0", "NA", "0", "NA", "NA", "NA", "0", "NA", "NA", "0", "0", "NA", "NA", "NA", "0", "NA", "NA", "NA", "NA", "1", "16", "0", "NA", "NA", "22"], ["480813", "Corner,  Arsenal. Conceded by Federico Fernández.", "23'", "Arsenal", "0", "0", "0", "0", "0", "0", "NA", "NA", "NA", "NA", "NA", "NA", "NA", "0", "NA", "NA", "0", "NA", "0", "0", "NA", "NA", "NA", "0", "NA", "NA", "NA", "0", "NA", "NA", "0", "NA", "0", "NA", "NA", "NA", "1", "Arsenal", "Federico Fernández", "0", "0", "NA", "NA", "NA", "0", "NA", "NA", "NA", "NA", "1", "17", "0", "NA", "NA", "23"], ["480813", "Foul by Per Mertesacker (Arsenal).", "25'", "Arsenal", "0", "0", "0", "0", "0", "0", "NA", "NA", "NA", "NA", "NA", "NA", "NA", "1", "Per Mertesacker", "Arsenal", "0", "NA", "0", "0", "NA", "NA", "NA", "0", "NA", "NA", "NA", "0", "NA", "NA", "0", "NA", "0", "NA", "NA", "NA", "0", "NA", "NA", "0", "0", "NA", "NA", "NA", "0", "NA", "NA", "NA", "NA", "1", "18", "0", "NA", "NA", "25"], ["480813", "Tammy Abraham (Swansea City) wins a free kick in the defensive half.", "25'", "Arsenal", "0", "0", "0", "0", "0", "0", "NA", "NA", "NA", "NA", "NA", "NA", "NA", "0", "NA", "NA", "0", "NA", "0", "0", "NA", "NA", "NA", "0", "NA", "NA", "NA", "0", "NA", "NA", "0", "NA", "1", "Tammy Abraham", "Swansea City", "defensive half", "0", "NA", "NA", "0", "0", "NA", "NA", "NA", "0", "NA", "NA", "NA", "NA", "1", "19", "0", "NA", "NA", "25"], ["480813", "Attempt missed. Sead Kolasinac (Arsenal) left footed shot from the left side of the box misses to the right. Assisted by Mesut Özil.", "27'", "Arsenal", "0", "0", "0", "0", "1", "0", "missed", "Sead Kolasinac", "Arsenal", "left", "the left side of the box", "right", "Mesut Özil", "0", "NA", "NA", "0", "NA", "0", "0", "NA", "NA", "NA", "0", "NA", "NA", "NA", "0", "NA", "NA", "0", "NA", "0", "NA", "NA", "NA", "0", "NA", "NA", "0", "0", "NA", "NA", "NA", "0", "NA", "NA", "NA", "NA", "1", "20", "0", "NA", "NA", "27"], ["480813", "Aaron Ramsey (Arsenal) wins a free kick on the right wing.", "32'", "Arsenal", "0", "0", "0", "0", "0", "0", "NA", "NA", "NA", "NA", "NA", "NA", "NA", "0", "NA", "NA", "0", "NA", "0", "0", "NA", "NA", "NA", "0", "NA", "NA", "NA", "0", "NA", "NA", "0", "NA", "1", "Aaron Ramsey", "Arsenal", "NA", "0", "NA", "NA", "0", "0", "NA", "NA", "NA", "0", "NA", "NA", "NA", "NA", "1", "21", "0", "NA", "NA", "32"], ["480813", "Foul by Tom Carroll (Swansea City).", "32'", "Arsenal", "0", "0", "0", "0", "0", "0", "NA", "NA", "NA", "NA", "NA", "NA", "NA", "1", "Tom Carroll", "Swansea City", "0", "NA", "0", "0", "NA", "NA", "NA", "0", "NA", "NA", "NA", "0", "NA", "NA", "0", "NA", "0", "NA", "NA", "NA", "0", "NA", "NA", "0", "0", "NA", "NA", "NA", "0", "NA", "NA", "NA", "NA", "1", "22", "0", "NA", "NA", "32"], ["480813", "Foul by Sead Kolasinac (Arsenal).", "33'", "Arsenal", "0", "0", "0", "0", "0", "0", "NA", "NA", "NA", "NA", "NA", "NA", "NA", "1", "Sead Kolasinac", "Arsenal", "0", "NA", "0", "0", "NA", "NA", "NA", "0", "NA", "NA", "NA", "0", "NA", "NA", "0", "NA", "0", "NA", "NA", "NA", "0", "NA", "NA", "0", "0", "NA", "NA", "NA", "0", "NA", "NA", "NA", "NA", "1", "23", "0", "NA", "NA", "33"], ["480813", "Leroy Fer (Swansea City) wins a free kick in the defensive half.", "33'", "Arsenal", "0", "0", "0", "0", "0", "0", "NA", "NA", "NA", "NA", "NA", "NA", "NA", "0", "NA", "NA", "0", "NA", "0", "0", "NA", "NA", "NA", "0", "NA", "NA", "NA", "0", "NA", "NA", "0", "NA", "1", "Leroy Fer", "Swansea City", "defensive half", "0", "NA", "NA", "0", "0", "NA", "NA", "NA", "0", "NA", "NA", "NA", "NA", "1", "24", "0", "NA", "NA", "33"], ["480813", "Corner,  Arsenal. Conceded by Alfie Mawson.", "37'", "Arsenal", "0", "0", "0", "0", "0", "0", "NA", "NA", "NA", "NA", "NA", "NA", "NA", "0", "NA", "NA", "0", "NA", "0", "0", "NA", "NA", "NA", "0", "NA", "NA", "NA", "0", "NA", "NA", "0", "NA", "0", "NA", "NA", "NA", "1", "Arsenal", "Alfie Mawson", "0", "0", "NA", "NA", "NA", "0", "NA", "NA", "NA", "NA", "1", "25", "0", "NA", "NA", "37"], ["480813", "Foul by Granit Xhaka (Arsenal).", "38'", "Arsenal", "0", "0", "0", "0", "0", "0", "NA", "NA", "NA", "NA", "NA", "NA", "NA", "1", "Granit Xhaka", "Arsenal", "0", "NA", "0", "0", "NA", "NA", "NA", "0", "NA", "NA", "NA", "0", "NA", "NA", "0", "NA", "0", "NA", "NA", "NA", "0", "NA", "NA", "0", "0", "NA", "NA", "NA", "0", "NA", "NA", "NA", "NA", "1", "26", "0", "NA", "NA", "38"], ["480813", "Jordan Ayew (Swansea City) wins a free kick in the defensive half.", "38'", "Arsenal", "0", "0", "0", "0", "0", "0", "NA", "NA", "NA", "NA", "NA", "NA", "NA", "0", "NA", "NA", "0", "NA", "0", "0", "NA", "NA", "NA", "0", "NA", "NA", "NA", "0", "NA", "NA", "0", "NA", "1", "Jordan Ayew", "Swansea City", "defensive half", "0", "NA", "NA", "0", "0", "NA", "NA", "NA", "0", "NA", "NA", "NA", "NA", "1", "27", "0", "NA", "NA", "38"], ["480813", "Foul by Nacho Monreal (Arsenal).", "40'", "Arsenal", "0", "0", "0", "0", "0", "0", "NA", "NA", "NA", "NA", "NA", "NA", "NA", "1", "Nacho Monreal", "Arsenal", "0", "NA", "0", "0", "NA", "NA", "NA", "0", "NA", "NA", "NA", "0", "NA", "NA", "0", "NA", "0", "NA", "NA", "NA", "0", "NA", "NA", "0", "0", "NA", "NA", "NA", "0", "NA", "NA", "NA", "NA", "1", "28", "0", "NA", "NA", "40"], ["480813", "Jordan Ayew (Swansea City) wins a free kick in the defensive half.", "40'", "Arsenal", "0", "0", "0", "0", "0", "0", "NA", "NA", "NA", "NA", "NA", "NA", "NA", "0", "NA", "NA", "0", "NA", "0", "0", "NA", "NA", "NA", "0", "NA", "NA", "NA", "0", "NA", "NA", "0", "NA", "1", "Jordan Ayew", "Swansea City", "defensive half", "0", "NA", "NA", "0", "0", "NA", "NA", "NA", "0", "NA", "NA", "NA", "NA", "1", "29", "0", "NA", "NA", "40"], ["480813", "Attempt missed. Sam Clucas (Swansea City) left footed shot from outside the box is close, but misses to the left. Assisted by Jordan Ayew.", "40'", "Arsenal", "0", "0", "0", "0", "1", "0", "missed", "Sam Clucas", "Swansea City", "left", "outside the box", "close, but left", "Jordan Ayew", "0", "NA", "NA", "0", "NA", "0", "0", "NA", "NA", "NA", "0", "NA", "NA", "NA", "0", "NA", "NA", "0", "NA", "0", "NA", "NA", "NA", "0", "NA", "NA", "0", "0", "NA", "NA", "NA", "0", "NA", "NA", "NA", "NA", "1", "30", "0", "NA", "NA", "40"], ["480813", "Attempt saved. Alexis Sánchez (Arsenal) right footed shot from the left side of the box is saved in the top centre of the goal. Assisted by Sead Kolasinac.", "41'", "Arsenal", "0", "0", "0", "0", "1", "0", "saved", "Alexis Sánchez", "Arsenal", "right", "the left side of the box", "the top centre of the goal", "Sead Kolasinac", "0", "NA", "NA", "0", "NA", "0", "0", "NA", "NA", "NA", "0", "NA", "NA", "NA", "0", "NA", "NA", "0", "NA", "0", "NA", "NA", "NA", "0", "NA", "NA", "0", "0", "NA", "NA", "NA", "0", "NA", "NA", "NA", "NA", "1", "31", "0", "NA", "NA", "41"], ["480813", "Corner,  Arsenal. Conceded by Lukasz Fabianski.", "41'", "Arsenal", "0", "0", "0", "0", "0", "0", "NA", "NA", "NA", "NA", "NA", "NA", "NA", "0", "NA", "NA", "0", "NA", "0", "0", "NA", "NA", "NA", "0", "NA", "NA", "NA", "0", "NA", "NA", "0", "NA", "0", "NA", "NA", "NA", "1", "Arsenal", "Lukasz Fabianski", "0", "0", "NA", "NA", "NA", "0", "NA", "NA", "NA", "NA", "1", "32", "0", "NA", "NA", "41"], ["480813", "Corner,  Arsenal. Conceded by Federico Fernández.", "42'", "Arsenal", "0", "0", "0", "0", "0", "0", "NA", "NA", "NA", "NA", "NA", "NA", "NA", "0", "NA", "NA", "0", "NA", "0", "0", "NA", "NA", "NA", "0", "NA", "NA", "NA", "0", "NA", "NA", "0", "NA", "0", "NA", "NA", "NA", "1", "Arsenal", "Federico Fernández", "0", "0", "NA", "NA", "NA", "0", "NA", "NA", "NA", "NA", "1", "33", "0", "NA", "NA", "42"], ["480813", "Corner,  Arsenal. Conceded by Leroy Fer.", "44'", "Arsenal", "0", "0", "0", "0", "0", "0", "NA", "NA", "NA", "NA", "NA", "NA", "NA", "0", "NA", "NA", "0", "NA", "0", "0", "NA", "NA", "NA", "0", "NA", "NA", "NA", "0", "NA", "NA", "0", "NA", "0", "NA", "NA", "NA", "1", "Arsenal", "Leroy Fer", "0", "0", "NA", "NA", "NA", "0", "NA", "NA", "NA", "NA", "1", "34", "0", "NA", "NA", "44"], ["480813", "Attempt saved. Jordan Ayew (Swansea City) right footed shot from the centre of the box is saved in the centre of the goal.", "45'", "Arsenal", "0", "0", "0", "0", "1", "0", "saved", "Jordan Ayew", "Swansea City", "right", "the centre of the box", "the centre of the goal", "NA", "0", "NA", "NA", "0", "NA", "0", "0", "NA", "NA", "NA", "0", "NA", "NA", "NA", "0", "NA", "NA", "0", "NA", "0", "NA", "NA", "NA", "0", "NA", "NA", "0", "0", "NA", "NA", "NA", "0", "NA", "NA", "NA", "NA", "1", "35", "0", "NA", "NA", "45"], ["480813", "Corner,  Swansea City. Conceded by Petr Cech.", "45'", "Arsenal", "0", "0", "0", "0", "0", "0", "NA", "NA", "NA", "NA", "NA", "NA", "NA", "0", "NA", "NA", "0", "NA", "0", "0", "NA", "NA", "NA", "0", "NA", "NA", "NA", "0", "NA", "NA", "0", "NA", "0", "NA", "NA", "NA", "1", "Swansea City", "Petr Cech", "0", "0", "NA", "NA", "NA", "0", "NA", "NA", "NA", "NA", "1", "36", "0", "NA", "NA", "45"], ["480813", "First Half ends, Arsenal 0, Swansea City 1.", "45'+2'", "Arsenal", "0", "1", "0", "0", "0", "0", "NA", "NA", "NA", "NA", "NA", "NA", "NA", "0", "NA", "NA", "0", "NA", "0", "0", "NA", "NA", "NA", "0", "NA", "NA", "NA", "0", "NA", "NA", "0", "NA", "0", "NA", "NA", "NA", "0", "NA", "NA", "0", "0", "NA", "NA", "NA", "0", "NA", "NA", "NA", "NA", "1", "37", "1", "NA", "NA", "47"], ["480813", "Second Half begins Arsenal 0, Swansea City 1.", "45'", "Arsenal", "0", "0", "0", "1", "0", "0", "NA", "NA", "NA", "NA", "NA", "NA", "NA", "0", "NA", "NA", "0", "NA", "0", "0", "NA", "NA", "NA", "0", "NA", "NA", "NA", "0", "NA", "NA", "0", "NA", "0", "NA", "NA", "NA", "0", "NA", "NA", "0", "0", "NA", "NA", "NA", "0", "NA", "NA", "NA", "NA", "2", "38", "0", "NA", "NA", "45"], ["480813", "Foul by Granit Xhaka (Arsenal).", "47'", "Arsenal", "0", "0", "0", "0", "0", "0", "NA", "NA", "NA", "NA", "NA", "NA", "NA", "1", "Granit Xhaka", "Arsenal", "0", "NA", "0", "0", "NA", "NA", "NA", "0", "NA", "NA", "NA", "0", "NA", "NA", "0", "NA", "0", "NA", "NA", "NA", "0", "NA", "NA", "0", "0", "NA", "NA", "NA", "0", "NA", "NA", "NA", "NA", "2", "39", "0", "NA", "NA", "47"], ["480813", "Tammy Abraham (Swansea City) wins a free kick in the defensive half.", "47'", "Arsenal", "0", "0", "0", "0", "0", "0", "NA", "NA", "NA", "NA", "NA", "NA", "NA", "0", "NA", "NA", "0", "NA", "0", "0", "NA", "NA", "NA", "0", "NA", "NA", "NA", "0", "NA", "NA", "0", "NA", "1", "Tammy Abraham", "Swansea City", "defensive half", "0", "NA", "NA", "0", "0", "NA", "NA", "NA", "0", "NA", "NA", "NA", "NA", "2", "40", "0", "NA", "NA", "47"], ["480813", "Foul by Jordan Ayew (Swansea City).", "50'", "Arsenal", "0", "0", "0", "0", "0", "0", "NA", "NA", "NA", "NA", "NA", "NA", "NA", "1", "Jordan Ayew", "Swansea City", "0", "NA", "0", "0", "NA", "NA", "NA", "0", "NA", "NA", "NA", "0", "NA", "NA", "0", "NA", "0", "NA", "NA", "NA", "0", "NA", "NA", "0", "0", "NA", "NA", "NA", "0", "NA", "NA", "NA", "NA", "2", "41", "0", "NA", "NA", "50"], ["480813", "Per Mertesacker (Arsenal) wins a free kick in the defensive half.", "50'", "Arsenal", "0", "0", "0", "0", "0", "0", "NA", "NA", "NA", "NA", "NA", "NA", "NA", "0", "NA", "NA", "0", "NA", "0", "0", "NA", "NA", "NA", "0", "NA", "NA", "NA", "0", "NA", "NA", "0", "NA", "1", "Per Mertesacker", "Arsenal", "defensive half", "0", "NA", "NA", "0", "0", "NA", "NA", "NA", "0", "NA", "NA", "NA", "NA", "2", "42", "0", "NA", "NA", "50"], ["480813", "Attempt blocked. Mesut Özil (Arsenal) right footed shot from the centre of the box is blocked. Assisted by Alexandre Lacazette.", "51'", "Arsenal", "0", "0", "0", "0", "1", "0", "blocked", "Mesut Özil", "Arsenal", "right", "the centre of the box", "NA", "Alexandre Lacazette", "0", "NA", "NA", "0", "NA", "0", "0", "NA", "NA", "NA", "0", "NA", "NA", "NA", "0", "NA", "NA", "0", "NA", "0", "NA", "NA", "NA", "0", "NA", "NA", "0", "0", "NA", "NA", "NA", "0", "NA", "NA", "NA", "NA", "2", "43", "0", "NA", "NA", "51"], ["480813", "Goal!  Arsenal 1, Swansea City 1. Sead Kolasinac (Arsenal) left footed shot from the left side of the box to the bottom right corner. Assisted by Mesut Özil.", "51'", "Arsenal", "1", "0", "0", "0", "1", "0", "goal", "Sead Kolasinac", "Arsenal", "left", "the left side of the box", "bottom right corner", "Mesut Özil", "0", "NA", "NA", "0", "NA", "0", "0", "NA", "NA", "NA", "0", "NA", "NA", "NA", "0", "NA", "NA", "0", "NA", "0", "NA", "NA", "NA", "0", "NA", "NA", "0", "0", "NA", "NA", "NA", "0", "NA", "NA", "NA", "NA", "2", "44", "0", "NA", "NA", "51"], ["480813", "Offside, Swansea City. Sam Clucas tries a through ball, but Tammy Abraham is caught offside.", "52'", "Arsenal", "1", "0", "0", "0", "0", "0", "NA", "NA", "NA", "NA", "NA", "NA", "NA", "0", "NA", "NA", "0", "NA", "0", "1", "Swansea City", "Tammy Abraham", "Sam Clucas", "0", "NA", "NA", "NA", "0", "NA", "NA", "0", "NA", "0", "NA", "NA", "NA", "0", "NA", "NA", "0", "0", "NA", "NA", "NA", "0", "NA", "NA", "NA", "NA", "2", "45", "0", "NA", "NA", "52"], ["480813", "Aaron Ramsey (Arsenal) wins a free kick in the attacking half.", "54'", "Arsenal", "1", "0", "0", "0", "0", "0", "NA", "NA", "NA", "NA", "NA", "NA", "NA", "0", "NA", "NA", "0", "NA", "0", "0", "NA", "NA", "NA", "0", "NA", "NA", "NA", "0", "NA", "NA", "0", "NA", "1", "Aaron Ramsey", "Arsenal", "attacking half", "0", "NA", "NA", "0", "0", "NA", "NA", "NA", "0", "NA", "NA", "NA", "NA", "2", "46", "0", "NA", "NA", "54"], ["480813", "Foul by Mike van der Hoorn (Swansea City).", "54'", "Arsenal", "1", "0", "0", "0", "0", "0", "NA", "NA", "NA", "NA", "NA", "NA", "NA", "1", "van der Hoorn", "Swansea City", "0", "NA", "0", "0", "NA", "NA", "NA", "0", "NA", "NA", "NA", "0", "NA", "NA", "0", "NA", "0", "NA", "NA", "NA", "0", "NA", "NA", "0", "0", "NA", "NA", "NA", "0", "NA", "NA", "NA", "NA", "2", "47", "0", "NA", "NA", "54"], ["480813", "Attempt missed. Laurent Koscielny (Arsenal) header from the centre of the box is close, but misses to the right. Assisted by Alexis Sánchez following a set piece situation.", "55'", "Arsenal", "1", "0", "0", "0", "1", "0", "missed", "Laurent Koscielny", "Arsenal", "header", "the centre of the box", "close, but right", "Alexis Sánchez", "0", "NA", "NA", "1", "NA", "0", "0", "NA", "NA", "NA", "0", "NA", "NA", "NA", "0", "NA", "NA", "0", "NA", "0", "NA", "NA", "NA", "0", "NA", "NA", "0", "0", "NA", "NA", "NA", "0", "NA", "NA", "NA", "NA", "2", "48", "0", "NA", "NA", "55"], ["480813", "Goal!  Arsenal 2, Swansea City 1. Aaron Ramsey (Arsenal) left footed shot from the centre of the box to the bottom left corner. Assisted by Sead Kolasinac.", "58'", "Arsenal", "2", "0", "0", "0", "1", "0", "goal", "Aaron Ramsey", "Arsenal", "left", "the centre of the box", "bottom left corner", "Sead Kolasinac", "0", "NA", "NA", "0", "NA", "0", "0", "NA", "NA", "NA", "0", "NA", "NA", "NA", "0", "NA", "NA", "0", "NA", "0", "NA", "NA", "NA", "0", "NA", "NA", "0", "0", "NA", "NA", "NA", "0", "NA", "NA", "NA", "NA", "2", "49", "0", "NA", "NA", "58"], ["480813", "Attempt missed. Aaron Ramsey (Arsenal) left footed shot from the centre of the box is high and wide to the left. Assisted by Mesut Özil.", "60'", "Arsenal", "2", "0", "0", "0", "1", "0", "missed", "Aaron Ramsey", "Arsenal", "left", "the centre of the box", "high and wide to the left", "Mesut Özil", "0", "NA", "NA", "0", "NA", "0", "0", "NA", "NA", "NA", "0", "NA", "NA", "NA", "0", "NA", "NA", "0", "NA", "0", "NA", "NA", "NA", "0", "NA", "NA", "0", "0", "NA", "NA", "NA", "0", "NA", "NA", "NA", "NA", "2", "50", "0", "NA", "NA", "60"], ["480813", "Attempt saved. Alexandre Lacazette (Arsenal) left footed shot from the centre of the box is saved in the bottom right corner. Assisted by Héctor Bellerín.", "64'", "Arsenal", "2", "0", "0", "0", "1", "0", "saved", "Alexandre Lacazette", "Arsenal", "left", "the centre of the box", "the bottom right corner", "Héctor Bellerín", "0", "NA", "NA", "0", "NA", "0", "0", "NA", "NA", "NA", "0", "NA", "NA", "NA", "0", "NA", "NA", "0", "NA", "0", "NA", "NA", "NA", "0", "NA", "NA", "0", "0", "NA", "NA", "NA", "0", "NA", "NA", "NA", "NA", "2", "51", "0", "NA", "NA", "64"], ["480813", "Corner,  Swansea City. Conceded by Per Mertesacker.", "65'", "Arsenal", "2", "0", "0", "0", "0", "0", "NA", "NA", "NA", "NA", "NA", "NA", "NA", "0", "NA", "NA", "0", "NA", "0", "0", "NA", "NA", "NA", "0", "NA", "NA", "NA", "0", "NA", "NA", "0", "NA", "0", "NA", "NA", "NA", "1", "Swansea City", "Per Mertesacker", "0", "0", "NA", "NA", "NA", "0", "NA", "NA", "NA", "NA", "2", "52", "0", "NA", "NA", "65"], ["480813", "Héctor Bellerín (Arsenal) hits the bar with a right footed shot from the right side of the six yard box. Assisted by Aaron Ramsey following a fast break.", "66'", "Arsenal", "2", "0", "0", "0", "0", "0", "NA", "NA", "NA", "NA", "NA", "NA", "Aaron Ramsey", "0", "NA", "NA", "0", "NA", "0", "0", "NA", "NA", "NA", "0", "NA", "NA", "NA", "0", "NA", "NA", "0", "NA", "0", "NA", "NA", "NA", "0", "NA", "NA", "0", "0", "NA", "NA", "NA", "0", "NA", "NA", "NA", "NA", "2", "53", "0", "NA", "NA", "66"], ["480813", "Foul by Alexandre Lacazette (Arsenal).", "66'", "Arsenal", "2", "0", "0", "0", "0", "0", "NA", "NA", "NA", "NA", "NA", "NA", "NA", "1", "Alexandre Lacazette", "Arsenal", "0", "NA", "0", "0", "NA", "NA", "NA", "0", "NA", "NA", "NA", "0", "NA", "NA", "0", "NA", "0", "NA", "NA", "NA", "0", "NA", "NA", "0", "0", "NA", "NA", "NA", "0", "NA", "NA", "NA", "NA", "2", "54", "0", "NA", "NA", "66"], ["480813", "Mike van der Hoorn (Swansea City) wins a free kick in the defensive half.", "66'", "Arsenal", "2", "0", "0", "0", "0", "0", "NA", "NA", "NA", "NA", "NA", "NA", "NA", "0", "NA", "NA", "0", "NA", "0", "0", "NA", "NA", "NA", "0", "NA", "NA", "NA", "0", "NA", "NA", "0", "NA", "1", "NA", "Swansea City", "defensive half", "0", "NA", "NA", "0", "0", "NA", "NA", "NA", "0", "NA", "NA", "NA", "NA", "2", "55", "0", "NA", "NA", "66"], ["480813", "Attempt missed. Alexis Sánchez (Arsenal) right footed shot from outside the box is high and wide to the right. Assisted by Aaron Ramsey.", "72'", "Arsenal", "2", "0", "0", "0", "1", "0", "missed", "Alexis Sánchez", "Arsenal", "right", "outside the box", "high and wide to the right", "Aaron Ramsey", "0", "NA", "NA", "0", "NA", "0", "0", "NA", "NA", "NA", "0", "NA", "NA", "NA", "0", "NA", "NA", "0", "NA", "0", "NA", "NA", "NA", "0", "NA", "NA", "0", "0", "NA", "NA", "NA", "0", "NA", "NA", "NA", "NA", "2", "56", "0", "NA", "NA", "72"], ["480813", "Foul by Aaron Ramsey (Arsenal).", "77'", "Arsenal", "2", "0", "0", "0", "0", "0", "NA", "NA", "NA", "NA", "NA", "NA", "NA", "1", "Aaron Ramsey", "Arsenal", "0", "NA", "0", "0", "NA", "NA", "NA", "0", "NA", "NA", "NA", "0", "NA", "NA", "0", "NA", "0", "NA", "NA", "NA", "0", "NA", "NA", "0", "0", "NA", "NA", "NA", "0", "NA", "NA", "NA", "NA", "2", "57", "0", "NA", "NA", "77"], ["480813", "Tom Carroll (Swansea City) wins a free kick in the attacking half.", "77'", "Arsenal", "2", "0", "0", "0", "0", "0", "NA", "NA", "NA", "NA", "NA", "NA", "NA", "0", "NA", "NA", "0", "NA", "0", "0", "NA", "NA", "NA", "0", "NA", "NA", "NA", "0", "NA", "NA", "0", "NA", "1", "Tom Carroll", "Swansea City", "attacking half", "0", "NA", "NA", "0", "0", "NA", "NA", "NA", "0", "NA", "NA", "NA", "NA", "2", "58", "0", "NA", "NA", "77"], ["480813", "Attempt missed. Tammy Abraham (Swansea City) right footed shot from the centre of the box is close, but misses to the left following a set piece situation.", "77'", "Arsenal", "2", "0", "0", "0", "1", "0", "missed", "Tammy Abraham", "Swansea City", "right", "the centre of the box", "close, but left", "NA", "0", "NA", "NA", "1", "NA", "0", "0", "NA", "NA", "NA", "0", "NA", "NA", "NA", "0", "NA", "NA", "0", "NA", "0", "NA", "NA", "NA", "0", "NA", "NA", "0", "0", "NA", "NA", "NA", "0", "NA", "NA", "NA", "NA", "2", "59", "0", "NA", "NA", "77"], ["480813", "Offside, Arsenal. Aaron Ramsey tries a through ball, but Alexandre Lacazette is caught offside.", "78'", "Arsenal", "2", "0", "0", "0", "0", "0", "NA", "NA", "NA", "NA", "NA", "NA", "NA", "0", "NA", "NA", "0", "NA", "0", "1", "Arsenal", "Alexandre Lacazette", "Aaron Ramsey", "0", "NA", "NA", "NA", "0", "NA", "NA", "0", "NA", "0", "NA", "NA", "NA", "0", "NA", "NA", "0", "0", "NA", "NA", "NA", "0", "NA", "NA", "NA", "NA", "2", "60", "0", "NA", "NA", "78"], ["480813", "Substitution, Arsenal. Rob Holding replaces Sead Kolasinac because of an injury.", "78'", "Arsenal", "2", "0", "0", "0", "0", "0", "NA", "NA", "NA", "NA", "NA", "NA", "NA", "0", "NA", "NA", "0", "NA", "0", "0", "NA", "NA", "NA", "0", "NA", "NA", "NA", "0", "NA", "NA", "0", "NA", "0", "NA", "NA", "NA", "0", "NA", "NA", "1", "1", "Arsenal", "Rob Holding", "Sead Kolasinac", "0", "NA", "NA", "NA", "NA", "2", "61", "0", "NA", "NA", "78"], ["480813", "Foul by Granit Xhaka (Arsenal).", "79'", "Arsenal", "2", "0", "0", "0", "0", "0", "NA", "NA", "NA", "NA", "NA", "NA", "NA", "1", "Granit Xhaka", "Arsenal", "0", "NA", "0", "0", "NA", "NA", "NA", "0", "NA", "NA", "NA", "0", "NA", "NA", "0", "NA", "0", "NA", "NA", "NA", "0", "NA", "NA", "0", "0", "NA", "NA", "NA", "0", "NA", "NA", "NA", "NA", "2", "62", "0", "NA", "NA", "79"], ["480813", "Leroy Fer (Swansea City) wins a free kick in the attacking half.", "79'", "Arsenal", "2", "0", "0", "0", "0", "0", "NA", "NA", "NA", "NA", "NA", "NA", "NA", "0", "NA", "NA", "0", "NA", "0", "0", "NA", "NA", "NA", "0", "NA", "NA", "NA", "0", "NA", "NA", "0", "NA", "1", "Leroy Fer", "Swansea City", "attacking half", "0", "NA", "NA", "0", "0", "NA", "NA", "NA", "0", "NA", "NA", "NA", "NA", "2", "63", "0", "NA", "NA", "79"], ["480813", "Substitution, Arsenal. Olivier Giroud replaces Alexandre Lacazette.", "81'", "Arsenal", "2", "0", "0", "0", "0", "0", "NA", "NA", "NA", "NA", "NA", "NA", "NA", "0", "NA", "NA", "0", "NA", "0", "0", "NA", "NA", "NA", "0", "NA", "NA", "NA", "0", "NA", "NA", "0", "NA", "0", "NA", "NA", "NA", "0", "NA", "NA", "1", "0", "Arsenal", "Olivier Giroud", "Alexandre Lacazette", "0", "NA", "NA", "NA", "NA", "2", "64", "0", "NA", "NA", "81"], ["480813", "Substitution, Swansea City. Luciano Narsingh replaces Jordan Ayew.", "81'", "Arsenal", "2", "0", "0", "0", "0", "0", "NA", "NA", "NA", "NA", "NA", "NA", "NA", "0", "NA", "NA", "0", "NA", "0", "0", "NA", "NA", "NA", "0", "NA", "NA", "NA", "0", "NA", "NA", "0", "NA", "0", "NA", "NA", "NA", "0", "NA", "NA", "1", "0", "Swansea City", "Luciano Narsingh", "Jordan Ayew", "0", "NA", "NA", "NA", "NA", "2", "65", "0", "NA", "NA", "81"], ["480813", "Substitution, Swansea City. Nathan Dyer replaces Mike van der Hoorn.", "82'", "Arsenal", "2", "0", "0", "0", "0", "0", "NA", "NA", "NA", "NA", "NA", "NA", "NA", "0", "NA", "NA", "0", "NA", "0", "0", "NA", "NA", "NA", "0", "NA", "NA", "NA", "0", "NA", "NA", "0", "NA", "0", "NA", "NA", "NA", "0", "NA", "NA", "1", "0", "Swansea City", "Nathan Dyer", "Mike van der", "0", "NA", "NA", "NA", "NA", "2", "66", "0", "NA", "NA", "82"], ["480813", "Foul by Leroy Fer (Swansea City).", "83'", "Arsenal", "2", "0", "0", "0", "0", "0", "NA", "NA", "NA", "NA", "NA", "NA", "NA", "1", "Leroy Fer", "Swansea City", "0", "NA", "0", "0", "NA", "NA", "NA", "0", "NA", "NA", "NA", "0", "NA", "NA", "0", "NA", "0", "NA", "NA", "NA", "0", "NA", "NA", "0", "0", "NA", "NA", "NA", "0", "NA", "NA", "NA", "NA", "2", "67", "0", "NA", "NA", "83"], ["480813", "Granit Xhaka (Arsenal) wins a free kick in the defensive half.", "83'", "Arsenal", "2", "0", "0", "0", "0", "0", "NA", "NA", "NA", "NA", "NA", "NA", "NA", "0", "NA", "NA", "0", "NA", "0", "0", "NA", "NA", "NA", "0", "NA", "NA", "NA", "0", "NA", "NA", "0", "NA", "1", "Granit Xhaka", "Arsenal", "defensive half", "0", "NA", "NA", "0", "0", "NA", "NA", "NA", "0", "NA", "NA", "NA", "NA", "2", "68", "0", "NA", "NA", "83"], ["480813", "Substitution, Swansea City. Oliver McBurnie replaces Tom Carroll.", "84'", "Arsenal", "2", "0", "0", "0", "0", "0", "NA", "NA", "NA", "NA", "NA", "NA", "NA", "0", "NA", "NA", "0", "NA", "0", "0", "NA", "NA", "NA", "0", "NA", "NA", "NA", "0", "NA", "NA", "0", "NA", "0", "NA", "NA", "NA", "0", "NA", "NA", "1", "0", "Swansea City", "Oliver McBurnie", "Tom Carroll", "0", "NA", "NA", "NA", "NA", "2", "69", "0", "NA", "NA", "84"], ["480813", "Alexis Sánchez (Arsenal) wins a free kick in the attacking half.", "85'", "Arsenal", "2", "0", "0", "0", "0", "0", "NA", "NA", "NA", "NA", "NA", "NA", "NA", "0", "NA", "NA", "0", "NA", "0", "0", "NA", "NA", "NA", "0", "NA", "NA", "NA", "0", "NA", "NA", "0", "NA", "1", "Alexis Sánchez", "Arsenal", "attacking half", "0", "NA", "NA", "0", "0", "NA", "NA", "NA", "0", "NA", "NA", "NA", "NA", "2", "70", "0", "NA", "NA", "85"], ["480813", "Foul by Federico Fernández (Swansea City).", "85'", "Arsenal", "2", "0", "0", "0", "0", "0", "NA", "NA", "NA", "NA", "NA", "NA", "NA", "1", "Federico Fernández", "Swansea City", "0", "NA", "0", "0", "NA", "NA", "NA", "0", "NA", "NA", "NA", "0", "NA", "NA", "0", "NA", "0", "NA", "NA", "NA", "0", "NA", "NA", "0", "0", "NA", "NA", "NA", "0", "NA", "NA", "NA", "NA", "2", "71", "0", "NA", "NA", "85"], ["480813", "Attempt missed. Olivier Giroud (Arsenal) left footed shot from the left side of the six yard box is close, but misses to the left. Assisted by Nacho Monreal with a cross.", "86'", "Arsenal", "2", "0", "0", "0", "1", "0", "missed", "Olivier Giroud", "Arsenal", "left", "the left side of the six yard box", "close, but left", "Nacho Monreal", "0", "NA", "NA", "0", "cross", "0", "0", "NA", "NA", "NA", "0", "NA", "NA", "NA", "0", "NA", "NA", "0", "NA", "0", "NA", "NA", "NA", "0", "NA", "NA", "0", "0", "NA", "NA", "NA", "0", "NA", "NA", "NA", "NA", "2", "72", "0", "NA", "NA", "86"], ["480813", "Attempt missed. Olivier Giroud (Arsenal) left footed shot from outside the box is close, but misses to the left. Assisted by Mesut Özil.", "89'", "Arsenal", "2", "0", "0", "0", "1", "0", "missed", "Olivier Giroud", "Arsenal", "left", "outside the box", "close, but left", "Mesut Özil", "0", "NA", "NA", "0", "NA", "0", "0", "NA", "NA", "NA", "0", "NA", "NA", "NA", "0", "NA", "NA", "0", "NA", "0", "NA", "NA", "NA", "0", "NA", "NA", "0", "0", "NA", "NA", "NA", "0", "NA", "NA", "NA", "NA", "2", "73", "0", "NA", "NA", "89"], ["480813", "Offside, Arsenal. Mesut Özil tries a through ball, but Alexis Sánchez is caught offside.", "90'+2'", "Arsenal", "2", "0", "0", "0", "0", "0", "NA", "NA", "NA", "NA", "NA", "NA", "NA", "0", "NA", "NA", "0", "NA", "0", "1", "Arsenal", "Alexis Sánchez", "Mesut Özil", "0", "NA", "NA", "NA", "0", "NA", "NA", "0", "NA", "0", "NA", "NA", "NA", "0", "NA", "NA", "0", "0", "NA", "NA", "NA", "0", "NA", "NA", "NA", "NA", "2", "74", "1", "NA", "NA", "92"], ["480813", "Foul by Alfie Mawson (Swansea City).", "90'+3'", "Arsenal", "2", "0", "0", "0", "0", "0", "NA", "NA", "NA", "NA", "NA", "NA", "NA", "1", "Alfie Mawson", "Swansea City", "0", "NA", "0", "0", "NA", "NA", "NA", "0", "NA", "NA", "NA", "0", "NA", "NA", "0", "NA", "0", "NA", "NA", "NA", "0", "NA", "NA", "0", "0", "NA", "NA", "NA", "0", "NA", "NA", "NA", "NA", "2", "75", "1", "NA", "NA", "93"], ["480813", "Granit Xhaka (Arsenal) wins a free kick in the defensive half.", "90'+3'", "Arsenal", "2", "0", "0", "0", "0", "0", "NA", "NA", "NA", "NA", "NA", "NA", "NA", "0", "NA", "NA", "0", "NA", "0", "0", "NA", "NA", "NA", "0", "NA", "NA", "NA", "0", "NA", "NA", "0", "NA", "1", "Granit Xhaka", "Arsenal", "defensive half", "0", "NA", "NA", "0", "0", "NA", "NA", "NA", "0", "NA", "NA", "NA", "NA", "2", "76", "1", "NA", "NA", "93"], ["480813", "Second Half ends, Arsenal 2, Swansea City 1.", "90'+4'", "Arsenal", "2", "1", "0", "0", "0", "0", "NA", "NA", "NA", "NA", "NA", "NA", "NA", "0", "NA", "NA", "0", "NA", "0", "0", "NA", "NA", "NA", "0", "NA", "NA", "NA", "0", "NA", "NA", "0", "NA", "0", "NA", "NA", "NA", "0", "NA", "NA", "0", "0", "NA", "NA", "NA", "0", "NA", "NA", "NA", "NA", "2", "77", "1", "NA", "NA", "94"], ["480813", "Match ends, Arsenal 2, Swansea City 1.", "90'+4'", "Arsenal", "2", "0", "1", "0", "0", "0", "NA", "NA", "NA", "NA", "NA", "NA", "NA", "0", "NA", "NA", "0", "NA", "0", "0", "NA", "NA", "NA", "0", "NA", "NA", "NA", "0", "NA", "NA", "0", "NA", "0", "NA", "NA", "NA", "0", "NA", "NA", "0", "0", "NA", "NA", "NA", "0", "NA", "NA", "NA", "NA", "2", "78", "1", "NA", "NA", "94"]], "Lineup": {"Home Player 9": "Aaron Ramsey", "Home Player 8": "Mesut Ozil", "Home Player 5": "Alexandre Lacazette", "Home Player 4": "Laurent Koscielny", "Home Player 7": "Nacho Monreal", "Home Player 6": "Per Mertesacker", "Home Player 1": "Hector Bellerin", "Home Player 3": "Sead Kolasinac", "Home Player 2": "Petr Cech", "Away Player 10": "Kyle Naughton", "Away Player 11": "Mike van der Hoorn", "Away Player 8": "Ki Sung-yueng", "Away Player 9": "Alfie Mawson", "Away Player 1": "Tammy Abraham", "Away Player 2": "Jordan Ayew", "Away Player 3": "Thomas Carroll", "Away Player 4": "Sam Clucas", "Away Player 5": "Lukasz Fabianski", "Away Player 6": "Leroy Fer", "Away Player 7": "Federico Fernandez", "Game ID": "g_1_2u9KvO07", "Home Player 11": "Granit Xhaka", "Home Player 10": "Alexis Sanchez"}}