{"Stats": {"Full Time Result": "A", "Away Team Corners": 7, "Referee": "N Swarbrick", "Home Team Fouls Committed": 7, "Away Team Shots": 14, "Away Team Red Cards": 0, "Home Team Red Cards": 0, "Half Time Away Team Goals": 3, "Full Time Home Team Goals": 0, "Away Team Yellow Cards": 1, "Away Team Shots on Target": 7, "Half Time Home Team Goals": 0, "Half Time Result": "A", "Away Team Fouls Committed": 4, "Home Team Yellow Cards": 1, "Home Team Shots": 6, "Div": "E0", "Home Team Corners": 4, "Home Team Shots on Target": 1, "Full Time Away Team Goals": 4}, "Description": "Attempt blocked. Harry Kane (Tottenham Hotspur) right footed shot from the right side of the box is blocked. Assisted by Kieran Trippier. at minute 1. Corner,  Tottenham Hotspur. Conceded by Zanka. at minute 1. Corner,  Tottenham Hotspur. Conceded by Chris Löwe. at minute 2. Foul by Zanka (Huddersfield Town). at minute 3. Harry Kane (Tottenham Hotspur) wins a free kick in the attacking half. at minute 3. Attempt saved. Tommy Smith (Huddersfield Town) left footed shot from outside the box is saved in the centre of the goal. Assisted by Laurent Depoitre. at minute 5. Foul by Jonathan Hogg (Huddersfield Town). at minute 7. Harry Winks (Tottenham Hotspur) wins a free kick in the defensive half. at minute 7. Offside, Tottenham Hotspur. Kieran Trippier tries a through ball, but Harry Kane is caught offside. at minute 7. Attempt blocked. Rajiv van La Parra (Huddersfield Town) right footed shot from the centre of the box is blocked. at minute 8. Corner,  Huddersfield Town. Conceded by Eric Dier. at minute 8. Goal!  Huddersfield Town 0, Tottenham Hotspur 1. Harry Kane (Tottenham Hotspur) right footed shot from the right side of the box to the bottom right corner. Assisted by Kieran Trippier with a headed pass. at minute 9. Christian Eriksen (Tottenham Hotspur) wins a free kick on the left wing. at minute 12. Foul by Rajiv van La Parra (Huddersfield Town). at minute 12. Foul by Kieran Trippier (Tottenham Hotspur). at minute 13. Rajiv van La Parra (Huddersfield Town) wins a free kick in the defensive half. at minute 13. Attempt blocked. Aaron Mooy (Huddersfield Town) left footed shot from the left side of the box is blocked. at minute 15. Goal!  Huddersfield Town 0, Tottenham Hotspur 2. Ben Davies (Tottenham Hotspur) left footed shot from the centre of the box to the bottom right corner. at minute 16. Attempt missed. Harry Kane (Tottenham Hotspur) right footed shot from outside the box is just a bit too high. Assisted by Dele Alli. at minute 18. Davinson Sánchez (Tottenham Hotspur) wins a free kick in the defensive half. at minute 19. Foul by Laurent Depoitre (Huddersfield Town). at minute 19. Attempt saved. Harry Kane (Tottenham Hotspur) right footed shot from the centre of the box is saved in the centre of the goal. at minute 20. Goal!  Huddersfield Town 0, Tottenham Hotspur 3. Harry Kane (Tottenham Hotspur) left footed shot from outside the box to the top left corner. Assisted by Kieran Trippier. at minute 23. Corner,  Huddersfield Town. Conceded by Eric Dier. at minute 27. Corner,  Huddersfield Town. Conceded by Kieran Trippier. at minute 30. Dele Alli (Tottenham Hotspur) hits the left post with a right footed shot from the right side of the box. at minute 31. Attempt missed. Dele Alli (Tottenham Hotspur) header from the right side of the six yard box is close, but misses the top right corner. Assisted by Harry Winks with a cross. at minute 31. Offside, Huddersfield Town. Tommy Smith tries a through ball, but Laurent Depoitre is caught offside. at minute 32. Elias Kachunga (Huddersfield Town) wins a free kick in the attacking half. at minute 34. Foul by Toby Alderweireld (Tottenham Hotspur). at minute 34. Offside, Tottenham Hotspur. Ben Davies tries a through ball, but Harry Kane is caught offside. at minute 36. Dele Alli (Tottenham Hotspur) wins a free kick on the left wing. at minute 41. Foul by Tommy Smith (Huddersfield Town). at minute 41. Corner,  Tottenham Hotspur. Conceded by Tommy Smith. at minute 41. Laurent Depoitre (Huddersfield Town) hits the bar with a right footed shot from outside the box. at minute 43. Corner,  Tottenham Hotspur. Conceded by Zanka. at minute 45. Attempt missed. Ben Davies (Tottenham Hotspur) left footed shot from the left side of the box misses to the right. at minute 47. First Half ends, Huddersfield Town 0, Tottenham Hotspur 3. at minute 47. Second Half begins Huddersfield Town 0, Tottenham Hotspur 3. at minute 45. Corner,  Tottenham Hotspur. Conceded by Jonathan Hogg. at minute 49. Delay in match Kieran Trippier (Tottenham Hotspur) because of an injury. at minute 53. Delay over. They are ready to continue. at minute 55. Dele Alli (Tottenham Hotspur) has gone down, but that's a dive. at minute 58. Dele Alli (Tottenham Hotspur) is shown the yellow card. at minute 58. Attempt missed. Jan Vertonghen (Tottenham Hotspur) left footed shot from outside the box is too high. at minute 60. Substitution, Huddersfield Town. Scott Malone replaces Chris Löwe. at minute 60. Substitution, Huddersfield Town. Philip Billing replaces Aaron Mooy. at minute 61. Foul by Elias Kachunga (Huddersfield Town). at minute 65. Jan Vertonghen (Tottenham Hotspur) wins a free kick in the defensive half. at minute 65. Elias Kachunga (Huddersfield Town) is shown the yellow card for a bad foul. at minute 65. Hand ball by Elias Kachunga (Huddersfield Town). at minute 66. Offside, Huddersfield Town. Scott Malone tries a through ball, but Rajiv van La Parra is caught offside. at minute 67. Attempt saved. Christian Eriksen (Tottenham Hotspur) right footed shot from the left side of the box is saved in the centre of the goal. Assisted by Ben Davies. at minute 67. Offside, Huddersfield Town. Zanka tries a through ball, but Laurent Depoitre is caught offside. at minute 70. Corner,  Tottenham Hotspur. Conceded by Zanka. at minute 73. Attempt blocked. Eric Dier (Tottenham Hotspur) right footed shot from outside the box is blocked. Assisted by Harry Kane. at minute 74. Corner,  Tottenham Hotspur. Conceded by Christopher Schindler. at minute 74. Substitution, Tottenham Hotspur. Moussa Sissoko replaces Christian Eriksen. at minute 75. Offside, Huddersfield Town. Zanka tries a through ball, but Tommy Smith is caught offside. at minute 76. Substitution, Huddersfield Town. Dean Whitehead replaces Jonathan Hogg. at minute 82. Substitution, Tottenham Hotspur. Kyle Walker-Peters replaces Kieran Trippier. at minute 82. Attempt blocked. Rajiv van La Parra (Huddersfield Town) right footed shot from outside the box is blocked. Assisted by Laurent Depoitre. at minute 85. Attempt saved. Moussa Sissoko (Tottenham Hotspur) left footed shot from the right side of the box is saved in the centre of the goal. Assisted by Dele Alli. at minute 86. Substitution, Tottenham Hotspur. Son Heung-Min replaces Harry Kane. at minute 87. Foul by Harry Winks (Tottenham Hotspur). at minute 88. Rajiv van La Parra (Huddersfield Town) wins a free kick on the right wing. at minute 88. Corner,  Huddersfield Town. Conceded by Ben Davies. at minute 89. Goal!  Huddersfield Town 0, Tottenham Hotspur 4. Moussa Sissoko (Tottenham Hotspur) left footed shot from the centre of the box to the bottom right corner. Assisted by Ben Davies. at minute 91. Attempt missed. Rajiv van La Parra (Huddersfield Town) right footed shot from outside the box misses to the left. Assisted by Zanka. at minute 92. Second Half ends, Huddersfield Town 0, Tottenham Hotspur 4. at minute 94. Match ends, Huddersfield Town 0, Tottenham Hotspur 4. at minute 94. ", "Home Team": "Huddersfield Town", "Away Team": "Tottenham Hotspur", "Date": "2017-09-30", "Commentary": [["480844", "First Half begins.", "-", "Huddersfield Town", "0", "0", "0", "1", "0", "0", "NA", "NA", "NA", "NA", "NA", "NA", "NA", "0", "NA", "NA", "0", "NA", "0", "0", "NA", "NA", "NA", "0", "NA", "NA", "NA", "0", "NA", "NA", "0", "NA", "0", "NA", "NA", "NA", "0", "NA", "NA", "0", "0", "NA", "NA", "NA", "0", "NA", "NA", "NA", "NA", "1", "1", "0", "NA", "NA", "NA"], ["480844", "Lineups are announced and players are warming up.", "-", "Huddersfield Town", "0", "0", "0", "0", "0", "0", "NA", "NA", "NA", "NA", "NA", "NA", "NA", "0", "NA", "NA", "0", "NA", "0", "0", "NA", "NA", "NA", "0", "NA", "NA", "NA", "0", "NA", "NA", "0", "NA", "0", "NA", "NA", "NA", "0", "NA", "NA", "0", "0", "NA", "NA", "NA", "0", "NA", "NA", "NA", "NA", "1", "2", "0", "NA", "NA", "NA"], ["480844", "Attempt blocked. Harry Kane (Tottenham Hotspur) right footed shot from the right side of the box is blocked. Assisted by Kieran Trippier.", "1'", "Huddersfield Town", "0", "0", "0", "0", "1", "0", "blocked", "Harry Kane", "Tottenham Hotspur", "right", "the right side of the box", "NA", "Kieran Trippier", "0", "NA", "NA", "0", "NA", "0", "0", "NA", "NA", "NA", "0", "NA", "NA", "NA", "0", "NA", "NA", "0", "NA", "0", "NA", "NA", "NA", "0", "NA", "NA", "0", "0", "NA", "NA", "NA", "0", "NA", "NA", "NA", "NA", "1", "3", "0", "NA", "NA", "1"], ["480844", "Corner,  Tottenham Hotspur. Conceded by Zanka.", "1'", "Huddersfield Town", "0", "0", "0", "0", "0", "0", "NA", "NA", "NA", "NA", "NA", "NA", "NA", "0", "NA", "NA", "0", "NA", "0", "0", "NA", "NA", "NA", "0", "NA", "NA", "NA", "0", "NA", "NA", "0", "NA", "0", "NA", "NA", "NA", "1", "Tottenham Hotspur", "Zanka", "0", "0", "NA", "NA", "NA", "0", "NA", "NA", "NA", "NA", "1", "4", "0", "NA", "NA", "1"], ["480844", "Corner,  Tottenham Hotspur. Conceded by Chris Löwe.", "2'", "Huddersfield Town", "0", "0", "0", "0", "0", "0", "NA", "NA", "NA", "NA", "NA", "NA", "NA", "0", "NA", "NA", "0", "NA", "0", "0", "NA", "NA", "NA", "0", "NA", "NA", "NA", "0", "NA", "NA", "0", "NA", "0", "NA", "NA", "NA", "1", "Tottenham Hotspur", "Chris Löwe", "0", "0", "NA", "NA", "NA", "0", "NA", "NA", "NA", "NA", "1", "5", "0", "NA", "NA", "2"], ["480844", "Foul by Zanka (Huddersfield Town).", "3'", "Huddersfield Town", "0", "0", "0", "0", "0", "0", "NA", "NA", "NA", "NA", "NA", "NA", "NA", "1", "Zanka", "Huddersfield Town", "0", "NA", "0", "0", "NA", "NA", "NA", "0", "NA", "NA", "NA", "0", "NA", "NA", "0", "NA", "0", "NA", "NA", "NA", "0", "NA", "NA", "0", "0", "NA", "NA", "NA", "0", "NA", "NA", "NA", "NA", "1", "6", "0", "NA", "NA", "3"], ["480844", "Harry Kane (Tottenham Hotspur) wins a free kick in the attacking half.", "3'", "Huddersfield Town", "0", "0", "0", "0", "0", "0", "NA", "NA", "NA", "NA", "NA", "NA", "NA", "0", "NA", "NA", "0", "NA", "0", "0", "NA", "NA", "NA", "0", "NA", "NA", "NA", "0", "NA", "NA", "0", "NA", "1", "Harry Kane", "Tottenham Hotspur", "attacking half", "0", "NA", "NA", "0", "0", "NA", "NA", "NA", "0", "NA", "NA", "NA", "NA", "1", "7", "0", "NA", "NA", "3"], ["480844", "Attempt saved. Tommy Smith (Huddersfield Town) left footed shot from outside the box is saved in the centre of the goal. Assisted by Laurent Depoitre.", "5'", "Huddersfield Town", "0", "0", "0", "0", "1", "0", "saved", "Tommy Smith", "Huddersfield Town", "left", "outside the box", "the centre of the goal", "Laurent Depoitre", "0", "NA", "NA", "0", "NA", "0", "0", "NA", "NA", "NA", "0", "NA", "NA", "NA", "0", "NA", "NA", "0", "NA", "0", "NA", "NA", "NA", "0", "NA", "NA", "0", "0", "NA", "NA", "NA", "0", "NA", "NA", "NA", "NA", "1", "8", "0", "NA", "NA", "5"], ["480844", "Foul by Jonathan Hogg (Huddersfield Town).", "7'", "Huddersfield Town", "0", "0", "0", "0", "0", "0", "NA", "NA", "NA", "NA", "NA", "NA", "NA", "1", "Jonathan Hogg", "Huddersfield Town", "0", "NA", "0", "0", "NA", "NA", "NA", "0", "NA", "NA", "NA", "0", "NA", "NA", "0", "NA", "0", "NA", "NA", "NA", "0", "NA", "NA", "0", "0", "NA", "NA", "NA", "0", "NA", "NA", "NA", "NA", "1", "9", "0", "NA", "NA", "7"], ["480844", "Harry Winks (Tottenham Hotspur) wins a free kick in the defensive half.", "7'", "Huddersfield Town", "0", "0", "0", "0", "0", "0", "NA", "NA", "NA", "NA", "NA", "NA", "NA", "0", "NA", "NA", "0", "NA", "0", "0", "NA", "NA", "NA", "0", "NA", "NA", "NA", "0", "NA", "NA", "0", "NA", "1", "Harry Winks", "Tottenham Hotspur", "defensive half", "0", "NA", "NA", "0", "0", "NA", "NA", "NA", "0", "NA", "NA", "NA", "NA", "1", "10", "0", "NA", "NA", "7"], ["480844", "Offside, Tottenham Hotspur. Kieran Trippier tries a through ball, but Harry Kane is caught offside.", "7'", "Huddersfield Town", "0", "0", "0", "0", "0", "0", "NA", "NA", "NA", "NA", "NA", "NA", "NA", "0", "NA", "NA", "0", "NA", "0", "1", "Tottenham Hotspur", "Harry Kane", "Kieran Trippier", "0", "NA", "NA", "NA", "0", "NA", "NA", "0", "NA", "0", "NA", "NA", "NA", "0", "NA", "NA", "0", "0", "NA", "NA", "NA", "0", "NA", "NA", "NA", "NA", "1", "11", "0", "NA", "NA", "7"], ["480844", "Attempt blocked. Rajiv van La Parra (Huddersfield Town) right footed shot from the centre of the box is blocked.", "8'", "Huddersfield Town", "0", "0", "0", "0", "1", "0", "blocked", "NA", "Huddersfield Town", "right", "the centre of the box", "NA", "NA", "0", "NA", "NA", "0", "NA", "0", "0", "NA", "NA", "NA", "0", "NA", "NA", "NA", "0", "NA", "NA", "0", "NA", "0", "NA", "NA", "NA", "0", "NA", "NA", "0", "0", "NA", "NA", "NA", "0", "NA", "NA", "NA", "NA", "1", "12", "0", "NA", "NA", "8"], ["480844", "Corner,  Huddersfield Town. Conceded by Eric Dier.", "8'", "Huddersfield Town", "0", "0", "0", "0", "0", "0", "NA", "NA", "NA", "NA", "NA", "NA", "NA", "0", "NA", "NA", "0", "NA", "0", "0", "NA", "NA", "NA", "0", "NA", "NA", "NA", "0", "NA", "NA", "0", "NA", "0", "NA", "NA", "NA", "1", "Huddersfield Town", "Eric Dier", "0", "0", "NA", "NA", "NA", "0", "NA", "NA", "NA", "NA", "1", "13", "0", "NA", "NA", "8"], ["480844", "Goal!  Huddersfield Town 0, Tottenham Hotspur 1. Harry Kane (Tottenham Hotspur) right footed shot from the right side of the box to the bottom right corner. Assisted by Kieran Trippier with a headed pass.", "9'", "Huddersfield Town", "0", "0", "0", "0", "1", "0", "goal", "Harry Kane", "Tottenham Hotspur", "right", "the right side of the box", "bottom right corner", "Kieran Trippier", "0", "NA", "NA", "0", "NA", "0", "0", "NA", "NA", "NA", "0", "NA", "NA", "NA", "0", "NA", "NA", "0", "NA", "0", "NA", "NA", "NA", "0", "NA", "NA", "0", "0", "NA", "NA", "NA", "0", "NA", "NA", "NA", "NA", "1", "14", "0", "NA", "NA", "9"], ["480844", "Christian Eriksen (Tottenham Hotspur) wins a free kick on the left wing.", "12'", "Huddersfield Town", "0", "0", "0", "0", "0", "0", "NA", "NA", "NA", "NA", "NA", "NA", "NA", "0", "NA", "NA", "0", "NA", "0", "0", "NA", "NA", "NA", "0", "NA", "NA", "NA", "0", "NA", "NA", "0", "NA", "1", "Christian Eriksen", "Tottenham Hotspur", "NA", "0", "NA", "NA", "0", "0", "NA", "NA", "NA", "0", "NA", "NA", "NA", "NA", "1", "15", "0", "NA", "NA", "12"], ["480844", "Foul by Rajiv van La Parra (Huddersfield Town).", "12'", "Huddersfield Town", "0", "0", "0", "0", "0", "0", "NA", "NA", "NA", "NA", "NA", "NA", "NA", "1", "van La Parra", "Huddersfield Town", "0", "NA", "0", "0", "NA", "NA", "NA", "0", "NA", "NA", "NA", "0", "NA", "NA", "0", "NA", "0", "NA", "NA", "NA", "0", "NA", "NA", "0", "0", "NA", "NA", "NA", "0", "NA", "NA", "NA", "NA", "1", "16", "0", "NA", "NA", "12"], ["480844", "Foul by Kieran Trippier (Tottenham Hotspur).", "13'", "Huddersfield Town", "0", "0", "0", "0", "0", "0", "NA", "NA", "NA", "NA", "NA", "NA", "NA", "1", "Kieran Trippier", "Tottenham Hotspur", "0", "NA", "0", "0", "NA", "NA", "NA", "0", "NA", "NA", "NA", "0", "NA", "NA", "0", "NA", "0", "NA", "NA", "NA", "0", "NA", "NA", "0", "0", "NA", "NA", "NA", "0", "NA", "NA", "NA", "NA", "1", "17", "0", "NA", "NA", "13"], ["480844", "Rajiv van La Parra (Huddersfield Town) wins a free kick in the defensive half.", "13'", "Huddersfield Town", "0", "0", "0", "0", "0", "0", "NA", "NA", "NA", "NA", "NA", "NA", "NA", "0", "NA", "NA", "0", "NA", "0", "0", "NA", "NA", "NA", "0", "NA", "NA", "NA", "0", "NA", "NA", "0", "NA", "1", "NA", "Huddersfield Town", "defensive half", "0", "NA", "NA", "0", "0", "NA", "NA", "NA", "0", "NA", "NA", "NA", "NA", "1", "18", "0", "NA", "NA", "13"], ["480844", "Attempt blocked. Aaron Mooy (Huddersfield Town) left footed shot from the left side of the box is blocked.", "15'", "Huddersfield Town", "0", "0", "0", "0", "1", "0", "blocked", "Aaron Mooy", "Huddersfield Town", "left", "the left side of the box", "NA", "NA", "0", "NA", "NA", "0", "NA", "0", "0", "NA", "NA", "NA", "0", "NA", "NA", "NA", "0", "NA", "NA", "0", "NA", "0", "NA", "NA", "NA", "0", "NA", "NA", "0", "0", "NA", "NA", "NA", "0", "NA", "NA", "NA", "NA", "1", "19", "0", "NA", "NA", "15"], ["480844", "Goal!  Huddersfield Town 0, Tottenham Hotspur 2. Ben Davies (Tottenham Hotspur) left footed shot from the centre of the box to the bottom right corner.", "16'", "Huddersfield Town", "0", "0", "0", "0", "1", "0", "goal", "Ben Davies", "Tottenham Hotspur", "left", "the centre of the box", "bottom right corner", "NA", "0", "NA", "NA", "0", "NA", "0", "0", "NA", "NA", "NA", "0", "NA", "NA", "NA", "0", "NA", "NA", "0", "NA", "0", "NA", "NA", "NA", "0", "NA", "NA", "0", "0", "NA", "NA", "NA", "0", "NA", "NA", "NA", "NA", "1", "20", "0", "NA", "NA", "16"], ["480844", "Attempt missed. Harry Kane (Tottenham Hotspur) right footed shot from outside the box is just a bit too high. Assisted by Dele Alli.", "18'", "Huddersfield Town", "0", "0", "0", "0", "1", "0", "missed", "Harry Kane", "Tottenham Hotspur", "right", "outside the box", "just a bit too high", "Dele Alli", "0", "NA", "NA", "0", "NA", "0", "0", "NA", "NA", "NA", "0", "NA", "NA", "NA", "0", "NA", "NA", "0", "NA", "0", "NA", "NA", "NA", "0", "NA", "NA", "0", "0", "NA", "NA", "NA", "0", "NA", "NA", "NA", "NA", "1", "21", "0", "NA", "NA", "18"], ["480844", "Davinson Sánchez (Tottenham Hotspur) wins a free kick in the defensive half.", "19'", "Huddersfield Town", "0", "0", "0", "0", "0", "0", "NA", "NA", "NA", "NA", "NA", "NA", "NA", "0", "NA", "NA", "0", "NA", "0", "0", "NA", "NA", "NA", "0", "NA", "NA", "NA", "0", "NA", "NA", "0", "NA", "1", "Davinson Sánchez", "Tottenham Hotspur", "defensive half", "0", "NA", "NA", "0", "0", "NA", "NA", "NA", "0", "NA", "NA", "NA", "NA", "1", "22", "0", "NA", "NA", "19"], ["480844", "Foul by Laurent Depoitre (Huddersfield Town).", "19'", "Huddersfield Town", "0", "0", "0", "0", "0", "0", "NA", "NA", "NA", "NA", "NA", "NA", "NA", "1", "Laurent Depoitre", "Huddersfield Town", "0", "NA", "0", "0", "NA", "NA", "NA", "0", "NA", "NA", "NA", "0", "NA", "NA", "0", "NA", "0", "NA", "NA", "NA", "0", "NA", "NA", "0", "0", "NA", "NA", "NA", "0", "NA", "NA", "NA", "NA", "1", "23", "0", "NA", "NA", "19"], ["480844", "Attempt saved. Harry Kane (Tottenham Hotspur) right footed shot from the centre of the box is saved in the centre of the goal.", "20'", "Huddersfield Town", "0", "0", "0", "0", "1", "0", "saved", "Harry Kane", "Tottenham Hotspur", "right", "the centre of the box", "the centre of the goal", "NA", "0", "NA", "NA", "0", "NA", "0", "0", "NA", "NA", "NA", "0", "NA", "NA", "NA", "0", "NA", "NA", "0", "NA", "0", "NA", "NA", "NA", "0", "NA", "NA", "0", "0", "NA", "NA", "NA", "0", "NA", "NA", "NA", "NA", "1", "24", "0", "NA", "NA", "20"], ["480844", "Goal!  Huddersfield Town 0, Tottenham Hotspur 3. Harry Kane (Tottenham Hotspur) left footed shot from outside the box to the top left corner. Assisted by Kieran Trippier.", "23'", "Huddersfield Town", "0", "0", "0", "0", "1", "0", "goal", "Harry Kane", "Tottenham Hotspur", "left", "outside the box", "top left corner", "Kieran Trippier", "0", "NA", "NA", "0", "NA", "0", "0", "NA", "NA", "NA", "0", "NA", "NA", "NA", "0", "NA", "NA", "0", "NA", "0", "NA", "NA", "NA", "0", "NA", "NA", "0", "0", "NA", "NA", "NA", "0", "NA", "NA", "NA", "NA", "1", "25", "0", "NA", "NA", "23"], ["480844", "Corner,  Huddersfield Town. Conceded by Eric Dier.", "27'", "Huddersfield Town", "0", "0", "0", "0", "0", "0", "NA", "NA", "NA", "NA", "NA", "NA", "NA", "0", "NA", "NA", "0", "NA", "0", "0", "NA", "NA", "NA", "0", "NA", "NA", "NA", "0", "NA", "NA", "0", "NA", "0", "NA", "NA", "NA", "1", "Huddersfield Town", "Eric Dier", "0", "0", "NA", "NA", "NA", "0", "NA", "NA", "NA", "NA", "1", "26", "0", "NA", "NA", "27"], ["480844", "Corner,  Huddersfield Town. Conceded by Kieran Trippier.", "30'", "Huddersfield Town", "0", "0", "0", "0", "0", "0", "NA", "NA", "NA", "NA", "NA", "NA", "NA", "0", "NA", "NA", "0", "NA", "0", "0", "NA", "NA", "NA", "0", "NA", "NA", "NA", "0", "NA", "NA", "0", "NA", "0", "NA", "NA", "NA", "1", "Huddersfield Town", "Kieran Trippier", "0", "0", "NA", "NA", "NA", "0", "NA", "NA", "NA", "NA", "1", "27", "0", "NA", "NA", "30"], ["480844", "Dele Alli (Tottenham Hotspur) hits the left post with a right footed shot from the right side of the box.", "31'", "Huddersfield Town", "0", "0", "0", "0", "0", "0", "NA", "NA", "NA", "NA", "NA", "NA", "NA", "0", "NA", "NA", "0", "NA", "0", "0", "NA", "NA", "NA", "0", "NA", "NA", "NA", "0", "NA", "NA", "0", "NA", "0", "NA", "NA", "NA", "0", "NA", "NA", "0", "0", "NA", "NA", "NA", "0", "NA", "NA", "NA", "NA", "1", "28", "0", "NA", "NA", "31"], ["480844", "Attempt missed. Dele Alli (Tottenham Hotspur) header from the right side of the six yard box is close, but misses the top right corner. Assisted by Harry Winks with a cross.", "31'", "Huddersfield Town", "0", "0", "0", "0", "1", "0", "missed", "Dele Alli", "Tottenham Hotspur", "header", "the right side of the six yard box", "close, but misses the top right corner", "Harry Winks", "0", "NA", "NA", "0", "cross", "0", "0", "NA", "NA", "NA", "0", "NA", "NA", "NA", "0", "NA", "NA", "0", "NA", "0", "NA", "NA", "NA", "0", "NA", "NA", "0", "0", "NA", "NA", "NA", "0", "NA", "NA", "NA", "NA", "1", "29", "0", "NA", "NA", "31"], ["480844", "Offside, Huddersfield Town. Tommy Smith tries a through ball, but Laurent Depoitre is caught offside.", "32'", "Huddersfield Town", "0", "0", "0", "0", "0", "0", "NA", "NA", "NA", "NA", "NA", "NA", "NA", "0", "NA", "NA", "0", "NA", "0", "1", "Huddersfield Town", "Laurent Depoitre", "Tommy Smith", "0", "NA", "NA", "NA", "0", "NA", "NA", "0", "NA", "0", "NA", "NA", "NA", "0", "NA", "NA", "0", "0", "NA", "NA", "NA", "0", "NA", "NA", "NA", "NA", "1", "30", "0", "NA", "NA", "32"], ["480844", "Elias Kachunga (Huddersfield Town) wins a free kick in the attacking half.", "34'", "Huddersfield Town", "0", "0", "0", "0", "0", "0", "NA", "NA", "NA", "NA", "NA", "NA", "NA", "0", "NA", "NA", "0", "NA", "0", "0", "NA", "NA", "NA", "0", "NA", "NA", "NA", "0", "NA", "NA", "0", "NA", "1", "Elias Kachunga", "Huddersfield Town", "attacking half", "0", "NA", "NA", "0", "0", "NA", "NA", "NA", "0", "NA", "NA", "NA", "NA", "1", "31", "0", "NA", "NA", "34"], ["480844", "Foul by Toby Alderweireld (Tottenham Hotspur).", "34'", "Huddersfield Town", "0", "0", "0", "0", "0", "0", "NA", "NA", "NA", "NA", "NA", "NA", "NA", "1", "Toby Alderweireld", "Tottenham Hotspur", "0", "NA", "0", "0", "NA", "NA", "NA", "0", "NA", "NA", "NA", "0", "NA", "NA", "0", "NA", "0", "NA", "NA", "NA", "0", "NA", "NA", "0", "0", "NA", "NA", "NA", "0", "NA", "NA", "NA", "NA", "1", "32", "0", "NA", "NA", "34"], ["480844", "Offside, Tottenham Hotspur. Ben Davies tries a through ball, but Harry Kane is caught offside.", "36'", "Huddersfield Town", "0", "0", "0", "0", "0", "0", "NA", "NA", "NA", "NA", "NA", "NA", "NA", "0", "NA", "NA", "0", "NA", "0", "1", "Tottenham Hotspur", "Harry Kane", "Ben Davies", "0", "NA", "NA", "NA", "0", "NA", "NA", "0", "NA", "0", "NA", "NA", "NA", "0", "NA", "NA", "0", "0", "NA", "NA", "NA", "0", "NA", "NA", "NA", "NA", "1", "33", "0", "NA", "NA", "36"], ["480844", "Dele Alli (Tottenham Hotspur) wins a free kick on the left wing.", "41'", "Huddersfield Town", "0", "0", "0", "0", "0", "0", "NA", "NA", "NA", "NA", "NA", "NA", "NA", "0", "NA", "NA", "0", "NA", "0", "0", "NA", "NA", "NA", "0", "NA", "NA", "NA", "0", "NA", "NA", "0", "NA", "1", "Dele Alli", "Tottenham Hotspur", "NA", "0", "NA", "NA", "0", "0", "NA", "NA", "NA", "0", "NA", "NA", "NA", "NA", "1", "34", "0", "NA", "NA", "41"], ["480844", "Foul by Tommy Smith (Huddersfield Town).", "41'", "Huddersfield Town", "0", "0", "0", "0", "0", "0", "NA", "NA", "NA", "NA", "NA", "NA", "NA", "1", "Tommy Smith", "Huddersfield Town", "0", "NA", "0", "0", "NA", "NA", "NA", "0", "NA", "NA", "NA", "0", "NA", "NA", "0", "NA", "0", "NA", "NA", "NA", "0", "NA", "NA", "0", "0", "NA", "NA", "NA", "0", "NA", "NA", "NA", "NA", "1", "35", "0", "NA", "NA", "41"], ["480844", "Corner,  Tottenham Hotspur. Conceded by Tommy Smith.", "41'", "Huddersfield Town", "0", "0", "0", "0", "0", "0", "NA", "NA", "NA", "NA", "NA", "NA", "NA", "0", "NA", "NA", "0", "NA", "0", "0", "NA", "NA", "NA", "0", "NA", "NA", "NA", "0", "NA", "NA", "0", "NA", "0", "NA", "NA", "NA", "1", "Tottenham Hotspur", "Tommy Smith", "0", "0", "NA", "NA", "NA", "0", "NA", "NA", "NA", "NA", "1", "36", "0", "NA", "NA", "41"], ["480844", "Laurent Depoitre (Huddersfield Town) hits the bar with a right footed shot from outside the box.", "43'", "Huddersfield Town", "0", "0", "0", "0", "0", "0", "NA", "NA", "NA", "NA", "NA", "NA", "NA", "0", "NA", "NA", "0", "NA", "0", "0", "NA", "NA", "NA", "0", "NA", "NA", "NA", "0", "NA", "NA", "0", "NA", "0", "NA", "NA", "NA", "0", "NA", "NA", "0", "0", "NA", "NA", "NA", "0", "NA", "NA", "NA", "NA", "1", "37", "0", "NA", "NA", "43"], ["480844", "Corner,  Tottenham Hotspur. Conceded by Zanka.", "45'", "Huddersfield Town", "0", "0", "0", "0", "0", "0", "NA", "NA", "NA", "NA", "NA", "NA", "NA", "0", "NA", "NA", "0", "NA", "0", "0", "NA", "NA", "NA", "0", "NA", "NA", "NA", "0", "NA", "NA", "0", "NA", "0", "NA", "NA", "NA", "1", "Tottenham Hotspur", "Zanka", "0", "0", "NA", "NA", "NA", "0", "NA", "NA", "NA", "NA", "1", "38", "0", "NA", "NA", "45"], ["480844", "Attempt missed. Ben Davies (Tottenham Hotspur) left footed shot from the left side of the box misses to the right.", "45'+2'", "Huddersfield Town", "0", "0", "0", "0", "1", "0", "missed", "Ben Davies", "Tottenham Hotspur", "left", "the left side of the box", "right", "NA", "0", "NA", "NA", "0", "NA", "0", "0", "NA", "NA", "NA", "0", "NA", "NA", "NA", "0", "NA", "NA", "0", "NA", "0", "NA", "NA", "NA", "0", "NA", "NA", "0", "0", "NA", "NA", "NA", "0", "NA", "NA", "NA", "NA", "1", "39", "1", "NA", "NA", "47"], ["480844", "First Half ends, Huddersfield Town 0, Tottenham Hotspur 3.", "45'+2'", "Huddersfield Town", "0", "1", "0", "0", "0", "0", "NA", "NA", "NA", "NA", "NA", "NA", "NA", "0", "NA", "NA", "0", "NA", "0", "0", "NA", "NA", "NA", "0", "NA", "NA", "NA", "0", "NA", "NA", "0", "NA", "0", "NA", "NA", "NA", "0", "NA", "NA", "0", "0", "NA", "NA", "NA", "0", "NA", "NA", "NA", "NA", "1", "40", "1", "NA", "NA", "47"], ["480844", "Second Half begins Huddersfield Town 0, Tottenham Hotspur 3.", "45'", "Huddersfield Town", "0", "0", "0", "1", "0", "0", "NA", "NA", "NA", "NA", "NA", "NA", "NA", "0", "NA", "NA", "0", "NA", "0", "0", "NA", "NA", "NA", "0", "NA", "NA", "NA", "0", "NA", "NA", "0", "NA", "0", "NA", "NA", "NA", "0", "NA", "NA", "0", "0", "NA", "NA", "NA", "0", "NA", "NA", "NA", "NA", "2", "41", "0", "NA", "NA", "45"], ["480844", "Corner,  Tottenham Hotspur. Conceded by Jonathan Hogg.", "49'", "Huddersfield Town", "0", "0", "0", "0", "0", "0", "NA", "NA", "NA", "NA", "NA", "NA", "NA", "0", "NA", "NA", "0", "NA", "0", "0", "NA", "NA", "NA", "0", "NA", "NA", "NA", "0", "NA", "NA", "0", "NA", "0", "NA", "NA", "NA", "1", "Tottenham Hotspur", "Jonathan Hogg", "0", "0", "NA", "NA", "NA", "0", "NA", "NA", "NA", "NA", "2", "42", "0", "NA", "NA", "49"], ["480844", "Delay in match Kieran Trippier (Tottenham Hotspur) because of an injury.", "53'", "Huddersfield Town", "0", "0", "0", "0", "0", "0", "NA", "NA", "NA", "NA", "NA", "NA", "NA", "0", "NA", "NA", "0", "NA", "0", "0", "NA", "NA", "NA", "0", "NA", "NA", "NA", "0", "NA", "NA", "1", "Tottenham Hotspur", "0", "NA", "NA", "NA", "0", "NA", "NA", "0", "0", "NA", "NA", "NA", "0", "NA", "NA", "NA", "NA", "2", "43", "0", "NA", "NA", "53"], ["480844", "Delay over. They are ready to continue.", "55'", "Huddersfield Town", "0", "0", "0", "0", "0", "0", "NA", "NA", "NA", "NA", "NA", "NA", "NA", "0", "NA", "NA", "0", "NA", "0", "0", "NA", "NA", "NA", "0", "NA", "NA", "NA", "0", "NA", "NA", "0", "NA", "0", "NA", "NA", "NA", "0", "NA", "NA", "0", "0", "NA", "NA", "NA", "0", "NA", "NA", "NA", "NA", "2", "44", "0", "NA", "NA", "55"], ["480844", "Dele Alli (Tottenham Hotspur) has gone down, but that's a dive.", "58'", "Huddersfield Town", "0", "0", "0", "0", "0", "0", "NA", "NA", "NA", "NA", "NA", "NA", "NA", "0", "NA", "NA", "0", "NA", "0", "0", "NA", "NA", "NA", "0", "NA", "NA", "NA", "0", "NA", "NA", "0", "NA", "0", "NA", "NA", "NA", "0", "NA", "NA", "0", "0", "NA", "NA", "NA", "0", "NA", "NA", "NA", "NA", "2", "45", "0", "NA", "NA", "58"], ["480844", "Dele Alli (Tottenham Hotspur) is shown the yellow card.", "58'", "Huddersfield Town", "0", "0", "0", "0", "0", "0", "NA", "NA", "NA", "NA", "NA", "NA", "NA", "0", "NA", "NA", "0", "NA", "0", "0", "NA", "NA", "NA", "1", "yellow", "Dele Alli", "Tottenham Hotspur", "0", "NA", "NA", "0", "NA", "0", "NA", "NA", "NA", "0", "NA", "NA", "0", "0", "NA", "NA", "NA", "0", "NA", "NA", "NA", "NA", "2", "46", "0", "NA", "NA", "58"], ["480844", "Attempt missed. Jan Vertonghen (Tottenham Hotspur) left footed shot from outside the box is too high.", "60'", "Huddersfield Town", "0", "0", "0", "0", "1", "0", "missed", "Jan Vertonghen", "Tottenham Hotspur", "left", "outside the box", "too high", "NA", "0", "NA", "NA", "0", "NA", "0", "0", "NA", "NA", "NA", "0", "NA", "NA", "NA", "0", "NA", "NA", "0", "NA", "0", "NA", "NA", "NA", "0", "NA", "NA", "0", "0", "NA", "NA", "NA", "0", "NA", "NA", "NA", "NA", "2", "47", "0", "NA", "NA", "60"], ["480844", "Substitution, Huddersfield Town. Scott Malone replaces Chris Löwe.", "60'", "Huddersfield Town", "0", "0", "0", "0", "0", "0", "NA", "NA", "NA", "NA", "NA", "NA", "NA", "0", "NA", "NA", "0", "NA", "0", "0", "NA", "NA", "NA", "0", "NA", "NA", "NA", "0", "NA", "NA", "0", "NA", "0", "NA", "NA", "NA", "0", "NA", "NA", "1", "0", "Huddersfield Town", "Scott Malone", "Chris Löwe", "0", "NA", "NA", "NA", "NA", "2", "48", "0", "NA", "NA", "60"], ["480844", "Substitution, Huddersfield Town. Philip Billing replaces Aaron Mooy.", "61'", "Huddersfield Town", "0", "0", "0", "0", "0", "0", "NA", "NA", "NA", "NA", "NA", "NA", "NA", "0", "NA", "NA", "0", "NA", "0", "0", "NA", "NA", "NA", "0", "NA", "NA", "NA", "0", "NA", "NA", "0", "NA", "0", "NA", "NA", "NA", "0", "NA", "NA", "1", "0", "Huddersfield Town", "Philip Billing", "Aaron Mooy", "0", "NA", "NA", "NA", "NA", "2", "49", "0", "NA", "NA", "61"], ["480844", "Foul by Elias Kachunga (Huddersfield Town).", "65'", "Huddersfield Town", "0", "0", "0", "0", "0", "0", "NA", "NA", "NA", "NA", "NA", "NA", "NA", "1", "Elias Kachunga", "Huddersfield Town", "0", "NA", "0", "0", "NA", "NA", "NA", "0", "NA", "NA", "NA", "0", "NA", "NA", "0", "NA", "0", "NA", "NA", "NA", "0", "NA", "NA", "0", "0", "NA", "NA", "NA", "0", "NA", "NA", "NA", "NA", "2", "50", "0", "NA", "NA", "65"], ["480844", "Jan Vertonghen (Tottenham Hotspur) wins a free kick in the defensive half.", "65'", "Huddersfield Town", "0", "0", "0", "0", "0", "0", "NA", "NA", "NA", "NA", "NA", "NA", "NA", "0", "NA", "NA", "0", "NA", "0", "0", "NA", "NA", "NA", "0", "NA", "NA", "NA", "0", "NA", "NA", "0", "NA", "1", "Jan Vertonghen", "Tottenham Hotspur", "defensive half", "0", "NA", "NA", "0", "0", "NA", "NA", "NA", "0", "NA", "NA", "NA", "NA", "2", "51", "0", "NA", "NA", "65"], ["480844", "Elias Kachunga (Huddersfield Town) is shown the yellow card for a bad foul.", "65'", "Huddersfield Town", "0", "0", "0", "0", "0", "0", "NA", "NA", "NA", "NA", "NA", "NA", "NA", "0", "NA", "NA", "0", "NA", "0", "0", "NA", "NA", "NA", "1", "yellow", "Elias Kachunga", "Huddersfield Town", "0", "NA", "NA", "0", "NA", "0", "NA", "NA", "NA", "0", "NA", "NA", "0", "0", "NA", "NA", "NA", "0", "NA", "NA", "NA", "NA", "2", "52", "0", "NA", "NA", "65"], ["480844", "Hand ball by Elias Kachunga (Huddersfield Town).", "66'", "Huddersfield Town", "0", "0", "0", "0", "0", "0", "NA", "NA", "NA", "NA", "NA", "NA", "NA", "0", "NA", "NA", "0", "NA", "0", "0", "NA", "NA", "NA", "0", "NA", "NA", "NA", "0", "NA", "NA", "0", "NA", "0", "NA", "NA", "NA", "0", "NA", "NA", "0", "0", "NA", "NA", "NA", "0", "NA", "NA", "NA", "NA", "2", "53", "0", "NA", "NA", "66"], ["480844", "Offside, Huddersfield Town. Scott Malone tries a through ball, but Rajiv van La Parra is caught offside.", "67'", "Huddersfield Town", "0", "0", "0", "0", "0", "0", "NA", "NA", "NA", "NA", "NA", "NA", "NA", "0", "NA", "NA", "0", "NA", "0", "1", "Huddersfield Town", "NA", "Scott Malone", "0", "NA", "NA", "NA", "0", "NA", "NA", "0", "NA", "0", "NA", "NA", "NA", "0", "NA", "NA", "0", "0", "NA", "NA", "NA", "0", "NA", "NA", "NA", "NA", "2", "54", "0", "NA", "NA", "67"], ["480844", "Attempt saved. Christian Eriksen (Tottenham Hotspur) right footed shot from the left side of the box is saved in the centre of the goal. Assisted by Ben Davies.", "67'", "Huddersfield Town", "0", "0", "0", "0", "1", "0", "saved", "Christian Eriksen", "Tottenham Hotspur", "right", "the left side of the box", "the centre of the goal", "Ben Davies", "0", "NA", "NA", "0", "NA", "0", "0", "NA", "NA", "NA", "0", "NA", "NA", "NA", "0", "NA", "NA", "0", "NA", "0", "NA", "NA", "NA", "0", "NA", "NA", "0", "0", "NA", "NA", "NA", "0", "NA", "NA", "NA", "NA", "2", "55", "0", "NA", "NA", "67"], ["480844", "Offside, Huddersfield Town. Zanka tries a through ball, but Laurent Depoitre is caught offside.", "70'", "Huddersfield Town", "0", "0", "0", "0", "0", "0", "NA", "NA", "NA", "NA", "NA", "NA", "NA", "0", "NA", "NA", "0", "NA", "0", "1", "Huddersfield Town", "Laurent Depoitre", "Zanka", "0", "NA", "NA", "NA", "0", "NA", "NA", "0", "NA", "0", "NA", "NA", "NA", "0", "NA", "NA", "0", "0", "NA", "NA", "NA", "0", "NA", "NA", "NA", "NA", "2", "56", "0", "NA", "NA", "70"], ["480844", "Corner,  Tottenham Hotspur. Conceded by Zanka.", "73'", "Huddersfield Town", "0", "0", "0", "0", "0", "0", "NA", "NA", "NA", "NA", "NA", "NA", "NA", "0", "NA", "NA", "0", "NA", "0", "0", "NA", "NA", "NA", "0", "NA", "NA", "NA", "0", "NA", "NA", "0", "NA", "0", "NA", "NA", "NA", "1", "Tottenham Hotspur", "Zanka", "0", "0", "NA", "NA", "NA", "0", "NA", "NA", "NA", "NA", "2", "57", "0", "NA", "NA", "73"], ["480844", "Attempt blocked. Eric Dier (Tottenham Hotspur) right footed shot from outside the box is blocked. Assisted by Harry Kane.", "74'", "Huddersfield Town", "0", "0", "0", "0", "1", "0", "blocked", "Eric Dier", "Tottenham Hotspur", "right", "outside the box", "NA", "Harry Kane", "0", "NA", "NA", "0", "NA", "0", "0", "NA", "NA", "NA", "0", "NA", "NA", "NA", "0", "NA", "NA", "0", "NA", "0", "NA", "NA", "NA", "0", "NA", "NA", "0", "0", "NA", "NA", "NA", "0", "NA", "NA", "NA", "NA", "2", "58", "0", "NA", "NA", "74"], ["480844", "Corner,  Tottenham Hotspur. Conceded by Christopher Schindler.", "74'", "Huddersfield Town", "0", "0", "0", "0", "0", "0", "NA", "NA", "NA", "NA", "NA", "NA", "NA", "0", "NA", "NA", "0", "NA", "0", "0", "NA", "NA", "NA", "0", "NA", "NA", "NA", "0", "NA", "NA", "0", "NA", "0", "NA", "NA", "NA", "1", "Tottenham Hotspur", "Christopher Schindler", "0", "0", "NA", "NA", "NA", "0", "NA", "NA", "NA", "NA", "2", "59", "0", "NA", "NA", "74"], ["480844", "Substitution, Tottenham Hotspur. Moussa Sissoko replaces Christian Eriksen.", "75'", "Huddersfield Town", "0", "0", "0", "0", "0", "0", "NA", "NA", "NA", "NA", "NA", "NA", "NA", "0", "NA", "NA", "0", "NA", "0", "0", "NA", "NA", "NA", "0", "NA", "NA", "NA", "0", "NA", "NA", "0", "NA", "0", "NA", "NA", "NA", "0", "NA", "NA", "1", "0", "Tottenham Hotspur", "Moussa Sissoko", "Christian Eriksen", "0", "NA", "NA", "NA", "NA", "2", "60", "0", "NA", "NA", "75"], ["480844", "Offside, Huddersfield Town. Zanka tries a through ball, but Tommy Smith is caught offside.", "76'", "Huddersfield Town", "0", "0", "0", "0", "0", "0", "NA", "NA", "NA", "NA", "NA", "NA", "NA", "0", "NA", "NA", "0", "NA", "0", "1", "Huddersfield Town", "Tommy Smith", "Zanka", "0", "NA", "NA", "NA", "0", "NA", "NA", "0", "NA", "0", "NA", "NA", "NA", "0", "NA", "NA", "0", "0", "NA", "NA", "NA", "0", "NA", "NA", "NA", "NA", "2", "61", "0", "NA", "NA", "76"], ["480844", "Substitution, Huddersfield Town. Dean Whitehead replaces Jonathan Hogg.", "82'", "Huddersfield Town", "0", "0", "0", "0", "0", "0", "NA", "NA", "NA", "NA", "NA", "NA", "NA", "0", "NA", "NA", "0", "NA", "0", "0", "NA", "NA", "NA", "0", "NA", "NA", "NA", "0", "NA", "NA", "0", "NA", "0", "NA", "NA", "NA", "0", "NA", "NA", "1", "0", "Huddersfield Town", "Dean Whitehead", "Jonathan Hogg", "0", "NA", "NA", "NA", "NA", "2", "62", "0", "NA", "NA", "82"], ["480844", "Substitution, Tottenham Hotspur. Kyle Walker-Peters replaces Kieran Trippier.", "82'", "Huddersfield Town", "0", "0", "0", "0", "0", "0", "NA", "NA", "NA", "NA", "NA", "NA", "NA", "0", "NA", "NA", "0", "NA", "0", "0", "NA", "NA", "NA", "0", "NA", "NA", "NA", "0", "NA", "NA", "0", "NA", "0", "NA", "NA", "NA", "0", "NA", "NA", "1", "0", "Tottenham Hotspur", "Kyle Walker-Peters", "Kieran Trippier", "0", "NA", "NA", "NA", "NA", "2", "63", "0", "NA", "NA", "82"], ["480844", "Attempt blocked. Rajiv van La Parra (Huddersfield Town) right footed shot from outside the box is blocked. Assisted by Laurent Depoitre.", "85'", "Huddersfield Town", "0", "0", "0", "0", "1", "0", "blocked", "NA", "Huddersfield Town", "right", "outside the box", "NA", "Laurent Depoitre", "0", "NA", "NA", "0", "NA", "0", "0", "NA", "NA", "NA", "0", "NA", "NA", "NA", "0", "NA", "NA", "0", "NA", "0", "NA", "NA", "NA", "0", "NA", "NA", "0", "0", "NA", "NA", "NA", "0", "NA", "NA", "NA", "NA", "2", "64", "0", "NA", "NA", "85"], ["480844", "Attempt saved. Moussa Sissoko (Tottenham Hotspur) left footed shot from the right side of the box is saved in the centre of the goal. Assisted by Dele Alli.", "86'", "Huddersfield Town", "0", "0", "0", "0", "1", "0", "saved", "Moussa Sissoko", "Tottenham Hotspur", "left", "the right side of the box", "the centre of the goal", "Dele Alli", "0", "NA", "NA", "0", "NA", "0", "0", "NA", "NA", "NA", "0", "NA", "NA", "NA", "0", "NA", "NA", "0", "NA", "0", "NA", "NA", "NA", "0", "NA", "NA", "0", "0", "NA", "NA", "NA", "0", "NA", "NA", "NA", "NA", "2", "65", "0", "NA", "NA", "86"], ["480844", "Substitution, Tottenham Hotspur. Son Heung-Min replaces Harry Kane.", "87'", "Huddersfield Town", "0", "0", "0", "0", "0", "0", "NA", "NA", "NA", "NA", "NA", "NA", "NA", "0", "NA", "NA", "0", "NA", "0", "0", "NA", "NA", "NA", "0", "NA", "NA", "NA", "0", "NA", "NA", "0", "NA", "0", "NA", "NA", "NA", "0", "NA", "NA", "1", "0", "Tottenham Hotspur", "Son Heung-Min", "Harry Kane", "0", "NA", "NA", "NA", "NA", "2", "66", "0", "NA", "NA", "87"], ["480844", "Foul by Harry Winks (Tottenham Hotspur).", "88'", "Huddersfield Town", "0", "0", "0", "0", "0", "0", "NA", "NA", "NA", "NA", "NA", "NA", "NA", "1", "Harry Winks", "Tottenham Hotspur", "0", "NA", "0", "0", "NA", "NA", "NA", "0", "NA", "NA", "NA", "0", "NA", "NA", "0", "NA", "0", "NA", "NA", "NA", "0", "NA", "NA", "0", "0", "NA", "NA", "NA", "0", "NA", "NA", "NA", "NA", "2", "67", "0", "NA", "NA", "88"], ["480844", "Rajiv van La Parra (Huddersfield Town) wins a free kick on the right wing.", "88'", "Huddersfield Town", "0", "0", "0", "0", "0", "0", "NA", "NA", "NA", "NA", "NA", "NA", "NA", "0", "NA", "NA", "0", "NA", "0", "0", "NA", "NA", "NA", "0", "NA", "NA", "NA", "0", "NA", "NA", "0", "NA", "1", "NA", "Huddersfield Town", "NA", "0", "NA", "NA", "0", "0", "NA", "NA", "NA", "0", "NA", "NA", "NA", "NA", "2", "68", "0", "NA", "NA", "88"], ["480844", "Corner,  Huddersfield Town. Conceded by Ben Davies.", "89'", "Huddersfield Town", "0", "0", "0", "0", "0", "0", "NA", "NA", "NA", "NA", "NA", "NA", "NA", "0", "NA", "NA", "0", "NA", "0", "0", "NA", "NA", "NA", "0", "NA", "NA", "NA", "0", "NA", "NA", "0", "NA", "0", "NA", "NA", "NA", "1", "Huddersfield Town", "Ben Davies", "0", "0", "NA", "NA", "NA", "0", "NA", "NA", "NA", "NA", "2", "69", "0", "NA", "NA", "89"], ["480844", "Goal!  Huddersfield Town 0, Tottenham Hotspur 4. Moussa Sissoko (Tottenham Hotspur) left footed shot from the centre of the box to the bottom right corner. Assisted by Ben Davies.", "90'+1'", "Huddersfield Town", "0", "0", "0", "0", "1", "0", "goal", "Moussa Sissoko", "Tottenham Hotspur", "left", "the centre of the box", "bottom right corner", "Ben Davies", "0", "NA", "NA", "0", "NA", "0", "0", "NA", "NA", "NA", "0", "NA", "NA", "NA", "0", "NA", "NA", "0", "NA", "0", "NA", "NA", "NA", "0", "NA", "NA", "0", "0", "NA", "NA", "NA", "0", "NA", "NA", "NA", "NA", "2", "70", "1", "NA", "NA", "91"], ["480844", "Attempt missed. Rajiv van La Parra (Huddersfield Town) right footed shot from outside the box misses to the left. Assisted by Zanka.", "90'+2'", "Huddersfield Town", "0", "0", "0", "0", "1", "0", "missed", "NA", "Huddersfield Town", "right", "outside the box", "left", "Zanka", "0", "NA", "NA", "0", "NA", "0", "0", "NA", "NA", "NA", "0", "NA", "NA", "NA", "0", "NA", "NA", "0", "NA", "0", "NA", "NA", "NA", "0", "NA", "NA", "0", "0", "NA", "NA", "NA", "0", "NA", "NA", "NA", "NA", "2", "71", "1", "NA", "NA", "92"], ["480844", "Second Half ends, Huddersfield Town 0, Tottenham Hotspur 4.", "90'+4'", "Huddersfield Town", "0", "1", "0", "0", "0", "0", "NA", "NA", "NA", "NA", "NA", "NA", "NA", "0", "NA", "NA", "0", "NA", "0", "0", "NA", "NA", "NA", "0", "NA", "NA", "NA", "0", "NA", "NA", "0", "NA", "0", "NA", "NA", "NA", "0", "NA", "NA", "0", "0", "NA", "NA", "NA", "0", "NA", "NA", "NA", "NA", "2", "72", "1", "NA", "NA", "94"], ["480844", "Match ends, Huddersfield Town 0, Tottenham Hotspur 4.", "90'+4'", "Huddersfield Town", "0", "0", "1", "0", "0", "0", "NA", "NA", "NA", "NA", "NA", "NA", "NA", "0", "NA", "NA", "0", "NA", "0", "0", "NA", "NA", "NA", "0", "NA", "NA", "NA", "0", "NA", "NA", "0", "NA", "0", "NA", "NA", "NA", "0", "NA", "NA", "0", "0", "NA", "NA", "NA", "0", "NA", "NA", "NA", "NA", "2", "73", "1", "NA", "NA", "94"]], "Lineup": {"Home Player 9": "Christopher Schindler", "Home Player 8": "Aaron Mooy", "Home Player 5": "Elias Kachunga", "Home Player 4": "Mathias Jorgensen", "Home Player 7": "Chris Lowe", "Home Player 6": "Jonas Lossl", "Home Player 1": "Laurent Depoitre", "Home Player 3": "Tom Ince", "Home Player 2": "Jonathan Hogg", "Away Player 10": "Jan Vertonghen", "Away Player 11": "Harry Winks", "Away Player 8": "Davinson Sanchez", "Away Player 9": "Kieran Trippier", "Away Player 1": "Toby Alderweireld", "Away Player 2": "Dele Alli", "Away Player 3": "Ben Davies", "Away Player 4": "Eric Dier", "Away Player 5": "Christian Eriksen", "Away Player 6": "Harry Kane", "Away Player 7": "Hugo Lloris", "Game ID": "g_1_I3qrbxrn", "Home Player 11": "Rajiv van La Parra", "Home Player 10": "Tom Smith"}}