{"Stats": {"Full Time Result": "H", "Away Team Corners": 4, "Referee": "C Pawson", "Home Team Fouls Committed": 5, "Away Team Shots": 9, "Away Team Red Cards": 0, "Home Team Red Cards": 0, "Half Time Away Team Goals": 0, "Full Time Home Team Goals": 2, "Away Team Yellow Cards": 0, "Away Team Shots on Target": 2, "Half Time Home Team Goals": 0, "Half Time Result": "D", "Away Team Fouls Committed": 12, "Home Team Yellow Cards": 0, "Home Team Shots": 15, "Div": "E0", "Home Team Corners": 6, "Home Team Shots on Target": 3, "Full Time Away Team Goals": 1}, "Description": "Andrew Surman (Bournemouth) wins a free kick in the defensive half. at minute 3. Foul by Tomer Hemed (Brighton and Hove Albion). at minute 3. Attempt missed. Anthony Knockaert (Brighton and Hove Albion) left footed shot from outside the box misses to the right. Assisted by Pascal Groß. at minute 9. Foul by Davy Pröpper (Brighton and Hove Albion). at minute 10. Harry Arter (Bournemouth) wins a free kick on the right wing. at minute 10. Attempt missed. Harry Arter (Bournemouth) left footed shot from outside the box is too high. Assisted by Ryan Fraser. at minute 11. Attempt blocked. Joshua King (Bournemouth) right footed shot from outside the box is blocked. at minute 14. Attempt missed. Marc Pugh (Bournemouth) left footed shot from the left side of the box is too high. Assisted by Charlie Daniels. at minute 20. Andrew Surman (Bournemouth) wins a free kick in the defensive half. at minute 21. Foul by Tomer Hemed (Brighton and Hove Albion). at minute 21. Adam Smith (Bournemouth) wins a free kick on the right wing. at minute 22. Foul by Solly March (Brighton and Hove Albion). at minute 22. Attempt saved. Charlie Daniels (Bournemouth) left footed shot from outside the box is saved in the top right corner. at minute 23. Foul by Adam Smith (Bournemouth). at minute 24. Solly March (Brighton and Hove Albion) wins a free kick on the left wing. at minute 24. Attempt missed. Davy Pröpper (Brighton and Hove Albion) right footed shot from outside the box is just a bit too high. at minute 30. Attempt missed. Jermain Defoe (Bournemouth) right footed shot from outside the box is close, but misses to the right. Assisted by Marc Pugh. at minute 30. Charlie Daniels (Bournemouth) wins a free kick in the defensive half. at minute 32. Foul by Tomer Hemed (Brighton and Hove Albion). at minute 32. Corner,  Bournemouth. Conceded by Liam Rosenior. at minute 35. Adam Smith (Bournemouth) wins a free kick on the left wing. at minute 39. Foul by Anthony Knockaert (Brighton and Hove Albion). at minute 39. Foul by Harry Arter (Bournemouth). at minute 42. Tomer Hemed (Brighton and Hove Albion) wins a free kick in the defensive half. at minute 42. Attempt blocked. Joshua King (Bournemouth) right footed shot from outside the box is blocked. at minute 44. Attempt blocked. Ryan Fraser (Bournemouth) left footed shot from outside the box is blocked. Assisted by Jermain Defoe. at minute 45. First Half ends, Bournemouth 0, Brighton and Hove Albion 0. at minute 46. Second Half begins Bournemouth 0, Brighton and Hove Albion 0. at minute 45. Corner,  Brighton and Hove Albion. Conceded by Adam Smith. at minute 51. Attempt blocked. Shane Duffy (Brighton and Hove Albion) header from the right side of the six yard box is blocked. Assisted by Pascal Groß with a cross. at minute 51. Attempt blocked. Davy Pröpper (Brighton and Hove Albion) header from the centre of the box is blocked. at minute 51. Corner,  Brighton and Hove Albion. Conceded by Andrew Surman. at minute 51. Attempt blocked. Shane Duffy (Brighton and Hove Albion) header from the centre of the box is blocked. Assisted by Pascal Groß with a cross. at minute 52. Dale Stephens (Brighton and Hove Albion) hits the bar with a header from very close range. Assisted by Shane Duffy following a corner. at minute 52. Attempt blocked. Harry Arter (Bournemouth) left footed shot from outside the box is blocked. Assisted by Marc Pugh. at minute 53. Corner,  Bournemouth. Conceded by Dale Stephens. at minute 53. Corner,  Bournemouth. Conceded by Solly March. at minute 53. Attempt missed. Marc Pugh (Bournemouth) right footed shot from outside the box is too high following a corner. at minute 54. Goal!  Bournemouth 0, Brighton and Hove Albion 1. Solly March (Brighton and Hove Albion) header from very close range to the bottom right corner. Assisted by Pascal Groß with a cross. at minute 55. Substitution, Bournemouth. Jordon Ibe replaces Ryan Fraser. at minute 65. Attempt blocked. Marc Pugh (Bournemouth) right footed shot from outside the box is blocked. Assisted by Andrew Surman. at minute 66. Goal!  Bournemouth 1, Brighton and Hove Albion 1. Andrew Surman (Bournemouth) left footed shot from the centre of the box to the bottom left corner. Assisted by Jordon Ibe with a through ball. at minute 67. Corner,  Brighton and Hove Albion. Conceded by Simon Francis. at minute 68. Attempt blocked. Jordon Ibe (Bournemouth) right footed shot from the centre of the box is blocked. at minute 71. Corner,  Bournemouth. Conceded by Lewis Dunk. at minute 71. Delay in match Pascal Groß (Brighton and Hove Albion) because of an injury. at minute 72. Delay over. They are ready to continue. at minute 73. Goal!  Bournemouth 2, Brighton and Hove Albion 1. Jermain Defoe (Bournemouth) right footed shot from the centre of the box to the bottom left corner. Assisted by Jordon Ibe with a through ball following a corner. at minute 73. Attempt missed. Liam Rosenior (Brighton and Hove Albion) right footed shot from outside the box is too high. at minute 75. Hand ball by Jermain Defoe (Bournemouth). at minute 76. Substitution, Brighton and Hove Albion. José Izquierdo replaces Anthony Knockaert. at minute 76. Substitution, Brighton and Hove Albion. Glenn Murray replaces Pascal Groß. at minute 77. Foul by Shane Duffy (Brighton and Hove Albion). at minute 77. Jermain Defoe (Bournemouth) wins a free kick in the defensive half. at minute 77. Substitution, Bournemouth. Benik Afobe replaces Jermain Defoe. at minute 78. Benik Afobe (Bournemouth) wins a free kick on the left wing. at minute 79. Foul by Solly March (Brighton and Hove Albion). at minute 79. Corner,  Bournemouth. Conceded by Liam Rosenior. at minute 79. Attempt blocked. Simon Francis (Bournemouth) header from the centre of the box is blocked. Assisted by Charlie Daniels with a cross. at minute 80. Dale Stephens (Brighton and Hove Albion) wins a free kick in the defensive half. at minute 81. Foul by Benik Afobe (Bournemouth). at minute 81. Foul by Benik Afobe (Bournemouth). at minute 85. Shane Duffy (Brighton and Hove Albion) wins a free kick in the defensive half. at minute 85. Corner,  Brighton and Hove Albion. Conceded by Simon Francis. at minute 86. Attempt missed. Liam Rosenior (Brighton and Hove Albion) right footed shot from outside the box is too high. Assisted by Solly March with a cross following a corner. at minute 86. Foul by Davy Pröpper (Brighton and Hove Albion). at minute 87. Jordon Ibe (Bournemouth) wins a free kick in the defensive half. at minute 87. Corner,  Bournemouth. Conceded by Liam Rosenior. at minute 89. Foul by Davy Pröpper (Brighton and Hove Albion). at minute 90. Harry Arter (Bournemouth) wins a free kick on the left wing. at minute 90. Foul by Lewis Dunk (Brighton and Hove Albion). at minute 91. Joshua King (Bournemouth) wins a free kick in the attacking half. at minute 91. Attempt missed. Jordon Ibe (Bournemouth) right footed shot from outside the box is close, but misses to the right from a direct free kick. at minute 91. Offside, Brighton and Hove Albion. Solly March tries a through ball, but Shane Duffy is caught offside. at minute 92. Substitution, Bournemouth. Dan Gosling replaces Joshua King. at minute 93. Offside, Bournemouth. Nathan Aké tries a through ball, but Benik Afobe is caught offside. at minute 94. Foul by Shane Duffy (Brighton and Hove Albion). at minute 95. Marc Pugh (Bournemouth) wins a free kick in the defensive half. at minute 95. Second Half ends, Bournemouth 2, Brighton and Hove Albion 1. at minute 96. Match ends, Bournemouth 2, Brighton and Hove Albion 1. at minute 96. ", "Home Team": "AFC Bournemouth", "Away Team": "Brighton & Hove Albion", "Date": "2017-09-15", "Commentary": [["480857", "First Half begins.", "-", "AFC Bournemouth", "0", "0", "0", "1", "0", "0", "NA", "NA", "NA", "NA", "NA", "NA", "NA", "0", "NA", "NA", "0", "NA", "0", "0", "NA", "NA", "NA", "0", "NA", "NA", "NA", "0", "NA", "NA", "0", "NA", "0", "NA", "NA", "NA", "0", "NA", "NA", "0", "0", "NA", "NA", "NA", "0", "NA", "NA", "NA", "NA", "1", "1", "0", "NA", "NA", "NA"], ["480857", "Lineups are announced and players are warming up.", "-", "AFC Bournemouth", "0", "0", "0", "0", "0", "0", "NA", "NA", "NA", "NA", "NA", "NA", "NA", "0", "NA", "NA", "0", "NA", "0", "0", "NA", "NA", "NA", "0", "NA", "NA", "NA", "0", "NA", "NA", "0", "NA", "0", "NA", "NA", "NA", "0", "NA", "NA", "0", "0", "NA", "NA", "NA", "0", "NA", "NA", "NA", "NA", "1", "2", "0", "NA", "NA", "NA"], ["480857", "Andrew Surman (Bournemouth) wins a free kick in the defensive half.", "3'", "AFC Bournemouth", "0", "0", "0", "0", "0", "0", "NA", "NA", "NA", "NA", "NA", "NA", "NA", "0", "NA", "NA", "0", "NA", "0", "0", "NA", "NA", "NA", "0", "NA", "NA", "NA", "0", "NA", "NA", "0", "NA", "1", "Andrew Surman", "NA", "defensive half", "0", "NA", "NA", "0", "0", "NA", "NA", "NA", "0", "NA", "NA", "NA", "NA", "1", "3", "0", "NA", "NA", "3"], ["480857", "Foul by Tomer Hemed (Brighton and Hove Albion).", "3'", "AFC Bournemouth", "0", "0", "0", "0", "0", "0", "NA", "NA", "NA", "NA", "NA", "NA", "NA", "1", "Tomer Hemed", "NA", "0", "NA", "0", "0", "NA", "NA", "NA", "0", "NA", "NA", "NA", "0", "NA", "NA", "0", "NA", "0", "NA", "NA", "NA", "0", "NA", "NA", "0", "0", "NA", "NA", "NA", "0", "NA", "NA", "NA", "NA", "1", "4", "0", "NA", "NA", "3"], ["480857", "Attempt missed. Anthony Knockaert (Brighton and Hove Albion) left footed shot from outside the box misses to the right. Assisted by Pascal Groß.", "9'", "AFC Bournemouth", "0", "0", "0", "0", "1", "0", "missed", "NA", "NA", "left", "outside the box", "right", "Pascal Groß", "0", "NA", "NA", "0", "NA", "0", "0", "NA", "NA", "NA", "0", "NA", "NA", "NA", "0", "NA", "NA", "0", "NA", "0", "NA", "NA", "NA", "0", "NA", "NA", "0", "0", "NA", "NA", "NA", "0", "NA", "NA", "NA", "NA", "1", "5", "0", "NA", "NA", "9"], ["480857", "Foul by Davy Pröpper (Brighton and Hove Albion).", "10'", "AFC Bournemouth", "0", "0", "0", "0", "0", "0", "NA", "NA", "NA", "NA", "NA", "NA", "NA", "1", "Davy Pröpper", "NA", "0", "NA", "0", "0", "NA", "NA", "NA", "0", "NA", "NA", "NA", "0", "NA", "NA", "0", "NA", "0", "NA", "NA", "NA", "0", "NA", "NA", "0", "0", "NA", "NA", "NA", "0", "NA", "NA", "NA", "NA", "1", "6", "0", "NA", "NA", "10"], ["480857", "Harry Arter (Bournemouth) wins a free kick on the right wing.", "10'", "AFC Bournemouth", "0", "0", "0", "0", "0", "0", "NA", "NA", "NA", "NA", "NA", "NA", "NA", "0", "NA", "NA", "0", "NA", "0", "0", "NA", "NA", "NA", "0", "NA", "NA", "NA", "0", "NA", "NA", "0", "NA", "1", "Harry Arter", "NA", "NA", "0", "NA", "NA", "0", "0", "NA", "NA", "NA", "0", "NA", "NA", "NA", "NA", "1", "7", "0", "NA", "NA", "10"], ["480857", "Attempt missed. Harry Arter (Bournemouth) left footed shot from outside the box is too high. Assisted by Ryan Fraser.", "11'", "AFC Bournemouth", "0", "0", "0", "0", "1", "0", "missed", "NA", "NA", "left", "outside the box", "too high", "Ryan Fraser", "0", "NA", "NA", "0", "NA", "0", "0", "NA", "NA", "NA", "0", "NA", "NA", "NA", "0", "NA", "NA", "0", "NA", "0", "NA", "NA", "NA", "0", "NA", "NA", "0", "0", "NA", "NA", "NA", "0", "NA", "NA", "NA", "NA", "1", "8", "0", "NA", "NA", "11"], ["480857", "Attempt blocked. Joshua King (Bournemouth) right footed shot from outside the box is blocked.", "14'", "AFC Bournemouth", "0", "0", "0", "0", "1", "0", "blocked", "NA", "NA", "right", "outside the box", "NA", "NA", "0", "NA", "NA", "0", "NA", "0", "0", "NA", "NA", "NA", "0", "NA", "NA", "NA", "0", "NA", "NA", "0", "NA", "0", "NA", "NA", "NA", "0", "NA", "NA", "0", "0", "NA", "NA", "NA", "0", "NA", "NA", "NA", "NA", "1", "9", "0", "NA", "NA", "14"], ["480857", "Attempt missed. Marc Pugh (Bournemouth) left footed shot from the left side of the box is too high. Assisted by Charlie Daniels.", "20'", "AFC Bournemouth", "0", "0", "0", "0", "1", "0", "missed", "NA", "NA", "left", "the left side of the box", "too high", "Charlie Daniels", "0", "NA", "NA", "0", "NA", "0", "0", "NA", "NA", "NA", "0", "NA", "NA", "NA", "0", "NA", "NA", "0", "NA", "0", "NA", "NA", "NA", "0", "NA", "NA", "0", "0", "NA", "NA", "NA", "0", "NA", "NA", "NA", "NA", "1", "10", "0", "NA", "NA", "20"], ["480857", "Andrew Surman (Bournemouth) wins a free kick in the defensive half.", "21'", "AFC Bournemouth", "0", "0", "0", "0", "0", "0", "NA", "NA", "NA", "NA", "NA", "NA", "NA", "0", "NA", "NA", "0", "NA", "0", "0", "NA", "NA", "NA", "0", "NA", "NA", "NA", "0", "NA", "NA", "0", "NA", "1", "Andrew Surman", "NA", "defensive half", "0", "NA", "NA", "0", "0", "NA", "NA", "NA", "0", "NA", "NA", "NA", "NA", "1", "11", "0", "NA", "NA", "21"], ["480857", "Foul by Tomer Hemed (Brighton and Hove Albion).", "21'", "AFC Bournemouth", "0", "0", "0", "0", "0", "0", "NA", "NA", "NA", "NA", "NA", "NA", "NA", "1", "Tomer Hemed", "NA", "0", "NA", "0", "0", "NA", "NA", "NA", "0", "NA", "NA", "NA", "0", "NA", "NA", "0", "NA", "0", "NA", "NA", "NA", "0", "NA", "NA", "0", "0", "NA", "NA", "NA", "0", "NA", "NA", "NA", "NA", "1", "12", "0", "NA", "NA", "21"], ["480857", "Adam Smith (Bournemouth) wins a free kick on the right wing.", "22'", "AFC Bournemouth", "0", "0", "0", "0", "0", "0", "NA", "NA", "NA", "NA", "NA", "NA", "NA", "0", "NA", "NA", "0", "NA", "0", "0", "NA", "NA", "NA", "0", "NA", "NA", "NA", "0", "NA", "NA", "0", "NA", "1", "Adam Smith", "NA", "NA", "0", "NA", "NA", "0", "0", "NA", "NA", "NA", "0", "NA", "NA", "NA", "NA", "1", "13", "0", "NA", "NA", "22"], ["480857", "Foul by Solly March (Brighton and Hove Albion).", "22'", "AFC Bournemouth", "0", "0", "0", "0", "0", "0", "NA", "NA", "NA", "NA", "NA", "NA", "NA", "1", "Solly March", "NA", "0", "NA", "0", "0", "NA", "NA", "NA", "0", "NA", "NA", "NA", "0", "NA", "NA", "0", "NA", "0", "NA", "NA", "NA", "0", "NA", "NA", "0", "0", "NA", "NA", "NA", "0", "NA", "NA", "NA", "NA", "1", "14", "0", "NA", "NA", "22"], ["480857", "Attempt saved. Charlie Daniels (Bournemouth) left footed shot from outside the box is saved in the top right corner.", "23'", "AFC Bournemouth", "0", "0", "0", "0", "1", "0", "saved", "NA", "NA", "left", "outside the box", "the top right corner", "NA", "0", "NA", "NA", "0", "NA", "0", "0", "NA", "NA", "NA", "0", "NA", "NA", "NA", "0", "NA", "NA", "0", "NA", "0", "NA", "NA", "NA", "0", "NA", "NA", "0", "0", "NA", "NA", "NA", "0", "NA", "NA", "NA", "NA", "1", "15", "0", "NA", "NA", "23"], ["480857", "Foul by Adam Smith (Bournemouth).", "24'", "AFC Bournemouth", "0", "0", "0", "0", "0", "0", "NA", "NA", "NA", "NA", "NA", "NA", "NA", "1", "Adam Smith", "NA", "0", "NA", "0", "0", "NA", "NA", "NA", "0", "NA", "NA", "NA", "0", "NA", "NA", "0", "NA", "0", "NA", "NA", "NA", "0", "NA", "NA", "0", "0", "NA", "NA", "NA", "0", "NA", "NA", "NA", "NA", "1", "16", "0", "NA", "NA", "24"], ["480857", "Solly March (Brighton and Hove Albion) wins a free kick on the left wing.", "24'", "AFC Bournemouth", "0", "0", "0", "0", "0", "0", "NA", "NA", "NA", "NA", "NA", "NA", "NA", "0", "NA", "NA", "0", "NA", "0", "0", "NA", "NA", "NA", "0", "NA", "NA", "NA", "0", "NA", "NA", "0", "NA", "1", "Solly March", "NA", "NA", "0", "NA", "NA", "0", "0", "NA", "NA", "NA", "0", "NA", "NA", "NA", "NA", "1", "17", "0", "NA", "NA", "24"], ["480857", "Attempt missed. Davy Pröpper (Brighton and Hove Albion) right footed shot from outside the box is just a bit too high.", "30'", "AFC Bournemouth", "0", "0", "0", "0", "1", "0", "missed", "NA", "NA", "right", "outside the box", "just a bit too high", "NA", "0", "NA", "NA", "0", "NA", "0", "0", "NA", "NA", "NA", "0", "NA", "NA", "NA", "0", "NA", "NA", "0", "NA", "0", "NA", "NA", "NA", "0", "NA", "NA", "0", "0", "NA", "NA", "NA", "0", "NA", "NA", "NA", "NA", "1", "18", "0", "NA", "NA", "30"], ["480857", "Attempt missed. Jermain Defoe (Bournemouth) right footed shot from outside the box is close, but misses to the right. Assisted by Marc Pugh.", "30'", "AFC Bournemouth", "0", "0", "0", "0", "1", "0", "missed", "NA", "NA", "right", "outside the box", "close, but right", "Marc Pugh", "0", "NA", "NA", "0", "NA", "0", "0", "NA", "NA", "NA", "0", "NA", "NA", "NA", "0", "NA", "NA", "0", "NA", "0", "NA", "NA", "NA", "0", "NA", "NA", "0", "0", "NA", "NA", "NA", "0", "NA", "NA", "NA", "NA", "1", "19", "0", "NA", "NA", "30"], ["480857", "Charlie Daniels (Bournemouth) wins a free kick in the defensive half.", "32'", "AFC Bournemouth", "0", "0", "0", "0", "0", "0", "NA", "NA", "NA", "NA", "NA", "NA", "NA", "0", "NA", "NA", "0", "NA", "0", "0", "NA", "NA", "NA", "0", "NA", "NA", "NA", "0", "NA", "NA", "0", "NA", "1", "Charlie Daniels", "NA", "defensive half", "0", "NA", "NA", "0", "0", "NA", "NA", "NA", "0", "NA", "NA", "NA", "NA", "1", "20", "0", "NA", "NA", "32"], ["480857", "Foul by Tomer Hemed (Brighton and Hove Albion).", "32'", "AFC Bournemouth", "0", "0", "0", "0", "0", "0", "NA", "NA", "NA", "NA", "NA", "NA", "NA", "1", "Tomer Hemed", "NA", "0", "NA", "0", "0", "NA", "NA", "NA", "0", "NA", "NA", "NA", "0", "NA", "NA", "0", "NA", "0", "NA", "NA", "NA", "0", "NA", "NA", "0", "0", "NA", "NA", "NA", "0", "NA", "NA", "NA", "NA", "1", "21", "0", "NA", "NA", "32"], ["480857", "Corner,  Bournemouth. Conceded by Liam Rosenior.", "35'", "AFC Bournemouth", "0", "0", "0", "0", "0", "0", "NA", "NA", "NA", "NA", "NA", "NA", "NA", "0", "NA", "NA", "0", "NA", "0", "0", "NA", "NA", "NA", "0", "NA", "NA", "NA", "0", "NA", "NA", "0", "NA", "0", "NA", "NA", "NA", "1", "NA", "Liam Rosenior", "0", "0", "NA", "NA", "NA", "0", "NA", "NA", "NA", "NA", "1", "22", "0", "NA", "NA", "35"], ["480857", "Adam Smith (Bournemouth) wins a free kick on the left wing.", "39'", "AFC Bournemouth", "0", "0", "0", "0", "0", "0", "NA", "NA", "NA", "NA", "NA", "NA", "NA", "0", "NA", "NA", "0", "NA", "0", "0", "NA", "NA", "NA", "0", "NA", "NA", "NA", "0", "NA", "NA", "0", "NA", "1", "Adam Smith", "NA", "NA", "0", "NA", "NA", "0", "0", "NA", "NA", "NA", "0", "NA", "NA", "NA", "NA", "1", "23", "0", "NA", "NA", "39"], ["480857", "Foul by Anthony Knockaert (Brighton and Hove Albion).", "39'", "AFC Bournemouth", "0", "0", "0", "0", "0", "0", "NA", "NA", "NA", "NA", "NA", "NA", "NA", "1", "Anthony Knockaert", "NA", "0", "NA", "0", "0", "NA", "NA", "NA", "0", "NA", "NA", "NA", "0", "NA", "NA", "0", "NA", "0", "NA", "NA", "NA", "0", "NA", "NA", "0", "0", "NA", "NA", "NA", "0", "NA", "NA", "NA", "NA", "1", "24", "0", "NA", "NA", "39"], ["480857", "Foul by Harry Arter (Bournemouth).", "42'", "AFC Bournemouth", "0", "0", "0", "0", "0", "0", "NA", "NA", "NA", "NA", "NA", "NA", "NA", "1", "Harry Arter", "NA", "0", "NA", "0", "0", "NA", "NA", "NA", "0", "NA", "NA", "NA", "0", "NA", "NA", "0", "NA", "0", "NA", "NA", "NA", "0", "NA", "NA", "0", "0", "NA", "NA", "NA", "0", "NA", "NA", "NA", "NA", "1", "25", "0", "NA", "NA", "42"], ["480857", "Tomer Hemed (Brighton and Hove Albion) wins a free kick in the defensive half.", "42'", "AFC Bournemouth", "0", "0", "0", "0", "0", "0", "NA", "NA", "NA", "NA", "NA", "NA", "NA", "0", "NA", "NA", "0", "NA", "0", "0", "NA", "NA", "NA", "0", "NA", "NA", "NA", "0", "NA", "NA", "0", "NA", "1", "Tomer Hemed", "NA", "defensive half", "0", "NA", "NA", "0", "0", "NA", "NA", "NA", "0", "NA", "NA", "NA", "NA", "1", "26", "0", "NA", "NA", "42"], ["480857", "Attempt blocked. Joshua King (Bournemouth) right footed shot from outside the box is blocked.", "44'", "AFC Bournemouth", "0", "0", "0", "0", "1", "0", "blocked", "NA", "NA", "right", "outside the box", "NA", "NA", "0", "NA", "NA", "0", "NA", "0", "0", "NA", "NA", "NA", "0", "NA", "NA", "NA", "0", "NA", "NA", "0", "NA", "0", "NA", "NA", "NA", "0", "NA", "NA", "0", "0", "NA", "NA", "NA", "0", "NA", "NA", "NA", "NA", "1", "27", "0", "NA", "NA", "44"], ["480857", "Attempt blocked. Ryan Fraser (Bournemouth) left footed shot from outside the box is blocked. Assisted by Jermain Defoe.", "45'", "AFC Bournemouth", "0", "0", "0", "0", "1", "0", "blocked", "NA", "NA", "left", "outside the box", "NA", "Jermain Defoe", "0", "NA", "NA", "0", "NA", "0", "0", "NA", "NA", "NA", "0", "NA", "NA", "NA", "0", "NA", "NA", "0", "NA", "0", "NA", "NA", "NA", "0", "NA", "NA", "0", "0", "NA", "NA", "NA", "0", "NA", "NA", "NA", "NA", "1", "28", "0", "NA", "NA", "45"], ["480857", "First Half ends, Bournemouth 0, Brighton and Hove Albion 0.", "45'+1'", "AFC Bournemouth", "0", "1", "0", "0", "0", "0", "NA", "NA", "NA", "NA", "NA", "NA", "NA", "0", "NA", "NA", "0", "NA", "0", "0", "NA", "NA", "NA", "0", "NA", "NA", "NA", "0", "NA", "NA", "0", "NA", "0", "NA", "NA", "NA", "0", "NA", "NA", "0", "0", "NA", "NA", "NA", "0", "NA", "NA", "NA", "NA", "1", "29", "1", "NA", "NA", "46"], ["480857", "Second Half begins Bournemouth 0, Brighton and Hove Albion 0.", "45'", "AFC Bournemouth", "0", "0", "0", "1", "0", "0", "NA", "NA", "NA", "NA", "NA", "NA", "NA", "0", "NA", "NA", "0", "NA", "0", "0", "NA", "NA", "NA", "0", "NA", "NA", "NA", "0", "NA", "NA", "0", "NA", "0", "NA", "NA", "NA", "0", "NA", "NA", "0", "0", "NA", "NA", "NA", "0", "NA", "NA", "NA", "NA", "2", "30", "0", "NA", "NA", "45"], ["480857", "Corner,  Brighton and Hove Albion. Conceded by Adam Smith.", "51'", "AFC Bournemouth", "0", "0", "0", "0", "0", "0", "NA", "NA", "NA", "NA", "NA", "NA", "NA", "0", "NA", "NA", "0", "NA", "0", "0", "NA", "NA", "NA", "0", "NA", "NA", "NA", "0", "NA", "NA", "0", "NA", "0", "NA", "NA", "NA", "1", "NA", "Adam Smith", "0", "0", "NA", "NA", "NA", "0", "NA", "NA", "NA", "NA", "2", "31", "0", "NA", "NA", "51"], ["480857", "Attempt blocked. Shane Duffy (Brighton and Hove Albion) header from the right side of the six yard box is blocked. Assisted by Pascal Groß with a cross.", "51'", "AFC Bournemouth", "0", "0", "0", "0", "1", "0", "blocked", "NA", "NA", "header", "the right side of the six yard box", "NA", "Pascal Groß", "0", "NA", "NA", "0", "cross", "0", "0", "NA", "NA", "NA", "0", "NA", "NA", "NA", "0", "NA", "NA", "0", "NA", "0", "NA", "NA", "NA", "0", "NA", "NA", "0", "0", "NA", "NA", "NA", "0", "NA", "NA", "NA", "NA", "2", "32", "0", "NA", "NA", "51"], ["480857", "Attempt blocked. Davy Pröpper (Brighton and Hove Albion) header from the centre of the box is blocked.", "51'", "AFC Bournemouth", "0", "0", "0", "0", "1", "0", "blocked", "NA", "NA", "header", "the centre of the box", "NA", "NA", "0", "NA", "NA", "0", "NA", "0", "0", "NA", "NA", "NA", "0", "NA", "NA", "NA", "0", "NA", "NA", "0", "NA", "0", "NA", "NA", "NA", "0", "NA", "NA", "0", "0", "NA", "NA", "NA", "0", "NA", "NA", "NA", "NA", "2", "33", "0", "NA", "NA", "51"], ["480857", "Corner,  Brighton and Hove Albion. Conceded by Andrew Surman.", "51'", "AFC Bournemouth", "0", "0", "0", "0", "0", "0", "NA", "NA", "NA", "NA", "NA", "NA", "NA", "0", "NA", "NA", "0", "NA", "0", "0", "NA", "NA", "NA", "0", "NA", "NA", "NA", "0", "NA", "NA", "0", "NA", "0", "NA", "NA", "NA", "1", "NA", "Andrew Surman", "0", "0", "NA", "NA", "NA", "0", "NA", "NA", "NA", "NA", "2", "34", "0", "NA", "NA", "51"], ["480857", "Attempt blocked. Shane Duffy (Brighton and Hove Albion) header from the centre of the box is blocked. Assisted by Pascal Groß with a cross.", "52'", "AFC Bournemouth", "0", "0", "0", "0", "1", "0", "blocked", "NA", "NA", "header", "the centre of the box", "NA", "Pascal Groß", "0", "NA", "NA", "0", "cross", "0", "0", "NA", "NA", "NA", "0", "NA", "NA", "NA", "0", "NA", "NA", "0", "NA", "0", "NA", "NA", "NA", "0", "NA", "NA", "0", "0", "NA", "NA", "NA", "0", "NA", "NA", "NA", "NA", "2", "35", "0", "NA", "NA", "52"], ["480857", "Dale Stephens (Brighton and Hove Albion) hits the bar with a header from very close range. Assisted by Shane Duffy following a corner.", "52'", "AFC Bournemouth", "0", "0", "0", "0", "0", "0", "NA", "NA", "NA", "NA", "NA", "NA", "Shane Duffy", "0", "NA", "NA", "0", "NA", "1", "0", "NA", "NA", "NA", "0", "NA", "NA", "NA", "0", "NA", "NA", "0", "NA", "0", "NA", "NA", "NA", "0", "NA", "NA", "0", "0", "NA", "NA", "NA", "0", "NA", "NA", "NA", "NA", "2", "36", "0", "NA", "NA", "52"], ["480857", "Attempt blocked. Harry Arter (Bournemouth) left footed shot from outside the box is blocked. Assisted by Marc Pugh.", "53'", "AFC Bournemouth", "0", "0", "0", "0", "1", "0", "blocked", "NA", "NA", "left", "outside the box", "NA", "Marc Pugh", "0", "NA", "NA", "0", "NA", "0", "0", "NA", "NA", "NA", "0", "NA", "NA", "NA", "0", "NA", "NA", "0", "NA", "0", "NA", "NA", "NA", "0", "NA", "NA", "0", "0", "NA", "NA", "NA", "0", "NA", "NA", "NA", "NA", "2", "37", "0", "NA", "NA", "53"], ["480857", "Corner,  Bournemouth. Conceded by Dale Stephens.", "53'", "AFC Bournemouth", "0", "0", "0", "0", "0", "0", "NA", "NA", "NA", "NA", "NA", "NA", "NA", "0", "NA", "NA", "0", "NA", "0", "0", "NA", "NA", "NA", "0", "NA", "NA", "NA", "0", "NA", "NA", "0", "NA", "0", "NA", "NA", "NA", "1", "NA", "Dale Stephens", "0", "0", "NA", "NA", "NA", "0", "NA", "NA", "NA", "NA", "2", "38", "0", "NA", "NA", "53"], ["480857", "Corner,  Bournemouth. Conceded by Solly March.", "53'", "AFC Bournemouth", "0", "0", "0", "0", "0", "0", "NA", "NA", "NA", "NA", "NA", "NA", "NA", "0", "NA", "NA", "0", "NA", "0", "0", "NA", "NA", "NA", "0", "NA", "NA", "NA", "0", "NA", "NA", "0", "NA", "0", "NA", "NA", "NA", "1", "NA", "Solly March", "0", "0", "NA", "NA", "NA", "0", "NA", "NA", "NA", "NA", "2", "39", "0", "NA", "NA", "53"], ["480857", "Attempt missed. Marc Pugh (Bournemouth) right footed shot from outside the box is too high following a corner.", "54'", "AFC Bournemouth", "0", "0", "0", "0", "1", "0", "missed", "NA", "NA", "right", "outside the box", "too high", "NA", "0", "NA", "NA", "0", "NA", "1", "0", "NA", "NA", "NA", "0", "NA", "NA", "NA", "0", "NA", "NA", "0", "NA", "0", "NA", "NA", "NA", "0", "NA", "NA", "0", "0", "NA", "NA", "NA", "0", "NA", "NA", "NA", "NA", "2", "40", "0", "NA", "NA", "54"], ["480857", "Goal!  Bournemouth 0, Brighton and Hove Albion 1. Solly March (Brighton and Hove Albion) header from very close range to the bottom right corner. Assisted by Pascal Groß with a cross.", "55'", "AFC Bournemouth", "0", "0", "0", "0", "1", "0", "goal", "NA", "NA", "header", "very close range", "bottom right corner", "Pascal Groß", "0", "NA", "NA", "0", "cross", "0", "0", "NA", "NA", "NA", "0", "NA", "NA", "NA", "0", "NA", "NA", "0", "NA", "0", "NA", "NA", "NA", "0", "NA", "NA", "0", "0", "NA", "NA", "NA", "0", "NA", "NA", "NA", "NA", "2", "41", "0", "NA", "NA", "55"], ["480857", "Substitution, Bournemouth. Jordon Ibe replaces Ryan Fraser.", "65'", "AFC Bournemouth", "0", "0", "0", "0", "0", "0", "NA", "NA", "NA", "NA", "NA", "NA", "NA", "0", "NA", "NA", "0", "NA", "0", "0", "NA", "NA", "NA", "0", "NA", "NA", "NA", "0", "NA", "NA", "0", "NA", "0", "NA", "NA", "NA", "0", "NA", "NA", "1", "0", "NA", "Jordon Ibe", "Ryan Fraser", "0", "NA", "NA", "NA", "NA", "2", "42", "0", "NA", "NA", "65"], ["480857", "Attempt blocked. Marc Pugh (Bournemouth) right footed shot from outside the box is blocked. Assisted by Andrew Surman.", "66'", "AFC Bournemouth", "0", "0", "0", "0", "1", "0", "blocked", "NA", "NA", "right", "outside the box", "NA", "Andrew Surman", "0", "NA", "NA", "0", "NA", "0", "0", "NA", "NA", "NA", "0", "NA", "NA", "NA", "0", "NA", "NA", "0", "NA", "0", "NA", "NA", "NA", "0", "NA", "NA", "0", "0", "NA", "NA", "NA", "0", "NA", "NA", "NA", "NA", "2", "43", "0", "NA", "NA", "66"], ["480857", "Goal!  Bournemouth 1, Brighton and Hove Albion 1. Andrew Surman (Bournemouth) left footed shot from the centre of the box to the bottom left corner. Assisted by Jordon Ibe with a through ball.", "67'", "AFC Bournemouth", "0", "0", "0", "0", "1", "0", "goal", "NA", "NA", "left", "the centre of the box", "bottom left corner", "Jordon Ibe", "0", "NA", "NA", "0", "through", "0", "0", "NA", "NA", "NA", "0", "NA", "NA", "NA", "0", "NA", "NA", "0", "NA", "0", "NA", "NA", "NA", "0", "NA", "NA", "0", "0", "NA", "NA", "NA", "0", "NA", "NA", "NA", "NA", "2", "44", "0", "NA", "NA", "67"], ["480857", "Corner,  Brighton and Hove Albion. Conceded by Simon Francis.", "68'", "AFC Bournemouth", "0", "0", "0", "0", "0", "0", "NA", "NA", "NA", "NA", "NA", "NA", "NA", "0", "NA", "NA", "0", "NA", "0", "0", "NA", "NA", "NA", "0", "NA", "NA", "NA", "0", "NA", "NA", "0", "NA", "0", "NA", "NA", "NA", "1", "NA", "Simon Francis", "0", "0", "NA", "NA", "NA", "0", "NA", "NA", "NA", "NA", "2", "45", "0", "NA", "NA", "68"], ["480857", "Attempt blocked. Jordon Ibe (Bournemouth) right footed shot from the centre of the box is blocked.", "71'", "AFC Bournemouth", "0", "0", "0", "0", "1", "0", "blocked", "NA", "NA", "right", "the centre of the box", "NA", "NA", "0", "NA", "NA", "0", "NA", "0", "0", "NA", "NA", "NA", "0", "NA", "NA", "NA", "0", "NA", "NA", "0", "NA", "0", "NA", "NA", "NA", "0", "NA", "NA", "0", "0", "NA", "NA", "NA", "0", "NA", "NA", "NA", "NA", "2", "46", "0", "NA", "NA", "71"], ["480857", "Corner,  Bournemouth. Conceded by Lewis Dunk.", "71'", "AFC Bournemouth", "0", "0", "0", "0", "0", "0", "NA", "NA", "NA", "NA", "NA", "NA", "NA", "0", "NA", "NA", "0", "NA", "0", "0", "NA", "NA", "NA", "0", "NA", "NA", "NA", "0", "NA", "NA", "0", "NA", "0", "NA", "NA", "NA", "1", "NA", "Lewis Dunk", "0", "0", "NA", "NA", "NA", "0", "NA", "NA", "NA", "NA", "2", "47", "0", "NA", "NA", "71"], ["480857", "Delay in match Pascal Groß (Brighton and Hove Albion) because of an injury.", "72'", "AFC Bournemouth", "0", "0", "0", "0", "0", "0", "NA", "NA", "NA", "NA", "NA", "NA", "NA", "0", "NA", "NA", "0", "NA", "0", "0", "NA", "NA", "NA", "0", "NA", "NA", "NA", "0", "NA", "NA", "1", "NA", "0", "NA", "NA", "NA", "0", "NA", "NA", "0", "0", "NA", "NA", "NA", "0", "NA", "NA", "NA", "NA", "2", "48", "0", "NA", "NA", "72"], ["480857", "Delay over. They are ready to continue.", "73'", "AFC Bournemouth", "0", "0", "0", "0", "0", "0", "NA", "NA", "NA", "NA", "NA", "NA", "NA", "0", "NA", "NA", "0", "NA", "0", "0", "NA", "NA", "NA", "0", "NA", "NA", "NA", "0", "NA", "NA", "0", "NA", "0", "NA", "NA", "NA", "0", "NA", "NA", "0", "0", "NA", "NA", "NA", "0", "NA", "NA", "NA", "NA", "2", "49", "0", "NA", "NA", "73"], ["480857", "Goal!  Bournemouth 2, Brighton and Hove Albion 1. Jermain Defoe (Bournemouth) right footed shot from the centre of the box to the bottom left corner. Assisted by Jordon Ibe with a through ball following a corner.", "73'", "AFC Bournemouth", "0", "0", "0", "0", "1", "0", "goal", "NA", "NA", "right", "the centre of the box", "bottom left corner", "Jordon Ibe", "0", "NA", "NA", "0", "through", "1", "0", "NA", "NA", "NA", "0", "NA", "NA", "NA", "0", "NA", "NA", "0", "NA", "0", "NA", "NA", "NA", "0", "NA", "NA", "0", "0", "NA", "NA", "NA", "0", "NA", "NA", "NA", "NA", "2", "50", "0", "NA", "NA", "73"], ["480857", "Attempt missed. Liam Rosenior (Brighton and Hove Albion) right footed shot from outside the box is too high.", "75'", "AFC Bournemouth", "0", "0", "0", "0", "1", "0", "missed", "NA", "NA", "right", "outside the box", "too high", "NA", "0", "NA", "NA", "0", "NA", "0", "0", "NA", "NA", "NA", "0", "NA", "NA", "NA", "0", "NA", "NA", "0", "NA", "0", "NA", "NA", "NA", "0", "NA", "NA", "0", "0", "NA", "NA", "NA", "0", "NA", "NA", "NA", "NA", "2", "51", "0", "NA", "NA", "75"], ["480857", "Hand ball by Jermain Defoe (Bournemouth).", "76'", "AFC Bournemouth", "0", "0", "0", "0", "0", "0", "NA", "NA", "NA", "NA", "NA", "NA", "NA", "0", "NA", "NA", "0", "NA", "0", "0", "NA", "NA", "NA", "0", "NA", "NA", "NA", "0", "NA", "NA", "0", "NA", "0", "NA", "NA", "NA", "0", "NA", "NA", "0", "0", "NA", "NA", "NA", "0", "NA", "NA", "NA", "NA", "2", "52", "0", "NA", "NA", "76"], ["480857", "Substitution, Brighton and Hove Albion. José Izquierdo replaces Anthony Knockaert.", "76'", "AFC Bournemouth", "0", "0", "0", "0", "0", "0", "NA", "NA", "NA", "NA", "NA", "NA", "NA", "0", "NA", "NA", "0", "NA", "0", "0", "NA", "NA", "NA", "0", "NA", "NA", "NA", "0", "NA", "NA", "0", "NA", "0", "NA", "NA", "NA", "0", "NA", "NA", "1", "0", "NA", "José Izquierdo", "Anthony Knockaert", "0", "NA", "NA", "NA", "NA", "2", "53", "0", "NA", "NA", "76"], ["480857", "Substitution, Brighton and Hove Albion. Glenn Murray replaces Pascal Groß.", "77'", "AFC Bournemouth", "0", "0", "0", "0", "0", "0", "NA", "NA", "NA", "NA", "NA", "NA", "NA", "0", "NA", "NA", "0", "NA", "0", "0", "NA", "NA", "NA", "0", "NA", "NA", "NA", "0", "NA", "NA", "0", "NA", "0", "NA", "NA", "NA", "0", "NA", "NA", "1", "0", "NA", "Glenn Murray", "Pascal Groß", "0", "NA", "NA", "NA", "NA", "2", "54", "0", "NA", "NA", "77"], ["480857", "Foul by Shane Duffy (Brighton and Hove Albion).", "77'", "AFC Bournemouth", "0", "0", "0", "0", "0", "0", "NA", "NA", "NA", "NA", "NA", "NA", "NA", "1", "Shane Duffy", "NA", "0", "NA", "0", "0", "NA", "NA", "NA", "0", "NA", "NA", "NA", "0", "NA", "NA", "0", "NA", "0", "NA", "NA", "NA", "0", "NA", "NA", "0", "0", "NA", "NA", "NA", "0", "NA", "NA", "NA", "NA", "2", "55", "0", "NA", "NA", "77"], ["480857", "Jermain Defoe (Bournemouth) wins a free kick in the defensive half.", "77'", "AFC Bournemouth", "0", "0", "0", "0", "0", "0", "NA", "NA", "NA", "NA", "NA", "NA", "NA", "0", "NA", "NA", "0", "NA", "0", "0", "NA", "NA", "NA", "0", "NA", "NA", "NA", "0", "NA", "NA", "0", "NA", "1", "Jermain Defoe", "NA", "defensive half", "0", "NA", "NA", "0", "0", "NA", "NA", "NA", "0", "NA", "NA", "NA", "NA", "2", "56", "0", "NA", "NA", "77"], ["480857", "Substitution, Bournemouth. Benik Afobe replaces Jermain Defoe.", "78'", "AFC Bournemouth", "0", "0", "0", "0", "0", "0", "NA", "NA", "NA", "NA", "NA", "NA", "NA", "0", "NA", "NA", "0", "NA", "0", "0", "NA", "NA", "NA", "0", "NA", "NA", "NA", "0", "NA", "NA", "0", "NA", "0", "NA", "NA", "NA", "0", "NA", "NA", "1", "0", "NA", "Benik Afobe", "Jermain Defoe", "0", "NA", "NA", "NA", "NA", "2", "57", "0", "NA", "NA", "78"], ["480857", "Benik Afobe (Bournemouth) wins a free kick on the left wing.", "79'", "AFC Bournemouth", "0", "0", "0", "0", "0", "0", "NA", "NA", "NA", "NA", "NA", "NA", "NA", "0", "NA", "NA", "0", "NA", "0", "0", "NA", "NA", "NA", "0", "NA", "NA", "NA", "0", "NA", "NA", "0", "NA", "1", "Benik Afobe", "NA", "NA", "0", "NA", "NA", "0", "0", "NA", "NA", "NA", "0", "NA", "NA", "NA", "NA", "2", "58", "0", "NA", "NA", "79"], ["480857", "Foul by Solly March (Brighton and Hove Albion).", "79'", "AFC Bournemouth", "0", "0", "0", "0", "0", "0", "NA", "NA", "NA", "NA", "NA", "NA", "NA", "1", "Solly March", "NA", "0", "NA", "0", "0", "NA", "NA", "NA", "0", "NA", "NA", "NA", "0", "NA", "NA", "0", "NA", "0", "NA", "NA", "NA", "0", "NA", "NA", "0", "0", "NA", "NA", "NA", "0", "NA", "NA", "NA", "NA", "2", "59", "0", "NA", "NA", "79"], ["480857", "Corner,  Bournemouth. Conceded by Liam Rosenior.", "79'", "AFC Bournemouth", "0", "0", "0", "0", "0", "0", "NA", "NA", "NA", "NA", "NA", "NA", "NA", "0", "NA", "NA", "0", "NA", "0", "0", "NA", "NA", "NA", "0", "NA", "NA", "NA", "0", "NA", "NA", "0", "NA", "0", "NA", "NA", "NA", "1", "NA", "Liam Rosenior", "0", "0", "NA", "NA", "NA", "0", "NA", "NA", "NA", "NA", "2", "60", "0", "NA", "NA", "79"], ["480857", "Attempt blocked. Simon Francis (Bournemouth) header from the centre of the box is blocked. Assisted by Charlie Daniels with a cross.", "80'", "AFC Bournemouth", "0", "0", "0", "0", "1", "0", "blocked", "NA", "NA", "header", "the centre of the box", "NA", "Charlie Daniels", "0", "NA", "NA", "0", "cross", "0", "0", "NA", "NA", "NA", "0", "NA", "NA", "NA", "0", "NA", "NA", "0", "NA", "0", "NA", "NA", "NA", "0", "NA", "NA", "0", "0", "NA", "NA", "NA", "0", "NA", "NA", "NA", "NA", "2", "61", "0", "NA", "NA", "80"], ["480857", "Dale Stephens (Brighton and Hove Albion) wins a free kick in the defensive half.", "81'", "AFC Bournemouth", "0", "0", "0", "0", "0", "0", "NA", "NA", "NA", "NA", "NA", "NA", "NA", "0", "NA", "NA", "0", "NA", "0", "0", "NA", "NA", "NA", "0", "NA", "NA", "NA", "0", "NA", "NA", "0", "NA", "1", "Dale Stephens", "NA", "defensive half", "0", "NA", "NA", "0", "0", "NA", "NA", "NA", "0", "NA", "NA", "NA", "NA", "2", "62", "0", "NA", "NA", "81"], ["480857", "Foul by Benik Afobe (Bournemouth).", "81'", "AFC Bournemouth", "0", "0", "0", "0", "0", "0", "NA", "NA", "NA", "NA", "NA", "NA", "NA", "1", "Benik Afobe", "NA", "0", "NA", "0", "0", "NA", "NA", "NA", "0", "NA", "NA", "NA", "0", "NA", "NA", "0", "NA", "0", "NA", "NA", "NA", "0", "NA", "NA", "0", "0", "NA", "NA", "NA", "0", "NA", "NA", "NA", "NA", "2", "63", "0", "NA", "NA", "81"], ["480857", "Foul by Benik Afobe (Bournemouth).", "85'", "AFC Bournemouth", "0", "0", "0", "0", "0", "0", "NA", "NA", "NA", "NA", "NA", "NA", "NA", "1", "Benik Afobe", "NA", "0", "NA", "0", "0", "NA", "NA", "NA", "0", "NA", "NA", "NA", "0", "NA", "NA", "0", "NA", "0", "NA", "NA", "NA", "0", "NA", "NA", "0", "0", "NA", "NA", "NA", "0", "NA", "NA", "NA", "NA", "2", "64", "0", "NA", "NA", "85"], ["480857", "Shane Duffy (Brighton and Hove Albion) wins a free kick in the defensive half.", "85'", "AFC Bournemouth", "0", "0", "0", "0", "0", "0", "NA", "NA", "NA", "NA", "NA", "NA", "NA", "0", "NA", "NA", "0", "NA", "0", "0", "NA", "NA", "NA", "0", "NA", "NA", "NA", "0", "NA", "NA", "0", "NA", "1", "Shane Duffy", "NA", "defensive half", "0", "NA", "NA", "0", "0", "NA", "NA", "NA", "0", "NA", "NA", "NA", "NA", "2", "65", "0", "NA", "NA", "85"], ["480857", "Corner,  Brighton and Hove Albion. Conceded by Simon Francis.", "86'", "AFC Bournemouth", "0", "0", "0", "0", "0", "0", "NA", "NA", "NA", "NA", "NA", "NA", "NA", "0", "NA", "NA", "0", "NA", "0", "0", "NA", "NA", "NA", "0", "NA", "NA", "NA", "0", "NA", "NA", "0", "NA", "0", "NA", "NA", "NA", "1", "NA", "Simon Francis", "0", "0", "NA", "NA", "NA", "0", "NA", "NA", "NA", "NA", "2", "66", "0", "NA", "NA", "86"], ["480857", "Attempt missed. Liam Rosenior (Brighton and Hove Albion) right footed shot from outside the box is too high. Assisted by Solly March with a cross following a corner.", "86'", "AFC Bournemouth", "0", "0", "0", "0", "1", "0", "missed", "NA", "NA", "right", "outside the box", "too high", "Solly March", "0", "NA", "NA", "0", "cross", "1", "0", "NA", "NA", "NA", "0", "NA", "NA", "NA", "0", "NA", "NA", "0", "NA", "0", "NA", "NA", "NA", "0", "NA", "NA", "0", "0", "NA", "NA", "NA", "0", "NA", "NA", "NA", "NA", "2", "67", "0", "NA", "NA", "86"], ["480857", "Foul by Davy Pröpper (Brighton and Hove Albion).", "87'", "AFC Bournemouth", "0", "0", "0", "0", "0", "0", "NA", "NA", "NA", "NA", "NA", "NA", "NA", "1", "Davy Pröpper", "NA", "0", "NA", "0", "0", "NA", "NA", "NA", "0", "NA", "NA", "NA", "0", "NA", "NA", "0", "NA", "0", "NA", "NA", "NA", "0", "NA", "NA", "0", "0", "NA", "NA", "NA", "0", "NA", "NA", "NA", "NA", "2", "68", "0", "NA", "NA", "87"], ["480857", "Jordon Ibe (Bournemouth) wins a free kick in the defensive half.", "87'", "AFC Bournemouth", "0", "0", "0", "0", "0", "0", "NA", "NA", "NA", "NA", "NA", "NA", "NA", "0", "NA", "NA", "0", "NA", "0", "0", "NA", "NA", "NA", "0", "NA", "NA", "NA", "0", "NA", "NA", "0", "NA", "1", "Jordon Ibe", "NA", "defensive half", "0", "NA", "NA", "0", "0", "NA", "NA", "NA", "0", "NA", "NA", "NA", "NA", "2", "69", "0", "NA", "NA", "87"], ["480857", "Corner,  Bournemouth. Conceded by Liam Rosenior.", "89'", "AFC Bournemouth", "0", "0", "0", "0", "0", "0", "NA", "NA", "NA", "NA", "NA", "NA", "NA", "0", "NA", "NA", "0", "NA", "0", "0", "NA", "NA", "NA", "0", "NA", "NA", "NA", "0", "NA", "NA", "0", "NA", "0", "NA", "NA", "NA", "1", "NA", "Liam Rosenior", "0", "0", "NA", "NA", "NA", "0", "NA", "NA", "NA", "NA", "2", "70", "0", "NA", "NA", "89"], ["480857", "Foul by Davy Pröpper (Brighton and Hove Albion).", "90'", "AFC Bournemouth", "0", "0", "0", "0", "0", "0", "NA", "NA", "NA", "NA", "NA", "NA", "NA", "1", "Davy Pröpper", "NA", "0", "NA", "0", "0", "NA", "NA", "NA", "0", "NA", "NA", "NA", "0", "NA", "NA", "0", "NA", "0", "NA", "NA", "NA", "0", "NA", "NA", "0", "0", "NA", "NA", "NA", "0", "NA", "NA", "NA", "NA", "2", "71", "0", "NA", "NA", "90"], ["480857", "Harry Arter (Bournemouth) wins a free kick on the left wing.", "90'", "AFC Bournemouth", "0", "0", "0", "0", "0", "0", "NA", "NA", "NA", "NA", "NA", "NA", "NA", "0", "NA", "NA", "0", "NA", "0", "0", "NA", "NA", "NA", "0", "NA", "NA", "NA", "0", "NA", "NA", "0", "NA", "1", "Harry Arter", "NA", "NA", "0", "NA", "NA", "0", "0", "NA", "NA", "NA", "0", "NA", "NA", "NA", "NA", "2", "72", "0", "NA", "NA", "90"], ["480857", "Foul by Lewis Dunk (Brighton and Hove Albion).", "90'+1'", "AFC Bournemouth", "0", "0", "0", "0", "0", "0", "NA", "NA", "NA", "NA", "NA", "NA", "NA", "1", "Lewis Dunk", "NA", "0", "NA", "0", "0", "NA", "NA", "NA", "0", "NA", "NA", "NA", "0", "NA", "NA", "0", "NA", "0", "NA", "NA", "NA", "0", "NA", "NA", "0", "0", "NA", "NA", "NA", "0", "NA", "NA", "NA", "NA", "2", "73", "1", "NA", "NA", "91"], ["480857", "Joshua King (Bournemouth) wins a free kick in the attacking half.", "90'+1'", "AFC Bournemouth", "0", "0", "0", "0", "0", "0", "NA", "NA", "NA", "NA", "NA", "NA", "NA", "0", "NA", "NA", "0", "NA", "0", "0", "NA", "NA", "NA", "0", "NA", "NA", "NA", "0", "NA", "NA", "0", "NA", "1", "Joshua King", "NA", "attacking half", "0", "NA", "NA", "0", "0", "NA", "NA", "NA", "0", "NA", "NA", "NA", "NA", "2", "74", "1", "NA", "NA", "91"], ["480857", "Attempt missed. Jordon Ibe (Bournemouth) right footed shot from outside the box is close, but misses to the right from a direct free kick.", "90'+1'", "AFC Bournemouth", "0", "0", "0", "0", "1", "0", "missed", "NA", "NA", "right", "outside the box", "close, but right", "NA", "0", "NA", "NA", "0", "NA", "0", "0", "NA", "NA", "NA", "0", "NA", "NA", "NA", "0", "NA", "NA", "0", "NA", "0", "NA", "NA", "NA", "0", "NA", "NA", "0", "0", "NA", "NA", "NA", "0", "NA", "NA", "NA", "NA", "2", "75", "1", "NA", "NA", "91"], ["480857", "Offside, Brighton and Hove Albion. Solly March tries a through ball, but Shane Duffy is caught offside.", "90'+2'", "AFC Bournemouth", "0", "0", "0", "0", "0", "0", "NA", "NA", "NA", "NA", "NA", "NA", "NA", "0", "NA", "NA", "0", "NA", "0", "1", "NA", "Shane Duffy", "Solly March", "0", "NA", "NA", "NA", "0", "NA", "NA", "0", "NA", "0", "NA", "NA", "NA", "0", "NA", "NA", "0", "0", "NA", "NA", "NA", "0", "NA", "NA", "NA", "NA", "2", "76", "1", "NA", "NA", "92"], ["480857", "Substitution, Bournemouth. Dan Gosling replaces Joshua King.", "90'+3'", "AFC Bournemouth", "0", "0", "0", "0", "0", "0", "NA", "NA", "NA", "NA", "NA", "NA", "NA", "0", "NA", "NA", "0", "NA", "0", "0", "NA", "NA", "NA", "0", "NA", "NA", "NA", "0", "NA", "NA", "0", "NA", "0", "NA", "NA", "NA", "0", "NA", "NA", "1", "0", "NA", "Dan Gosling", "Joshua King", "0", "NA", "NA", "NA", "NA", "2", "77", "1", "NA", "NA", "93"], ["480857", "Offside, Bournemouth. Nathan Aké tries a through ball, but Benik Afobe is caught offside.", "90'+4'", "AFC Bournemouth", "0", "0", "0", "0", "0", "0", "NA", "NA", "NA", "NA", "NA", "NA", "NA", "0", "NA", "NA", "0", "NA", "0", "1", "NA", "Benik Afobe", "Nathan Aké", "0", "NA", "NA", "NA", "0", "NA", "NA", "0", "NA", "0", "NA", "NA", "NA", "0", "NA", "NA", "0", "0", "NA", "NA", "NA", "0", "NA", "NA", "NA", "NA", "2", "78", "1", "NA", "NA", "94"], ["480857", "Foul by Shane Duffy (Brighton and Hove Albion).", "90'+5'", "AFC Bournemouth", "0", "0", "0", "0", "0", "0", "NA", "NA", "NA", "NA", "NA", "NA", "NA", "1", "Shane Duffy", "NA", "0", "NA", "0", "0", "NA", "NA", "NA", "0", "NA", "NA", "NA", "0", "NA", "NA", "0", "NA", "0", "NA", "NA", "NA", "0", "NA", "NA", "0", "0", "NA", "NA", "NA", "0", "NA", "NA", "NA", "NA", "2", "79", "1", "NA", "NA", "95"], ["480857", "Marc Pugh (Bournemouth) wins a free kick in the defensive half.", "90'+5'", "AFC Bournemouth", "0", "0", "0", "0", "0", "0", "NA", "NA", "NA", "NA", "NA", "NA", "NA", "0", "NA", "NA", "0", "NA", "0", "0", "NA", "NA", "NA", "0", "NA", "NA", "NA", "0", "NA", "NA", "0", "NA", "1", "Marc Pugh", "NA", "defensive half", "0", "NA", "NA", "0", "0", "NA", "NA", "NA", "0", "NA", "NA", "NA", "NA", "2", "80", "1", "NA", "NA", "95"], ["480857", "Second Half ends, Bournemouth 2, Brighton and Hove Albion 1.", "90'+6'", "AFC Bournemouth", "0", "1", "0", "0", "0", "0", "NA", "NA", "NA", "NA", "NA", "NA", "NA", "0", "NA", "NA", "0", "NA", "0", "0", "NA", "NA", "NA", "0", "NA", "NA", "NA", "0", "NA", "NA", "0", "NA", "0", "NA", "NA", "NA", "0", "NA", "NA", "0", "0", "NA", "NA", "NA", "0", "NA", "NA", "NA", "NA", "2", "81", "1", "NA", "NA", "96"], ["480857", "Match ends, Bournemouth 2, Brighton and Hove Albion 1.", "90'+6'", "AFC Bournemouth", "0", "0", "1", "0", "0", "0", "NA", "NA", "NA", "NA", "NA", "NA", "NA", "0", "NA", "NA", "0", "NA", "0", "0", "NA", "NA", "NA", "0", "NA", "NA", "NA", "0", "NA", "NA", "0", "NA", "0", "NA", "NA", "NA", "0", "NA", "NA", "0", "0", "NA", "NA", "NA", "0", "NA", "NA", "NA", "NA", "2", "82", "1", "NA", "NA", "96"]], "Lineup": {"Home Player 9": "Marc Pugh", "Home Player 8": "Joshua King", "Home Player 5": "Jermain Defoe", "Home Player 4": "Charlie Daniels", "Home Player 7": "Ryan Fraser", "Home Player 6": "Simon Francis", "Home Player 1": "Nathan Ake", "Home Player 3": "Asmir Begovic", "Home Player 2": "Harry Arter", "Away Player 10": "Dale Stephens", "Away Player 11": "Markus Suttner", "Away Player 8": "Liam Rosenior", "Away Player 9": "Mathew Ryan", "Away Player 1": "Shane Duffy", "Away Player 2": "Lewis Dunk", "Away Player 3": "Pascal Gross", "Away Player 4": "Tomer Hemed", "Away Player 5": "Anthony Knockaert", "Away Player 6": "Solomon March", "Away Player 7": "Davy Propper", "Game ID": "g_1_jVf7R477", "Home Player 11": "Andrew Surman", "Home Player 10": "Adam Smith"}}