{"Stats": {"Full Time Result": "A", "Away Team Corners": 7, "Referee": "N Swarbrick", "Home Team Fouls Committed": 5, "Away Team Shots": 19, "Away Team Red Cards": 0, "Home Team Red Cards": 0, "Half Time Away Team Goals": 2, "Full Time Home Team Goals": 1, "Away Team Yellow Cards": 1, "Away Team Shots on Target": 7, "Half Time Home Team Goals": 1, "Half Time Result": "A", "Away Team Fouls Committed": 11, "Home Team Yellow Cards": 0, "Home Team Shots": 4, "Div": "E0", "Home Team Corners": 0, "Home Team Shots on Target": 1, "Full Time Away Team Goals": 4}, "Description": "Offside, West Ham United. Aaron Cresswell tries a through ball, but Marko Arnautovic is caught offside. at minute 6. Foul by Mark Noble (West Ham United). at minute 8. Kevin De Bruyne (Manchester City) wins a free kick in the attacking half. at minute 8. Attempt missed. Ilkay Gündogan (Manchester City) left footed shot from the centre of the box misses to the left. Assisted by Kyle Walker. at minute 9. Corner,  Manchester City. Conceded by Aaron Cresswell. at minute 11. Goal!  West Ham United 0, Manchester City 1. Leroy Sané (Manchester City) left footed shot from outside the box to the bottom left corner. Assisted by Raheem Sterling. at minute 13. Foul by Kyle Walker (Manchester City). at minute 16. Mark Noble (West Ham United) wins a free kick on the left wing. at minute 16. Attempt missed. Raheem Sterling (Manchester City) left footed shot from the centre of the box misses to the right. Assisted by Ilkay Gündogan. at minute 20. Attempt missed. Fernandinho (Manchester City) right footed shot from outside the box is close, but misses to the left. Assisted by Ilkay Gündogan. at minute 21. Attempt blocked. Kevin De Bruyne (Manchester City) left footed shot from outside the box is blocked. Assisted by Kyle Walker. at minute 22. Foul by Aymeric Laporte (Manchester City). at minute 24. Marko Arnautovic (West Ham United) wins a free kick on the right wing. at minute 24. Attempt blocked. Raheem Sterling (Manchester City) left footed shot from outside the box is blocked. at minute 27. Own Goal by Pablo Zabaleta, West Ham United.  West Ham United 0, Manchester City 2. at minute 27. Delay in match Cheikhou Kouyaté (West Ham United) because of an injury. at minute 29. Delay over. They are ready to continue. at minute 32. Foul by Ilkay Gündogan (Manchester City). at minute 33. Mark Noble (West Ham United) wins a free kick in the attacking half. at minute 33. Corner,  Manchester City. Conceded by Adrián. at minute 35. Foul by Nicolás Otamendi (Manchester City). at minute 37. Manuel Lanzini (West Ham United) wins a free kick in the attacking half. at minute 37. Nicolás Otamendi (Manchester City) is shown the yellow card for a bad foul. at minute 37. Attempt missed. Declan Rice (West Ham United) left footed shot from the centre of the box is high and wide to the left following a set piece situation. at minute 38. Ederson (Manchester City) wins a free kick in the defensive half. at minute 39. Foul by Marko Arnautovic (West Ham United). at minute 39. Attempt missed. Cheikhou Kouyaté (West Ham United) right footed shot from the centre of the box misses to the right. Assisted by Edimilson Fernandes with a cross. at minute 41. Edimilson Fernandes (West Ham United) wins a free kick in the attacking half. at minute 41. Foul by Ilkay Gündogan (Manchester City). at minute 41. Goal!  West Ham United 1, Manchester City 2. Aaron Cresswell (West Ham United) from a free kick with a left footed shot to the bottom right corner. at minute 42. Attempt saved. Kevin De Bruyne (Manchester City) left footed shot from outside the box is saved in the centre of the goal. at minute 43. Offside, West Ham United. Patrice Evra tries a through ball, but Cheikhou Kouyaté is caught offside. at minute 44. Attempt missed. Kevin De Bruyne (Manchester City) right footed shot from outside the box is close, but misses to the right. Assisted by Leroy Sané. at minute 46. Attempt saved. Raheem Sterling (Manchester City) right footed shot from the centre of the box is saved in the bottom right corner. Assisted by Leroy Sané. at minute 47. Offside, West Ham United. Angelo Ogbonna tries a through ball, but Aaron Cresswell is caught offside. at minute 48. Foul by Nicolás Otamendi (Manchester City). at minute 49. Manuel Lanzini (West Ham United) wins a free kick in the attacking half. at minute 49. Attempt blocked. Marko Arnautovic (West Ham United) header from the centre of the box is blocked. Assisted by Mark Noble. at minute 50. First Half ends, West Ham United 1, Manchester City 2. at minute 50. Second Half begins West Ham United 1, Manchester City 2. at minute 45. Foul by Raheem Sterling (Manchester City). at minute 48. Mark Noble (West Ham United) wins a free kick in the defensive half. at minute 48. Foul by Marko Arnautovic (West Ham United). at minute 49. Nicolás Otamendi (Manchester City) wins a free kick in the defensive half. at minute 49. Offside, West Ham United. Aaron Cresswell tries a through ball, but Marko Arnautovic is caught offside. at minute 52. Goal!  West Ham United 1, Manchester City 3. Gabriel Jesus (Manchester City) right footed shot from very close range to the centre of the goal. Assisted by Raheem Sterling. at minute 53. Foul by Raheem Sterling (Manchester City). at minute 56. Mark Noble (West Ham United) wins a free kick in the defensive half. at minute 56. Hand ball by Raheem Sterling (Manchester City). at minute 57. Attempt missed. Kevin De Bruyne (Manchester City) right footed shot from the centre of the box is close, but misses to the right. Assisted by Raheem Sterling. at minute 59. Hand ball by Angelo Ogbonna (West Ham United). at minute 60. Attempt missed. Ilkay Gündogan (Manchester City) right footed shot from outside the box is close, but misses to the left. Assisted by Gabriel Jesus. at minute 61. Substitution, Manchester City. Danilo replaces Kyle Walker. at minute 61. Attempt saved. Raheem Sterling (Manchester City) right footed shot from the right side of the box is saved in the centre of the goal. Assisted by Gabriel Jesus with a through ball. at minute 62. Offside, Manchester City. Kevin De Bruyne tries a through ball, but Raheem Sterling is caught offside. at minute 64. Goal!  West Ham United 1, Manchester City 4. Fernandinho (Manchester City) right footed shot from the centre of the box to the centre of the goal. Assisted by Raheem Sterling. at minute 64. Substitution, West Ham United. João Mário replaces Edimilson Fernandes. at minute 65. Substitution, West Ham United. Chicharito replaces Manuel Lanzini. at minute 66. Substitution, West Ham United. Arthur Masuaku replaces Patrice Evra. at minute 66. Substitution, Manchester City. Yaya Touré replaces Ilkay Gündogan. at minute 71. Attempt blocked. Gabriel Jesus (Manchester City) right footed shot from very close range is blocked. at minute 77. Attempt blocked. Raheem Sterling (Manchester City) left footed shot from the centre of the box is blocked. Assisted by Fabian Delph with a cross. at minute 77. Attempt saved. Kevin De Bruyne (Manchester City) right footed shot from outside the box is saved in the centre of the goal. Assisted by Leroy Sané. at minute 77. Corner,  Manchester City. Conceded by Pablo Zabaleta. at minute 79. Substitution, Manchester City. Lukas Nmecha replaces Gabriel Jesus. at minute 80. Attempt missed. Raheem Sterling (Manchester City) right footed shot from the centre of the box misses to the right. Assisted by Yaya Touré. at minute 82. Corner,  Manchester City. Conceded by João Mário. at minute 85. Foul by Cheikhou Kouyaté (West Ham United). at minute 87. Leroy Sané (Manchester City) wins a free kick in the attacking half. at minute 87. Attempt blocked. Yaya Touré (Manchester City) right footed shot from outside the box is blocked. at minute 88. Corner,  Manchester City. Conceded by Cheikhou Kouyaté. at minute 88. Corner,  Manchester City. Conceded by Aaron Cresswell. at minute 90. Angelo Ogbonna (West Ham United) wins a free kick in the defensive half. at minute 91. Foul by Yaya Touré (Manchester City). at minute 91. Arthur Masuaku (West Ham United) wins a free kick on the left wing. at minute 91. Foul by Kevin De Bruyne (Manchester City). at minute 91. Corner,  Manchester City. Conceded by Pablo Zabaleta. at minute 92. Second Half ends, West Ham United 1, Manchester City 4. at minute 94. Match ends, West Ham United 1, Manchester City 4. at minute 94. ", "Home Team": "West Ham United", "Away Team": "Manchester City", "Date": "2018-04-29", "Commentary": [["480552", "First Half begins.", "-", "West Ham United", "0", "0", "0", "1", "0", "0", "NA", "NA", "NA", "NA", "NA", "NA", "NA", "0", "NA", "NA", "0", "NA", "0", "0", "NA", "NA", "NA", "0", "NA", "NA", "NA", "0", "NA", "NA", "0", "NA", "0", "NA", "NA", "NA", "0", "NA", "NA", "0", "0", "NA", "NA", "NA", "0", "NA", "NA", "NA", "NA", "1", "1", "0", "NA", "NA", "NA"], ["480552", "Lineups are announced and players are warming up.", "-", "West Ham United", "0", "0", "0", "0", "0", "0", "NA", "NA", "NA", "NA", "NA", "NA", "NA", "0", "NA", "NA", "0", "NA", "0", "0", "NA", "NA", "NA", "0", "NA", "NA", "NA", "0", "NA", "NA", "0", "NA", "0", "NA", "NA", "NA", "0", "NA", "NA", "0", "0", "NA", "NA", "NA", "0", "NA", "NA", "NA", "NA", "1", "2", "0", "NA", "NA", "NA"], ["480552", "Offside, West Ham United. Aaron Cresswell tries a through ball, but Marko Arnautovic is caught offside.", "6'", "West Ham United", "0", "0", "0", "0", "0", "0", "NA", "NA", "NA", "NA", "NA", "NA", "NA", "0", "NA", "NA", "0", "NA", "0", "1", "West Ham United", "Marko Arnautovic", "Aaron Cresswell", "0", "NA", "NA", "NA", "0", "NA", "NA", "0", "NA", "0", "NA", "NA", "NA", "0", "NA", "NA", "0", "0", "NA", "NA", "NA", "0", "NA", "NA", "NA", "NA", "1", "3", "0", "NA", "NA", "6"], ["480552", "Foul by Mark Noble (West Ham United).", "8'", "West Ham United", "0", "0", "0", "0", "0", "0", "NA", "NA", "NA", "NA", "NA", "NA", "NA", "1", "Mark Noble", "West Ham United", "0", "NA", "0", "0", "NA", "NA", "NA", "0", "NA", "NA", "NA", "0", "NA", "NA", "0", "NA", "0", "NA", "NA", "NA", "0", "NA", "NA", "0", "0", "NA", "NA", "NA", "0", "NA", "NA", "NA", "NA", "1", "4", "0", "NA", "NA", "8"], ["480552", "Kevin De Bruyne (Manchester City) wins a free kick in the attacking half.", "8'", "West Ham United", "0", "0", "0", "0", "0", "0", "NA", "NA", "NA", "NA", "NA", "NA", "NA", "0", "NA", "NA", "0", "NA", "0", "0", "NA", "NA", "NA", "0", "NA", "NA", "NA", "0", "NA", "NA", "0", "NA", "1", "Kevin De Bruyne", "Manchester City", "attacking half", "0", "NA", "NA", "0", "0", "NA", "NA", "NA", "0", "NA", "NA", "NA", "NA", "1", "5", "0", "NA", "NA", "8"], ["480552", "Attempt missed. Ilkay Gündogan (Manchester City) left footed shot from the centre of the box misses to the left. Assisted by Kyle Walker.", "9'", "West Ham United", "0", "0", "0", "0", "1", "0", "missed", "Ilkay Gündogan", "Manchester City", "left", "the centre of the box", "left", "Kyle Walker", "0", "NA", "NA", "0", "NA", "0", "0", "NA", "NA", "NA", "0", "NA", "NA", "NA", "0", "NA", "NA", "0", "NA", "0", "NA", "NA", "NA", "0", "NA", "NA", "0", "0", "NA", "NA", "NA", "0", "NA", "NA", "NA", "NA", "1", "6", "0", "NA", "NA", "9"], ["480552", "Corner,  Manchester City. Conceded by Aaron Cresswell.", "11'", "West Ham United", "0", "0", "0", "0", "0", "0", "NA", "NA", "NA", "NA", "NA", "NA", "NA", "0", "NA", "NA", "0", "NA", "0", "0", "NA", "NA", "NA", "0", "NA", "NA", "NA", "0", "NA", "NA", "0", "NA", "0", "NA", "NA", "NA", "1", "Manchester City", "Aaron Cresswell", "0", "0", "NA", "NA", "NA", "0", "NA", "NA", "NA", "NA", "1", "7", "0", "NA", "NA", "11"], ["480552", "Goal!  West Ham United 0, Manchester City 1. Leroy Sané (Manchester City) left footed shot from outside the box to the bottom left corner. Assisted by Raheem Sterling.", "13'", "West Ham United", "0", "0", "0", "0", "1", "0", "goal", "Leroy Sané", "Manchester City", "left", "outside the box", "bottom left corner", "Raheem Sterling", "0", "NA", "NA", "0", "NA", "0", "0", "NA", "NA", "NA", "0", "NA", "NA", "NA", "0", "NA", "NA", "0", "NA", "0", "NA", "NA", "NA", "0", "NA", "NA", "0", "0", "NA", "NA", "NA", "0", "NA", "NA", "NA", "NA", "1", "8", "0", "NA", "NA", "13"], ["480552", "Foul by Kyle Walker (Manchester City).", "16'", "West Ham United", "0", "0", "0", "0", "0", "0", "NA", "NA", "NA", "NA", "NA", "NA", "NA", "1", "Kyle Walker", "Manchester City", "0", "NA", "0", "0", "NA", "NA", "NA", "0", "NA", "NA", "NA", "0", "NA", "NA", "0", "NA", "0", "NA", "NA", "NA", "0", "NA", "NA", "0", "0", "NA", "NA", "NA", "0", "NA", "NA", "NA", "NA", "1", "9", "0", "NA", "NA", "16"], ["480552", "Mark Noble (West Ham United) wins a free kick on the left wing.", "16'", "West Ham United", "0", "0", "0", "0", "0", "0", "NA", "NA", "NA", "NA", "NA", "NA", "NA", "0", "NA", "NA", "0", "NA", "0", "0", "NA", "NA", "NA", "0", "NA", "NA", "NA", "0", "NA", "NA", "0", "NA", "1", "Mark Noble", "West Ham United", "NA", "0", "NA", "NA", "0", "0", "NA", "NA", "NA", "0", "NA", "NA", "NA", "NA", "1", "10", "0", "NA", "NA", "16"], ["480552", "Attempt missed. Raheem Sterling (Manchester City) left footed shot from the centre of the box misses to the right. Assisted by Ilkay Gündogan.", "20'", "West Ham United", "0", "0", "0", "0", "1", "0", "missed", "Raheem Sterling", "Manchester City", "left", "the centre of the box", "right", "Ilkay Gündogan", "0", "NA", "NA", "0", "NA", "0", "0", "NA", "NA", "NA", "0", "NA", "NA", "NA", "0", "NA", "NA", "0", "NA", "0", "NA", "NA", "NA", "0", "NA", "NA", "0", "0", "NA", "NA", "NA", "0", "NA", "NA", "NA", "NA", "1", "11", "0", "NA", "NA", "20"], ["480552", "Attempt missed. Fernandinho (Manchester City) right footed shot from outside the box is close, but misses to the left. Assisted by Ilkay Gündogan.", "21'", "West Ham United", "0", "0", "0", "0", "1", "0", "missed", "Fernandinho", "Manchester City", "right", "outside the box", "close, but left", "Ilkay Gündogan", "0", "NA", "NA", "0", "NA", "0", "0", "NA", "NA", "NA", "0", "NA", "NA", "NA", "0", "NA", "NA", "0", "NA", "0", "NA", "NA", "NA", "0", "NA", "NA", "0", "0", "NA", "NA", "NA", "0", "NA", "NA", "NA", "NA", "1", "12", "0", "NA", "NA", "21"], ["480552", "Attempt blocked. Kevin De Bruyne (Manchester City) left footed shot from outside the box is blocked. Assisted by Kyle Walker.", "22'", "West Ham United", "0", "0", "0", "0", "1", "0", "blocked", "Kevin De Bruyne", "Manchester City", "left", "outside the box", "NA", "Kyle Walker", "0", "NA", "NA", "0", "NA", "0", "0", "NA", "NA", "NA", "0", "NA", "NA", "NA", "0", "NA", "NA", "0", "NA", "0", "NA", "NA", "NA", "0", "NA", "NA", "0", "0", "NA", "NA", "NA", "0", "NA", "NA", "NA", "NA", "1", "13", "0", "NA", "NA", "22"], ["480552", "Foul by Aymeric Laporte (Manchester City).", "24'", "West Ham United", "0", "0", "0", "0", "0", "0", "NA", "NA", "NA", "NA", "NA", "NA", "NA", "1", "Aymeric Laporte", "Manchester City", "0", "NA", "0", "0", "NA", "NA", "NA", "0", "NA", "NA", "NA", "0", "NA", "NA", "0", "NA", "0", "NA", "NA", "NA", "0", "NA", "NA", "0", "0", "NA", "NA", "NA", "0", "NA", "NA", "NA", "NA", "1", "14", "0", "NA", "NA", "24"], ["480552", "Marko Arnautovic (West Ham United) wins a free kick on the right wing.", "24'", "West Ham United", "0", "0", "0", "0", "0", "0", "NA", "NA", "NA", "NA", "NA", "NA", "NA", "0", "NA", "NA", "0", "NA", "0", "0", "NA", "NA", "NA", "0", "NA", "NA", "NA", "0", "NA", "NA", "0", "NA", "1", "Marko Arnautovic", "West Ham United", "NA", "0", "NA", "NA", "0", "0", "NA", "NA", "NA", "0", "NA", "NA", "NA", "NA", "1", "15", "0", "NA", "NA", "24"], ["480552", "Attempt blocked. Raheem Sterling (Manchester City) left footed shot from outside the box is blocked.", "27'", "West Ham United", "0", "0", "0", "0", "1", "0", "blocked", "Raheem Sterling", "Manchester City", "left", "outside the box", "NA", "NA", "0", "NA", "NA", "0", "NA", "0", "0", "NA", "NA", "NA", "0", "NA", "NA", "NA", "0", "NA", "NA", "0", "NA", "0", "NA", "NA", "NA", "0", "NA", "NA", "0", "0", "NA", "NA", "NA", "0", "NA", "NA", "NA", "NA", "1", "16", "0", "NA", "NA", "27"], ["480552", "Own Goal by Pablo Zabaleta, West Ham United.  West Ham United 0, Manchester City 2.", "27'", "West Ham United", "0", "0", "0", "0", "0", "0", "own goal", "Pablo Zabaleta", "West Ham United", "NA", "NA", "NA", "NA", "0", "NA", "NA", "0", "NA", "0", "0", "NA", "NA", "NA", "0", "NA", "NA", "NA", "0", "NA", "NA", "0", "NA", "0", "NA", "NA", "NA", "0", "NA", "NA", "0", "0", "NA", "NA", "NA", "0", "NA", "NA", "NA", "NA", "1", "17", "0", "NA", "NA", "27"], ["480552", "Delay in match Cheikhou Kouyaté (West Ham United) because of an injury.", "29'", "West Ham United", "0", "0", "0", "0", "0", "0", "NA", "NA", "NA", "NA", "NA", "NA", "NA", "0", "NA", "NA", "0", "NA", "0", "0", "NA", "NA", "NA", "0", "NA", "NA", "NA", "0", "NA", "NA", "1", "West Ham United", "0", "NA", "NA", "NA", "0", "NA", "NA", "0", "0", "NA", "NA", "NA", "0", "NA", "NA", "NA", "NA", "1", "18", "0", "NA", "NA", "29"], ["480552", "Delay over. They are ready to continue.", "32'", "West Ham United", "0", "0", "0", "0", "0", "0", "NA", "NA", "NA", "NA", "NA", "NA", "NA", "0", "NA", "NA", "0", "NA", "0", "0", "NA", "NA", "NA", "0", "NA", "NA", "NA", "0", "NA", "NA", "0", "NA", "0", "NA", "NA", "NA", "0", "NA", "NA", "0", "0", "NA", "NA", "NA", "0", "NA", "NA", "NA", "NA", "1", "19", "0", "NA", "NA", "32"], ["480552", "Foul by Ilkay Gündogan (Manchester City).", "33'", "West Ham United", "0", "0", "0", "0", "0", "0", "NA", "NA", "NA", "NA", "NA", "NA", "NA", "1", "Ilkay Gündogan", "Manchester City", "0", "NA", "0", "0", "NA", "NA", "NA", "0", "NA", "NA", "NA", "0", "NA", "NA", "0", "NA", "0", "NA", "NA", "NA", "0", "NA", "NA", "0", "0", "NA", "NA", "NA", "0", "NA", "NA", "NA", "NA", "1", "20", "0", "NA", "NA", "33"], ["480552", "Mark Noble (West Ham United) wins a free kick in the attacking half.", "33'", "West Ham United", "0", "0", "0", "0", "0", "0", "NA", "NA", "NA", "NA", "NA", "NA", "NA", "0", "NA", "NA", "0", "NA", "0", "0", "NA", "NA", "NA", "0", "NA", "NA", "NA", "0", "NA", "NA", "0", "NA", "1", "Mark Noble", "West Ham United", "attacking half", "0", "NA", "NA", "0", "0", "NA", "NA", "NA", "0", "NA", "NA", "NA", "NA", "1", "21", "0", "NA", "NA", "33"], ["480552", "Corner,  Manchester City. Conceded by Adrián.", "35'", "West Ham United", "0", "0", "0", "0", "0", "0", "NA", "NA", "NA", "NA", "NA", "NA", "NA", "0", "NA", "NA", "0", "NA", "0", "0", "NA", "NA", "NA", "0", "NA", "NA", "NA", "0", "NA", "NA", "0", "NA", "0", "NA", "NA", "NA", "1", "Manchester City", "Adrián", "0", "0", "NA", "NA", "NA", "0", "NA", "NA", "NA", "NA", "1", "22", "0", "NA", "NA", "35"], ["480552", "Foul by Nicolás Otamendi (Manchester City).", "37'", "West Ham United", "0", "0", "0", "0", "0", "0", "NA", "NA", "NA", "NA", "NA", "NA", "NA", "1", "Nicolás Otamendi", "Manchester City", "0", "NA", "0", "0", "NA", "NA", "NA", "0", "NA", "NA", "NA", "0", "NA", "NA", "0", "NA", "0", "NA", "NA", "NA", "0", "NA", "NA", "0", "0", "NA", "NA", "NA", "0", "NA", "NA", "NA", "NA", "1", "23", "0", "NA", "NA", "37"], ["480552", "Manuel Lanzini (West Ham United) wins a free kick in the attacking half.", "37'", "West Ham United", "0", "0", "0", "0", "0", "0", "NA", "NA", "NA", "NA", "NA", "NA", "NA", "0", "NA", "NA", "0", "NA", "0", "0", "NA", "NA", "NA", "0", "NA", "NA", "NA", "0", "NA", "NA", "0", "NA", "1", "Manuel Lanzini", "West Ham United", "attacking half", "0", "NA", "NA", "0", "0", "NA", "NA", "NA", "0", "NA", "NA", "NA", "NA", "1", "24", "0", "NA", "NA", "37"], ["480552", "Nicolás Otamendi (Manchester City) is shown the yellow card for a bad foul.", "37'", "West Ham United", "0", "0", "0", "0", "0", "0", "NA", "NA", "NA", "NA", "NA", "NA", "NA", "0", "NA", "NA", "0", "NA", "0", "0", "NA", "NA", "NA", "1", "yellow", "Nicolás Otamendi", "Manchester City", "0", "NA", "NA", "0", "NA", "0", "NA", "NA", "NA", "0", "NA", "NA", "0", "0", "NA", "NA", "NA", "0", "NA", "NA", "NA", "NA", "1", "25", "0", "NA", "NA", "37"], ["480552", "Attempt missed. Declan Rice (West Ham United) left footed shot from the centre of the box is high and wide to the left following a set piece situation.", "38'", "West Ham United", "0", "0", "0", "0", "1", "0", "missed", "Declan Rice", "West Ham United", "left", "the centre of the box", "high and wide to the left", "NA", "0", "NA", "NA", "1", "NA", "0", "0", "NA", "NA", "NA", "0", "NA", "NA", "NA", "0", "NA", "NA", "0", "NA", "0", "NA", "NA", "NA", "0", "NA", "NA", "0", "0", "NA", "NA", "NA", "0", "NA", "NA", "NA", "NA", "1", "26", "0", "NA", "NA", "38"], ["480552", "Ederson (Manchester City) wins a free kick in the defensive half.", "39'", "West Ham United", "0", "0", "0", "0", "0", "0", "NA", "NA", "NA", "NA", "NA", "NA", "NA", "0", "NA", "NA", "0", "NA", "0", "0", "NA", "NA", "NA", "0", "NA", "NA", "NA", "0", "NA", "NA", "0", "NA", "1", "Ederson", "Manchester City", "defensive half", "0", "NA", "NA", "0", "0", "NA", "NA", "NA", "0", "NA", "NA", "NA", "NA", "1", "27", "0", "NA", "NA", "39"], ["480552", "Foul by Marko Arnautovic (West Ham United).", "39'", "West Ham United", "0", "0", "0", "0", "0", "0", "NA", "NA", "NA", "NA", "NA", "NA", "NA", "1", "Marko Arnautovic", "West Ham United", "0", "NA", "0", "0", "NA", "NA", "NA", "0", "NA", "NA", "NA", "0", "NA", "NA", "0", "NA", "0", "NA", "NA", "NA", "0", "NA", "NA", "0", "0", "NA", "NA", "NA", "0", "NA", "NA", "NA", "NA", "1", "28", "0", "NA", "NA", "39"], ["480552", "Attempt missed. Cheikhou Kouyaté (West Ham United) right footed shot from the centre of the box misses to the right. Assisted by Edimilson Fernandes with a cross.", "41'", "West Ham United", "0", "0", "0", "0", "1", "0", "missed", "Cheikhou Kouyaté", "West Ham United", "right", "the centre of the box", "right", "Edimilson Fernandes", "0", "NA", "NA", "0", "cross", "0", "0", "NA", "NA", "NA", "0", "NA", "NA", "NA", "0", "NA", "NA", "0", "NA", "0", "NA", "NA", "NA", "0", "NA", "NA", "0", "0", "NA", "NA", "NA", "0", "NA", "NA", "NA", "NA", "1", "29", "0", "NA", "NA", "41"], ["480552", "Edimilson Fernandes (West Ham United) wins a free kick in the attacking half.", "41'", "West Ham United", "0", "0", "0", "0", "0", "0", "NA", "NA", "NA", "NA", "NA", "NA", "NA", "0", "NA", "NA", "0", "NA", "0", "0", "NA", "NA", "NA", "0", "NA", "NA", "NA", "0", "NA", "NA", "0", "NA", "1", "Edimilson Fernandes", "West Ham United", "attacking half", "0", "NA", "NA", "0", "0", "NA", "NA", "NA", "0", "NA", "NA", "NA", "NA", "1", "30", "0", "NA", "NA", "41"], ["480552", "Foul by Ilkay Gündogan (Manchester City).", "41'", "West Ham United", "0", "0", "0", "0", "0", "0", "NA", "NA", "NA", "NA", "NA", "NA", "NA", "1", "Ilkay Gündogan", "Manchester City", "0", "NA", "0", "0", "NA", "NA", "NA", "0", "NA", "NA", "NA", "0", "NA", "NA", "0", "NA", "0", "NA", "NA", "NA", "0", "NA", "NA", "0", "0", "NA", "NA", "NA", "0", "NA", "NA", "NA", "NA", "1", "31", "0", "NA", "NA", "41"], ["480552", "Goal!  West Ham United 1, Manchester City 2. Aaron Cresswell (West Ham United) from a free kick with a left footed shot to the bottom right corner.", "42'", "West Ham United", "1", "0", "0", "0", "1", "0", "goal", "Aaron Cresswell", "West Ham United", "left", "NA", "bottom right corner", "NA", "0", "NA", "NA", "0", "NA", "0", "0", "NA", "NA", "NA", "0", "NA", "NA", "NA", "0", "NA", "NA", "0", "NA", "0", "NA", "NA", "NA", "0", "NA", "NA", "0", "0", "NA", "NA", "NA", "0", "NA", "NA", "NA", "NA", "1", "32", "0", "NA", "NA", "42"], ["480552", "Attempt saved. Kevin De Bruyne (Manchester City) left footed shot from outside the box is saved in the centre of the goal.", "43'", "West Ham United", "1", "0", "0", "0", "1", "0", "saved", "Kevin De Bruyne", "Manchester City", "left", "outside the box", "the centre of the goal", "NA", "0", "NA", "NA", "0", "NA", "0", "0", "NA", "NA", "NA", "0", "NA", "NA", "NA", "0", "NA", "NA", "0", "NA", "0", "NA", "NA", "NA", "0", "NA", "NA", "0", "0", "NA", "NA", "NA", "0", "NA", "NA", "NA", "NA", "1", "33", "0", "NA", "NA", "43"], ["480552", "Offside, West Ham United. Patrice Evra tries a through ball, but Cheikhou Kouyaté is caught offside.", "44'", "West Ham United", "1", "0", "0", "0", "0", "0", "NA", "NA", "NA", "NA", "NA", "NA", "NA", "0", "NA", "NA", "0", "NA", "0", "1", "West Ham United", "Cheikhou Kouyaté", "Patrice Evra", "0", "NA", "NA", "NA", "0", "NA", "NA", "0", "NA", "0", "NA", "NA", "NA", "0", "NA", "NA", "0", "0", "NA", "NA", "NA", "0", "NA", "NA", "NA", "NA", "1", "34", "0", "NA", "NA", "44"], ["480552", "Attempt missed. Kevin De Bruyne (Manchester City) right footed shot from outside the box is close, but misses to the right. Assisted by Leroy Sané.", "45'+1'", "West Ham United", "1", "0", "0", "0", "1", "0", "missed", "Kevin De Bruyne", "Manchester City", "right", "outside the box", "close, but right", "Leroy Sané", "0", "NA", "NA", "0", "NA", "0", "0", "NA", "NA", "NA", "0", "NA", "NA", "NA", "0", "NA", "NA", "0", "NA", "0", "NA", "NA", "NA", "0", "NA", "NA", "0", "0", "NA", "NA", "NA", "0", "NA", "NA", "NA", "NA", "1", "35", "1", "NA", "NA", "46"], ["480552", "Attempt saved. Raheem Sterling (Manchester City) right footed shot from the centre of the box is saved in the bottom right corner. Assisted by Leroy Sané.", "45'+2'", "West Ham United", "1", "0", "0", "0", "1", "0", "saved", "Raheem Sterling", "Manchester City", "right", "the centre of the box", "the bottom right corner", "Leroy Sané", "0", "NA", "NA", "0", "NA", "0", "0", "NA", "NA", "NA", "0", "NA", "NA", "NA", "0", "NA", "NA", "0", "NA", "0", "NA", "NA", "NA", "0", "NA", "NA", "0", "0", "NA", "NA", "NA", "0", "NA", "NA", "NA", "NA", "1", "36", "1", "NA", "NA", "47"], ["480552", "Offside, West Ham United. Angelo Ogbonna tries a through ball, but Aaron Cresswell is caught offside.", "45'+3'", "West Ham United", "1", "0", "0", "0", "0", "0", "NA", "NA", "NA", "NA", "NA", "NA", "NA", "0", "NA", "NA", "0", "NA", "0", "1", "West Ham United", "Aaron Cresswell", "Angelo Ogbonna", "0", "NA", "NA", "NA", "0", "NA", "NA", "0", "NA", "0", "NA", "NA", "NA", "0", "NA", "NA", "0", "0", "NA", "NA", "NA", "0", "NA", "NA", "NA", "NA", "1", "37", "1", "NA", "NA", "48"], ["480552", "Foul by Nicolás Otamendi (Manchester City).", "45'+4'", "West Ham United", "1", "0", "0", "0", "0", "0", "NA", "NA", "NA", "NA", "NA", "NA", "NA", "1", "Nicolás Otamendi", "Manchester City", "0", "NA", "0", "0", "NA", "NA", "NA", "0", "NA", "NA", "NA", "0", "NA", "NA", "0", "NA", "0", "NA", "NA", "NA", "0", "NA", "NA", "0", "0", "NA", "NA", "NA", "0", "NA", "NA", "NA", "NA", "1", "38", "1", "NA", "NA", "49"], ["480552", "Manuel Lanzini (West Ham United) wins a free kick in the attacking half.", "45'+4'", "West Ham United", "1", "0", "0", "0", "0", "0", "NA", "NA", "NA", "NA", "NA", "NA", "NA", "0", "NA", "NA", "0", "NA", "0", "0", "NA", "NA", "NA", "0", "NA", "NA", "NA", "0", "NA", "NA", "0", "NA", "1", "Manuel Lanzini", "West Ham United", "attacking half", "0", "NA", "NA", "0", "0", "NA", "NA", "NA", "0", "NA", "NA", "NA", "NA", "1", "39", "1", "NA", "NA", "49"], ["480552", "Attempt blocked. Marko Arnautovic (West Ham United) header from the centre of the box is blocked. Assisted by Mark Noble.", "45'+5'", "West Ham United", "1", "0", "0", "0", "1", "0", "blocked", "Marko Arnautovic", "West Ham United", "header", "the centre of the box", "NA", "Mark Noble", "0", "NA", "NA", "0", "NA", "0", "0", "NA", "NA", "NA", "0", "NA", "NA", "NA", "0", "NA", "NA", "0", "NA", "0", "NA", "NA", "NA", "0", "NA", "NA", "0", "0", "NA", "NA", "NA", "0", "NA", "NA", "NA", "NA", "1", "40", "1", "NA", "NA", "50"], ["480552", "First Half ends, West Ham United 1, Manchester City 2.", "45'+5'", "West Ham United", "1", "1", "0", "0", "0", "0", "NA", "NA", "NA", "NA", "NA", "NA", "NA", "0", "NA", "NA", "0", "NA", "0", "0", "NA", "NA", "NA", "0", "NA", "NA", "NA", "0", "NA", "NA", "0", "NA", "0", "NA", "NA", "NA", "0", "NA", "NA", "0", "0", "NA", "NA", "NA", "0", "NA", "NA", "NA", "NA", "1", "41", "1", "NA", "NA", "50"], ["480552", "Second Half begins West Ham United 1, Manchester City 2.", "45'", "West Ham United", "1", "0", "0", "1", "0", "0", "NA", "NA", "NA", "NA", "NA", "NA", "NA", "0", "NA", "NA", "0", "NA", "0", "0", "NA", "NA", "NA", "0", "NA", "NA", "NA", "0", "NA", "NA", "0", "NA", "0", "NA", "NA", "NA", "0", "NA", "NA", "0", "0", "NA", "NA", "NA", "0", "NA", "NA", "NA", "NA", "2", "42", "0", "NA", "NA", "45"], ["480552", "Foul by Raheem Sterling (Manchester City).", "48'", "West Ham United", "1", "0", "0", "0", "0", "0", "NA", "NA", "NA", "NA", "NA", "NA", "NA", "1", "Raheem Sterling", "Manchester City", "0", "NA", "0", "0", "NA", "NA", "NA", "0", "NA", "NA", "NA", "0", "NA", "NA", "0", "NA", "0", "NA", "NA", "NA", "0", "NA", "NA", "0", "0", "NA", "NA", "NA", "0", "NA", "NA", "NA", "NA", "2", "43", "0", "NA", "NA", "48"], ["480552", "Mark Noble (West Ham United) wins a free kick in the defensive half.", "48'", "West Ham United", "1", "0", "0", "0", "0", "0", "NA", "NA", "NA", "NA", "NA", "NA", "NA", "0", "NA", "NA", "0", "NA", "0", "0", "NA", "NA", "NA", "0", "NA", "NA", "NA", "0", "NA", "NA", "0", "NA", "1", "Mark Noble", "West Ham United", "defensive half", "0", "NA", "NA", "0", "0", "NA", "NA", "NA", "0", "NA", "NA", "NA", "NA", "2", "44", "0", "NA", "NA", "48"], ["480552", "Foul by Marko Arnautovic (West Ham United).", "49'", "West Ham United", "1", "0", "0", "0", "0", "0", "NA", "NA", "NA", "NA", "NA", "NA", "NA", "1", "Marko Arnautovic", "West Ham United", "0", "NA", "0", "0", "NA", "NA", "NA", "0", "NA", "NA", "NA", "0", "NA", "NA", "0", "NA", "0", "NA", "NA", "NA", "0", "NA", "NA", "0", "0", "NA", "NA", "NA", "0", "NA", "NA", "NA", "NA", "2", "45", "0", "NA", "NA", "49"], ["480552", "Nicolás Otamendi (Manchester City) wins a free kick in the defensive half.", "49'", "West Ham United", "1", "0", "0", "0", "0", "0", "NA", "NA", "NA", "NA", "NA", "NA", "NA", "0", "NA", "NA", "0", "NA", "0", "0", "NA", "NA", "NA", "0", "NA", "NA", "NA", "0", "NA", "NA", "0", "NA", "1", "Nicolás Otamendi", "Manchester City", "defensive half", "0", "NA", "NA", "0", "0", "NA", "NA", "NA", "0", "NA", "NA", "NA", "NA", "2", "46", "0", "NA", "NA", "49"], ["480552", "Offside, West Ham United. Aaron Cresswell tries a through ball, but Marko Arnautovic is caught offside.", "52'", "West Ham United", "1", "0", "0", "0", "0", "0", "NA", "NA", "NA", "NA", "NA", "NA", "NA", "0", "NA", "NA", "0", "NA", "0", "1", "West Ham United", "Marko Arnautovic", "Aaron Cresswell", "0", "NA", "NA", "NA", "0", "NA", "NA", "0", "NA", "0", "NA", "NA", "NA", "0", "NA", "NA", "0", "0", "NA", "NA", "NA", "0", "NA", "NA", "NA", "NA", "2", "47", "0", "NA", "NA", "52"], ["480552", "Goal!  West Ham United 1, Manchester City 3. Gabriel Jesus (Manchester City) right footed shot from very close range to the centre of the goal. Assisted by Raheem Sterling.", "53'", "West Ham United", "1", "0", "0", "0", "1", "0", "goal", "Gabriel Jesus", "Manchester City", "right", "right shot very close range", "centre of the goal", "Raheem Sterling", "0", "NA", "NA", "0", "NA", "0", "0", "NA", "NA", "NA", "0", "NA", "NA", "NA", "0", "NA", "NA", "0", "NA", "0", "NA", "NA", "NA", "0", "NA", "NA", "0", "0", "NA", "NA", "NA", "0", "NA", "NA", "NA", "NA", "2", "48", "0", "NA", "NA", "53"], ["480552", "Foul by Raheem Sterling (Manchester City).", "56'", "West Ham United", "1", "0", "0", "0", "0", "0", "NA", "NA", "NA", "NA", "NA", "NA", "NA", "1", "Raheem Sterling", "Manchester City", "0", "NA", "0", "0", "NA", "NA", "NA", "0", "NA", "NA", "NA", "0", "NA", "NA", "0", "NA", "0", "NA", "NA", "NA", "0", "NA", "NA", "0", "0", "NA", "NA", "NA", "0", "NA", "NA", "NA", "NA", "2", "49", "0", "NA", "NA", "56"], ["480552", "Mark Noble (West Ham United) wins a free kick in the defensive half.", "56'", "West Ham United", "1", "0", "0", "0", "0", "0", "NA", "NA", "NA", "NA", "NA", "NA", "NA", "0", "NA", "NA", "0", "NA", "0", "0", "NA", "NA", "NA", "0", "NA", "NA", "NA", "0", "NA", "NA", "0", "NA", "1", "Mark Noble", "West Ham United", "defensive half", "0", "NA", "NA", "0", "0", "NA", "NA", "NA", "0", "NA", "NA", "NA", "NA", "2", "50", "0", "NA", "NA", "56"], ["480552", "Hand ball by Raheem Sterling (Manchester City).", "57'", "West Ham United", "1", "0", "0", "0", "0", "0", "NA", "NA", "NA", "NA", "NA", "NA", "NA", "0", "NA", "NA", "0", "NA", "0", "0", "NA", "NA", "NA", "0", "NA", "NA", "NA", "0", "NA", "NA", "0", "NA", "0", "NA", "NA", "NA", "0", "NA", "NA", "0", "0", "NA", "NA", "NA", "0", "NA", "NA", "NA", "NA", "2", "51", "0", "NA", "NA", "57"], ["480552", "Attempt missed. Kevin De Bruyne (Manchester City) right footed shot from the centre of the box is close, but misses to the right. Assisted by Raheem Sterling.", "59'", "West Ham United", "1", "0", "0", "0", "1", "0", "missed", "Kevin De Bruyne", "Manchester City", "right", "the centre of the box", "close, but right", "Raheem Sterling", "0", "NA", "NA", "0", "NA", "0", "0", "NA", "NA", "NA", "0", "NA", "NA", "NA", "0", "NA", "NA", "0", "NA", "0", "NA", "NA", "NA", "0", "NA", "NA", "0", "0", "NA", "NA", "NA", "0", "NA", "NA", "NA", "NA", "2", "52", "0", "NA", "NA", "59"], ["480552", "Hand ball by Angelo Ogbonna (West Ham United).", "60'", "West Ham United", "1", "0", "0", "0", "0", "0", "NA", "NA", "NA", "NA", "NA", "NA", "NA", "0", "NA", "NA", "0", "NA", "0", "0", "NA", "NA", "NA", "0", "NA", "NA", "NA", "0", "NA", "NA", "0", "NA", "0", "NA", "NA", "NA", "0", "NA", "NA", "0", "0", "NA", "NA", "NA", "0", "NA", "NA", "NA", "NA", "2", "53", "0", "NA", "NA", "60"], ["480552", "Attempt missed. Ilkay Gündogan (Manchester City) right footed shot from outside the box is close, but misses to the left. Assisted by Gabriel Jesus.", "61'", "West Ham United", "1", "0", "0", "0", "1", "0", "missed", "Ilkay Gündogan", "Manchester City", "right", "outside the box", "close, but left", "Gabriel Jesus", "0", "NA", "NA", "0", "NA", "0", "0", "NA", "NA", "NA", "0", "NA", "NA", "NA", "0", "NA", "NA", "0", "NA", "0", "NA", "NA", "NA", "0", "NA", "NA", "0", "0", "NA", "NA", "NA", "0", "NA", "NA", "NA", "NA", "2", "54", "0", "NA", "NA", "61"], ["480552", "Substitution, Manchester City. Danilo replaces Kyle Walker.", "61'", "West Ham United", "1", "0", "0", "0", "0", "0", "NA", "NA", "NA", "NA", "NA", "NA", "NA", "0", "NA", "NA", "0", "NA", "0", "0", "NA", "NA", "NA", "0", "NA", "NA", "NA", "0", "NA", "NA", "0", "NA", "0", "NA", "NA", "NA", "0", "NA", "NA", "1", "0", "Manchester City", "Danilo", "Kyle Walker", "0", "NA", "NA", "NA", "NA", "2", "55", "0", "NA", "NA", "61"], ["480552", "Attempt saved. Raheem Sterling (Manchester City) right footed shot from the right side of the box is saved in the centre of the goal. Assisted by Gabriel Jesus with a through ball.", "62'", "West Ham United", "1", "0", "0", "0", "1", "0", "saved", "Raheem Sterling", "Manchester City", "right", "the right side of the box", "the centre of the goal", "Gabriel Jesus", "0", "NA", "NA", "0", "through", "0", "0", "NA", "NA", "NA", "0", "NA", "NA", "NA", "0", "NA", "NA", "0", "NA", "0", "NA", "NA", "NA", "0", "NA", "NA", "0", "0", "NA", "NA", "NA", "0", "NA", "NA", "NA", "NA", "2", "56", "0", "NA", "NA", "62"], ["480552", "Offside, Manchester City. Kevin De Bruyne tries a through ball, but Raheem Sterling is caught offside.", "64'", "West Ham United", "1", "0", "0", "0", "0", "0", "NA", "NA", "NA", "NA", "NA", "NA", "NA", "0", "NA", "NA", "0", "NA", "0", "1", "Manchester City", "Raheem Sterling", "Kevin De Bruyne", "0", "NA", "NA", "NA", "0", "NA", "NA", "0", "NA", "0", "NA", "NA", "NA", "0", "NA", "NA", "0", "0", "NA", "NA", "NA", "0", "NA", "NA", "NA", "NA", "2", "57", "0", "NA", "NA", "64"], ["480552", "Goal!  West Ham United 1, Manchester City 4. Fernandinho (Manchester City) right footed shot from the centre of the box to the centre of the goal. Assisted by Raheem Sterling.", "64'", "West Ham United", "1", "0", "0", "0", "1", "0", "goal", "Fernandinho", "Manchester City", "right", "the centre of the box", "centre of the goal", "Raheem Sterling", "0", "NA", "NA", "0", "NA", "0", "0", "NA", "NA", "NA", "0", "NA", "NA", "NA", "0", "NA", "NA", "0", "NA", "0", "NA", "NA", "NA", "0", "NA", "NA", "0", "0", "NA", "NA", "NA", "0", "NA", "NA", "NA", "NA", "2", "58", "0", "NA", "NA", "64"], ["480552", "Substitution, West Ham United. João Mário replaces Edimilson Fernandes.", "65'", "West Ham United", "1", "0", "0", "0", "0", "0", "NA", "NA", "NA", "NA", "NA", "NA", "NA", "0", "NA", "NA", "0", "NA", "0", "0", "NA", "NA", "NA", "0", "NA", "NA", "NA", "0", "NA", "NA", "0", "NA", "0", "NA", "NA", "NA", "0", "NA", "NA", "1", "0", "West Ham United", "João Mário", "Edimilson Fernandes", "0", "NA", "NA", "NA", "NA", "2", "59", "0", "NA", "NA", "65"], ["480552", "Substitution, West Ham United. Chicharito replaces Manuel Lanzini.", "66'", "West Ham United", "1", "0", "0", "0", "0", "0", "NA", "NA", "NA", "NA", "NA", "NA", "NA", "0", "NA", "NA", "0", "NA", "0", "0", "NA", "NA", "NA", "0", "NA", "NA", "NA", "0", "NA", "NA", "0", "NA", "0", "NA", "NA", "NA", "0", "NA", "NA", "1", "0", "West Ham United", "Chicharito", "Manuel Lanzini", "0", "NA", "NA", "NA", "NA", "2", "60", "0", "NA", "NA", "66"], ["480552", "Substitution, West Ham United. Arthur Masuaku replaces Patrice Evra.", "66'", "West Ham United", "1", "0", "0", "0", "0", "0", "NA", "NA", "NA", "NA", "NA", "NA", "NA", "0", "NA", "NA", "0", "NA", "0", "0", "NA", "NA", "NA", "0", "NA", "NA", "NA", "0", "NA", "NA", "0", "NA", "0", "NA", "NA", "NA", "0", "NA", "NA", "1", "0", "West Ham United", "Arthur Masuaku", "Patrice Evra", "0", "NA", "NA", "NA", "NA", "2", "61", "0", "NA", "NA", "66"], ["480552", "Substitution, Manchester City. Yaya Touré replaces Ilkay Gündogan.", "71'", "West Ham United", "1", "0", "0", "0", "0", "0", "NA", "NA", "NA", "NA", "NA", "NA", "NA", "0", "NA", "NA", "0", "NA", "0", "0", "NA", "NA", "NA", "0", "NA", "NA", "NA", "0", "NA", "NA", "0", "NA", "0", "NA", "NA", "NA", "0", "NA", "NA", "1", "0", "Manchester City", "Yaya Touré", "Ilkay Gündogan", "0", "NA", "NA", "NA", "NA", "2", "62", "0", "NA", "NA", "71"], ["480552", "Attempt blocked. Gabriel Jesus (Manchester City) right footed shot from very close range is blocked.", "77'", "West Ham United", "1", "0", "0", "0", "1", "0", "blocked", "Gabriel Jesus", "Manchester City", "right", "right shot very close range", "NA", "NA", "0", "NA", "NA", "0", "NA", "0", "0", "NA", "NA", "NA", "0", "NA", "NA", "NA", "0", "NA", "NA", "0", "NA", "0", "NA", "NA", "NA", "0", "NA", "NA", "0", "0", "NA", "NA", "NA", "0", "NA", "NA", "NA", "NA", "2", "63", "0", "NA", "NA", "77"], ["480552", "Attempt blocked. Raheem Sterling (Manchester City) left footed shot from the centre of the box is blocked. Assisted by Fabian Delph with a cross.", "77'", "West Ham United", "1", "0", "0", "0", "1", "0", "blocked", "Raheem Sterling", "Manchester City", "left", "the centre of the box", "NA", "Fabian Delph", "0", "NA", "NA", "0", "cross", "0", "0", "NA", "NA", "NA", "0", "NA", "NA", "NA", "0", "NA", "NA", "0", "NA", "0", "NA", "NA", "NA", "0", "NA", "NA", "0", "0", "NA", "NA", "NA", "0", "NA", "NA", "NA", "NA", "2", "64", "0", "NA", "NA", "77"], ["480552", "Attempt saved. Kevin De Bruyne (Manchester City) right footed shot from outside the box is saved in the centre of the goal. Assisted by Leroy Sané.", "77'", "West Ham United", "1", "0", "0", "0", "1", "0", "saved", "Kevin De Bruyne", "Manchester City", "right", "outside the box", "the centre of the goal", "Leroy Sané", "0", "NA", "NA", "0", "NA", "0", "0", "NA", "NA", "NA", "0", "NA", "NA", "NA", "0", "NA", "NA", "0", "NA", "0", "NA", "NA", "NA", "0", "NA", "NA", "0", "0", "NA", "NA", "NA", "0", "NA", "NA", "NA", "NA", "2", "65", "0", "NA", "NA", "77"], ["480552", "Corner,  Manchester City. Conceded by Pablo Zabaleta.", "79'", "West Ham United", "1", "0", "0", "0", "0", "0", "NA", "NA", "NA", "NA", "NA", "NA", "NA", "0", "NA", "NA", "0", "NA", "0", "0", "NA", "NA", "NA", "0", "NA", "NA", "NA", "0", "NA", "NA", "0", "NA", "0", "NA", "NA", "NA", "1", "Manchester City", "Pablo Zabaleta", "0", "0", "NA", "NA", "NA", "0", "NA", "NA", "NA", "NA", "2", "66", "0", "NA", "NA", "79"], ["480552", "Substitution, Manchester City. Lukas Nmecha replaces Gabriel Jesus.", "80'", "West Ham United", "1", "0", "0", "0", "0", "0", "NA", "NA", "NA", "NA", "NA", "NA", "NA", "0", "NA", "NA", "0", "NA", "0", "0", "NA", "NA", "NA", "0", "NA", "NA", "NA", "0", "NA", "NA", "0", "NA", "0", "NA", "NA", "NA", "0", "NA", "NA", "1", "0", "Manchester City", "Lukas Nmecha", "Gabriel Jesus", "0", "NA", "NA", "NA", "NA", "2", "67", "0", "NA", "NA", "80"], ["480552", "Attempt missed. Raheem Sterling (Manchester City) right footed shot from the centre of the box misses to the right. Assisted by Yaya Touré.", "82'", "West Ham United", "1", "0", "0", "0", "1", "0", "missed", "Raheem Sterling", "Manchester City", "right", "the centre of the box", "right", "Yaya Touré", "0", "NA", "NA", "0", "NA", "0", "0", "NA", "NA", "NA", "0", "NA", "NA", "NA", "0", "NA", "NA", "0", "NA", "0", "NA", "NA", "NA", "0", "NA", "NA", "0", "0", "NA", "NA", "NA", "0", "NA", "NA", "NA", "NA", "2", "68", "0", "NA", "NA", "82"], ["480552", "Corner,  Manchester City. Conceded by João Mário.", "85'", "West Ham United", "1", "0", "0", "0", "0", "0", "NA", "NA", "NA", "NA", "NA", "NA", "NA", "0", "NA", "NA", "0", "NA", "0", "0", "NA", "NA", "NA", "0", "NA", "NA", "NA", "0", "NA", "NA", "0", "NA", "0", "NA", "NA", "NA", "1", "Manchester City", "João Mário", "0", "0", "NA", "NA", "NA", "0", "NA", "NA", "NA", "NA", "2", "69", "0", "NA", "NA", "85"], ["480552", "Foul by Cheikhou Kouyaté (West Ham United).", "87'", "West Ham United", "1", "0", "0", "0", "0", "0", "NA", "NA", "NA", "NA", "NA", "NA", "NA", "1", "Cheikhou Kouyaté", "West Ham United", "0", "NA", "0", "0", "NA", "NA", "NA", "0", "NA", "NA", "NA", "0", "NA", "NA", "0", "NA", "0", "NA", "NA", "NA", "0", "NA", "NA", "0", "0", "NA", "NA", "NA", "0", "NA", "NA", "NA", "NA", "2", "70", "0", "NA", "NA", "87"], ["480552", "Leroy Sané (Manchester City) wins a free kick in the attacking half.", "87'", "West Ham United", "1", "0", "0", "0", "0", "0", "NA", "NA", "NA", "NA", "NA", "NA", "NA", "0", "NA", "NA", "0", "NA", "0", "0", "NA", "NA", "NA", "0", "NA", "NA", "NA", "0", "NA", "NA", "0", "NA", "1", "Leroy Sané", "Manchester City", "attacking half", "0", "NA", "NA", "0", "0", "NA", "NA", "NA", "0", "NA", "NA", "NA", "NA", "2", "71", "0", "NA", "NA", "87"], ["480552", "Attempt blocked. Yaya Touré (Manchester City) right footed shot from outside the box is blocked.", "88'", "West Ham United", "1", "0", "0", "0", "1", "0", "blocked", "Yaya Touré", "Manchester City", "right", "outside the box", "NA", "NA", "0", "NA", "NA", "0", "NA", "0", "0", "NA", "NA", "NA", "0", "NA", "NA", "NA", "0", "NA", "NA", "0", "NA", "0", "NA", "NA", "NA", "0", "NA", "NA", "0", "0", "NA", "NA", "NA", "0", "NA", "NA", "NA", "NA", "2", "72", "0", "NA", "NA", "88"], ["480552", "Corner,  Manchester City. Conceded by Cheikhou Kouyaté.", "88'", "West Ham United", "1", "0", "0", "0", "0", "0", "NA", "NA", "NA", "NA", "NA", "NA", "NA", "0", "NA", "NA", "0", "NA", "0", "0", "NA", "NA", "NA", "0", "NA", "NA", "NA", "0", "NA", "NA", "0", "NA", "0", "NA", "NA", "NA", "1", "Manchester City", "Cheikhou Kouyaté", "0", "0", "NA", "NA", "NA", "0", "NA", "NA", "NA", "NA", "2", "73", "0", "NA", "NA", "88"], ["480552", "Corner,  Manchester City. Conceded by Aaron Cresswell.", "90'", "West Ham United", "1", "0", "0", "0", "0", "0", "NA", "NA", "NA", "NA", "NA", "NA", "NA", "0", "NA", "NA", "0", "NA", "0", "0", "NA", "NA", "NA", "0", "NA", "NA", "NA", "0", "NA", "NA", "0", "NA", "0", "NA", "NA", "NA", "1", "Manchester City", "Aaron Cresswell", "0", "0", "NA", "NA", "NA", "0", "NA", "NA", "NA", "NA", "2", "74", "0", "NA", "NA", "90"], ["480552", "Angelo Ogbonna (West Ham United) wins a free kick in the defensive half.", "90'+1'", "West Ham United", "1", "0", "0", "0", "0", "0", "NA", "NA", "NA", "NA", "NA", "NA", "NA", "0", "NA", "NA", "0", "NA", "0", "0", "NA", "NA", "NA", "0", "NA", "NA", "NA", "0", "NA", "NA", "0", "NA", "1", "Angelo Ogbonna", "West Ham United", "defensive half", "0", "NA", "NA", "0", "0", "NA", "NA", "NA", "0", "NA", "NA", "NA", "NA", "2", "75", "1", "NA", "NA", "91"], ["480552", "Foul by Yaya Touré (Manchester City).", "90'+1'", "West Ham United", "1", "0", "0", "0", "0", "0", "NA", "NA", "NA", "NA", "NA", "NA", "NA", "1", "Yaya Touré", "Manchester City", "0", "NA", "0", "0", "NA", "NA", "NA", "0", "NA", "NA", "NA", "0", "NA", "NA", "0", "NA", "0", "NA", "NA", "NA", "0", "NA", "NA", "0", "0", "NA", "NA", "NA", "0", "NA", "NA", "NA", "NA", "2", "76", "1", "NA", "NA", "91"], ["480552", "Arthur Masuaku (West Ham United) wins a free kick on the left wing.", "90'+1'", "West Ham United", "1", "0", "0", "0", "0", "0", "NA", "NA", "NA", "NA", "NA", "NA", "NA", "0", "NA", "NA", "0", "NA", "0", "0", "NA", "NA", "NA", "0", "NA", "NA", "NA", "0", "NA", "NA", "0", "NA", "1", "Arthur Masuaku", "West Ham United", "NA", "0", "NA", "NA", "0", "0", "NA", "NA", "NA", "0", "NA", "NA", "NA", "NA", "2", "77", "1", "NA", "NA", "91"], ["480552", "Foul by Kevin De Bruyne (Manchester City).", "90'+1'", "West Ham United", "1", "0", "0", "0", "0", "0", "NA", "NA", "NA", "NA", "NA", "NA", "NA", "1", "Kevin De Bruyne", "Manchester City", "0", "NA", "0", "0", "NA", "NA", "NA", "0", "NA", "NA", "NA", "0", "NA", "NA", "0", "NA", "0", "NA", "NA", "NA", "0", "NA", "NA", "0", "0", "NA", "NA", "NA", "0", "NA", "NA", "NA", "NA", "2", "78", "1", "NA", "NA", "91"], ["480552", "Corner,  Manchester City. Conceded by Pablo Zabaleta.", "90'+2'", "West Ham United", "1", "0", "0", "0", "0", "0", "NA", "NA", "NA", "NA", "NA", "NA", "NA", "0", "NA", "NA", "0", "NA", "0", "0", "NA", "NA", "NA", "0", "NA", "NA", "NA", "0", "NA", "NA", "0", "NA", "0", "NA", "NA", "NA", "1", "Manchester City", "Pablo Zabaleta", "0", "0", "NA", "NA", "NA", "0", "NA", "NA", "NA", "NA", "2", "79", "1", "NA", "NA", "92"], ["480552", "Second Half ends, West Ham United 1, Manchester City 4.", "90'+4'", "West Ham United", "1", "1", "0", "0", "0", "0", "NA", "NA", "NA", "NA", "NA", "NA", "NA", "0", "NA", "NA", "0", "NA", "0", "0", "NA", "NA", "NA", "0", "NA", "NA", "NA", "0", "NA", "NA", "0", "NA", "0", "NA", "NA", "NA", "0", "NA", "NA", "0", "0", "NA", "NA", "NA", "0", "NA", "NA", "NA", "NA", "2", "80", "1", "NA", "NA", "94"], ["480552", "Match ends, West Ham United 1, Manchester City 4.", "90'+4'", "West Ham United", "1", "0", "1", "0", "0", "0", "NA", "NA", "NA", "NA", "NA", "NA", "NA", "0", "NA", "NA", "0", "NA", "0", "0", "NA", "NA", "NA", "0", "NA", "NA", "NA", "0", "NA", "NA", "0", "NA", "0", "NA", "NA", "NA", "0", "NA", "NA", "0", "0", "NA", "NA", "NA", "0", "NA", "NA", "NA", "NA", "2", "81", "1", "NA", "NA", "94"]], "Lineup": {"Home Player 9": "Angelo Ogbonna", "Home Player 8": "Mark Noble", "Home Player 5": "Edimilson Fernandes", "Home Player 4": "Patrice Evra", "Home Player 7": "Manuel Lanzini", "Home Player 6": "Cheikhou Kouyate", "Home Player 1": "Adrian", "Home Player 3": "Aaron Cresswell", "Home Player 2": "Marko Arnautovic", "Away Player 10": "Raheem Sterling", "Away Player 11": "Kyle Walker", "Away Player 8": "Nicolas Otamendi", "Away Player 9": "Leroy Sane", "Away Player 1": "Kevin De Bruyne", "Away Player 2": "Fabian Delph", "Away Player 3": "Ederson", "Away Player 4": "Fernandinho", "Away Player 5": "Jesus Gabriel", "Away Player 6": "Ilkay Gundogan", "Away Player 7": "Aymeric Laporte", "Game ID": "g_1_IBZf2hYI", "Home Player 11": "Pablo Zabaleta", "Home Player 10": "Declan Rice"}}